Workbook

Sheet Assumptions
A1: MyAdvocate Financial Model v17 — Assumptions
A2: Source: PMP v22 | v17.0 — March 2026 | SIMPLIFIED: Decay-curve SEO, YT as traffic funnel, IG as traffic boost
A3: Blue = input (user-editable) | Black = calculated | Green = cross-sheet link
A5: CORE BUSINESS ASSUMPTIONS
A6: Launch Month | B6: 1 | C6: Month 1 = Launch
A7: Planning Horizon (months) | B7: 36 | C7: 3-year projection
A9: PRICING STRUCTURE
A10: Founding Advocate Annual Price | B10: 34 | C10: $34/year — first 250 subs, locked forever
A11: Founding Advocate Monthly Equivalent | B11: =B10/12 -> 2.8333333 | C11: $34/12 — MRR calculation
A12: FA Renewal Price (Year 2+) | B12: 55 | C12: $55/yr — permanent FA rate
A13: FA Cohort Cap | B13: 250 | C13: Maximum Founding Advocates
A14: Basic Tier Monthly | B14: 8 | C14: Launch tier — all new subs M1–M8
A15: Standard Tier Monthly (M9+) | B15: 13 | C15: Price increase M9 — new subs only
A16: Advocate Builder Quarterly | B16: 21 | C16: $21/quarter
A17: Advocate Builder Monthly Equiv | B17: =B16/3 -> 7 | C17: $21/3 — MRR purposes
A18: Annual Standard Price | B18: 55 | C18: $55/yr committed annual
A19: Premium Monthly (Phase 4+) | B19: 21 | C19: Native app tier — Phase 4 unlock
A21: CONVERSION RATES — HEALTHCARE COLD TRAFFIC
A22: Conservative Paid Conversion | B22: 0.0015 | C22: 0.15% — cold traffic baseline. Validated: industry 0.5-1.5% for warm; cold = lower
A23: Expected Paid Conversion | B23: 0.0025 | C23: 0.25% — moderate, denial-code SEO boost
A24: Optimistic Paid Conversion | B24: 0.005 | C24: 0.50% — high-intent denial code + optimized funnel
A25: Free Signup / Email Capture Rate | B25: 0.02 | C25: 2.0% of total visitors — email list growth (tracked elsewhere)
A26: Denial Decoder Free-to-Paid Lift | B26: 1.15 | C26: 15% higher conversion from denial code visitors
A27: FA Conversion Rate (of early subs) | B27: 0.4 | C27: ~40% of first subs take FA offer
A29: SEO TRAFFIC — DECAY CURVE MODEL
A30: Month 1 Traffic — Conservative | B30: 250 | C30: New domain, minimal indexed content
A31: Month 1 Traffic — Expected | B31: 500 | C31: Early SEO content live at launch
A32: Month 1 Traffic — Optimistic | B32: 750 | C32: Pre-launch content build + denial codes starting
A34: YEAR 1 (M1-M12) MoM Growth — Conservative | B34: 0.1 | C34: 10% — slow organic compounding, denial codes indexing
A35: YEAR 1 (M1-M12) MoM Growth — Expected | B35: 0.14 | C35: 14% — consistent 2x/week + denial codes
A36: YEAR 1 (M1-M12) MoM Growth — Optimistic | B36: 0.18 | C36: 18% — aggressive SEO + denial codes indexing fast
A38: YEAR 2 (M13-M24) MoM Growth — Conservative | B38: 0.06 | C38: 6% — competition ceilings hit
A39: YEAR 2 (M13-M24) MoM Growth — Expected | B39: 0.09 | C39: 9% — clusters maturing, backlinks growing
A40: YEAR 2 (M13-M24) MoM Growth — Optimistic | B40: 0.12 | C40: 12% — strong domain authority building
A42: YEAR 3 (M25-M36) MoM Growth — Conservative | B42: 0.04 | C42: 4% — mature, near ceiling for solo ops
A43: YEAR 3 (M25-M36) MoM Growth — Expected | B43: 0.06 | C43: 6% — sustained with refresh + new clusters
A44: YEAR 3 (M25-M36) MoM Growth — Optimistic | B44: 0.08 | C44: 8% — strong brand + expanding content
... A47: Content Cluster Maturity Boost (M6+) | B47: 1.08 | C47: 8% lift as pillar/cluster architecture matures
A49: CHURN & RETENTION
A50: Monthly Churn — Conservative | B50: 0.08 | C50: 8% — challenging healthcare retention
A51: Monthly Churn — Expected | B51: 0.07 | C51: 7% — decent product-market fit. Benchmark: consumer SaaS 6.5-8%
A52: Monthly Churn — Optimistic | B52: 0.06 | C52: 6% — strong engagement. Benchmark: good subscription = 4-6%
A53: FA Churn Rate | B53: 0.02 | C53: 2% — locked pricing creates loyalty
A55: ATTORNEY REFERRAL ECONOMICS
A56: Referral Program Start Month | B56: 6 | C56: Month 6 — Signal 1 gate
A57: Referral Conversion Rate (of visitors) | B57: 0.001 | C57: 0.1% of monthly visitors → referred
A58: Blended Revenue per Referral ($) | B58: 350 | C58: $350 blended — $300-$400 range
A60: COSTS — API & INFRASTRUCTURE
A61: Cost per Letter Generation | B61: 0.08 | C61: claude-haiku default
A62: Letters per Paid Sub per Month | B62: 3.5 | C62: Average usage
A63: Base Infrastructure Monthly | B63: 31 | C63: Vercel + Supabase + domain
A64: Infra Scale Threshold (subs) | B64: 500 | C64: Upgrade at ~500 subs (+$45/mo)
A65: Ahrefs Lite Monthly | B65: 29 | C65: SEO tool stack
A66: Buffer Monthly | B66: 6 | C66: Social scheduling
A67: n8n Pro Monthly | B67: 20 | C67: Board of Agents
A68: Claude Code Monthly | B68: 20 | C68: Dev tool — founder only
A69: Google Workspace Annual | B69: 120 | C69: $10/mo equiv
A70: Stripe Transaction Fee % | B70: 0.029 | C70: 2.9% per transaction
A71: Stripe Fixed Fee | B71: 0.3 | C71: $0.30 per transaction
A72: YT Tool Cost Monthly (M3+) | B72: 66 | C72: HeyGen $24 + ElevenLabs $22 + Claude API $15 + Whisper $5
A74: ONE-TIME LAUNCH COSTS (Month 1 only)
A75: Healthcare Compliance Attorney | B75: 2250 | C75: $1,500-$3,000 range midpoint
A76: Security Audit | B76: 500 | C76: External audit — launch blocker
A77: LLC Formation | B77: 500 | C77: Already done
A79: TRAFFIC MILESTONE GATES (tracked, not modeled)
A80: Signal 1 | B80: 10000 | C80: 10K monthly visitors
A81: Signal 2 | B81: 25000 | C81: 25K monthly visitors
A82: Signal 3 | B82: 40000 | C82: 40K
A83: Signal 4 | B83: 65000 | C83: 65K
A84: Signal 5 | B84: 110000 | C84: 110K
A85: Signal 6 | B85: 175000 | C85: 175K
A87: OWNER'S DRAW — SIMPLIFIED
A88: Phase 1 Withdrawal Rate | B88: 0 | C88: 0% — all profit builds reserve
A89: Reserve Floor (months of opex) | B89: 3 | C89: 3-month reserve before any draw
A90: Safe Withdrawal Rate | B90: 0.3 | C90: 30% of monthly profit after reserve floor met
A91: Max Withdrawal Rate (6+ months reserve) | B91: 0.5 | C91: 50% of monthly profit — strong reserve
A93: PER-CASE REVENUE ASSUMPTIONS
A94: Per-Case Letter Price ($) | B94: 13 | C94: $13 one-time — Standard tier price
A95: Letter Tool Engagement Rate | B95: 0.08 | C95: 8% of visitors use free tool
A96: Free-to-Second-Letter Rate | B96: 0.15 | C96: 15% need 2nd letter same month
A97: Per-Case Purchase Rate | B97: 0.25 | C97: 25% choose $13 vs subscribe or leave
A99: YOUTUBE — TRAFFIC FUNNEL MODEL (MA-YT-001)
A100: YT Content Start Month (EN) | B100: 3 | C100: Phase 1: 2-3 Shorts/week + 1 long-form/month
A101: YT ES Channel Start Month | B101: 9 | C101: Spanish channel duplicates EN content
A103: EN Monthly Views M3-M8 | B103: 500 | C103: Early — building library, minimal discovery
A104: EN Monthly Views M9-M12 | B104: 2000 | C104: Growing — consistency paying off
A105: EN Monthly Views M13-M18 | B105: 5000 | C105: Compounding — Shorts algorithm kicking in
A106: EN Monthly Views M19-M24 | B106: 10000 | C106: Established — regular audience
A107: EN Monthly Views M25-M36 | B107: 18000 | C107: Mature solo operation
A109: ES Views as % of EN | B109: 0.5 | C109: 50% of EN views (starts M9)
A111: YT Viewer-to-Site CTR | B111: 0.02 | C111: 2% of viewers visit site — CTA in every video
A113: EN YPP Month (AdSense starts) | B113: 12 | C113: 1K subs + 4K watch hours
A114: ES YPP Month | B114: 16 | C114: ES ~4mo after EN
A115: EN AdSense CPM ($) | B115: 8 | C115: CONSERVATIVE: low-end healthcare $8-$15
A116: ES AdSense CPM ($) | B116: 3 | C116: CONSERVATIVE: Spanish healthcare
A118: INSTAGRAM — TRAFFIC BOOST MODEL (MA-IG-001)
A119: IG Starting Followers | B119: 50 | C119: Organic seed at launch
A120: IG Follower Growth M1-M6 | B120: 0.2 | C120: 20% MoM — small account, Reels strategy
A121: IG Follower Growth M7-M12 | B121: 0.15 | C121: 15% — moderate deceleration
A122: IG Follower Growth M13-M36 | B122: 0.1 | C122: 10% — mature growth
...

Sheet Dashboard
A1: MyAdvocate Projections v17 — Executive Dashboard
A2: Simplified: Decay-curve SEO | YT traffic funnel | IG traffic boost | Owner's Draw
B4: Conservative | C4: Expected | D4: Optimistic
A5: Total Monthly Visitors (M36) | B5: =Conservative!E39 -> 3445 | C5: =Expected!E39 -> 15433 | D5: =Optimistic!E39 -> 57029
A6: → Organic SEO | B6: =Conservative!B39 -> 2854 | C6: =Expected!B39 -> 14842 | D6: =Optimistic!B39 -> 56438
A7: → YouTube | B7: =Conservative!C39 -> 540 | C7: =Expected!C39 -> 540 | D7: =Optimistic!C39 -> 540
A8: → Instagram | B8: =Conservative!D39 -> 51 | C8: =Expected!D39 -> 51 | D8: =Optimistic!D39 -> 51
A9: Paid Subscribers (M36) | B9: =Conservative!H39 -> 44 | C9: =Expected!H39 -> 304 | D9: =Optimistic!H39 -> 2116
A10: MRR (M36) | B10: =Conservative!I39 -> 505 | C10: =Expected!I39 -> 3488 | D10: =Optimistic!I39 -> 24281
A11: Total Revenue (M36) | B11: =Conservative!M39 -> 1939 | C11: =Expected!M39 -> 9586 | D11: =Optimistic!M39 -> 46559
A12: Gross Profit (M36) | B12: =Conservative!O39 -> 1717 | C12: =Expected!O39 -> 9127 | D12: =Optimistic!O39 -> 44401
A13: Owner's Draw (M36) | B13: =Conservative!P39 -> 859 | C13: =Expected!P39 -> 4564 | D13: =Optimistic!P39 -> 22201
A14: Reserve Balance (M36) | B14: =Conservative!Q39 -> 11033 | C14: =Expected!Q39 -> 56802 | D14: =Optimistic!Q39 -> 236042
A16: 3-YEAR TOTALS
A17: 3-Yr Subscription Revenue | B17: =Conservative!I40 -> 7149 | C17: =Expected!I40 -> 41836 | D17: =Optimistic!I40 -> 246709
A18: 3-Yr Per-Case Revenue | B18: =Conservative!J40 -> 2345 | C18: =Expected!J40 -> 8425 | D18: =Optimistic!J40 -> 25610
A19: 3-Yr Referral Revenue | B19: =Conservative!K40 -> 20449 | C19: =Expected!K40 -> 74296 | D19: =Optimistic!K40 -> 227747
A20: 3-Yr YT AdSense | B20: =Conservative!L40 -> 1858 | C20: =Expected!L40 -> 1858 | D20: =Optimistic!L40 -> 1858
A21: 3-Yr Total Revenue | B21: =Conservative!M40 -> 31801 | C21: =Expected!M40 -> 126415 | D21: =Optimistic!M40 -> 501924
A22: 3-Yr Total Costs | B22: =Conservative!N40 -> 10243 | C22: =Expected!N40 -> 13007 | D22: =Optimistic!N40 -> 30011
A23: 3-Yr Gross Profit | B23: =Conservative!O40 -> 21558 | C23: =Expected!O40 -> 113408 | D23: =Optimistic!O40 -> 471913
A24: 3-Yr Owner's Draw | B24: =Conservative!P40 -> 10525 | C24: =Expected!P40 -> 56606 | D24: =Optimistic!P40 -> 235871
A26: KEY ASSUMPTIONS
A27: Paid Conversion Rate | B27: =Assumptions!B22 -> 0.0015 | C27: =Assumptions!B23 -> 0.0025 | D27: =Assumptions!B24 -> 0.005
A28: Y1 Traffic Growth | B28: =Assumptions!B34 -> 0.1 | C28: =Assumptions!B35 -> 0.14 | D28: =Assumptions!B36 -> 0.18
A29: Monthly Churn | B29: =Assumptions!B50 -> 0.08 | C29: =Assumptions!B51 -> 0.07 | D29: =Assumptions!B52 -> 0.06

Sheet Conservative
A1: CONSERVATIVE SCENARIO
A3: Month | B3: Organic SEO | C3: YT Visitors | D3: IG Visitors | E3: TOTAL Visitors | F3: New Paid Subs | G3: Churn | H3: Total Paid Subs | I3: MRR ($) | J3: Per-Case Rev ($) | K3: Referral Rev ($) | L3: YT AdSense ($) | M3: Total Revenue ($) | N3: Total Costs ($) | O3: Gross Profit ($) | P3: Owner's Draw ($) | Q3: Reserve ($)
A4: 1 | B4: =Assumptions!B30 -> 250 | C4: =ROUND(IF(A4<Assumptions!B100,0,IF(A4<=8,Assumptions!B103,IF(A4<=12,Assumptions!B104,IF(A4<=18,Assumptions!B105,IF(A4<=24,Assumptions!B106,Assumptions!B107))))*(1+IF(A4>=Assumptions!B101,Assumptions!B109,0))*Assumptions!B111),0) -> 0 | D4: =ROUND(Assumptions!B119*Assumptions!B123,0) -> 1 | E4: =B4+C4+D4 -> 251 | F4: =ROUND(E4*Assumptions!B22,0) -> 0 | G4: 0 | H4: =F4 -> 0 | I4: =ROUND(H4*Assumptions!B14,0) -> 0 | J4: =ROUND(E4*Assumptions!B95*Assumptions!B96*Assumptions!B97*Assumptions!B94,0) -> 10 | K4: 0 | L4: =ROUND(IF(A4<Assumptions!B113,0,IF(A4<=18,Assumptions!B105,Assumptions!B107)/1000*Assumptions!B115*0.55+IF(A4>=Assumptions!B114,IF(A4<=18,Assumptions!B105,Assumptions!B107)*Assumptions!B109/1000*Assumptions!B116*0.55,0)),0) -> 0 | M4: =I4+J4+K4+L4 -> 10 | N4: =ROUND(H4*Assumptions!B62*Assumptions!B61,0)+Assumptions!B63+IF(H4>Assumptions!B64,45,0)+Assumptions!B65+Assumptions!B66+Assumptions!B67+Assumptions!B68+Assumptions!B69/12+IF(A4>=3,Assumptions!B72,0)+ROUND(I4*Assumptions!B70+H4*Assumptions!B71,0)+Assumptions!B75+Assumptions!B76+Assumptions!B77 -> 3366 | O4: =M4-N4 -> -3356 | P4: =IF(O4<N4*Assumptions!B89,0,IF(O4<N4*6,ROUND(MAX(O4,0)*Assumptions!B90,0),ROUND(MAX(O4,0)*Assumptions!B91,0))) -> 0 | Q4: =O4-P4 -> -3356
A5: 2 | B5: =ROUND(B4*(1+Assumptions!B34),0) -> 275 | C5: =ROUND(IF(A5<Assumptions!B100,0,IF(A5<=8,Assumptions!B103,IF(A5<=12,Assumptions!B104,IF(A5<=18,Assumptions!B105,IF(A5<=24,Assumptions!B106,Assumptions!B107))))*(1+IF(A5>=Assumptions!B101,Assumptions!B109,0))*Assumptions!B111),0) -> 0 | D5: =ROUND(ROUND(Assumptions!B119*(1+Assumptions!B120)^(A5-1),0)*Assumptions!B123,0) -> 1 | E5: =B5+C5+D5 -> 276 | F5: =ROUND(E5*Assumptions!B22,0) -> 0 | G5: =ROUND(H4*Assumptions!B50,0) -> 0 | H5: =H4+F5-G5 -> 0 | I5: =ROUND(H5*Assumptions!B14,0) -> 0 | J5: =ROUND(E5*Assumptions!B95*Assumptions!B96*Assumptions!B97*Assumptions!B94,0) -> 11 | K5: 0 | L5: =ROUND(IF(A5<Assumptions!B113,0,IF(A5<=18,Assumptions!B105,Assumptions!B107)/1000*Assumptions!B115*0.55+IF(A5>=Assumptions!B114,IF(A5<=18,Assumptions!B105,Assumptions!B107)*Assumptions!B109/1000*Assumptions!B116*0.55,0)),0) -> 0 | M5: =I5+J5+K5+L5 -> 11 | N5: =ROUND(H5*Assumptions!B62*Assumptions!B61,0)+Assumptions!B63+IF(H5>Assumptions!B64,45,0)+Assumptions!B65+Assumptions!B66+Assumptions!B67+Assumptions!B68+Assumptions!B69/12+IF(A5>=3,Assumptions!B72,0)+ROUND(I5*Assumptions!B70+H5*Assumptions!B71,0)+0 -> 116 | O5: =M5-N5 -> -105 | P5: =IF((Q4+O5)<N5*Assumptions!B89,0,IF((Q4+O5)<N5*6,ROUND(MAX(O5,0)*Assumptions!B90,0),ROUND(MAX(O5,0)*Assumptions!B91,0))) -> 0 | Q5: =Q4+O5-P5 -> -3461
A6: 3 | B6: =ROUND(B5*(1+Assumptions!B34)*Assumptions!B46,0) -> 348 | C6: =ROUND(IF(A6<Assumptions!B100,0,IF(A6<=8,Assumptions!B103,IF(A6<=12,Assumptions!B104,IF(A6<=18,Assumptions!B105,IF(A6<=24,Assumptions!B106,Assumptions!B107))))*(1+IF(A6>=Assumptions!B101,Assumptions!B109,0))*Assumptions!B111),0) -> 10 | D6: =ROUND(ROUND(Assumptions!B119*(1+Assumptions!B120)^(A6-1),0)*Assumptions!B123,0) -> 1 | E6: =B6+C6+D6 -> 359 | F6: =ROUND(E6*Assumptions!B22,0) -> 1 | G6: =ROUND(H5*Assumptions!B50,0) -> 0 | H6: =H5+F6-G6 -> 1 | I6: =ROUND(H6*Assumptions!B14,0) -> 8 | J6: =ROUND(E6*Assumptions!B95*Assumptions!B96*Assumptions!B97*Assumptions!B94,0) -> 14 | K6: 0 | L6: =ROUND(IF(A6<Assumptions!B113,0,IF(A6<=18,Assumptions!B105,Assumptions!B107)/1000*Assumptions!B115*0.55+IF(A6>=Assumptions!B114,IF(A6<=18,Assumptions!B105,Assumptions!B107)*Assumptions!B109/1000*Assumptions!B116*0.55,0)),0) -> 0 | M6: =I6+J6+K6+L6 -> 22 | N6: =ROUND(H6*Assumptions!B62*Assumptions!B61,0)+Assumptions!B63+IF(H6>Assumptions!B64,45,0)+Assumptions!B65+Assumptions!B66+Assumptions!B67+Assumptions!B68+Assumptions!B69/12+IF(A6>=3,Assumptions!B72,0)+ROUND(I6*Assumptions!B70+H6*Assumptions!B71,0)+0 -> 183 | O6: =M6-N6 -> -161 | P6: =IF((Q5+O6)<N6*Assumptions!B89,0,IF((Q5+O6)<N6*6,ROUND(MAX(O6,0)*Assumptions!B90,0),ROUND(MAX(O6,0)*Assumptions!B91,0))) -> 0 | Q6: =Q5+O6-P6 -> -3622
A7: 4 | B7: =ROUND(B6*(1+Assumptions!B34),0) -> 383 | C7: =ROUND(IF(A7<Assumptions!B100,0,IF(A7<=8,Assumptions!B103,IF(A7<=12,Assumptions!B104,IF(A7<=18,Assumptions!B105,IF(A7<=24,Assumptions!B106,Assumptions!B107))))*(1+IF(A7>=Assumptions!B101,Assumptions!B109,0))*Assumptions!B111),0) -> 10 | D7: =ROUND(ROUND(Assumptions!B119*(1+Assumptions!B120)^(A7-1),0)*Assumptions!B123,0) -> 1 | E7: =B7+C7+D7 -> 394 | F7: =ROUND(E7*Assumptions!B22,0) -> 1 | G7: =ROUND(H6*Assumptions!B50,0) -> 0 | H7: =H6+F7-G7 -> 2 | I7: =ROUND(H7*Assumptions!B14,0) -> 16 | J7: =ROUND(E7*Assumptions!B95*Assumptions!B96*Assumptions!B97*Assumptions!B94,0) -> 15 | K7: 0 | L7: =ROUND(IF(A7<Assumptions!B113,0,IF(A7<=18,Assumptions!B105,Assumptions!B107)/1000*Assumptions!B115*0.55+IF(A7>=Assumptions!B114,IF(A7<=18,Assumptions!B105,Assumptions!B107)*Assumptions!B109/1000*Assumptions!B116*0.55,0)),0) -> 0 | M7: =I7+J7+K7+L7 -> 31 | N7: =ROUND(H7*Assumptions!B62*Assumptions!B61,0)+Assumptions!B63+IF(H7>Assumptions!B64,45,0)+Assumptions!B65+Assumptions!B66+Assumptions!B67+Assumptions!B68+Assumptions!B69/12+IF(A7>=3,Assumptions!B72,0)+ROUND(I7*Assumptions!B70+H7*Assumptions!B71,0)+0 -> 184 | O7: =M7-N7 -> -153 | P7: =IF((Q6+O7)<N7*Assumptions!B89,0,IF((Q6+O7)<N7*6,ROUND(MAX(O7,0)*Assumptions!B90,0),ROUND(MAX(O7,0)*Assumptions!B91,0))) -> 0 | Q7: =Q6+O7-P7 -> -3775
A8: 5 | B8: =ROUND(B7*(1+Assumptions!B34),0) -> 421 | C8: =ROUND(IF(A8<Assumptions!B100,0,IF(A8<=8,Assumptions!B103,IF(A8<=12,Assumptions!B104,IF(A8<=18,Assumptions!B105,IF(A8<=24,Assumptions!B106,Assumptions!B107))))*(1+IF(A8>=Assumptions!B101,Assumptions!B109,0))*Assumptions!B111),0) -> 10 | D8: =ROUND(ROUND(Assumptions!B119*(1+Assumptions!B120)^(A8-1),0)*Assumptions!B123,0) -> 2 | E8: =B8+C8+D8 -> 433 | F8: =ROUND(E8*Assumptions!B22,0) -> 1 | G8: =ROUND(H7*Assumptions!B50,0) -> 0 | H8: =H7+F8-G8 -> 3 | I8: =ROUND(H8*Assumptions!B14,0) -> 24 | J8: =ROUND(E8*Assumptions!B95*Assumptions!B96*Assumptions!B97*Assumptions!B94,0) -> 17 | K8: 0 | L8: =ROUND(IF(A8<Assumptions!B113,0,IF(A8<=18,Assumptions!B105,Assumptions!B107)/1000*Assumptions!B115*0.55+IF(A8>=Assumptions!B114,IF(A8<=18,Assumptions!B105,Assumptions!B107)*Assumptions!B109/1000*Assumptions!B116*0.55,0)),0) -> 0 | M8: =I8+J8+K8+L8 -> 41 | N8: =ROUND(H8*Assumptions!B62*Assumptions!B61,0)+Assumptions!B63+IF(H8>Assumptions!B64,45,0)+Assumptions!B65+Assumptions!B66+Assumptions!B67+Assumptions!B68+Assumptions!B69/12+IF(A8>=3,Assumptions!B72,0)+ROUND(I8*Assumptions!B70+H8*Assumptions!B71,0)+0 -> 185 | O8: =M8-N8 -> -144 | P8: =IF((Q7+O8)<N8*Assumptions!B89,0,IF((Q7+O8)<N8*6,ROUND(MAX(O8,0)*Assumptions!B90,0),ROUND(MAX(O8,0)*Assumptions!B91,0))) -> 0 | Q8: =Q7+O8-P8 -> -3919
A9: 6 | B9: =ROUND(B8*(1+Assumptions!B34)*Assumptions!B47,0) -> 500 | C9: =ROUND(IF(A9<Assumptions!B100,0,IF(A9<=8,Assumptions!B103,IF(A9<=12,Assumptions!B104,IF(A9<=18,Assumptions!B105,IF(A9<=24,Assumptions!B106,Assumptions!B107))))*(1+IF(A9>=Assumptions!B101,Assumptions!B109,0))*Assumptions!B111),0) -> 10 | D9: =ROUND(ROUND(Assumptions!B119*(1+Assumptions!B120)^(A9-1),0)*Assumptions!B123,0) -> 2 | E9: =B9+C9+D9 -> 512 | F9: =ROUND(E9*Assumptions!B22,0) -> 1 | G9: =ROUND(H8*Assumptions!B50,0) -> 0 | H9: =H8+F9-G9 -> 4 | I9: =ROUND(H9*Assumptions!B14,0) -> 32 | J9: =ROUND(E9*Assumptions!B95*Assumptions!B96*Assumptions!B97*Assumptions!B94,0) -> 20 | K9: =ROUND(E9*Assumptions!B57*Assumptions!B58,0) -> 179 | L9: =ROUND(IF(A9<Assumptions!B113,0,IF(A9<=18,Assumptions!B105,Assumptions!B107)/1000*Assumptions!B115*0.55+IF(A9>=Assumptions!B114,IF(A9<=18,Assumptions!B105,Assumptions!B107)*Assumptions!B109/1000*Assumptions!B116*0.55,0)),0) -> 0 | M9: =I9+J9+K9+L9 -> 231 | N9: =ROUND(H9*Assumptions!B62*Assumptions!B61,0)+Assumptions!B63+IF(H9>Assumptions!B64,45,0)+Assumptions!B65+Assumptions!B66+Assumptions!B67+Assumptions!B68+Assumptions!B69/12+IF(A9>=3,Assumptions!B72,0)+ROUND(I9*Assumptions!B70+H9*Assumptions!B71,0)+0 -> 185 | O9: =M9-N9 -> 46 | P9: =IF((Q8+O9)<N9*Assumptions!B89,0,IF((Q8+O9)<N9*6,ROUND(MAX(O9,0)*Assumptions!B90,0),ROUND(MAX(O9,0)*Assumptions!B91,0))) -> 0 | Q9: =Q8+O9-P9 -> -3873
A10: 7 | B10: =ROUND(B9*(1+Assumptions!B34),0) -> 550 | C10: =ROUND(IF(A10<Assumptions!B100,0,IF(A10<=8,Assumptions!B103,IF(A10<=12,Assumptions!B104,IF(A10<=18,Assumptions!B105,IF(A10<=24,Assumptions!B106,Assumptions!B107))))*(1+IF(A10>=Assumptions!B101,Assumptions!B109,0))*Assumptions!B111),0) -> 10 | D10: =ROUND(ROUND(Assumptions!B119*(1+Assumptions!B120)^6*(1+Assumptions!B121)^(A10-6),0)*Assumptions!B123,0) -> 3 | E10: =B10+C10+D10 -> 563 | F10: =ROUND(E10*Assumptions!B22,0) -> 1 | G10: =ROUND(H9*Assumptions!B50,0) -> 0 | H10: =H9+F10-G10 -> 5 | I10: =ROUND(H10*Assumptions!B14,0) -> 40 | J10: =ROUND(E10*Assumptions!B95*Assumptions!B96*Assumptions!B97*Assumptions!B94,0) -> 22 | K10: =ROUND(E10*Assumptions!B57*Assumptions!B58,0) -> 197 | L10: =ROUND(IF(A10<Assumptions!B113,0,IF(A10<=18,Assumptions!B105,Assumptions!B107)/1000*Assumptions!B115*0.55+IF(A10>=Assumptions!B114,IF(A10<=18,Assumptions!B105,Assumptions!B107)*Assumptions!B109/1000*Assumptions!B116*0.55,0)),0) -> 0 | M10: =I10+J10+K10+L10 -> 259 | N10: =ROUND(H10*Assumptions!B62*Assumptions!B61,0)+Assumptions!B63+IF(H10>Assumptions!B64,45,0)+Assumptions!B65+Assumptions!B66+Assumptions!B67+Assumptions!B68+Assumptions!B69/12+IF(A10>=3,Assumptions!B72,0)+ROUND(I10*Assumptions!B70+H10*Assumptions!B71,0)+0 -> 186 | O10: =M10-N10 -> 73 | P10: =IF((Q9+O10)<N10*Assumptions!B89,0,IF((Q9+O10)<N10*6,ROUND(MAX(O10,0)*Assumptions!B90,0),ROUND(MAX(O10,0)*Assumptions!B91,0))) -> 0 | Q10: =Q9+O10-P10 -> -3800
A11: 8 | B11: =ROUND(B10*(1+Assumptions!B34),0) -> 605 | C11: =ROUND(IF(A11<Assumptions!B100,0,IF(A11<=8,Assumptions!B103,IF(A11<=12,Assumptions!B104,IF(A11<=18,Assumptions!B105,IF(A11<=24,Assumptions!B106,Assumptions!B107))))*(1+IF(A11>=Assumptions!B101,Assumptions!B109,0))*Assumptions!B111),0) -> 10 | D11: =ROUND(ROUND(Assumptions!B119*(1+Assumptions!B120)^6*(1+Assumptions!B121)^(A11-6),0)*Assumptions!B123,0) -> 3 | E11: =B11+C11+D11 -> 618 | F11: =ROUND(E11*Assumptions!B22,0) -> 1 | G11: =ROUND(H10*Assumptions!B50,0) -> 0 | H11: =H10+F11-G11 -> 6 | I11: =ROUND(H11*Assumptions!B14,0) -> 48 | J11: =ROUND(E11*Assumptions!B95*Assumptions!B96*Assumptions!B97*Assumptions!B94,0) -> 24 | K11: =ROUND(E11*Assumptions!B57*Assumptions!B58,0) -> 216 | L11: =ROUND(IF(A11<Assumptions!B113,0,IF(A11<=18,Assumptions!B105,Assumptions!B107)/1000*Assumptions!B115*0.55+IF(A11>=Assumptions!B114,IF(A11<=18,Assumptions!B105,Assumptions!B107)*Assumptions!B109/1000*Assumptions!B116*0.55,0)),0) -> 0 | M11: =I11+J11+K11+L11 -> 288 | N11: =ROUND(H11*Assumptions!B62*Assumptions!B61,0)+Assumptions!B63+IF(H11>Assumptions!B64,45,0)+Assumptions!B65+Assumptions!B66+Assumptions!B67+Assumptions!B68+Assumptions!B69/12+IF(A11>=3,Assumptions!B72,0)+ROUND(I11*Assumptions!B70+H11*Assumptions!B71,0)+0 -> 187 | O11: =M11-N11 -> 101 | P11: =IF((Q10+O11)<N11*Assumptions!B89,0,IF((Q10+O11)<N11*6,ROUND(MAX(O11,0)*Assumptions!B90,0),ROUND(MAX(O11,0)*Assumptions!B91,0))) -> 0 | Q11: =Q10+O11-P11 -> -3699
A12: 9 | B12: =ROUND(B11*(1+Assumptions!B34),0) -> 666 | C12: =ROUND(IF(A12<Assumptions!B100,0,IF(A12<=8,Assumptions!B103,IF(A12<=12,Assumptions!B104,IF(A12<=18,Assumptions!B105,IF(A12<=24,Assumptions!B106,Assumptions!B107))))*(1+IF(A12>=Assumptions!B101,Assumptions!B109,0))*Assumptions!B111),0) -> 60 | D12: =ROUND(ROUND(Assumptions!B119*(1+Assumptions!B120)^6*(1+Assumptions!B121)^(A12-6),0)*Assumptions!B123,0) -> 3 | E12: =B12+C12+D12 -> 729 | F12: =ROUND(E12*Assumptions!B22,0) -> 1 | G12: =ROUND(H11*Assumptions!B50,0) -> 0 | H12: =H11+F12-G12 -> 7 | I12: =ROUND(H12*((Assumptions!B14+Assumptions!B15)/2),0) -> 74 | J12: =ROUND(E12*Assumptions!B95*Assumptions!B96*Assumptions!B97*Assumptions!B94,0) -> 28 | K12: =ROUND(E12*Assumptions!B57*Assumptions!B58,0) -> 255 | L12: =ROUND(IF(A12<Assumptions!B113,0,IF(A12<=18,Assumptions!B105,Assumptions!B107)/1000*Assumptions!B115*0.55+IF(A12>=Assumptions!B114,IF(A12<=18,Assumptions!B105,Assumptions!B107)*Assumptions!B109/1000*Assumptions!B116*0.55,0)),0) -> 0 | M12: =I12+J12+K12+L12 -> 357 | N12: =ROUND(H12*Assumptions!B62*Assumptions!B61,0)+Assumptions!B63+IF(H12>Assumptions!B64,45,0)+Assumptions!B65+Assumptions!B66+Assumptions!B67+Assumptions!B68+Assumptions!B69/12+IF(A12>=3,Assumptions!B72,0)+ROUND(I12*Assumptions!B70+H12*Assumptions!B71,0)+0 -> 188 | O12: =M12-N12 -> 169 | P12: =IF((Q11+O12)<N12*Assumptions!B89,0,IF((Q11+O12)<N12*6,ROUND(MAX(O12,0)*Assumptions!B90,0),ROUND(MAX(O12,0)*Assumptions!B91,0))) -> 0 | Q12: =Q11+O12-P12 -> -3530
A13: 10 | B13: =ROUND(B12*(1+Assumptions!B34),0) -> 733 | C13: =ROUND(IF(A13<Assumptions!B100,0,IF(A13<=8,Assumptions!B103,IF(A13<=12,Assumptions!B104,IF(A13<=18,Assumptions!B105,IF(A13<=24,Assumptions!B106,Assumptions!B107))))*(1+IF(A13>=Assumptions!B101,Assumptions!B109,0))*Assumptions!B111),0) -> 60 | D13: =ROUND(ROUND(Assumptions!B119*(1+Assumptions!B120)^6*(1+Assumptions!B121)^(A13-6),0)*Assumptions!B123,0) -> 4 | E13: =B13+C13+D13 -> 797 | F13: =ROUND(E13*Assumptions!B22,0) -> 1 | G13: =ROUND(H12*Assumptions!B50,0) -> 1 | H13: =H12+F13-G13 -> 7 | I13: =ROUND(H13*(Assumptions!B15*0.85+Assumptions!B11*0.15),0) -> 80 | J13: =ROUND(E13*Assumptions!B95*Assumptions!B96*Assumptions!B97*Assumptions!B94,0) -> 31 | K13: =ROUND(E13*Assumptions!B57*Assumptions!B58,0) -> 279 | L13: =ROUND(IF(A13<Assumptions!B113,0,IF(A13<=18,Assumptions!B105,Assumptions!B107)/1000*Assumptions!B115*0.55+IF(A13>=Assumptions!B114,IF(A13<=18,Assumptions!B105,Assumptions!B107)*Assumptions!B109/1000*Assumptions!B116*0.55,0)),0) -> 0 | M13: =I13+J13+K13+L13 -> 390 | N13: =ROUND(H13*Assumptions!B62*Assumptions!B61,0)+Assumptions!B63+IF(H13>Assumptions!B64,45,0)+Assumptions!B65+Assumptions!B66+Assumptions!B67+Assumptions!B68+Assumptions!B69/12+IF(A13>=3,Assumptions!B72,0)+ROUND(I13*Assumptions!B70+H13*Assumptions!B71,0)+0 -> 188 | O13: =M13-N13 -> 202 | P13: =IF((Q12+O13)<N13*Assumptions!B89,0,IF((Q12+O13)<N13*6,ROUND(MAX(O13,0)*Assumptions!B90,0),ROUND(MAX(O13,0)*Assumptions!B91,0))) -> 0 | Q13: =Q12+O13-P13 -> -3328
A14: 11 | B14: =ROUND(B13*(1+Assumptions!B34),0) -> 806 | C14: =ROUND(IF(A14<Assumptions!B100,0,IF(A14<=8,Assumptions!B103,IF(A14<=12,Assumptions!B104,IF(A14<=18,Assumptions!B105,IF(A14<=24,Assumptions!B106,Assumptions!B107))))*(1+IF(A14>=Assumptions!B101,Assumptions!B109,0))*Assumptions!B111),0) -> 60 | D14: =ROUND(ROUND(Assumptions!B119*(1+Assumptions!B120)^6*(1+Assumptions!B121)^(A14-6),0)*Assumptions!B123,0) -> 5 | E14: =B14+C14+D14 -> 871 | F14: =ROUND(E14*Assumptions!B22,0) -> 1 | G14: =ROUND(H13*Assumptions!B50,0) -> 1 | H14: =H13+F14-G14 -> 7 | I14: =ROUND(H14*(Assumptions!B15*0.85+Assumptions!B11*0.15),0) -> 80 | J14: =ROUND(E14*Assumptions!B95*Assumptions!B96*Assumptions!B97*Assumptions!B94,0) -> 34 | K14: =ROUND(E14*Assumptions!B57*Assumptions!B58,0) -> 305 | L14: =ROUND(IF(A14<Assumptions!B113,0,IF(A14<=18,Assumptions!B105,Assumptions!B107)/1000*Assumptions!B115*0.55+IF(A14>=Assumptions!B114,IF(A14<=18,Assumptions!B105,Assumptions!B107)*Assumptions!B109/1000*Assumptions!B116*0.55,0)),0) -> 0 | M14: =I14+J14+K14+L14 -> 419 | N14: =ROUND(H14*Assumptions!B62*Assumptions!B61,0)+Assumptions!B63+IF(H14>Assumptions!B64,45,0)+Assumptions!B65+Assumptions!B66+Assumptions!B67+Assumptions!B68+Assumptions!B69/12+IF(A14>=3,Assumptions!B72,0)+ROUND(I14*Assumptions!B70+H14*Assumptions!B71,0)+0 -> 188 | O14: =M14-N14 -> 231 | P14: =IF((Q13+O14)<N14*Assumptions!B89,0,IF((Q13+O14)<N14*6,ROUND(MAX(O14,0)*Assumptions!B90,0),ROUND(MAX(O14,0)*Assumptions!B91,0))) -> 0 | Q14: =Q13+O14-P14 -> -3097
A15: 12 | B15: =ROUND(B14*(1+Assumptions!B34),0) -> 887 | C15: =ROUND(IF(A15<Assumptions!B100,0,IF(A15<=8,Assumptions!B103,IF(A15<=12,Assumptions!B104,IF(A15<=18,Assumptions!B105,IF(A15<=24,Assumptions!B106,Assumptions!B107))))*(1+IF(A15>=Assumptions!B101,Assumptions!B109,0))*Assumptions!B111),0) -> 60 | D15: =ROUND(ROUND(Assumptions!B119*(1+Assumptions!B120)^6*(1+Assumptions!B121)^(A15-6),0)*Assumptions!B123,0) -> 5 | E15: =B15+C15+D15 -> 952 | F15: =ROUND(E15*Assumptions!B22,0) -> 1 | G15: =ROUND(H14*Assumptions!B50,0) -> 1 | H15: =H14+F15-G15 -> 7 | I15: =ROUND(H15*(Assumptions!B15*0.85+Assumptions!B11*0.15),0) -> 80 | J15: =ROUND(E15*Assumptions!B95*Assumptions!B96*Assumptions!B97*Assumptions!B94,0) -> 37 | K15: =ROUND(E15*Assumptions!B57*Assumptions!B58,0) -> 333 | L15: =ROUND(IF(A15<Assumptions!B113,0,IF(A15<=18,Assumptions!B105,Assumptions!B107)/1000*Assumptions!B115*0.55+IF(A15>=Assumptions!B114,IF(A15<=18,Assumptions!B105,Assumptions!B107)*Assumptions!B109/1000*Assumptions!B116*0.55,0)),0) -> 22 | M15: =I15+J15+K15+L15 -> 472 | N15: =ROUND(H15*Assumptions!B62*Assumptions!B61,0)+Assumptions!B63+IF(H15>Assumptions!B64,45,0)+Assumptions!B65+Assumptions!B66+Assumptions!B67+Assumptions!B68+Assumptions!B69/12+IF(A15>=3,Assumptions!B72,0)+ROUND(I15*Assumptions!B70+H15*Assumptions!B71,0)+0 -> 188 | O15: =M15-N15 -> 284 | P15: =IF((Q14+O15)<N15*Assumptions!B89,0,IF((Q14+O15)<N15*6,ROUND(MAX(O15,0)*Assumptions!B90,0),ROUND(MAX(O15,0)*Assumptions!B91,0))) -> 0 | Q15: =Q14+O15-P15 -> -2813
A16: 13 | B16: =ROUND(B15*(1+Assumptions!B38),0) -> 940 | C16: =ROUND(IF(A16<Assumptions!B100,0,IF(A16<=8,Assumptions!B103,IF(A16<=12,Assumptions!B104,IF(A16<=18,Assumptions!B105,IF(A16<=24,Assumptions!B106,Assumptions!B107))))*(1+IF(A16>=Assumptions!B101,Assumptions!B109,0))*Assumptions!B111),0) -> 150 | D16: =ROUND(ROUND(Assumptions!B119*(1+Assumptions!B120)^6*(1+Assumptions!B121)^6*(1+Assumptions!B122)^(A16-12),0)*Assumptions!B123,0) -> 6 | E16: =B16+C16+D16 -> 1096 | F16: =ROUND(E16*Assumptions!B22,0) -> 2 | G16: =ROUND(H15*Assumptions!B50,0) -> 1 | H16: =H15+F16-G16 -> 8 | I16: =ROUND(H16*(Assumptions!B15*0.85+Assumptions!B11*0.15),0) -> 92 | J16: =ROUND(E16*Assumptions!B95*Assumptions!B96*Assumptions!B97*Assumptions!B94,0) -> 43 | K16: =ROUND(E16*Assumptions!B57*Assumptions!B58,0) -> 384 | L16: =ROUND(IF(A16<Assumptions!B113,0,IF(A16<=18,Assumptions!B105,Assumptions!B107)/1000*Assumptions!B115*0.55+IF(A16>=Assumptions!B114,IF(A16<=18,Assumptions!B105,Assumptions!B107)*Assumptions!B109/1000*Assumptions!B116*0.55,0)),0) -> 22 | M16: =I16+J16+K16+L16 -> 541 | N16: =ROUND(H16*Assumptions!B62*Assumptions!B61,0)+Assumptions!B63+IF(H16>Assumptions!B64,45,0)+Assumptions!B65+Assumptions!B66+Assumptions!B67+Assumptions!B68+Assumptions!B69/12+IF(A16>=3,Assumptions!B72,0)+ROUND(I16*Assumptions!B70+H16*Assumptions!B71,0)+0 -> 189 | O16: =M16-N16 -> 352 | P16: =IF((Q15+O16)<N16*Assumptions!B89,0,IF((Q15+O16)<N16*6,ROUND(MAX(O16,0)*Assumptions!B90,0),ROUND(MAX(O16,0)*Assumptions!B91,0))) -> 0 | Q16: =Q15+O16-P16 -> -2461
A17: 14 | B17: =ROUND(B16*(1+Assumptions!B38),0) -> 996 | C17: =ROUND(IF(A17<Assumptions!B100,0,IF(A17<=8,Assumptions!B103,IF(A17<=12,Assumptions!B104,IF(A17<=18,Assumptions!B105,IF(A17<=24,Assumptions!B106,Assumptions!B107))))*(1+IF(A17>=Assumptions!B101,Assumptions!B109,0))*Assumptions!B111),0) -> 150 | D17: =ROUND(ROUND(Assumptions!B119*(1+Assumptions!B120)^6*(1+Assumptions!B121)^6*(1+Assumptions!B122)^(A17-12),0)*Assumptions!B123,0) -> 6 | E17: =B17+C17+D17 -> 1152 | F17: =ROUND(E17*Assumptions!B22,0) -> 2 | G17: =ROUND(H16*Assumptions!B50,0) -> 1 | H17: =H16+F17-G17 -> 9 | I17: =ROUND(H17*(Assumptions!B15*0.85+Assumptions!B11*0.15),0) -> 103 | J17: =ROUND(E17*Assumptions!B95*Assumptions!B96*Assumptions!B97*Assumptions!B94,0) -> 45 | K17: =ROUND(E17*Assumptions!B57*Assumptions!B58,0) -> 403 | L17: =ROUND(IF(A17<Assumptions!B113,0,IF(A17<=18,Assumptions!B105,Assumptions!B107)/1000*Assumptions!B115*0.55+IF(A17>=Assumptions!B114,IF(A17<=18,Assumptions!B105,Assumptions!B107)*Assumptions!B109/1000*Assumptions!B116*0.55,0)),0) -> 22 | M17: =I17+J17+K17+L17 -> 573 | N17: =ROUND(H17*Assumptions!B62*Assumptions!B61,0)+Assumptions!B63+IF(H17>Assumptions!B64,45,0)+Assumptions!B65+Assumptions!B66+Assumptions!B67+Assumptions!B68+Assumptions!B69/12+IF(A17>=3,Assumptions!B72,0)+ROUND(I17*Assumptions!B70+H17*Assumptions!B71,0)+0 -> 191 | O17: =M17-N17 -> 382 | P17: =IF((Q16+O17)<N17*Assumptions!B89,0,IF((Q16+O17)<N17*6,ROUND(MAX(O17,0)*Assumptions!B90,0),ROUND(MAX(O17,0)*Assumptions!B91,0))) -> 0 | Q17: =Q16+O17-P17 -> -2079
A18: 15 | B18: =ROUND(B17*(1+Assumptions!B38),0) -> 1056 | C18: =ROUND(IF(A18<Assumptions!B100,0,IF(A18<=8,Assumptions!B103,IF(A18<=12,Assumptions!B104,IF(A18<=18,Assumptions!B105,IF(A18<=24,Assumptions!B106,Assumptions!B107))))*(1+IF(A18>=Assumptions!B101,Assumptions!B109,0))*Assumptions!B111),0) -> 150 | D18: =ROUND(ROUND(Assumptions!B119*(1+Assumptions!B120)^6*(1+Assumptions!B121)^6*(1+Assumptions!B122)^(A18-12),0)*Assumptions!B123,0) -> 7 | E18: =B18+C18+D18 -> 1213 | F18: =ROUND(E18*Assumptions!B22,0) -> 2 | G18: =ROUND(H17*Assumptions!B50,0) -> 1 | H18: =H17+F18-G18 -> 10 | I18: =ROUND(H18*(Assumptions!B15*0.85+Assumptions!B11*0.15),0) -> 115 | J18: =ROUND(E18*Assumptions!B95*Assumptions!B96*Assumptions!B97*Assumptions!B94,0) -> 47 | K18: =ROUND(E18*Assumptions!B57*Assumptions!B58,0) -> 425 | L18: =ROUND(IF(A18<Assumptions!B113,0,IF(A18<=18,Assumptions!B105,Assumptions!B107)/1000*Assumptions!B115*0.55+IF(A18>=Assumptions!B114,IF(A18<=18,Assumptions!B105,Assumptions!B107)*Assumptions!B109/1000*Assumptions!B116*0.55,0)),0) -> 22 | M18: =I18+J18+K18+L18 -> 609 | N18: =ROUND(H18*Assumptions!B62*Assumptions!B61,0)+Assumptions!B63+IF(H18>Assumptions!B64,45,0)+Assumptions!B65+Assumptions!B66+Assumptions!B67+Assumptions!B68+Assumptions!B69/12+IF(A18>=3,Assumptions!B72,0)+ROUND(I18*Assumptions!B70+H18*Assumptions!B71,0)+0 -> 191 | O18: =M18-N18 -> 418 | P18: =IF((Q17+O18)<N18*Assumptions!B89,0,IF((Q17+O18)<N18*6,ROUND(MAX(O18,0)*Assumptions!B90,0),ROUND(MAX(O18,0)*Assumptions!B91,0))) -> 0 | Q18: =Q17+O18-P18 -> -1661
A19: 16 | B19: =ROUND(B18*(1+Assumptions!B38),0) -> 1119 | C19: =ROUND(IF(A19<Assumptions!B100,0,IF(A19<=8,Assumptions!B103,IF(A19<=12,Assumptions!B104,IF(A19<=18,Assumptions!B105,IF(A19<=24,Assumptions!B106,Assumptions!B107))))*(1+IF(A19>=Assumptions!B101,Assumptions!B109,0))*Assumptions!B111),0) -> 150 | D19: =ROUND(ROUND(Assumptions!B119*(1+Assumptions!B120)^6*(1+Assumptions!B121)^6*(1+Assumptions!B122)^(A19-12),0)*Assumptions!B123,0) -> 8 | E19: =B19+C19+D19 -> 1277 | F19: =ROUND(E19*Assumptions!B22,0) -> 2 | G19: =ROUND(H18*Assumptions!B50,0) -> 1 | H19: =H18+F19-G19 -> 11 | I19: =ROUND(H19*(Assumptions!B15*0.85+Assumptions!B11*0.15),0) -> 126 | J19: =ROUND(E19*Assumptions!B95*Assumptions!B96*Assumptions!B97*Assumptions!B94,0) -> 50 | K19: =ROUND(E19*Assumptions!B57*Assumptions!B58,0) -> 447 | L19: =ROUND(IF(A19<Assumptions!B113,0,IF(A19<=18,Assumptions!B105,Assumptions!B107)/1000*Assumptions!B115*0.55+IF(A19>=Assumptions!B114,IF(A19<=18,Assumptions!B105,Assumptions!B107)*Assumptions!B109/1000*Assumptions!B116*0.55,0)),0) -> 26 | M19: =I19+J19+K19+L19 -> 649 | N19: =ROUND(H19*Assumptions!B62*Assumptions!B61,0)+Assumptions!B63+IF(H19>Assumptions!B64,45,0)+Assumptions!B65+Assumptions!B66+Assumptions!B67+Assumptions!B68+Assumptions!B69/12+IF(A19>=3,Assumptions!B72,0)+ROUND(I19*Assumptions!B70+H19*Assumptions!B71,0)+0 -> 192 | O19: =M19-N19 -> 457 | P19: =IF((Q18+O19)<N19*Assumptions!B89,0,IF((Q18+O19)<N19*6,ROUND(MAX(O19,0)*Assumptions!B90,0),ROUND(MAX(O19,0)*Assumptions!B91,0))) -> 0 | Q19: =Q18+O19-P19 -> -1204
A20: 17 | B20: =ROUND(B19*(1+Assumptions!B38),0) -> 1186 | C20: =ROUND(IF(A20<Assumptions!B100,0,IF(A20<=8,Assumptions!B103,IF(A20<=12,Assumptions!B104,IF(A20<=18,Assumptions!B105,IF(A20<=24,Assumptions!B106,Assumptions!B107))))*(1+IF(A20>=Assumptions!B101,Assumptions!B109,0))*Assumptions!B111),0) -> 150 | D20: =ROUND(ROUND(Assumptions!B119*(1+Assumptions!B120)^6*(1+Assumptions!B121)^6*(1+Assumptions!B122)^(A20-12),0)*Assumptions!B123,0) -> 8 | E20: =B20+C20+D20 -> 1344 | F20: =ROUND(E20*Assumptions!B22,0) -> 2 | G20: =ROUND(H19*Assumptions!B50,0) -> 1 | H20: =H19+F20-G20 -> 12 | I20: =ROUND(H20*(Assumptions!B15*0.85+Assumptions!B11*0.15),0) -> 138 | J20: =ROUND(E20*Assumptions!B95*Assumptions!B96*Assumptions!B97*Assumptions!B94,0) -> 52 | K20: =ROUND(E20*Assumptions!B57*Assumptions!B58,0) -> 470 | L20: =ROUND(IF(A20<Assumptions!B113,0,IF(A20<=18,Assumptions!B105,Assumptions!B107)/1000*Assumptions!B115*0.55+IF(A20>=Assumptions!B114,IF(A20<=18,Assumptions!B105,Assumptions!B107)*Assumptions!B109/1000*Assumptions!B116*0.55,0)),0) -> 26 | M20: =I20+J20+K20+L20 -> 686 | N20: =ROUND(H20*Assumptions!B62*Assumptions!B61,0)+Assumptions!B63+IF(H20>Assumptions!B64,45,0)+Assumptions!B65+Assumptions!B66+Assumptions!B67+Assumptions!B68+Assumptions!B69/12+IF(A20>=3,Assumptions!B72,0)+ROUND(I20*Assumptions!B70+H20*Assumptions!B71,0)+0 -> 193 | O20: =M20-N20 -> 493 | P20: =IF((Q19+O20)<N20*Assumptions!B89,0,IF((Q19+O20)<N20*6,ROUND(MAX(O20,0)*Assumptions!B90,0),ROUND(MAX(O20,0)*Assumptions!B91,0))) -> 0 | Q20: =Q19+O20-P20 -> -711
A21: 18 | B21: =ROUND(B20*(1+Assumptions!B38),0) -> 1257 | C21: =ROUND(IF(A21<Assumptions!B100,0,IF(A21<=8,Assumptions!B103,IF(A21<=12,Assumptions!B104,IF(A21<=18,Assumptions!B105,IF(A21<=24,Assumptions!B106,Assumptions!B107))))*(1+IF(A21>=Assumptions!B101,Assumptions!B109,0))*Assumptions!B111),0) -> 150 | D21: =ROUND(ROUND(Assumptions!B119*(1+Assumptions!B120)^6*(1+Assumptions!B121)^6*(1+Assumptions!B122)^(A21-12),0)*Assumptions!B123,0) -> 9 | E21: =B21+C21+D21 -> 1416 | F21: =ROUND(E21*Assumptions!B22,0) -> 2 | G21: =ROUND(H20*Assumptions!B50,0) -> 1 | H21: =H20+F21-G21 -> 13 | I21: =ROUND(H21*(Assumptions!B15*0.85+Assumptions!B11*0.15),0) -> 149 | J21: =ROUND(E21*Assumptions!B95*Assumptions!B96*Assumptions!B97*Assumptions!B94,0) -> 55 | K21: =ROUND(E21*Assumptions!B57*Assumptions!B58,0) -> 496 | L21: =ROUND(IF(A21<Assumptions!B113,0,IF(A21<=18,Assumptions!B105,Assumptions!B107)/1000*Assumptions!B115*0.55+IF(A21>=Assumptions!B114,IF(A21<=18,Assumptions!B105,Assumptions!B107)*Assumptions!B109/1000*Assumptions!B116*0.55,0)),0) -> 26 | M21: =I21+J21+K21+L21 -> 726 | N21: =ROUND(H21*Assumptions!B62*Assumptions!B61,0)+Assumptions!B63+IF(H21>Assumptions!B64,45,0)+Assumptions!B65+Assumptions!B66+Assumptions!B67+Assumptions!B68+Assumptions!B69/12+IF(A21>=3,Assumptions!B72,0)+ROUND(I21*Assumptions!B70+H21*Assumptions!B71,0)+0 -> 194 | O21: =M21-N21 -> 532 | P21: =IF((Q20+O21)<N21*Assumptions!B89,0,IF((Q20+O21)<N21*6,ROUND(MAX(O21,0)*Assumptions!B90,0),ROUND(MAX(O21,0)*Assumptions!B91,0))) -> 0 | Q21: =Q20+O21-P21 -> -179
A22: 19 | B22: =ROUND(B21*(1+Assumptions!B38),0) -> 1332 | C22: =ROUND(IF(A22<Assumptions!B100,0,IF(A22<=8,Assumptions!B103,IF(A22<=12,Assumptions!B104,IF(A22<=18,Assumptions!B105,IF(A22<=24,Assumptions!B106,Assumptions!B107))))*(1+IF(A22>=Assumptions!B101,Assumptions!B109,0))*Assumptions!B111),0) -> 300 | D22: =ROUND(ROUND(Assumptions!B119*(1+Assumptions!B120)^6*(1+Assumptions!B121)^6*(1+Assumptions!B122)^(A22-12),0)*Assumptions!B123,0) -> 10 | E22: =B22+C22+D22 -> 1642 | F22: =ROUND(E22*Assumptions!B22,0) -> 2 | G22: =ROUND(H21*Assumptions!B50,0) -> 1 | H22: =H21+F22-G22 -> 14 | I22: =ROUND(H22*(Assumptions!B15*0.85+Assumptions!B11*0.15),0) -> 161 | J22: =ROUND(E22*Assumptions!B95*Assumptions!B96*Assumptions!B97*Assumptions!B94,0) -> 64 | K22: =ROUND(E22*Assumptions!B57*Assumptions!B58,0) -> 575 | L22: =ROUND(IF(A22<Assumptions!B113,0,IF(A22<=18,Assumptions!B105,Assumptions!B107)/1000*Assumptions!B115*0.55+IF(A22>=Assumptions!B114,IF(A22<=18,Assumptions!B105,Assumptions!B107)*Assumptions!B109/1000*Assumptions!B116*0.55,0)),0) -> 94 | M22: =I22+J22+K22+L22 -> 894 | N22: =ROUND(H22*Assumptions!B62*Assumptions!B61,0)+Assumptions!B63+IF(H22>Assumptions!B64,45,0)+Assumptions!B65+Assumptions!B66+Assumptions!B67+Assumptions!B68+Assumptions!B69/12+IF(A22>=3,Assumptions!B72,0)+ROUND(I22*Assumptions!B70+H22*Assumptions!B71,0)+0 -> 195 | O22: =M22-N22 -> 699 | P22: =IF((Q21+O22)<N22*Assumptions!B89,0,IF((Q21+O22)<N22*6,ROUND(MAX(O22,0)*Assumptions!B90,0),ROUND(MAX(O22,0)*Assumptions!B91,0))) -> 0 | Q22: =Q21+O22-P22 -> 520
A23: 20 | B23: =ROUND(B22*(1+Assumptions!B38),0) -> 1412 | C23: =ROUND(IF(A23<Assumptions!B100,0,IF(A23<=8,Assumptions!B103,IF(A23<=12,Assumptions!B104,IF(A23<=18,Assumptions!B105,IF(A23<=24,Assumptions!B106,Assumptions!B107))))*(1+IF(A23>=Assumptions!B101,Assumptions!B109,0))*Assumptions!B111),0) -> 300 | D23: =ROUND(ROUND(Assumptions!B119*(1+Assumptions!B120)^6*(1+Assumptions!B121)^6*(1+Assumptions!B122)^(A23-12),0)*Assumptions!B123,0) -> 11 | E23: =B23+C23+D23 -> 1723 | F23: =ROUND(E23*Assumptions!B22,0) -> 3 | G23: =ROUND(H22*Assumptions!B50,0) -> 1 | H23: =H22+F23-G23 -> 16 | I23: =ROUND(H23*(Assumptions!B15*0.85+Assumptions!B11*0.15),0) -> 184 | J23: =ROUND(E23*Assumptions!B95*Assumptions!B96*Assumptions!B97*Assumptions!B94,0) -> 67 | K23: =ROUND(E23*Assumptions!B57*Assumptions!B58,0) -> 603 | L23: =ROUND(IF(A23<Assumptions!B113,0,IF(A23<=18,Assumptions!B105,Assumptions!B107)/1000*Assumptions!B115*0.55+IF(A23>=Assumptions!B114,IF(A23<=18,Assumptions!B105,Assumptions!B107)*Assumptions!B109/1000*Assumptions!B116*0.55,0)),0) -> 94 | M23: =I23+J23+K23+L23 -> 948 | N23: =ROUND(H23*Assumptions!B62*Assumptions!B61,0)+Assumptions!B63+IF(H23>Assumptions!B64,45,0)+Assumptions!B65+Assumptions!B66+Assumptions!B67+Assumptions!B68+Assumptions!B69/12+IF(A23>=3,Assumptions!B72,0)+ROUND(I23*Assumptions!B70+H23*Assumptions!B71,0)+0 -> 196 | O23: =M23-N23 -> 752 | P23: =IF((Q22+O23)<N23*Assumptions!B89,0,IF((Q22+O23)<N23*6,ROUND(MAX(O23,0)*Assumptions!B90,0),ROUND(MAX(O23,0)*Assumptions!B91,0))) -> 376 | Q23: =Q22+O23-P23 -> 896
A24: 21 | B24: =ROUND(B23*(1+Assumptions!B38),0) -> 1497 | C24: =ROUND(IF(A24<Assumptions!B100,0,IF(A24<=8,Assumptions!B103,IF(A24<=12,Assumptions!B104,IF(A24<=18,Assumptions!B105,IF(A24<=24,Assumptions!B106,Assumptions!B107))))*(1+IF(A24>=Assumptions!B101,Assumptions!B109,0))*Assumptions!B111),0) -> 300 | D24: =ROUND(ROUND(Assumptions!B119*(1+Assumptions!B120)^6*(1+Assumptions!B121)^6*(1+Assumptions!B122)^(A24-12),0)*Assumptions!B123,0) -> 12 | E24: =B24+C24+D24 -> 1809 | F24: =ROUND(E24*Assumptions!B22,0) -> 3 | G24: =ROUND(H23*Assumptions!B50,0) -> 1 | H24: =H23+F24-G24 -> 18 | I24: =ROUND(H24*(Assumptions!B15*0.85+Assumptions!B11*0.15),0) -> 207 | J24: =ROUND(E24*Assumptions!B95*Assumptions!B96*Assumptions!B97*Assumptions!B94,0) -> 71 | K24: =ROUND(E24*Assumptions!B57*Assumptions!B58,0) -> 633 | L24: =ROUND(IF(A24<Assumptions!B113,0,IF(A24<=18,Assumptions!B105,Assumptions!B107)/1000*Assumptions!B115*0.55+IF(A24>=Assumptions!B114,IF(A24<=18,Assumptions!B105,Assumptions!B107)*Assumptions!B109/1000*Assumptions!B116*0.55,0)),0) -> 94 | M24: =I24+J24+K24+L24 -> 1005 | N24: =ROUND(H24*Assumptions!B62*Assumptions!B61,0)+Assumptions!B63+IF(H24>Assumptions!B64,45,0)+Assumptions!B65+Assumptions!B66+Assumptions!B67+Assumptions!B68+Assumptions!B69/12+IF(A24>=3,Assumptions!B72,0)+ROUND(I24*Assumptions!B70+H24*Assumptions!B71,0)+0 -> 198 | O24: =M24-N24 -> 807 | P24: =IF((Q23+O24)<N24*Assumptions!B89,0,IF((Q23+O24)<N24*6,ROUND(MAX(O24,0)*Assumptions!B90,0),ROUND(MAX(O24,0)*Assumptions!B91,0))) -> 404 | Q24: =Q23+O24-P24 -> 1299
A25: 22 | B25: =ROUND(B24*(1+Assumptions!B38),0) -> 1587 | C25: =ROUND(IF(A25<Assumptions!B100,0,IF(A25<=8,Assumptions!B103,IF(A25<=12,Assumptions!B104,IF(A25<=18,Assumptions!B105,IF(A25<=24,Assumptions!B106,Assumptions!B107))))*(1+IF(A25>=Assumptions!B101,Assumptions!B109,0))*Assumptions!B111),0) -> 300 | D25: =ROUND(ROUND(Assumptions!B119*(1+Assumptions!B120)^6*(1+Assumptions!B121)^6*(1+Assumptions!B122)^(A25-12),0)*Assumptions!B123,0) -> 13 | E25: =B25+C25+D25 -> 1900 | F25: =ROUND(E25*Assumptions!B22,0) -> 3 | G25: =ROUND(H24*Assumptions!B50,0) -> 1 | H25: =H24+F25-G25 -> 20 | I25: =ROUND(H25*(Assumptions!B15*0.85+Assumptions!B11*0.15),0) -> 230 | J25: =ROUND(E25*Assumptions!B95*Assumptions!B96*Assumptions!B97*Assumptions!B94,0) -> 74 | K25: =ROUND(E25*Assumptions!B57*Assumptions!B58,0) -> 665 | L25: =ROUND(IF(A25<Assumptions!B113,0,IF(A25<=18,Assumptions!B105,Assumptions!B107)/1000*Assumptions!B115*0.55+IF(A25>=Assumptions!B114,IF(A25<=18,Assumptions!B105,Assumptions!B107)*Assumptions!B109/1000*Assumptions!B116*0.55,0)),0) -> 94 | M25: =I25+J25+K25+L25 -> 1063 | N25: =ROUND(H25*Assumptions!B62*Assumptions!B61,0)+Assumptions!B63+IF(H25>Assumptions!B64,45,0)+Assumptions!B65+Assumptions!B66+Assumptions!B67+Assumptions!B68+Assumptions!B69/12+IF(A25>=3,Assumptions!B72,0)+ROUND(I25*Assumptions!B70+H25*Assumptions!B71,0)+0 -> 201 | O25: =M25-N25 -> 862 | P25: =IF((Q24+O25)<N25*Assumptions!B89,0,IF((Q24+O25)<N25*6,ROUND(MAX(O25,0)*Assumptions!B90,0),ROUND(MAX(O25,0)*Assumptions!B91,0))) -> 431 | Q25: =Q24+O25-P25 -> 1730
A26: 23 | B26: =ROUND(B25*(1+Assumptions!B38),0) -> 1682 | C26: =ROUND(IF(A26<Assumptions!B100,0,IF(A26<=8,Assumptions!B103,IF(A26<=12,Assumptions!B104,IF(A26<=18,Assumptions!B105,IF(A26<=24,Assumptions!B106,Assumptions!B107))))*(1+IF(A26>=Assumptions!B101,Assumptions!B109,0))*Assumptions!B111),0) -> 300 | D26: =ROUND(ROUND(Assumptions!B119*(1+Assumptions!B120)^6*(1+Assumptions!B121)^6*(1+Assumptions!B122)^(A26-12),0)*Assumptions!B123,0) -> 15 | E26: =B26+C26+D26 -> 1997 | F26: =ROUND(E26*Assumptions!B22,0) -> 3 | G26: =ROUND(H25*Assumptions!B50,0) -> 2 | H26: =H25+F26-G26 -> 21 | I26: =ROUND(H26*(Assumptions!B15*0.85+Assumptions!B11*0.15),0) -> 241 | J26: =ROUND(E26*Assumptions!B95*Assumptions!B96*Assumptions!B97*Assumptions!B94,0) -> 78 | K26: =ROUND(E26*Assumptions!B57*Assumptions!B58,0) -> 699 | L26: =ROUND(IF(A26<Assumptions!B113,0,IF(A26<=18,Assumptions!B105,Assumptions!B107)/1000*Assumptions!B115*0.55+IF(A26>=Assumptions!B114,IF(A26<=18,Assumptions!B105,Assumptions!B107)*Assumptions!B109/1000*Assumptions!B116*0.55,0)),0) -> 94 | M26: =I26+J26+K26+L26 -> 1112 | N26: =ROUND(H26*Assumptions!B62*Assumptions!B61,0)+Assumptions!B63+IF(H26>Assumptions!B64,45,0)+Assumptions!B65+Assumptions!B66+Assumptions!B67+Assumptions!B68+Assumptions!B69/12+IF(A26>=3,Assumptions!B72,0)+ROUND(I26*Assumptions!B70+H26*Assumptions!B71,0)+0 -> 201 | O26: =M26-N26 -> 911 | P26: =IF((Q25+O26)<N26*Assumptions!B89,0,IF((Q25+O26)<N26*6,ROUND(MAX(O26,0)*Assumptions!B90,0),ROUND(MAX(O26,0)*Assumptions!B91,0))) -> 456 | Q26: =Q25+O26-P26 -> 2185
A27: 24 | B27: =ROUND(B26*(1+Assumptions!B38),0) -> 1783 | C27: =ROUND(IF(A27<Assumptions!B100,0,IF(A27<=8,Assumptions!B103,IF(A27<=12,Assumptions!B104,IF(A27<=18,Assumptions!B105,IF(A27<=24,Assumptions!B106,Assumptions!B107))))*(1+IF(A27>=Assumptions!B101,Assumptions!B109,0))*Assumptions!B111),0) -> 300 | D27: =ROUND(ROUND(Assumptions!B119*(1+Assumptions!B120)^6*(1+Assumptions!B121)^6*(1+Assumptions!B122)^(A27-12),0)*Assumptions!B123,0) -> 16 | E27: =B27+C27+D27 -> 2099 | F27: =ROUND(E27*Assumptions!B22,0) -> 3 | G27: =ROUND(H26*Assumptions!B50,0) -> 2 | H27: =H26+F27-G27 -> 22 | I27: =ROUND(H27*(Assumptions!B15*0.85+Assumptions!B11*0.15),0) -> 252 | J27: =ROUND(E27*Assumptions!B95*Assumptions!B96*Assumptions!B97*Assumptions!B94,0) -> 82 | K27: =ROUND(E27*Assumptions!B57*Assumptions!B58,0) -> 735 | L27: =ROUND(IF(A27<Assumptions!B113,0,IF(A27<=18,Assumptions!B105,Assumptions!B107)/1000*Assumptions!B115*0.55+IF(A27>=Assumptions!B114,IF(A27<=18,Assumptions!B105,Assumptions!B107)*Assumptions!B109/1000*Assumptions!B116*0.55,0)),0) -> 94 | M27: =I27+J27+K27+L27 -> 1163 | N27: =ROUND(H27*Assumptions!B62*Assumptions!B61,0)+Assumptions!B63+IF(H27>Assumptions!B64,45,0)+Assumptions!B65+Assumptions!B66+Assumptions!B67+Assumptions!B68+Assumptions!B69/12+IF(A27>=3,Assumptions!B72,0)+ROUND(I27*Assumptions!B70+H27*Assumptions!B71,0)+0 -> 202 | O27: =M27-N27 -> 961 | P27: =IF((Q26+O27)<N27*Assumptions!B89,0,IF((Q26+O27)<N27*6,ROUND(MAX(O27,0)*Assumptions!B90,0),ROUND(MAX(O27,0)*Assumptions!B91,0))) -> 481 | Q27: =Q26+O27-P27 -> 2665
A28: 25 | B28: =ROUND(B27*(1+Assumptions!B42),0) -> 1854 | C28: =ROUND(IF(A28<Assumptions!B100,0,IF(A28<=8,Assumptions!B103,IF(A28<=12,Assumptions!B104,IF(A28<=18,Assumptions!B105,IF(A28<=24,Assumptions!B106,Assumptions!B107))))*(1+IF(A28>=Assumptions!B101,Assumptions!B109,0))*Assumptions!B111),0) -> 540 | D28: =ROUND(ROUND(Assumptions!B119*(1+Assumptions!B120)^6*(1+Assumptions!B121)^6*(1+Assumptions!B122)^(A28-12),0)*Assumptions!B123,0) -> 18 | E28: =B28+C28+D28 -> 2412 | F28: =ROUND(E28*Assumptions!B22,0) -> 4 | G28: =ROUND(H27*Assumptions!B50,0) -> 2 | H28: =H27+F28-G28 -> 24 | I28: =ROUND(H28*(Assumptions!B15*0.85+Assumptions!B11*0.15),0) -> 275 | J28: =ROUND(E28*Assumptions!B95*Assumptions!B96*Assumptions!B97*Assumptions!B94,0) -> 94 | K28: =ROUND(E28*Assumptions!B57*Assumptions!B58,0) -> 844 | L28: =ROUND(IF(A28<Assumptions!B113,0,IF(A28<=18,Assumptions!B105,Assumptions!B107)/1000*Assumptions!B115*0.55+IF(A28>=Assumptions!B114,IF(A28<=18,Assumptions!B105,Assumptions!B107)*Assumptions!B109/1000*Assumptions!B116*0.55,0)),0) -> 94 | M28: =I28+J28+K28+L28 -> 1307 | N28: =ROUND(H28*Assumptions!B62*Assumptions!B61,0)+Assumptions!B63+IF(H28>Assumptions!B64,45,0)+Assumptions!B65+Assumptions!B66+Assumptions!B67+Assumptions!B68+Assumptions!B69/12+IF(A28>=3,Assumptions!B72,0)+ROUND(I28*Assumptions!B70+H28*Assumptions!B71,0)+0 -> 204 | O28: =M28-N28 -> 1103 | P28: =IF((Q27+O28)<N28*Assumptions!B89,0,IF((Q27+O28)<N28*6,ROUND(MAX(O28,0)*Assumptions!B90,0),ROUND(MAX(O28,0)*Assumptions!B91,0))) -> 552 | Q28: =Q27+O28-P28 -> 3216
A29: 26 | B29: =ROUND(B28*(1+Assumptions!B42),0) -> 1928 | C29: =ROUND(IF(A29<Assumptions!B100,0,IF(A29<=8,Assumptions!B103,IF(A29<=12,Assumptions!B104,IF(A29<=18,Assumptions!B105,IF(A29<=24,Assumptions!B106,Assumptions!B107))))*(1+IF(A29>=Assumptions!B101,Assumptions!B109,0))*Assumptions!B111),0) -> 540 | D29: =ROUND(ROUND(Assumptions!B119*(1+Assumptions!B120)^6*(1+Assumptions!B121)^6*(1+Assumptions!B122)^(A29-12),0)*Assumptions!B123,0) -> 20 | E29: =B29+C29+D29 -> 2488 | F29: =ROUND(E29*Assumptions!B22,0) -> 4 | G29: =ROUND(H28*Assumptions!B50,0) -> 2 | H29: =H28+F29-G29 -> 26 | I29: =ROUND(H29*(Assumptions!B15*0.85+Assumptions!B11*0.15),0) -> 298 | J29: =ROUND(E29*Assumptions!B95*Assumptions!B96*Assumptions!B97*Assumptions!B94,0) -> 97 | K29: =ROUND(E29*Assumptions!B57*Assumptions!B58,0) -> 871 | L29: =ROUND(IF(A29<Assumptions!B113,0,IF(A29<=18,Assumptions!B105,Assumptions!B107)/1000*Assumptions!B115*0.55+IF(A29>=Assumptions!B114,IF(A29<=18,Assumptions!B105,Assumptions!B107)*Assumptions!B109/1000*Assumptions!B116*0.55,0)),0) -> 94 | M29: =I29+J29+K29+L29 -> 1360 | N29: =ROUND(H29*Assumptions!B62*Assumptions!B61,0)+Assumptions!B63+IF(H29>Assumptions!B64,45,0)+Assumptions!B65+Assumptions!B66+Assumptions!B67+Assumptions!B68+Assumptions!B69/12+IF(A29>=3,Assumptions!B72,0)+ROUND(I29*Assumptions!B70+H29*Assumptions!B71,0)+0 -> 205 | O29: =M29-N29 -> 1155 | P29: =IF((Q28+O29)<N29*Assumptions!B89,0,IF((Q28+O29)<N29*6,ROUND(MAX(O29,0)*Assumptions!B90,0),ROUND(MAX(O29,0)*Assumptions!B91,0))) -> 578 | Q29: =Q28+O29-P29 -> 3793
A30: 27 | B30: =ROUND(B29*(1+Assumptions!B42),0) -> 2005 | C30: =ROUND(IF(A30<Assumptions!B100,0,IF(A30<=8,Assumptions!B103,IF(A30<=12,Assumptions!B104,IF(A30<=18,Assumptions!B105,IF(A30<=24,Assumptions!B106,Assumptions!B107))))*(1+IF(A30>=Assumptions!B101,Assumptions!B109,0))*Assumptions!B111),0) -> 540 | D30: =ROUND(ROUND(Assumptions!B119*(1+Assumptions!B120)^6*(1+Assumptions!B121)^6*(1+Assumptions!B122)^(A30-12),0)*Assumptions!B123,0) -> 22 | E30: =B30+C30+D30 -> 2567 | F30: =ROUND(E30*Assumptions!B22,0) -> 4 | G30: =ROUND(H29*Assumptions!B50,0) -> 2 | H30: =H29+F30-G30 -> 28 | I30: =ROUND(H30*(Assumptions!B15*0.85+Assumptions!B11*0.15),0) -> 321 | J30: =ROUND(E30*Assumptions!B95*Assumptions!B96*Assumptions!B97*Assumptions!B94,0) -> 100 | K30: =ROUND(E30*Assumptions!B57*Assumptions!B58,0) -> 898 | L30: =ROUND(IF(A30<Assumptions!B113,0,IF(A30<=18,Assumptions!B105,Assumptions!B107)/1000*Assumptions!B115*0.55+IF(A30>=Assumptions!B114,IF(A30<=18,Assumptions!B105,Assumptions!B107)*Assumptions!B109/1000*Assumptions!B116*0.55,0)),0) -> 94 | M30: =I30+J30+K30+L30 -> 1413 | N30: =ROUND(H30*Assumptions!B62*Assumptions!B61,0)+Assumptions!B63+IF(H30>Assumptions!B64,45,0)+Assumptions!B65+Assumptions!B66+Assumptions!B67+Assumptions!B68+Assumptions!B69/12+IF(A30>=3,Assumptions!B72,0)+ROUND(I30*Assumptions!B70+H30*Assumptions!B71,0)+0 -> 208 | O30: =M30-N30 -> 1205 | P30: =IF((Q29+O30)<N30*Assumptions!B89,0,IF((Q29+O30)<N30*6,ROUND(MAX(O30,0)*Assumptions!B90,0),ROUND(MAX(O30,0)*Assumptions!B91,0))) -> 603 | Q30: =Q29+O30-P30 -> 4395
A31: 28 | B31: =ROUND(B30*(1+Assumptions!B42),0) -> 2085 | C31: =ROUND(IF(A31<Assumptions!B100,0,IF(A31<=8,Assumptions!B103,IF(A31<=12,Assumptions!B104,IF(A31<=18,Assumptions!B105,IF(A31<=24,Assumptions!B106,Assumptions!B107))))*(1+IF(A31>=Assumptions!B101,Assumptions!B109,0))*Assumptions!B111),0) -> 540 | D31: =ROUND(ROUND(Assumptions!B119*(1+Assumptions!B120)^6*(1+Assumptions!B121)^6*(1+Assumptions!B122)^(A31-12),0)*Assumptions!B123,0) -> 24 | E31: =B31+C31+D31 -> 2649 | F31: =ROUND(E31*Assumptions!B22,0) -> 4 | G31: =ROUND(H30*Assumptions!B50,0) -> 2 | H31: =H30+F31-G31 -> 30 | I31: =ROUND(H31*(Assumptions!B15*0.85+Assumptions!B11*0.15),0) -> 344 | J31: =ROUND(E31*Assumptions!B95*Assumptions!B96*Assumptions!B97*Assumptions!B94,0) -> 103 | K31: =ROUND(E31*Assumptions!B57*Assumptions!B58,0) -> 927 | L31: =ROUND(IF(A31<Assumptions!B113,0,IF(A31<=18,Assumptions!B105,Assumptions!B107)/1000*Assumptions!B115*0.55+IF(A31>=Assumptions!B114,IF(A31<=18,Assumptions!B105,Assumptions!B107)*Assumptions!B109/1000*Assumptions!B116*0.55,0)),0) -> 94 | M31: =I31+J31+K31+L31 -> 1468 | N31: =ROUND(H31*Assumptions!B62*Assumptions!B61,0)+Assumptions!B63+IF(H31>Assumptions!B64,45,0)+Assumptions!B65+Assumptions!B66+Assumptions!B67+Assumptions!B68+Assumptions!B69/12+IF(A31>=3,Assumptions!B72,0)+ROUND(I31*Assumptions!B70+H31*Assumptions!B71,0)+0 -> 209 | O31: =M31-N31 -> 1259 | P31: =IF((Q30+O31)<N31*Assumptions!B89,0,IF((Q30+O31)<N31*6,ROUND(MAX(O31,0)*Assumptions!B90,0),ROUND(MAX(O31,0)*Assumptions!B91,0))) -> 630 | Q31: =Q30+O31-P31 -> 5024
A32: 29 | B32: =ROUND(B31*(1+Assumptions!B42),0) -> 2168 | C32: =ROUND(IF(A32<Assumptions!B100,0,IF(A32<=8,Assumptions!B103,IF(A32<=12,Assumptions!B104,IF(A32<=18,Assumptions!B105,IF(A32<=24,Assumptions!B106,Assumptions!B107))))*(1+IF(A32>=Assumptions!B101,Assumptions!B109,0))*Assumptions!B111),0) -> 540 | D32: =ROUND(ROUND(Assumptions!B119*(1+Assumptions!B120)^6*(1+Assumptions!B121)^6*(1+Assumptions!B122)^(A32-12),0)*Assumptions!B123,0) -> 26 | E32: =B32+C32+D32 -> 2734 | F32: =ROUND(E32*Assumptions!B22,0) -> 4 | G32: =ROUND(H31*Assumptions!B50,0) -> 2 | H32: =H31+F32-G32 -> 32 | I32: =ROUND(H32*(Assumptions!B15*0.85+Assumptions!B11*0.15),0) -> 367 | J32: =ROUND(E32*Assumptions!B95*Assumptions!B96*Assumptions!B97*Assumptions!B94,0) -> 107 | K32: =ROUND(E32*Assumptions!B57*Assumptions!B58,0) -> 957 | L32: =ROUND(IF(A32<Assumptions!B113,0,IF(A32<=18,Assumptions!B105,Assumptions!B107)/1000*Assumptions!B115*0.55+IF(A32>=Assumptions!B114,IF(A32<=18,Assumptions!B105,Assumptions!B107)*Assumptions!B109/1000*Assumptions!B116*0.55,0)),0) -> 94 | M32: =I32+J32+K32+L32 -> 1525 | N32: =ROUND(H32*Assumptions!B62*Assumptions!B61,0)+Assumptions!B63+IF(H32>Assumptions!B64,45,0)+Assumptions!B65+Assumptions!B66+Assumptions!B67+Assumptions!B68+Assumptions!B69/12+IF(A32>=3,Assumptions!B72,0)+ROUND(I32*Assumptions!B70+H32*Assumptions!B71,0)+0 -> 211 | O32: =M32-N32 -> 1314 | P32: =IF((Q31+O32)<N32*Assumptions!B89,0,IF((Q31+O32)<N32*6,ROUND(MAX(O32,0)*Assumptions!B90,0),ROUND(MAX(O32,0)*Assumptions!B91,0))) -> 657 | Q32: =Q31+O32-P32 -> 5681
A33: 30 | B33: =ROUND(B32*(1+Assumptions!B42),0) -> 2255 | C33: =ROUND(IF(A33<Assumptions!B100,0,IF(A33<=8,Assumptions!B103,IF(A33<=12,Assumptions!B104,IF(A33<=18,Assumptions!B105,IF(A33<=24,Assumptions!B106,Assumptions!B107))))*(1+IF(A33>=Assumptions!B101,Assumptions!B109,0))*Assumptions!B111),0) -> 540 | D33: =ROUND(ROUND(Assumptions!B119*(1+Assumptions!B120)^6*(1+Assumptions!B121)^6*(1+Assumptions!B122)^(A33-12),0)*Assumptions!B123,0) -> 29 | E33: =B33+C33+D33 -> 2824 | F33: =ROUND(E33*Assumptions!B22,0) -> 4 | G33: =ROUND(H32*Assumptions!B50,0) -> 3 | H33: =H32+F33-G33 -> 33 | I33: =ROUND(H33*(Assumptions!B15*0.85+Assumptions!B11*0.15),0) -> 379 | J33: =ROUND(E33*Assumptions!B95*Assumptions!B96*Assumptions!B97*Assumptions!B94,0) -> 110 | K33: =ROUND(E33*Assumptions!B57*Assumptions!B58,0) -> 988 | L33: =ROUND(IF(A33<Assumptions!B113,0,IF(A33<=18,Assumptions!B105,Assumptions!B107)/1000*Assumptions!B115*0.55+IF(A33>=Assumptions!B114,IF(A33<=18,Assumptions!B105,Assumptions!B107)*Assumptions!B109/1000*Assumptions!B116*0.55,0)),0) -> 94 | M33: =I33+J33+K33+L33 -> 1571 | N33: =ROUND(H33*Assumptions!B62*Assumptions!B61,0)+Assumptions!B63+IF(H33>Assumptions!B64,45,0)+Assumptions!B65+Assumptions!B66+Assumptions!B67+Assumptions!B68+Assumptions!B69/12+IF(A33>=3,Assumptions!B72,0)+ROUND(I33*Assumptions!B70+H33*Assumptions!B71,0)+0 -> 212 | O33: =M33-N33 -> 1359 | P33: =IF((Q32+O33)<N33*Assumptions!B89,0,IF((Q32+O33)<N33*6,ROUND(MAX(O33,0)*Assumptions!B90,0),ROUND(MAX(O33,0)*Assumptions!B91,0))) -> 680 | Q33: =Q32+O33-P33 -> 6360
A34: 31 | B34: =ROUND(B33*(1+Assumptions!B42),0) -> 2345 | C34: =ROUND(IF(A34<Assumptions!B100,0,IF(A34<=8,Assumptions!B103,IF(A34<=12,Assumptions!B104,IF(A34<=18,Assumptions!B105,IF(A34<=24,Assumptions!B106,Assumptions!B107))))*(1+IF(A34>=Assumptions!B101,Assumptions!B109,0))*Assumptions!B111),0) -> 540 | D34: =ROUND(ROUND(Assumptions!B119*(1+Assumptions!B120)^6*(1+Assumptions!B121)^6*(1+Assumptions!B122)^(A34-12),0)*Assumptions!B123,0) -> 32 | E34: =B34+C34+D34 -> 2917 | F34: =ROUND(E34*Assumptions!B22,0) -> 4 | G34: =ROUND(H33*Assumptions!B50,0) -> 3 | H34: =H33+F34-G34 -> 34 | I34: =ROUND(H34*(Assumptions!B15*0.85+Assumptions!B11*0.15),0) -> 390 | J34: =ROUND(E34*Assumptions!B95*Assumptions!B96*Assumptions!B97*Assumptions!B94,0) -> 114 | K34: =ROUND(E34*Assumptions!B57*Assumptions!B58,0) -> 1021 | L34: =ROUND(IF(A34<Assumptions!B113,0,IF(A34<=18,Assumptions!B105,Assumptions!B107)/1000*Assumptions!B115*0.55+IF(A34>=Assumptions!B114,IF(A34<=18,Assumptions!B105,Assumptions!B107)*Assumptions!B109/1000*Assumptions!B116*0.55,0)),0) -> 94 | M34: =I34+J34+K34+L34 -> 1619 | N34: =ROUND(H34*Assumptions!B62*Assumptions!B61,0)+Assumptions!B63+IF(H34>Assumptions!B64,45,0)+Assumptions!B65+Assumptions!B66+Assumptions!B67+Assumptions!B68+Assumptions!B69/12+IF(A34>=3,Assumptions!B72,0)+ROUND(I34*Assumptions!B70+H34*Assumptions!B71,0)+0 -> 214 | O34: =M34-N34 -> 1405 | P34: =IF((Q33+O34)<N34*Assumptions!B89,0,IF((Q33+O34)<N34*6,ROUND(MAX(O34,0)*Assumptions!B90,0),ROUND(MAX(O34,0)*Assumptions!B91,0))) -> 703 | Q34: =Q33+O34-P34 -> 7062
A35: 32 | B35: =ROUND(B34*(1+Assumptions!B42),0) -> 2439 | C35: =ROUND(IF(A35<Assumptions!B100,0,IF(A35<=8,Assumptions!B103,IF(A35<=12,Assumptions!B104,IF(A35<=18,Assumptions!B105,IF(A35<=24,Assumptions!B106,Assumptions!B107))))*(1+IF(A35>=Assumptions!B101,Assumptions!B109,0))*Assumptions!B111),0) -> 540 | D35: =ROUND(ROUND(Assumptions!B119*(1+Assumptions!B120)^6*(1+Assumptions!B121)^6*(1+Assumptions!B122)^(A35-12),0)*Assumptions!B123,0) -> 35 | E35: =B35+C35+D35 -> 3014 | F35: =ROUND(E35*Assumptions!B22,0) -> 5 | G35: =ROUND(H34*Assumptions!B50,0) -> 3 | H35: =H34+F35-G35 -> 36 | I35: =ROUND(H35*(Assumptions!B15*0.85+Assumptions!B11*0.15),0) -> 413 | J35: =ROUND(E35*Assumptions!B95*Assumptions!B96*Assumptions!B97*Assumptions!B94,0) -> 118 | K35: =ROUND(E35*Assumptions!B57*Assumptions!B58,0) -> 1055 | L35: =ROUND(IF(A35<Assumptions!B113,0,IF(A35<=18,Assumptions!B105,Assumptions!B107)/1000*Assumptions!B115*0.55+IF(A35>=Assumptions!B114,IF(A35<=18,Assumptions!B105,Assumptions!B107)*Assumptions!B109/1000*Assumptions!B116*0.55,0)),0) -> 94 | M35: =I35+J35+K35+L35 -> 1680 | N35: =ROUND(H35*Assumptions!B62*Assumptions!B61,0)+Assumptions!B63+IF(H35>Assumptions!B64,45,0)+Assumptions!B65+Assumptions!B66+Assumptions!B67+Assumptions!B68+Assumptions!B69/12+IF(A35>=3,Assumptions!B72,0)+ROUND(I35*Assumptions!B70+H35*Assumptions!B71,0)+0 -> 215 | O35: =M35-N35 -> 1465 | P35: =IF((Q34+O35)<N35*Assumptions!B89,0,IF((Q34+O35)<N35*6,ROUND(MAX(O35,0)*Assumptions!B90,0),ROUND(MAX(O35,0)*Assumptions!B91,0))) -> 733 | Q35: =Q34+O35-P35 -> 7794
A36: 33 | B36: =ROUND(B35*(1+Assumptions!B42),0) -> 2537 | C36: =ROUND(IF(A36<Assumptions!B100,0,IF(A36<=8,Assumptions!B103,IF(A36<=12,Assumptions!B104,IF(A36<=18,Assumptions!B105,IF(A36<=24,Assumptions!B106,Assumptions!B107))))*(1+IF(A36>=Assumptions!B101,Assumptions!B109,0))*Assumptions!B111),0) -> 540 | D36: =ROUND(ROUND(Assumptions!B119*(1+Assumptions!B120)^6*(1+Assumptions!B121)^6*(1+Assumptions!B122)^(A36-12),0)*Assumptions!B123,0) -> 38 | E36: =B36+C36+D36 -> 3115 | F36: =ROUND(E36*Assumptions!B22,0) -> 5 | G36: =ROUND(H35*Assumptions!B50,0) -> 3 | H36: =H35+F36-G36 -> 38 | I36: =ROUND(H36*(Assumptions!B15*0.85+Assumptions!B11*0.15),0) -> 436 | J36: =ROUND(E36*Assumptions!B95*Assumptions!B96*Assumptions!B97*Assumptions!B94,0) -> 121 | K36: =ROUND(E36*Assumptions!B57*Assumptions!B58,0) -> 1090 | L36: =ROUND(IF(A36<Assumptions!B113,0,IF(A36<=18,Assumptions!B105,Assumptions!B107)/1000*Assumptions!B115*0.55+IF(A36>=Assumptions!B114,IF(A36<=18,Assumptions!B105,Assumptions!B107)*Assumptions!B109/1000*Assumptions!B116*0.55,0)),0) -> 94 | M36: =I36+J36+K36+L36 -> 1741 | N36: =ROUND(H36*Assumptions!B62*Assumptions!B61,0)+Assumptions!B63+IF(H36>Assumptions!B64,45,0)+Assumptions!B65+Assumptions!B66+Assumptions!B67+Assumptions!B68+Assumptions!B69/12+IF(A36>=3,Assumptions!B72,0)+ROUND(I36*Assumptions!B70+H36*Assumptions!B71,0)+0 -> 217 | O36: =M36-N36 -> 1524 | P36: =IF((Q35+O36)<N36*Assumptions!B89,0,IF((Q35+O36)<N36*6,ROUND(MAX(O36,0)*Assumptions!B90,0),ROUND(MAX(O36,0)*Assumptions!B91,0))) -> 762 | Q36: =Q35+O36-P36 -> 8556
A37: 34 | B37: =ROUND(B36*(1+Assumptions!B42),0) -> 2638 | C37: =ROUND(IF(A37<Assumptions!B100,0,IF(A37<=8,Assumptions!B103,IF(A37<=12,Assumptions!B104,IF(A37<=18,Assumptions!B105,IF(A37<=24,Assumptions!B106,Assumptions!B107))))*(1+IF(A37>=Assumptions!B101,Assumptions!B109,0))*Assumptions!B111),0) -> 540 | D37: =ROUND(ROUND(Assumptions!B119*(1+Assumptions!B120)^6*(1+Assumptions!B121)^6*(1+Assumptions!B122)^(A37-12),0)*Assumptions!B123,0) -> 42 | E37: =B37+C37+D37 -> 3220 | F37: =ROUND(E37*Assumptions!B22,0) -> 5 | G37: =ROUND(H36*Assumptions!B50,0) -> 3 | H37: =H36+F37-G37 -> 40 | I37: =ROUND(H37*(Assumptions!B15*0.85+Assumptions!B11*0.15),0) -> 459 | J37: =ROUND(E37*Assumptions!B95*Assumptions!B96*Assumptions!B97*Assumptions!B94,0) -> 126 | K37: =ROUND(E37*Assumptions!B57*Assumptions!B58,0) -> 1127 | L37: =ROUND(IF(A37<Assumptions!B113,0,IF(A37<=18,Assumptions!B105,Assumptions!B107)/1000*Assumptions!B115*0.55+IF(A37>=Assumptions!B114,IF(A37<=18,Assumptions!B105,Assumptions!B107)*Assumptions!B109/1000*Assumptions!B116*0.55,0)),0) -> 94 | M37: =I37+J37+K37+L37 -> 1806 | N37: =ROUND(H37*Assumptions!B62*Assumptions!B61,0)+Assumptions!B63+IF(H37>Assumptions!B64,45,0)+Assumptions!B65+Assumptions!B66+Assumptions!B67+Assumptions!B68+Assumptions!B69/12+IF(A37>=3,Assumptions!B72,0)+ROUND(I37*Assumptions!B70+H37*Assumptions!B71,0)+0 -> 218 | O37: =M37-N37 -> 1588 | P37: =IF((Q36+O37)<N37*Assumptions!B89,0,IF((Q36+O37)<N37*6,ROUND(MAX(O37,0)*Assumptions!B90,0),ROUND(MAX(O37,0)*Assumptions!B91,0))) -> 794 | Q37: =Q36+O37-P37 -> 9350
A38: 35 | B38: =ROUND(B37*(1+Assumptions!B42),0) -> 2744 | C38: =ROUND(IF(A38<Assumptions!B100,0,IF(A38<=8,Assumptions!B103,IF(A38<=12,Assumptions!B104,IF(A38<=18,Assumptions!B105,IF(A38<=24,Assumptions!B106,Assumptions!B107))))*(1+IF(A38>=Assumptions!B101,Assumptions!B109,0))*Assumptions!B111),0) -> 540 | D38: =ROUND(ROUND(Assumptions!B119*(1+Assumptions!B120)^6*(1+Assumptions!B121)^6*(1+Assumptions!B122)^(A38-12),0)*Assumptions!B123,0) -> 46 | E38: =B38+C38+D38 -> 3330 | F38: =ROUND(E38*Assumptions!B22,0) -> 5 | G38: =ROUND(H37*Assumptions!B50,0) -> 3 | H38: =H37+F38-G38 -> 42 | I38: =ROUND(H38*(Assumptions!B15*0.85+Assumptions!B11*0.15),0) -> 482 | J38: =ROUND(E38*Assumptions!B95*Assumptions!B96*Assumptions!B97*Assumptions!B94,0) -> 130 | K38: =ROUND(E38*Assumptions!B57*Assumptions!B58,0) -> 1166 | L38: =ROUND(IF(A38<Assumptions!B113,0,IF(A38<=18,Assumptions!B105,Assumptions!B107)/1000*Assumptions!B115*0.55+IF(A38>=Assumptions!B114,IF(A38<=18,Assumptions!B105,Assumptions!B107)*Assumptions!B109/1000*Assumptions!B116*0.55,0)),0) -> 94 | M38: =I38+J38+K38+L38 -> 1872 | N38: =ROUND(H38*Assumptions!B62*Assumptions!B61,0)+Assumptions!B63+IF(H38>Assumptions!B64,45,0)+Assumptions!B65+Assumptions!B66+Assumptions!B67+Assumptions!B68+Assumptions!B69/12+IF(A38>=3,Assumptions!B72,0)+ROUND(I38*Assumptions!B70+H38*Assumptions!B71,0)+0 -> 221 | O38: =M38-N38 -> 1651 | P38: =IF((Q37+O38)<N38*Assumptions!B89,0,IF((Q37+O38)<N38*6,ROUND(MAX(O38,0)*Assumptions!B90,0),ROUND(MAX(O38,0)*Assumptions!B91,0))) -> 826 | Q38: =Q37+O38-P38 -> 10175
A39: 36 | B39: =ROUND(B38*(1+Assumptions!B42),0) -> 2854 | C39: =ROUND(IF(A39<Assumptions!B100,0,IF(A39<=8,Assumptions!B103,IF(A39<=12,Assumptions!B104,IF(A39<=18,Assumptions!B105,IF(A39<=24,Assumptions!B106,Assumptions!B107))))*(1+IF(A39>=Assumptions!B101,Assumptions!B109,0))*Assumptions!B111),0) -> 540 | D39: =ROUND(ROUND(Assumptions!B119*(1+Assumptions!B120)^6*(1+Assumptions!B121)^6*(1+Assumptions!B122)^(A39-12),0)*Assumptions!B123,0) -> 51 | E39: =B39+C39+D39 -> 3445 | F39: =ROUND(E39*Assumptions!B22,0) -> 5 | G39: =ROUND(H38*Assumptions!B50,0) -> 3 | H39: =H38+F39-G39 -> 44 | I39: =ROUND(H39*(Assumptions!B15*0.85+Assumptions!B11*0.15),0) -> 505 | J39: =ROUND(E39*Assumptions!B95*Assumptions!B96*Assumptions!B97*Assumptions!B94,0) -> 134 | K39: =ROUND(E39*Assumptions!B57*Assumptions!B58,0) -> 1206 | L39: =ROUND(IF(A39<Assumptions!B113,0,IF(A39<=18,Assumptions!B105,Assumptions!B107)/1000*Assumptions!B115*0.55+IF(A39>=Assumptions!B114,IF(A39<=18,Assumptions!B105,Assumptions!B107)*Assumptions!B109/1000*Assumptions!B116*0.55,0)),0) -> 94 | M39: =I39+J39+K39+L39 -> 1939 | N39: =ROUND(H39*Assumptions!B62*Assumptions!B61,0)+Assumptions!B63+IF(H39>Assumptions!B64,45,0)+Assumptions!B65+Assumptions!B66+Assumptions!B67+Assumptions!B68+Assumptions!B69/12+IF(A39>=3,Assumptions!B72,0)+ROUND(I39*Assumptions!B70+H39*Assumptions!B71,0)+0 -> 222 | O39: =M39-N39 -> 1717 | P39: =IF((Q38+O39)<N39*Assumptions!B89,0,IF((Q38+O39)<N39*6,ROUND(MAX(O39,0)*Assumptions!B90,0),ROUND(MAX(O39,0)*Assumptions!B91,0))) -> 859 | Q39: =Q38+O39-P39 -> 11033
A40: TOTALS | I40: =SUM(I4:I39) -> 7149 | J40: =SUM(J4:J39) -> 2345 | K40: =SUM(K4:K39) -> 20449 | L40: =SUM(L4:L39) -> 1858 | M40: =SUM(M4:M39) -> 31801 | N40: =SUM(N4:N39) -> 10243 | O40: =SUM(O4:O39) -> 21558 | P40: =SUM(P4:P39) -> 10525
A41: M36 | B41: =B39 -> 2854 | C41: =C39 -> 540 | D41: =D39 -> 51 | E41: =E39 -> 3445 | H41: =H39 -> 44 | I41: =I39 -> 505 | M41: =M39 -> 1939 | P41: =P39 -> 859 | Q41: =Q39 -> 11033

Sheet Expected
A1: EXPECTED SCENARIO
A3: Month | B3: Organic SEO | C3: YT Visitors | D3: IG Visitors | E3: TOTAL Visitors | F3: New Paid Subs | G3: Churn | H3: Total Paid Subs | I3: MRR ($) | J3: Per-Case Rev ($) | K3: Referral Rev ($) | L3: YT AdSense ($) | M3: Total Revenue ($) | N3: Total Costs ($) | O3: Gross Profit ($) | P3: Owner's Draw ($) | Q3: Reserve ($)
A4: 1 | B4: =Assumptions!B31 -> 500 | C4: =ROUND(IF(A4<Assumptions!B100,0,IF(A4<=8,Assumptions!B103,IF(A4<=12,Assumptions!B104,IF(A4<=18,Assumptions!B105,IF(A4<=24,Assumptions!B106,Assumptions!B107))))*(1+IF(A4>=Assumptions!B101,Assumptions!B109,0))*Assumptions!B111),0) -> 0 | D4: =ROUND(Assumptions!B119*Assumptions!B123,0) -> 1 | E4: =B4+C4+D4 -> 501 | F4: =ROUND(E4*Assumptions!B23,0) -> 1 | G4: 0 | H4: =F4 -> 1 | I4: =ROUND(H4*Assumptions!B14,0) -> 8 | J4: =ROUND(E4*Assumptions!B95*Assumptions!B96*Assumptions!B97*Assumptions!B94,0) -> 20 | K4: 0 | L4: =ROUND(IF(A4<Assumptions!B113,0,IF(A4<=18,Assumptions!B105,Assumptions!B107)/1000*Assumptions!B115*0.55+IF(A4>=Assumptions!B114,IF(A4<=18,Assumptions!B105,Assumptions!B107)*Assumptions!B109/1000*Assumptions!B116*0.55,0)),0) -> 0 | M4: =I4+J4+K4+L4 -> 28 | N4: =ROUND(H4*Assumptions!B62*Assumptions!B61,0)+Assumptions!B63+IF(H4>Assumptions!B64,45,0)+Assumptions!B65+Assumptions!B66+Assumptions!B67+Assumptions!B68+Assumptions!B69/12+IF(A4>=3,Assumptions!B72,0)+ROUND(I4*Assumptions!B70+H4*Assumptions!B71,0)+Assumptions!B75+Assumptions!B76+Assumptions!B77 -> 3367 | O4: =M4-N4 -> -3339 | P4: =IF(O4<N4*Assumptions!B89,0,IF(O4<N4*6,ROUND(MAX(O4,0)*Assumptions!B90,0),ROUND(MAX(O4,0)*Assumptions!B91,0))) -> 0 | Q4: =O4-P4 -> -3339
A5: 2 | B5: =ROUND(B4*(1+Assumptions!B35),0) -> 570 | C5: =ROUND(IF(A5<Assumptions!B100,0,IF(A5<=8,Assumptions!B103,IF(A5<=12,Assumptions!B104,IF(A5<=18,Assumptions!B105,IF(A5<=24,Assumptions!B106,Assumptions!B107))))*(1+IF(A5>=Assumptions!B101,Assumptions!B109,0))*Assumptions!B111),0) -> 0 | D5: =ROUND(ROUND(Assumptions!B119*(1+Assumptions!B120)^(A5-1),0)*Assumptions!B123,0) -> 1 | E5: =B5+C5+D5 -> 571 | F5: =ROUND(E5*Assumptions!B23,0) -> 1 | G5: =ROUND(H4*Assumptions!B51,0) -> 0 | H5: =H4+F5-G5 -> 2 | I5: =ROUND(H5*Assumptions!B14,0) -> 16 | J5: =ROUND(E5*Assumptions!B95*Assumptions!B96*Assumptions!B97*Assumptions!B94,0) -> 22 | K5: 0 | L5: =ROUND(IF(A5<Assumptions!B113,0,IF(A5<=18,Assumptions!B105,Assumptions!B107)/1000*Assumptions!B115*0.55+IF(A5>=Assumptions!B114,IF(A5<=18,Assumptions!B105,Assumptions!B107)*Assumptions!B109/1000*Assumptions!B116*0.55,0)),0) -> 0 | M5: =I5+J5+K5+L5 -> 38 | N5: =ROUND(H5*Assumptions!B62*Assumptions!B61,0)+Assumptions!B63+IF(H5>Assumptions!B64,45,0)+Assumptions!B65+Assumptions!B66+Assumptions!B67+Assumptions!B68+Assumptions!B69/12+IF(A5>=3,Assumptions!B72,0)+ROUND(I5*Assumptions!B70+H5*Assumptions!B71,0)+0 -> 118 | O5: =M5-N5 -> -80 | P5: =IF((Q4+O5)<N5*Assumptions!B89,0,IF((Q4+O5)<N5*6,ROUND(MAX(O5,0)*Assumptions!B90,0),ROUND(MAX(O5,0)*Assumptions!B91,0))) -> 0 | Q5: =Q4+O5-P5 -> -3419
A6: 3 | B6: =ROUND(B5*(1+Assumptions!B35)*Assumptions!B46,0) -> 747 | C6: =ROUND(IF(A6<Assumptions!B100,0,IF(A6<=8,Assumptions!B103,IF(A6<=12,Assumptions!B104,IF(A6<=18,Assumptions!B105,IF(A6<=24,Assumptions!B106,Assumptions!B107))))*(1+IF(A6>=Assumptions!B101,Assumptions!B109,0))*Assumptions!B111),0) -> 10 | D6: =ROUND(ROUND(Assumptions!B119*(1+Assumptions!B120)^(A6-1),0)*Assumptions!B123,0) -> 1 | E6: =B6+C6+D6 -> 758 | F6: =ROUND(E6*Assumptions!B23,0) -> 2 | G6: =ROUND(H5*Assumptions!B51,0) -> 0 | H6: =H5+F6-G6 -> 4 | I6: =ROUND(H6*Assumptions!B14,0) -> 32 | J6: =ROUND(E6*Assumptions!B95*Assumptions!B96*Assumptions!B97*Assumptions!B94,0) -> 30 | K6: 0 | L6: =ROUND(IF(A6<Assumptions!B113,0,IF(A6<=18,Assumptions!B105,Assumptions!B107)/1000*Assumptions!B115*0.55+IF(A6>=Assumptions!B114,IF(A6<=18,Assumptions!B105,Assumptions!B107)*Assumptions!B109/1000*Assumptions!B116*0.55,0)),0) -> 0 | M6: =I6+J6+K6+L6 -> 62 | N6: =ROUND(H6*Assumptions!B62*Assumptions!B61,0)+Assumptions!B63+IF(H6>Assumptions!B64,45,0)+Assumptions!B65+Assumptions!B66+Assumptions!B67+Assumptions!B68+Assumptions!B69/12+IF(A6>=3,Assumptions!B72,0)+ROUND(I6*Assumptions!B70+H6*Assumptions!B71,0)+0 -> 185 | O6: =M6-N6 -> -123 | P6: =IF((Q5+O6)<N6*Assumptions!B89,0,IF((Q5+O6)<N6*6,ROUND(MAX(O6,0)*Assumptions!B90,0),ROUND(MAX(O6,0)*Assumptions!B91,0))) -> 0 | Q6: =Q5+O6-P6 -> -3542
A7: 4 | B7: =ROUND(B6*(1+Assumptions!B35),0) -> 852 | C7: =ROUND(IF(A7<Assumptions!B100,0,IF(A7<=8,Assumptions!B103,IF(A7<=12,Assumptions!B104,IF(A7<=18,Assumptions!B105,IF(A7<=24,Assumptions!B106,Assumptions!B107))))*(1+IF(A7>=Assumptions!B101,Assumptions!B109,0))*Assumptions!B111),0) -> 10 | D7: =ROUND(ROUND(Assumptions!B119*(1+Assumptions!B120)^(A7-1),0)*Assumptions!B123,0) -> 1 | E7: =B7+C7+D7 -> 863 | F7: =ROUND(E7*Assumptions!B23,0) -> 2 | G7: =ROUND(H6*Assumptions!B51,0) -> 0 | H7: =H6+F7-G7 -> 6 | I7: =ROUND(H7*Assumptions!B14,0) -> 48 | J7: =ROUND(E7*Assumptions!B95*Assumptions!B96*Assumptions!B97*Assumptions!B94,0) -> 34 | K7: 0 | L7: =ROUND(IF(A7<Assumptions!B113,0,IF(A7<=18,Assumptions!B105,Assumptions!B107)/1000*Assumptions!B115*0.55+IF(A7>=Assumptions!B114,IF(A7<=18,Assumptions!B105,Assumptions!B107)*Assumptions!B109/1000*Assumptions!B116*0.55,0)),0) -> 0 | M7: =I7+J7+K7+L7 -> 82 | N7: =ROUND(H7*Assumptions!B62*Assumptions!B61,0)+Assumptions!B63+IF(H7>Assumptions!B64,45,0)+Assumptions!B65+Assumptions!B66+Assumptions!B67+Assumptions!B68+Assumptions!B69/12+IF(A7>=3,Assumptions!B72,0)+ROUND(I7*Assumptions!B70+H7*Assumptions!B71,0)+0 -> 187 | O7: =M7-N7 -> -105 | P7: =IF((Q6+O7)<N7*Assumptions!B89,0,IF((Q6+O7)<N7*6,ROUND(MAX(O7,0)*Assumptions!B90,0),ROUND(MAX(O7,0)*Assumptions!B91,0))) -> 0 | Q7: =Q6+O7-P7 -> -3647
A8: 5 | B8: =ROUND(B7*(1+Assumptions!B35),0) -> 971 | C8: =ROUND(IF(A8<Assumptions!B100,0,IF(A8<=8,Assumptions!B103,IF(A8<=12,Assumptions!B104,IF(A8<=18,Assumptions!B105,IF(A8<=24,Assumptions!B106,Assumptions!B107))))*(1+IF(A8>=Assumptions!B101,Assumptions!B109,0))*Assumptions!B111),0) -> 10 | D8: =ROUND(ROUND(Assumptions!B119*(1+Assumptions!B120)^(A8-1),0)*Assumptions!B123,0) -> 2 | E8: =B8+C8+D8 -> 983 | F8: =ROUND(E8*Assumptions!B23,0) -> 2 | G8: =ROUND(H7*Assumptions!B51,0) -> 0 | H8: =H7+F8-G8 -> 8 | I8: =ROUND(H8*Assumptions!B14,0) -> 64 | J8: =ROUND(E8*Assumptions!B95*Assumptions!B96*Assumptions!B97*Assumptions!B94,0) -> 38 | K8: 0 | L8: =ROUND(IF(A8<Assumptions!B113,0,IF(A8<=18,Assumptions!B105,Assumptions!B107)/1000*Assumptions!B115*0.55+IF(A8>=Assumptions!B114,IF(A8<=18,Assumptions!B105,Assumptions!B107)*Assumptions!B109/1000*Assumptions!B116*0.55,0)),0) -> 0 | M8: =I8+J8+K8+L8 -> 102 | N8: =ROUND(H8*Assumptions!B62*Assumptions!B61,0)+Assumptions!B63+IF(H8>Assumptions!B64,45,0)+Assumptions!B65+Assumptions!B66+Assumptions!B67+Assumptions!B68+Assumptions!B69/12+IF(A8>=3,Assumptions!B72,0)+ROUND(I8*Assumptions!B70+H8*Assumptions!B71,0)+0 -> 188 | O8: =M8-N8 -> -86 | P8: =IF((Q7+O8)<N8*Assumptions!B89,0,IF((Q7+O8)<N8*6,ROUND(MAX(O8,0)*Assumptions!B90,0),ROUND(MAX(O8,0)*Assumptions!B91,0))) -> 0 | Q8: =Q7+O8-P8 -> -3733
A9: 6 | B9: =ROUND(B8*(1+Assumptions!B35)*Assumptions!B47,0) -> 1195 | C9: =ROUND(IF(A9<Assumptions!B100,0,IF(A9<=8,Assumptions!B103,IF(A9<=12,Assumptions!B104,IF(A9<=18,Assumptions!B105,IF(A9<=24,Assumptions!B106,Assumptions!B107))))*(1+IF(A9>=Assumptions!B101,Assumptions!B109,0))*Assumptions!B111),0) -> 10 | D9: =ROUND(ROUND(Assumptions!B119*(1+Assumptions!B120)^(A9-1),0)*Assumptions!B123,0) -> 2 | E9: =B9+C9+D9 -> 1207 | F9: =ROUND(E9*Assumptions!B23,0) -> 3 | G9: =ROUND(H8*Assumptions!B51,0) -> 1 | H9: =H8+F9-G9 -> 10 | I9: =ROUND(H9*Assumptions!B14,0) -> 80 | J9: =ROUND(E9*Assumptions!B95*Assumptions!B96*Assumptions!B97*Assumptions!B94,0) -> 47 | K9: =ROUND(E9*Assumptions!B57*Assumptions!B58,0) -> 422 | L9: =ROUND(IF(A9<Assumptions!B113,0,IF(A9<=18,Assumptions!B105,Assumptions!B107)/1000*Assumptions!B115*0.55+IF(A9>=Assumptions!B114,IF(A9<=18,Assumptions!B105,Assumptions!B107)*Assumptions!B109/1000*Assumptions!B116*0.55,0)),0) -> 0 | M9: =I9+J9+K9+L9 -> 549 | N9: =ROUND(H9*Assumptions!B62*Assumptions!B61,0)+Assumptions!B63+IF(H9>Assumptions!B64,45,0)+Assumptions!B65+Assumptions!B66+Assumptions!B67+Assumptions!B68+Assumptions!B69/12+IF(A9>=3,Assumptions!B72,0)+ROUND(I9*Assumptions!B70+H9*Assumptions!B71,0)+0 -> 190 | O9: =M9-N9 -> 359 | P9: =IF((Q8+O9)<N9*Assumptions!B89,0,IF((Q8+O9)<N9*6,ROUND(MAX(O9,0)*Assumptions!B90,0),ROUND(MAX(O9,0)*Assumptions!B91,0))) -> 0 | Q9: =Q8+O9-P9 -> -3374
A10: 7 | B10: =ROUND(B9*(1+Assumptions!B35),0) -> 1362 | C10: =ROUND(IF(A10<Assumptions!B100,0,IF(A10<=8,Assumptions!B103,IF(A10<=12,Assumptions!B104,IF(A10<=18,Assumptions!B105,IF(A10<=24,Assumptions!B106,Assumptions!B107))))*(1+IF(A10>=Assumptions!B101,Assumptions!B109,0))*Assumptions!B111),0) -> 10 | D10: =ROUND(ROUND(Assumptions!B119*(1+Assumptions!B120)^6*(1+Assumptions!B121)^(A10-6),0)*Assumptions!B123,0) -> 3 | E10: =B10+C10+D10 -> 1375 | F10: =ROUND(E10*Assumptions!B23,0) -> 3 | G10: =ROUND(H9*Assumptions!B51,0) -> 1 | H10: =H9+F10-G10 -> 12 | I10: =ROUND(H10*Assumptions!B14,0) -> 96 | J10: =ROUND(E10*Assumptions!B95*Assumptions!B96*Assumptions!B97*Assumptions!B94,0) -> 54 | K10: =ROUND(E10*Assumptions!B57*Assumptions!B58,0) -> 481 | L10: =ROUND(IF(A10<Assumptions!B113,0,IF(A10<=18,Assumptions!B105,Assumptions!B107)/1000*Assumptions!B115*0.55+IF(A10>=Assumptions!B114,IF(A10<=18,Assumptions!B105,Assumptions!B107)*Assumptions!B109/1000*Assumptions!B116*0.55,0)),0) -> 0 | M10: =I10+J10+K10+L10 -> 631 | N10: =ROUND(H10*Assumptions!B62*Assumptions!B61,0)+Assumptions!B63+IF(H10>Assumptions!B64,45,0)+Assumptions!B65+Assumptions!B66+Assumptions!B67+Assumptions!B68+Assumptions!B69/12+IF(A10>=3,Assumptions!B72,0)+ROUND(I10*Assumptions!B70+H10*Assumptions!B71,0)+0 -> 191 | O10: =M10-N10 -> 440 | P10: =IF((Q9+O10)<N10*Assumptions!B89,0,IF((Q9+O10)<N10*6,ROUND(MAX(O10,0)*Assumptions!B90,0),ROUND(MAX(O10,0)*Assumptions!B91,0))) -> 0 | Q10: =Q9+O10-P10 -> -2934
A11: 8 | B11: =ROUND(B10*(1+Assumptions!B35),0) -> 1553 | C11: =ROUND(IF(A11<Assumptions!B100,0,IF(A11<=8,Assumptions!B103,IF(A11<=12,Assumptions!B104,IF(A11<=18,Assumptions!B105,IF(A11<=24,Assumptions!B106,Assumptions!B107))))*(1+IF(A11>=Assumptions!B101,Assumptions!B109,0))*Assumptions!B111),0) -> 10 | D11: =ROUND(ROUND(Assumptions!B119*(1+Assumptions!B120)^6*(1+Assumptions!B121)^(A11-6),0)*Assumptions!B123,0) -> 3 | E11: =B11+C11+D11 -> 1566 | F11: =ROUND(E11*Assumptions!B23,0) -> 4 | G11: =ROUND(H10*Assumptions!B51,0) -> 1 | H11: =H10+F11-G11 -> 15 | I11: =ROUND(H11*Assumptions!B14,0) -> 120 | J11: =ROUND(E11*Assumptions!B95*Assumptions!B96*Assumptions!B97*Assumptions!B94,0) -> 61 | K11: =ROUND(E11*Assumptions!B57*Assumptions!B58,0) -> 548 | L11: =ROUND(IF(A11<Assumptions!B113,0,IF(A11<=18,Assumptions!B105,Assumptions!B107)/1000*Assumptions!B115*0.55+IF(A11>=Assumptions!B114,IF(A11<=18,Assumptions!B105,Assumptions!B107)*Assumptions!B109/1000*Assumptions!B116*0.55,0)),0) -> 0 | M11: =I11+J11+K11+L11 -> 729 | N11: =ROUND(H11*Assumptions!B62*Assumptions!B61,0)+Assumptions!B63+IF(H11>Assumptions!B64,45,0)+Assumptions!B65+Assumptions!B66+Assumptions!B67+Assumptions!B68+Assumptions!B69/12+IF(A11>=3,Assumptions!B72,0)+ROUND(I11*Assumptions!B70+H11*Assumptions!B71,0)+0 -> 194 | O11: =M11-N11 -> 535 | P11: =IF((Q10+O11)<N11*Assumptions!B89,0,IF((Q10+O11)<N11*6,ROUND(MAX(O11,0)*Assumptions!B90,0),ROUND(MAX(O11,0)*Assumptions!B91,0))) -> 0 | Q11: =Q10+O11-P11 -> -2399
A12: 9 | B12: =ROUND(B11*(1+Assumptions!B35),0) -> 1770 | C12: =ROUND(IF(A12<Assumptions!B100,0,IF(A12<=8,Assumptions!B103,IF(A12<=12,Assumptions!B104,IF(A12<=18,Assumptions!B105,IF(A12<=24,Assumptions!B106,Assumptions!B107))))*(1+IF(A12>=Assumptions!B101,Assumptions!B109,0))*Assumptions!B111),0) -> 60 | D12: =ROUND(ROUND(Assumptions!B119*(1+Assumptions!B120)^6*(1+Assumptions!B121)^(A12-6),0)*Assumptions!B123,0) -> 3 | E12: =B12+C12+D12 -> 1833 | F12: =ROUND(E12*Assumptions!B23,0) -> 5 | G12: =ROUND(H11*Assumptions!B51,0) -> 1 | H12: =H11+F12-G12 -> 19 | I12: =ROUND(H12*((Assumptions!B14+Assumptions!B15)/2),0) -> 200 | J12: =ROUND(E12*Assumptions!B95*Assumptions!B96*Assumptions!B97*Assumptions!B94,0) -> 71 | K12: =ROUND(E12*Assumptions!B57*Assumptions!B58,0) -> 642 | L12: =ROUND(IF(A12<Assumptions!B113,0,IF(A12<=18,Assumptions!B105,Assumptions!B107)/1000*Assumptions!B115*0.55+IF(A12>=Assumptions!B114,IF(A12<=18,Assumptions!B105,Assumptions!B107)*Assumptions!B109/1000*Assumptions!B116*0.55,0)),0) -> 0 | M12: =I12+J12+K12+L12 -> 913 | N12: =ROUND(H12*Assumptions!B62*Assumptions!B61,0)+Assumptions!B63+IF(H12>Assumptions!B64,45,0)+Assumptions!B65+Assumptions!B66+Assumptions!B67+Assumptions!B68+Assumptions!B69/12+IF(A12>=3,Assumptions!B72,0)+ROUND(I12*Assumptions!B70+H12*Assumptions!B71,0)+0 -> 199 | O12: =M12-N12 -> 714 | P12: =IF((Q11+O12)<N12*Assumptions!B89,0,IF((Q11+O12)<N12*6,ROUND(MAX(O12,0)*Assumptions!B90,0),ROUND(MAX(O12,0)*Assumptions!B91,0))) -> 0 | Q12: =Q11+O12-P12 -> -1685
A13: 10 | B13: =ROUND(B12*(1+Assumptions!B35),0) -> 2018 | C13: =ROUND(IF(A13<Assumptions!B100,0,IF(A13<=8,Assumptions!B103,IF(A13<=12,Assumptions!B104,IF(A13<=18,Assumptions!B105,IF(A13<=24,Assumptions!B106,Assumptions!B107))))*(1+IF(A13>=Assumptions!B101,Assumptions!B109,0))*Assumptions!B111),0) -> 60 | D13: =ROUND(ROUND(Assumptions!B119*(1+Assumptions!B120)^6*(1+Assumptions!B121)^(A13-6),0)*Assumptions!B123,0) -> 4 | E13: =B13+C13+D13 -> 2082 | F13: =ROUND(E13*Assumptions!B23,0) -> 5 | G13: =ROUND(H12*Assumptions!B51,0) -> 1 | H13: =H12+F13-G13 -> 23 | I13: =ROUND(H13*(Assumptions!B15*0.85+Assumptions!B11*0.15),0) -> 264 | J13: =ROUND(E13*Assumptions!B95*Assumptions!B96*Assumptions!B97*Assumptions!B94,0) -> 81 | K13: =ROUND(E13*Assumptions!B57*Assumptions!B58,0) -> 729 | L13: =ROUND(IF(A13<Assumptions!B113,0,IF(A13<=18,Assumptions!B105,Assumptions!B107)/1000*Assumptions!B115*0.55+IF(A13>=Assumptions!B114,IF(A13<=18,Assumptions!B105,Assumptions!B107)*Assumptions!B109/1000*Assumptions!B116*0.55,0)),0) -> 0 | M13: =I13+J13+K13+L13 -> 1074 | N13: =ROUND(H13*Assumptions!B62*Assumptions!B61,0)+Assumptions!B63+IF(H13>Assumptions!B64,45,0)+Assumptions!B65+Assumptions!B66+Assumptions!B67+Assumptions!B68+Assumptions!B69/12+IF(A13>=3,Assumptions!B72,0)+ROUND(I13*Assumptions!B70+H13*Assumptions!B71,0)+0 -> 203 | O13: =M13-N13 -> 871 | P13: =IF((Q12+O13)<N13*Assumptions!B89,0,IF((Q12+O13)<N13*6,ROUND(MAX(O13,0)*Assumptions!B90,0),ROUND(MAX(O13,0)*Assumptions!B91,0))) -> 0 | Q13: =Q12+O13-P13 -> -814
A14: 11 | B14: =ROUND(B13*(1+Assumptions!B35),0) -> 2301 | C14: =ROUND(IF(A14<Assumptions!B100,0,IF(A14<=8,Assumptions!B103,IF(A14<=12,Assumptions!B104,IF(A14<=18,Assumptions!B105,IF(A14<=24,Assumptions!B106,Assumptions!B107))))*(1+IF(A14>=Assumptions!B101,Assumptions!B109,0))*Assumptions!B111),0) -> 60 | D14: =ROUND(ROUND(Assumptions!B119*(1+Assumptions!B120)^6*(1+Assumptions!B121)^(A14-6),0)*Assumptions!B123,0) -> 5 | E14: =B14+C14+D14 -> 2366 | F14: =ROUND(E14*Assumptions!B23,0) -> 6 | G14: =ROUND(H13*Assumptions!B51,0) -> 2 | H14: =H13+F14-G14 -> 27 | I14: =ROUND(H14*(Assumptions!B15*0.85+Assumptions!B11*0.15),0) -> 310 | J14: =ROUND(E14*Assumptions!B95*Assumptions!B96*Assumptions!B97*Assumptions!B94,0) -> 92 | K14: =ROUND(E14*Assumptions!B57*Assumptions!B58,0) -> 828 | L14: =ROUND(IF(A14<Assumptions!B113,0,IF(A14<=18,Assumptions!B105,Assumptions!B107)/1000*Assumptions!B115*0.55+IF(A14>=Assumptions!B114,IF(A14<=18,Assumptions!B105,Assumptions!B107)*Assumptions!B109/1000*Assumptions!B116*0.55,0)),0) -> 0 | M14: =I14+J14+K14+L14 -> 1230 | N14: =ROUND(H14*Assumptions!B62*Assumptions!B61,0)+Assumptions!B63+IF(H14>Assumptions!B64,45,0)+Assumptions!B65+Assumptions!B66+Assumptions!B67+Assumptions!B68+Assumptions!B69/12+IF(A14>=3,Assumptions!B72,0)+ROUND(I14*Assumptions!B70+H14*Assumptions!B71,0)+0 -> 207 | O14: =M14-N14 -> 1023 | P14: =IF((Q13+O14)<N14*Assumptions!B89,0,IF((Q13+O14)<N14*6,ROUND(MAX(O14,0)*Assumptions!B90,0),ROUND(MAX(O14,0)*Assumptions!B91,0))) -> 0 | Q14: =Q13+O14-P14 -> 209
A15: 12 | B15: =ROUND(B14*(1+Assumptions!B35),0) -> 2623 | C15: =ROUND(IF(A15<Assumptions!B100,0,IF(A15<=8,Assumptions!B103,IF(A15<=12,Assumptions!B104,IF(A15<=18,Assumptions!B105,IF(A15<=24,Assumptions!B106,Assumptions!B107))))*(1+IF(A15>=Assumptions!B101,Assumptions!B109,0))*Assumptions!B111),0) -> 60 | D15: =ROUND(ROUND(Assumptions!B119*(1+Assumptions!B120)^6*(1+Assumptions!B121)^(A15-6),0)*Assumptions!B123,0) -> 5 | E15: =B15+C15+D15 -> 2688 | F15: =ROUND(E15*Assumptions!B23,0) -> 7 | G15: =ROUND(H14*Assumptions!B51,0) -> 2 | H15: =H14+F15-G15 -> 32 | I15: =ROUND(H15*(Assumptions!B15*0.85+Assumptions!B11*0.15),0) -> 367 | J15: =ROUND(E15*Assumptions!B95*Assumptions!B96*Assumptions!B97*Assumptions!B94,0) -> 105 | K15: =ROUND(E15*Assumptions!B57*Assumptions!B58,0) -> 941 | L15: =ROUND(IF(A15<Assumptions!B113,0,IF(A15<=18,Assumptions!B105,Assumptions!B107)/1000*Assumptions!B115*0.55+IF(A15>=Assumptions!B114,IF(A15<=18,Assumptions!B105,Assumptions!B107)*Assumptions!B109/1000*Assumptions!B116*0.55,0)),0) -> 22 | M15: =I15+J15+K15+L15 -> 1435 | N15: =ROUND(H15*Assumptions!B62*Assumptions!B61,0)+Assumptions!B63+IF(H15>Assumptions!B64,45,0)+Assumptions!B65+Assumptions!B66+Assumptions!B67+Assumptions!B68+Assumptions!B69/12+IF(A15>=3,Assumptions!B72,0)+ROUND(I15*Assumptions!B70+H15*Assumptions!B71,0)+0 -> 211 | O15: =M15-N15 -> 1224 | P15: =IF((Q14+O15)<N15*Assumptions!B89,0,IF((Q14+O15)<N15*6,ROUND(MAX(O15,0)*Assumptions!B90,0),ROUND(MAX(O15,0)*Assumptions!B91,0))) -> 612 | Q15: =Q14+O15-P15 -> 821
A16: 13 | B16: =ROUND(B15*(1+Assumptions!B39),0) -> 2859 | C16: =ROUND(IF(A16<Assumptions!B100,0,IF(A16<=8,Assumptions!B103,IF(A16<=12,Assumptions!B104,IF(A16<=18,Assumptions!B105,IF(A16<=24,Assumptions!B106,Assumptions!B107))))*(1+IF(A16>=Assumptions!B101,Assumptions!B109,0))*Assumptions!B111),0) -> 150 | D16: =ROUND(ROUND(Assumptions!B119*(1+Assumptions!B120)^6*(1+Assumptions!B121)^6*(1+Assumptions!B122)^(A16-12),0)*Assumptions!B123,0) -> 6 | E16: =B16+C16+D16 -> 3015 | F16: =ROUND(E16*Assumptions!B23,0) -> 8 | G16: =ROUND(H15*Assumptions!B51,0) -> 2 | H16: =H15+F16-G16 -> 38 | I16: =ROUND(H16*(Assumptions!B15*0.85+Assumptions!B11*0.15),0) -> 436 | J16: =ROUND(E16*Assumptions!B95*Assumptions!B96*Assumptions!B97*Assumptions!B94,0) -> 118 | K16: =ROUND(E16*Assumptions!B57*Assumptions!B58,0) -> 1055 | L16: =ROUND(IF(A16<Assumptions!B113,0,IF(A16<=18,Assumptions!B105,Assumptions!B107)/1000*Assumptions!B115*0.55+IF(A16>=Assumptions!B114,IF(A16<=18,Assumptions!B105,Assumptions!B107)*Assumptions!B109/1000*Assumptions!B116*0.55,0)),0) -> 22 | M16: =I16+J16+K16+L16 -> 1631 | N16: =ROUND(H16*Assumptions!B62*Assumptions!B61,0)+Assumptions!B63+IF(H16>Assumptions!B64,45,0)+Assumptions!B65+Assumptions!B66+Assumptions!B67+Assumptions!B68+Assumptions!B69/12+IF(A16>=3,Assumptions!B72,0)+ROUND(I16*Assumptions!B70+H16*Assumptions!B71,0)+0 -> 217 | O16: =M16-N16 -> 1414 | P16: =IF((Q15+O16)<N16*Assumptions!B89,0,IF((Q15+O16)<N16*6,ROUND(MAX(O16,0)*Assumptions!B90,0),ROUND(MAX(O16,0)*Assumptions!B91,0))) -> 707 | Q16: =Q15+O16-P16 -> 1528
A17: 14 | B17: =ROUND(B16*(1+Assumptions!B39),0) -> 3116 | C17: =ROUND(IF(A17<Assumptions!B100,0,IF(A17<=8,Assumptions!B103,IF(A17<=12,Assumptions!B104,IF(A17<=18,Assumptions!B105,IF(A17<=24,Assumptions!B106,Assumptions!B107))))*(1+IF(A17>=Assumptions!B101,Assumptions!B109,0))*Assumptions!B111),0) -> 150 | D17: =ROUND(ROUND(Assumptions!B119*(1+Assumptions!B120)^6*(1+Assumptions!B121)^6*(1+Assumptions!B122)^(A17-12),0)*Assumptions!B123,0) -> 6 | E17: =B17+C17+D17 -> 3272 | F17: =ROUND(E17*Assumptions!B23,0) -> 8 | G17: =ROUND(H16*Assumptions!B51,0) -> 3 | H17: =H16+F17-G17 -> 43 | I17: =ROUND(H17*(Assumptions!B15*0.85+Assumptions!B11*0.15),0) -> 493 | J17: =ROUND(E17*Assumptions!B95*Assumptions!B96*Assumptions!B97*Assumptions!B94,0) -> 128 | K17: =ROUND(E17*Assumptions!B57*Assumptions!B58,0) -> 1145 | L17: =ROUND(IF(A17<Assumptions!B113,0,IF(A17<=18,Assumptions!B105,Assumptions!B107)/1000*Assumptions!B115*0.55+IF(A17>=Assumptions!B114,IF(A17<=18,Assumptions!B105,Assumptions!B107)*Assumptions!B109/1000*Assumptions!B116*0.55,0)),0) -> 22 | M17: =I17+J17+K17+L17 -> 1788 | N17: =ROUND(H17*Assumptions!B62*Assumptions!B61,0)+Assumptions!B63+IF(H17>Assumptions!B64,45,0)+Assumptions!B65+Assumptions!B66+Assumptions!B67+Assumptions!B68+Assumptions!B69/12+IF(A17>=3,Assumptions!B72,0)+ROUND(I17*Assumptions!B70+H17*Assumptions!B71,0)+0 -> 221 | O17: =M17-N17 -> 1567 | P17: =IF((Q16+O17)<N17*Assumptions!B89,0,IF((Q16+O17)<N17*6,ROUND(MAX(O17,0)*Assumptions!B90,0),ROUND(MAX(O17,0)*Assumptions!B91,0))) -> 784 | Q17: =Q16+O17-P17 -> 2311
A18: 15 | B18: =ROUND(B17*(1+Assumptions!B39),0) -> 3396 | C18: =ROUND(IF(A18<Assumptions!B100,0,IF(A18<=8,Assumptions!B103,IF(A18<=12,Assumptions!B104,IF(A18<=18,Assumptions!B105,IF(A18<=24,Assumptions!B106,Assumptions!B107))))*(1+IF(A18>=Assumptions!B101,Assumptions!B109,0))*Assumptions!B111),0) -> 150 | D18: =ROUND(ROUND(Assumptions!B119*(1+Assumptions!B120)^6*(1+Assumptions!B121)^6*(1+Assumptions!B122)^(A18-12),0)*Assumptions!B123,0) -> 7 | E18: =B18+C18+D18 -> 3553 | F18: =ROUND(E18*Assumptions!B23,0) -> 9 | G18: =ROUND(H17*Assumptions!B51,0) -> 3 | H18: =H17+F18-G18 -> 49 | I18: =ROUND(H18*(Assumptions!B15*0.85+Assumptions!B11*0.15),0) -> 562 | J18: =ROUND(E18*Assumptions!B95*Assumptions!B96*Assumptions!B97*Assumptions!B94,0) -> 139 | K18: =ROUND(E18*Assumptions!B57*Assumptions!B58,0) -> 1244 | L18: =ROUND(IF(A18<Assumptions!B113,0,IF(A18<=18,Assumptions!B105,Assumptions!B107)/1000*Assumptions!B115*0.55+IF(A18>=Assumptions!B114,IF(A18<=18,Assumptions!B105,Assumptions!B107)*Assumptions!B109/1000*Assumptions!B116*0.55,0)),0) -> 22 | M18: =I18+J18+K18+L18 -> 1967 | N18: =ROUND(H18*Assumptions!B62*Assumptions!B61,0)+Assumptions!B63+IF(H18>Assumptions!B64,45,0)+Assumptions!B65+Assumptions!B66+Assumptions!B67+Assumptions!B68+Assumptions!B69/12+IF(A18>=3,Assumptions!B72,0)+ROUND(I18*Assumptions!B70+H18*Assumptions!B71,0)+0 -> 227 | O18: =M18-N18 -> 1740 | P18: =IF((Q17+O18)<N18*Assumptions!B89,0,IF((Q17+O18)<N18*6,ROUND(MAX(O18,0)*Assumptions!B90,0),ROUND(MAX(O18,0)*Assumptions!B91,0))) -> 870 | Q18: =Q17+O18-P18 -> 3181
A19: 16 | B19: =ROUND(B18*(1+Assumptions!B39),0) -> 3702 | C19: =ROUND(IF(A19<Assumptions!B100,0,IF(A19<=8,Assumptions!B103,IF(A19<=12,Assumptions!B104,IF(A19<=18,Assumptions!B105,IF(A19<=24,Assumptions!B106,Assumptions!B107))))*(1+IF(A19>=Assumptions!B101,Assumptions!B109,0))*Assumptions!B111),0) -> 150 | D19: =ROUND(ROUND(Assumptions!B119*(1+Assumptions!B120)^6*(1+Assumptions!B121)^6*(1+Assumptions!B122)^(A19-12),0)*Assumptions!B123,0) -> 8 | E19: =B19+C19+D19 -> 3860 | F19: =ROUND(E19*Assumptions!B23,0) -> 10 | G19: =ROUND(H18*Assumptions!B51,0) -> 3 | H19: =H18+F19-G19 -> 56 | I19: =ROUND(H19*(Assumptions!B15*0.85+Assumptions!B11*0.15),0) -> 643 | J19: =ROUND(E19*Assumptions!B95*Assumptions!B96*Assumptions!B97*Assumptions!B94,0) -> 151 | K19: =ROUND(E19*Assumptions!B57*Assumptions!B58,0) -> 1351 | L19: =ROUND(IF(A19<Assumptions!B113,0,IF(A19<=18,Assumptions!B105,Assumptions!B107)/1000*Assumptions!B115*0.55+IF(A19>=Assumptions!B114,IF(A19<=18,Assumptions!B105,Assumptions!B107)*Assumptions!B109/1000*Assumptions!B116*0.55,0)),0) -> 26 | M19: =I19+J19+K19+L19 -> 2171 | N19: =ROUND(H19*Assumptions!B62*Assumptions!B61,0)+Assumptions!B63+IF(H19>Assumptions!B64,45,0)+Assumptions!B65+Assumptions!B66+Assumptions!B67+Assumptions!B68+Assumptions!B69/12+IF(A19>=3,Assumptions!B72,0)+ROUND(I19*Assumptions!B70+H19*Assumptions!B71,0)+0 -> 233 | O19: =M19-N19 -> 1938 | P19: =IF((Q18+O19)<N19*Assumptions!B89,0,IF((Q18+O19)<N19*6,ROUND(MAX(O19,0)*Assumptions!B90,0),ROUND(MAX(O19,0)*Assumptions!B91,0))) -> 969 | Q19: =Q18+O19-P19 -> 4150
A20: 17 | B20: =ROUND(B19*(1+Assumptions!B39),0) -> 4035 | C20: =ROUND(IF(A20<Assumptions!B100,0,IF(A20<=8,Assumptions!B103,IF(A20<=12,Assumptions!B104,IF(A20<=18,Assumptions!B105,IF(A20<=24,Assumptions!B106,Assumptions!B107))))*(1+IF(A20>=Assumptions!B101,Assumptions!B109,0))*Assumptions!B111),0) -> 150 | D20: =ROUND(ROUND(Assumptions!B119*(1+Assumptions!B120)^6*(1+Assumptions!B121)^6*(1+Assumptions!B122)^(A20-12),0)*Assumptions!B123,0) -> 8 | E20: =B20+C20+D20 -> 4193 | F20: =ROUND(E20*Assumptions!B23,0) -> 10 | G20: =ROUND(H19*Assumptions!B51,0) -> 4 | H20: =H19+F20-G20 -> 62 | I20: =ROUND(H20*(Assumptions!B15*0.85+Assumptions!B11*0.15),0) -> 711 | J20: =ROUND(E20*Assumptions!B95*Assumptions!B96*Assumptions!B97*Assumptions!B94,0) -> 164 | K20: =ROUND(E20*Assumptions!B57*Assumptions!B58,0) -> 1468 | L20: =ROUND(IF(A20<Assumptions!B113,0,IF(A20<=18,Assumptions!B105,Assumptions!B107)/1000*Assumptions!B115*0.55+IF(A20>=Assumptions!B114,IF(A20<=18,Assumptions!B105,Assumptions!B107)*Assumptions!B109/1000*Assumptions!B116*0.55,0)),0) -> 26 | M20: =I20+J20+K20+L20 -> 2369 | N20: =ROUND(H20*Assumptions!B62*Assumptions!B61,0)+Assumptions!B63+IF(H20>Assumptions!B64,45,0)+Assumptions!B65+Assumptions!B66+Assumptions!B67+Assumptions!B68+Assumptions!B69/12+IF(A20>=3,Assumptions!B72,0)+ROUND(I20*Assumptions!B70+H20*Assumptions!B71,0)+0 -> 238 | O20: =M20-N20 -> 2131 | P20: =IF((Q19+O20)<N20*Assumptions!B89,0,IF((Q19+O20)<N20*6,ROUND(MAX(O20,0)*Assumptions!B90,0),ROUND(MAX(O20,0)*Assumptions!B91,0))) -> 1066 | Q20: =Q19+O20-P20 -> 5215
A21: 18 | B21: =ROUND(B20*(1+Assumptions!B39),0) -> 4398 | C21: =ROUND(IF(A21<Assumptions!B100,0,IF(A21<=8,Assumptions!B103,IF(A21<=12,Assumptions!B104,IF(A21<=18,Assumptions!B105,IF(A21<=24,Assumptions!B106,Assumptions!B107))))*(1+IF(A21>=Assumptions!B101,Assumptions!B109,0))*Assumptions!B111),0) -> 150 | D21: =ROUND(ROUND(Assumptions!B119*(1+Assumptions!B120)^6*(1+Assumptions!B121)^6*(1+Assumptions!B122)^(A21-12),0)*Assumptions!B123,0) -> 9 | E21: =B21+C21+D21 -> 4557 | F21: =ROUND(E21*Assumptions!B23,0) -> 11 | G21: =ROUND(H20*Assumptions!B51,0) -> 4 | H21: =H20+F21-G21 -> 69 | I21: =ROUND(H21*(Assumptions!B15*0.85+Assumptions!B11*0.15),0) -> 792 | J21: =ROUND(E21*Assumptions!B95*Assumptions!B96*Assumptions!B97*Assumptions!B94,0) -> 178 | K21: =ROUND(E21*Assumptions!B57*Assumptions!B58,0) -> 1595 | L21: =ROUND(IF(A21<Assumptions!B113,0,IF(A21<=18,Assumptions!B105,Assumptions!B107)/1000*Assumptions!B115*0.55+IF(A21>=Assumptions!B114,IF(A21<=18,Assumptions!B105,Assumptions!B107)*Assumptions!B109/1000*Assumptions!B116*0.55,0)),0) -> 26 | M21: =I21+J21+K21+L21 -> 2591 | N21: =ROUND(H21*Assumptions!B62*Assumptions!B61,0)+Assumptions!B63+IF(H21>Assumptions!B64,45,0)+Assumptions!B65+Assumptions!B66+Assumptions!B67+Assumptions!B68+Assumptions!B69/12+IF(A21>=3,Assumptions!B72,0)+ROUND(I21*Assumptions!B70+H21*Assumptions!B71,0)+0 -> 245 | O21: =M21-N21 -> 2346 | P21: =IF((Q20+O21)<N21*Assumptions!B89,0,IF((Q20+O21)<N21*6,ROUND(MAX(O21,0)*Assumptions!B90,0),ROUND(MAX(O21,0)*Assumptions!B91,0))) -> 1173 | Q21: =Q20+O21-P21 -> 6388
A22: 19 | B22: =ROUND(B21*(1+Assumptions!B39),0) -> 4794 | C22: =ROUND(IF(A22<Assumptions!B100,0,IF(A22<=8,Assumptions!B103,IF(A22<=12,Assumptions!B104,IF(A22<=18,Assumptions!B105,IF(A22<=24,Assumptions!B106,Assumptions!B107))))*(1+IF(A22>=Assumptions!B101,Assumptions!B109,0))*Assumptions!B111),0) -> 300 | D22: =ROUND(ROUND(Assumptions!B119*(1+Assumptions!B120)^6*(1+Assumptions!B121)^6*(1+Assumptions!B122)^(A22-12),0)*Assumptions!B123,0) -> 10 | E22: =B22+C22+D22 -> 5104 | F22: =ROUND(E22*Assumptions!B23,0) -> 13 | G22: =ROUND(H21*Assumptions!B51,0) -> 5 | H22: =H21+F22-G22 -> 77 | I22: =ROUND(H22*(Assumptions!B15*0.85+Assumptions!B11*0.15),0) -> 884 | J22: =ROUND(E22*Assumptions!B95*Assumptions!B96*Assumptions!B97*Assumptions!B94,0) -> 199 | K22: =ROUND(E22*Assumptions!B57*Assumptions!B58,0) -> 1786 | L22: =ROUND(IF(A22<Assumptions!B113,0,IF(A22<=18,Assumptions!B105,Assumptions!B107)/1000*Assumptions!B115*0.55+IF(A22>=Assumptions!B114,IF(A22<=18,Assumptions!B105,Assumptions!B107)*Assumptions!B109/1000*Assumptions!B116*0.55,0)),0) -> 94 | M22: =I22+J22+K22+L22 -> 2963 | N22: =ROUND(H22*Assumptions!B62*Assumptions!B61,0)+Assumptions!B63+IF(H22>Assumptions!B64,45,0)+Assumptions!B65+Assumptions!B66+Assumptions!B67+Assumptions!B68+Assumptions!B69/12+IF(A22>=3,Assumptions!B72,0)+ROUND(I22*Assumptions!B70+H22*Assumptions!B71,0)+0 -> 253 | O22: =M22-N22 -> 2710 | P22: =IF((Q21+O22)<N22*Assumptions!B89,0,IF((Q21+O22)<N22*6,ROUND(MAX(O22,0)*Assumptions!B90,0),ROUND(MAX(O22,0)*Assumptions!B91,0))) -> 1355 | Q22: =Q21+O22-P22 -> 7743
A23: 20 | B23: =ROUND(B22*(1+Assumptions!B39),0) -> 5225 | C23: =ROUND(IF(A23<Assumptions!B100,0,IF(A23<=8,Assumptions!B103,IF(A23<=12,Assumptions!B104,IF(A23<=18,Assumptions!B105,IF(A23<=24,Assumptions!B106,Assumptions!B107))))*(1+IF(A23>=Assumptions!B101,Assumptions!B109,0))*Assumptions!B111),0) -> 300 | D23: =ROUND(ROUND(Assumptions!B119*(1+Assumptions!B120)^6*(1+Assumptions!B121)^6*(1+Assumptions!B122)^(A23-12),0)*Assumptions!B123,0) -> 11 | E23: =B23+C23+D23 -> 5536 | F23: =ROUND(E23*Assumptions!B23,0) -> 14 | G23: =ROUND(H22*Assumptions!B51,0) -> 5 | H23: =H22+F23-G23 -> 86 | I23: =ROUND(H23*(Assumptions!B15*0.85+Assumptions!B11*0.15),0) -> 987 | J23: =ROUND(E23*Assumptions!B95*Assumptions!B96*Assumptions!B97*Assumptions!B94,0) -> 216 | K23: =ROUND(E23*Assumptions!B57*Assumptions!B58,0) -> 1938 | L23: =ROUND(IF(A23<Assumptions!B113,0,IF(A23<=18,Assumptions!B105,Assumptions!B107)/1000*Assumptions!B115*0.55+IF(A23>=Assumptions!B114,IF(A23<=18,Assumptions!B105,Assumptions!B107)*Assumptions!B109/1000*Assumptions!B116*0.55,0)),0) -> 94 | M23: =I23+J23+K23+L23 -> 3235 | N23: =ROUND(H23*Assumptions!B62*Assumptions!B61,0)+Assumptions!B63+IF(H23>Assumptions!B64,45,0)+Assumptions!B65+Assumptions!B66+Assumptions!B67+Assumptions!B68+Assumptions!B69/12+IF(A23>=3,Assumptions!B72,0)+ROUND(I23*Assumptions!B70+H23*Assumptions!B71,0)+0 -> 260 | O23: =M23-N23 -> 2975 | P23: =IF((Q22+O23)<N23*Assumptions!B89,0,IF((Q22+O23)<N23*6,ROUND(MAX(O23,0)*Assumptions!B90,0),ROUND(MAX(O23,0)*Assumptions!B91,0))) -> 1488 | Q23: =Q22+O23-P23 -> 9230
A24: 21 | B24: =ROUND(B23*(1+Assumptions!B39),0) -> 5695 | C24: =ROUND(IF(A24<Assumptions!B100,0,IF(A24<=8,Assumptions!B103,IF(A24<=12,Assumptions!B104,IF(A24<=18,Assumptions!B105,IF(A24<=24,Assumptions!B106,Assumptions!B107))))*(1+IF(A24>=Assumptions!B101,Assumptions!B109,0))*Assumptions!B111),0) -> 300 | D24: =ROUND(ROUND(Assumptions!B119*(1+Assumptions!B120)^6*(1+Assumptions!B121)^6*(1+Assumptions!B122)^(A24-12),0)*Assumptions!B123,0) -> 12 | E24: =B24+C24+D24 -> 6007 | F24: =ROUND(E24*Assumptions!B23,0) -> 15 | G24: =ROUND(H23*Assumptions!B51,0) -> 6 | H24: =H23+F24-G24 -> 95 | I24: =ROUND(H24*(Assumptions!B15*0.85+Assumptions!B11*0.15),0) -> 1090 | J24: =ROUND(E24*Assumptions!B95*Assumptions!B96*Assumptions!B97*Assumptions!B94,0) -> 234 | K24: =ROUND(E24*Assumptions!B57*Assumptions!B58,0) -> 2102 | L24: =ROUND(IF(A24<Assumptions!B113,0,IF(A24<=18,Assumptions!B105,Assumptions!B107)/1000*Assumptions!B115*0.55+IF(A24>=Assumptions!B114,IF(A24<=18,Assumptions!B105,Assumptions!B107)*Assumptions!B109/1000*Assumptions!B116*0.55,0)),0) -> 94 | M24: =I24+J24+K24+L24 -> 3520 | N24: =ROUND(H24*Assumptions!B62*Assumptions!B61,0)+Assumptions!B63+IF(H24>Assumptions!B64,45,0)+Assumptions!B65+Assumptions!B66+Assumptions!B67+Assumptions!B68+Assumptions!B69/12+IF(A24>=3,Assumptions!B72,0)+ROUND(I24*Assumptions!B70+H24*Assumptions!B71,0)+0 -> 269 | O24: =M24-N24 -> 3251 | P24: =IF((Q23+O24)<N24*Assumptions!B89,0,IF((Q23+O24)<N24*6,ROUND(MAX(O24,0)*Assumptions!B90,0),ROUND(MAX(O24,0)*Assumptions!B91,0))) -> 1626 | Q24: =Q23+O24-P24 -> 10855
A25: 22 | B25: =ROUND(B24*(1+Assumptions!B39),0) -> 6208 | C25: =ROUND(IF(A25<Assumptions!B100,0,IF(A25<=8,Assumptions!B103,IF(A25<=12,Assumptions!B104,IF(A25<=18,Assumptions!B105,IF(A25<=24,Assumptions!B106,Assumptions!B107))))*(1+IF(A25>=Assumptions!B101,Assumptions!B109,0))*Assumptions!B111),0) -> 300 | D25: =ROUND(ROUND(Assumptions!B119*(1+Assumptions!B120)^6*(1+Assumptions!B121)^6*(1+Assumptions!B122)^(A25-12),0)*Assumptions!B123,0) -> 13 | E25: =B25+C25+D25 -> 6521 | F25: =ROUND(E25*Assumptions!B23,0) -> 16 | G25: =ROUND(H24*Assumptions!B51,0) -> 7 | H25: =H24+F25-G25 -> 104 | I25: =ROUND(H25*(Assumptions!B15*0.85+Assumptions!B11*0.15),0) -> 1193 | J25: =ROUND(E25*Assumptions!B95*Assumptions!B96*Assumptions!B97*Assumptions!B94,0) -> 254 | K25: =ROUND(E25*Assumptions!B57*Assumptions!B58,0) -> 2282 | L25: =ROUND(IF(A25<Assumptions!B113,0,IF(A25<=18,Assumptions!B105,Assumptions!B107)/1000*Assumptions!B115*0.55+IF(A25>=Assumptions!B114,IF(A25<=18,Assumptions!B105,Assumptions!B107)*Assumptions!B109/1000*Assumptions!B116*0.55,0)),0) -> 94 | M25: =I25+J25+K25+L25 -> 3823 | N25: =ROUND(H25*Assumptions!B62*Assumptions!B61,0)+Assumptions!B63+IF(H25>Assumptions!B64,45,0)+Assumptions!B65+Assumptions!B66+Assumptions!B67+Assumptions!B68+Assumptions!B69/12+IF(A25>=3,Assumptions!B72,0)+ROUND(I25*Assumptions!B70+H25*Assumptions!B71,0)+0 -> 277 | O25: =M25-N25 -> 3546 | P25: =IF((Q24+O25)<N25*Assumptions!B89,0,IF((Q24+O25)<N25*6,ROUND(MAX(O25,0)*Assumptions!B90,0),ROUND(MAX(O25,0)*Assumptions!B91,0))) -> 1773 | Q25: =Q24+O25-P25 -> 12628
A26: 23 | B26: =ROUND(B25*(1+Assumptions!B39),0) -> 6767 | C26: =ROUND(IF(A26<Assumptions!B100,0,IF(A26<=8,Assumptions!B103,IF(A26<=12,Assumptions!B104,IF(A26<=18,Assumptions!B105,IF(A26<=24,Assumptions!B106,Assumptions!B107))))*(1+IF(A26>=Assumptions!B101,Assumptions!B109,0))*Assumptions!B111),0) -> 300 | D26: =ROUND(ROUND(Assumptions!B119*(1+Assumptions!B120)^6*(1+Assumptions!B121)^6*(1+Assumptions!B122)^(A26-12),0)*Assumptions!B123,0) -> 15 | E26: =B26+C26+D26 -> 7082 | F26: =ROUND(E26*Assumptions!B23,0) -> 18 | G26: =ROUND(H25*Assumptions!B51,0) -> 7 | H26: =H25+F26-G26 -> 115 | I26: =ROUND(H26*(Assumptions!B15*0.85+Assumptions!B11*0.15),0) -> 1320 | J26: =ROUND(E26*Assumptions!B95*Assumptions!B96*Assumptions!B97*Assumptions!B94,0) -> 276 | K26: =ROUND(E26*Assumptions!B57*Assumptions!B58,0) -> 2479 | L26: =ROUND(IF(A26<Assumptions!B113,0,IF(A26<=18,Assumptions!B105,Assumptions!B107)/1000*Assumptions!B115*0.55+IF(A26>=Assumptions!B114,IF(A26<=18,Assumptions!B105,Assumptions!B107)*Assumptions!B109/1000*Assumptions!B116*0.55,0)),0) -> 94 | M26: =I26+J26+K26+L26 -> 4169 | N26: =ROUND(H26*Assumptions!B62*Assumptions!B61,0)+Assumptions!B63+IF(H26>Assumptions!B64,45,0)+Assumptions!B65+Assumptions!B66+Assumptions!B67+Assumptions!B68+Assumptions!B69/12+IF(A26>=3,Assumptions!B72,0)+ROUND(I26*Assumptions!B70+H26*Assumptions!B71,0)+0 -> 287 | O26: =M26-N26 -> 3882 | P26: =IF((Q25+O26)<N26*Assumptions!B89,0,IF((Q25+O26)<N26*6,ROUND(MAX(O26,0)*Assumptions!B90,0),ROUND(MAX(O26,0)*Assumptions!B91,0))) -> 1941 | Q26: =Q25+O26-P26 -> 14569
A27: 24 | B27: =ROUND(B26*(1+Assumptions!B39),0) -> 7376 | C27: =ROUND(IF(A27<Assumptions!B100,0,IF(A27<=8,Assumptions!B103,IF(A27<=12,Assumptions!B104,IF(A27<=18,Assumptions!B105,IF(A27<=24,Assumptions!B106,Assumptions!B107))))*(1+IF(A27>=Assumptions!B101,Assumptions!B109,0))*Assumptions!B111),0) -> 300 | D27: =ROUND(ROUND(Assumptions!B119*(1+Assumptions!B120)^6*(1+Assumptions!B121)^6*(1+Assumptions!B122)^(A27-12),0)*Assumptions!B123,0) -> 16 | E27: =B27+C27+D27 -> 7692 | F27: =ROUND(E27*Assumptions!B23,0) -> 19 | G27: =ROUND(H26*Assumptions!B51,0) -> 8 | H27: =H26+F27-G27 -> 126 | I27: =ROUND(H27*(Assumptions!B15*0.85+Assumptions!B11*0.15),0) -> 1446 | J27: =ROUND(E27*Assumptions!B95*Assumptions!B96*Assumptions!B97*Assumptions!B94,0) -> 300 | K27: =ROUND(E27*Assumptions!B57*Assumptions!B58,0) -> 2692 | L27: =ROUND(IF(A27<Assumptions!B113,0,IF(A27<=18,Assumptions!B105,Assumptions!B107)/1000*Assumptions!B115*0.55+IF(A27>=Assumptions!B114,IF(A27<=18,Assumptions!B105,Assumptions!B107)*Assumptions!B109/1000*Assumptions!B116*0.55,0)),0) -> 94 | M27: =I27+J27+K27+L27 -> 4532 | N27: =ROUND(H27*Assumptions!B62*Assumptions!B61,0)+Assumptions!B63+IF(H27>Assumptions!B64,45,0)+Assumptions!B65+Assumptions!B66+Assumptions!B67+Assumptions!B68+Assumptions!B69/12+IF(A27>=3,Assumptions!B72,0)+ROUND(I27*Assumptions!B70+H27*Assumptions!B71,0)+0 -> 297 | O27: =M27-N27 -> 4235 | P27: =IF((Q26+O27)<N27*Assumptions!B89,0,IF((Q26+O27)<N27*6,ROUND(MAX(O27,0)*Assumptions!B90,0),ROUND(MAX(O27,0)*Assumptions!B91,0))) -> 2118 | Q27: =Q26+O27-P27 -> 16686
A28: 25 | B28: =ROUND(B27*(1+Assumptions!B43),0) -> 7819 | C28: =ROUND(IF(A28<Assumptions!B100,0,IF(A28<=8,Assumptions!B103,IF(A28<=12,Assumptions!B104,IF(A28<=18,Assumptions!B105,IF(A28<=24,Assumptions!B106,Assumptions!B107))))*(1+IF(A28>=Assumptions!B101,Assumptions!B109,0))*Assumptions!B111),0) -> 540 | D28: =ROUND(ROUND(Assumptions!B119*(1+Assumptions!B120)^6*(1+Assumptions!B121)^6*(1+Assumptions!B122)^(A28-12),0)*Assumptions!B123,0) -> 18 | E28: =B28+C28+D28 -> 8377 | F28: =ROUND(E28*Assumptions!B23,0) -> 21 | G28: =ROUND(H27*Assumptions!B51,0) -> 9 | H28: =H27+F28-G28 -> 138 | I28: =ROUND(H28*(Assumptions!B15*0.85+Assumptions!B11*0.15),0) -> 1584 | J28: =ROUND(E28*Assumptions!B95*Assumptions!B96*Assumptions!B97*Assumptions!B94,0) -> 327 | K28: =ROUND(E28*Assumptions!B57*Assumptions!B58,0) -> 2932 | L28: =ROUND(IF(A28<Assumptions!B113,0,IF(A28<=18,Assumptions!B105,Assumptions!B107)/1000*Assumptions!B115*0.55+IF(A28>=Assumptions!B114,IF(A28<=18,Assumptions!B105,Assumptions!B107)*Assumptions!B109/1000*Assumptions!B116*0.55,0)),0) -> 94 | M28: =I28+J28+K28+L28 -> 4937 | N28: =ROUND(H28*Assumptions!B62*Assumptions!B61,0)+Assumptions!B63+IF(H28>Assumptions!B64,45,0)+Assumptions!B65+Assumptions!B66+Assumptions!B67+Assumptions!B68+Assumptions!B69/12+IF(A28>=3,Assumptions!B72,0)+ROUND(I28*Assumptions!B70+H28*Assumptions!B71,0)+0 -> 308 | O28: =M28-N28 -> 4629 | P28: =IF((Q27+O28)<N28*Assumptions!B89,0,IF((Q27+O28)<N28*6,ROUND(MAX(O28,0)*Assumptions!B90,0),ROUND(MAX(O28,0)*Assumptions!B91,0))) -> 2315 | Q28: =Q27+O28-P28 -> 19000
A29: 26 | B29: =ROUND(B28*(1+Assumptions!B43),0) -> 8288 | C29: =ROUND(IF(A29<Assumptions!B100,0,IF(A29<=8,Assumptions!B103,IF(A29<=12,Assumptions!B104,IF(A29<=18,Assumptions!B105,IF(A29<=24,Assumptions!B106,Assumptions!B107))))*(1+IF(A29>=Assumptions!B101,Assumptions!B109,0))*Assumptions!B111),0) -> 540 | D29: =ROUND(ROUND(Assumptions!B119*(1+Assumptions!B120)^6*(1+Assumptions!B121)^6*(1+Assumptions!B122)^(A29-12),0)*Assumptions!B123,0) -> 20 | E29: =B29+C29+D29 -> 8848 | F29: =ROUND(E29*Assumptions!B23,0) -> 22 | G29: =ROUND(H28*Assumptions!B51,0) -> 10 | H29: =H28+F29-G29 -> 150 | I29: =ROUND(H29*(Assumptions!B15*0.85+Assumptions!B11*0.15),0) -> 1721 | J29: =ROUND(E29*Assumptions!B95*Assumptions!B96*Assumptions!B97*Assumptions!B94,0) -> 345 | K29: =ROUND(E29*Assumptions!B57*Assumptions!B58,0) -> 3097 | L29: =ROUND(IF(A29<Assumptions!B113,0,IF(A29<=18,Assumptions!B105,Assumptions!B107)/1000*Assumptions!B115*0.55+IF(A29>=Assumptions!B114,IF(A29<=18,Assumptions!B105,Assumptions!B107)*Assumptions!B109/1000*Assumptions!B116*0.55,0)),0) -> 94 | M29: =I29+J29+K29+L29 -> 5257 | N29: =ROUND(H29*Assumptions!B62*Assumptions!B61,0)+Assumptions!B63+IF(H29>Assumptions!B64,45,0)+Assumptions!B65+Assumptions!B66+Assumptions!B67+Assumptions!B68+Assumptions!B69/12+IF(A29>=3,Assumptions!B72,0)+ROUND(I29*Assumptions!B70+H29*Assumptions!B71,0)+0 -> 319 | O29: =M29-N29 -> 4938 | P29: =IF((Q28+O29)<N29*Assumptions!B89,0,IF((Q28+O29)<N29*6,ROUND(MAX(O29,0)*Assumptions!B90,0),ROUND(MAX(O29,0)*Assumptions!B91,0))) -> 2469 | Q29: =Q28+O29-P29 -> 21469
A30: 27 | B30: =ROUND(B29*(1+Assumptions!B43),0) -> 8785 | C30: =ROUND(IF(A30<Assumptions!B100,0,IF(A30<=8,Assumptions!B103,IF(A30<=12,Assumptions!B104,IF(A30<=18,Assumptions!B105,IF(A30<=24,Assumptions!B106,Assumptions!B107))))*(1+IF(A30>=Assumptions!B101,Assumptions!B109,0))*Assumptions!B111),0) -> 540 | D30: =ROUND(ROUND(Assumptions!B119*(1+Assumptions!B120)^6*(1+Assumptions!B121)^6*(1+Assumptions!B122)^(A30-12),0)*Assumptions!B123,0) -> 22 | E30: =B30+C30+D30 -> 9347 | F30: =ROUND(E30*Assumptions!B23,0) -> 23 | G30: =ROUND(H29*Assumptions!B51,0) -> 11 | H30: =H29+F30-G30 -> 162 | I30: =ROUND(H30*(Assumptions!B15*0.85+Assumptions!B11*0.15),0) -> 1859 | J30: =ROUND(E30*Assumptions!B95*Assumptions!B96*Assumptions!B97*Assumptions!B94,0) -> 365 | K30: =ROUND(E30*Assumptions!B57*Assumptions!B58,0) -> 3271 | L30: =ROUND(IF(A30<Assumptions!B113,0,IF(A30<=18,Assumptions!B105,Assumptions!B107)/1000*Assumptions!B115*0.55+IF(A30>=Assumptions!B114,IF(A30<=18,Assumptions!B105,Assumptions!B107)*Assumptions!B109/1000*Assumptions!B116*0.55,0)),0) -> 94 | M30: =I30+J30+K30+L30 -> 5589 | N30: =ROUND(H30*Assumptions!B62*Assumptions!B61,0)+Assumptions!B63+IF(H30>Assumptions!B64,45,0)+Assumptions!B65+Assumptions!B66+Assumptions!B67+Assumptions!B68+Assumptions!B69/12+IF(A30>=3,Assumptions!B72,0)+ROUND(I30*Assumptions!B70+H30*Assumptions!B71,0)+0 -> 330 | O30: =M30-N30 -> 5259 | P30: =IF((Q29+O30)<N30*Assumptions!B89,0,IF((Q29+O30)<N30*6,ROUND(MAX(O30,0)*Assumptions!B90,0),ROUND(MAX(O30,0)*Assumptions!B91,0))) -> 2630 | Q30: =Q29+O30-P30 -> 24098
A31: 28 | B31: =ROUND(B30*(1+Assumptions!B43),0) -> 9312 | C31: =ROUND(IF(A31<Assumptions!B100,0,IF(A31<=8,Assumptions!B103,IF(A31<=12,Assumptions!B104,IF(A31<=18,Assumptions!B105,IF(A31<=24,Assumptions!B106,Assumptions!B107))))*(1+IF(A31>=Assumptions!B101,Assumptions!B109,0))*Assumptions!B111),0) -> 540 | D31: =ROUND(ROUND(Assumptions!B119*(1+Assumptions!B120)^6*(1+Assumptions!B121)^6*(1+Assumptions!B122)^(A31-12),0)*Assumptions!B123,0) -> 24 | E31: =B31+C31+D31 -> 9876 | F31: =ROUND(E31*Assumptions!B23,0) -> 25 | G31: =ROUND(H30*Assumptions!B51,0) -> 11 | H31: =H30+F31-G31 -> 176 | I31: =ROUND(H31*(Assumptions!B15*0.85+Assumptions!B11*0.15),0) -> 2020 | J31: =ROUND(E31*Assumptions!B95*Assumptions!B96*Assumptions!B97*Assumptions!B94,0) -> 385 | K31: =ROUND(E31*Assumptions!B57*Assumptions!B58,0) -> 3457 | L31: =ROUND(IF(A31<Assumptions!B113,0,IF(A31<=18,Assumptions!B105,Assumptions!B107)/1000*Assumptions!B115*0.55+IF(A31>=Assumptions!B114,IF(A31<=18,Assumptions!B105,Assumptions!B107)*Assumptions!B109/1000*Assumptions!B116*0.55,0)),0) -> 94 | M31: =I31+J31+K31+L31 -> 5956 | N31: =ROUND(H31*Assumptions!B62*Assumptions!B61,0)+Assumptions!B63+IF(H31>Assumptions!B64,45,0)+Assumptions!B65+Assumptions!B66+Assumptions!B67+Assumptions!B68+Assumptions!B69/12+IF(A31>=3,Assumptions!B72,0)+ROUND(I31*Assumptions!B70+H31*Assumptions!B71,0)+0 -> 342 | O31: =M31-N31 -> 5614 | P31: =IF((Q30+O31)<N31*Assumptions!B89,0,IF((Q30+O31)<N31*6,ROUND(MAX(O31,0)*Assumptions!B90,0),ROUND(MAX(O31,0)*Assumptions!B91,0))) -> 2807 | Q31: =Q30+O31-P31 -> 26905
A32: 29 | B32: =ROUND(B31*(1+Assumptions!B43),0) -> 9871 | C32: =ROUND(IF(A32<Assumptions!B100,0,IF(A32<=8,Assumptions!B103,IF(A32<=12,Assumptions!B104,IF(A32<=18,Assumptions!B105,IF(A32<=24,Assumptions!B106,Assumptions!B107))))*(1+IF(A32>=Assumptions!B101,Assumptions!B109,0))*Assumptions!B111),0) -> 540 | D32: =ROUND(ROUND(Assumptions!B119*(1+Assumptions!B120)^6*(1+Assumptions!B121)^6*(1+Assumptions!B122)^(A32-12),0)*Assumptions!B123,0) -> 26 | E32: =B32+C32+D32 -> 10437 | F32: =ROUND(E32*Assumptions!B23,0) -> 26 | G32: =ROUND(H31*Assumptions!B51,0) -> 12 | H32: =H31+F32-G32 -> 190 | I32: =ROUND(H32*(Assumptions!B15*0.85+Assumptions!B11*0.15),0) -> 2180 | J32: =ROUND(E32*Assumptions!B95*Assumptions!B96*Assumptions!B97*Assumptions!B94,0) -> 407 | K32: =ROUND(E32*Assumptions!B57*Assumptions!B58,0) -> 3653 | L32: =ROUND(IF(A32<Assumptions!B113,0,IF(A32<=18,Assumptions!B105,Assumptions!B107)/1000*Assumptions!B115*0.55+IF(A32>=Assumptions!B114,IF(A32<=18,Assumptions!B105,Assumptions!B107)*Assumptions!B109/1000*Assumptions!B116*0.55,0)),0) -> 94 | M32: =I32+J32+K32+L32 -> 6334 | N32: =ROUND(H32*Assumptions!B62*Assumptions!B61,0)+Assumptions!B63+IF(H32>Assumptions!B64,45,0)+Assumptions!B65+Assumptions!B66+Assumptions!B67+Assumptions!B68+Assumptions!B69/12+IF(A32>=3,Assumptions!B72,0)+ROUND(I32*Assumptions!B70+H32*Assumptions!B71,0)+0 -> 355 | O32: =M32-N32 -> 5979 | P32: =IF((Q31+O32)<N32*Assumptions!B89,0,IF((Q31+O32)<N32*6,ROUND(MAX(O32,0)*Assumptions!B90,0),ROUND(MAX(O32,0)*Assumptions!B91,0))) -> 2990 | Q32: =Q31+O32-P32 -> 29894
A33: 30 | B33: =ROUND(B32*(1+Assumptions!B43),0) -> 10463 | C33: =ROUND(IF(A33<Assumptions!B100,0,IF(A33<=8,Assumptions!B103,IF(A33<=12,Assumptions!B104,IF(A33<=18,Assumptions!B105,IF(A33<=24,Assumptions!B106,Assumptions!B107))))*(1+IF(A33>=Assumptions!B101,Assumptions!B109,0))*Assumptions!B111),0) -> 540 | D33: =ROUND(ROUND(Assumptions!B119*(1+Assumptions!B120)^6*(1+Assumptions!B121)^6*(1+Assumptions!B122)^(A33-12),0)*Assumptions!B123,0) -> 29 | E33: =B33+C33+D33 -> 11032 | F33: =ROUND(E33*Assumptions!B23,0) -> 28 | G33: =ROUND(H32*Assumptions!B51,0) -> 13 | H33: =H32+F33-G33 -> 205 | I33: =ROUND(H33*(Assumptions!B15*0.85+Assumptions!B11*0.15),0) -> 2352 | J33: =ROUND(E33*Assumptions!B95*Assumptions!B96*Assumptions!B97*Assumptions!B94,0) -> 430 | K33: =ROUND(E33*Assumptions!B57*Assumptions!B58,0) -> 3861 | L33: =ROUND(IF(A33<Assumptions!B113,0,IF(A33<=18,Assumptions!B105,Assumptions!B107)/1000*Assumptions!B115*0.55+IF(A33>=Assumptions!B114,IF(A33<=18,Assumptions!B105,Assumptions!B107)*Assumptions!B109/1000*Assumptions!B116*0.55,0)),0) -> 94 | M33: =I33+J33+K33+L33 -> 6737 | N33: =ROUND(H33*Assumptions!B62*Assumptions!B61,0)+Assumptions!B63+IF(H33>Assumptions!B64,45,0)+Assumptions!B65+Assumptions!B66+Assumptions!B67+Assumptions!B68+Assumptions!B69/12+IF(A33>=3,Assumptions!B72,0)+ROUND(I33*Assumptions!B70+H33*Assumptions!B71,0)+0 -> 369 | O33: =M33-N33 -> 6368 | P33: =IF((Q32+O33)<N33*Assumptions!B89,0,IF((Q32+O33)<N33*6,ROUND(MAX(O33,0)*Assumptions!B90,0),ROUND(MAX(O33,0)*Assumptions!B91,0))) -> 3184 | Q33: =Q32+O33-P33 -> 33078
A34: 31 | B34: =ROUND(B33*(1+Assumptions!B43),0) -> 11091 | C34: =ROUND(IF(A34<Assumptions!B100,0,IF(A34<=8,Assumptions!B103,IF(A34<=12,Assumptions!B104,IF(A34<=18,Assumptions!B105,IF(A34<=24,Assumptions!B106,Assumptions!B107))))*(1+IF(A34>=Assumptions!B101,Assumptions!B109,0))*Assumptions!B111),0) -> 540 | D34: =ROUND(ROUND(Assumptions!B119*(1+Assumptions!B120)^6*(1+Assumptions!B121)^6*(1+Assumptions!B122)^(A34-12),0)*Assumptions!B123,0) -> 32 | E34: =B34+C34+D34 -> 11663 | F34: =ROUND(E34*Assumptions!B23,0) -> 29 | G34: =ROUND(H33*Assumptions!B51,0) -> 14 | H34: =H33+F34-G34 -> 220 | I34: =ROUND(H34*(Assumptions!B15*0.85+Assumptions!B11*0.15),0) -> 2525 | J34: =ROUND(E34*Assumptions!B95*Assumptions!B96*Assumptions!B97*Assumptions!B94,0) -> 455 | K34: =ROUND(E34*Assumptions!B57*Assumptions!B58,0) -> 4082 | L34: =ROUND(IF(A34<Assumptions!B113,0,IF(A34<=18,Assumptions!B105,Assumptions!B107)/1000*Assumptions!B115*0.55+IF(A34>=Assumptions!B114,IF(A34<=18,Assumptions!B105,Assumptions!B107)*Assumptions!B109/1000*Assumptions!B116*0.55,0)),0) -> 94 | M34: =I34+J34+K34+L34 -> 7156 | N34: =ROUND(H34*Assumptions!B62*Assumptions!B61,0)+Assumptions!B63+IF(H34>Assumptions!B64,45,0)+Assumptions!B65+Assumptions!B66+Assumptions!B67+Assumptions!B68+Assumptions!B69/12+IF(A34>=3,Assumptions!B72,0)+ROUND(I34*Assumptions!B70+H34*Assumptions!B71,0)+0 -> 383 | O34: =M34-N34 -> 6773 | P34: =IF((Q33+O34)<N34*Assumptions!B89,0,IF((Q33+O34)<N34*6,ROUND(MAX(O34,0)*Assumptions!B90,0),ROUND(MAX(O34,0)*Assumptions!B91,0))) -> 3387 | Q34: =Q33+O34-P34 -> 36464
A35: 32 | B35: =ROUND(B34*(1+Assumptions!B43),0) -> 11756 | C35: =ROUND(IF(A35<Assumptions!B100,0,IF(A35<=8,Assumptions!B103,IF(A35<=12,Assumptions!B104,IF(A35<=18,Assumptions!B105,IF(A35<=24,Assumptions!B106,Assumptions!B107))))*(1+IF(A35>=Assumptions!B101,Assumptions!B109,0))*Assumptions!B111),0) -> 540 | D35: =ROUND(ROUND(Assumptions!B119*(1+Assumptions!B120)^6*(1+Assumptions!B121)^6*(1+Assumptions!B122)^(A35-12),0)*Assumptions!B123,0) -> 35 | E35: =B35+C35+D35 -> 12331 | F35: =ROUND(E35*Assumptions!B23,0) -> 31 | G35: =ROUND(H34*Assumptions!B51,0) -> 15 | H35: =H34+F35-G35 -> 236 | I35: =ROUND(H35*(Assumptions!B15*0.85+Assumptions!B11*0.15),0) -> 2708 | J35: =ROUND(E35*Assumptions!B95*Assumptions!B96*Assumptions!B97*Assumptions!B94,0) -> 481 | K35: =ROUND(E35*Assumptions!B57*Assumptions!B58,0) -> 4316 | L35: =ROUND(IF(A35<Assumptions!B113,0,IF(A35<=18,Assumptions!B105,Assumptions!B107)/1000*Assumptions!B115*0.55+IF(A35>=Assumptions!B114,IF(A35<=18,Assumptions!B105,Assumptions!B107)*Assumptions!B109/1000*Assumptions!B116*0.55,0)),0) -> 94 | M35: =I35+J35+K35+L35 -> 7599 | N35: =ROUND(H35*Assumptions!B62*Assumptions!B61,0)+Assumptions!B63+IF(H35>Assumptions!B64,45,0)+Assumptions!B65+Assumptions!B66+Assumptions!B67+Assumptions!B68+Assumptions!B69/12+IF(A35>=3,Assumptions!B72,0)+ROUND(I35*Assumptions!B70+H35*Assumptions!B71,0)+0 -> 397 | O35: =M35-N35 -> 7202 | P35: =IF((Q34+O35)<N35*Assumptions!B89,0,IF((Q34+O35)<N35*6,ROUND(MAX(O35,0)*Assumptions!B90,0),ROUND(MAX(O35,0)*Assumptions!B91,0))) -> 3601 | Q35: =Q34+O35-P35 -> 40065
A36: 33 | B36: =ROUND(B35*(1+Assumptions!B43),0) -> 12461 | C36: =ROUND(IF(A36<Assumptions!B100,0,IF(A36<=8,Assumptions!B103,IF(A36<=12,Assumptions!B104,IF(A36<=18,Assumptions!B105,IF(A36<=24,Assumptions!B106,Assumptions!B107))))*(1+IF(A36>=Assumptions!B101,Assumptions!B109,0))*Assumptions!B111),0) -> 540 | D36: =ROUND(ROUND(Assumptions!B119*(1+Assumptions!B120)^6*(1+Assumptions!B121)^6*(1+Assumptions!B122)^(A36-12),0)*Assumptions!B123,0) -> 38 | E36: =B36+C36+D36 -> 13039 | F36: =ROUND(E36*Assumptions!B23,0) -> 33 | G36: =ROUND(H35*Assumptions!B51,0) -> 17 | H36: =H35+F36-G36 -> 252 | I36: =ROUND(H36*(Assumptions!B15*0.85+Assumptions!B11*0.15),0) -> 2892 | J36: =ROUND(E36*Assumptions!B95*Assumptions!B96*Assumptions!B97*Assumptions!B94,0) -> 509 | K36: =ROUND(E36*Assumptions!B57*Assumptions!B58,0) -> 4564 | L36: =ROUND(IF(A36<Assumptions!B113,0,IF(A36<=18,Assumptions!B105,Assumptions!B107)/1000*Assumptions!B115*0.55+IF(A36>=Assumptions!B114,IF(A36<=18,Assumptions!B105,Assumptions!B107)*Assumptions!B109/1000*Assumptions!B116*0.55,0)),0) -> 94 | M36: =I36+J36+K36+L36 -> 8059 | N36: =ROUND(H36*Assumptions!B62*Assumptions!B61,0)+Assumptions!B63+IF(H36>Assumptions!B64,45,0)+Assumptions!B65+Assumptions!B66+Assumptions!B67+Assumptions!B68+Assumptions!B69/12+IF(A36>=3,Assumptions!B72,0)+ROUND(I36*Assumptions!B70+H36*Assumptions!B71,0)+0 -> 412 | O36: =M36-N36 -> 7647 | P36: =IF((Q35+O36)<N36*Assumptions!B89,0,IF((Q35+O36)<N36*6,ROUND(MAX(O36,0)*Assumptions!B90,0),ROUND(MAX(O36,0)*Assumptions!B91,0))) -> 3824 | Q36: =Q35+O36-P36 -> 43888
A37: 34 | B37: =ROUND(B36*(1+Assumptions!B43),0) -> 13209 | C37: =ROUND(IF(A37<Assumptions!B100,0,IF(A37<=8,Assumptions!B103,IF(A37<=12,Assumptions!B104,IF(A37<=18,Assumptions!B105,IF(A37<=24,Assumptions!B106,Assumptions!B107))))*(1+IF(A37>=Assumptions!B101,Assumptions!B109,0))*Assumptions!B111),0) -> 540 | D37: =ROUND(ROUND(Assumptions!B119*(1+Assumptions!B120)^6*(1+Assumptions!B121)^6*(1+Assumptions!B122)^(A37-12),0)*Assumptions!B123,0) -> 42 | E37: =B37+C37+D37 -> 13791 | F37: =ROUND(E37*Assumptions!B23,0) -> 34 | G37: =ROUND(H36*Assumptions!B51,0) -> 18 | H37: =H36+F37-G37 -> 268 | I37: =ROUND(H37*(Assumptions!B15*0.85+Assumptions!B11*0.15),0) -> 3075 | J37: =ROUND(E37*Assumptions!B95*Assumptions!B96*Assumptions!B97*Assumptions!B94,0) -> 538 | K37: =ROUND(E37*Assumptions!B57*Assumptions!B58,0) -> 4827 | L37: =ROUND(IF(A37<Assumptions!B113,0,IF(A37<=18,Assumptions!B105,Assumptions!B107)/1000*Assumptions!B115*0.55+IF(A37>=Assumptions!B114,IF(A37<=18,Assumptions!B105,Assumptions!B107)*Assumptions!B109/1000*Assumptions!B116*0.55,0)),0) -> 94 | M37: =I37+J37+K37+L37 -> 8534 | N37: =ROUND(H37*Assumptions!B62*Assumptions!B61,0)+Assumptions!B63+IF(H37>Assumptions!B64,45,0)+Assumptions!B65+Assumptions!B66+Assumptions!B67+Assumptions!B68+Assumptions!B69/12+IF(A37>=3,Assumptions!B72,0)+ROUND(I37*Assumptions!B70+H37*Assumptions!B71,0)+0 -> 427 | O37: =M37-N37 -> 8107 | P37: =IF((Q36+O37)<N37*Assumptions!B89,0,IF((Q36+O37)<N37*6,ROUND(MAX(O37,0)*Assumptions!B90,0),ROUND(MAX(O37,0)*Assumptions!B91,0))) -> 4054 | Q37: =Q36+O37-P37 -> 47941
A38: 35 | B38: =ROUND(B37*(1+Assumptions!B43),0) -> 14002 | C38: =ROUND(IF(A38<Assumptions!B100,0,IF(A38<=8,Assumptions!B103,IF(A38<=12,Assumptions!B104,IF(A38<=18,Assumptions!B105,IF(A38<=24,Assumptions!B106,Assumptions!B107))))*(1+IF(A38>=Assumptions!B101,Assumptions!B109,0))*Assumptions!B111),0) -> 540 | D38: =ROUND(ROUND(Assumptions!B119*(1+Assumptions!B120)^6*(1+Assumptions!B121)^6*(1+Assumptions!B122)^(A38-12),0)*Assumptions!B123,0) -> 46 | E38: =B38+C38+D38 -> 14588 | F38: =ROUND(E38*Assumptions!B23,0) -> 36 | G38: =ROUND(H37*Assumptions!B51,0) -> 19 | H38: =H37+F38-G38 -> 285 | I38: =ROUND(H38*(Assumptions!B15*0.85+Assumptions!B11*0.15),0) -> 3270 | J38: =ROUND(E38*Assumptions!B95*Assumptions!B96*Assumptions!B97*Assumptions!B94,0) -> 569 | K38: =ROUND(E38*Assumptions!B57*Assumptions!B58,0) -> 5106 | L38: =ROUND(IF(A38<Assumptions!B113,0,IF(A38<=18,Assumptions!B105,Assumptions!B107)/1000*Assumptions!B115*0.55+IF(A38>=Assumptions!B114,IF(A38<=18,Assumptions!B105,Assumptions!B107)*Assumptions!B109/1000*Assumptions!B116*0.55,0)),0) -> 94 | M38: =I38+J38+K38+L38 -> 9039 | N38: =ROUND(H38*Assumptions!B62*Assumptions!B61,0)+Assumptions!B63+IF(H38>Assumptions!B64,45,0)+Assumptions!B65+Assumptions!B66+Assumptions!B67+Assumptions!B68+Assumptions!B69/12+IF(A38>=3,Assumptions!B72,0)+ROUND(I38*Assumptions!B70+H38*Assumptions!B71,0)+0 -> 442 | O38: =M38-N38 -> 8597 | P38: =IF((Q37+O38)<N38*Assumptions!B89,0,IF((Q37+O38)<N38*6,ROUND(MAX(O38,0)*Assumptions!B90,0),ROUND(MAX(O38,0)*Assumptions!B91,0))) -> 4299 | Q38: =Q37+O38-P38 -> 52239
A39: 36 | B39: =ROUND(B38*(1+Assumptions!B43),0) -> 14842 | C39: =ROUND(IF(A39<Assumptions!B100,0,IF(A39<=8,Assumptions!B103,IF(A39<=12,Assumptions!B104,IF(A39<=18,Assumptions!B105,IF(A39<=24,Assumptions!B106,Assumptions!B107))))*(1+IF(A39>=Assumptions!B101,Assumptions!B109,0))*Assumptions!B111),0) -> 540 | D39: =ROUND(ROUND(Assumptions!B119*(1+Assumptions!B120)^6*(1+Assumptions!B121)^6*(1+Assumptions!B122)^(A39-12),0)*Assumptions!B123,0) -> 51 | E39: =B39+C39+D39 -> 15433 | F39: =ROUND(E39*Assumptions!B23,0) -> 39 | G39: =ROUND(H38*Assumptions!B51,0) -> 20 | H39: =H38+F39-G39 -> 304 | I39: =ROUND(H39*(Assumptions!B15*0.85+Assumptions!B11*0.15),0) -> 3488 | J39: =ROUND(E39*Assumptions!B95*Assumptions!B96*Assumptions!B97*Assumptions!B94,0) -> 602 | K39: =ROUND(E39*Assumptions!B57*Assumptions!B58,0) -> 5402 | L39: =ROUND(IF(A39<Assumptions!B113,0,IF(A39<=18,Assumptions!B105,Assumptions!B107)/1000*Assumptions!B115*0.55+IF(A39>=Assumptions!B114,IF(A39<=18,Assumptions!B105,Assumptions!B107)*Assumptions!B109/1000*Assumptions!B116*0.55,0)),0) -> 94 | M39: =I39+J39+K39+L39 -> 9586 | N39: =ROUND(H39*Assumptions!B62*Assumptions!B61,0)+Assumptions!B63+IF(H39>Assumptions!B64,45,0)+Assumptions!B65+Assumptions!B66+Assumptions!B67+Assumptions!B68+Assumptions!B69/12+IF(A39>=3,Assumptions!B72,0)+ROUND(I39*Assumptions!B70+H39*Assumptions!B71,0)+0 -> 459 | O39: =M39-N39 -> 9127 | P39: =IF((Q38+O39)<N39*Assumptions!B89,0,IF((Q38+O39)<N39*6,ROUND(MAX(O39,0)*Assumptions!B90,0),ROUND(MAX(O39,0)*Assumptions!B91,0))) -> 4564 | Q39: =Q38+O39-P39 -> 56802
A40: TOTALS | I40: =SUM(I4:I39) -> 41836 | J40: =SUM(J4:J39) -> 8425 | K40: =SUM(K4:K39) -> 74296 | L40: =SUM(L4:L39) -> 1858 | M40: =SUM(M4:M39) -> 126415 | N40: =SUM(N4:N39) -> 13007 | O40: =SUM(O4:O39) -> 113408 | P40: =SUM(P4:P39) -> 56606
A41: M36 | B41: =B39 -> 14842 | C41: =C39 -> 540 | D41: =D39 -> 51 | E41: =E39 -> 15433 | H41: =H39 -> 304 | I41: =I39 -> 3488 | M41: =M39 -> 9586 | P41: =P39 -> 4564 | Q41: =Q39 -> 56802

Sheet Optimistic
A1: OPTIMISTIC SCENARIO
A3: Month | B3: Organic SEO | C3: YT Visitors | D3: IG Visitors | E3: TOTAL Visitors | F3: New Paid Subs | G3: Churn | H3: Total Paid Subs | I3: MRR ($) | J3: Per-Case Rev ($) | K3: Referral Rev ($) | L3: YT AdSense ($) | M3: Total Revenue ($) | N3: Total Costs ($) | O3: Gross Profit ($) | P3: Owner's Draw ($) | Q3: Reserve ($)
A4: 1 | B4: =Assumptions!B32 -> 750 | C4: =ROUND(IF(A4<Assumptions!B100,0,IF(A4<=8,Assumptions!B103,IF(A4<=12,Assumptions!B104,IF(A4<=18,Assumptions!B105,IF(A4<=24,Assumptions!B106,Assumptions!B107))))*(1+IF(A4>=Assumptions!B101,Assumptions!B109,0))*Assumptions!B111),0) -> 0 | D4: =ROUND(Assumptions!B119*Assumptions!B123,0) -> 1 | E4: =B4+C4+D4 -> 751 | F4: =ROUND(E4*Assumptions!B24,0) -> 4 | G4: 0 | H4: =F4 -> 4 | I4: =ROUND(H4*Assumptions!B14,0) -> 32 | J4: =ROUND(E4*Assumptions!B95*Assumptions!B96*Assumptions!B97*Assumptions!B94,0) -> 29 | K4: 0 | L4: =ROUND(IF(A4<Assumptions!B113,0,IF(A4<=18,Assumptions!B105,Assumptions!B107)/1000*Assumptions!B115*0.55+IF(A4>=Assumptions!B114,IF(A4<=18,Assumptions!B105,Assumptions!B107)*Assumptions!B109/1000*Assumptions!B116*0.55,0)),0) -> 0 | M4: =I4+J4+K4+L4 -> 61 | N4: =ROUND(H4*Assumptions!B62*Assumptions!B61,0)+Assumptions!B63+IF(H4>Assumptions!B64,45,0)+Assumptions!B65+Assumptions!B66+Assumptions!B67+Assumptions!B68+Assumptions!B69/12+IF(A4>=3,Assumptions!B72,0)+ROUND(I4*Assumptions!B70+H4*Assumptions!B71,0)+Assumptions!B75+Assumptions!B76+Assumptions!B77 -> 3369 | O4: =M4-N4 -> -3308 | P4: =IF(O4<N4*Assumptions!B89,0,IF(O4<N4*6,ROUND(MAX(O4,0)*Assumptions!B90,0),ROUND(MAX(O4,0)*Assumptions!B91,0))) -> 0 | Q4: =O4-P4 -> -3308
A5: 2 | B5: =ROUND(B4*(1+Assumptions!B36),0) -> 885 | C5: =ROUND(IF(A5<Assumptions!B100,0,IF(A5<=8,Assumptions!B103,IF(A5<=12,Assumptions!B104,IF(A5<=18,Assumptions!B105,IF(A5<=24,Assumptions!B106,Assumptions!B107))))*(1+IF(A5>=Assumptions!B101,Assumptions!B109,0))*Assumptions!B111),0) -> 0 | D5: =ROUND(ROUND(Assumptions!B119*(1+Assumptions!B120)^(A5-1),0)*Assumptions!B123,0) -> 1 | E5: =B5+C5+D5 -> 886 | F5: =ROUND(E5*Assumptions!B24,0) -> 4 | G5: =ROUND(H4*Assumptions!B52,0) -> 0 | H5: =H4+F5-G5 -> 8 | I5: =ROUND(H5*Assumptions!B14,0) -> 64 | J5: =ROUND(E5*Assumptions!B95*Assumptions!B96*Assumptions!B97*Assumptions!B94,0) -> 35 | K5: 0 | L5: =ROUND(IF(A5<Assumptions!B113,0,IF(A5<=18,Assumptions!B105,Assumptions!B107)/1000*Assumptions!B115*0.55+IF(A5>=Assumptions!B114,IF(A5<=18,Assumptions!B105,Assumptions!B107)*Assumptions!B109/1000*Assumptions!B116*0.55,0)),0) -> 0 | M5: =I5+J5+K5+L5 -> 99 | N5: =ROUND(H5*Assumptions!B62*Assumptions!B61,0)+Assumptions!B63+IF(H5>Assumptions!B64,45,0)+Assumptions!B65+Assumptions!B66+Assumptions!B67+Assumptions!B68+Assumptions!B69/12+IF(A5>=3,Assumptions!B72,0)+ROUND(I5*Assumptions!B70+H5*Assumptions!B71,0)+0 -> 122 | O5: =M5-N5 -> -23 | P5: =IF((Q4+O5)<N5*Assumptions!B89,0,IF((Q4+O5)<N5*6,ROUND(MAX(O5,0)*Assumptions!B90,0),ROUND(MAX(O5,0)*Assumptions!B91,0))) -> 0 | Q5: =Q4+O5-P5 -> -3331
A6: 3 | B6: =ROUND(B5*(1+Assumptions!B36)*Assumptions!B46,0) -> 1201 | C6: =ROUND(IF(A6<Assumptions!B100,0,IF(A6<=8,Assumptions!B103,IF(A6<=12,Assumptions!B104,IF(A6<=18,Assumptions!B105,IF(A6<=24,Assumptions!B106,Assumptions!B107))))*(1+IF(A6>=Assumptions!B101,Assumptions!B109,0))*Assumptions!B111),0) -> 10 | D6: =ROUND(ROUND(Assumptions!B119*(1+Assumptions!B120)^(A6-1),0)*Assumptions!B123,0) -> 1 | E6: =B6+C6+D6 -> 1212 | F6: =ROUND(E6*Assumptions!B24,0) -> 6 | G6: =ROUND(H5*Assumptions!B52,0) -> 0 | H6: =H5+F6-G6 -> 14 | I6: =ROUND(H6*Assumptions!B14,0) -> 112 | J6: =ROUND(E6*Assumptions!B95*Assumptions!B96*Assumptions!B97*Assumptions!B94,0) -> 47 | K6: 0 | L6: =ROUND(IF(A6<Assumptions!B113,0,IF(A6<=18,Assumptions!B105,Assumptions!B107)/1000*Assumptions!B115*0.55+IF(A6>=Assumptions!B114,IF(A6<=18,Assumptions!B105,Assumptions!B107)*Assumptions!B109/1000*Assumptions!B116*0.55,0)),0) -> 0 | M6: =I6+J6+K6+L6 -> 159 | N6: =ROUND(H6*Assumptions!B62*Assumptions!B61,0)+Assumptions!B63+IF(H6>Assumptions!B64,45,0)+Assumptions!B65+Assumptions!B66+Assumptions!B67+Assumptions!B68+Assumptions!B69/12+IF(A6>=3,Assumptions!B72,0)+ROUND(I6*Assumptions!B70+H6*Assumptions!B71,0)+0 -> 193 | O6: =M6-N6 -> -34 | P6: =IF((Q5+O6)<N6*Assumptions!B89,0,IF((Q5+O6)<N6*6,ROUND(MAX(O6,0)*Assumptions!B90,0),ROUND(MAX(O6,0)*Assumptions!B91,0))) -> 0 | Q6: =Q5+O6-P6 -> -3365
A7: 4 | B7: =ROUND(B6*(1+Assumptions!B36),0) -> 1417 | C7: =ROUND(IF(A7<Assumptions!B100,0,IF(A7<=8,Assumptions!B103,IF(A7<=12,Assumptions!B104,IF(A7<=18,Assumptions!B105,IF(A7<=24,Assumptions!B106,Assumptions!B107))))*(1+IF(A7>=Assumptions!B101,Assumptions!B109,0))*Assumptions!B111),0) -> 10 | D7: =ROUND(ROUND(Assumptions!B119*(1+Assumptions!B120)^(A7-1),0)*Assumptions!B123,0) -> 1 | E7: =B7+C7+D7 -> 1428 | F7: =ROUND(E7*Assumptions!B24,0) -> 7 | G7: =ROUND(H6*Assumptions!B52,0) -> 1 | H7: =H6+F7-G7 -> 20 | I7: =ROUND(H7*Assumptions!B14,0) -> 160 | J7: =ROUND(E7*Assumptions!B95*Assumptions!B96*Assumptions!B97*Assumptions!B94,0) -> 56 | K7: 0 | L7: =ROUND(IF(A7<Assumptions!B113,0,IF(A7<=18,Assumptions!B105,Assumptions!B107)/1000*Assumptions!B115*0.55+IF(A7>=Assumptions!B114,IF(A7<=18,Assumptions!B105,Assumptions!B107)*Assumptions!B109/1000*Assumptions!B116*0.55,0)),0) -> 0 | M7: =I7+J7+K7+L7 -> 216 | N7: =ROUND(H7*Assumptions!B62*Assumptions!B61,0)+Assumptions!B63+IF(H7>Assumptions!B64,45,0)+Assumptions!B65+Assumptions!B66+Assumptions!B67+Assumptions!B68+Assumptions!B69/12+IF(A7>=3,Assumptions!B72,0)+ROUND(I7*Assumptions!B70+H7*Assumptions!B71,0)+0 -> 199 | O7: =M7-N7 -> 17 | P7: =IF((Q6+O7)<N7*Assumptions!B89,0,IF((Q6+O7)<N7*6,ROUND(MAX(O7,0)*Assumptions!B90,0),ROUND(MAX(O7,0)*Assumptions!B91,0))) -> 0 | Q7: =Q6+O7-P7 -> -3348
A8: 5 | B8: =ROUND(B7*(1+Assumptions!B36),0) -> 1672 | C8: =ROUND(IF(A8<Assumptions!B100,0,IF(A8<=8,Assumptions!B103,IF(A8<=12,Assumptions!B104,IF(A8<=18,Assumptions!B105,IF(A8<=24,Assumptions!B106,Assumptions!B107))))*(1+IF(A8>=Assumptions!B101,Assumptions!B109,0))*Assumptions!B111),0) -> 10 | D8: =ROUND(ROUND(Assumptions!B119*(1+Assumptions!B120)^(A8-1),0)*Assumptions!B123,0) -> 2 | E8: =B8+C8+D8 -> 1684 | F8: =ROUND(E8*Assumptions!B24,0) -> 8 | G8: =ROUND(H7*Assumptions!B52,0) -> 1 | H8: =H7+F8-G8 -> 27 | I8: =ROUND(H8*Assumptions!B14,0) -> 216 | J8: =ROUND(E8*Assumptions!B95*Assumptions!B96*Assumptions!B97*Assumptions!B94,0) -> 66 | K8: 0 | L8: =ROUND(IF(A8<Assumptions!B113,0,IF(A8<=18,Assumptions!B105,Assumptions!B107)/1000*Assumptions!B115*0.55+IF(A8>=Assumptions!B114,IF(A8<=18,Assumptions!B105,Assumptions!B107)*Assumptions!B109/1000*Assumptions!B116*0.55,0)),0) -> 0 | M8: =I8+J8+K8+L8 -> 282 | N8: =ROUND(H8*Assumptions!B62*Assumptions!B61,0)+Assumptions!B63+IF(H8>Assumptions!B64,45,0)+Assumptions!B65+Assumptions!B66+Assumptions!B67+Assumptions!B68+Assumptions!B69/12+IF(A8>=3,Assumptions!B72,0)+ROUND(I8*Assumptions!B70+H8*Assumptions!B71,0)+0 -> 204 | O8: =M8-N8 -> 78 | P8: =IF((Q7+O8)<N8*Assumptions!B89,0,IF((Q7+O8)<N8*6,ROUND(MAX(O8,0)*Assumptions!B90,0),ROUND(MAX(O8,0)*Assumptions!B91,0))) -> 0 | Q8: =Q7+O8-P8 -> -3270
A9: 6 | B9: =ROUND(B8*(1+Assumptions!B36)*Assumptions!B47,0) -> 2131 | C9: =ROUND(IF(A9<Assumptions!B100,0,IF(A9<=8,Assumptions!B103,IF(A9<=12,Assumptions!B104,IF(A9<=18,Assumptions!B105,IF(A9<=24,Assumptions!B106,Assumptions!B107))))*(1+IF(A9>=Assumptions!B101,Assumptions!B109,0))*Assumptions!B111),0) -> 10 | D9: =ROUND(ROUND(Assumptions!B119*(1+Assumptions!B120)^(A9-1),0)*Assumptions!B123,0) -> 2 | E9: =B9+C9+D9 -> 2143 | F9: =ROUND(E9*Assumptions!B24,0) -> 11 | G9: =ROUND(H8*Assumptions!B52,0) -> 2 | H9: =H8+F9-G9 -> 36 | I9: =ROUND(H9*Assumptions!B14,0) -> 288 | J9: =ROUND(E9*Assumptions!B95*Assumptions!B96*Assumptions!B97*Assumptions!B94,0) -> 84 | K9: =ROUND(E9*Assumptions!B57*Assumptions!B58,0) -> 750 | L9: =ROUND(IF(A9<Assumptions!B113,0,IF(A9<=18,Assumptions!B105,Assumptions!B107)/1000*Assumptions!B115*0.55+IF(A9>=Assumptions!B114,IF(A9<=18,Assumptions!B105,Assumptions!B107)*Assumptions!B109/1000*Assumptions!B116*0.55,0)),0) -> 0 | M9: =I9+J9+K9+L9 -> 1122 | N9: =ROUND(H9*Assumptions!B62*Assumptions!B61,0)+Assumptions!B63+IF(H9>Assumptions!B64,45,0)+Assumptions!B65+Assumptions!B66+Assumptions!B67+Assumptions!B68+Assumptions!B69/12+IF(A9>=3,Assumptions!B72,0)+ROUND(I9*Assumptions!B70+H9*Assumptions!B71,0)+0 -> 211 | O9: =M9-N9 -> 911 | P9: =IF((Q8+O9)<N9*Assumptions!B89,0,IF((Q8+O9)<N9*6,ROUND(MAX(O9,0)*Assumptions!B90,0),ROUND(MAX(O9,0)*Assumptions!B91,0))) -> 0 | Q9: =Q8+O9-P9 -> -2359
A10: 7 | B10: =ROUND(B9*(1+Assumptions!B36),0) -> 2515 | C10: =ROUND(IF(A10<Assumptions!B100,0,IF(A10<=8,Assumptions!B103,IF(A10<=12,Assumptions!B104,IF(A10<=18,Assumptions!B105,IF(A10<=24,Assumptions!B106,Assumptions!B107))))*(1+IF(A10>=Assumptions!B101,Assumptions!B109,0))*Assumptions!B111),0) -> 10 | D10: =ROUND(ROUND(Assumptions!B119*(1+Assumptions!B120)^6*(1+Assumptions!B121)^(A10-6),0)*Assumptions!B123,0) -> 3 | E10: =B10+C10+D10 -> 2528 | F10: =ROUND(E10*Assumptions!B24,0) -> 13 | G10: =ROUND(H9*Assumptions!B52,0) -> 2 | H10: =H9+F10-G10 -> 47 | I10: =ROUND(H10*Assumptions!B14,0) -> 376 | J10: =ROUND(E10*Assumptions!B95*Assumptions!B96*Assumptions!B97*Assumptions!B94,0) -> 99 | K10: =ROUND(E10*Assumptions!B57*Assumptions!B58,0) -> 885 | L10: =ROUND(IF(A10<Assumptions!B113,0,IF(A10<=18,Assumptions!B105,Assumptions!B107)/1000*Assumptions!B115*0.55+IF(A10>=Assumptions!B114,IF(A10<=18,Assumptions!B105,Assumptions!B107)*Assumptions!B109/1000*Assumptions!B116*0.55,0)),0) -> 0 | M10: =I10+J10+K10+L10 -> 1360 | N10: =ROUND(H10*Assumptions!B62*Assumptions!B61,0)+Assumptions!B63+IF(H10>Assumptions!B64,45,0)+Assumptions!B65+Assumptions!B66+Assumptions!B67+Assumptions!B68+Assumptions!B69/12+IF(A10>=3,Assumptions!B72,0)+ROUND(I10*Assumptions!B70+H10*Assumptions!B71,0)+0 -> 220 | O10: =M10-N10 -> 1140 | P10: =IF((Q9+O10)<N10*Assumptions!B89,0,IF((Q9+O10)<N10*6,ROUND(MAX(O10,0)*Assumptions!B90,0),ROUND(MAX(O10,0)*Assumptions!B91,0))) -> 0 | Q10: =Q9+O10-P10 -> -1219
A11: 8 | B11: =ROUND(B10*(1+Assumptions!B36),0) -> 2968 | C11: =ROUND(IF(A11<Assumptions!B100,0,IF(A11<=8,Assumptions!B103,IF(A11<=12,Assumptions!B104,IF(A11<=18,Assumptions!B105,IF(A11<=24,Assumptions!B106,Assumptions!B107))))*(1+IF(A11>=Assumptions!B101,Assumptions!B109,0))*Assumptions!B111),0) -> 10 | D11: =ROUND(ROUND(Assumptions!B119*(1+Assumptions!B120)^6*(1+Assumptions!B121)^(A11-6),0)*Assumptions!B123,0) -> 3 | E11: =B11+C11+D11 -> 2981 | F11: =ROUND(E11*Assumptions!B24,0) -> 15 | G11: =ROUND(H10*Assumptions!B52,0) -> 3 | H11: =H10+F11-G11 -> 59 | I11: =ROUND(H11*Assumptions!B14,0) -> 472 | J11: =ROUND(E11*Assumptions!B95*Assumptions!B96*Assumptions!B97*Assumptions!B94,0) -> 116 | K11: =ROUND(E11*Assumptions!B57*Assumptions!B58,0) -> 1043 | L11: =ROUND(IF(A11<Assumptions!B113,0,IF(A11<=18,Assumptions!B105,Assumptions!B107)/1000*Assumptions!B115*0.55+IF(A11>=Assumptions!B114,IF(A11<=18,Assumptions!B105,Assumptions!B107)*Assumptions!B109/1000*Assumptions!B116*0.55,0)),0) -> 0 | M11: =I11+J11+K11+L11 -> 1631 | N11: =ROUND(H11*Assumptions!B62*Assumptions!B61,0)+Assumptions!B63+IF(H11>Assumptions!B64,45,0)+Assumptions!B65+Assumptions!B66+Assumptions!B67+Assumptions!B68+Assumptions!B69/12+IF(A11>=3,Assumptions!B72,0)+ROUND(I11*Assumptions!B70+H11*Assumptions!B71,0)+0 -> 230 | O11: =M11-N11 -> 1401 | P11: =IF((Q10+O11)<N11*Assumptions!B89,0,IF((Q10+O11)<N11*6,ROUND(MAX(O11,0)*Assumptions!B90,0),ROUND(MAX(O11,0)*Assumptions!B91,0))) -> 0 | Q11: =Q10+O11-P11 -> 182
A12: 9 | B12: =ROUND(B11*(1+Assumptions!B36),0) -> 3502 | C12: =ROUND(IF(A12<Assumptions!B100,0,IF(A12<=8,Assumptions!B103,IF(A12<=12,Assumptions!B104,IF(A12<=18,Assumptions!B105,IF(A12<=24,Assumptions!B106,Assumptions!B107))))*(1+IF(A12>=Assumptions!B101,Assumptions!B109,0))*Assumptions!B111),0) -> 60 | D12: =ROUND(ROUND(Assumptions!B119*(1+Assumptions!B120)^6*(1+Assumptions!B121)^(A12-6),0)*Assumptions!B123,0) -> 3 | E12: =B12+C12+D12 -> 3565 | F12: =ROUND(E12*Assumptions!B24,0) -> 18 | G12: =ROUND(H11*Assumptions!B52,0) -> 4 | H12: =H11+F12-G12 -> 73 | I12: =ROUND(H12*((Assumptions!B14+Assumptions!B15)/2),0) -> 767 | J12: =ROUND(E12*Assumptions!B95*Assumptions!B96*Assumptions!B97*Assumptions!B94,0) -> 139 | K12: =ROUND(E12*Assumptions!B57*Assumptions!B58,0) -> 1248 | L12: =ROUND(IF(A12<Assumptions!B113,0,IF(A12<=18,Assumptions!B105,Assumptions!B107)/1000*Assumptions!B115*0.55+IF(A12>=Assumptions!B114,IF(A12<=18,Assumptions!B105,Assumptions!B107)*Assumptions!B109/1000*Assumptions!B116*0.55,0)),0) -> 0 | M12: =I12+J12+K12+L12 -> 2154 | N12: =ROUND(H12*Assumptions!B62*Assumptions!B61,0)+Assumptions!B63+IF(H12>Assumptions!B64,45,0)+Assumptions!B65+Assumptions!B66+Assumptions!B67+Assumptions!B68+Assumptions!B69/12+IF(A12>=3,Assumptions!B72,0)+ROUND(I12*Assumptions!B70+H12*Assumptions!B71,0)+0 -> 246 | O12: =M12-N12 -> 1908 | P12: =IF((Q11+O12)<N12*Assumptions!B89,0,IF((Q11+O12)<N12*6,ROUND(MAX(O12,0)*Assumptions!B90,0),ROUND(MAX(O12,0)*Assumptions!B91,0))) -> 954 | Q12: =Q11+O12-P12 -> 1136
A13: 10 | B13: =ROUND(B12*(1+Assumptions!B36),0) -> 4132 | C13: =ROUND(IF(A13<Assumptions!B100,0,IF(A13<=8,Assumptions!B103,IF(A13<=12,Assumptions!B104,IF(A13<=18,Assumptions!B105,IF(A13<=24,Assumptions!B106,Assumptions!B107))))*(1+IF(A13>=Assumptions!B101,Assumptions!B109,0))*Assumptions!B111),0) -> 60 | D13: =ROUND(ROUND(Assumptions!B119*(1+Assumptions!B120)^6*(1+Assumptions!B121)^(A13-6),0)*Assumptions!B123,0) -> 4 | E13: =B13+C13+D13 -> 4196 | F13: =ROUND(E13*Assumptions!B24,0) -> 21 | G13: =ROUND(H12*Assumptions!B52,0) -> 4 | H13: =H12+F13-G13 -> 90 | I13: =ROUND(H13*(Assumptions!B15*0.85+Assumptions!B11*0.15),0) -> 1033 | J13: =ROUND(E13*Assumptions!B95*Assumptions!B96*Assumptions!B97*Assumptions!B94,0) -> 164 | K13: =ROUND(E13*Assumptions!B57*Assumptions!B58,0) -> 1469 | L13: =ROUND(IF(A13<Assumptions!B113,0,IF(A13<=18,Assumptions!B105,Assumptions!B107)/1000*Assumptions!B115*0.55+IF(A13>=Assumptions!B114,IF(A13<=18,Assumptions!B105,Assumptions!B107)*Assumptions!B109/1000*Assumptions!B116*0.55,0)),0) -> 0 | M13: =I13+J13+K13+L13 -> 2666 | N13: =ROUND(H13*Assumptions!B62*Assumptions!B61,0)+Assumptions!B63+IF(H13>Assumptions!B64,45,0)+Assumptions!B65+Assumptions!B66+Assumptions!B67+Assumptions!B68+Assumptions!B69/12+IF(A13>=3,Assumptions!B72,0)+ROUND(I13*Assumptions!B70+H13*Assumptions!B71,0)+0 -> 264 | O13: =M13-N13 -> 2402 | P13: =IF((Q12+O13)<N13*Assumptions!B89,0,IF((Q12+O13)<N13*6,ROUND(MAX(O13,0)*Assumptions!B90,0),ROUND(MAX(O13,0)*Assumptions!B91,0))) -> 1201 | Q13: =Q12+O13-P13 -> 2337
A14: 11 | B14: =ROUND(B13*(1+Assumptions!B36),0) -> 4876 | C14: =ROUND(IF(A14<Assumptions!B100,0,IF(A14<=8,Assumptions!B103,IF(A14<=12,Assumptions!B104,IF(A14<=18,Assumptions!B105,IF(A14<=24,Assumptions!B106,Assumptions!B107))))*(1+IF(A14>=Assumptions!B101,Assumptions!B109,0))*Assumptions!B111),0) -> 60 | D14: =ROUND(ROUND(Assumptions!B119*(1+Assumptions!B120)^6*(1+Assumptions!B121)^(A14-6),0)*Assumptions!B123,0) -> 5 | E14: =B14+C14+D14 -> 4941 | F14: =ROUND(E14*Assumptions!B24,0) -> 25 | G14: =ROUND(H13*Assumptions!B52,0) -> 5 | H14: =H13+F14-G14 -> 110 | I14: =ROUND(H14*(Assumptions!B15*0.85+Assumptions!B11*0.15),0) -> 1262 | J14: =ROUND(E14*Assumptions!B95*Assumptions!B96*Assumptions!B97*Assumptions!B94,0) -> 193 | K14: =ROUND(E14*Assumptions!B57*Assumptions!B58,0) -> 1729 | L14: =ROUND(IF(A14<Assumptions!B113,0,IF(A14<=18,Assumptions!B105,Assumptions!B107)/1000*Assumptions!B115*0.55+IF(A14>=Assumptions!B114,IF(A14<=18,Assumptions!B105,Assumptions!B107)*Assumptions!B109/1000*Assumptions!B116*0.55,0)),0) -> 0 | M14: =I14+J14+K14+L14 -> 3184 | N14: =ROUND(H14*Assumptions!B62*Assumptions!B61,0)+Assumptions!B63+IF(H14>Assumptions!B64,45,0)+Assumptions!B65+Assumptions!B66+Assumptions!B67+Assumptions!B68+Assumptions!B69/12+IF(A14>=3,Assumptions!B72,0)+ROUND(I14*Assumptions!B70+H14*Assumptions!B71,0)+0 -> 283 | O14: =M14-N14 -> 2901 | P14: =IF((Q13+O14)<N14*Assumptions!B89,0,IF((Q13+O14)<N14*6,ROUND(MAX(O14,0)*Assumptions!B90,0),ROUND(MAX(O14,0)*Assumptions!B91,0))) -> 1451 | Q14: =Q13+O14-P14 -> 3787
A15: 12 | B15: =ROUND(B14*(1+Assumptions!B36),0) -> 5754 | C15: =ROUND(IF(A15<Assumptions!B100,0,IF(A15<=8,Assumptions!B103,IF(A15<=12,Assumptions!B104,IF(A15<=18,Assumptions!B105,IF(A15<=24,Assumptions!B106,Assumptions!B107))))*(1+IF(A15>=Assumptions!B101,Assumptions!B109,0))*Assumptions!B111),0) -> 60 | D15: =ROUND(ROUND(Assumptions!B119*(1+Assumptions!B120)^6*(1+Assumptions!B121)^(A15-6),0)*Assumptions!B123,0) -> 5 | E15: =B15+C15+D15 -> 5819 | F15: =ROUND(E15*Assumptions!B24,0) -> 29 | G15: =ROUND(H14*Assumptions!B52,0) -> 7 | H15: =H14+F15-G15 -> 132 | I15: =ROUND(H15*(Assumptions!B15*0.85+Assumptions!B11*0.15),0) -> 1515 | J15: =ROUND(E15*Assumptions!B95*Assumptions!B96*Assumptions!B97*Assumptions!B94,0) -> 227 | K15: =ROUND(E15*Assumptions!B57*Assumptions!B58,0) -> 2037 | L15: =ROUND(IF(A15<Assumptions!B113,0,IF(A15<=18,Assumptions!B105,Assumptions!B107)/1000*Assumptions!B115*0.55+IF(A15>=Assumptions!B114,IF(A15<=18,Assumptions!B105,Assumptions!B107)*Assumptions!B109/1000*Assumptions!B116*0.55,0)),0) -> 22 | M15: =I15+J15+K15+L15 -> 3801 | N15: =ROUND(H15*Assumptions!B62*Assumptions!B61,0)+Assumptions!B63+IF(H15>Assumptions!B64,45,0)+Assumptions!B65+Assumptions!B66+Assumptions!B67+Assumptions!B68+Assumptions!B69/12+IF(A15>=3,Assumptions!B72,0)+ROUND(I15*Assumptions!B70+H15*Assumptions!B71,0)+0 -> 303 | O15: =M15-N15 -> 3498 | P15: =IF((Q14+O15)<N15*Assumptions!B89,0,IF((Q14+O15)<N15*6,ROUND(MAX(O15,0)*Assumptions!B90,0),ROUND(MAX(O15,0)*Assumptions!B91,0))) -> 1749 | Q15: =Q14+O15-P15 -> 5536
A16: 13 | B16: =ROUND(B15*(1+Assumptions!B40),0) -> 6444 | C16: =ROUND(IF(A16<Assumptions!B100,0,IF(A16<=8,Assumptions!B103,IF(A16<=12,Assumptions!B104,IF(A16<=18,Assumptions!B105,IF(A16<=24,Assumptions!B106,Assumptions!B107))))*(1+IF(A16>=Assumptions!B101,Assumptions!B109,0))*Assumptions!B111),0) -> 150 | D16: =ROUND(ROUND(Assumptions!B119*(1+Assumptions!B120)^6*(1+Assumptions!B121)^6*(1+Assumptions!B122)^(A16-12),0)*Assumptions!B123,0) -> 6 | E16: =B16+C16+D16 -> 6600 | F16: =ROUND(E16*Assumptions!B24,0) -> 33 | G16: =ROUND(H15*Assumptions!B52,0) -> 8 | H16: =H15+F16-G16 -> 157 | I16: =ROUND(H16*(Assumptions!B15*0.85+Assumptions!B11*0.15),0) -> 1802 | J16: =ROUND(E16*Assumptions!B95*Assumptions!B96*Assumptions!B97*Assumptions!B94,0) -> 257 | K16: =ROUND(E16*Assumptions!B57*Assumptions!B58,0) -> 2310 | L16: =ROUND(IF(A16<Assumptions!B113,0,IF(A16<=18,Assumptions!B105,Assumptions!B107)/1000*Assumptions!B115*0.55+IF(A16>=Assumptions!B114,IF(A16<=18,Assumptions!B105,Assumptions!B107)*Assumptions!B109/1000*Assumptions!B116*0.55,0)),0) -> 22 | M16: =I16+J16+K16+L16 -> 4391 | N16: =ROUND(H16*Assumptions!B62*Assumptions!B61,0)+Assumptions!B63+IF(H16>Assumptions!B64,45,0)+Assumptions!B65+Assumptions!B66+Assumptions!B67+Assumptions!B68+Assumptions!B69/12+IF(A16>=3,Assumptions!B72,0)+ROUND(I16*Assumptions!B70+H16*Assumptions!B71,0)+0 -> 325 | O16: =M16-N16 -> 4066 | P16: =IF((Q15+O16)<N16*Assumptions!B89,0,IF((Q15+O16)<N16*6,ROUND(MAX(O16,0)*Assumptions!B90,0),ROUND(MAX(O16,0)*Assumptions!B91,0))) -> 2033 | Q16: =Q15+O16-P16 -> 7569
A17: 14 | B17: =ROUND(B16*(1+Assumptions!B40),0) -> 7217 | C17: =ROUND(IF(A17<Assumptions!B100,0,IF(A17<=8,Assumptions!B103,IF(A17<=12,Assumptions!B104,IF(A17<=18,Assumptions!B105,IF(A17<=24,Assumptions!B106,Assumptions!B107))))*(1+IF(A17>=Assumptions!B101,Assumptions!B109,0))*Assumptions!B111),0) -> 150 | D17: =ROUND(ROUND(Assumptions!B119*(1+Assumptions!B120)^6*(1+Assumptions!B121)^6*(1+Assumptions!B122)^(A17-12),0)*Assumptions!B123,0) -> 6 | E17: =B17+C17+D17 -> 7373 | F17: =ROUND(E17*Assumptions!B24,0) -> 37 | G17: =ROUND(H16*Assumptions!B52,0) -> 9 | H17: =H16+F17-G17 -> 185 | I17: =ROUND(H17*(Assumptions!B15*0.85+Assumptions!B11*0.15),0) -> 2123 | J17: =ROUND(E17*Assumptions!B95*Assumptions!B96*Assumptions!B97*Assumptions!B94,0) -> 288 | K17: =ROUND(E17*Assumptions!B57*Assumptions!B58,0) -> 2581 | L17: =ROUND(IF(A17<Assumptions!B113,0,IF(A17<=18,Assumptions!B105,Assumptions!B107)/1000*Assumptions!B115*0.55+IF(A17>=Assumptions!B114,IF(A17<=18,Assumptions!B105,Assumptions!B107)*Assumptions!B109/1000*Assumptions!B116*0.55,0)),0) -> 22 | M17: =I17+J17+K17+L17 -> 5014 | N17: =ROUND(H17*Assumptions!B62*Assumptions!B61,0)+Assumptions!B63+IF(H17>Assumptions!B64,45,0)+Assumptions!B65+Assumptions!B66+Assumptions!B67+Assumptions!B68+Assumptions!B69/12+IF(A17>=3,Assumptions!B72,0)+ROUND(I17*Assumptions!B70+H17*Assumptions!B71,0)+0 -> 351 | O17: =M17-N17 -> 4663 | P17: =IF((Q16+O17)<N17*Assumptions!B89,0,IF((Q16+O17)<N17*6,ROUND(MAX(O17,0)*Assumptions!B90,0),ROUND(MAX(O17,0)*Assumptions!B91,0))) -> 2332 | Q17: =Q16+O17-P17 -> 9900
A18: 15 | B18: =ROUND(B17*(1+Assumptions!B40),0) -> 8083 | C18: =ROUND(IF(A18<Assumptions!B100,0,IF(A18<=8,Assumptions!B103,IF(A18<=12,Assumptions!B104,IF(A18<=18,Assumptions!B105,IF(A18<=24,Assumptions!B106,Assumptions!B107))))*(1+IF(A18>=Assumptions!B101,Assumptions!B109,0))*Assumptions!B111),0) -> 150 | D18: =ROUND(ROUND(Assumptions!B119*(1+Assumptions!B120)^6*(1+Assumptions!B121)^6*(1+Assumptions!B122)^(A18-12),0)*Assumptions!B123,0) -> 7 | E18: =B18+C18+D18 -> 8240 | F18: =ROUND(E18*Assumptions!B24,0) -> 41 | G18: =ROUND(H17*Assumptions!B52,0) -> 11 | H18: =H17+F18-G18 -> 215 | I18: =ROUND(H18*(Assumptions!B15*0.85+Assumptions!B11*0.15),0) -> 2467 | J18: =ROUND(E18*Assumptions!B95*Assumptions!B96*Assumptions!B97*Assumptions!B94,0) -> 321 | K18: =ROUND(E18*Assumptions!B57*Assumptions!B58,0) -> 2884 | L18: =ROUND(IF(A18<Assumptions!B113,0,IF(A18<=18,Assumptions!B105,Assumptions!B107)/1000*Assumptions!B115*0.55+IF(A18>=Assumptions!B114,IF(A18<=18,Assumptions!B105,Assumptions!B107)*Assumptions!B109/1000*Assumptions!B116*0.55,0)),0) -> 22 | M18: =I18+J18+K18+L18 -> 5694 | N18: =ROUND(H18*Assumptions!B62*Assumptions!B61,0)+Assumptions!B63+IF(H18>Assumptions!B64,45,0)+Assumptions!B65+Assumptions!B66+Assumptions!B67+Assumptions!B68+Assumptions!B69/12+IF(A18>=3,Assumptions!B72,0)+ROUND(I18*Assumptions!B70+H18*Assumptions!B71,0)+0 -> 378 | O18: =M18-N18 -> 5316 | P18: =IF((Q17+O18)<N18*Assumptions!B89,0,IF((Q17+O18)<N18*6,ROUND(MAX(O18,0)*Assumptions!B90,0),ROUND(MAX(O18,0)*Assumptions!B91,0))) -> 2658 | Q18: =Q17+O18-P18 -> 12558
A19: 16 | B19: =ROUND(B18*(1+Assumptions!B40),0) -> 9053 | C19: =ROUND(IF(A19<Assumptions!B100,0,IF(A19<=8,Assumptions!B103,IF(A19<=12,Assumptions!B104,IF(A19<=18,Assumptions!B105,IF(A19<=24,Assumptions!B106,Assumptions!B107))))*(1+IF(A19>=Assumptions!B101,Assumptions!B109,0))*Assumptions!B111),0) -> 150 | D19: =ROUND(ROUND(Assumptions!B119*(1+Assumptions!B120)^6*(1+Assumptions!B121)^6*(1+Assumptions!B122)^(A19-12),0)*Assumptions!B123,0) -> 8 | E19: =B19+C19+D19 -> 9211 | F19: =ROUND(E19*Assumptions!B24,0) -> 46 | G19: =ROUND(H18*Assumptions!B52,0) -> 13 | H19: =H18+F19-G19 -> 248 | I19: =ROUND(H19*(Assumptions!B15*0.85+Assumptions!B11*0.15),0) -> 2846 | J19: =ROUND(E19*Assumptions!B95*Assumptions!B96*Assumptions!B97*Assumptions!B94,0) -> 359 | K19: =ROUND(E19*Assumptions!B57*Assumptions!B58,0) -> 3224 | L19: =ROUND(IF(A19<Assumptions!B113,0,IF(A19<=18,Assumptions!B105,Assumptions!B107)/1000*Assumptions!B115*0.55+IF(A19>=Assumptions!B114,IF(A19<=18,Assumptions!B105,Assumptions!B107)*Assumptions!B109/1000*Assumptions!B116*0.55,0)),0) -> 26 | M19: =I19+J19+K19+L19 -> 6455 | N19: =ROUND(H19*Assumptions!B62*Assumptions!B61,0)+Assumptions!B63+IF(H19>Assumptions!B64,45,0)+Assumptions!B65+Assumptions!B66+Assumptions!B67+Assumptions!B68+Assumptions!B69/12+IF(A19>=3,Assumptions!B72,0)+ROUND(I19*Assumptions!B70+H19*Assumptions!B71,0)+0 -> 408 | O19: =M19-N19 -> 6047 | P19: =IF((Q18+O19)<N19*Assumptions!B89,0,IF((Q18+O19)<N19*6,ROUND(MAX(O19,0)*Assumptions!B90,0),ROUND(MAX(O19,0)*Assumptions!B91,0))) -> 3024 | Q19: =Q18+O19-P19 -> 15581
A20: 17 | B20: =ROUND(B19*(1+Assumptions!B40),0) -> 10139 | C20: =ROUND(IF(A20<Assumptions!B100,0,IF(A20<=8,Assumptions!B103,IF(A20<=12,Assumptions!B104,IF(A20<=18,Assumptions!B105,IF(A20<=24,Assumptions!B106,Assumptions!B107))))*(1+IF(A20>=Assumptions!B101,Assumptions!B109,0))*Assumptions!B111),0) -> 150 | D20: =ROUND(ROUND(Assumptions!B119*(1+Assumptions!B120)^6*(1+Assumptions!B121)^6*(1+Assumptions!B122)^(A20-12),0)*Assumptions!B123,0) -> 8 | E20: =B20+C20+D20 -> 10297 | F20: =ROUND(E20*Assumptions!B24,0) -> 51 | G20: =ROUND(H19*Assumptions!B52,0) -> 15 | H20: =H19+F20-G20 -> 284 | I20: =ROUND(H20*(Assumptions!B15*0.85+Assumptions!B11*0.15),0) -> 3259 | J20: =ROUND(E20*Assumptions!B95*Assumptions!B96*Assumptions!B97*Assumptions!B94,0) -> 402 | K20: =ROUND(E20*Assumptions!B57*Assumptions!B58,0) -> 3604 | L20: =ROUND(IF(A20<Assumptions!B113,0,IF(A20<=18,Assumptions!B105,Assumptions!B107)/1000*Assumptions!B115*0.55+IF(A20>=Assumptions!B114,IF(A20<=18,Assumptions!B105,Assumptions!B107)*Assumptions!B109/1000*Assumptions!B116*0.55,0)),0) -> 26 | M20: =I20+J20+K20+L20 -> 7291 | N20: =ROUND(H20*Assumptions!B62*Assumptions!B61,0)+Assumptions!B63+IF(H20>Assumptions!B64,45,0)+Assumptions!B65+Assumptions!B66+Assumptions!B67+Assumptions!B68+Assumptions!B69/12+IF(A20>=3,Assumptions!B72,0)+ROUND(I20*Assumptions!B70+H20*Assumptions!B71,0)+0 -> 442 | O20: =M20-N20 -> 6849 | P20: =IF((Q19+O20)<N20*Assumptions!B89,0,IF((Q19+O20)<N20*6,ROUND(MAX(O20,0)*Assumptions!B90,0),ROUND(MAX(O20,0)*Assumptions!B91,0))) -> 3425 | Q20: =Q19+O20-P20 -> 19005
A21: 18 | B21: =ROUND(B20*(1+Assumptions!B40),0) -> 11356 | C21: =ROUND(IF(A21<Assumptions!B100,0,IF(A21<=8,Assumptions!B103,IF(A21<=12,Assumptions!B104,IF(A21<=18,Assumptions!B105,IF(A21<=24,Assumptions!B106,Assumptions!B107))))*(1+IF(A21>=Assumptions!B101,Assumptions!B109,0))*Assumptions!B111),0) -> 150 | D21: =ROUND(ROUND(Assumptions!B119*(1+Assumptions!B120)^6*(1+Assumptions!B121)^6*(1+Assumptions!B122)^(A21-12),0)*Assumptions!B123,0) -> 9 | E21: =B21+C21+D21 -> 11515 | F21: =ROUND(E21*Assumptions!B24,0) -> 58 | G21: =ROUND(H20*Assumptions!B52,0) -> 17 | H21: =H20+F21-G21 -> 325 | I21: =ROUND(H21*(Assumptions!B15*0.85+Assumptions!B11*0.15),0) -> 3729 | J21: =ROUND(E21*Assumptions!B95*Assumptions!B96*Assumptions!B97*Assumptions!B94,0) -> 449 | K21: =ROUND(E21*Assumptions!B57*Assumptions!B58,0) -> 4030 | L21: =ROUND(IF(A21<Assumptions!B113,0,IF(A21<=18,Assumptions!B105,Assumptions!B107)/1000*Assumptions!B115*0.55+IF(A21>=Assumptions!B114,IF(A21<=18,Assumptions!B105,Assumptions!B107)*Assumptions!B109/1000*Assumptions!B116*0.55,0)),0) -> 26 | M21: =I21+J21+K21+L21 -> 8234 | N21: =ROUND(H21*Assumptions!B62*Assumptions!B61,0)+Assumptions!B63+IF(H21>Assumptions!B64,45,0)+Assumptions!B65+Assumptions!B66+Assumptions!B67+Assumptions!B68+Assumptions!B69/12+IF(A21>=3,Assumptions!B72,0)+ROUND(I21*Assumptions!B70+H21*Assumptions!B71,0)+0 -> 479 | O21: =M21-N21 -> 7755 | P21: =IF((Q20+O21)<N21*Assumptions!B89,0,IF((Q20+O21)<N21*6,ROUND(MAX(O21,0)*Assumptions!B90,0),ROUND(MAX(O21,0)*Assumptions!B91,0))) -> 3878 | Q21: =Q20+O21-P21 -> 22882
A22: 19 | B22: =ROUND(B21*(1+Assumptions!B40),0) -> 12719 | C22: =ROUND(IF(A22<Assumptions!B100,0,IF(A22<=8,Assumptions!B103,IF(A22<=12,Assumptions!B104,IF(A22<=18,Assumptions!B105,IF(A22<=24,Assumptions!B106,Assumptions!B107))))*(1+IF(A22>=Assumptions!B101,Assumptions!B109,0))*Assumptions!B111),0) -> 300 | D22: =ROUND(ROUND(Assumptions!B119*(1+Assumptions!B120)^6*(1+Assumptions!B121)^6*(1+Assumptions!B122)^(A22-12),0)*Assumptions!B123,0) -> 10 | E22: =B22+C22+D22 -> 13029 | F22: =ROUND(E22*Assumptions!B24,0) -> 65 | G22: =ROUND(H21*Assumptions!B52,0) -> 20 | H22: =H21+F22-G22 -> 370 | I22: =ROUND(H22*(Assumptions!B15*0.85+Assumptions!B11*0.15),0) -> 4246 | J22: =ROUND(E22*Assumptions!B95*Assumptions!B96*Assumptions!B97*Assumptions!B94,0) -> 508 | K22: =ROUND(E22*Assumptions!B57*Assumptions!B58,0) -> 4560 | L22: =ROUND(IF(A22<Assumptions!B113,0,IF(A22<=18,Assumptions!B105,Assumptions!B107)/1000*Assumptions!B115*0.55+IF(A22>=Assumptions!B114,IF(A22<=18,Assumptions!B105,Assumptions!B107)*Assumptions!B109/1000*Assumptions!B116*0.55,0)),0) -> 94 | M22: =I22+J22+K22+L22 -> 9408 | N22: =ROUND(H22*Assumptions!B62*Assumptions!B61,0)+Assumptions!B63+IF(H22>Assumptions!B64,45,0)+Assumptions!B65+Assumptions!B66+Assumptions!B67+Assumptions!B68+Assumptions!B69/12+IF(A22>=3,Assumptions!B72,0)+ROUND(I22*Assumptions!B70+H22*Assumptions!B71,0)+0 -> 520 | O22: =M22-N22 -> 8888 | P22: =IF((Q21+O22)<N22*Assumptions!B89,0,IF((Q21+O22)<N22*6,ROUND(MAX(O22,0)*Assumptions!B90,0),ROUND(MAX(O22,0)*Assumptions!B91,0))) -> 4444 | Q22: =Q21+O22-P22 -> 27326
A23: 20 | B23: =ROUND(B22*(1+Assumptions!B40),0) -> 14245 | C23: =ROUND(IF(A23<Assumptions!B100,0,IF(A23<=8,Assumptions!B103,IF(A23<=12,Assumptions!B104,IF(A23<=18,Assumptions!B105,IF(A23<=24,Assumptions!B106,Assumptions!B107))))*(1+IF(A23>=Assumptions!B101,Assumptions!B109,0))*Assumptions!B111),0) -> 300 | D23: =ROUND(ROUND(Assumptions!B119*(1+Assumptions!B120)^6*(1+Assumptions!B121)^6*(1+Assumptions!B122)^(A23-12),0)*Assumptions!B123,0) -> 11 | E23: =B23+C23+D23 -> 14556 | F23: =ROUND(E23*Assumptions!B24,0) -> 73 | G23: =ROUND(H22*Assumptions!B52,0) -> 22 | H23: =H22+F23-G23 -> 421 | I23: =ROUND(H23*(Assumptions!B15*0.85+Assumptions!B11*0.15),0) -> 4831 | J23: =ROUND(E23*Assumptions!B95*Assumptions!B96*Assumptions!B97*Assumptions!B94,0) -> 568 | K23: =ROUND(E23*Assumptions!B57*Assumptions!B58,0) -> 5095 | L23: =ROUND(IF(A23<Assumptions!B113,0,IF(A23<=18,Assumptions!B105,Assumptions!B107)/1000*Assumptions!B115*0.55+IF(A23>=Assumptions!B114,IF(A23<=18,Assumptions!B105,Assumptions!B107)*Assumptions!B109/1000*Assumptions!B116*0.55,0)),0) -> 94 | M23: =I23+J23+K23+L23 -> 10588 | N23: =ROUND(H23*Assumptions!B62*Assumptions!B61,0)+Assumptions!B63+IF(H23>Assumptions!B64,45,0)+Assumptions!B65+Assumptions!B66+Assumptions!B67+Assumptions!B68+Assumptions!B69/12+IF(A23>=3,Assumptions!B72,0)+ROUND(I23*Assumptions!B70+H23*Assumptions!B71,0)+0 -> 566 | O23: =M23-N23 -> 10022 | P23: =IF((Q22+O23)<N23*Assumptions!B89,0,IF((Q22+O23)<N23*6,ROUND(MAX(O23,0)*Assumptions!B90,0),ROUND(MAX(O23,0)*Assumptions!B91,0))) -> 5011 | Q23: =Q22+O23-P23 -> 32337
A24: 21 | B24: =ROUND(B23*(1+Assumptions!B40),0) -> 15954 | C24: =ROUND(IF(A24<Assumptions!B100,0,IF(A24<=8,Assumptions!B103,IF(A24<=12,Assumptions!B104,IF(A24<=18,Assumptions!B105,IF(A24<=24,Assumptions!B106,Assumptions!B107))))*(1+IF(A24>=Assumptions!B101,Assumptions!B109,0))*Assumptions!B111),0) -> 300 | D24: =ROUND(ROUND(Assumptions!B119*(1+Assumptions!B120)^6*(1+Assumptions!B121)^6*(1+Assumptions!B122)^(A24-12),0)*Assumptions!B123,0) -> 12 | E24: =B24+C24+D24 -> 16266 | F24: =ROUND(E24*Assumptions!B24,0) -> 81 | G24: =ROUND(H23*Assumptions!B52,0) -> 25 | H24: =H23+F24-G24 -> 477 | I24: =ROUND(H24*(Assumptions!B15*0.85+Assumptions!B11*0.15),0) -> 5474 | J24: =ROUND(E24*Assumptions!B95*Assumptions!B96*Assumptions!B97*Assumptions!B94,0) -> 634 | K24: =ROUND(E24*Assumptions!B57*Assumptions!B58,0) -> 5693 | L24: =ROUND(IF(A24<Assumptions!B113,0,IF(A24<=18,Assumptions!B105,Assumptions!B107)/1000*Assumptions!B115*0.55+IF(A24>=Assumptions!B114,IF(A24<=18,Assumptions!B105,Assumptions!B107)*Assumptions!B109/1000*Assumptions!B116*0.55,0)),0) -> 94 | M24: =I24+J24+K24+L24 -> 11895 | N24: =ROUND(H24*Assumptions!B62*Assumptions!B61,0)+Assumptions!B63+IF(H24>Assumptions!B64,45,0)+Assumptions!B65+Assumptions!B66+Assumptions!B67+Assumptions!B68+Assumptions!B69/12+IF(A24>=3,Assumptions!B72,0)+ROUND(I24*Assumptions!B70+H24*Assumptions!B71,0)+0 -> 618 | O24: =M24-N24 -> 11277 | P24: =IF((Q23+O24)<N24*Assumptions!B89,0,IF((Q23+O24)<N24*6,ROUND(MAX(O24,0)*Assumptions!B90,0),ROUND(MAX(O24,0)*Assumptions!B91,0))) -> 5639 | Q24: =Q23+O24-P24 -> 37975
A25: 22 | B25: =ROUND(B24*(1+Assumptions!B40),0) -> 17868 | C25: =ROUND(IF(A25<Assumptions!B100,0,IF(A25<=8,Assumptions!B103,IF(A25<=12,Assumptions!B104,IF(A25<=18,Assumptions!B105,IF(A25<=24,Assumptions!B106,Assumptions!B107))))*(1+IF(A25>=Assumptions!B101,Assumptions!B109,0))*Assumptions!B111),0) -> 300 | D25: =ROUND(ROUND(Assumptions!B119*(1+Assumptions!B120)^6*(1+Assumptions!B121)^6*(1+Assumptions!B122)^(A25-12),0)*Assumptions!B123,0) -> 13 | E25: =B25+C25+D25 -> 18181 | F25: =ROUND(E25*Assumptions!B24,0) -> 91 | G25: =ROUND(H24*Assumptions!B52,0) -> 29 | H25: =H24+F25-G25 -> 539 | I25: =ROUND(H25*(Assumptions!B15*0.85+Assumptions!B11*0.15),0) -> 6185 | J25: =ROUND(E25*Assumptions!B95*Assumptions!B96*Assumptions!B97*Assumptions!B94,0) -> 709 | K25: =ROUND(E25*Assumptions!B57*Assumptions!B58,0) -> 6363 | L25: =ROUND(IF(A25<Assumptions!B113,0,IF(A25<=18,Assumptions!B105,Assumptions!B107)/1000*Assumptions!B115*0.55+IF(A25>=Assumptions!B114,IF(A25<=18,Assumptions!B105,Assumptions!B107)*Assumptions!B109/1000*Assumptions!B116*0.55,0)),0) -> 94 | M25: =I25+J25+K25+L25 -> 13351 | N25: =ROUND(H25*Assumptions!B62*Assumptions!B61,0)+Assumptions!B63+IF(H25>Assumptions!B64,45,0)+Assumptions!B65+Assumptions!B66+Assumptions!B67+Assumptions!B68+Assumptions!B69/12+IF(A25>=3,Assumptions!B72,0)+ROUND(I25*Assumptions!B70+H25*Assumptions!B71,0)+0 -> 719 | O25: =M25-N25 -> 12632 | P25: =IF((Q24+O25)<N25*Assumptions!B89,0,IF((Q24+O25)<N25*6,ROUND(MAX(O25,0)*Assumptions!B90,0),ROUND(MAX(O25,0)*Assumptions!B91,0))) -> 6316 | Q25: =Q24+O25-P25 -> 44291
A26: 23 | B26: =ROUND(B25*(1+Assumptions!B40),0) -> 20012 | C26: =ROUND(IF(A26<Assumptions!B100,0,IF(A26<=8,Assumptions!B103,IF(A26<=12,Assumptions!B104,IF(A26<=18,Assumptions!B105,IF(A26<=24,Assumptions!B106,Assumptions!B107))))*(1+IF(A26>=Assumptions!B101,Assumptions!B109,0))*Assumptions!B111),0) -> 300 | D26: =ROUND(ROUND(Assumptions!B119*(1+Assumptions!B120)^6*(1+Assumptions!B121)^6*(1+Assumptions!B122)^(A26-12),0)*Assumptions!B123,0) -> 15 | E26: =B26+C26+D26 -> 20327 | F26: =ROUND(E26*Assumptions!B24,0) -> 102 | G26: =ROUND(H25*Assumptions!B52,0) -> 32 | H26: =H25+F26-G26 -> 609 | I26: =ROUND(H26*(Assumptions!B15*0.85+Assumptions!B11*0.15),0) -> 6988 | J26: =ROUND(E26*Assumptions!B95*Assumptions!B96*Assumptions!B97*Assumptions!B94,0) -> 793 | K26: =ROUND(E26*Assumptions!B57*Assumptions!B58,0) -> 7114 | L26: =ROUND(IF(A26<Assumptions!B113,0,IF(A26<=18,Assumptions!B105,Assumptions!B107)/1000*Assumptions!B115*0.55+IF(A26>=Assumptions!B114,IF(A26<=18,Assumptions!B105,Assumptions!B107)*Assumptions!B109/1000*Assumptions!B116*0.55,0)),0) -> 94 | M26: =I26+J26+K26+L26 -> 14989 | N26: =ROUND(H26*Assumptions!B62*Assumptions!B61,0)+Assumptions!B63+IF(H26>Assumptions!B64,45,0)+Assumptions!B65+Assumptions!B66+Assumptions!B67+Assumptions!B68+Assumptions!B69/12+IF(A26>=3,Assumptions!B72,0)+ROUND(I26*Assumptions!B70+H26*Assumptions!B71,0)+0 -> 783 | O26: =M26-N26 -> 14206 | P26: =IF((Q25+O26)<N26*Assumptions!B89,0,IF((Q25+O26)<N26*6,ROUND(MAX(O26,0)*Assumptions!B90,0),ROUND(MAX(O26,0)*Assumptions!B91,0))) -> 7103 | Q26: =Q25+O26-P26 -> 51394
A27: 24 | B27: =ROUND(B26*(1+Assumptions!B40),0) -> 22413 | C27: =ROUND(IF(A27<Assumptions!B100,0,IF(A27<=8,Assumptions!B103,IF(A27<=12,Assumptions!B104,IF(A27<=18,Assumptions!B105,IF(A27<=24,Assumptions!B106,Assumptions!B107))))*(1+IF(A27>=Assumptions!B101,Assumptions!B109,0))*Assumptions!B111),0) -> 300 | D27: =ROUND(ROUND(Assumptions!B119*(1+Assumptions!B120)^6*(1+Assumptions!B121)^6*(1+Assumptions!B122)^(A27-12),0)*Assumptions!B123,0) -> 16 | E27: =B27+C27+D27 -> 22729 | F27: =ROUND(E27*Assumptions!B24,0) -> 114 | G27: =ROUND(H26*Assumptions!B52,0) -> 37 | H27: =H26+F27-G27 -> 686 | I27: =ROUND(H27*(Assumptions!B15*0.85+Assumptions!B11*0.15),0) -> 7872 | J27: =ROUND(E27*Assumptions!B95*Assumptions!B96*Assumptions!B97*Assumptions!B94,0) -> 886 | K27: =ROUND(E27*Assumptions!B57*Assumptions!B58,0) -> 7955 | L27: =ROUND(IF(A27<Assumptions!B113,0,IF(A27<=18,Assumptions!B105,Assumptions!B107)/1000*Assumptions!B115*0.55+IF(A27>=Assumptions!B114,IF(A27<=18,Assumptions!B105,Assumptions!B107)*Assumptions!B109/1000*Assumptions!B116*0.55,0)),0) -> 94 | M27: =I27+J27+K27+L27 -> 16807 | N27: =ROUND(H27*Assumptions!B62*Assumptions!B61,0)+Assumptions!B63+IF(H27>Assumptions!B64,45,0)+Assumptions!B65+Assumptions!B66+Assumptions!B67+Assumptions!B68+Assumptions!B69/12+IF(A27>=3,Assumptions!B72,0)+ROUND(I27*Assumptions!B70+H27*Assumptions!B71,0)+0 -> 853 | O27: =M27-N27 -> 15954 | P27: =IF((Q26+O27)<N27*Assumptions!B89,0,IF((Q26+O27)<N27*6,ROUND(MAX(O27,0)*Assumptions!B90,0),ROUND(MAX(O27,0)*Assumptions!B91,0))) -> 7977 | Q27: =Q26+O27-P27 -> 59371
A28: 25 | B28: =ROUND(B27*(1+Assumptions!B44),0) -> 24206 | C28: =ROUND(IF(A28<Assumptions!B100,0,IF(A28<=8,Assumptions!B103,IF(A28<=12,Assumptions!B104,IF(A28<=18,Assumptions!B105,IF(A28<=24,Assumptions!B106,Assumptions!B107))))*(1+IF(A28>=Assumptions!B101,Assumptions!B109,0))*Assumptions!B111),0) -> 540 | D28: =ROUND(ROUND(Assumptions!B119*(1+Assumptions!B120)^6*(1+Assumptions!B121)^6*(1+Assumptions!B122)^(A28-12),0)*Assumptions!B123,0) -> 18 | E28: =B28+C28+D28 -> 24764 | F28: =ROUND(E28*Assumptions!B24,0) -> 124 | G28: =ROUND(H27*Assumptions!B52,0) -> 41 | H28: =H27+F28-G28 -> 769 | I28: =ROUND(H28*(Assumptions!B15*0.85+Assumptions!B11*0.15),0) -> 8824 | J28: =ROUND(E28*Assumptions!B95*Assumptions!B96*Assumptions!B97*Assumptions!B94,0) -> 966 | K28: =ROUND(E28*Assumptions!B57*Assumptions!B58,0) -> 8667 | L28: =ROUND(IF(A28<Assumptions!B113,0,IF(A28<=18,Assumptions!B105,Assumptions!B107)/1000*Assumptions!B115*0.55+IF(A28>=Assumptions!B114,IF(A28<=18,Assumptions!B105,Assumptions!B107)*Assumptions!B109/1000*Assumptions!B116*0.55,0)),0) -> 94 | M28: =I28+J28+K28+L28 -> 18551 | N28: =ROUND(H28*Assumptions!B62*Assumptions!B61,0)+Assumptions!B63+IF(H28>Assumptions!B64,45,0)+Assumptions!B65+Assumptions!B66+Assumptions!B67+Assumptions!B68+Assumptions!B69/12+IF(A28>=3,Assumptions!B72,0)+ROUND(I28*Assumptions!B70+H28*Assumptions!B71,0)+0 -> 929 | O28: =M28-N28 -> 17622 | P28: =IF((Q27+O28)<N28*Assumptions!B89,0,IF((Q27+O28)<N28*6,ROUND(MAX(O28,0)*Assumptions!B90,0),ROUND(MAX(O28,0)*Assumptions!B91,0))) -> 8811 | Q28: =Q27+O28-P28 -> 68182
A29: 26 | B29: =ROUND(B28*(1+Assumptions!B44),0) -> 26142 | C29: =ROUND(IF(A29<Assumptions!B100,0,IF(A29<=8,Assumptions!B103,IF(A29<=12,Assumptions!B104,IF(A29<=18,Assumptions!B105,IF(A29<=24,Assumptions!B106,Assumptions!B107))))*(1+IF(A29>=Assumptions!B101,Assumptions!B109,0))*Assumptions!B111),0) -> 540 | D29: =ROUND(ROUND(Assumptions!B119*(1+Assumptions!B120)^6*(1+Assumptions!B121)^6*(1+Assumptions!B122)^(A29-12),0)*Assumptions!B123,0) -> 20 | E29: =B29+C29+D29 -> 26702 | F29: =ROUND(E29*Assumptions!B24,0) -> 134 | G29: =ROUND(H28*Assumptions!B52,0) -> 46 | H29: =H28+F29-G29 -> 857 | I29: =ROUND(H29*(Assumptions!B15*0.85+Assumptions!B11*0.15),0) -> 9834 | J29: =ROUND(E29*Assumptions!B95*Assumptions!B96*Assumptions!B97*Assumptions!B94,0) -> 1041 | K29: =ROUND(E29*Assumptions!B57*Assumptions!B58,0) -> 9346 | L29: =ROUND(IF(A29<Assumptions!B113,0,IF(A29<=18,Assumptions!B105,Assumptions!B107)/1000*Assumptions!B115*0.55+IF(A29>=Assumptions!B114,IF(A29<=18,Assumptions!B105,Assumptions!B107)*Assumptions!B109/1000*Assumptions!B116*0.55,0)),0) -> 94 | M29: =I29+J29+K29+L29 -> 20315 | N29: =ROUND(H29*Assumptions!B62*Assumptions!B61,0)+Assumptions!B63+IF(H29>Assumptions!B64,45,0)+Assumptions!B65+Assumptions!B66+Assumptions!B67+Assumptions!B68+Assumptions!B69/12+IF(A29>=3,Assumptions!B72,0)+ROUND(I29*Assumptions!B70+H29*Assumptions!B71,0)+0 -> 1009 | O29: =M29-N29 -> 19306 | P29: =IF((Q28+O29)<N29*Assumptions!B89,0,IF((Q28+O29)<N29*6,ROUND(MAX(O29,0)*Assumptions!B90,0),ROUND(MAX(O29,0)*Assumptions!B91,0))) -> 9653 | Q29: =Q28+O29-P29 -> 77835
A30: 27 | B30: =ROUND(B29*(1+Assumptions!B44),0) -> 28233 | C30: =ROUND(IF(A30<Assumptions!B100,0,IF(A30<=8,Assumptions!B103,IF(A30<=12,Assumptions!B104,IF(A30<=18,Assumptions!B105,IF(A30<=24,Assumptions!B106,Assumptions!B107))))*(1+IF(A30>=Assumptions!B101,Assumptions!B109,0))*Assumptions!B111),0) -> 540 | D30: =ROUND(ROUND(Assumptions!B119*(1+Assumptions!B120)^6*(1+Assumptions!B121)^6*(1+Assumptions!B122)^(A30-12),0)*Assumptions!B123,0) -> 22 | E30: =B30+C30+D30 -> 28795 | F30: =ROUND(E30*Assumptions!B24,0) -> 144 | G30: =ROUND(H29*Assumptions!B52,0) -> 51 | H30: =H29+F30-G30 -> 950 | I30: =ROUND(H30*(Assumptions!B15*0.85+Assumptions!B11*0.15),0) -> 10901 | J30: =ROUND(E30*Assumptions!B95*Assumptions!B96*Assumptions!B97*Assumptions!B94,0) -> 1123 | K30: =ROUND(E30*Assumptions!B57*Assumptions!B58,0) -> 10078 | L30: =ROUND(IF(A30<Assumptions!B113,0,IF(A30<=18,Assumptions!B105,Assumptions!B107)/1000*Assumptions!B115*0.55+IF(A30>=Assumptions!B114,IF(A30<=18,Assumptions!B105,Assumptions!B107)*Assumptions!B109/1000*Assumptions!B116*0.55,0)),0) -> 94 | M30: =I30+J30+K30+L30 -> 22196 | N30: =ROUND(H30*Assumptions!B62*Assumptions!B61,0)+Assumptions!B63+IF(H30>Assumptions!B64,45,0)+Assumptions!B65+Assumptions!B66+Assumptions!B67+Assumptions!B68+Assumptions!B69/12+IF(A30>=3,Assumptions!B72,0)+ROUND(I30*Assumptions!B70+H30*Assumptions!B71,0)+0 -> 1094 | O30: =M30-N30 -> 21102 | P30: =IF((Q29+O30)<N30*Assumptions!B89,0,IF((Q29+O30)<N30*6,ROUND(MAX(O30,0)*Assumptions!B90,0),ROUND(MAX(O30,0)*Assumptions!B91,0))) -> 10551 | Q30: =Q29+O30-P30 -> 88386
A31: 28 | B31: =ROUND(B30*(1+Assumptions!B44),0) -> 30492 | C31: =ROUND(IF(A31<Assumptions!B100,0,IF(A31<=8,Assumptions!B103,IF(A31<=12,Assumptions!B104,IF(A31<=18,Assumptions!B105,IF(A31<=24,Assumptions!B106,Assumptions!B107))))*(1+IF(A31>=Assumptions!B101,Assumptions!B109,0))*Assumptions!B111),0) -> 540 | D31: =ROUND(ROUND(Assumptions!B119*(1+Assumptions!B120)^6*(1+Assumptions!B121)^6*(1+Assumptions!B122)^(A31-12),0)*Assumptions!B123,0) -> 24 | E31: =B31+C31+D31 -> 31056 | F31: =ROUND(E31*Assumptions!B24,0) -> 155 | G31: =ROUND(H30*Assumptions!B52,0) -> 57 | H31: =H30+F31-G31 -> 1048 | I31: =ROUND(H31*(Assumptions!B15*0.85+Assumptions!B11*0.15),0) -> 12026 | J31: =ROUND(E31*Assumptions!B95*Assumptions!B96*Assumptions!B97*Assumptions!B94,0) -> 1211 | K31: =ROUND(E31*Assumptions!B57*Assumptions!B58,0) -> 10870 | L31: =ROUND(IF(A31<Assumptions!B113,0,IF(A31<=18,Assumptions!B105,Assumptions!B107)/1000*Assumptions!B115*0.55+IF(A31>=Assumptions!B114,IF(A31<=18,Assumptions!B105,Assumptions!B107)*Assumptions!B109/1000*Assumptions!B116*0.55,0)),0) -> 94 | M31: =I31+J31+K31+L31 -> 24201 | N31: =ROUND(H31*Assumptions!B62*Assumptions!B61,0)+Assumptions!B63+IF(H31>Assumptions!B64,45,0)+Assumptions!B65+Assumptions!B66+Assumptions!B67+Assumptions!B68+Assumptions!B69/12+IF(A31>=3,Assumptions!B72,0)+ROUND(I31*Assumptions!B70+H31*Assumptions!B71,0)+0 -> 1183 | O31: =M31-N31 -> 23018 | P31: =IF((Q30+O31)<N31*Assumptions!B89,0,IF((Q30+O31)<N31*6,ROUND(MAX(O31,0)*Assumptions!B90,0),ROUND(MAX(O31,0)*Assumptions!B91,0))) -> 11509 | Q31: =Q30+O31-P31 -> 99895
A32: 29 | B32: =ROUND(B31*(1+Assumptions!B44),0) -> 32931 | C32: =ROUND(IF(A32<Assumptions!B100,0,IF(A32<=8,Assumptions!B103,IF(A32<=12,Assumptions!B104,IF(A32<=18,Assumptions!B105,IF(A32<=24,Assumptions!B106,Assumptions!B107))))*(1+IF(A32>=Assumptions!B101,Assumptions!B109,0))*Assumptions!B111),0) -> 540 | D32: =ROUND(ROUND(Assumptions!B119*(1+Assumptions!B120)^6*(1+Assumptions!B121)^6*(1+Assumptions!B122)^(A32-12),0)*Assumptions!B123,0) -> 26 | E32: =B32+C32+D32 -> 33497 | F32: =ROUND(E32*Assumptions!B24,0) -> 167 | G32: =ROUND(H31*Assumptions!B52,0) -> 63 | H32: =H31+F32-G32 -> 1152 | I32: =ROUND(H32*(Assumptions!B15*0.85+Assumptions!B11*0.15),0) -> 13219 | J32: =ROUND(E32*Assumptions!B95*Assumptions!B96*Assumptions!B97*Assumptions!B94,0) -> 1306 | K32: =ROUND(E32*Assumptions!B57*Assumptions!B58,0) -> 11724 | L32: =ROUND(IF(A32<Assumptions!B113,0,IF(A32<=18,Assumptions!B105,Assumptions!B107)/1000*Assumptions!B115*0.55+IF(A32>=Assumptions!B114,IF(A32<=18,Assumptions!B105,Assumptions!B107)*Assumptions!B109/1000*Assumptions!B116*0.55,0)),0) -> 94 | M32: =I32+J32+K32+L32 -> 26343 | N32: =ROUND(H32*Assumptions!B62*Assumptions!B61,0)+Assumptions!B63+IF(H32>Assumptions!B64,45,0)+Assumptions!B65+Assumptions!B66+Assumptions!B67+Assumptions!B68+Assumptions!B69/12+IF(A32>=3,Assumptions!B72,0)+ROUND(I32*Assumptions!B70+H32*Assumptions!B71,0)+0 -> 1279 | O32: =M32-N32 -> 25064 | P32: =IF((Q31+O32)<N32*Assumptions!B89,0,IF((Q31+O32)<N32*6,ROUND(MAX(O32,0)*Assumptions!B90,0),ROUND(MAX(O32,0)*Assumptions!B91,0))) -> 12532 | Q32: =Q31+O32-P32 -> 112427
A33: 30 | B33: =ROUND(B32*(1+Assumptions!B44),0) -> 35565 | C33: =ROUND(IF(A33<Assumptions!B100,0,IF(A33<=8,Assumptions!B103,IF(A33<=12,Assumptions!B104,IF(A33<=18,Assumptions!B105,IF(A33<=24,Assumptions!B106,Assumptions!B107))))*(1+IF(A33>=Assumptions!B101,Assumptions!B109,0))*Assumptions!B111),0) -> 540 | D33: =ROUND(ROUND(Assumptions!B119*(1+Assumptions!B120)^6*(1+Assumptions!B121)^6*(1+Assumptions!B122)^(A33-12),0)*Assumptions!B123,0) -> 29 | E33: =B33+C33+D33 -> 36134 | F33: =ROUND(E33*Assumptions!B24,0) -> 181 | G33: =ROUND(H32*Assumptions!B52,0) -> 69 | H33: =H32+F33-G33 -> 1264 | I33: =ROUND(H33*(Assumptions!B15*0.85+Assumptions!B11*0.15),0) -> 14504 | J33: =ROUND(E33*Assumptions!B95*Assumptions!B96*Assumptions!B97*Assumptions!B94,0) -> 1409 | K33: =ROUND(E33*Assumptions!B57*Assumptions!B58,0) -> 12647 | L33: =ROUND(IF(A33<Assumptions!B113,0,IF(A33<=18,Assumptions!B105,Assumptions!B107)/1000*Assumptions!B115*0.55+IF(A33>=Assumptions!B114,IF(A33<=18,Assumptions!B105,Assumptions!B107)*Assumptions!B109/1000*Assumptions!B116*0.55,0)),0) -> 94 | M33: =I33+J33+K33+L33 -> 28654 | N33: =ROUND(H33*Assumptions!B62*Assumptions!B61,0)+Assumptions!B63+IF(H33>Assumptions!B64,45,0)+Assumptions!B65+Assumptions!B66+Assumptions!B67+Assumptions!B68+Assumptions!B69/12+IF(A33>=3,Assumptions!B72,0)+ROUND(I33*Assumptions!B70+H33*Assumptions!B71,0)+0 -> 1381 | O33: =M33-N33 -> 27273 | P33: =IF((Q32+O33)<N33*Assumptions!B89,0,IF((Q32+O33)<N33*6,ROUND(MAX(O33,0)*Assumptions!B90,0),ROUND(MAX(O33,0)*Assumptions!B91,0))) -> 13637 | Q33: =Q32+O33-P33 -> 126063
A34: 31 | B34: =ROUND(B33*(1+Assumptions!B44),0) -> 38410 | C34: =ROUND(IF(A34<Assumptions!B100,0,IF(A34<=8,Assumptions!B103,IF(A34<=12,Assumptions!B104,IF(A34<=18,Assumptions!B105,IF(A34<=24,Assumptions!B106,Assumptions!B107))))*(1+IF(A34>=Assumptions!B101,Assumptions!B109,0))*Assumptions!B111),0) -> 540 | D34: =ROUND(ROUND(Assumptions!B119*(1+Assumptions!B120)^6*(1+Assumptions!B121)^6*(1+Assumptions!B122)^(A34-12),0)*Assumptions!B123,0) -> 32 | E34: =B34+C34+D34 -> 38982 | F34: =ROUND(E34*Assumptions!B24,0) -> 195 | G34: =ROUND(H33*Assumptions!B52,0) -> 76 | H34: =H33+F34-G34 -> 1383 | I34: =ROUND(H34*(Assumptions!B15*0.85+Assumptions!B11*0.15),0) -> 15870 | J34: =ROUND(E34*Assumptions!B95*Assumptions!B96*Assumptions!B97*Assumptions!B94,0) -> 1520 | K34: =ROUND(E34*Assumptions!B57*Assumptions!B58,0) -> 13644 | L34: =ROUND(IF(A34<Assumptions!B113,0,IF(A34<=18,Assumptions!B105,Assumptions!B107)/1000*Assumptions!B115*0.55+IF(A34>=Assumptions!B114,IF(A34<=18,Assumptions!B105,Assumptions!B107)*Assumptions!B109/1000*Assumptions!B116*0.55,0)),0) -> 94 | M34: =I34+J34+K34+L34 -> 31128 | N34: =ROUND(H34*Assumptions!B62*Assumptions!B61,0)+Assumptions!B63+IF(H34>Assumptions!B64,45,0)+Assumptions!B65+Assumptions!B66+Assumptions!B67+Assumptions!B68+Assumptions!B69/12+IF(A34>=3,Assumptions!B72,0)+ROUND(I34*Assumptions!B70+H34*Assumptions!B71,0)+0 -> 1489 | O34: =M34-N34 -> 29639 | P34: =IF((Q33+O34)<N34*Assumptions!B89,0,IF((Q33+O34)<N34*6,ROUND(MAX(O34,0)*Assumptions!B90,0),ROUND(MAX(O34,0)*Assumptions!B91,0))) -> 14820 | Q34: =Q33+O34-P34 -> 140882
A35: 32 | B35: =ROUND(B34*(1+Assumptions!B44),0) -> 41483 | C35: =ROUND(IF(A35<Assumptions!B100,0,IF(A35<=8,Assumptions!B103,IF(A35<=12,Assumptions!B104,IF(A35<=18,Assumptions!B105,IF(A35<=24,Assumptions!B106,Assumptions!B107))))*(1+IF(A35>=Assumptions!B101,Assumptions!B109,0))*Assumptions!B111),0) -> 540 | D35: =ROUND(ROUND(Assumptions!B119*(1+Assumptions!B120)^6*(1+Assumptions!B121)^6*(1+Assumptions!B122)^(A35-12),0)*Assumptions!B123,0) -> 35 | E35: =B35+C35+D35 -> 42058 | F35: =ROUND(E35*Assumptions!B24,0) -> 210 | G35: =ROUND(H34*Assumptions!B52,0) -> 83 | H35: =H34+F35-G35 -> 1510 | I35: =ROUND(H35*(Assumptions!B15*0.85+Assumptions!B11*0.15),0) -> 17327 | J35: =ROUND(E35*Assumptions!B95*Assumptions!B96*Assumptions!B97*Assumptions!B94,0) -> 1640 | K35: =ROUND(E35*Assumptions!B57*Assumptions!B58,0) -> 14720 | L35: =ROUND(IF(A35<Assumptions!B113,0,IF(A35<=18,Assumptions!B105,Assumptions!B107)/1000*Assumptions!B115*0.55+IF(A35>=Assumptions!B114,IF(A35<=18,Assumptions!B105,Assumptions!B107)*Assumptions!B109/1000*Assumptions!B116*0.55,0)),0) -> 94 | M35: =I35+J35+K35+L35 -> 33781 | N35: =ROUND(H35*Assumptions!B62*Assumptions!B61,0)+Assumptions!B63+IF(H35>Assumptions!B64,45,0)+Assumptions!B65+Assumptions!B66+Assumptions!B67+Assumptions!B68+Assumptions!B69/12+IF(A35>=3,Assumptions!B72,0)+ROUND(I35*Assumptions!B70+H35*Assumptions!B71,0)+0 -> 1605 | O35: =M35-N35 -> 32176 | P35: =IF((Q34+O35)<N35*Assumptions!B89,0,IF((Q34+O35)<N35*6,ROUND(MAX(O35,0)*Assumptions!B90,0),ROUND(MAX(O35,0)*Assumptions!B91,0))) -> 16088 | Q35: =Q34+O35-P35 -> 156970
A36: 33 | B36: =ROUND(B35*(1+Assumptions!B44),0) -> 44802 | C36: =ROUND(IF(A36<Assumptions!B100,0,IF(A36<=8,Assumptions!B103,IF(A36<=12,Assumptions!B104,IF(A36<=18,Assumptions!B105,IF(A36<=24,Assumptions!B106,Assumptions!B107))))*(1+IF(A36>=Assumptions!B101,Assumptions!B109,0))*Assumptions!B111),0) -> 540 | D36: =ROUND(ROUND(Assumptions!B119*(1+Assumptions!B120)^6*(1+Assumptions!B121)^6*(1+Assumptions!B122)^(A36-12),0)*Assumptions!B123,0) -> 38 | E36: =B36+C36+D36 -> 45380 | F36: =ROUND(E36*Assumptions!B24,0) -> 227 | G36: =ROUND(H35*Assumptions!B52,0) -> 91 | H36: =H35+F36-G36 -> 1646 | I36: =ROUND(H36*(Assumptions!B15*0.85+Assumptions!B11*0.15),0) -> 18888 | J36: =ROUND(E36*Assumptions!B95*Assumptions!B96*Assumptions!B97*Assumptions!B94,0) -> 1770 | K36: =ROUND(E36*Assumptions!B57*Assumptions!B58,0) -> 15883 | L36: =ROUND(IF(A36<Assumptions!B113,0,IF(A36<=18,Assumptions!B105,Assumptions!B107)/1000*Assumptions!B115*0.55+IF(A36>=Assumptions!B114,IF(A36<=18,Assumptions!B105,Assumptions!B107)*Assumptions!B109/1000*Assumptions!B116*0.55,0)),0) -> 94 | M36: =I36+J36+K36+L36 -> 36635 | N36: =ROUND(H36*Assumptions!B62*Assumptions!B61,0)+Assumptions!B63+IF(H36>Assumptions!B64,45,0)+Assumptions!B65+Assumptions!B66+Assumptions!B67+Assumptions!B68+Assumptions!B69/12+IF(A36>=3,Assumptions!B72,0)+ROUND(I36*Assumptions!B70+H36*Assumptions!B71,0)+0 -> 1730 | O36: =M36-N36 -> 34905 | P36: =IF((Q35+O36)<N36*Assumptions!B89,0,IF((Q35+O36)<N36*6,ROUND(MAX(O36,0)*Assumptions!B90,0),ROUND(MAX(O36,0)*Assumptions!B91,0))) -> 17453 | Q36: =Q35+O36-P36 -> 174422
A37: 34 | B37: =ROUND(B36*(1+Assumptions!B44),0) -> 48386 | C37: =ROUND(IF(A37<Assumptions!B100,0,IF(A37<=8,Assumptions!B103,IF(A37<=12,Assumptions!B104,IF(A37<=18,Assumptions!B105,IF(A37<=24,Assumptions!B106,Assumptions!B107))))*(1+IF(A37>=Assumptions!B101,Assumptions!B109,0))*Assumptions!B111),0) -> 540 | D37: =ROUND(ROUND(Assumptions!B119*(1+Assumptions!B120)^6*(1+Assumptions!B121)^6*(1+Assumptions!B122)^(A37-12),0)*Assumptions!B123,0) -> 42 | E37: =B37+C37+D37 -> 48968 | F37: =ROUND(E37*Assumptions!B24,0) -> 245 | G37: =ROUND(H36*Assumptions!B52,0) -> 99 | H37: =H36+F37-G37 -> 1792 | I37: =ROUND(H37*(Assumptions!B15*0.85+Assumptions!B11*0.15),0) -> 20563 | J37: =ROUND(E37*Assumptions!B95*Assumptions!B96*Assumptions!B97*Assumptions!B94,0) -> 1910 | K37: =ROUND(E37*Assumptions!B57*Assumptions!B58,0) -> 17139 | L37: =ROUND(IF(A37<Assumptions!B113,0,IF(A37<=18,Assumptions!B105,Assumptions!B107)/1000*Assumptions!B115*0.55+IF(A37>=Assumptions!B114,IF(A37<=18,Assumptions!B105,Assumptions!B107)*Assumptions!B109/1000*Assumptions!B116*0.55,0)),0) -> 94 | M37: =I37+J37+K37+L37 -> 39706 | N37: =ROUND(H37*Assumptions!B62*Assumptions!B61,0)+Assumptions!B63+IF(H37>Assumptions!B64,45,0)+Assumptions!B65+Assumptions!B66+Assumptions!B67+Assumptions!B68+Assumptions!B69/12+IF(A37>=3,Assumptions!B72,0)+ROUND(I37*Assumptions!B70+H37*Assumptions!B71,0)+0 -> 1863 | O37: =M37-N37 -> 37843 | P37: =IF((Q36+O37)<N37*Assumptions!B89,0,IF((Q36+O37)<N37*6,ROUND(MAX(O37,0)*Assumptions!B90,0),ROUND(MAX(O37,0)*Assumptions!B91,0))) -> 18922 | Q37: =Q36+O37-P37 -> 193343
A38: 35 | B38: =ROUND(B37*(1+Assumptions!B44),0) -> 52257 | C38: =ROUND(IF(A38<Assumptions!B100,0,IF(A38<=8,Assumptions!B103,IF(A38<=12,Assumptions!B104,IF(A38<=18,Assumptions!B105,IF(A38<=24,Assumptions!B106,Assumptions!B107))))*(1+IF(A38>=Assumptions!B101,Assumptions!B109,0))*Assumptions!B111),0) -> 540 | D38: =ROUND(ROUND(Assumptions!B119*(1+Assumptions!B120)^6*(1+Assumptions!B121)^6*(1+Assumptions!B122)^(A38-12),0)*Assumptions!B123,0) -> 46 | E38: =B38+C38+D38 -> 52843 | F38: =ROUND(E38*Assumptions!B24,0) -> 264 | G38: =ROUND(H37*Assumptions!B52,0) -> 108 | H38: =H37+F38-G38 -> 1948 | I38: =ROUND(H38*(Assumptions!B15*0.85+Assumptions!B11*0.15),0) -> 22353 | J38: =ROUND(E38*Assumptions!B95*Assumptions!B96*Assumptions!B97*Assumptions!B94,0) -> 2061 | K38: =ROUND(E38*Assumptions!B57*Assumptions!B58,0) -> 18495 | L38: =ROUND(IF(A38<Assumptions!B113,0,IF(A38<=18,Assumptions!B105,Assumptions!B107)/1000*Assumptions!B115*0.55+IF(A38>=Assumptions!B114,IF(A38<=18,Assumptions!B105,Assumptions!B107)*Assumptions!B109/1000*Assumptions!B116*0.55,0)),0) -> 94 | M38: =I38+J38+K38+L38 -> 43003 | N38: =ROUND(H38*Assumptions!B62*Assumptions!B61,0)+Assumptions!B63+IF(H38>Assumptions!B64,45,0)+Assumptions!B65+Assumptions!B66+Assumptions!B67+Assumptions!B68+Assumptions!B69/12+IF(A38>=3,Assumptions!B72,0)+ROUND(I38*Assumptions!B70+H38*Assumptions!B71,0)+0 -> 2005 | O38: =M38-N38 -> 40998 | P38: =IF((Q37+O38)<N38*Assumptions!B89,0,IF((Q37+O38)<N38*6,ROUND(MAX(O38,0)*Assumptions!B90,0),ROUND(MAX(O38,0)*Assumptions!B91,0))) -> 20499 | Q38: =Q37+O38-P38 -> 213842
A39: 36 | B39: =ROUND(B38*(1+Assumptions!B44),0) -> 56438 | C39: =ROUND(IF(A39<Assumptions!B100,0,IF(A39<=8,Assumptions!B103,IF(A39<=12,Assumptions!B104,IF(A39<=18,Assumptions!B105,IF(A39<=24,Assumptions!B106,Assumptions!B107))))*(1+IF(A39>=Assumptions!B101,Assumptions!B109,0))*Assumptions!B111),0) -> 540 | D39: =ROUND(ROUND(Assumptions!B119*(1+Assumptions!B120)^6*(1+Assumptions!B121)^6*(1+Assumptions!B122)^(A39-12),0)*Assumptions!B123,0) -> 51 | E39: =B39+C39+D39 -> 57029 | F39: =ROUND(E39*Assumptions!B24,0) -> 285 | G39: =ROUND(H38*Assumptions!B52,0) -> 117 | H39: =H38+F39-G39 -> 2116 | I39: =ROUND(H39*(Assumptions!B15*0.85+Assumptions!B11*0.15),0) -> 24281 | J39: =ROUND(E39*Assumptions!B95*Assumptions!B96*Assumptions!B97*Assumptions!B94,0) -> 2224 | K39: =ROUND(E39*Assumptions!B57*Assumptions!B58,0) -> 19960 | L39: =ROUND(IF(A39<Assumptions!B113,0,IF(A39<=18,Assumptions!B105,Assumptions!B107)/1000*Assumptions!B115*0.55+IF(A39>=Assumptions!B114,IF(A39<=18,Assumptions!B105,Assumptions!B107)*Assumptions!B109/1000*Assumptions!B116*0.55,0)),0) -> 94 | M39: =I39+J39+K39+L39 -> 46559 | N39: =ROUND(H39*Assumptions!B62*Assumptions!B61,0)+Assumptions!B63+IF(H39>Assumptions!B64,45,0)+Assumptions!B65+Assumptions!B66+Assumptions!B67+Assumptions!B68+Assumptions!B69/12+IF(A39>=3,Assumptions!B72,0)+ROUND(I39*Assumptions!B70+H39*Assumptions!B71,0)+0 -> 2158 | O39: =M39-N39 -> 44401 | P39: =IF((Q38+O39)<N39*Assumptions!B89,0,IF((Q38+O39)<N39*6,ROUND(MAX(O39,0)*Assumptions!B90,0),ROUND(MAX(O39,0)*Assumptions!B91,0))) -> 22201 | Q39: =Q38+O39-P39 -> 236042
A40: TOTALS | I40: =SUM(I4:I39) -> 246709 | J40: =SUM(J4:J39) -> 25610 | K40: =SUM(K4:K39) -> 227747 | L40: =SUM(L4:L39) -> 1858 | M40: =SUM(M4:M39) -> 501924 | N40: =SUM(N4:N39) -> 30011 | O40: =SUM(O4:O39) -> 471913 | P40: =SUM(P4:P39) -> 235871
A41: M36 | B41: =B39 -> 56438 | C41: =C39 -> 540 | D41: =D39 -> 51 | E41: =E39 -> 57029 | H41: =H39 -> 2116 | I41: =I39 -> 24281 | M41: =M39 -> 46559 | P41: =P39 -> 22201 | Q41: =Q39 -> 236042

Sheet VALIDATION
A1: VALIDATION — ALL MUST PASS BEFORE RELEASE
A2: Run after every update. Any FAIL blocks release.
A3: Check | B3: Expected | C3: Actual | D3: Status | E3: Notes
A4: Conservative conv = 0.15% | B4: 0.15% | C4: =Assumptions!B22 -> 0.0015 | D4: =IF(Assumptions!B22=0.0015,"PASS","FAIL") -> PASS | E4: Core check
A5: Expected conv = 0.25% | B5: 0.25% | C5: =Assumptions!B23 -> 0.0025 | D5: =IF(Assumptions!B23=0.0025,"PASS","FAIL") -> PASS | E5: Core check
A6: Optimistic conv = 0.50% | B6: 0.50% | C6: =Assumptions!B24 -> 0.005 | D6: =IF(Assumptions!B24=0.005,"PASS","FAIL") -> PASS | E6: Core check
A7: Conservative churn = 8% | B7: 8% | C7: =Assumptions!B50 -> 0.08 | D7: =IF(Assumptions!B50=0.08,"PASS","FAIL") -> PASS | E7: Updated from v16
A8: Expected churn = 7% | B8: 7% | C8: =Assumptions!B51 -> 0.07 | D8: =IF(Assumptions!B51=0.07,"PASS","FAIL") -> PASS | E8: NEW in v17
A9: Optimistic churn = 6% | B9: 6% | C9: =Assumptions!B52 -> 0.06 | D9: =IF(Assumptions!B52=0.06,"PASS","FAIL") -> PASS | E9: NEW in v17
A10: Y1 growth: Cons=10% | B10: 10% | C10: =Assumptions!B34 -> 0.1 | D10: =IF(Assumptions!B34=0.1,"PASS","FAIL") -> PASS | E10: Decay curve Y1
A11: Y2 growth decays: Cons Y2 < Y1 | B11: Y2<Y1 | C11: =Assumptions!B38 -> 0.06 | D11: =IF(Assumptions!B38<Assumptions!B34,"PASS","FAIL") -> PASS | E11: Decay curve check
A12: Y3 growth decays: Cons Y3 < Y2 | B12: Y3<Y2 | C12: =Assumptions!B42 -> 0.04 | D12: =IF(Assumptions!B42<Assumptions!B38,"PASS","FAIL") -> PASS | E12: Decay curve check
A13: Referral starts M6 | B13: 6 | C13: =Assumptions!B56 -> 6 | D13: =IF(Assumptions!B56=6,"PASS","FAIL") -> PASS | E13: PMP gate
A14: Conservative M36 reserve > 0 | B14: >$0 | C14: =Conservative!Q39 -> 11033 | D14: =IF(Conservative!Q39>0,"PASS","FAIL") -> PASS | E14: Sustainability
A15: Expected M36 reserve > 0 | B15: >$0 | C15: =Expected!Q39 -> 56802 | D15: =IF(Expected!Q39>0,"PASS","FAIL") -> PASS | E15: Sustainability
A16: Expected M36 subs > 0 | B16: >0 | C16: =Expected!H39 -> 304 | D16: =IF(Expected!H39>0,"PASS","FAIL") -> PASS | E16: Growth sanity
A17: Opt MRR > Cons MRR at M36 | B17: Opt>Cons | C17: =Optimistic!I39 -> 24281 | D17: =IF(Optimistic!I39>Conservative!I39,"PASS","FAIL") -> PASS | E17: Scenario ordering
A18: YT visitors > 0 at M12 Expected | B18: >0 | C18: =Expected!C15 -> 60 | D18: =IF(Expected!C15>0,"PASS","FAIL") -> PASS | E18: YT funnel check
A19: IG visitors > 0 at M6 Expected | B19: >0 | C19: =Expected!D9 -> 2 | D19: =IF(Expected!D9>0,"PASS","FAIL") -> PASS | E19: IG traffic check
A20: Total visitors > organic (YT+IG additive) | B20: E>B | C20: =Expected!E39 -> 15433 | D20: =IF(Expected!E39>Expected!B39,"PASS","FAIL") -> PASS | E20: Multi-channel
A21: Per-case revenue > 0 at M12 Expected | B21: >$0 | C21: =Expected!J15 -> 105 | D21: =IF(Expected!J15>0,"PASS","FAIL") -> PASS | E21: Per-case check
A22: IG CTR = 1.5% | B22: 1.5% | C22: =Assumptions!B123 -> 0.015 | D22: =IF(Assumptions!B123=0.015,"PASS","FAIL") -> PASS | E22: Updated from 0.3%
A23: YT viewer CTR = 2% | B23: 2% | C23: =Assumptions!B111 -> 0.02 | D23: =IF(Assumptions!B111=0.02,"PASS","FAIL") -> PASS | E23: YT-to-site funnel
A24: TOTAL | D24: =COUNTIF(D4:D23,"PASS")&" of 20 PASS" -> 20 of 20 PASS
