Workbook

Sheet Dashboard
A1: MyAdvocate Projections v16 — Executive Dashboard
A2: Source: PMP v22 | v16.0 — March 2026 | NEW: YouTube (MA-YT-001) + Instagram (MA-IG-001) revenue streams integrated
A4: KEY METRICS — MONTH 36 | B4: Conservative | C4: Expected | D4: Optimistic
A5: Total Monthly Visitors (incl. YT+IG) | B5: =Conservative!AB41 -> 9590.6988 | C5: =Expected!AB41 -> 52870.702 | D5: =Optimistic!AB41 -> 198893.8
A6: → Organic SEO Visitors | B6: =Conservative!B41 -> 9181.6988 | C6: =Expected!B41 -> 52461.702 | D6: =Optimistic!B41 -> 198484.8
A7: → YT Referral Visitors | B7: =Conservative!Z41 -> 400 | C7: =Expected!Z41 -> 400 | D7: =Optimistic!Z41 -> 400
A8: → IG Direct Visitors | B8: =Conservative!AA41 -> 9 | C8: =Expected!AA41 -> 9 | D8: =Optimistic!AA41 -> 9
A9: Paid Subscribers | B9: =Conservative!E41 -> 99 | C9: =Expected!E41 -> 825 | D9: =Optimistic!E41 -> 6021
A10: MRR ($) | B10: =Conservative!H41 -> 1136 | C10: =Expected!H41 -> 9467 | D10: =Optimistic!H41 -> 69091
A11: Monthly Referral Revenue ($) | B11: =Conservative!R41 -> 3357 | C11: =Expected!R41 -> 18505 | D11: =Optimistic!R41 -> 69613
A12: Per-Case Revenue ($) | B12: =Conservative!W41 -> 374 | C12: =Expected!W41 -> 2062 | D12: =Optimistic!W41 -> 7757
A13: YT AdSense Revenue ($) ▼NEW | B13: =Conservative!AC41 -> 76 | C13: =Expected!AC41 -> 76 | D13: =Optimistic!AC41 -> 76
A14: IG Direct Revenue ($) ▼NEW | B14: =Conservative!AD41 -> 20 | C14: =Expected!AD41 -> 20 | D14: =Optimistic!AD41 -> 20
A15: Total Revenue ($) | B15: =Conservative!S41 -> 4963 | C15: =Expected!S41 -> 30130 | D15: =Optimistic!S41 -> 146557
A16: Owner's Draw ($) | B16: =Conservative!T41 -> 1321 | C16: =Expected!T41 -> 8224 | D16: =Optimistic!T41 -> 39868
A17: Reserve Balance ($) | B17: =Conservative!U41 -> 50924 | C17: =Expected!U41 -> 254020 | D17: =Optimistic!U41 -> 1042634
A18: Traffic Signal | B18: =Conservative!V41 -> Pre-Signal 1 | C18: =Expected!V41 -> Signal 3 | D18: =Optimistic!V41 -> Signal 6
A20: 3-YEAR TOTALS (M1-M36)
A21: 3-Yr Subscription Revenue | B21: =Conservative!I43 -> 13742 | C21: =Expected!I43 -> 84687 | D21: =Optimistic!I43 -> 517537
A22: 3-Yr Referral Revenue | B22: =Conservative!R43 -> 42154 | C22: =Expected!R43 -> 169031 | D22: =Optimistic!R43 -> 528369
A23: 3-Yr Per-Case Revenue | B23: =Conservative!W43 -> 4823 | C23: =Expected!W43 -> 19052 | D23: =Optimistic!W43 -> 59224
A24: 3-Yr YT AdSense Revenue ▼NEW | B24: =Conservative!AC43 -> 1363 | C24: =Expected!AC43 -> 1363 | D24: =Optimistic!AC43 -> 1363
A25: 3-Yr IG Direct Revenue ▼NEW | B25: =Conservative!AD43 -> 155 | C25: =Expected!AD43 -> 155 | D25: =Optimistic!AD43 -> 155
A26: 3-Yr Total Revenue | B26: =Conservative!S43 -> 62237 | C26: =Expected!S43 -> 274288 | D26: =Optimistic!S43 -> 1106648
A28: CONVERSION & GROWTH ASSUMPTIONS
B29: Conservative | C29: Expected | D29: Optimistic
A30: Paid Conversion Rate | B30: =Assumptions!B22 -> 0.0015 | C30: =Assumptions!B23 -> 0.0025 | D30: =Assumptions!B24 -> 0.005
A31: Monthly Traffic Growth | B31: =Assumptions!B33 -> 0.08 | C31: =Assumptions!B34 -> 0.12 | D31: =Assumptions!B35 -> 0.15
A32: Monthly Churn | B32: =Assumptions!B43 -> 0.08 | C32: =Assumptions!B44 -> 0.06 | D32: =Assumptions!B45 -> 0.04
A33: Per-Case Price | B33: =Assumptions!B136 -> 13 | C33: =Assumptions!B136 -> 13 | D33: =Assumptions!B136 -> 13
A34: Tool Engagement Rate | B34: =Assumptions!B137 -> 0.08 | C34: =Assumptions!B137 -> 0.08 | D34: =Assumptions!B137 -> 0.08
A35: EN AdSense CPM | B35: =Assumptions!B146 -> 8 | C35: =Assumptions!B146 -> 8 | D35: =Assumptions!B146 -> 8
A36: IG Bio Link CTR | B36: =Assumptions!B166 -> 0.003 | C36: =Assumptions!B166 -> 0.003 | D36: =Assumptions!B166 -> 0.003

Sheet Assumptions
A1: MyAdvocate Financial Model v16 — Assumptions
A2: Source: PMP v22 | Blue = input (user-editable) | Black = calculated | Green = cross-sheet link
A3: Version: v16.0 — March 2026 | Scenarios: Conservative / Expected / Optimistic | NEW v16: YouTube (MA-YT-001) + Instagram (MA-IG-001)
A5: CORE BUSINESS ASSUMPTIONS
A6: Launch Month | B6: 1 | C6: Month 1 = Launch
A7: Planning Horizon (months) | B7: 36 | C7: 3-year projection
A9: PRICING STRUCTURE
A10: Founding Advocate Annual Price | B10: 34 | C10: $34/year — first 250 subs, locked forever
A11: Founding Advocate Monthly Equivalent | B11: =B10/12 -> 2.8333333 | C11: $34/12 — for MRR calculation purposes
A12: Founding Advocate Renewal Price (Year 2+) | B12: 55 | C12: $55/yr — permanent FA rate after Year 1 lock
A13: FA Cohort Cap | B13: 250 | C13: Maximum Founding Advocates — hard cap
A14: Basic Tier Monthly | B14: 8 | C14: Launch tier — all new subs Months 1–8
A15: Standard Tier Monthly (Month 9+) | B15: 13 | C15: Price increase Month 9 — new subs only
A16: Advocate Builder Quarterly | B16: 21 | C16: $21/quarter — alternative entry point
A17: Advocate Builder Monthly Equivalent | B17: =B16/3 -> 7 | C17: $21/3 — for MRR purposes
A18: Annual Standard Price | B18: 55 | C18: $55/yr for committed annual subscribers
A19: Premium Monthly (Phase 4+) | B19: 21 | C19: Native app tier — Phase 4 unlock
A21: CONVERSION RATES — HEALTHCARE COLD TRAFFIC
A22: Conservative Paid Conversion Rate | B22: 0.0015 | C22: 0.15% — cold traffic baseline. Source: PMP v22 §3
A23: Expected Paid Conversion Rate | B23: 0.0025 | C23: 0.25% — moderate, denial-code SEO boost
A24: Optimistic Paid Conversion Rate | B24: 0.005 | C24: 0.50% — high-intent denial code + SEO optimization
A25: Free Signup / Email Capture Rate | B25: 0.02 | C25: 2.0% of total visitors — owned email list growth
A26: Denial Decoder Free-to-Paid Lift | B26: 1.15 | C26: 15% higher conversion from denial code page visitors
A27: Founding Advocate Conversion Rate (of early subs) | B27: 0.4 | C27: ~40% of first subs take the FA offer
A29: SEO TRAFFIC GROWTH MODEL
A30: Month 1 Traffic — Conservative | B30: 500 | C30: Minimal launch, no prior SEO momentum
A31: Month 1 Traffic — Expected | B31: 800 | C31: Early SEO content live at launch
A32: Month 1 Traffic — Optimistic | B32: 1200 | C32: Aggressive pre-launch content build
A33: Monthly Traffic Growth — Conservative | B33: 0.08 | C33: 8% MoM — slow organic compounding
A34: Monthly Traffic Growth — Expected | B34: 0.12 | C34: 12% MoM — consistent 2x/week publishing
A35: Monthly Traffic Growth — Optimistic | B35: 0.15 | C35: 15% MoM — aggressive SEO + denial codes indexing fast
A36: Denial Code Program Traffic Boost (Month 3+) | B36: 1.15 | C36: 15% additional traffic lift from 200+ denial code pages indexing
A37: Content Cluster Maturity Boost (Month 6+) | B37: 1.08 | C37: 8% additional lift as pillar/cluster architecture matures
A38: Publishing Cadence (articles/week) | B38: 2 | C38: 2x/week per PMP v22 §4C — sustained from Month 1
A39: Denial Code Pages (Month 3 launch) | B39: 200 | C39: 200 denial code pages built — one-time SEO asset
A40: Month 12 Cumulative Articles Target | B40: 60 | C40: ~2x/week × 26 weeks = ~52 articles + backlog
A42: CHURN & RETENTION
A43: Monthly Churn — Conservative | B43: 0.08 | C43: 8% monthly churn — challenging retention environment
A44: Monthly Churn — Expected | B44: 0.06 | C44: 6% monthly churn — decent product-market fit
A45: Monthly Churn — Optimistic | B45: 0.04 | C45: 4% monthly churn — strong engagement, content value
A46: Founding Advocate Churn Rate | B46: 0.02 | C46: 2% — locked pricing creates loyalty. Grandfathered rate.
A47: Annual Subscriber Churn Rate | B47: 0.04 | C47: 4% annual — commitment reduces churn significantly
A49: ATTORNEY REFERRAL ECONOMICS — TRAFFIC-BASED FLAT RATE
A50: Referral Program Start Month | B50: 6 | C50: Month 6 — Signal 1 gate. Source: PMP v22 §3
A51: Referral Conversion Rate (of total visitors) | B51: 0.001 | C51: 0.1% of monthly visitors → referred. Living assumption.
A52: Blended Revenue per Referral ($) | B52: 350 | C52: $350 blended — midpoint of $300–$400 range. Update with actuals.
A64: COSTS — API & INFRASTRUCTURE
A65: Cost per Letter Generation (Claude API) | B65: 0.08 | C65: Per letter — claude-haiku default. Source: MA-COST-001
A66: Cost per Denial Decoder Lookup | B66: 0.01 | C66: Static lookup — no LLM call in Phase 2
A67: Cost per Document Parse | B67: 0.05 | C67: Bounded document parsing
A68: Letters per Paid Sub per Month | B68: 3.5 | C68: Average usage — 2 tools × ~1.75 letters each
A69: Denial Decoder Lookups per User per Month (free) | B69: 5 | C69: Free tier usage — no signup required
A70: Base Infrastructure Monthly | B70: 31 | C70: Vercel + Supabase + domain — Phase 1 baseline
A71: Anthropic API Hard Cap Monthly | B71: 200 | C71: Emergency shutoff cap — budget-monitor.ts tripwire
A72: Infrastructure Scale Threshold (subs) | B72: 500 | C72: Upgrade Vercel/Supabase to paid at ~500 subs (+$45/mo)
A74: COSTS — CONTENT & SEO
A75: Content Production Cost per Article | B75: 0 | C75: Founder-written Phase 1 — $0 direct cost
A76: SEO Tool Stack Monthly (Ahrefs Lite) | B76: 29 | C76: Ahrefs Lite $29/mo. GSC free.
A77: Social Scheduling (Buffer) | B77: 6 | C77: $6/mo for cross-platform scheduling
A78: Denial Code Database Build Cost | B78: 0 | C78: Founder-built — data is public
A80: COSTS — PLATFORM OPERATIONS
A81: n8n Pro Monthly | B81: 20 | C81: Board of Agents automation platform
A82: Claude Code Monthly (Founder Dev) | B82: 20 | C82: Anthropic Pro plan — development only, not user-facing
A83: Beehiiv Monthly (to 1k subs) | B83: 0 | C83: Free tier covers first 1,000 email subscribers
A84: Beehiiv Monthly (1k+ subs) | B84: 42 | C84: $42/mo Beehiiv Scale — activates at ~1k email subs (~Month 12)
A85: Stripe Transaction Fee % | B85: 0.029 | C85: 2.9% per transaction
A86: Stripe Fixed Fee per Transaction | B86: 0.3 | C86: $0.30 per transaction
A87: Google Workspace + Domain Annual | B87: 120 | C87: $10/mo equiv — sarsh@getmyadvocate.org + domain
A93: ONE-TIME LAUNCH COSTS
A94: Healthcare Compliance Attorney Review | B94: 2250 | C94: $1,500–$3,000 range — using midpoint. Source: PMP v22 §11
A95: Security Audit (External) | B95: 500 | C95: External audit — Month 1 launch blocker
A96: LLC Formation / DBA Registration | B96: 500 | C96: Already done — included for completeness
A97: Total One-Time Launch Costs | B97: =B94+B95+B96 -> 3250 | C97: Sum of one-time items
A101: TRAFFIC MILESTONE GATES — PMP v22 §3
A102: Signal 1 — Phase 2 Unlock | B102: 10000 | C102: 10,000 monthly visitors. Referral outreach + CMO/COO agents
A103: Signal 2 — Phase 3 Unlock | B103: 25000 | C103: 25,000 monthly visitors AND $5,000 MRR. CSO/CPO agents
A104: Signal 3 — Fractional Hire Consider | B104: 40000 | C104: 40,000 monthly visitors. Referral automation, fractional help
A105: Signal 4 — Phase 4 Scale | B105: 65000 | C105: 65,000 monthly visitors AND $15,000 MRR. Full agent stack
A106: Signal 5 — B2B + Native App | B106: 110000 | C106: 110,000 monthly visitors. B2B outreach, VA hire
A107: Signal 6 — First Full-Time Hire Assessment | B107: 175000 | C107: 175,000 monthly visitors. Full-time transition review
A108: Signal 2 MRR Gate | B108: 5000 | C108: $5,000 MRR required alongside Signal 2 traffic
A109: Signal 4 MRR Gate | B109: 15000 | C109: $15,000 MRR required alongside Signal 4 traffic
A111: FOUNDER COMPENSATION — PHASE-GATED WITHDRAWAL RATES
A112: Phase 1 Withdrawal Rate | B112: 0 | C112: 0% — all profit builds reserve. No exceptions.
A113: Phase 2 Withdrawal Rate (Baseline) | B113: 0.236 | C113: 23.6% of monthly profit — Phase 2 standard
A114: Phase 3 Withdrawal Rate (Baseline) | B114: 0.382 | C114: 38.2% of monthly profit — Phase 3 standard
A115: Phase 4 Withdrawal Rate (Baseline) | B115: 0.618 | C115: 61.8% of monthly profit — Phase 4 standard
A116: Native App Development Fund % | B116: 0.2 | C116: 20% of monthly profit → app development fund
A117: Phase 2 Reserve Floor (months of opex) | B117: 3 | C117: 3-month reserve required for Phase 2 withdrawal
A118: Phase 3 Reserve Floor (months of opex) | B118: 6 | C118: 6-month reserve required for Phase 3 withdrawal
A119: Phase 4 Reserve Floor (months of opex) | B119: 12 | C119: 12-month reserve for Phase 4 withdrawal
A121: PROFIT RELEASE WINDOWS — DISCRETIONARY DRAW CAPS
A122: Level 4-5 (Phase 2) Quarterly Reserve Bar | B122: 4 | C122: 4 months — standard quarterly PRW bar
A123: Level 4-5 (Phase 2) Monthly Trigger Reserve Bar | B123: 6 | C123: 6 months — higher bar for monthly trigger option
A124: Level 4-5 Discretionary Cap | B124: 0.35 | C124: 35% of monthly profit — max with health check
A125: Level 6-7 (Phase 3) Quarterly Reserve Bar | B125: 6 | C125: 6 months
A126: Level 6-7 (Phase 3) Monthly Trigger Reserve Bar | B126: 8 | C126: 8 months
A127: Level 6-7 Discretionary Cap | B127: 0.55 | C127: 55% of monthly profit
A128: Level 8 (Phase 4) Quarterly Reserve Bar | B128: 8 | C128: 8 months
A129: Level 8 Monthly Trigger Reserve Bar | B129: 10 | C129: 10 months
...

Sheet Conservative
A1: CONSERVATIVE SCENARIO — Conservative Growth
A2: 0.15% paid conversion | 8% MoM traffic growth | 8% monthly churn | Referral: 0.1% of total visitors x $350 blended
A3: Blue = hardcoded inputs | Black = calculated formulas | Green = Assumptions references | ▼ = NEW v16 columns (YT+IG integration)
A5: Month | B5: Organic Visitors | C5: Free Signups (Email 2%) | D5: New Paid Subs | E5: Total Paid Subs | F5: Churn This Month | G5: Net New Subs | H5: MRR ($) | I5: Monthly Revenue ($) | J5: Letter Gens | K5: API Costs ($) | L5: Infra ($) | M5: Content/ SEO ($) | N5: n8n+Tools ($) | O5: Stripe Fees ($) | P5: Total Costs ($) | Q5: Gross Profit ($) | R5: Referral Revenue ($) | S5: Total Revenue ($) | T5: Owner's Draw ($) | U5: Reserve Balance ($) | V5: Traffic Signal | W5: Per-Case Revenue ($) | X5: Free Tier API Cost ($) | Y5: IG Followers ▼ | Z5: YT Referral Visitors ▼ | AA5: IG Direct Visitors ▼ | AB5: TOTAL Visitors ▼ | AC5: YT AdSense Revenue ($) ▼ | AD5: IG Direct Revenue ($) ▼
A6: 1 | B6: =Assumptions!B30 -> 500 | C6: =ROUND(AB6*Assumptions!B25,0) -> 10 | D6: =ROUND(AB6*Assumptions!B22,0) -> 1 | E6: =D6 -> 1 | F6: =0 -> 0 | G6: =D6-F6 -> 1 | H6: =ROUND(E6*Assumptions!B14,0) -> 8 | I6: =H6 -> 8 | J6: =ROUND(E6*Assumptions!B68,0) -> 4 | K6: =ROUND(J6*Assumptions!B65,0) -> 0 | L6: =Assumptions!B70+IF(E6>Assumptions!B72,45,0) -> 31 | M6: =Assumptions!B94+Assumptions!B95+Assumptions!B76+Assumptions!B77 -> 2785 | N6: =Assumptions!B81+Assumptions!B82+Assumptions!B87/12 -> 50 | O6: =ROUND(I6*Assumptions!B85+E6*Assumptions!B86+W6*Assumptions!B85+ROUND(AB6*Assumptions!B137*Assumptions!B138*Assumptions!B139,0)*Assumptions!B86,0) -> 2 | P6: =K6+L6+M6+N6+O6+X6 -> 2871 | Q6: =I6-P6 -> -2863 | R6: =0 -> 0 | S6: =I6+R6+W6+AC6+AD6 -> 28 | T6: =IF(U6<P6*3,0,IF(U6<P6*6,ROUND((Q6+R6+W6+AC6+AD6)*0.75*Assumptions!B113,0),ROUND((Q6+R6+W6+AC6+AD6)*0.75*Assumptions!B114,0))) -> 0 | U6: =Q6+R6+W6+AC6+AD6 -> -2843 | V6: =IF(AB6>=Assumptions!B107,"Signal 6",IF(AB6>=Assumptions!B106,"Signal 5",IF(AB6>=Assumptions!B105,"Signal 4",IF(AB6>=Assumptions!B104,"Signal 3",IF(AB6>=Assumptions!B103,"Signal 2",IF(AB6>=Assumptions!B102,"Signal 1","Pre-Signal 1")))))) -> Pre-Signal 1 | W6: =ROUND(AB6*Assumptions!B137*Assumptions!B138*Assumptions!B139*Assumptions!B136,0) -> 20 | X6: =ROUND(AB6*Assumptions!B137*Assumptions!B65,0) -> 3 | Y6: =Assumptions!B162 -> 50 | Z6: =Assumptions!B153 -> 0 | AA6: =ROUND(Y6*Assumptions!B166,0) -> 0 | AB6: =B6+Z6+AA6 -> 500 | AC6: =ROUND(IF(A6>=Assumptions!B144,(IF(A6>=25,Assumptions!B151,IF(A6>=16,Assumptions!B150,Assumptions!B149))/1000*Assumptions!B146)+IF(A6>=Assumptions!B145,(IF(A6>=25,Assumptions!B151,IF(A6>=16,Assumptions!B150,Assumptions!B149))*Assumptions!B152/1000*Assumptions!B147),0),0),0) -> 0 | AD6: =IF(Y6>=10000,Assumptions!B170,IF(Y6>=5000,Assumptions!B169,IF(Y6>=2000,Assumptions!B168,IF(Y6>=500,Assumptions!B167,0)))) -> 0
A7: 2 | B7: =B6*(1+Assumptions!B33) -> 540 | C7: =ROUND(AB7*Assumptions!B25,0) -> 11 | D7: =ROUND(AB7*Assumptions!B22,0) -> 1 | E7: =E6+D7-F7 -> 2 | F7: =ROUND(E6*Assumptions!B43,0) -> 0 | G7: =D7-F7 -> 1 | H7: =ROUND(E7*Assumptions!B14,0) -> 16 | I7: =H7 -> 16 | J7: =ROUND(E7*Assumptions!B68,0) -> 7 | K7: =ROUND(J7*Assumptions!B65,0) -> 1 | L7: =Assumptions!B70+IF(E7>Assumptions!B72,45,0) -> 31 | M7: =Assumptions!B76+Assumptions!B77 -> 35 | N7: =Assumptions!B81+Assumptions!B82+Assumptions!B87/12 -> 50 | O7: =ROUND(I7*Assumptions!B85+E7*Assumptions!B86+W7*Assumptions!B85+ROUND(AB7*Assumptions!B137*Assumptions!B138*Assumptions!B139,0)*Assumptions!B86,0) -> 2 | P7: =K7+L7+M7+N7+O7+X7 -> 122 | Q7: =I7-P7 -> -106 | R7: =0 -> 0 | S7: =I7+R7+W7+AC7+AD7 -> 37 | T7: =IF(U7<P7*3,0,IF(U7<P7*6,ROUND((Q7+R7+W7+AC7+AD7)*0.75*Assumptions!B113,0),ROUND((Q7+R7+W7+AC7+AD7)*0.75*Assumptions!B114,0))) -> 0 | U7: =U6+Q7+R7+W7+AC7+AD7 -> -2928 | V7: =IF(AB7>=Assumptions!B107,"Signal 6",IF(AB7>=Assumptions!B106,"Signal 5",IF(AB7>=Assumptions!B105,"Signal 4",IF(AB7>=Assumptions!B104,"Signal 3",IF(AB7>=Assumptions!B103,"Signal 2",IF(AB7>=Assumptions!B102,"Signal 1","Pre-Signal 1")))))) -> Pre-Signal 1 | W7: =ROUND(AB7*Assumptions!B137*Assumptions!B138*Assumptions!B139*Assumptions!B136,0) -> 21 | X7: =ROUND(AB7*Assumptions!B137*Assumptions!B65,0) -> 3 | Y7: =ROUND(Y6*(1+Assumptions!B163),0) -> 60 | Z7: =Assumptions!B153 -> 0 | AA7: =ROUND(Y7*Assumptions!B166,0) -> 0 | AB7: =B7+Z7+AA7 -> 540 | AC7: =ROUND(IF(A7>=Assumptions!B144,(IF(A7>=25,Assumptions!B151,IF(A7>=16,Assumptions!B150,Assumptions!B149))/1000*Assumptions!B146)+IF(A7>=Assumptions!B145,(IF(A7>=25,Assumptions!B151,IF(A7>=16,Assumptions!B150,Assumptions!B149))*Assumptions!B152/1000*Assumptions!B147),0),0),0) -> 0 | AD7: =IF(Y7>=10000,Assumptions!B170,IF(Y7>=5000,Assumptions!B169,IF(Y7>=2000,Assumptions!B168,IF(Y7>=500,Assumptions!B167,0)))) -> 0
A8: 3 | B8: =B7*(1+Assumptions!B33)*Assumptions!B36 -> 670.68 | C8: =ROUND(AB8*Assumptions!B25,0) -> 13 | D8: =ROUND(AB8*Assumptions!B22,0) -> 1 | E8: =E7+D8-F8 -> 3 | F8: =ROUND(E7*Assumptions!B43,0) -> 0 | G8: =D8-F8 -> 1 | H8: =ROUND(E8*Assumptions!B14,0) -> 24 | I8: =H8 -> 24 | J8: =ROUND(E8*Assumptions!B68,0) -> 11 | K8: =ROUND(J8*Assumptions!B65,0) -> 1 | L8: =Assumptions!B70+IF(E8>Assumptions!B72,45,0) -> 31 | M8: =Assumptions!B76+Assumptions!B77 -> 35 | N8: =Assumptions!B81+Assumptions!B82+Assumptions!B87/12+Assumptions!B148 -> 116 | O8: =ROUND(I8*Assumptions!B85+E8*Assumptions!B86+W8*Assumptions!B85+ROUND(AB8*Assumptions!B137*Assumptions!B138*Assumptions!B139,0)*Assumptions!B86,0) -> 3 | P8: =K8+L8+M8+N8+O8+X8 -> 190 | Q8: =I8-P8 -> -166 | R8: =0 -> 0 | S8: =I8+R8+W8+AC8+AD8 -> 50 | T8: =IF(U8<P8*3,0,IF(U8<P8*6,ROUND((Q8+R8+W8+AC8+AD8)*0.75*Assumptions!B113,0),ROUND((Q8+R8+W8+AC8+AD8)*0.75*Assumptions!B114,0))) -> 0 | U8: =U7+Q8+R8+W8+AC8+AD8 -> -3068 | V8: =IF(AB8>=Assumptions!B107,"Signal 6",IF(AB8>=Assumptions!B106,"Signal 5",IF(AB8>=Assumptions!B105,"Signal 4",IF(AB8>=Assumptions!B104,"Signal 3",IF(AB8>=Assumptions!B103,"Signal 2",IF(AB8>=Assumptions!B102,"Signal 1","Pre-Signal 1")))))) -> Pre-Signal 1 | W8: =ROUND(AB8*Assumptions!B137*Assumptions!B138*Assumptions!B139*Assumptions!B136,0) -> 26 | X8: =ROUND(AB8*Assumptions!B137*Assumptions!B65,0) -> 4 | Y8: =ROUND(Y7*(1+Assumptions!B163),0) -> 72 | Z8: =Assumptions!B153 -> 0 | AA8: =ROUND(Y8*Assumptions!B166,0) -> 0 | AB8: =B8+Z8+AA8 -> 670.68 | AC8: =ROUND(IF(A8>=Assumptions!B144,(IF(A8>=25,Assumptions!B151,IF(A8>=16,Assumptions!B150,Assumptions!B149))/1000*Assumptions!B146)+IF(A8>=Assumptions!B145,(IF(A8>=25,Assumptions!B151,IF(A8>=16,Assumptions!B150,Assumptions!B149))*Assumptions!B152/1000*Assumptions!B147),0),0),0) -> 0 | AD8: =IF(Y8>=10000,Assumptions!B170,IF(Y8>=5000,Assumptions!B169,IF(Y8>=2000,Assumptions!B168,IF(Y8>=500,Assumptions!B167,0)))) -> 0
A9: 4 | B9: =B8*(1+Assumptions!B33) -> 724.3344 | C9: =ROUND(AB9*Assumptions!B25,0) -> 14 | D9: =ROUND(AB9*Assumptions!B22,0) -> 1 | E9: =E8+D9-F9 -> 4 | F9: =ROUND(E8*Assumptions!B43,0) -> 0 | G9: =D9-F9 -> 1 | H9: =ROUND(E9*Assumptions!B14,0) -> 32 | I9: =H9 -> 32 | J9: =ROUND(E9*Assumptions!B68,0) -> 14 | K9: =ROUND(J9*Assumptions!B65,0) -> 1 | L9: =Assumptions!B70+IF(E9>Assumptions!B72,45,0) -> 31 | M9: =Assumptions!B76+Assumptions!B77 -> 35 | N9: =Assumptions!B81+Assumptions!B82+Assumptions!B87/12+Assumptions!B148 -> 116 | O9: =ROUND(I9*Assumptions!B85+E9*Assumptions!B86+W9*Assumptions!B85+ROUND(AB9*Assumptions!B137*Assumptions!B138*Assumptions!B139,0)*Assumptions!B86,0) -> 4 | P9: =K9+L9+M9+N9+O9+X9 -> 192 | Q9: =I9-P9 -> -160 | R9: =0 -> 0 | S9: =I9+R9+W9+AC9+AD9 -> 60 | T9: =IF(U9<P9*3,0,IF(U9<P9*6,ROUND((Q9+R9+W9+AC9+AD9)*0.75*Assumptions!B113,0),ROUND((Q9+R9+W9+AC9+AD9)*0.75*Assumptions!B114,0))) -> 0 | U9: =U8+Q9+R9+W9+AC9+AD9 -> -3200 | V9: =IF(AB9>=Assumptions!B107,"Signal 6",IF(AB9>=Assumptions!B106,"Signal 5",IF(AB9>=Assumptions!B105,"Signal 4",IF(AB9>=Assumptions!B104,"Signal 3",IF(AB9>=Assumptions!B103,"Signal 2",IF(AB9>=Assumptions!B102,"Signal 1","Pre-Signal 1")))))) -> Pre-Signal 1 | W9: =ROUND(AB9*Assumptions!B137*Assumptions!B138*Assumptions!B139*Assumptions!B136,0) -> 28 | X9: =ROUND(AB9*Assumptions!B137*Assumptions!B65,0) -> 5 | Y9: =ROUND(Y8*(1+Assumptions!B163),0) -> 86 | Z9: =Assumptions!B153 -> 0 | AA9: =ROUND(Y9*Assumptions!B166,0) -> 0 | AB9: =B9+Z9+AA9 -> 724.3344 | AC9: =ROUND(IF(A9>=Assumptions!B144,(IF(A9>=25,Assumptions!B151,IF(A9>=16,Assumptions!B150,Assumptions!B149))/1000*Assumptions!B146)+IF(A9>=Assumptions!B145,(IF(A9>=25,Assumptions!B151,IF(A9>=16,Assumptions!B150,Assumptions!B149))*Assumptions!B152/1000*Assumptions!B147),0),0),0) -> 0 | AD9: =IF(Y9>=10000,Assumptions!B170,IF(Y9>=5000,Assumptions!B169,IF(Y9>=2000,Assumptions!B168,IF(Y9>=500,Assumptions!B167,0)))) -> 0
A10: 5 | B10: =B9*(1+Assumptions!B33) -> 782.28115 | C10: =ROUND(AB10*Assumptions!B25,0) -> 16 | D10: =ROUND(AB10*Assumptions!B22,0) -> 1 | E10: =E9+D10-F10 -> 5 | F10: =ROUND(E9*Assumptions!B43,0) -> 0 | G10: =D10-F10 -> 1 | H10: =ROUND(E10*Assumptions!B14,0) -> 40 | I10: =H10 -> 40 | J10: =ROUND(E10*Assumptions!B68,0) -> 18 | K10: =ROUND(J10*Assumptions!B65,0) -> 1 | L10: =Assumptions!B70+IF(E10>Assumptions!B72,45,0) -> 31 | M10: =Assumptions!B76+Assumptions!B77 -> 35 | N10: =Assumptions!B81+Assumptions!B82+Assumptions!B87/12+Assumptions!B148 -> 116 | O10: =ROUND(I10*Assumptions!B85+E10*Assumptions!B86+W10*Assumptions!B85+ROUND(AB10*Assumptions!B137*Assumptions!B138*Assumptions!B139,0)*Assumptions!B86,0) -> 4 | P10: =K10+L10+M10+N10+O10+X10 -> 192 | Q10: =I10-P10 -> -152 | R10: =0 -> 0 | S10: =I10+R10+W10+AC10+AD10 -> 71 | T10: =IF(U10<P10*3,0,IF(U10<P10*6,ROUND((Q10+R10+W10+AC10+AD10)*0.75*Assumptions!B113,0),ROUND((Q10+R10+W10+AC10+AD10)*0.75*Assumptions!B114,0))) -> 0 | U10: =U9+Q10+R10+W10+AC10+AD10 -> -3321 | V10: =IF(AB10>=Assumptions!B107,"Signal 6",IF(AB10>=Assumptions!B106,"Signal 5",IF(AB10>=Assumptions!B105,"Signal 4",IF(AB10>=Assumptions!B104,"Signal 3",IF(AB10>=Assumptions!B103,"Signal 2",IF(AB10>=Assumptions!B102,"Signal 1","Pre-Signal 1")))))) -> Pre-Signal 1 | W10: =ROUND(AB10*Assumptions!B137*Assumptions!B138*Assumptions!B139*Assumptions!B136,0) -> 31 | X10: =ROUND(AB10*Assumptions!B137*Assumptions!B65,0) -> 5 | Y10: =ROUND(Y9*(1+Assumptions!B163),0) -> 103 | Z10: =Assumptions!B153 -> 0 | AA10: =ROUND(Y10*Assumptions!B166,0) -> 0 | AB10: =B10+Z10+AA10 -> 782.28115 | AC10: =ROUND(IF(A10>=Assumptions!B144,(IF(A10>=25,Assumptions!B151,IF(A10>=16,Assumptions!B150,Assumptions!B149))/1000*Assumptions!B146)+IF(A10>=Assumptions!B145,(IF(A10>=25,Assumptions!B151,IF(A10>=16,Assumptions!B150,Assumptions!B149))*Assumptions!B152/1000*Assumptions!B147),0),0),0) -> 0 | AD10: =IF(Y10>=10000,Assumptions!B170,IF(Y10>=5000,Assumptions!B169,IF(Y10>=2000,Assumptions!B168,IF(Y10>=500,Assumptions!B167,0)))) -> 0
A11: 6 | B11: =B10*(1+Assumptions!B33)*Assumptions!B37 -> 912.45274 | C11: =ROUND(AB11*Assumptions!B25,0) -> 19 | D11: =ROUND(AB11*Assumptions!B22,0) -> 1 | E11: =E10+D11-F11 -> 6 | F11: =ROUND(E10*Assumptions!B43,0) -> 0 | G11: =D11-F11 -> 1 | H11: =ROUND(E11*Assumptions!B14,0) -> 48 | I11: =H11 -> 48 | J11: =ROUND(E11*Assumptions!B68,0) -> 21 | K11: =ROUND(J11*Assumptions!B65,0) -> 2 | L11: =Assumptions!B70+IF(E11>Assumptions!B72,45,0) -> 31 | M11: =Assumptions!B76+Assumptions!B77 -> 35 | N11: =Assumptions!B81+Assumptions!B82+Assumptions!B87/12+Assumptions!B148 -> 116 | O11: =ROUND(I11*Assumptions!B85+E11*Assumptions!B86+W11*Assumptions!B85+ROUND(AB11*Assumptions!B137*Assumptions!B138*Assumptions!B139,0)*Assumptions!B86,0) -> 5 | P11: =K11+L11+M11+N11+O11+X11 -> 195 | Q11: =I11-P11 -> -147 | R11: =ROUND(AB11*Assumptions!B51*Assumptions!B52,0) -> 328 | S11: =I11+R11+W11+AC11+AD11 -> 413 | T11: =IF(U11<P11*3,0,IF(U11<P11*6,ROUND((Q11+R11+W11+AC11+AD11)*0.75*Assumptions!B113,0),ROUND((Q11+R11+W11+AC11+AD11)*0.75*Assumptions!B114,0))) -> 0 | U11: =U10+Q11+R11+W11+AC11+AD11 -> -3103 | V11: =IF(AB11>=Assumptions!B107,"Signal 6",IF(AB11>=Assumptions!B106,"Signal 5",IF(AB11>=Assumptions!B105,"Signal 4",IF(AB11>=Assumptions!B104,"Signal 3",IF(AB11>=Assumptions!B103,"Signal 2",IF(AB11>=Assumptions!B102,"Signal 1","Pre-Signal 1")))))) -> Pre-Signal 1 | W11: =ROUND(AB11*Assumptions!B137*Assumptions!B138*Assumptions!B139*Assumptions!B136,0) -> 37 | X11: =ROUND(AB11*Assumptions!B137*Assumptions!B65,0) -> 6 | Y11: =ROUND(Y10*(1+Assumptions!B163),0) -> 124 | Z11: =Assumptions!B154 -> 25 | AA11: =ROUND(Y11*Assumptions!B166,0) -> 0 | AB11: =B11+Z11+AA11 -> 937.45274 | AC11: =ROUND(IF(A11>=Assumptions!B144,(IF(A11>=25,Assumptions!B151,IF(A11>=16,Assumptions!B150,Assumptions!B149))/1000*Assumptions!B146)+IF(A11>=Assumptions!B145,(IF(A11>=25,Assumptions!B151,IF(A11>=16,Assumptions!B150,Assumptions!B149))*Assumptions!B152/1000*Assumptions!B147),0),0),0) -> 0 | AD11: =IF(Y11>=10000,Assumptions!B170,IF(Y11>=5000,Assumptions!B169,IF(Y11>=2000,Assumptions!B168,IF(Y11>=500,Assumptions!B167,0)))) -> 0
A12: 7 | B12: =B11*(1+Assumptions!B33) -> 985.44895 | C12: =ROUND(AB12*Assumptions!B25,0) -> 20 | D12: =ROUND(AB12*Assumptions!B22,0) -> 2 | E12: =E11+D12-F12 -> 8 | F12: =ROUND(E11*Assumptions!B43,0) -> 0 | G12: =D12-F12 -> 2 | H12: =ROUND(E12*Assumptions!B14,0) -> 64 | I12: =H12 -> 64 | J12: =ROUND(E12*Assumptions!B68,0) -> 28 | K12: =ROUND(J12*Assumptions!B65,0) -> 2 | L12: =Assumptions!B70+IF(E12>Assumptions!B72,45,0) -> 31 | M12: =Assumptions!B76+Assumptions!B77 -> 35 | N12: =Assumptions!B81+Assumptions!B82+Assumptions!B87/12+Assumptions!B148 -> 116 | O12: =ROUND(I12*Assumptions!B85+E12*Assumptions!B86+W12*Assumptions!B85+ROUND(AB12*Assumptions!B137*Assumptions!B138*Assumptions!B139,0)*Assumptions!B86,0) -> 6 | P12: =K12+L12+M12+N12+O12+X12 -> 196 | Q12: =I12-P12 -> -132 | R12: =ROUND(AB12*Assumptions!B51*Assumptions!B52,0) -> 354 | S12: =I12+R12+W12+AC12+AD12 -> 457 | T12: =IF(U12<P12*3,0,IF(U12<P12*6,ROUND((Q12+R12+W12+AC12+AD12)*0.75*Assumptions!B113,0),ROUND((Q12+R12+W12+AC12+AD12)*0.75*Assumptions!B114,0))) -> 0 | U12: =U11+Q12+R12+W12+AC12+AD12 -> -2842 | V12: =IF(AB12>=Assumptions!B107,"Signal 6",IF(AB12>=Assumptions!B106,"Signal 5",IF(AB12>=Assumptions!B105,"Signal 4",IF(AB12>=Assumptions!B104,"Signal 3",IF(AB12>=Assumptions!B103,"Signal 2",IF(AB12>=Assumptions!B102,"Signal 1","Pre-Signal 1")))))) -> Pre-Signal 1 | W12: =ROUND(AB12*Assumptions!B137*Assumptions!B138*Assumptions!B139*Assumptions!B136,0) -> 39 | X12: =ROUND(AB12*Assumptions!B137*Assumptions!B65,0) -> 6 | Y12: =ROUND(Y11*(1+Assumptions!B164),0) -> 143 | Z12: =Assumptions!B154 -> 25 | AA12: =ROUND(Y12*Assumptions!B166,0) -> 0 | AB12: =B12+Z12+AA12 -> 1010.449 | AC12: =ROUND(IF(A12>=Assumptions!B144,(IF(A12>=25,Assumptions!B151,IF(A12>=16,Assumptions!B150,Assumptions!B149))/1000*Assumptions!B146)+IF(A12>=Assumptions!B145,(IF(A12>=25,Assumptions!B151,IF(A12>=16,Assumptions!B150,Assumptions!B149))*Assumptions!B152/1000*Assumptions!B147),0),0),0) -> 0 | AD12: =IF(Y12>=10000,Assumptions!B170,IF(Y12>=5000,Assumptions!B169,IF(Y12>=2000,Assumptions!B168,IF(Y12>=500,Assumptions!B167,0)))) -> 0
A13: 8 | B13: =B12*(1+Assumptions!B33) -> 1064.2849 | C13: =ROUND(AB13*Assumptions!B25,0) -> 22 | D13: =ROUND(AB13*Assumptions!B22,0) -> 2 | E13: =E12+D13-F13 -> 9 | F13: =ROUND(E12*Assumptions!B43,0) -> 1 | G13: =D13-F13 -> 1 | H13: =ROUND(E13*Assumptions!B14,0) -> 72 | I13: =H13 -> 72 | J13: =ROUND(E13*Assumptions!B68,0) -> 32 | K13: =ROUND(J13*Assumptions!B65,0) -> 3 | L13: =Assumptions!B70+IF(E13>Assumptions!B72,45,0) -> 31 | M13: =Assumptions!B76+Assumptions!B77 -> 35 | N13: =Assumptions!B81+Assumptions!B82+Assumptions!B87/12+Assumptions!B148 -> 116 | O13: =ROUND(I13*Assumptions!B85+E13*Assumptions!B86+W13*Assumptions!B85+ROUND(AB13*Assumptions!B137*Assumptions!B138*Assumptions!B139,0)*Assumptions!B86,0) -> 7 | P13: =K13+L13+M13+N13+O13+X13 -> 199 | Q13: =I13-P13 -> -127 | R13: =ROUND(AB13*Assumptions!B51*Assumptions!B52,0) -> 381 | S13: =I13+R13+W13+AC13+AD13 -> 495 | T13: =IF(U13<P13*3,0,IF(U13<P13*6,ROUND((Q13+R13+W13+AC13+AD13)*0.75*Assumptions!B113,0),ROUND((Q13+R13+W13+AC13+AD13)*0.75*Assumptions!B114,0))) -> 0 | U13: =U12+Q13+R13+W13+AC13+AD13 -> -2546 | V13: =IF(AB13>=Assumptions!B107,"Signal 6",IF(AB13>=Assumptions!B106,"Signal 5",IF(AB13>=Assumptions!B105,"Signal 4",IF(AB13>=Assumptions!B104,"Signal 3",IF(AB13>=Assumptions!B103,"Signal 2",IF(AB13>=Assumptions!B102,"Signal 1","Pre-Signal 1")))))) -> Pre-Signal 1 | W13: =ROUND(AB13*Assumptions!B137*Assumptions!B138*Assumptions!B139*Assumptions!B136,0) -> 42 | X13: =ROUND(AB13*Assumptions!B137*Assumptions!B65,0) -> 7 | Y13: =ROUND(Y12*(1+Assumptions!B164),0) -> 164 | Z13: =Assumptions!B154 -> 25 | AA13: =ROUND(Y13*Assumptions!B166,0) -> 0 | AB13: =B13+Z13+AA13 -> 1089.2849 | AC13: =ROUND(IF(A13>=Assumptions!B144,(IF(A13>=25,Assumptions!B151,IF(A13>=16,Assumptions!B150,Assumptions!B149))/1000*Assumptions!B146)+IF(A13>=Assumptions!B145,(IF(A13>=25,Assumptions!B151,IF(A13>=16,Assumptions!B150,Assumptions!B149))*Assumptions!B152/1000*Assumptions!B147),0),0),0) -> 0 | AD13: =IF(Y13>=10000,Assumptions!B170,IF(Y13>=5000,Assumptions!B169,IF(Y13>=2000,Assumptions!B168,IF(Y13>=500,Assumptions!B167,0)))) -> 0
A14: 9 | B14: =B13*(1+Assumptions!B33) -> 1149.4277 | C14: =ROUND(AB14*Assumptions!B25,0) -> 24 | D14: =ROUND(AB14*Assumptions!B22,0) -> 2 | E14: =E13+D14-F14 -> 10 | F14: =ROUND(E13*Assumptions!B43,0) -> 1 | G14: =D14-F14 -> 1 | H14: =ROUND(E14*((Assumptions!B14+Assumptions!B15)/2),0) -> 105 | I14: =H14 -> 105 | J14: =ROUND(E14*Assumptions!B68,0) -> 35 | K14: =ROUND(J14*Assumptions!B65,0) -> 3 | L14: =Assumptions!B70+IF(E14>Assumptions!B72,45,0) -> 31 | M14: =Assumptions!B76+Assumptions!B77 -> 35 | N14: =Assumptions!B81+Assumptions!B82+Assumptions!B87/12+Assumptions!B148 -> 116 | O14: =ROUND(I14*Assumptions!B85+E14*Assumptions!B86+W14*Assumptions!B85+ROUND(AB14*Assumptions!B137*Assumptions!B138*Assumptions!B139,0)*Assumptions!B86,0) -> 9 | P14: =K14+L14+M14+N14+O14+X14 -> 202 | Q14: =I14-P14 -> -97 | R14: =ROUND(AB14*Assumptions!B51*Assumptions!B52,0) -> 424 | S14: =I14+R14+W14+AC14+AD14 -> 576 | T14: =IF(U14<P14*3,0,IF(U14<P14*6,ROUND((Q14+R14+W14+AC14+AD14)*0.75*Assumptions!B113,0),ROUND((Q14+R14+W14+AC14+AD14)*0.75*Assumptions!B114,0))) -> 0 | U14: =U13+Q14+R14+W14+AC14+AD14 -> -2172 | V14: =IF(AB14>=Assumptions!B107,"Signal 6",IF(AB14>=Assumptions!B106,"Signal 5",IF(AB14>=Assumptions!B105,"Signal 4",IF(AB14>=Assumptions!B104,"Signal 3",IF(AB14>=Assumptions!B103,"Signal 2",IF(AB14>=Assumptions!B102,"Signal 1","Pre-Signal 1")))))) -> Pre-Signal 1 | W14: =ROUND(AB14*Assumptions!B137*Assumptions!B138*Assumptions!B139*Assumptions!B136,0) -> 47 | X14: =ROUND(AB14*Assumptions!B137*Assumptions!B65,0) -> 8 | Y14: =ROUND(Y13*(1+Assumptions!B164),0) -> 189 | Z14: =Assumptions!B155 -> 60 | AA14: =ROUND(Y14*Assumptions!B166,0) -> 1 | AB14: =B14+Z14+AA14 -> 1210.4277 | AC14: =ROUND(IF(A14>=Assumptions!B144,(IF(A14>=25,Assumptions!B151,IF(A14>=16,Assumptions!B150,Assumptions!B149))/1000*Assumptions!B146)+IF(A14>=Assumptions!B145,(IF(A14>=25,Assumptions!B151,IF(A14>=16,Assumptions!B150,Assumptions!B149))*Assumptions!B152/1000*Assumptions!B147),0),0),0) -> 0 | AD14: =IF(Y14>=10000,Assumptions!B170,IF(Y14>=5000,Assumptions!B169,IF(Y14>=2000,Assumptions!B168,IF(Y14>=500,Assumptions!B167,0)))) -> 0
A15: 10 | B15: =B14*(1+Assumptions!B33) -> 1241.3819 | C15: =ROUND(AB15*Assumptions!B25,0) -> 26 | D15: =ROUND(AB15*Assumptions!B22,0) -> 2 | E15: =E14+D15-F15 -> 11 | F15: =ROUND(E14*Assumptions!B43,0) -> 1 | G15: =D15-F15 -> 1 | H15: =ROUND(E15*(Assumptions!B15*0.85+Assumptions!B11*0.15),0) -> 126 | I15: =H15 -> 126 | J15: =ROUND(E15*Assumptions!B68,0) -> 39 | K15: =ROUND(J15*Assumptions!B65,0) -> 3 | L15: =Assumptions!B70+IF(E15>Assumptions!B72,45,0) -> 31 | M15: =Assumptions!B76+Assumptions!B77 -> 35 | N15: =Assumptions!B81+Assumptions!B82+Assumptions!B87/12+Assumptions!B148 -> 116 | O15: =ROUND(I15*Assumptions!B85+E15*Assumptions!B86+W15*Assumptions!B85+ROUND(AB15*Assumptions!B137*Assumptions!B138*Assumptions!B139,0)*Assumptions!B86,0) -> 10 | P15: =K15+L15+M15+N15+O15+X15 -> 203 | Q15: =I15-P15 -> -77 | R15: =ROUND(AB15*Assumptions!B51*Assumptions!B52,0) -> 456 | S15: =I15+R15+W15+AC15+AD15 -> 633 | T15: =IF(U15<P15*3,0,IF(U15<P15*6,ROUND((Q15+R15+W15+AC15+AD15)*0.75*Assumptions!B113,0),ROUND((Q15+R15+W15+AC15+AD15)*0.75*Assumptions!B114,0))) -> 0 | U15: =U14+Q15+R15+W15+AC15+AD15 -> -1742 | V15: =IF(AB15>=Assumptions!B107,"Signal 6",IF(AB15>=Assumptions!B106,"Signal 5",IF(AB15>=Assumptions!B105,"Signal 4",IF(AB15>=Assumptions!B104,"Signal 3",IF(AB15>=Assumptions!B103,"Signal 2",IF(AB15>=Assumptions!B102,"Signal 1","Pre-Signal 1")))))) -> Pre-Signal 1 | W15: =ROUND(AB15*Assumptions!B137*Assumptions!B138*Assumptions!B139*Assumptions!B136,0) -> 51 | X15: =ROUND(AB15*Assumptions!B137*Assumptions!B65,0) -> 8 | Y15: =ROUND(Y14*(1+Assumptions!B164),0) -> 217 | Z15: =Assumptions!B155 -> 60 | AA15: =ROUND(Y15*Assumptions!B166,0) -> 1 | AB15: =B15+Z15+AA15 -> 1302.3819 | AC15: =ROUND(IF(A15>=Assumptions!B144,(IF(A15>=25,Assumptions!B151,IF(A15>=16,Assumptions!B150,Assumptions!B149))/1000*Assumptions!B146)+IF(A15>=Assumptions!B145,(IF(A15>=25,Assumptions!B151,IF(A15>=16,Assumptions!B150,Assumptions!B149))*Assumptions!B152/1000*Assumptions!B147),0),0),0) -> 0 | AD15: =IF(Y15>=10000,Assumptions!B170,IF(Y15>=5000,Assumptions!B169,IF(Y15>=2000,Assumptions!B168,IF(Y15>=500,Assumptions!B167,0)))) -> 0
A16: 11 | B16: =B15*(1+Assumptions!B33) -> 1340.6924 | C16: =ROUND(AB16*Assumptions!B25,0) -> 28 | D16: =ROUND(AB16*Assumptions!B22,0) -> 2 | E16: =E15+D16-F16 -> 12 | F16: =ROUND(E15*Assumptions!B43,0) -> 1 | G16: =D16-F16 -> 1 | H16: =ROUND(E16*(Assumptions!B15*0.85+Assumptions!B11*0.15),0) -> 138 | I16: =H16 -> 138 | J16: =ROUND(E16*Assumptions!B68,0) -> 42 | K16: =ROUND(J16*Assumptions!B65,0) -> 3 | L16: =Assumptions!B70+IF(E16>Assumptions!B72,45,0) -> 31 | M16: =Assumptions!B76+Assumptions!B77 -> 35 | N16: =Assumptions!B81+Assumptions!B82+Assumptions!B87/12+Assumptions!B148 -> 116 | O16: =ROUND(I16*Assumptions!B85+E16*Assumptions!B86+W16*Assumptions!B85+ROUND(AB16*Assumptions!B137*Assumptions!B138*Assumptions!B139,0)*Assumptions!B86,0) -> 10 | P16: =K16+L16+M16+N16+O16+X16 -> 204 | Q16: =I16-P16 -> -66 | R16: =ROUND(AB16*Assumptions!B51*Assumptions!B52,0) -> 491 | S16: =I16+R16+W16+AC16+AD16 -> 684 | T16: =IF(U16<P16*3,0,IF(U16<P16*6,ROUND((Q16+R16+W16+AC16+AD16)*0.75*Assumptions!B113,0),ROUND((Q16+R16+W16+AC16+AD16)*0.75*Assumptions!B114,0))) -> 0 | U16: =U15+Q16+R16+W16+AC16+AD16 -> -1262 | V16: =IF(AB16>=Assumptions!B107,"Signal 6",IF(AB16>=Assumptions!B106,"Signal 5",IF(AB16>=Assumptions!B105,"Signal 4",IF(AB16>=Assumptions!B104,"Signal 3",IF(AB16>=Assumptions!B103,"Signal 2",IF(AB16>=Assumptions!B102,"Signal 1","Pre-Signal 1")))))) -> Pre-Signal 1 | W16: =ROUND(AB16*Assumptions!B137*Assumptions!B138*Assumptions!B139*Assumptions!B136,0) -> 55 | X16: =ROUND(AB16*Assumptions!B137*Assumptions!B65,0) -> 9 | Y16: =ROUND(Y15*(1+Assumptions!B164),0) -> 250 | Z16: =Assumptions!B155 -> 60 | AA16: =ROUND(Y16*Assumptions!B166,0) -> 1 | AB16: =B16+Z16+AA16 -> 1401.6924 | AC16: =ROUND(IF(A16>=Assumptions!B144,(IF(A16>=25,Assumptions!B151,IF(A16>=16,Assumptions!B150,Assumptions!B149))/1000*Assumptions!B146)+IF(A16>=Assumptions!B145,(IF(A16>=25,Assumptions!B151,IF(A16>=16,Assumptions!B150,Assumptions!B149))*Assumptions!B152/1000*Assumptions!B147),0),0),0) -> 0 | AD16: =IF(Y16>=10000,Assumptions!B170,IF(Y16>=5000,Assumptions!B169,IF(Y16>=2000,Assumptions!B168,IF(Y16>=500,Assumptions!B167,0)))) -> 0
A17: 12 | B17: =B16*(1+Assumptions!B33) -> 1447.9478 | C17: =ROUND(AB17*Assumptions!B25,0) -> 31 | D17: =ROUND(AB17*Assumptions!B22,0) -> 2 | E17: =E16+D17-F17 -> 13 | F17: =ROUND(E16*Assumptions!B43,0) -> 1 | G17: =D17-F17 -> 1 | H17: =ROUND(E17*(Assumptions!B15*0.85+Assumptions!B11*0.15),0) -> 149 | I17: =H17 -> 149 | J17: =ROUND(E17*Assumptions!B68,0) -> 46 | K17: =ROUND(J17*Assumptions!B65,0) -> 4 | L17: =Assumptions!B70+IF(E17>Assumptions!B72,45,0) -> 31 | M17: =Assumptions!B76+Assumptions!B77 -> 35 | N17: =Assumptions!B81+Assumptions!B82+Assumptions!B87/12+Assumptions!B148 -> 116 | O17: =ROUND(I17*Assumptions!B85+E17*Assumptions!B86+W17*Assumptions!B85+ROUND(AB17*Assumptions!B137*Assumptions!B138*Assumptions!B139,0)*Assumptions!B86,0) -> 11 | P17: =K17+L17+M17+N17+O17+X17 -> 207 | Q17: =I17-P17 -> -58 | R17: =ROUND(AB17*Assumptions!B51*Assumptions!B52,0) -> 551 | S17: =I17+R17+W17+AC17+AD17 -> 777 | T17: =IF(U17<P17*3,0,IF(U17<P17*6,ROUND((Q17+R17+W17+AC17+AD17)*0.75*Assumptions!B113,0),ROUND((Q17+R17+W17+AC17+AD17)*0.75*Assumptions!B114,0))) -> 0 | U17: =U16+Q17+R17+W17+AC17+AD17 -> -692 | V17: =IF(AB17>=Assumptions!B107,"Signal 6",IF(AB17>=Assumptions!B106,"Signal 5",IF(AB17>=Assumptions!B105,"Signal 4",IF(AB17>=Assumptions!B104,"Signal 3",IF(AB17>=Assumptions!B103,"Signal 2",IF(AB17>=Assumptions!B102,"Signal 1","Pre-Signal 1")))))) -> Pre-Signal 1 | W17: =ROUND(AB17*Assumptions!B137*Assumptions!B138*Assumptions!B139*Assumptions!B136,0) -> 61 | X17: =ROUND(AB17*Assumptions!B137*Assumptions!B65,0) -> 10 | Y17: =ROUND(Y16*(1+Assumptions!B164),0) -> 288 | Z17: =Assumptions!B156 -> 125 | AA17: =ROUND(Y17*Assumptions!B166,0) -> 1 | AB17: =B17+Z17+AA17 -> 1573.9478 | AC17: =ROUND(IF(A17>=Assumptions!B144,(IF(A17>=25,Assumptions!B151,IF(A17>=16,Assumptions!B150,Assumptions!B149))/1000*Assumptions!B146)+IF(A17>=Assumptions!B145,(IF(A17>=25,Assumptions!B151,IF(A17>=16,Assumptions!B150,Assumptions!B149))*Assumptions!B152/1000*Assumptions!B147),0),0),0) -> 16 | AD17: =IF(Y17>=10000,Assumptions!B170,IF(Y17>=5000,Assumptions!B169,IF(Y17>=2000,Assumptions!B168,IF(Y17>=500,Assumptions!B167,0)))) -> 0
A18: 13 | B18: =B17*(1+Assumptions!B33) -> 1563.7836 | C18: =ROUND(AB18*Assumptions!B25,0) -> 34 | D18: =ROUND(AB18*Assumptions!B22,0) -> 3 | E18: =E17+D18-F18 -> 15 | F18: =ROUND(E17*Assumptions!B43,0) -> 1 | G18: =D18-F18 -> 2 | H18: =ROUND(E18*(Assumptions!B15*0.85+Assumptions!B11*0.15),0) -> 172 | I18: =H18 -> 172 | J18: =ROUND(E18*Assumptions!B68,0) -> 53 | K18: =ROUND(J18*Assumptions!B65,0) -> 4 | L18: =Assumptions!B70+IF(E18>Assumptions!B72,45,0) -> 31 | M18: =Assumptions!B76+Assumptions!B77 -> 35 | N18: =Assumptions!B81+Assumptions!B82+Assumptions!B87/12+Assumptions!B148 -> 116 | O18: =ROUND(I18*Assumptions!B85+E18*Assumptions!B86+W18*Assumptions!B85+ROUND(AB18*Assumptions!B137*Assumptions!B138*Assumptions!B139,0)*Assumptions!B86,0) -> 13 | P18: =K18+L18+M18+N18+O18+X18 -> 210 | Q18: =I18-P18 -> -38 | R18: =ROUND(AB18*Assumptions!B51*Assumptions!B52,0) -> 591 | S18: =I18+R18+W18+AC18+AD18 -> 845 | T18: =IF(U18<P18*3,0,IF(U18<P18*6,ROUND((Q18+R18+W18+AC18+AD18)*0.75*Assumptions!B113,0),ROUND((Q18+R18+W18+AC18+AD18)*0.75*Assumptions!B114,0))) -> 0 | U18: =U17+Q18+R18+W18+AC18+AD18 -> -57 | V18: =IF(AB18>=Assumptions!B107,"Signal 6",IF(AB18>=Assumptions!B106,"Signal 5",IF(AB18>=Assumptions!B105,"Signal 4",IF(AB18>=Assumptions!B104,"Signal 3",IF(AB18>=Assumptions!B103,"Signal 2",IF(AB18>=Assumptions!B102,"Signal 1","Pre-Signal 1")))))) -> Pre-Signal 1 | W18: =ROUND(AB18*Assumptions!B137*Assumptions!B138*Assumptions!B139*Assumptions!B136,0) -> 66 | X18: =ROUND(AB18*Assumptions!B137*Assumptions!B65,0) -> 11 | Y18: =ROUND(Y17*(1+Assumptions!B165),0) -> 317 | Z18: =Assumptions!B156 -> 125 | AA18: =ROUND(Y18*Assumptions!B166,0) -> 1 | AB18: =B18+Z18+AA18 -> 1689.7836 | AC18: =ROUND(IF(A18>=Assumptions!B144,(IF(A18>=25,Assumptions!B151,IF(A18>=16,Assumptions!B150,Assumptions!B149))/1000*Assumptions!B146)+IF(A18>=Assumptions!B145,(IF(A18>=25,Assumptions!B151,IF(A18>=16,Assumptions!B150,Assumptions!B149))*Assumptions!B152/1000*Assumptions!B147),0),0),0) -> 16 | AD18: =IF(Y18>=10000,Assumptions!B170,IF(Y18>=5000,Assumptions!B169,IF(Y18>=2000,Assumptions!B168,IF(Y18>=500,Assumptions!B167,0)))) -> 0
A19: 14 | B19: =B18*(1+Assumptions!B33) -> 1688.8863 | C19: =ROUND(AB19*Assumptions!B25,0) -> 36 | D19: =ROUND(AB19*Assumptions!B22,0) -> 3 | E19: =E18+D19-F19 -> 17 | F19: =ROUND(E18*Assumptions!B43,0) -> 1 | G19: =D19-F19 -> 2 | H19: =ROUND(E19*(Assumptions!B15*0.85+Assumptions!B11*0.15),0) -> 195 | I19: =H19 -> 195 | J19: =ROUND(E19*Assumptions!B68,0) -> 60 | K19: =ROUND(J19*Assumptions!B65,0) -> 5 | L19: =Assumptions!B70+IF(E19>Assumptions!B72,45,0) -> 31 | M19: =Assumptions!B76+Assumptions!B77 -> 35 | N19: =Assumptions!B81+Assumptions!B82+Assumptions!B87/12+Assumptions!B148 -> 116 | O19: =ROUND(I19*Assumptions!B85+E19*Assumptions!B86+W19*Assumptions!B85+ROUND(AB19*Assumptions!B137*Assumptions!B138*Assumptions!B139,0)*Assumptions!B86,0) -> 14 | P19: =K19+L19+M19+N19+O19+X19 -> 213 | Q19: =I19-P19 -> -18 | R19: =ROUND(AB19*Assumptions!B51*Assumptions!B52,0) -> 635 | S19: =I19+R19+W19+AC19+AD19 -> 917 | T19: =IF(U19<P19*3,0,IF(U19<P19*6,ROUND((Q19+R19+W19+AC19+AD19)*0.75*Assumptions!B113,0),ROUND((Q19+R19+W19+AC19+AD19)*0.75*Assumptions!B114,0))) -> 125 | U19: =U18+Q19+R19+W19+AC19+AD19 -> 647 | V19: =IF(AB19>=Assumptions!B107,"Signal 6",IF(AB19>=Assumptions!B106,"Signal 5",IF(AB19>=Assumptions!B105,"Signal 4",IF(AB19>=Assumptions!B104,"Signal 3",IF(AB19>=Assumptions!B103,"Signal 2",IF(AB19>=Assumptions!B102,"Signal 1","Pre-Signal 1")))))) -> Pre-Signal 1 | W19: =ROUND(AB19*Assumptions!B137*Assumptions!B138*Assumptions!B139*Assumptions!B136,0) -> 71 | X19: =ROUND(AB19*Assumptions!B137*Assumptions!B65,0) -> 12 | Y19: =ROUND(Y18*(1+Assumptions!B165),0) -> 349 | Z19: =Assumptions!B156 -> 125 | AA19: =ROUND(Y19*Assumptions!B166,0) -> 1 | AB19: =B19+Z19+AA19 -> 1814.8863 | AC19: =ROUND(IF(A19>=Assumptions!B144,(IF(A19>=25,Assumptions!B151,IF(A19>=16,Assumptions!B150,Assumptions!B149))/1000*Assumptions!B146)+IF(A19>=Assumptions!B145,(IF(A19>=25,Assumptions!B151,IF(A19>=16,Assumptions!B150,Assumptions!B149))*Assumptions!B152/1000*Assumptions!B147),0),0),0) -> 16 | AD19: =IF(Y19>=10000,Assumptions!B170,IF(Y19>=5000,Assumptions!B169,IF(Y19>=2000,Assumptions!B168,IF(Y19>=500,Assumptions!B167,0)))) -> 0
A20: 15 | B20: =B19*(1+Assumptions!B33) -> 1823.9972 | C20: =ROUND(AB20*Assumptions!B25,0) -> 39 | D20: =ROUND(AB20*Assumptions!B22,0) -> 3 | E20: =E19+D20-F20 -> 19 | F20: =ROUND(E19*Assumptions!B43,0) -> 1 | G20: =D20-F20 -> 2 | H20: =ROUND(E20*(Assumptions!B15*0.85+Assumptions!B11*0.15),0) -> 218 | I20: =H20 -> 218 | J20: =ROUND(E20*Assumptions!B68,0) -> 67 | K20: =ROUND(J20*Assumptions!B65,0) -> 5 | L20: =Assumptions!B70+IF(E20>Assumptions!B72,45,0) -> 31 | M20: =Assumptions!B76+Assumptions!B77 -> 35 | N20: =Assumptions!B81+Assumptions!B82+Assumptions!B87/12+Assumptions!B148 -> 116 | O20: =ROUND(I20*Assumptions!B85+E20*Assumptions!B86+W20*Assumptions!B85+ROUND(AB20*Assumptions!B137*Assumptions!B138*Assumptions!B139,0)*Assumptions!B86,0) -> 16 | P20: =K20+L20+M20+N20+O20+X20 -> 215 | Q20: =I20-P20 -> 3 | R20: =ROUND(AB20*Assumptions!B51*Assumptions!B52,0) -> 682 | S20: =I20+R20+W20+AC20+AD20 -> 992 | T20: =IF(U20<P20*3,0,IF(U20<P20*6,ROUND((Q20+R20+W20+AC20+AD20)*0.75*Assumptions!B113,0),ROUND((Q20+R20+W20+AC20+AD20)*0.75*Assumptions!B114,0))) -> 223 | U20: =U19+Q20+R20+W20+AC20+AD20 -> 1424 | V20: =IF(AB20>=Assumptions!B107,"Signal 6",IF(AB20>=Assumptions!B106,"Signal 5",IF(AB20>=Assumptions!B105,"Signal 4",IF(AB20>=Assumptions!B104,"Signal 3",IF(AB20>=Assumptions!B103,"Signal 2",IF(AB20>=Assumptions!B102,"Signal 1","Pre-Signal 1")))))) -> Pre-Signal 1 | W20: =ROUND(AB20*Assumptions!B137*Assumptions!B138*Assumptions!B139*Assumptions!B136,0) -> 76 | X20: =ROUND(AB20*Assumptions!B137*Assumptions!B65,0) -> 12 | Y20: =ROUND(Y19*(1+Assumptions!B165),0) -> 384 | Z20: =Assumptions!B156 -> 125 | AA20: =ROUND(Y20*Assumptions!B166,0) -> 1 | AB20: =B20+Z20+AA20 -> 1949.9972 | AC20: =ROUND(IF(A20>=Assumptions!B144,(IF(A20>=25,Assumptions!B151,IF(A20>=16,Assumptions!B150,Assumptions!B149))/1000*Assumptions!B146)+IF(A20>=Assumptions!B145,(IF(A20>=25,Assumptions!B151,IF(A20>=16,Assumptions!B150,Assumptions!B149))*Assumptions!B152/1000*Assumptions!B147),0),0),0) -> 16 | AD20: =IF(Y20>=10000,Assumptions!B170,IF(Y20>=5000,Assumptions!B169,IF(Y20>=2000,Assumptions!B168,IF(Y20>=500,Assumptions!B167,0)))) -> 0
A21: 16 | B21: =B20*(1+Assumptions!B33) -> 1969.917 | C21: =ROUND(AB21*Assumptions!B25,0) -> 44 | D21: =ROUND(AB21*Assumptions!B22,0) -> 3 | E21: =E20+D21-F21 -> 20 | F21: =ROUND(E20*Assumptions!B43,0) -> 2 | G21: =D21-F21 -> 1 | H21: =ROUND(E21*(Assumptions!B15*0.85+Assumptions!B11*0.15),0) -> 230 | I21: =H21 -> 230 | J21: =ROUND(E21*Assumptions!B68,0) -> 70 | K21: =ROUND(J21*Assumptions!B65,0) -> 6 | L21: =Assumptions!B70+IF(E21>Assumptions!B72,45,0) -> 31 | M21: =Assumptions!B76+Assumptions!B77 -> 35 | N21: =Assumptions!B81+Assumptions!B82+Assumptions!B87/12+Assumptions!B148 -> 116 | O21: =ROUND(I21*Assumptions!B85+E21*Assumptions!B86+W21*Assumptions!B85+ROUND(AB21*Assumptions!B137*Assumptions!B138*Assumptions!B139,0)*Assumptions!B86,0) -> 17 | P21: =K21+L21+M21+N21+O21+X21 -> 219 | Q21: =I21-P21 -> 11 | R21: =ROUND(AB21*Assumptions!B51*Assumptions!B52,0) -> 777 | S21: =I21+R21+W21+AC21+AD21 -> 1137 | T21: =IF(U21<P21*3,0,IF(U21<P21*6,ROUND((Q21+R21+W21+AC21+AD21)*0.75*Assumptions!B113,0),ROUND((Q21+R21+W21+AC21+AD21)*0.75*Assumptions!B114,0))) -> 263 | U21: =U20+Q21+R21+W21+AC21+AD21 -> 2342 | V21: =IF(AB21>=Assumptions!B107,"Signal 6",IF(AB21>=Assumptions!B106,"Signal 5",IF(AB21>=Assumptions!B105,"Signal 4",IF(AB21>=Assumptions!B104,"Signal 3",IF(AB21>=Assumptions!B103,"Signal 2",IF(AB21>=Assumptions!B102,"Signal 1","Pre-Signal 1")))))) -> Pre-Signal 1 | W21: =ROUND(AB21*Assumptions!B137*Assumptions!B138*Assumptions!B139*Assumptions!B136,0) -> 87 | X21: =ROUND(AB21*Assumptions!B137*Assumptions!B65,0) -> 14 | Y21: =ROUND(Y20*(1+Assumptions!B165),0) -> 422 | Z21: =Assumptions!B157 -> 250 | AA21: =ROUND(Y21*Assumptions!B166,0) -> 1 | AB21: =B21+Z21+AA21 -> 2220.917 | AC21: =ROUND(IF(A21>=Assumptions!B144,(IF(A21>=25,Assumptions!B151,IF(A21>=16,Assumptions!B150,Assumptions!B149))/1000*Assumptions!B146)+IF(A21>=Assumptions!B145,(IF(A21>=25,Assumptions!B151,IF(A21>=16,Assumptions!B150,Assumptions!B149))*Assumptions!B152/1000*Assumptions!B147),0),0),0) -> 43 | AD21: =IF(Y21>=10000,Assumptions!B170,IF(Y21>=5000,Assumptions!B169,IF(Y21>=2000,Assumptions!B168,IF(Y21>=500,Assumptions!B167,0)))) -> 0
A22: 17 | B22: =B21*(1+Assumptions!B33) -> 2127.5104 | C22: =ROUND(AB22*Assumptions!B25,0) -> 48 | D22: =ROUND(AB22*Assumptions!B22,0) -> 4 | E22: =E21+D22-F22 -> 22 | F22: =ROUND(E21*Assumptions!B43,0) -> 2 | G22: =D22-F22 -> 2 | H22: =ROUND(E22*(Assumptions!B15*0.85+Assumptions!B11*0.15),0) -> 252 | I22: =H22 -> 252 | J22: =ROUND(E22*Assumptions!B68,0) -> 77 | K22: =ROUND(J22*Assumptions!B65,0) -> 6 | L22: =Assumptions!B70+IF(E22>Assumptions!B72,45,0) -> 31 | M22: =Assumptions!B76+Assumptions!B77 -> 35 | N22: =Assumptions!B81+Assumptions!B82+Assumptions!B87/12+Assumptions!B148 -> 116 | O22: =ROUND(I22*Assumptions!B85+E22*Assumptions!B86+W22*Assumptions!B85+ROUND(AB22*Assumptions!B137*Assumptions!B138*Assumptions!B139,0)*Assumptions!B86,0) -> 19 | P22: =K22+L22+M22+N22+O22+X22 -> 222 | Q22: =I22-P22 -> 30 | R22: =ROUND(AB22*Assumptions!B51*Assumptions!B52,0) -> 832 | S22: =I22+R22+W22+AC22+AD22 -> 1220 | T22: =IF(U22<P22*3,0,IF(U22<P22*6,ROUND((Q22+R22+W22+AC22+AD22)*0.75*Assumptions!B113,0),ROUND((Q22+R22+W22+AC22+AD22)*0.75*Assumptions!B114,0))) -> 286 | U22: =U21+Q22+R22+W22+AC22+AD22 -> 3340 | V22: =IF(AB22>=Assumptions!B107,"Signal 6",IF(AB22>=Assumptions!B106,"Signal 5",IF(AB22>=Assumptions!B105,"Signal 4",IF(AB22>=Assumptions!B104,"Signal 3",IF(AB22>=Assumptions!B103,"Signal 2",IF(AB22>=Assumptions!B102,"Signal 1","Pre-Signal 1")))))) -> Pre-Signal 1 | W22: =ROUND(AB22*Assumptions!B137*Assumptions!B138*Assumptions!B139*Assumptions!B136,0) -> 93 | X22: =ROUND(AB22*Assumptions!B137*Assumptions!B65,0) -> 15 | Y22: =ROUND(Y21*(1+Assumptions!B165),0) -> 464 | Z22: =Assumptions!B157 -> 250 | AA22: =ROUND(Y22*Assumptions!B166,0) -> 1 | AB22: =B22+Z22+AA22 -> 2378.5104 | AC22: =ROUND(IF(A22>=Assumptions!B144,(IF(A22>=25,Assumptions!B151,IF(A22>=16,Assumptions!B150,Assumptions!B149))/1000*Assumptions!B146)+IF(A22>=Assumptions!B145,(IF(A22>=25,Assumptions!B151,IF(A22>=16,Assumptions!B150,Assumptions!B149))*Assumptions!B152/1000*Assumptions!B147),0),0),0) -> 43 | AD22: =IF(Y22>=10000,Assumptions!B170,IF(Y22>=5000,Assumptions!B169,IF(Y22>=2000,Assumptions!B168,IF(Y22>=500,Assumptions!B167,0)))) -> 0
A23: 18 | B23: =B22*(1+Assumptions!B33) -> 2297.7112 | C23: =ROUND(AB23*Assumptions!B25,0) -> 51 | D23: =ROUND(AB23*Assumptions!B22,0) -> 4 | E23: =E22+D23-F23 -> 24 | F23: =ROUND(E22*Assumptions!B43,0) -> 2 | G23: =D23-F23 -> 2 | H23: =ROUND(E23*(Assumptions!B15*0.85+Assumptions!B11*0.15),0) -> 275 | I23: =H23 -> 275 | J23: =ROUND(E23*Assumptions!B68,0) -> 84 | K23: =ROUND(J23*Assumptions!B65,0) -> 7 | L23: =Assumptions!B70+IF(E23>Assumptions!B72,45,0) -> 31 | M23: =Assumptions!B76+Assumptions!B77 -> 35 | N23: =Assumptions!B81+Assumptions!B82+Assumptions!B87/12+Assumptions!B148 -> 116 | O23: =ROUND(I23*Assumptions!B85+E23*Assumptions!B86+W23*Assumptions!B85+ROUND(AB23*Assumptions!B137*Assumptions!B138*Assumptions!B139,0)*Assumptions!B86,0) -> 20 | P23: =K23+L23+M23+N23+O23+X23 -> 225 | Q23: =I23-P23 -> 50 | R23: =ROUND(AB23*Assumptions!B51*Assumptions!B52,0) -> 892 | S23: =I23+R23+W23+AC23+AD23 -> 1314 | T23: =IF(U23<P23*3,0,IF(U23<P23*6,ROUND((Q23+R23+W23+AC23+AD23)*0.75*Assumptions!B113,0),ROUND((Q23+R23+W23+AC23+AD23)*0.75*Assumptions!B114,0))) -> 312 | U23: =U22+Q23+R23+W23+AC23+AD23 -> 4429 | V23: =IF(AB23>=Assumptions!B107,"Signal 6",IF(AB23>=Assumptions!B106,"Signal 5",IF(AB23>=Assumptions!B105,"Signal 4",IF(AB23>=Assumptions!B104,"Signal 3",IF(AB23>=Assumptions!B103,"Signal 2",IF(AB23>=Assumptions!B102,"Signal 1","Pre-Signal 1")))))) -> Pre-Signal 1 | W23: =ROUND(AB23*Assumptions!B137*Assumptions!B138*Assumptions!B139*Assumptions!B136,0) -> 99 | X23: =ROUND(AB23*Assumptions!B137*Assumptions!B65,0) -> 16 | Y23: =ROUND(Y22*(1+Assumptions!B165),0) -> 510 | Z23: =Assumptions!B157 -> 250 | AA23: =ROUND(Y23*Assumptions!B166,0) -> 2 | AB23: =B23+Z23+AA23 -> 2549.7112 | AC23: =ROUND(IF(A23>=Assumptions!B144,(IF(A23>=25,Assumptions!B151,IF(A23>=16,Assumptions!B150,Assumptions!B149))/1000*Assumptions!B146)+IF(A23>=Assumptions!B145,(IF(A23>=25,Assumptions!B151,IF(A23>=16,Assumptions!B150,Assumptions!B149))*Assumptions!B152/1000*Assumptions!B147),0),0),0) -> 43 | AD23: =IF(Y23>=10000,Assumptions!B170,IF(Y23>=5000,Assumptions!B169,IF(Y23>=2000,Assumptions!B168,IF(Y23>=500,Assumptions!B167,0)))) -> 5
A24: 19 | B24: =B23*(1+Assumptions!B33) -> 2481.5281 | C24: =ROUND(AB24*Assumptions!B25,0) -> 55 | D24: =ROUND(AB24*Assumptions!B22,0) -> 4 | E24: =E23+D24-F24 -> 26 | F24: =ROUND(E23*Assumptions!B43,0) -> 2 | G24: =D24-F24 -> 2 | H24: =ROUND(E24*(Assumptions!B15*0.85+Assumptions!B11*0.15),0) -> 298 | I24: =H24 -> 298 | J24: =ROUND(E24*Assumptions!B68,0) -> 91 | K24: =ROUND(J24*Assumptions!B65,0) -> 7 | L24: =Assumptions!B70+IF(E24>Assumptions!B72,45,0) -> 31 | M24: =Assumptions!B76+Assumptions!B77 -> 35 | N24: =Assumptions!B81+Assumptions!B82+Assumptions!B87/12+Assumptions!B148 -> 116 | O24: =ROUND(I24*Assumptions!B85+E24*Assumptions!B86+W24*Assumptions!B85+ROUND(AB24*Assumptions!B137*Assumptions!B138*Assumptions!B139,0)*Assumptions!B86,0) -> 22 | P24: =K24+L24+M24+N24+O24+X24 -> 228 | Q24: =I24-P24 -> 70 | R24: =ROUND(AB24*Assumptions!B51*Assumptions!B52,0) -> 957 | S24: =I24+R24+W24+AC24+AD24 -> 1410 | T24: =IF(U24<P24*3,0,IF(U24<P24*6,ROUND((Q24+R24+W24+AC24+AD24)*0.75*Assumptions!B113,0),ROUND((Q24+R24+W24+AC24+AD24)*0.75*Assumptions!B114,0))) -> 339 | U24: =U23+Q24+R24+W24+AC24+AD24 -> 5611 | V24: =IF(AB24>=Assumptions!B107,"Signal 6",IF(AB24>=Assumptions!B106,"Signal 5",IF(AB24>=Assumptions!B105,"Signal 4",IF(AB24>=Assumptions!B104,"Signal 3",IF(AB24>=Assumptions!B103,"Signal 2",IF(AB24>=Assumptions!B102,"Signal 1","Pre-Signal 1")))))) -> Pre-Signal 1 | W24: =ROUND(AB24*Assumptions!B137*Assumptions!B138*Assumptions!B139*Assumptions!B136,0) -> 107 | X24: =ROUND(AB24*Assumptions!B137*Assumptions!B65,0) -> 17 | Y24: =ROUND(Y23*(1+Assumptions!B165),0) -> 561 | Z24: =Assumptions!B157 -> 250 | AA24: =ROUND(Y24*Assumptions!B166,0) -> 2 | AB24: =B24+Z24+AA24 -> 2733.5281 | AC24: =ROUND(IF(A24>=Assumptions!B144,(IF(A24>=25,Assumptions!B151,IF(A24>=16,Assumptions!B150,Assumptions!B149))/1000*Assumptions!B146)+IF(A24>=Assumptions!B145,(IF(A24>=25,Assumptions!B151,IF(A24>=16,Assumptions!B150,Assumptions!B149))*Assumptions!B152/1000*Assumptions!B147),0),0),0) -> 43 | AD24: =IF(Y24>=10000,Assumptions!B170,IF(Y24>=5000,Assumptions!B169,IF(Y24>=2000,Assumptions!B168,IF(Y24>=500,Assumptions!B167,0)))) -> 5
A25: 20 | B25: =B24*(1+Assumptions!B33) -> 2680.0504 | C25: =ROUND(AB25*Assumptions!B25,0) -> 59 | D25: =ROUND(AB25*Assumptions!B22,0) -> 4 | E25: =E24+D25-F25 -> 28 | F25: =ROUND(E24*Assumptions!B43,0) -> 2 | G25: =D25-F25 -> 2 | H25: =ROUND(E25*(Assumptions!B15*0.85+Assumptions!B11*0.15),0) -> 321 | I25: =H25 -> 321 | J25: =ROUND(E25*Assumptions!B68,0) -> 98 | K25: =ROUND(J25*Assumptions!B65,0) -> 8 | L25: =Assumptions!B70+IF(E25>Assumptions!B72,45,0) -> 31 | M25: =Assumptions!B76+Assumptions!B77 -> 35 | N25: =Assumptions!B81+Assumptions!B82+Assumptions!B87/12+Assumptions!B148 -> 116 | O25: =ROUND(I25*Assumptions!B85+E25*Assumptions!B86+W25*Assumptions!B85+ROUND(AB25*Assumptions!B137*Assumptions!B138*Assumptions!B139,0)*Assumptions!B86,0) -> 24 | P25: =K25+L25+M25+N25+O25+X25 -> 233 | Q25: =I25-P25 -> 88 | R25: =ROUND(AB25*Assumptions!B51*Assumptions!B52,0) -> 1026 | S25: =I25+R25+W25+AC25+AD25 -> 1509 | T25: =IF(U25<P25*3,0,IF(U25<P25*6,ROUND((Q25+R25+W25+AC25+AD25)*0.75*Assumptions!B113,0),ROUND((Q25+R25+W25+AC25+AD25)*0.75*Assumptions!B114,0))) -> 366 | U25: =U24+Q25+R25+W25+AC25+AD25 -> 6887 | V25: =IF(AB25>=Assumptions!B107,"Signal 6",IF(AB25>=Assumptions!B106,"Signal 5",IF(AB25>=Assumptions!B105,"Signal 4",IF(AB25>=Assumptions!B104,"Signal 3",IF(AB25>=Assumptions!B103,"Signal 2",IF(AB25>=Assumptions!B102,"Signal 1","Pre-Signal 1")))))) -> Pre-Signal 1 | W25: =ROUND(AB25*Assumptions!B137*Assumptions!B138*Assumptions!B139*Assumptions!B136,0) -> 114 | X25: =ROUND(AB25*Assumptions!B137*Assumptions!B65,0) -> 19 | Y25: =ROUND(Y24*(1+Assumptions!B165),0) -> 617 | Z25: =Assumptions!B157 -> 250 | AA25: =ROUND(Y25*Assumptions!B166,0) -> 2 | AB25: =B25+Z25+AA25 -> 2932.0504 | AC25: =ROUND(IF(A25>=Assumptions!B144,(IF(A25>=25,Assumptions!B151,IF(A25>=16,Assumptions!B150,Assumptions!B149))/1000*Assumptions!B146)+IF(A25>=Assumptions!B145,(IF(A25>=25,Assumptions!B151,IF(A25>=16,Assumptions!B150,Assumptions!B149))*Assumptions!B152/1000*Assumptions!B147),0),0),0) -> 43 | AD25: =IF(Y25>=10000,Assumptions!B170,IF(Y25>=5000,Assumptions!B169,IF(Y25>=2000,Assumptions!B168,IF(Y25>=500,Assumptions!B167,0)))) -> 5
A26: 21 | B26: =B25*(1+Assumptions!B33) -> 2894.4544 | C26: =ROUND(AB26*Assumptions!B25,0) -> 63 | D26: =ROUND(AB26*Assumptions!B22,0) -> 5 | E26: =E25+D26-F26 -> 31 | F26: =ROUND(E25*Assumptions!B43,0) -> 2 | G26: =D26-F26 -> 3 | H26: =ROUND(E26*(Assumptions!B15*0.85+Assumptions!B11*0.15),0) -> 356 | I26: =H26 -> 356 | J26: =ROUND(E26*Assumptions!B68,0) -> 109 | K26: =ROUND(J26*Assumptions!B65,0) -> 9 | L26: =Assumptions!B70+IF(E26>Assumptions!B72,45,0) -> 31 | M26: =Assumptions!B76+Assumptions!B77 -> 35 | N26: =Assumptions!B81+Assumptions!B82+Assumptions!B87/12+Assumptions!B148 -> 116 | O26: =ROUND(I26*Assumptions!B85+E26*Assumptions!B86+W26*Assumptions!B85+ROUND(AB26*Assumptions!B137*Assumptions!B138*Assumptions!B139,0)*Assumptions!B86,0) -> 26 | P26: =K26+L26+M26+N26+O26+X26 -> 237 | Q26: =I26-P26 -> 119 | R26: =ROUND(AB26*Assumptions!B51*Assumptions!B52,0) -> 1101 | S26: =I26+R26+W26+AC26+AD26 -> 1628 | T26: =IF(U26<P26*3,0,IF(U26<P26*6,ROUND((Q26+R26+W26+AC26+AD26)*0.75*Assumptions!B113,0),ROUND((Q26+R26+W26+AC26+AD26)*0.75*Assumptions!B114,0))) -> 399 | U26: =U25+Q26+R26+W26+AC26+AD26 -> 8278 | V26: =IF(AB26>=Assumptions!B107,"Signal 6",IF(AB26>=Assumptions!B106,"Signal 5",IF(AB26>=Assumptions!B105,"Signal 4",IF(AB26>=Assumptions!B104,"Signal 3",IF(AB26>=Assumptions!B103,"Signal 2",IF(AB26>=Assumptions!B102,"Signal 1","Pre-Signal 1")))))) -> Pre-Signal 1 | W26: =ROUND(AB26*Assumptions!B137*Assumptions!B138*Assumptions!B139*Assumptions!B136,0) -> 123 | X26: =ROUND(AB26*Assumptions!B137*Assumptions!B65,0) -> 20 | Y26: =ROUND(Y25*(1+Assumptions!B165),0) -> 679 | Z26: =Assumptions!B157 -> 250 | AA26: =ROUND(Y26*Assumptions!B166,0) -> 2 | AB26: =B26+Z26+AA26 -> 3146.4544 | AC26: =ROUND(IF(A26>=Assumptions!B144,(IF(A26>=25,Assumptions!B151,IF(A26>=16,Assumptions!B150,Assumptions!B149))/1000*Assumptions!B146)+IF(A26>=Assumptions!B145,(IF(A26>=25,Assumptions!B151,IF(A26>=16,Assumptions!B150,Assumptions!B149))*Assumptions!B152/1000*Assumptions!B147),0),0),0) -> 43 | AD26: =IF(Y26>=10000,Assumptions!B170,IF(Y26>=5000,Assumptions!B169,IF(Y26>=2000,Assumptions!B168,IF(Y26>=500,Assumptions!B167,0)))) -> 5
A27: 22 | B27: =B26*(1+Assumptions!B33) -> 3126.0107 | C27: =ROUND(AB27*Assumptions!B25,0) -> 68 | D27: =ROUND(AB27*Assumptions!B22,0) -> 5 | E27: =E26+D27-F27 -> 34 | F27: =ROUND(E26*Assumptions!B43,0) -> 2 | G27: =D27-F27 -> 3 | H27: =ROUND(E27*(Assumptions!B15*0.85+Assumptions!B11*0.15),0) -> 390 | I27: =H27 -> 390 | J27: =ROUND(E27*Assumptions!B68,0) -> 119 | K27: =ROUND(J27*Assumptions!B65,0) -> 10 | L27: =Assumptions!B70+IF(E27>Assumptions!B72,45,0) -> 31 | M27: =Assumptions!B76+Assumptions!B77 -> 35 | N27: =Assumptions!B81+Assumptions!B82+Assumptions!B87/12+Assumptions!B148 -> 116 | O27: =ROUND(I27*Assumptions!B85+E27*Assumptions!B86+W27*Assumptions!B85+ROUND(AB27*Assumptions!B137*Assumptions!B138*Assumptions!B139,0)*Assumptions!B86,0) -> 28 | P27: =K27+L27+M27+N27+O27+X27 -> 242 | Q27: =I27-P27 -> 148 | R27: =ROUND(AB27*Assumptions!B51*Assumptions!B52,0) -> 1182 | S27: =I27+R27+W27+AC27+AD27 -> 1752 | T27: =IF(U27<P27*3,0,IF(U27<P27*6,ROUND((Q27+R27+W27+AC27+AD27)*0.75*Assumptions!B113,0),ROUND((Q27+R27+W27+AC27+AD27)*0.75*Assumptions!B114,0))) -> 433 | U27: =U26+Q27+R27+W27+AC27+AD27 -> 9788 | V27: =IF(AB27>=Assumptions!B107,"Signal 6",IF(AB27>=Assumptions!B106,"Signal 5",IF(AB27>=Assumptions!B105,"Signal 4",IF(AB27>=Assumptions!B104,"Signal 3",IF(AB27>=Assumptions!B103,"Signal 2",IF(AB27>=Assumptions!B102,"Signal 1","Pre-Signal 1")))))) -> Pre-Signal 1 | W27: =ROUND(AB27*Assumptions!B137*Assumptions!B138*Assumptions!B139*Assumptions!B136,0) -> 132 | X27: =ROUND(AB27*Assumptions!B137*Assumptions!B65,0) -> 22 | Y27: =ROUND(Y26*(1+Assumptions!B165),0) -> 747 | Z27: =Assumptions!B157 -> 250 | AA27: =ROUND(Y27*Assumptions!B166,0) -> 2 | AB27: =B27+Z27+AA27 -> 3378.0107 | AC27: =ROUND(IF(A27>=Assumptions!B144,(IF(A27>=25,Assumptions!B151,IF(A27>=16,Assumptions!B150,Assumptions!B149))/1000*Assumptions!B146)+IF(A27>=Assumptions!B145,(IF(A27>=25,Assumptions!B151,IF(A27>=16,Assumptions!B150,Assumptions!B149))*Assumptions!B152/1000*Assumptions!B147),0),0),0) -> 43 | AD27: =IF(Y27>=10000,Assumptions!B170,IF(Y27>=5000,Assumptions!B169,IF(Y27>=2000,Assumptions!B168,IF(Y27>=500,Assumptions!B167,0)))) -> 5
A28: 23 | B28: =B27*(1+Assumptions!B33) -> 3376.0916 | C28: =ROUND(AB28*Assumptions!B25,0) -> 73 | D28: =ROUND(AB28*Assumptions!B22,0) -> 5 | E28: =E27+D28-F28 -> 36 | F28: =ROUND(E27*Assumptions!B43,0) -> 3 | G28: =D28-F28 -> 2 | H28: =ROUND(E28*(Assumptions!B15*0.85+Assumptions!B11*0.15),0) -> 413 | I28: =H28 -> 413 | J28: =ROUND(E28*Assumptions!B68,0) -> 126 | K28: =ROUND(J28*Assumptions!B65,0) -> 10 | L28: =Assumptions!B70+IF(E28>Assumptions!B72,45,0) -> 31 | M28: =Assumptions!B76+Assumptions!B77 -> 35 | N28: =Assumptions!B81+Assumptions!B82+Assumptions!B87/12+Assumptions!B148 -> 116 | O28: =ROUND(I28*Assumptions!B85+E28*Assumptions!B86+W28*Assumptions!B85+ROUND(AB28*Assumptions!B137*Assumptions!B138*Assumptions!B139,0)*Assumptions!B86,0) -> 30 | P28: =K28+L28+M28+N28+O28+X28 -> 245 | Q28: =I28-P28 -> 168 | R28: =ROUND(AB28*Assumptions!B51*Assumptions!B52,0) -> 1270 | S28: =I28+R28+W28+AC28+AD28 -> 1872 | T28: =IF(U28<P28*3,0,IF(U28<P28*6,ROUND((Q28+R28+W28+AC28+AD28)*0.75*Assumptions!B113,0),ROUND((Q28+R28+W28+AC28+AD28)*0.75*Assumptions!B114,0))) -> 466 | U28: =U27+Q28+R28+W28+AC28+AD28 -> 11415 | V28: =IF(AB28>=Assumptions!B107,"Signal 6",IF(AB28>=Assumptions!B106,"Signal 5",IF(AB28>=Assumptions!B105,"Signal 4",IF(AB28>=Assumptions!B104,"Signal 3",IF(AB28>=Assumptions!B103,"Signal 2",IF(AB28>=Assumptions!B102,"Signal 1","Pre-Signal 1")))))) -> Pre-Signal 1 | W28: =ROUND(AB28*Assumptions!B137*Assumptions!B138*Assumptions!B139*Assumptions!B136,0) -> 141 | X28: =ROUND(AB28*Assumptions!B137*Assumptions!B65,0) -> 23 | Y28: =ROUND(Y27*(1+Assumptions!B165),0) -> 822 | Z28: =Assumptions!B157 -> 250 | AA28: =ROUND(Y28*Assumptions!B166,0) -> 2 | AB28: =B28+Z28+AA28 -> 3628.0916 | AC28: =ROUND(IF(A28>=Assumptions!B144,(IF(A28>=25,Assumptions!B151,IF(A28>=16,Assumptions!B150,Assumptions!B149))/1000*Assumptions!B146)+IF(A28>=Assumptions!B145,(IF(A28>=25,Assumptions!B151,IF(A28>=16,Assumptions!B150,Assumptions!B149))*Assumptions!B152/1000*Assumptions!B147),0),0),0) -> 43 | AD28: =IF(Y28>=10000,Assumptions!B170,IF(Y28>=5000,Assumptions!B169,IF(Y28>=2000,Assumptions!B168,IF(Y28>=500,Assumptions!B167,0)))) -> 5
A29: 24 | B29: =B28*(1+Assumptions!B33) -> 3646.1789 | C29: =ROUND(AB29*Assumptions!B25,0) -> 78 | D29: =ROUND(AB29*Assumptions!B22,0) -> 6 | E29: =E28+D29-F29 -> 39 | F29: =ROUND(E28*Assumptions!B43,0) -> 3 | G29: =D29-F29 -> 3 | H29: =ROUND(E29*(Assumptions!B15*0.85+Assumptions!B11*0.15),0) -> 448 | I29: =H29 -> 448 | J29: =ROUND(E29*Assumptions!B68,0) -> 137 | K29: =ROUND(J29*Assumptions!B65,0) -> 11 | L29: =Assumptions!B70+IF(E29>Assumptions!B72,45,0) -> 31 | M29: =Assumptions!B76+Assumptions!B77 -> 35 | N29: =Assumptions!B81+Assumptions!B82+Assumptions!B87/12+Assumptions!B148 -> 116 | O29: =ROUND(I29*Assumptions!B85+E29*Assumptions!B86+W29*Assumptions!B85+ROUND(AB29*Assumptions!B137*Assumptions!B138*Assumptions!B139,0)*Assumptions!B86,0) -> 33 | P29: =K29+L29+M29+N29+O29+X29 -> 251 | Q29: =I29-P29 -> 197 | R29: =ROUND(AB29*Assumptions!B51*Assumptions!B52,0) -> 1365 | S29: =I29+R29+W29+AC29+AD29 -> 2013 | T29: =IF(U29<P29*3,0,IF(U29<P29*6,ROUND((Q29+R29+W29+AC29+AD29)*0.75*Assumptions!B113,0),ROUND((Q29+R29+W29+AC29+AD29)*0.75*Assumptions!B114,0))) -> 505 | U29: =U28+Q29+R29+W29+AC29+AD29 -> 13177 | V29: =IF(AB29>=Assumptions!B107,"Signal 6",IF(AB29>=Assumptions!B106,"Signal 5",IF(AB29>=Assumptions!B105,"Signal 4",IF(AB29>=Assumptions!B104,"Signal 3",IF(AB29>=Assumptions!B103,"Signal 2",IF(AB29>=Assumptions!B102,"Signal 1","Pre-Signal 1")))))) -> Pre-Signal 1 | W29: =ROUND(AB29*Assumptions!B137*Assumptions!B138*Assumptions!B139*Assumptions!B136,0) -> 152 | X29: =ROUND(AB29*Assumptions!B137*Assumptions!B65,0) -> 25 | Y29: =ROUND(Y28*(1+Assumptions!B165),0) -> 904 | Z29: =Assumptions!B157 -> 250 | AA29: =ROUND(Y29*Assumptions!B166,0) -> 3 | AB29: =B29+Z29+AA29 -> 3899.1789 | AC29: =ROUND(IF(A29>=Assumptions!B144,(IF(A29>=25,Assumptions!B151,IF(A29>=16,Assumptions!B150,Assumptions!B149))/1000*Assumptions!B146)+IF(A29>=Assumptions!B145,(IF(A29>=25,Assumptions!B151,IF(A29>=16,Assumptions!B150,Assumptions!B149))*Assumptions!B152/1000*Assumptions!B147),0),0),0) -> 43 | AD29: =IF(Y29>=10000,Assumptions!B170,IF(Y29>=5000,Assumptions!B169,IF(Y29>=2000,Assumptions!B168,IF(Y29>=500,Assumptions!B167,0)))) -> 5
A30: 25 | B30: =B29*(1+Assumptions!B33) -> 3937.8732 | C30: =ROUND(AB30*Assumptions!B25,0) -> 87 | D30: =ROUND(AB30*Assumptions!B22,0) -> 7 | E30: =E29+D30-F30 -> 43 | F30: =ROUND(E29*Assumptions!B43,0) -> 3 | G30: =D30-F30 -> 4 | H30: =ROUND(E30*(Assumptions!B15*0.85+Assumptions!B11*0.15),0) -> 493 | I30: =H30 -> 493 | J30: =ROUND(E30*Assumptions!B68,0) -> 151 | K30: =ROUND(J30*Assumptions!B65,0) -> 12 | L30: =Assumptions!B70+IF(E30>Assumptions!B72,45,0) -> 31 | M30: =Assumptions!B76+Assumptions!B77 -> 35 | N30: =Assumptions!B81+Assumptions!B82+Assumptions!B87/12+Assumptions!B148 -> 116 | O30: =ROUND(I30*Assumptions!B85+E30*Assumptions!B86+W30*Assumptions!B85+ROUND(AB30*Assumptions!B137*Assumptions!B138*Assumptions!B139,0)*Assumptions!B86,0) -> 36 | P30: =K30+L30+M30+N30+O30+X30 -> 258 | Q30: =I30-P30 -> 235 | R30: =ROUND(AB30*Assumptions!B51*Assumptions!B52,0) -> 1519 | S30: =I30+R30+W30+AC30+AD30 -> 2262 | T30: =IF(U30<P30*3,0,IF(U30<P30*6,ROUND((Q30+R30+W30+AC30+AD30)*0.75*Assumptions!B113,0),ROUND((Q30+R30+W30+AC30+AD30)*0.75*Assumptions!B114,0))) -> 574 | U30: =U29+Q30+R30+W30+AC30+AD30 -> 15181 | V30: =IF(AB30>=Assumptions!B107,"Signal 6",IF(AB30>=Assumptions!B106,"Signal 5",IF(AB30>=Assumptions!B105,"Signal 4",IF(AB30>=Assumptions!B104,"Signal 3",IF(AB30>=Assumptions!B103,"Signal 2",IF(AB30>=Assumptions!B102,"Signal 1","Pre-Signal 1")))))) -> Pre-Signal 1 | W30: =ROUND(AB30*Assumptions!B137*Assumptions!B138*Assumptions!B139*Assumptions!B136,0) -> 169 | X30: =ROUND(AB30*Assumptions!B137*Assumptions!B65,0) -> 28 | Y30: =ROUND(Y29*(1+Assumptions!B165),0) -> 994 | Z30: =Assumptions!B158 -> 400 | AA30: =ROUND(Y30*Assumptions!B166,0) -> 3 | AB30: =B30+Z30+AA30 -> 4340.8732 | AC30: =ROUND(IF(A30>=Assumptions!B144,(IF(A30>=25,Assumptions!B151,IF(A30>=16,Assumptions!B150,Assumptions!B149))/1000*Assumptions!B146)+IF(A30>=Assumptions!B145,(IF(A30>=25,Assumptions!B151,IF(A30>=16,Assumptions!B150,Assumptions!B149))*Assumptions!B152/1000*Assumptions!B147),0),0),0) -> 76 | AD30: =IF(Y30>=10000,Assumptions!B170,IF(Y30>=5000,Assumptions!B169,IF(Y30>=2000,Assumptions!B168,IF(Y30>=500,Assumptions!B167,0)))) -> 5
A31: 26 | B31: =B30*(1+Assumptions!B33) -> 4252.9031 | C31: =ROUND(AB31*Assumptions!B25,0) -> 93 | D31: =ROUND(AB31*Assumptions!B22,0) -> 7 | E31: =E30+D31-F31 -> 47 | F31: =ROUND(E30*Assumptions!B43,0) -> 3 | G31: =D31-F31 -> 4 | H31: =ROUND(E31*(Assumptions!B15*0.85+Assumptions!B11*0.15),0) -> 539 | I31: =H31 -> 539 | J31: =ROUND(E31*Assumptions!B68,0) -> 165 | K31: =ROUND(J31*Assumptions!B65,0) -> 13 | L31: =Assumptions!B70+IF(E31>Assumptions!B72,45,0) -> 31 | M31: =Assumptions!B76+Assumptions!B77 -> 35 | N31: =Assumptions!B81+Assumptions!B82+Assumptions!B87/12+Assumptions!B148 -> 116 | O31: =ROUND(I31*Assumptions!B85+E31*Assumptions!B86+W31*Assumptions!B85+ROUND(AB31*Assumptions!B137*Assumptions!B138*Assumptions!B139,0)*Assumptions!B86,0) -> 39 | P31: =K31+L31+M31+N31+O31+X31 -> 264 | Q31: =I31-P31 -> 275 | R31: =ROUND(AB31*Assumptions!B51*Assumptions!B52,0) -> 1630 | S31: =I31+R31+W31+AC31+AD31 -> 2432 | T31: =IF(U31<P31*3,0,IF(U31<P31*6,ROUND((Q31+R31+W31+AC31+AD31)*0.75*Assumptions!B113,0),ROUND((Q31+R31+W31+AC31+AD31)*0.75*Assumptions!B114,0))) -> 621 | U31: =U30+Q31+R31+W31+AC31+AD31 -> 17349 | V31: =IF(AB31>=Assumptions!B107,"Signal 6",IF(AB31>=Assumptions!B106,"Signal 5",IF(AB31>=Assumptions!B105,"Signal 4",IF(AB31>=Assumptions!B104,"Signal 3",IF(AB31>=Assumptions!B103,"Signal 2",IF(AB31>=Assumptions!B102,"Signal 1","Pre-Signal 1")))))) -> Pre-Signal 1 | W31: =ROUND(AB31*Assumptions!B137*Assumptions!B138*Assumptions!B139*Assumptions!B136,0) -> 182 | X31: =ROUND(AB31*Assumptions!B137*Assumptions!B65,0) -> 30 | Y31: =ROUND(Y30*(1+Assumptions!B165),0) -> 1093 | Z31: =Assumptions!B158 -> 400 | AA31: =ROUND(Y31*Assumptions!B166,0) -> 3 | AB31: =B31+Z31+AA31 -> 4655.9031 | AC31: =ROUND(IF(A31>=Assumptions!B144,(IF(A31>=25,Assumptions!B151,IF(A31>=16,Assumptions!B150,Assumptions!B149))/1000*Assumptions!B146)+IF(A31>=Assumptions!B145,(IF(A31>=25,Assumptions!B151,IF(A31>=16,Assumptions!B150,Assumptions!B149))*Assumptions!B152/1000*Assumptions!B147),0),0),0) -> 76 | AD31: =IF(Y31>=10000,Assumptions!B170,IF(Y31>=5000,Assumptions!B169,IF(Y31>=2000,Assumptions!B168,IF(Y31>=500,Assumptions!B167,0)))) -> 5
A32: 27 | B32: =B31*(1+Assumptions!B33) -> 4593.1353 | C32: =ROUND(AB32*Assumptions!B25,0) -> 100 | D32: =ROUND(AB32*Assumptions!B22,0) -> 7 | E32: =E31+D32-F32 -> 50 | F32: =ROUND(E31*Assumptions!B43,0) -> 4 | G32: =D32-F32 -> 3 | H32: =ROUND(E32*(Assumptions!B15*0.85+Assumptions!B11*0.15),0) -> 574 | I32: =H32 -> 574 | J32: =ROUND(E32*Assumptions!B68,0) -> 175 | K32: =ROUND(J32*Assumptions!B65,0) -> 14 | L32: =Assumptions!B70+IF(E32>Assumptions!B72,45,0) -> 31 | M32: =Assumptions!B76+Assumptions!B77 -> 35 | N32: =Assumptions!B81+Assumptions!B82+Assumptions!B87/12+Assumptions!B148 -> 116 | O32: =ROUND(I32*Assumptions!B85+E32*Assumptions!B86+W32*Assumptions!B85+ROUND(AB32*Assumptions!B137*Assumptions!B138*Assumptions!B139,0)*Assumptions!B86,0) -> 42 | P32: =K32+L32+M32+N32+O32+X32 -> 270 | Q32: =I32-P32 -> 304 | R32: =ROUND(AB32*Assumptions!B51*Assumptions!B52,0) -> 1749 | S32: =I32+R32+W32+AC32+AD32 -> 2599 | T32: =IF(U32<P32*3,0,IF(U32<P32*6,ROUND((Q32+R32+W32+AC32+AD32)*0.75*Assumptions!B113,0),ROUND((Q32+R32+W32+AC32+AD32)*0.75*Assumptions!B114,0))) -> 667 | U32: =U31+Q32+R32+W32+AC32+AD32 -> 19678 | V32: =IF(AB32>=Assumptions!B107,"Signal 6",IF(AB32>=Assumptions!B106,"Signal 5",IF(AB32>=Assumptions!B105,"Signal 4",IF(AB32>=Assumptions!B104,"Signal 3",IF(AB32>=Assumptions!B103,"Signal 2",IF(AB32>=Assumptions!B102,"Signal 1","Pre-Signal 1")))))) -> Pre-Signal 1 | W32: =ROUND(AB32*Assumptions!B137*Assumptions!B138*Assumptions!B139*Assumptions!B136,0) -> 195 | X32: =ROUND(AB32*Assumptions!B137*Assumptions!B65,0) -> 32 | Y32: =ROUND(Y31*(1+Assumptions!B165),0) -> 1202 | Z32: =Assumptions!B158 -> 400 | AA32: =ROUND(Y32*Assumptions!B166,0) -> 4 | AB32: =B32+Z32+AA32 -> 4997.1353 | AC32: =ROUND(IF(A32>=Assumptions!B144,(IF(A32>=25,Assumptions!B151,IF(A32>=16,Assumptions!B150,Assumptions!B149))/1000*Assumptions!B146)+IF(A32>=Assumptions!B145,(IF(A32>=25,Assumptions!B151,IF(A32>=16,Assumptions!B150,Assumptions!B149))*Assumptions!B152/1000*Assumptions!B147),0),0),0) -> 76 | AD32: =IF(Y32>=10000,Assumptions!B170,IF(Y32>=5000,Assumptions!B169,IF(Y32>=2000,Assumptions!B168,IF(Y32>=500,Assumptions!B167,0)))) -> 5
A33: 28 | B33: =B32*(1+Assumptions!B33) -> 4960.5862 | C33: =ROUND(AB33*Assumptions!B25,0) -> 107 | D33: =ROUND(AB33*Assumptions!B22,0) -> 8 | E33: =E32+D33-F33 -> 54 | F33: =ROUND(E32*Assumptions!B43,0) -> 4 | G33: =D33-F33 -> 4 | H33: =ROUND(E33*(Assumptions!B15*0.85+Assumptions!B11*0.15),0) -> 620 | I33: =H33 -> 620 | J33: =ROUND(E33*Assumptions!B68,0) -> 189 | K33: =ROUND(J33*Assumptions!B65,0) -> 15 | L33: =Assumptions!B70+IF(E33>Assumptions!B72,45,0) -> 31 | M33: =Assumptions!B76+Assumptions!B77 -> 35 | N33: =Assumptions!B81+Assumptions!B82+Assumptions!B87/12+Assumptions!B148 -> 116 | O33: =ROUND(I33*Assumptions!B85+E33*Assumptions!B86+W33*Assumptions!B85+ROUND(AB33*Assumptions!B137*Assumptions!B138*Assumptions!B139,0)*Assumptions!B86,0) -> 45 | P33: =K33+L33+M33+N33+O33+X33 -> 276 | Q33: =I33-P33 -> 344 | R33: =ROUND(AB33*Assumptions!B51*Assumptions!B52,0) -> 1878 | S33: =I33+R33+W33+AC33+AD33 -> 2788 | T33: =IF(U33<P33*3,0,IF(U33<P33*6,ROUND((Q33+R33+W33+AC33+AD33)*0.75*Assumptions!B113,0),ROUND((Q33+R33+W33+AC33+AD33)*0.75*Assumptions!B114,0))) -> 720 | U33: =U32+Q33+R33+W33+AC33+AD33 -> 22190 | V33: =IF(AB33>=Assumptions!B107,"Signal 6",IF(AB33>=Assumptions!B106,"Signal 5",IF(AB33>=Assumptions!B105,"Signal 4",IF(AB33>=Assumptions!B104,"Signal 3",IF(AB33>=Assumptions!B103,"Signal 2",IF(AB33>=Assumptions!B102,"Signal 1","Pre-Signal 1")))))) -> Pre-Signal 1 | W33: =ROUND(AB33*Assumptions!B137*Assumptions!B138*Assumptions!B139*Assumptions!B136,0) -> 209 | X33: =ROUND(AB33*Assumptions!B137*Assumptions!B65,0) -> 34 | Y33: =ROUND(Y32*(1+Assumptions!B165),0) -> 1322 | Z33: =Assumptions!B158 -> 400 | AA33: =ROUND(Y33*Assumptions!B166,0) -> 4 | AB33: =B33+Z33+AA33 -> 5364.5862 | AC33: =ROUND(IF(A33>=Assumptions!B144,(IF(A33>=25,Assumptions!B151,IF(A33>=16,Assumptions!B150,Assumptions!B149))/1000*Assumptions!B146)+IF(A33>=Assumptions!B145,(IF(A33>=25,Assumptions!B151,IF(A33>=16,Assumptions!B150,Assumptions!B149))*Assumptions!B152/1000*Assumptions!B147),0),0),0) -> 76 | AD33: =IF(Y33>=10000,Assumptions!B170,IF(Y33>=5000,Assumptions!B169,IF(Y33>=2000,Assumptions!B168,IF(Y33>=500,Assumptions!B167,0)))) -> 5
A34: 29 | B34: =B33*(1+Assumptions!B33) -> 5357.4331 | C34: =ROUND(AB34*Assumptions!B25,0) -> 115 | D34: =ROUND(AB34*Assumptions!B22,0) -> 9 | E34: =E33+D34-F34 -> 59 | F34: =ROUND(E33*Assumptions!B43,0) -> 4 | G34: =D34-F34 -> 5 | H34: =ROUND(E34*(Assumptions!B15*0.85+Assumptions!B11*0.15),0) -> 677 | I34: =H34 -> 677 | J34: =ROUND(E34*Assumptions!B68,0) -> 207 | K34: =ROUND(J34*Assumptions!B65,0) -> 17 | L34: =Assumptions!B70+IF(E34>Assumptions!B72,45,0) -> 31 | M34: =Assumptions!B76+Assumptions!B77 -> 35 | N34: =Assumptions!B81+Assumptions!B82+Assumptions!B87/12+Assumptions!B148 -> 116 | O34: =ROUND(I34*Assumptions!B85+E34*Assumptions!B86+W34*Assumptions!B85+ROUND(AB34*Assumptions!B137*Assumptions!B138*Assumptions!B139,0)*Assumptions!B86,0) -> 49 | P34: =K34+L34+M34+N34+O34+X34 -> 285 | Q34: =I34-P34 -> 392 | R34: =ROUND(AB34*Assumptions!B51*Assumptions!B52,0) -> 2017 | S34: =I34+R34+W34+AC34+AD34 -> 3000 | T34: =IF(U34<P34*3,0,IF(U34<P34*6,ROUND((Q34+R34+W34+AC34+AD34)*0.75*Assumptions!B113,0),ROUND((Q34+R34+W34+AC34+AD34)*0.75*Assumptions!B114,0))) -> 778 | U34: =U33+Q34+R34+W34+AC34+AD34 -> 24905 | V34: =IF(AB34>=Assumptions!B107,"Signal 6",IF(AB34>=Assumptions!B106,"Signal 5",IF(AB34>=Assumptions!B105,"Signal 4",IF(AB34>=Assumptions!B104,"Signal 3",IF(AB34>=Assumptions!B103,"Signal 2",IF(AB34>=Assumptions!B102,"Signal 1","Pre-Signal 1")))))) -> Pre-Signal 1 | W34: =ROUND(AB34*Assumptions!B137*Assumptions!B138*Assumptions!B139*Assumptions!B136,0) -> 225 | X34: =ROUND(AB34*Assumptions!B137*Assumptions!B65,0) -> 37 | Y34: =ROUND(Y33*(1+Assumptions!B165),0) -> 1454 | Z34: =Assumptions!B158 -> 400 | AA34: =ROUND(Y34*Assumptions!B166,0) -> 4 | AB34: =B34+Z34+AA34 -> 5761.4331 | AC34: =ROUND(IF(A34>=Assumptions!B144,(IF(A34>=25,Assumptions!B151,IF(A34>=16,Assumptions!B150,Assumptions!B149))/1000*Assumptions!B146)+IF(A34>=Assumptions!B145,(IF(A34>=25,Assumptions!B151,IF(A34>=16,Assumptions!B150,Assumptions!B149))*Assumptions!B152/1000*Assumptions!B147),0),0),0) -> 76 | AD34: =IF(Y34>=10000,Assumptions!B170,IF(Y34>=5000,Assumptions!B169,IF(Y34>=2000,Assumptions!B168,IF(Y34>=500,Assumptions!B167,0)))) -> 5
A35: 30 | B35: =B34*(1+Assumptions!B33) -> 5786.0277 | C35: =ROUND(AB35*Assumptions!B25,0) -> 124 | D35: =ROUND(AB35*Assumptions!B22,0) -> 9 | E35: =E34+D35-F35 -> 63 | F35: =ROUND(E34*Assumptions!B43,0) -> 5 | G35: =D35-F35 -> 4 | H35: =ROUND(E35*(Assumptions!B15*0.85+Assumptions!B11*0.15),0) -> 723 | I35: =H35 -> 723 | J35: =ROUND(E35*Assumptions!B68,0) -> 221 | K35: =ROUND(J35*Assumptions!B65,0) -> 18 | L35: =Assumptions!B70+IF(E35>Assumptions!B72,45,0) -> 31 | M35: =Assumptions!B76+Assumptions!B77 -> 35 | N35: =Assumptions!B81+Assumptions!B82+Assumptions!B87/12+Assumptions!B148 -> 116 | O35: =ROUND(I35*Assumptions!B85+E35*Assumptions!B86+W35*Assumptions!B85+ROUND(AB35*Assumptions!B137*Assumptions!B138*Assumptions!B139,0)*Assumptions!B86,0) -> 53 | P35: =K35+L35+M35+N35+O35+X35 -> 293 | Q35: =I35-P35 -> 430 | R35: =ROUND(AB35*Assumptions!B51*Assumptions!B52,0) -> 2167 | S35: =I35+R35+W35+AC35+AD35 -> 3212 | T35: =IF(U35<P35*3,0,IF(U35<P35*6,ROUND((Q35+R35+W35+AC35+AD35)*0.75*Assumptions!B113,0),ROUND((Q35+R35+W35+AC35+AD35)*0.75*Assumptions!B114,0))) -> 836 | U35: =U34+Q35+R35+W35+AC35+AD35 -> 27824 | V35: =IF(AB35>=Assumptions!B107,"Signal 6",IF(AB35>=Assumptions!B106,"Signal 5",IF(AB35>=Assumptions!B105,"Signal 4",IF(AB35>=Assumptions!B104,"Signal 3",IF(AB35>=Assumptions!B103,"Signal 2",IF(AB35>=Assumptions!B102,"Signal 1","Pre-Signal 1")))))) -> Pre-Signal 1 | W35: =ROUND(AB35*Assumptions!B137*Assumptions!B138*Assumptions!B139*Assumptions!B136,0) -> 241 | X35: =ROUND(AB35*Assumptions!B137*Assumptions!B65,0) -> 40 | Y35: =ROUND(Y34*(1+Assumptions!B165),0) -> 1599 | Z35: =Assumptions!B158 -> 400 | AA35: =ROUND(Y35*Assumptions!B166,0) -> 5 | AB35: =B35+Z35+AA35 -> 6191.0277 | AC35: =ROUND(IF(A35>=Assumptions!B144,(IF(A35>=25,Assumptions!B151,IF(A35>=16,Assumptions!B150,Assumptions!B149))/1000*Assumptions!B146)+IF(A35>=Assumptions!B145,(IF(A35>=25,Assumptions!B151,IF(A35>=16,Assumptions!B150,Assumptions!B149))*Assumptions!B152/1000*Assumptions!B147),0),0),0) -> 76 | AD35: =IF(Y35>=10000,Assumptions!B170,IF(Y35>=5000,Assumptions!B169,IF(Y35>=2000,Assumptions!B168,IF(Y35>=500,Assumptions!B167,0)))) -> 5
A36: 31 | B36: =B35*(1+Assumptions!B33) -> 6248.9099 | C36: =ROUND(AB36*Assumptions!B25,0) -> 133 | D36: =ROUND(AB36*Assumptions!B22,0) -> 10 | E36: =E35+D36-F36 -> 68 | F36: =ROUND(E35*Assumptions!B43,0) -> 5 | G36: =D36-F36 -> 5 | H36: =ROUND(E36*(Assumptions!B15*0.85+Assumptions!B11*0.15),0) -> 780 | I36: =H36 -> 780 | J36: =ROUND(E36*Assumptions!B68,0) -> 238 | K36: =ROUND(J36*Assumptions!B65,0) -> 19 | L36: =Assumptions!B70+IF(E36>Assumptions!B72,45,0) -> 31 | M36: =Assumptions!B76+Assumptions!B77 -> 35 | N36: =Assumptions!B81+Assumptions!B82+Assumptions!B87/12+Assumptions!B148 -> 116 | O36: =ROUND(I36*Assumptions!B85+E36*Assumptions!B86+W36*Assumptions!B85+ROUND(AB36*Assumptions!B137*Assumptions!B138*Assumptions!B139,0)*Assumptions!B86,0) -> 57 | P36: =K36+L36+M36+N36+O36+X36 -> 301 | Q36: =I36-P36 -> 479 | R36: =ROUND(AB36*Assumptions!B51*Assumptions!B52,0) -> 2329 | S36: =I36+R36+W36+AC36+AD36 -> 3450 | T36: =IF(U36<P36*3,0,IF(U36<P36*6,ROUND((Q36+R36+W36+AC36+AD36)*0.75*Assumptions!B113,0),ROUND((Q36+R36+W36+AC36+AD36)*0.75*Assumptions!B114,0))) -> 902 | U36: =U35+Q36+R36+W36+AC36+AD36 -> 30973 | V36: =IF(AB36>=Assumptions!B107,"Signal 6",IF(AB36>=Assumptions!B106,"Signal 5",IF(AB36>=Assumptions!B105,"Signal 4",IF(AB36>=Assumptions!B104,"Signal 3",IF(AB36>=Assumptions!B103,"Signal 2",IF(AB36>=Assumptions!B102,"Signal 1","Pre-Signal 1")))))) -> Pre-Signal 1 | W36: =ROUND(AB36*Assumptions!B137*Assumptions!B138*Assumptions!B139*Assumptions!B136,0) -> 260 | X36: =ROUND(AB36*Assumptions!B137*Assumptions!B65,0) -> 43 | Y36: =ROUND(Y35*(1+Assumptions!B165),0) -> 1759 | Z36: =Assumptions!B158 -> 400 | AA36: =ROUND(Y36*Assumptions!B166,0) -> 5 | AB36: =B36+Z36+AA36 -> 6653.9099 | AC36: =ROUND(IF(A36>=Assumptions!B144,(IF(A36>=25,Assumptions!B151,IF(A36>=16,Assumptions!B150,Assumptions!B149))/1000*Assumptions!B146)+IF(A36>=Assumptions!B145,(IF(A36>=25,Assumptions!B151,IF(A36>=16,Assumptions!B150,Assumptions!B149))*Assumptions!B152/1000*Assumptions!B147),0),0),0) -> 76 | AD36: =IF(Y36>=10000,Assumptions!B170,IF(Y36>=5000,Assumptions!B169,IF(Y36>=2000,Assumptions!B168,IF(Y36>=500,Assumptions!B167,0)))) -> 5
A37: 32 | B37: =B36*(1+Assumptions!B33) -> 6748.8227 | C37: =ROUND(AB37*Assumptions!B25,0) -> 143 | D37: =ROUND(AB37*Assumptions!B22,0) -> 11 | E37: =E36+D37-F37 -> 74 | F37: =ROUND(E36*Assumptions!B43,0) -> 5 | G37: =D37-F37 -> 6 | H37: =ROUND(E37*(Assumptions!B15*0.85+Assumptions!B11*0.15),0) -> 849 | I37: =H37 -> 849 | J37: =ROUND(E37*Assumptions!B68,0) -> 259 | K37: =ROUND(J37*Assumptions!B65,0) -> 21 | L37: =Assumptions!B70+IF(E37>Assumptions!B72,45,0) -> 31 | M37: =Assumptions!B76+Assumptions!B77 -> 35 | N37: =Assumptions!B81+Assumptions!B82+Assumptions!B87/12+Assumptions!B148 -> 116 | O37: =ROUND(I37*Assumptions!B85+E37*Assumptions!B86+W37*Assumptions!B85+ROUND(AB37*Assumptions!B137*Assumptions!B138*Assumptions!B139,0)*Assumptions!B86,0) -> 61 | P37: =K37+L37+M37+N37+O37+X37 -> 310 | Q37: =I37-P37 -> 539 | R37: =ROUND(AB37*Assumptions!B51*Assumptions!B52,0) -> 2504 | S37: =I37+R37+W37+AC37+AD37 -> 3713 | T37: =IF(U37<P37*3,0,IF(U37<P37*6,ROUND((Q37+R37+W37+AC37+AD37)*0.75*Assumptions!B113,0),ROUND((Q37+R37+W37+AC37+AD37)*0.75*Assumptions!B114,0))) -> 975 | U37: =U36+Q37+R37+W37+AC37+AD37 -> 34376 | V37: =IF(AB37>=Assumptions!B107,"Signal 6",IF(AB37>=Assumptions!B106,"Signal 5",IF(AB37>=Assumptions!B105,"Signal 4",IF(AB37>=Assumptions!B104,"Signal 3",IF(AB37>=Assumptions!B103,"Signal 2",IF(AB37>=Assumptions!B102,"Signal 1","Pre-Signal 1")))))) -> Pre-Signal 1 | W37: =ROUND(AB37*Assumptions!B137*Assumptions!B138*Assumptions!B139*Assumptions!B136,0) -> 279 | X37: =ROUND(AB37*Assumptions!B137*Assumptions!B65,0) -> 46 | Y37: =ROUND(Y36*(1+Assumptions!B165),0) -> 1935 | Z37: =Assumptions!B158 -> 400 | AA37: =ROUND(Y37*Assumptions!B166,0) -> 6 | AB37: =B37+Z37+AA37 -> 7154.8227 | AC37: =ROUND(IF(A37>=Assumptions!B144,(IF(A37>=25,Assumptions!B151,IF(A37>=16,Assumptions!B150,Assumptions!B149))/1000*Assumptions!B146)+IF(A37>=Assumptions!B145,(IF(A37>=25,Assumptions!B151,IF(A37>=16,Assumptions!B150,Assumptions!B149))*Assumptions!B152/1000*Assumptions!B147),0),0),0) -> 76 | AD37: =IF(Y37>=10000,Assumptions!B170,IF(Y37>=5000,Assumptions!B169,IF(Y37>=2000,Assumptions!B168,IF(Y37>=500,Assumptions!B167,0)))) -> 5
A38: 33 | B38: =B37*(1+Assumptions!B33) -> 7288.7285 | C38: =ROUND(AB38*Assumptions!B25,0) -> 154 | D38: =ROUND(AB38*Assumptions!B22,0) -> 12 | E38: =E37+D38-F38 -> 80 | F38: =ROUND(E37*Assumptions!B43,0) -> 6 | G38: =D38-F38 -> 6 | H38: =ROUND(E38*(Assumptions!B15*0.85+Assumptions!B11*0.15),0) -> 918 | I38: =H38 -> 918 | J38: =ROUND(E38*Assumptions!B68,0) -> 280 | K38: =ROUND(J38*Assumptions!B65,0) -> 22 | L38: =Assumptions!B70+IF(E38>Assumptions!B72,45,0) -> 31 | M38: =Assumptions!B76+Assumptions!B77 -> 35 | N38: =Assumptions!B81+Assumptions!B82+Assumptions!B87/12+Assumptions!B148 -> 116 | O38: =ROUND(I38*Assumptions!B85+E38*Assumptions!B86+W38*Assumptions!B85+ROUND(AB38*Assumptions!B137*Assumptions!B138*Assumptions!B139,0)*Assumptions!B86,0) -> 66 | P38: =K38+L38+M38+N38+O38+X38 -> 319 | Q38: =I38-P38 -> 599 | R38: =ROUND(AB38*Assumptions!B51*Assumptions!B52,0) -> 2693 | S38: =I38+R38+W38+AC38+AD38 -> 4007 | T38: =IF(U38<P38*3,0,IF(U38<P38*6,ROUND((Q38+R38+W38+AC38+AD38)*0.75*Assumptions!B113,0),ROUND((Q38+R38+W38+AC38+AD38)*0.75*Assumptions!B114,0))) -> 1057 | U38: =U37+Q38+R38+W38+AC38+AD38 -> 38064 | V38: =IF(AB38>=Assumptions!B107,"Signal 6",IF(AB38>=Assumptions!B106,"Signal 5",IF(AB38>=Assumptions!B105,"Signal 4",IF(AB38>=Assumptions!B104,"Signal 3",IF(AB38>=Assumptions!B103,"Signal 2",IF(AB38>=Assumptions!B102,"Signal 1","Pre-Signal 1")))))) -> Pre-Signal 1 | W38: =ROUND(AB38*Assumptions!B137*Assumptions!B138*Assumptions!B139*Assumptions!B136,0) -> 300 | X38: =ROUND(AB38*Assumptions!B137*Assumptions!B65,0) -> 49 | Y38: =ROUND(Y37*(1+Assumptions!B165),0) -> 2129 | Z38: =Assumptions!B158 -> 400 | AA38: =ROUND(Y38*Assumptions!B166,0) -> 6 | AB38: =B38+Z38+AA38 -> 7694.7285 | AC38: =ROUND(IF(A38>=Assumptions!B144,(IF(A38>=25,Assumptions!B151,IF(A38>=16,Assumptions!B150,Assumptions!B149))/1000*Assumptions!B146)+IF(A38>=Assumptions!B145,(IF(A38>=25,Assumptions!B151,IF(A38>=16,Assumptions!B150,Assumptions!B149))*Assumptions!B152/1000*Assumptions!B147),0),0),0) -> 76 | AD38: =IF(Y38>=10000,Assumptions!B170,IF(Y38>=5000,Assumptions!B169,IF(Y38>=2000,Assumptions!B168,IF(Y38>=500,Assumptions!B167,0)))) -> 20
A39: 34 | B39: =B38*(1+Assumptions!B33) -> 7871.8268 | C39: =ROUND(AB39*Assumptions!B25,0) -> 166 | D39: =ROUND(AB39*Assumptions!B22,0) -> 12 | E39: =E38+D39-F39 -> 86 | F39: =ROUND(E38*Assumptions!B43,0) -> 6 | G39: =D39-F39 -> 6 | H39: =ROUND(E39*(Assumptions!B15*0.85+Assumptions!B11*0.15),0) -> 987 | I39: =H39 -> 987 | J39: =ROUND(E39*Assumptions!B68,0) -> 301 | K39: =ROUND(J39*Assumptions!B65,0) -> 24 | L39: =Assumptions!B70+IF(E39>Assumptions!B72,45,0) -> 31 | M39: =Assumptions!B76+Assumptions!B77 -> 35 | N39: =Assumptions!B81+Assumptions!B82+Assumptions!B87/12+Assumptions!B148 -> 116 | O39: =ROUND(I39*Assumptions!B85+E39*Assumptions!B86+W39*Assumptions!B85+ROUND(AB39*Assumptions!B137*Assumptions!B138*Assumptions!B139,0)*Assumptions!B86,0) -> 71 | P39: =K39+L39+M39+N39+O39+X39 -> 330 | Q39: =I39-P39 -> 657 | R39: =ROUND(AB39*Assumptions!B51*Assumptions!B52,0) -> 2898 | S39: =I39+R39+W39+AC39+AD39 -> 4304 | T39: =IF(U39<P39*3,0,IF(U39<P39*6,ROUND((Q39+R39+W39+AC39+AD39)*0.75*Assumptions!B113,0),ROUND((Q39+R39+W39+AC39+AD39)*0.75*Assumptions!B114,0))) -> 1139 | U39: =U38+Q39+R39+W39+AC39+AD39 -> 42038 | V39: =IF(AB39>=Assumptions!B107,"Signal 6",IF(AB39>=Assumptions!B106,"Signal 5",IF(AB39>=Assumptions!B105,"Signal 4",IF(AB39>=Assumptions!B104,"Signal 3",IF(AB39>=Assumptions!B103,"Signal 2",IF(AB39>=Assumptions!B102,"Signal 1","Pre-Signal 1")))))) -> Pre-Signal 1 | W39: =ROUND(AB39*Assumptions!B137*Assumptions!B138*Assumptions!B139*Assumptions!B136,0) -> 323 | X39: =ROUND(AB39*Assumptions!B137*Assumptions!B65,0) -> 53 | Y39: =ROUND(Y38*(1+Assumptions!B165),0) -> 2342 | Z39: =Assumptions!B158 -> 400 | AA39: =ROUND(Y39*Assumptions!B166,0) -> 7 | AB39: =B39+Z39+AA39 -> 8278.8268 | AC39: =ROUND(IF(A39>=Assumptions!B144,(IF(A39>=25,Assumptions!B151,IF(A39>=16,Assumptions!B150,Assumptions!B149))/1000*Assumptions!B146)+IF(A39>=Assumptions!B145,(IF(A39>=25,Assumptions!B151,IF(A39>=16,Assumptions!B150,Assumptions!B149))*Assumptions!B152/1000*Assumptions!B147),0),0),0) -> 76 | AD39: =IF(Y39>=10000,Assumptions!B170,IF(Y39>=5000,Assumptions!B169,IF(Y39>=2000,Assumptions!B168,IF(Y39>=500,Assumptions!B167,0)))) -> 20
A40: 35 | B40: =B39*(1+Assumptions!B33) -> 8501.573 | C40: =ROUND(AB40*Assumptions!B25,0) -> 178 | D40: =ROUND(AB40*Assumptions!B22,0) -> 13 | E40: =E39+D40-F40 -> 92 | F40: =ROUND(E39*Assumptions!B43,0) -> 7 | G40: =D40-F40 -> 6 | H40: =ROUND(E40*(Assumptions!B15*0.85+Assumptions!B11*0.15),0) -> 1056 | I40: =H40 -> 1056 | J40: =ROUND(E40*Assumptions!B68,0) -> 322 | K40: =ROUND(J40*Assumptions!B65,0) -> 26 | L40: =Assumptions!B70+IF(E40>Assumptions!B72,45,0) -> 31 | M40: =Assumptions!B76+Assumptions!B77 -> 35 | N40: =Assumptions!B81+Assumptions!B82+Assumptions!B87/12+Assumptions!B148 -> 116 | O40: =ROUND(I40*Assumptions!B85+E40*Assumptions!B86+W40*Assumptions!B85+ROUND(AB40*Assumptions!B137*Assumptions!B138*Assumptions!B139,0)*Assumptions!B86,0) -> 76 | P40: =K40+L40+M40+N40+O40+X40 -> 341 | Q40: =I40-P40 -> 715 | R40: =ROUND(AB40*Assumptions!B51*Assumptions!B52,0) -> 3118 | S40: =I40+R40+W40+AC40+AD40 -> 4617 | T40: =IF(U40<P40*3,0,IF(U40<P40*6,ROUND((Q40+R40+W40+AC40+AD40)*0.75*Assumptions!B113,0),ROUND((Q40+R40+W40+AC40+AD40)*0.75*Assumptions!B114,0))) -> 1225 | U40: =U39+Q40+R40+W40+AC40+AD40 -> 46314 | V40: =IF(AB40>=Assumptions!B107,"Signal 6",IF(AB40>=Assumptions!B106,"Signal 5",IF(AB40>=Assumptions!B105,"Signal 4",IF(AB40>=Assumptions!B104,"Signal 3",IF(AB40>=Assumptions!B103,"Signal 2",IF(AB40>=Assumptions!B102,"Signal 1","Pre-Signal 1")))))) -> Pre-Signal 1 | W40: =ROUND(AB40*Assumptions!B137*Assumptions!B138*Assumptions!B139*Assumptions!B136,0) -> 347 | X40: =ROUND(AB40*Assumptions!B137*Assumptions!B65,0) -> 57 | Y40: =ROUND(Y39*(1+Assumptions!B165),0) -> 2576 | Z40: =Assumptions!B158 -> 400 | AA40: =ROUND(Y40*Assumptions!B166,0) -> 8 | AB40: =B40+Z40+AA40 -> 8909.573 | AC40: =ROUND(IF(A40>=Assumptions!B144,(IF(A40>=25,Assumptions!B151,IF(A40>=16,Assumptions!B150,Assumptions!B149))/1000*Assumptions!B146)+IF(A40>=Assumptions!B145,(IF(A40>=25,Assumptions!B151,IF(A40>=16,Assumptions!B150,Assumptions!B149))*Assumptions!B152/1000*Assumptions!B147),0),0),0) -> 76 | AD40: =IF(Y40>=10000,Assumptions!B170,IF(Y40>=5000,Assumptions!B169,IF(Y40>=2000,Assumptions!B168,IF(Y40>=500,Assumptions!B167,0)))) -> 20
A41: 36 | B41: =B40*(1+Assumptions!B33) -> 9181.6988 | C41: =ROUND(AB41*Assumptions!B25,0) -> 192 | D41: =ROUND(AB41*Assumptions!B22,0) -> 14 | E41: =E40+D41-F41 -> 99 | F41: =ROUND(E40*Assumptions!B43,0) -> 7 | G41: =D41-F41 -> 7 | H41: =ROUND(E41*(Assumptions!B15*0.85+Assumptions!B11*0.15),0) -> 1136 | I41: =H41 -> 1136 | J41: =ROUND(E41*Assumptions!B68,0) -> 347 | K41: =ROUND(J41*Assumptions!B65,0) -> 28 | L41: =Assumptions!B70+IF(E41>Assumptions!B72,45,0) -> 31 | M41: =Assumptions!B76+Assumptions!B77 -> 35 | N41: =Assumptions!B81+Assumptions!B82+Assumptions!B87/12+Assumptions!B148 -> 116 | O41: =ROUND(I41*Assumptions!B85+E41*Assumptions!B86+W41*Assumptions!B85+ROUND(AB41*Assumptions!B137*Assumptions!B138*Assumptions!B139,0)*Assumptions!B86,0) -> 82 | P41: =K41+L41+M41+N41+O41+X41 -> 353 | Q41: =I41-P41 -> 783 | R41: =ROUND(AB41*Assumptions!B51*Assumptions!B52,0) -> 3357 | S41: =I41+R41+W41+AC41+AD41 -> 4963 | T41: =IF(U41<P41*3,0,IF(U41<P41*6,ROUND((Q41+R41+W41+AC41+AD41)*0.75*Assumptions!B113,0),ROUND((Q41+R41+W41+AC41+AD41)*0.75*Assumptions!B114,0))) -> 1321 | U41: =U40+Q41+R41+W41+AC41+AD41 -> 50924 | V41: =IF(AB41>=Assumptions!B107,"Signal 6",IF(AB41>=Assumptions!B106,"Signal 5",IF(AB41>=Assumptions!B105,"Signal 4",IF(AB41>=Assumptions!B104,"Signal 3",IF(AB41>=Assumptions!B103,"Signal 2",IF(AB41>=Assumptions!B102,"Signal 1","Pre-Signal 1")))))) -> Pre-Signal 1 | W41: =ROUND(AB41*Assumptions!B137*Assumptions!B138*Assumptions!B139*Assumptions!B136,0) -> 374 | X41: =ROUND(AB41*Assumptions!B137*Assumptions!B65,0) -> 61 | Y41: =ROUND(Y40*(1+Assumptions!B165),0) -> 2834 | Z41: =Assumptions!B158 -> 400 | AA41: =ROUND(Y41*Assumptions!B166,0) -> 9 | AB41: =B41+Z41+AA41 -> 9590.6988 | AC41: =ROUND(IF(A41>=Assumptions!B144,(IF(A41>=25,Assumptions!B151,IF(A41>=16,Assumptions!B150,Assumptions!B149))/1000*Assumptions!B146)+IF(A41>=Assumptions!B145,(IF(A41>=25,Assumptions!B151,IF(A41>=16,Assumptions!B150,Assumptions!B149))*Assumptions!B152/1000*Assumptions!B147),0),0),0) -> 76 | AD41: =IF(Y41>=10000,Assumptions!B170,IF(Y41>=5000,Assumptions!B169,IF(Y41>=2000,Assumptions!B168,IF(Y41>=500,Assumptions!B167,0)))) -> 20
A43: TOTALS | I43: =SUM(I6:I41) -> 13742 | P43: =SUM(P6:P41) -> 11313 | Q43: =SUM(Q6:Q41) -> 2429 | R43: =SUM(R6:R41) -> 42154 | S43: =SUM(S6:S41) -> 62237 | T43: =SUM(T6:T41) -> 14532 | W43: =SUM(W6:W41) -> 4823 | X43: =SUM(X6:X41) -> 790 | AC43: =SUM(AC6:AC41) -> 1363 | AD43: =SUM(AD6:AD41) -> 155
A44: AVG MO | H44: =AVERAGE(H6:H41) -> 381.72222 | Q44: =AVERAGE(Q6:Q41) -> 67.472222
A45: M36 | B45: =AB41 -> 9590.6988 | E45: =E41 -> 99 | H45: =H41 -> 1136 | S45: =S41 -> 4963 | T45: =T41 -> 1321 | U45: =U41 -> 50924 | V45: =V41 -> Pre-Signal 1 | AC45: =AC41 -> 76 | AD45: =AD41 -> 20

Sheet Expected
A1: EXPECTED SCENARIO — Expected Growth
A2: 0.25% paid conversion | 12% MoM traffic growth | 6% monthly churn | Referral: 0.1% of total visitors x $350 blended
A3: Blue = hardcoded inputs | Black = calculated formulas | Green = Assumptions references | ▼ = NEW v16 columns (YT+IG integration)
A5: Month | B5: Organic Visitors | C5: Free Signups (Email 2%) | D5: New Paid Subs | E5: Total Paid Subs | F5: Churn This Month | G5: Net New Subs | H5: MRR ($) | I5: Monthly Revenue ($) | J5: Letter Gens | K5: API Costs ($) | L5: Infra ($) | M5: Content/ SEO ($) | N5: n8n+Tools ($) | O5: Stripe Fees ($) | P5: Total Costs ($) | Q5: Gross Profit ($) | R5: Referral Revenue ($) | S5: Total Revenue ($) | T5: Owner's Draw ($) | U5: Reserve Balance ($) | V5: Traffic Signal | W5: Per-Case Revenue ($) | X5: Free Tier API Cost ($) | Y5: IG Followers ▼ | Z5: YT Referral Visitors ▼ | AA5: IG Direct Visitors ▼ | AB5: TOTAL Visitors ▼ | AC5: YT AdSense Revenue ($) ▼ | AD5: IG Direct Revenue ($) ▼
A6: 1 | B6: =Assumptions!B31 -> 800 | C6: =ROUND(AB6*Assumptions!B25,0) -> 16 | D6: =ROUND(AB6*Assumptions!B23,0) -> 2 | E6: =D6 -> 2 | F6: =0 -> 0 | G6: =D6-F6 -> 2 | H6: =ROUND(E6*Assumptions!B14,0) -> 16 | I6: =H6 -> 16 | J6: =ROUND(E6*Assumptions!B68,0) -> 7 | K6: =ROUND(J6*Assumptions!B65,0) -> 1 | L6: =Assumptions!B70+IF(E6>Assumptions!B72,45,0) -> 31 | M6: =Assumptions!B94+Assumptions!B95+Assumptions!B76+Assumptions!B77 -> 2785 | N6: =Assumptions!B81+Assumptions!B82+Assumptions!B87/12 -> 50 | O6: =ROUND(I6*Assumptions!B85+E6*Assumptions!B86+W6*Assumptions!B85+ROUND(AB6*Assumptions!B137*Assumptions!B138*Assumptions!B139,0)*Assumptions!B86,0) -> 3 | P6: =K6+L6+M6+N6+O6+X6 -> 2875 | Q6: =I6-P6 -> -2859 | R6: =0 -> 0 | S6: =I6+R6+W6+AC6+AD6 -> 47 | T6: =IF(U6<P6*3,0,IF(U6<P6*6,ROUND((Q6+R6+W6+AC6+AD6)*0.75*Assumptions!B113,0),ROUND((Q6+R6+W6+AC6+AD6)*0.75*Assumptions!B114,0))) -> 0 | U6: =Q6+R6+W6+AC6+AD6 -> -2828 | V6: =IF(AB6>=Assumptions!B107,"Signal 6",IF(AB6>=Assumptions!B106,"Signal 5",IF(AB6>=Assumptions!B105,"Signal 4",IF(AB6>=Assumptions!B104,"Signal 3",IF(AB6>=Assumptions!B103,"Signal 2",IF(AB6>=Assumptions!B102,"Signal 1","Pre-Signal 1")))))) -> Pre-Signal 1 | W6: =ROUND(AB6*Assumptions!B137*Assumptions!B138*Assumptions!B139*Assumptions!B136,0) -> 31 | X6: =ROUND(AB6*Assumptions!B137*Assumptions!B65,0) -> 5 | Y6: =Assumptions!B162 -> 50 | Z6: =Assumptions!B153 -> 0 | AA6: =ROUND(Y6*Assumptions!B166,0) -> 0 | AB6: =B6+Z6+AA6 -> 800 | AC6: =ROUND(IF(A6>=Assumptions!B144,(IF(A6>=25,Assumptions!B151,IF(A6>=16,Assumptions!B150,Assumptions!B149))/1000*Assumptions!B146)+IF(A6>=Assumptions!B145,(IF(A6>=25,Assumptions!B151,IF(A6>=16,Assumptions!B150,Assumptions!B149))*Assumptions!B152/1000*Assumptions!B147),0),0),0) -> 0 | AD6: =IF(Y6>=10000,Assumptions!B170,IF(Y6>=5000,Assumptions!B169,IF(Y6>=2000,Assumptions!B168,IF(Y6>=500,Assumptions!B167,0)))) -> 0
A7: 2 | B7: =B6*(1+Assumptions!B34) -> 896 | C7: =ROUND(AB7*Assumptions!B25,0) -> 18 | D7: =ROUND(AB7*Assumptions!B23,0) -> 2 | E7: =E6+D7-F7 -> 4 | F7: =ROUND(E6*Assumptions!B44,0) -> 0 | G7: =D7-F7 -> 2 | H7: =ROUND(E7*Assumptions!B14,0) -> 32 | I7: =H7 -> 32 | J7: =ROUND(E7*Assumptions!B68,0) -> 14 | K7: =ROUND(J7*Assumptions!B65,0) -> 1 | L7: =Assumptions!B70+IF(E7>Assumptions!B72,45,0) -> 31 | M7: =Assumptions!B76+Assumptions!B77 -> 35 | N7: =Assumptions!B81+Assumptions!B82+Assumptions!B87/12 -> 50 | O7: =ROUND(I7*Assumptions!B85+E7*Assumptions!B86+W7*Assumptions!B85+ROUND(AB7*Assumptions!B137*Assumptions!B138*Assumptions!B139,0)*Assumptions!B86,0) -> 4 | P7: =K7+L7+M7+N7+O7+X7 -> 127 | Q7: =I7-P7 -> -95 | R7: =0 -> 0 | S7: =I7+R7+W7+AC7+AD7 -> 67 | T7: =IF(U7<P7*3,0,IF(U7<P7*6,ROUND((Q7+R7+W7+AC7+AD7)*0.75*Assumptions!B113,0),ROUND((Q7+R7+W7+AC7+AD7)*0.75*Assumptions!B114,0))) -> 0 | U7: =U6+Q7+R7+W7+AC7+AD7 -> -2888 | V7: =IF(AB7>=Assumptions!B107,"Signal 6",IF(AB7>=Assumptions!B106,"Signal 5",IF(AB7>=Assumptions!B105,"Signal 4",IF(AB7>=Assumptions!B104,"Signal 3",IF(AB7>=Assumptions!B103,"Signal 2",IF(AB7>=Assumptions!B102,"Signal 1","Pre-Signal 1")))))) -> Pre-Signal 1 | W7: =ROUND(AB7*Assumptions!B137*Assumptions!B138*Assumptions!B139*Assumptions!B136,0) -> 35 | X7: =ROUND(AB7*Assumptions!B137*Assumptions!B65,0) -> 6 | Y7: =ROUND(Y6*(1+Assumptions!B163),0) -> 60 | Z7: =Assumptions!B153 -> 0 | AA7: =ROUND(Y7*Assumptions!B166,0) -> 0 | AB7: =B7+Z7+AA7 -> 896 | AC7: =ROUND(IF(A7>=Assumptions!B144,(IF(A7>=25,Assumptions!B151,IF(A7>=16,Assumptions!B150,Assumptions!B149))/1000*Assumptions!B146)+IF(A7>=Assumptions!B145,(IF(A7>=25,Assumptions!B151,IF(A7>=16,Assumptions!B150,Assumptions!B149))*Assumptions!B152/1000*Assumptions!B147),0),0),0) -> 0 | AD7: =IF(Y7>=10000,Assumptions!B170,IF(Y7>=5000,Assumptions!B169,IF(Y7>=2000,Assumptions!B168,IF(Y7>=500,Assumptions!B167,0)))) -> 0
A8: 3 | B8: =B7*(1+Assumptions!B34)*Assumptions!B36 -> 1154.048 | C8: =ROUND(AB8*Assumptions!B25,0) -> 23 | D8: =ROUND(AB8*Assumptions!B23,0) -> 3 | E8: =E7+D8-F8 -> 7 | F8: =ROUND(E7*Assumptions!B44,0) -> 0 | G8: =D8-F8 -> 3 | H8: =ROUND(E8*Assumptions!B14,0) -> 56 | I8: =H8 -> 56 | J8: =ROUND(E8*Assumptions!B68,0) -> 25 | K8: =ROUND(J8*Assumptions!B65,0) -> 2 | L8: =Assumptions!B70+IF(E8>Assumptions!B72,45,0) -> 31 | M8: =Assumptions!B76+Assumptions!B77 -> 35 | N8: =Assumptions!B81+Assumptions!B82+Assumptions!B87/12+Assumptions!B148 -> 116 | O8: =ROUND(I8*Assumptions!B85+E8*Assumptions!B86+W8*Assumptions!B85+ROUND(AB8*Assumptions!B137*Assumptions!B138*Assumptions!B139,0)*Assumptions!B86,0) -> 6 | P8: =K8+L8+M8+N8+O8+X8 -> 197 | Q8: =I8-P8 -> -141 | R8: =0 -> 0 | S8: =I8+R8+W8+AC8+AD8 -> 101 | T8: =IF(U8<P8*3,0,IF(U8<P8*6,ROUND((Q8+R8+W8+AC8+AD8)*0.75*Assumptions!B113,0),ROUND((Q8+R8+W8+AC8+AD8)*0.75*Assumptions!B114,0))) -> 0 | U8: =U7+Q8+R8+W8+AC8+AD8 -> -2984 | V8: =IF(AB8>=Assumptions!B107,"Signal 6",IF(AB8>=Assumptions!B106,"Signal 5",IF(AB8>=Assumptions!B105,"Signal 4",IF(AB8>=Assumptions!B104,"Signal 3",IF(AB8>=Assumptions!B103,"Signal 2",IF(AB8>=Assumptions!B102,"Signal 1","Pre-Signal 1")))))) -> Pre-Signal 1 | W8: =ROUND(AB8*Assumptions!B137*Assumptions!B138*Assumptions!B139*Assumptions!B136,0) -> 45 | X8: =ROUND(AB8*Assumptions!B137*Assumptions!B65,0) -> 7 | Y8: =ROUND(Y7*(1+Assumptions!B163),0) -> 72 | Z8: =Assumptions!B153 -> 0 | AA8: =ROUND(Y8*Assumptions!B166,0) -> 0 | AB8: =B8+Z8+AA8 -> 1154.048 | AC8: =ROUND(IF(A8>=Assumptions!B144,(IF(A8>=25,Assumptions!B151,IF(A8>=16,Assumptions!B150,Assumptions!B149))/1000*Assumptions!B146)+IF(A8>=Assumptions!B145,(IF(A8>=25,Assumptions!B151,IF(A8>=16,Assumptions!B150,Assumptions!B149))*Assumptions!B152/1000*Assumptions!B147),0),0),0) -> 0 | AD8: =IF(Y8>=10000,Assumptions!B170,IF(Y8>=5000,Assumptions!B169,IF(Y8>=2000,Assumptions!B168,IF(Y8>=500,Assumptions!B167,0)))) -> 0
A9: 4 | B9: =B8*(1+Assumptions!B34) -> 1292.5338 | C9: =ROUND(AB9*Assumptions!B25,0) -> 26 | D9: =ROUND(AB9*Assumptions!B23,0) -> 3 | E9: =E8+D9-F9 -> 10 | F9: =ROUND(E8*Assumptions!B44,0) -> 0 | G9: =D9-F9 -> 3 | H9: =ROUND(E9*Assumptions!B14,0) -> 80 | I9: =H9 -> 80 | J9: =ROUND(E9*Assumptions!B68,0) -> 35 | K9: =ROUND(J9*Assumptions!B65,0) -> 3 | L9: =Assumptions!B70+IF(E9>Assumptions!B72,45,0) -> 31 | M9: =Assumptions!B76+Assumptions!B77 -> 35 | N9: =Assumptions!B81+Assumptions!B82+Assumptions!B87/12+Assumptions!B148 -> 116 | O9: =ROUND(I9*Assumptions!B85+E9*Assumptions!B86+W9*Assumptions!B85+ROUND(AB9*Assumptions!B137*Assumptions!B138*Assumptions!B139,0)*Assumptions!B86,0) -> 8 | P9: =K9+L9+M9+N9+O9+X9 -> 201 | Q9: =I9-P9 -> -121 | R9: =0 -> 0 | S9: =I9+R9+W9+AC9+AD9 -> 130 | T9: =IF(U9<P9*3,0,IF(U9<P9*6,ROUND((Q9+R9+W9+AC9+AD9)*0.75*Assumptions!B113,0),ROUND((Q9+R9+W9+AC9+AD9)*0.75*Assumptions!B114,0))) -> 0 | U9: =U8+Q9+R9+W9+AC9+AD9 -> -3055 | V9: =IF(AB9>=Assumptions!B107,"Signal 6",IF(AB9>=Assumptions!B106,"Signal 5",IF(AB9>=Assumptions!B105,"Signal 4",IF(AB9>=Assumptions!B104,"Signal 3",IF(AB9>=Assumptions!B103,"Signal 2",IF(AB9>=Assumptions!B102,"Signal 1","Pre-Signal 1")))))) -> Pre-Signal 1 | W9: =ROUND(AB9*Assumptions!B137*Assumptions!B138*Assumptions!B139*Assumptions!B136,0) -> 50 | X9: =ROUND(AB9*Assumptions!B137*Assumptions!B65,0) -> 8 | Y9: =ROUND(Y8*(1+Assumptions!B163),0) -> 86 | Z9: =Assumptions!B153 -> 0 | AA9: =ROUND(Y9*Assumptions!B166,0) -> 0 | AB9: =B9+Z9+AA9 -> 1292.5338 | AC9: =ROUND(IF(A9>=Assumptions!B144,(IF(A9>=25,Assumptions!B151,IF(A9>=16,Assumptions!B150,Assumptions!B149))/1000*Assumptions!B146)+IF(A9>=Assumptions!B145,(IF(A9>=25,Assumptions!B151,IF(A9>=16,Assumptions!B150,Assumptions!B149))*Assumptions!B152/1000*Assumptions!B147),0),0),0) -> 0 | AD9: =IF(Y9>=10000,Assumptions!B170,IF(Y9>=5000,Assumptions!B169,IF(Y9>=2000,Assumptions!B168,IF(Y9>=500,Assumptions!B167,0)))) -> 0
A10: 5 | B10: =B9*(1+Assumptions!B34) -> 1447.6378 | C10: =ROUND(AB10*Assumptions!B25,0) -> 29 | D10: =ROUND(AB10*Assumptions!B23,0) -> 4 | E10: =E9+D10-F10 -> 13 | F10: =ROUND(E9*Assumptions!B44,0) -> 1 | G10: =D10-F10 -> 3 | H10: =ROUND(E10*Assumptions!B14,0) -> 104 | I10: =H10 -> 104 | J10: =ROUND(E10*Assumptions!B68,0) -> 46 | K10: =ROUND(J10*Assumptions!B65,0) -> 4 | L10: =Assumptions!B70+IF(E10>Assumptions!B72,45,0) -> 31 | M10: =Assumptions!B76+Assumptions!B77 -> 35 | N10: =Assumptions!B81+Assumptions!B82+Assumptions!B87/12+Assumptions!B148 -> 116 | O10: =ROUND(I10*Assumptions!B85+E10*Assumptions!B86+W10*Assumptions!B85+ROUND(AB10*Assumptions!B137*Assumptions!B138*Assumptions!B139,0)*Assumptions!B86,0) -> 10 | P10: =K10+L10+M10+N10+O10+X10 -> 205 | Q10: =I10-P10 -> -101 | R10: =0 -> 0 | S10: =I10+R10+W10+AC10+AD10 -> 160 | T10: =IF(U10<P10*3,0,IF(U10<P10*6,ROUND((Q10+R10+W10+AC10+AD10)*0.75*Assumptions!B113,0),ROUND((Q10+R10+W10+AC10+AD10)*0.75*Assumptions!B114,0))) -> 0 | U10: =U9+Q10+R10+W10+AC10+AD10 -> -3100 | V10: =IF(AB10>=Assumptions!B107,"Signal 6",IF(AB10>=Assumptions!B106,"Signal 5",IF(AB10>=Assumptions!B105,"Signal 4",IF(AB10>=Assumptions!B104,"Signal 3",IF(AB10>=Assumptions!B103,"Signal 2",IF(AB10>=Assumptions!B102,"Signal 1","Pre-Signal 1")))))) -> Pre-Signal 1 | W10: =ROUND(AB10*Assumptions!B137*Assumptions!B138*Assumptions!B139*Assumptions!B136,0) -> 56 | X10: =ROUND(AB10*Assumptions!B137*Assumptions!B65,0) -> 9 | Y10: =ROUND(Y9*(1+Assumptions!B163),0) -> 103 | Z10: =Assumptions!B153 -> 0 | AA10: =ROUND(Y10*Assumptions!B166,0) -> 0 | AB10: =B10+Z10+AA10 -> 1447.6378 | AC10: =ROUND(IF(A10>=Assumptions!B144,(IF(A10>=25,Assumptions!B151,IF(A10>=16,Assumptions!B150,Assumptions!B149))/1000*Assumptions!B146)+IF(A10>=Assumptions!B145,(IF(A10>=25,Assumptions!B151,IF(A10>=16,Assumptions!B150,Assumptions!B149))*Assumptions!B152/1000*Assumptions!B147),0),0),0) -> 0 | AD10: =IF(Y10>=10000,Assumptions!B170,IF(Y10>=5000,Assumptions!B169,IF(Y10>=2000,Assumptions!B168,IF(Y10>=500,Assumptions!B167,0)))) -> 0
A11: 6 | B11: =B10*(1+Assumptions!B34)*Assumptions!B37 -> 1751.0627 | C11: =ROUND(AB11*Assumptions!B25,0) -> 36 | D11: =ROUND(AB11*Assumptions!B23,0) -> 4 | E11: =E10+D11-F11 -> 16 | F11: =ROUND(E10*Assumptions!B44,0) -> 1 | G11: =D11-F11 -> 3 | H11: =ROUND(E11*Assumptions!B14,0) -> 128 | I11: =H11 -> 128 | J11: =ROUND(E11*Assumptions!B68,0) -> 56 | K11: =ROUND(J11*Assumptions!B65,0) -> 4 | L11: =Assumptions!B70+IF(E11>Assumptions!B72,45,0) -> 31 | M11: =Assumptions!B76+Assumptions!B77 -> 35 | N11: =Assumptions!B81+Assumptions!B82+Assumptions!B87/12+Assumptions!B148 -> 116 | O11: =ROUND(I11*Assumptions!B85+E11*Assumptions!B86+W11*Assumptions!B85+ROUND(AB11*Assumptions!B137*Assumptions!B138*Assumptions!B139,0)*Assumptions!B86,0) -> 12 | P11: =K11+L11+M11+N11+O11+X11 -> 209 | Q11: =I11-P11 -> -81 | R11: =ROUND(AB11*Assumptions!B51*Assumptions!B52,0) -> 622 | S11: =I11+R11+W11+AC11+AD11 -> 819 | T11: =IF(U11<P11*3,0,IF(U11<P11*6,ROUND((Q11+R11+W11+AC11+AD11)*0.75*Assumptions!B113,0),ROUND((Q11+R11+W11+AC11+AD11)*0.75*Assumptions!B114,0))) -> 0 | U11: =U10+Q11+R11+W11+AC11+AD11 -> -2490 | V11: =IF(AB11>=Assumptions!B107,"Signal 6",IF(AB11>=Assumptions!B106,"Signal 5",IF(AB11>=Assumptions!B105,"Signal 4",IF(AB11>=Assumptions!B104,"Signal 3",IF(AB11>=Assumptions!B103,"Signal 2",IF(AB11>=Assumptions!B102,"Signal 1","Pre-Signal 1")))))) -> Pre-Signal 1 | W11: =ROUND(AB11*Assumptions!B137*Assumptions!B138*Assumptions!B139*Assumptions!B136,0) -> 69 | X11: =ROUND(AB11*Assumptions!B137*Assumptions!B65,0) -> 11 | Y11: =ROUND(Y10*(1+Assumptions!B163),0) -> 124 | Z11: =Assumptions!B154 -> 25 | AA11: =ROUND(Y11*Assumptions!B166,0) -> 0 | AB11: =B11+Z11+AA11 -> 1776.0627 | AC11: =ROUND(IF(A11>=Assumptions!B144,(IF(A11>=25,Assumptions!B151,IF(A11>=16,Assumptions!B150,Assumptions!B149))/1000*Assumptions!B146)+IF(A11>=Assumptions!B145,(IF(A11>=25,Assumptions!B151,IF(A11>=16,Assumptions!B150,Assumptions!B149))*Assumptions!B152/1000*Assumptions!B147),0),0),0) -> 0 | AD11: =IF(Y11>=10000,Assumptions!B170,IF(Y11>=5000,Assumptions!B169,IF(Y11>=2000,Assumptions!B168,IF(Y11>=500,Assumptions!B167,0)))) -> 0
A12: 7 | B12: =B11*(1+Assumptions!B34) -> 1961.1902 | C12: =ROUND(AB12*Assumptions!B25,0) -> 40 | D12: =ROUND(AB12*Assumptions!B23,0) -> 5 | E12: =E11+D12-F12 -> 20 | F12: =ROUND(E11*Assumptions!B44,0) -> 1 | G12: =D12-F12 -> 4 | H12: =ROUND(E12*Assumptions!B14,0) -> 160 | I12: =H12 -> 160 | J12: =ROUND(E12*Assumptions!B68,0) -> 70 | K12: =ROUND(J12*Assumptions!B65,0) -> 6 | L12: =Assumptions!B70+IF(E12>Assumptions!B72,45,0) -> 31 | M12: =Assumptions!B76+Assumptions!B77 -> 35 | N12: =Assumptions!B81+Assumptions!B82+Assumptions!B87/12+Assumptions!B148 -> 116 | O12: =ROUND(I12*Assumptions!B85+E12*Assumptions!B86+W12*Assumptions!B85+ROUND(AB12*Assumptions!B137*Assumptions!B138*Assumptions!B139,0)*Assumptions!B86,0) -> 15 | P12: =K12+L12+M12+N12+O12+X12 -> 216 | Q12: =I12-P12 -> -56 | R12: =ROUND(AB12*Assumptions!B51*Assumptions!B52,0) -> 695 | S12: =I12+R12+W12+AC12+AD12 -> 932 | T12: =IF(U12<P12*3,0,IF(U12<P12*6,ROUND((Q12+R12+W12+AC12+AD12)*0.75*Assumptions!B113,0),ROUND((Q12+R12+W12+AC12+AD12)*0.75*Assumptions!B114,0))) -> 0 | U12: =U11+Q12+R12+W12+AC12+AD12 -> -1774 | V12: =IF(AB12>=Assumptions!B107,"Signal 6",IF(AB12>=Assumptions!B106,"Signal 5",IF(AB12>=Assumptions!B105,"Signal 4",IF(AB12>=Assumptions!B104,"Signal 3",IF(AB12>=Assumptions!B103,"Signal 2",IF(AB12>=Assumptions!B102,"Signal 1","Pre-Signal 1")))))) -> Pre-Signal 1 | W12: =ROUND(AB12*Assumptions!B137*Assumptions!B138*Assumptions!B139*Assumptions!B136,0) -> 77 | X12: =ROUND(AB12*Assumptions!B137*Assumptions!B65,0) -> 13 | Y12: =ROUND(Y11*(1+Assumptions!B164),0) -> 143 | Z12: =Assumptions!B154 -> 25 | AA12: =ROUND(Y12*Assumptions!B166,0) -> 0 | AB12: =B12+Z12+AA12 -> 1986.1902 | AC12: =ROUND(IF(A12>=Assumptions!B144,(IF(A12>=25,Assumptions!B151,IF(A12>=16,Assumptions!B150,Assumptions!B149))/1000*Assumptions!B146)+IF(A12>=Assumptions!B145,(IF(A12>=25,Assumptions!B151,IF(A12>=16,Assumptions!B150,Assumptions!B149))*Assumptions!B152/1000*Assumptions!B147),0),0),0) -> 0 | AD12: =IF(Y12>=10000,Assumptions!B170,IF(Y12>=5000,Assumptions!B169,IF(Y12>=2000,Assumptions!B168,IF(Y12>=500,Assumptions!B167,0)))) -> 0
A13: 8 | B13: =B12*(1+Assumptions!B34) -> 2196.533 | C13: =ROUND(AB13*Assumptions!B25,0) -> 44 | D13: =ROUND(AB13*Assumptions!B23,0) -> 6 | E13: =E12+D13-F13 -> 25 | F13: =ROUND(E12*Assumptions!B44,0) -> 1 | G13: =D13-F13 -> 5 | H13: =ROUND(E13*Assumptions!B14,0) -> 200 | I13: =H13 -> 200 | J13: =ROUND(E13*Assumptions!B68,0) -> 88 | K13: =ROUND(J13*Assumptions!B65,0) -> 7 | L13: =Assumptions!B70+IF(E13>Assumptions!B72,45,0) -> 31 | M13: =Assumptions!B76+Assumptions!B77 -> 35 | N13: =Assumptions!B81+Assumptions!B82+Assumptions!B87/12+Assumptions!B148 -> 116 | O13: =ROUND(I13*Assumptions!B85+E13*Assumptions!B86+W13*Assumptions!B85+ROUND(AB13*Assumptions!B137*Assumptions!B138*Assumptions!B139,0)*Assumptions!B86,0) -> 18 | P13: =K13+L13+M13+N13+O13+X13 -> 221 | Q13: =I13-P13 -> -21 | R13: =ROUND(AB13*Assumptions!B51*Assumptions!B52,0) -> 778 | S13: =I13+R13+W13+AC13+AD13 -> 1065 | T13: =IF(U13<P13*3,0,IF(U13<P13*6,ROUND((Q13+R13+W13+AC13+AD13)*0.75*Assumptions!B113,0),ROUND((Q13+R13+W13+AC13+AD13)*0.75*Assumptions!B114,0))) -> 0 | U13: =U12+Q13+R13+W13+AC13+AD13 -> -930 | V13: =IF(AB13>=Assumptions!B107,"Signal 6",IF(AB13>=Assumptions!B106,"Signal 5",IF(AB13>=Assumptions!B105,"Signal 4",IF(AB13>=Assumptions!B104,"Signal 3",IF(AB13>=Assumptions!B103,"Signal 2",IF(AB13>=Assumptions!B102,"Signal 1","Pre-Signal 1")))))) -> Pre-Signal 1 | W13: =ROUND(AB13*Assumptions!B137*Assumptions!B138*Assumptions!B139*Assumptions!B136,0) -> 87 | X13: =ROUND(AB13*Assumptions!B137*Assumptions!B65,0) -> 14 | Y13: =ROUND(Y12*(1+Assumptions!B164),0) -> 164 | Z13: =Assumptions!B154 -> 25 | AA13: =ROUND(Y13*Assumptions!B166,0) -> 0 | AB13: =B13+Z13+AA13 -> 2221.533 | AC13: =ROUND(IF(A13>=Assumptions!B144,(IF(A13>=25,Assumptions!B151,IF(A13>=16,Assumptions!B150,Assumptions!B149))/1000*Assumptions!B146)+IF(A13>=Assumptions!B145,(IF(A13>=25,Assumptions!B151,IF(A13>=16,Assumptions!B150,Assumptions!B149))*Assumptions!B152/1000*Assumptions!B147),0),0),0) -> 0 | AD13: =IF(Y13>=10000,Assumptions!B170,IF(Y13>=5000,Assumptions!B169,IF(Y13>=2000,Assumptions!B168,IF(Y13>=500,Assumptions!B167,0)))) -> 0
A14: 9 | B14: =B13*(1+Assumptions!B34) -> 2460.117 | C14: =ROUND(AB14*Assumptions!B25,0) -> 50 | D14: =ROUND(AB14*Assumptions!B23,0) -> 6 | E14: =E13+D14-F14 -> 29 | F14: =ROUND(E13*Assumptions!B44,0) -> 2 | G14: =D14-F14 -> 4 | H14: =ROUND(E14*((Assumptions!B14+Assumptions!B15)/2),0) -> 305 | I14: =H14 -> 305 | J14: =ROUND(E14*Assumptions!B68,0) -> 102 | K14: =ROUND(J14*Assumptions!B65,0) -> 8 | L14: =Assumptions!B70+IF(E14>Assumptions!B72,45,0) -> 31 | M14: =Assumptions!B76+Assumptions!B77 -> 35 | N14: =Assumptions!B81+Assumptions!B82+Assumptions!B87/12+Assumptions!B148 -> 116 | O14: =ROUND(I14*Assumptions!B85+E14*Assumptions!B86+W14*Assumptions!B85+ROUND(AB14*Assumptions!B137*Assumptions!B138*Assumptions!B139,0)*Assumptions!B86,0) -> 23 | P14: =K14+L14+M14+N14+O14+X14 -> 229 | Q14: =I14-P14 -> 76 | R14: =ROUND(AB14*Assumptions!B51*Assumptions!B52,0) -> 882 | S14: =I14+R14+W14+AC14+AD14 -> 1285 | T14: =IF(U14<P14*3,0,IF(U14<P14*6,ROUND((Q14+R14+W14+AC14+AD14)*0.75*Assumptions!B113,0),ROUND((Q14+R14+W14+AC14+AD14)*0.75*Assumptions!B114,0))) -> 0 | U14: =U13+Q14+R14+W14+AC14+AD14 -> 126 | V14: =IF(AB14>=Assumptions!B107,"Signal 6",IF(AB14>=Assumptions!B106,"Signal 5",IF(AB14>=Assumptions!B105,"Signal 4",IF(AB14>=Assumptions!B104,"Signal 3",IF(AB14>=Assumptions!B103,"Signal 2",IF(AB14>=Assumptions!B102,"Signal 1","Pre-Signal 1")))))) -> Pre-Signal 1 | W14: =ROUND(AB14*Assumptions!B137*Assumptions!B138*Assumptions!B139*Assumptions!B136,0) -> 98 | X14: =ROUND(AB14*Assumptions!B137*Assumptions!B65,0) -> 16 | Y14: =ROUND(Y13*(1+Assumptions!B164),0) -> 189 | Z14: =Assumptions!B155 -> 60 | AA14: =ROUND(Y14*Assumptions!B166,0) -> 1 | AB14: =B14+Z14+AA14 -> 2521.117 | AC14: =ROUND(IF(A14>=Assumptions!B144,(IF(A14>=25,Assumptions!B151,IF(A14>=16,Assumptions!B150,Assumptions!B149))/1000*Assumptions!B146)+IF(A14>=Assumptions!B145,(IF(A14>=25,Assumptions!B151,IF(A14>=16,Assumptions!B150,Assumptions!B149))*Assumptions!B152/1000*Assumptions!B147),0),0),0) -> 0 | AD14: =IF(Y14>=10000,Assumptions!B170,IF(Y14>=5000,Assumptions!B169,IF(Y14>=2000,Assumptions!B168,IF(Y14>=500,Assumptions!B167,0)))) -> 0
A15: 10 | B15: =B14*(1+Assumptions!B34) -> 2755.3311 | C15: =ROUND(AB15*Assumptions!B25,0) -> 56 | D15: =ROUND(AB15*Assumptions!B23,0) -> 7 | E15: =E14+D15-F15 -> 34 | F15: =ROUND(E14*Assumptions!B44,0) -> 2 | G15: =D15-F15 -> 5 | H15: =ROUND(E15*(Assumptions!B15*0.85+Assumptions!B11*0.15),0) -> 390 | I15: =H15 -> 390 | J15: =ROUND(E15*Assumptions!B68,0) -> 119 | K15: =ROUND(J15*Assumptions!B65,0) -> 10 | L15: =Assumptions!B70+IF(E15>Assumptions!B72,45,0) -> 31 | M15: =Assumptions!B76+Assumptions!B77 -> 35 | N15: =Assumptions!B81+Assumptions!B82+Assumptions!B87/12+Assumptions!B148 -> 116 | O15: =ROUND(I15*Assumptions!B85+E15*Assumptions!B86+W15*Assumptions!B85+ROUND(AB15*Assumptions!B137*Assumptions!B138*Assumptions!B139,0)*Assumptions!B86,0) -> 27 | P15: =K15+L15+M15+N15+O15+X15 -> 237 | Q15: =I15-P15 -> 153 | R15: =ROUND(AB15*Assumptions!B51*Assumptions!B52,0) -> 986 | S15: =I15+R15+W15+AC15+AD15 -> 1486 | T15: =IF(U15<P15*3,0,IF(U15<P15*6,ROUND((Q15+R15+W15+AC15+AD15)*0.75*Assumptions!B113,0),ROUND((Q15+R15+W15+AC15+AD15)*0.75*Assumptions!B114,0))) -> 221 | U15: =U14+Q15+R15+W15+AC15+AD15 -> 1375 | V15: =IF(AB15>=Assumptions!B107,"Signal 6",IF(AB15>=Assumptions!B106,"Signal 5",IF(AB15>=Assumptions!B105,"Signal 4",IF(AB15>=Assumptions!B104,"Signal 3",IF(AB15>=Assumptions!B103,"Signal 2",IF(AB15>=Assumptions!B102,"Signal 1","Pre-Signal 1")))))) -> Pre-Signal 1 | W15: =ROUND(AB15*Assumptions!B137*Assumptions!B138*Assumptions!B139*Assumptions!B136,0) -> 110 | X15: =ROUND(AB15*Assumptions!B137*Assumptions!B65,0) -> 18 | Y15: =ROUND(Y14*(1+Assumptions!B164),0) -> 217 | Z15: =Assumptions!B155 -> 60 | AA15: =ROUND(Y15*Assumptions!B166,0) -> 1 | AB15: =B15+Z15+AA15 -> 2816.3311 | AC15: =ROUND(IF(A15>=Assumptions!B144,(IF(A15>=25,Assumptions!B151,IF(A15>=16,Assumptions!B150,Assumptions!B149))/1000*Assumptions!B146)+IF(A15>=Assumptions!B145,(IF(A15>=25,Assumptions!B151,IF(A15>=16,Assumptions!B150,Assumptions!B149))*Assumptions!B152/1000*Assumptions!B147),0),0),0) -> 0 | AD15: =IF(Y15>=10000,Assumptions!B170,IF(Y15>=5000,Assumptions!B169,IF(Y15>=2000,Assumptions!B168,IF(Y15>=500,Assumptions!B167,0)))) -> 0
A16: 11 | B16: =B15*(1+Assumptions!B34) -> 3085.9708 | C16: =ROUND(AB16*Assumptions!B25,0) -> 63 | D16: =ROUND(AB16*Assumptions!B23,0) -> 8 | E16: =E15+D16-F16 -> 40 | F16: =ROUND(E15*Assumptions!B44,0) -> 2 | G16: =D16-F16 -> 6 | H16: =ROUND(E16*(Assumptions!B15*0.85+Assumptions!B11*0.15),0) -> 459 | I16: =H16 -> 459 | J16: =ROUND(E16*Assumptions!B68,0) -> 140 | K16: =ROUND(J16*Assumptions!B65,0) -> 11 | L16: =Assumptions!B70+IF(E16>Assumptions!B72,45,0) -> 31 | M16: =Assumptions!B76+Assumptions!B77 -> 35 | N16: =Assumptions!B81+Assumptions!B82+Assumptions!B87/12+Assumptions!B148 -> 116 | O16: =ROUND(I16*Assumptions!B85+E16*Assumptions!B86+W16*Assumptions!B85+ROUND(AB16*Assumptions!B137*Assumptions!B138*Assumptions!B139,0)*Assumptions!B86,0) -> 32 | P16: =K16+L16+M16+N16+O16+X16 -> 245 | Q16: =I16-P16 -> 214 | R16: =ROUND(AB16*Assumptions!B51*Assumptions!B52,0) -> 1101 | S16: =I16+R16+W16+AC16+AD16 -> 1683 | T16: =IF(U16<P16*3,0,IF(U16<P16*6,ROUND((Q16+R16+W16+AC16+AD16)*0.75*Assumptions!B113,0),ROUND((Q16+R16+W16+AC16+AD16)*0.75*Assumptions!B114,0))) -> 412 | U16: =U15+Q16+R16+W16+AC16+AD16 -> 2813 | V16: =IF(AB16>=Assumptions!B107,"Signal 6",IF(AB16>=Assumptions!B106,"Signal 5",IF(AB16>=Assumptions!B105,"Signal 4",IF(AB16>=Assumptions!B104,"Signal 3",IF(AB16>=Assumptions!B103,"Signal 2",IF(AB16>=Assumptions!B102,"Signal 1","Pre-Signal 1")))))) -> Pre-Signal 1 | W16: =ROUND(AB16*Assumptions!B137*Assumptions!B138*Assumptions!B139*Assumptions!B136,0) -> 123 | X16: =ROUND(AB16*Assumptions!B137*Assumptions!B65,0) -> 20 | Y16: =ROUND(Y15*(1+Assumptions!B164),0) -> 250 | Z16: =Assumptions!B155 -> 60 | AA16: =ROUND(Y16*Assumptions!B166,0) -> 1 | AB16: =B16+Z16+AA16 -> 3146.9708 | AC16: =ROUND(IF(A16>=Assumptions!B144,(IF(A16>=25,Assumptions!B151,IF(A16>=16,Assumptions!B150,Assumptions!B149))/1000*Assumptions!B146)+IF(A16>=Assumptions!B145,(IF(A16>=25,Assumptions!B151,IF(A16>=16,Assumptions!B150,Assumptions!B149))*Assumptions!B152/1000*Assumptions!B147),0),0),0) -> 0 | AD16: =IF(Y16>=10000,Assumptions!B170,IF(Y16>=5000,Assumptions!B169,IF(Y16>=2000,Assumptions!B168,IF(Y16>=500,Assumptions!B167,0)))) -> 0
A17: 12 | B17: =B16*(1+Assumptions!B34) -> 3456.2873 | C17: =ROUND(AB17*Assumptions!B25,0) -> 72 | D17: =ROUND(AB17*Assumptions!B23,0) -> 9 | E17: =E16+D17-F17 -> 47 | F17: =ROUND(E16*Assumptions!B44,0) -> 2 | G17: =D17-F17 -> 7 | H17: =ROUND(E17*(Assumptions!B15*0.85+Assumptions!B11*0.15),0) -> 539 | I17: =H17 -> 539 | J17: =ROUND(E17*Assumptions!B68,0) -> 165 | K17: =ROUND(J17*Assumptions!B65,0) -> 13 | L17: =Assumptions!B70+IF(E17>Assumptions!B72,45,0) -> 31 | M17: =Assumptions!B76+Assumptions!B77 -> 35 | N17: =Assumptions!B81+Assumptions!B82+Assumptions!B87/12+Assumptions!B148 -> 116 | O17: =ROUND(I17*Assumptions!B85+E17*Assumptions!B86+W17*Assumptions!B85+ROUND(AB17*Assumptions!B137*Assumptions!B138*Assumptions!B139,0)*Assumptions!B86,0) -> 37 | P17: =K17+L17+M17+N17+O17+X17 -> 255 | Q17: =I17-P17 -> 284 | R17: =ROUND(AB17*Assumptions!B51*Assumptions!B52,0) -> 1254 | S17: =I17+R17+W17+AC17+AD17 -> 1949 | T17: =IF(U17<P17*3,0,IF(U17<P17*6,ROUND((Q17+R17+W17+AC17+AD17)*0.75*Assumptions!B113,0),ROUND((Q17+R17+W17+AC17+AD17)*0.75*Assumptions!B114,0))) -> 485 | U17: =U16+Q17+R17+W17+AC17+AD17 -> 4507 | V17: =IF(AB17>=Assumptions!B107,"Signal 6",IF(AB17>=Assumptions!B106,"Signal 5",IF(AB17>=Assumptions!B105,"Signal 4",IF(AB17>=Assumptions!B104,"Signal 3",IF(AB17>=Assumptions!B103,"Signal 2",IF(AB17>=Assumptions!B102,"Signal 1","Pre-Signal 1")))))) -> Pre-Signal 1 | W17: =ROUND(AB17*Assumptions!B137*Assumptions!B138*Assumptions!B139*Assumptions!B136,0) -> 140 | X17: =ROUND(AB17*Assumptions!B137*Assumptions!B65,0) -> 23 | Y17: =ROUND(Y16*(1+Assumptions!B164),0) -> 288 | Z17: =Assumptions!B156 -> 125 | AA17: =ROUND(Y17*Assumptions!B166,0) -> 1 | AB17: =B17+Z17+AA17 -> 3582.2873 | AC17: =ROUND(IF(A17>=Assumptions!B144,(IF(A17>=25,Assumptions!B151,IF(A17>=16,Assumptions!B150,Assumptions!B149))/1000*Assumptions!B146)+IF(A17>=Assumptions!B145,(IF(A17>=25,Assumptions!B151,IF(A17>=16,Assumptions!B150,Assumptions!B149))*Assumptions!B152/1000*Assumptions!B147),0),0),0) -> 16 | AD17: =IF(Y17>=10000,Assumptions!B170,IF(Y17>=5000,Assumptions!B169,IF(Y17>=2000,Assumptions!B168,IF(Y17>=500,Assumptions!B167,0)))) -> 0
A18: 13 | B18: =B17*(1+Assumptions!B34) -> 3871.0417 | C18: =ROUND(AB18*Assumptions!B25,0) -> 80 | D18: =ROUND(AB18*Assumptions!B23,0) -> 10 | E18: =E17+D18-F18 -> 54 | F18: =ROUND(E17*Assumptions!B44,0) -> 3 | G18: =D18-F18 -> 7 | H18: =ROUND(E18*(Assumptions!B15*0.85+Assumptions!B11*0.15),0) -> 620 | I18: =H18 -> 620 | J18: =ROUND(E18*Assumptions!B68,0) -> 189 | K18: =ROUND(J18*Assumptions!B65,0) -> 15 | L18: =Assumptions!B70+IF(E18>Assumptions!B72,45,0) -> 31 | M18: =Assumptions!B76+Assumptions!B77 -> 35 | N18: =Assumptions!B81+Assumptions!B82+Assumptions!B87/12+Assumptions!B148 -> 116 | O18: =ROUND(I18*Assumptions!B85+E18*Assumptions!B86+W18*Assumptions!B85+ROUND(AB18*Assumptions!B137*Assumptions!B138*Assumptions!B139,0)*Assumptions!B86,0) -> 42 | P18: =K18+L18+M18+N18+O18+X18 -> 265 | Q18: =I18-P18 -> 355 | R18: =ROUND(AB18*Assumptions!B51*Assumptions!B52,0) -> 1399 | S18: =I18+R18+W18+AC18+AD18 -> 2191 | T18: =IF(U18<P18*3,0,IF(U18<P18*6,ROUND((Q18+R18+W18+AC18+AD18)*0.75*Assumptions!B113,0),ROUND((Q18+R18+W18+AC18+AD18)*0.75*Assumptions!B114,0))) -> 552 | U18: =U17+Q18+R18+W18+AC18+AD18 -> 6433 | V18: =IF(AB18>=Assumptions!B107,"Signal 6",IF(AB18>=Assumptions!B106,"Signal 5",IF(AB18>=Assumptions!B105,"Signal 4",IF(AB18>=Assumptions!B104,"Signal 3",IF(AB18>=Assumptions!B103,"Signal 2",IF(AB18>=Assumptions!B102,"Signal 1","Pre-Signal 1")))))) -> Pre-Signal 1 | W18: =ROUND(AB18*Assumptions!B137*Assumptions!B138*Assumptions!B139*Assumptions!B136,0) -> 156 | X18: =ROUND(AB18*Assumptions!B137*Assumptions!B65,0) -> 26 | Y18: =ROUND(Y17*(1+Assumptions!B165),0) -> 317 | Z18: =Assumptions!B156 -> 125 | AA18: =ROUND(Y18*Assumptions!B166,0) -> 1 | AB18: =B18+Z18+AA18 -> 3997.0417 | AC18: =ROUND(IF(A18>=Assumptions!B144,(IF(A18>=25,Assumptions!B151,IF(A18>=16,Assumptions!B150,Assumptions!B149))/1000*Assumptions!B146)+IF(A18>=Assumptions!B145,(IF(A18>=25,Assumptions!B151,IF(A18>=16,Assumptions!B150,Assumptions!B149))*Assumptions!B152/1000*Assumptions!B147),0),0),0) -> 16 | AD18: =IF(Y18>=10000,Assumptions!B170,IF(Y18>=5000,Assumptions!B169,IF(Y18>=2000,Assumptions!B168,IF(Y18>=500,Assumptions!B167,0)))) -> 0
A19: 14 | B19: =B18*(1+Assumptions!B34) -> 4335.5668 | C19: =ROUND(AB19*Assumptions!B25,0) -> 89 | D19: =ROUND(AB19*Assumptions!B23,0) -> 11 | E19: =E18+D19-F19 -> 62 | F19: =ROUND(E18*Assumptions!B44,0) -> 3 | G19: =D19-F19 -> 8 | H19: =ROUND(E19*(Assumptions!B15*0.85+Assumptions!B11*0.15),0) -> 711 | I19: =H19 -> 711 | J19: =ROUND(E19*Assumptions!B68,0) -> 217 | K19: =ROUND(J19*Assumptions!B65,0) -> 17 | L19: =Assumptions!B70+IF(E19>Assumptions!B72,45,0) -> 31 | M19: =Assumptions!B76+Assumptions!B77 -> 35 | N19: =Assumptions!B81+Assumptions!B82+Assumptions!B87/12+Assumptions!B148 -> 116 | O19: =ROUND(I19*Assumptions!B85+E19*Assumptions!B86+W19*Assumptions!B85+ROUND(AB19*Assumptions!B137*Assumptions!B138*Assumptions!B139,0)*Assumptions!B86,0) -> 48 | P19: =K19+L19+M19+N19+O19+X19 -> 276 | Q19: =I19-P19 -> 435 | R19: =ROUND(AB19*Assumptions!B51*Assumptions!B52,0) -> 1562 | S19: =I19+R19+W19+AC19+AD19 -> 2463 | T19: =IF(U19<P19*3,0,IF(U19<P19*6,ROUND((Q19+R19+W19+AC19+AD19)*0.75*Assumptions!B113,0),ROUND((Q19+R19+W19+AC19+AD19)*0.75*Assumptions!B114,0))) -> 627 | U19: =U18+Q19+R19+W19+AC19+AD19 -> 8620 | V19: =IF(AB19>=Assumptions!B107,"Signal 6",IF(AB19>=Assumptions!B106,"Signal 5",IF(AB19>=Assumptions!B105,"Signal 4",IF(AB19>=Assumptions!B104,"Signal 3",IF(AB19>=Assumptions!B103,"Signal 2",IF(AB19>=Assumptions!B102,"Signal 1","Pre-Signal 1")))))) -> Pre-Signal 1 | W19: =ROUND(AB19*Assumptions!B137*Assumptions!B138*Assumptions!B139*Assumptions!B136,0) -> 174 | X19: =ROUND(AB19*Assumptions!B137*Assumptions!B65,0) -> 29 | Y19: =ROUND(Y18*(1+Assumptions!B165),0) -> 349 | Z19: =Assumptions!B156 -> 125 | AA19: =ROUND(Y19*Assumptions!B166,0) -> 1 | AB19: =B19+Z19+AA19 -> 4461.5668 | AC19: =ROUND(IF(A19>=Assumptions!B144,(IF(A19>=25,Assumptions!B151,IF(A19>=16,Assumptions!B150,Assumptions!B149))/1000*Assumptions!B146)+IF(A19>=Assumptions!B145,(IF(A19>=25,Assumptions!B151,IF(A19>=16,Assumptions!B150,Assumptions!B149))*Assumptions!B152/1000*Assumptions!B147),0),0),0) -> 16 | AD19: =IF(Y19>=10000,Assumptions!B170,IF(Y19>=5000,Assumptions!B169,IF(Y19>=2000,Assumptions!B168,IF(Y19>=500,Assumptions!B167,0)))) -> 0
A20: 15 | B20: =B19*(1+Assumptions!B34) -> 4855.8348 | C20: =ROUND(AB20*Assumptions!B25,0) -> 100 | D20: =ROUND(AB20*Assumptions!B23,0) -> 12 | E20: =E19+D20-F20 -> 70 | F20: =ROUND(E19*Assumptions!B44,0) -> 4 | G20: =D20-F20 -> 8 | H20: =ROUND(E20*(Assumptions!B15*0.85+Assumptions!B11*0.15),0) -> 803 | I20: =H20 -> 803 | J20: =ROUND(E20*Assumptions!B68,0) -> 245 | K20: =ROUND(J20*Assumptions!B65,0) -> 20 | L20: =Assumptions!B70+IF(E20>Assumptions!B72,45,0) -> 31 | M20: =Assumptions!B76+Assumptions!B77 -> 35 | N20: =Assumptions!B81+Assumptions!B82+Assumptions!B87/12+Assumptions!B148 -> 116 | O20: =ROUND(I20*Assumptions!B85+E20*Assumptions!B86+W20*Assumptions!B85+ROUND(AB20*Assumptions!B137*Assumptions!B138*Assumptions!B139,0)*Assumptions!B86,0) -> 54 | P20: =K20+L20+M20+N20+O20+X20 -> 288 | Q20: =I20-P20 -> 515 | R20: =ROUND(AB20*Assumptions!B51*Assumptions!B52,0) -> 1744 | S20: =I20+R20+W20+AC20+AD20 -> 2757 | T20: =IF(U20<P20*3,0,IF(U20<P20*6,ROUND((Q20+R20+W20+AC20+AD20)*0.75*Assumptions!B113,0),ROUND((Q20+R20+W20+AC20+AD20)*0.75*Assumptions!B114,0))) -> 707 | U20: =U19+Q20+R20+W20+AC20+AD20 -> 11089 | V20: =IF(AB20>=Assumptions!B107,"Signal 6",IF(AB20>=Assumptions!B106,"Signal 5",IF(AB20>=Assumptions!B105,"Signal 4",IF(AB20>=Assumptions!B104,"Signal 3",IF(AB20>=Assumptions!B103,"Signal 2",IF(AB20>=Assumptions!B102,"Signal 1","Pre-Signal 1")))))) -> Pre-Signal 1 | W20: =ROUND(AB20*Assumptions!B137*Assumptions!B138*Assumptions!B139*Assumptions!B136,0) -> 194 | X20: =ROUND(AB20*Assumptions!B137*Assumptions!B65,0) -> 32 | Y20: =ROUND(Y19*(1+Assumptions!B165),0) -> 384 | Z20: =Assumptions!B156 -> 125 | AA20: =ROUND(Y20*Assumptions!B166,0) -> 1 | AB20: =B20+Z20+AA20 -> 4981.8348 | AC20: =ROUND(IF(A20>=Assumptions!B144,(IF(A20>=25,Assumptions!B151,IF(A20>=16,Assumptions!B150,Assumptions!B149))/1000*Assumptions!B146)+IF(A20>=Assumptions!B145,(IF(A20>=25,Assumptions!B151,IF(A20>=16,Assumptions!B150,Assumptions!B149))*Assumptions!B152/1000*Assumptions!B147),0),0),0) -> 16 | AD20: =IF(Y20>=10000,Assumptions!B170,IF(Y20>=5000,Assumptions!B169,IF(Y20>=2000,Assumptions!B168,IF(Y20>=500,Assumptions!B167,0)))) -> 0
A21: 16 | B21: =B20*(1+Assumptions!B34) -> 5438.5349 | C21: =ROUND(AB21*Assumptions!B25,0) -> 114 | D21: =ROUND(AB21*Assumptions!B23,0) -> 14 | E21: =E20+D21-F21 -> 80 | F21: =ROUND(E20*Assumptions!B44,0) -> 4 | G21: =D21-F21 -> 10 | H21: =ROUND(E21*(Assumptions!B15*0.85+Assumptions!B11*0.15),0) -> 918 | I21: =H21 -> 918 | J21: =ROUND(E21*Assumptions!B68,0) -> 280 | K21: =ROUND(J21*Assumptions!B65,0) -> 22 | L21: =Assumptions!B70+IF(E21>Assumptions!B72,45,0) -> 31 | M21: =Assumptions!B76+Assumptions!B77 -> 35 | N21: =Assumptions!B81+Assumptions!B82+Assumptions!B87/12+Assumptions!B148 -> 116 | O21: =ROUND(I21*Assumptions!B85+E21*Assumptions!B86+W21*Assumptions!B85+ROUND(AB21*Assumptions!B137*Assumptions!B138*Assumptions!B139,0)*Assumptions!B86,0) -> 62 | P21: =K21+L21+M21+N21+O21+X21 -> 302 | Q21: =I21-P21 -> 616 | R21: =ROUND(AB21*Assumptions!B51*Assumptions!B52,0) -> 1991 | S21: =I21+R21+W21+AC21+AD21 -> 3174 | T21: =IF(U21<P21*3,0,IF(U21<P21*6,ROUND((Q21+R21+W21+AC21+AD21)*0.75*Assumptions!B113,0),ROUND((Q21+R21+W21+AC21+AD21)*0.75*Assumptions!B114,0))) -> 823 | U21: =U20+Q21+R21+W21+AC21+AD21 -> 13961 | V21: =IF(AB21>=Assumptions!B107,"Signal 6",IF(AB21>=Assumptions!B106,"Signal 5",IF(AB21>=Assumptions!B105,"Signal 4",IF(AB21>=Assumptions!B104,"Signal 3",IF(AB21>=Assumptions!B103,"Signal 2",IF(AB21>=Assumptions!B102,"Signal 1","Pre-Signal 1")))))) -> Pre-Signal 1 | W21: =ROUND(AB21*Assumptions!B137*Assumptions!B138*Assumptions!B139*Assumptions!B136,0) -> 222 | X21: =ROUND(AB21*Assumptions!B137*Assumptions!B65,0) -> 36 | Y21: =ROUND(Y20*(1+Assumptions!B165),0) -> 422 | Z21: =Assumptions!B157 -> 250 | AA21: =ROUND(Y21*Assumptions!B166,0) -> 1 | AB21: =B21+Z21+AA21 -> 5689.5349 | AC21: =ROUND(IF(A21>=Assumptions!B144,(IF(A21>=25,Assumptions!B151,IF(A21>=16,Assumptions!B150,Assumptions!B149))/1000*Assumptions!B146)+IF(A21>=Assumptions!B145,(IF(A21>=25,Assumptions!B151,IF(A21>=16,Assumptions!B150,Assumptions!B149))*Assumptions!B152/1000*Assumptions!B147),0),0),0) -> 43 | AD21: =IF(Y21>=10000,Assumptions!B170,IF(Y21>=5000,Assumptions!B169,IF(Y21>=2000,Assumptions!B168,IF(Y21>=500,Assumptions!B167,0)))) -> 0
A22: 17 | B22: =B21*(1+Assumptions!B34) -> 6091.1591 | C22: =ROUND(AB22*Assumptions!B25,0) -> 127 | D22: =ROUND(AB22*Assumptions!B23,0) -> 16 | E22: =E21+D22-F22 -> 91 | F22: =ROUND(E21*Assumptions!B44,0) -> 5 | G22: =D22-F22 -> 11 | H22: =ROUND(E22*(Assumptions!B15*0.85+Assumptions!B11*0.15),0) -> 1044 | I22: =H22 -> 1044 | J22: =ROUND(E22*Assumptions!B68,0) -> 319 | K22: =ROUND(J22*Assumptions!B65,0) -> 26 | L22: =Assumptions!B70+IF(E22>Assumptions!B72,45,0) -> 31 | M22: =Assumptions!B76+Assumptions!B77 -> 35 | N22: =Assumptions!B81+Assumptions!B82+Assumptions!B87/12+Assumptions!B148 -> 116 | O22: =ROUND(I22*Assumptions!B85+E22*Assumptions!B86+W22*Assumptions!B85+ROUND(AB22*Assumptions!B137*Assumptions!B138*Assumptions!B139,0)*Assumptions!B86,0) -> 70 | P22: =K22+L22+M22+N22+O22+X22 -> 319 | Q22: =I22-P22 -> 725 | R22: =ROUND(AB22*Assumptions!B51*Assumptions!B52,0) -> 2220 | S22: =I22+R22+W22+AC22+AD22 -> 3554 | T22: =IF(U22<P22*3,0,IF(U22<P22*6,ROUND((Q22+R22+W22+AC22+AD22)*0.75*Assumptions!B113,0),ROUND((Q22+R22+W22+AC22+AD22)*0.75*Assumptions!B114,0))) -> 927 | U22: =U21+Q22+R22+W22+AC22+AD22 -> 17196 | V22: =IF(AB22>=Assumptions!B107,"Signal 6",IF(AB22>=Assumptions!B106,"Signal 5",IF(AB22>=Assumptions!B105,"Signal 4",IF(AB22>=Assumptions!B104,"Signal 3",IF(AB22>=Assumptions!B103,"Signal 2",IF(AB22>=Assumptions!B102,"Signal 1","Pre-Signal 1")))))) -> Pre-Signal 1 | W22: =ROUND(AB22*Assumptions!B137*Assumptions!B138*Assumptions!B139*Assumptions!B136,0) -> 247 | X22: =ROUND(AB22*Assumptions!B137*Assumptions!B65,0) -> 41 | Y22: =ROUND(Y21*(1+Assumptions!B165),0) -> 464 | Z22: =Assumptions!B157 -> 250 | AA22: =ROUND(Y22*Assumptions!B166,0) -> 1 | AB22: =B22+Z22+AA22 -> 6342.1591 | AC22: =ROUND(IF(A22>=Assumptions!B144,(IF(A22>=25,Assumptions!B151,IF(A22>=16,Assumptions!B150,Assumptions!B149))/1000*Assumptions!B146)+IF(A22>=Assumptions!B145,(IF(A22>=25,Assumptions!B151,IF(A22>=16,Assumptions!B150,Assumptions!B149))*Assumptions!B152/1000*Assumptions!B147),0),0),0) -> 43 | AD22: =IF(Y22>=10000,Assumptions!B170,IF(Y22>=5000,Assumptions!B169,IF(Y22>=2000,Assumptions!B168,IF(Y22>=500,Assumptions!B167,0)))) -> 0
A23: 18 | B23: =B22*(1+Assumptions!B34) -> 6822.0982 | C23: =ROUND(AB23*Assumptions!B25,0) -> 141 | D23: =ROUND(AB23*Assumptions!B23,0) -> 18 | E23: =E22+D23-F23 -> 104 | F23: =ROUND(E22*Assumptions!B44,0) -> 5 | G23: =D23-F23 -> 13 | H23: =ROUND(E23*(Assumptions!B15*0.85+Assumptions!B11*0.15),0) -> 1193 | I23: =H23 -> 1193 | J23: =ROUND(E23*Assumptions!B68,0) -> 364 | K23: =ROUND(J23*Assumptions!B65,0) -> 29 | L23: =Assumptions!B70+IF(E23>Assumptions!B72,45,0) -> 31 | M23: =Assumptions!B76+Assumptions!B77 -> 35 | N23: =Assumptions!B81+Assumptions!B82+Assumptions!B87/12+Assumptions!B148 -> 116 | O23: =ROUND(I23*Assumptions!B85+E23*Assumptions!B86+W23*Assumptions!B85+ROUND(AB23*Assumptions!B137*Assumptions!B138*Assumptions!B139,0)*Assumptions!B86,0) -> 80 | P23: =K23+L23+M23+N23+O23+X23 -> 336 | Q23: =I23-P23 -> 857 | R23: =ROUND(AB23*Assumptions!B51*Assumptions!B52,0) -> 2476 | S23: =I23+R23+W23+AC23+AD23 -> 3993 | T23: =IF(U23<P23*3,0,IF(U23<P23*6,ROUND((Q23+R23+W23+AC23+AD23)*0.75*Assumptions!B113,0),ROUND((Q23+R23+W23+AC23+AD23)*0.75*Assumptions!B114,0))) -> 1048 | U23: =U22+Q23+R23+W23+AC23+AD23 -> 20853 | V23: =IF(AB23>=Assumptions!B107,"Signal 6",IF(AB23>=Assumptions!B106,"Signal 5",IF(AB23>=Assumptions!B105,"Signal 4",IF(AB23>=Assumptions!B104,"Signal 3",IF(AB23>=Assumptions!B103,"Signal 2",IF(AB23>=Assumptions!B102,"Signal 1","Pre-Signal 1")))))) -> Pre-Signal 1 | W23: =ROUND(AB23*Assumptions!B137*Assumptions!B138*Assumptions!B139*Assumptions!B136,0) -> 276 | X23: =ROUND(AB23*Assumptions!B137*Assumptions!B65,0) -> 45 | Y23: =ROUND(Y22*(1+Assumptions!B165),0) -> 510 | Z23: =Assumptions!B157 -> 250 | AA23: =ROUND(Y23*Assumptions!B166,0) -> 2 | AB23: =B23+Z23+AA23 -> 7074.0982 | AC23: =ROUND(IF(A23>=Assumptions!B144,(IF(A23>=25,Assumptions!B151,IF(A23>=16,Assumptions!B150,Assumptions!B149))/1000*Assumptions!B146)+IF(A23>=Assumptions!B145,(IF(A23>=25,Assumptions!B151,IF(A23>=16,Assumptions!B150,Assumptions!B149))*Assumptions!B152/1000*Assumptions!B147),0),0),0) -> 43 | AD23: =IF(Y23>=10000,Assumptions!B170,IF(Y23>=5000,Assumptions!B169,IF(Y23>=2000,Assumptions!B168,IF(Y23>=500,Assumptions!B167,0)))) -> 5
A24: 19 | B24: =B23*(1+Assumptions!B34) -> 7640.75 | C24: =ROUND(AB24*Assumptions!B25,0) -> 158 | D24: =ROUND(AB24*Assumptions!B23,0) -> 20 | E24: =E23+D24-F24 -> 118 | F24: =ROUND(E23*Assumptions!B44,0) -> 6 | G24: =D24-F24 -> 14 | H24: =ROUND(E24*(Assumptions!B15*0.85+Assumptions!B11*0.15),0) -> 1354 | I24: =H24 -> 1354 | J24: =ROUND(E24*Assumptions!B68,0) -> 413 | K24: =ROUND(J24*Assumptions!B65,0) -> 33 | L24: =Assumptions!B70+IF(E24>Assumptions!B72,45,0) -> 31 | M24: =Assumptions!B76+Assumptions!B77 -> 35 | N24: =Assumptions!B81+Assumptions!B82+Assumptions!B87/12+Assumptions!B148 -> 116 | O24: =ROUND(I24*Assumptions!B85+E24*Assumptions!B86+W24*Assumptions!B85+ROUND(AB24*Assumptions!B137*Assumptions!B138*Assumptions!B139,0)*Assumptions!B86,0) -> 91 | P24: =K24+L24+M24+N24+O24+X24 -> 357 | Q24: =I24-P24 -> 997 | R24: =ROUND(AB24*Assumptions!B51*Assumptions!B52,0) -> 2762 | S24: =I24+R24+W24+AC24+AD24 -> 4472 | T24: =IF(U24<P24*3,0,IF(U24<P24*6,ROUND((Q24+R24+W24+AC24+AD24)*0.75*Assumptions!B113,0),ROUND((Q24+R24+W24+AC24+AD24)*0.75*Assumptions!B114,0))) -> 1179 | U24: =U23+Q24+R24+W24+AC24+AD24 -> 24968 | V24: =IF(AB24>=Assumptions!B107,"Signal 6",IF(AB24>=Assumptions!B106,"Signal 5",IF(AB24>=Assumptions!B105,"Signal 4",IF(AB24>=Assumptions!B104,"Signal 3",IF(AB24>=Assumptions!B103,"Signal 2",IF(AB24>=Assumptions!B102,"Signal 1","Pre-Signal 1")))))) -> Pre-Signal 1 | W24: =ROUND(AB24*Assumptions!B137*Assumptions!B138*Assumptions!B139*Assumptions!B136,0) -> 308 | X24: =ROUND(AB24*Assumptions!B137*Assumptions!B65,0) -> 51 | Y24: =ROUND(Y23*(1+Assumptions!B165),0) -> 561 | Z24: =Assumptions!B157 -> 250 | AA24: =ROUND(Y24*Assumptions!B166,0) -> 2 | AB24: =B24+Z24+AA24 -> 7892.75 | AC24: =ROUND(IF(A24>=Assumptions!B144,(IF(A24>=25,Assumptions!B151,IF(A24>=16,Assumptions!B150,Assumptions!B149))/1000*Assumptions!B146)+IF(A24>=Assumptions!B145,(IF(A24>=25,Assumptions!B151,IF(A24>=16,Assumptions!B150,Assumptions!B149))*Assumptions!B152/1000*Assumptions!B147),0),0),0) -> 43 | AD24: =IF(Y24>=10000,Assumptions!B170,IF(Y24>=5000,Assumptions!B169,IF(Y24>=2000,Assumptions!B168,IF(Y24>=500,Assumptions!B167,0)))) -> 5
A25: 20 | B25: =B24*(1+Assumptions!B34) -> 8557.64 | C25: =ROUND(AB25*Assumptions!B25,0) -> 176 | D25: =ROUND(AB25*Assumptions!B23,0) -> 22 | E25: =E24+D25-F25 -> 133 | F25: =ROUND(E24*Assumptions!B44,0) -> 7 | G25: =D25-F25 -> 15 | H25: =ROUND(E25*(Assumptions!B15*0.85+Assumptions!B11*0.15),0) -> 1526 | I25: =H25 -> 1526 | J25: =ROUND(E25*Assumptions!B68,0) -> 466 | K25: =ROUND(J25*Assumptions!B65,0) -> 37 | L25: =Assumptions!B70+IF(E25>Assumptions!B72,45,0) -> 31 | M25: =Assumptions!B76+Assumptions!B77 -> 35 | N25: =Assumptions!B81+Assumptions!B82+Assumptions!B87/12+Assumptions!B148 -> 116 | O25: =ROUND(I25*Assumptions!B85+E25*Assumptions!B86+W25*Assumptions!B85+ROUND(AB25*Assumptions!B137*Assumptions!B138*Assumptions!B139,0)*Assumptions!B86,0) -> 102 | P25: =K25+L25+M25+N25+O25+X25 -> 377 | Q25: =I25-P25 -> 1149 | R25: =ROUND(AB25*Assumptions!B51*Assumptions!B52,0) -> 3083 | S25: =I25+R25+W25+AC25+AD25 -> 5001 | T25: =IF(U25<P25*3,0,IF(U25<P25*6,ROUND((Q25+R25+W25+AC25+AD25)*0.75*Assumptions!B113,0),ROUND((Q25+R25+W25+AC25+AD25)*0.75*Assumptions!B114,0))) -> 1325 | U25: =U24+Q25+R25+W25+AC25+AD25 -> 29592 | V25: =IF(AB25>=Assumptions!B107,"Signal 6",IF(AB25>=Assumptions!B106,"Signal 5",IF(AB25>=Assumptions!B105,"Signal 4",IF(AB25>=Assumptions!B104,"Signal 3",IF(AB25>=Assumptions!B103,"Signal 2",IF(AB25>=Assumptions!B102,"Signal 1","Pre-Signal 1")))))) -> Pre-Signal 1 | W25: =ROUND(AB25*Assumptions!B137*Assumptions!B138*Assumptions!B139*Assumptions!B136,0) -> 344 | X25: =ROUND(AB25*Assumptions!B137*Assumptions!B65,0) -> 56 | Y25: =ROUND(Y24*(1+Assumptions!B165),0) -> 617 | Z25: =Assumptions!B157 -> 250 | AA25: =ROUND(Y25*Assumptions!B166,0) -> 2 | AB25: =B25+Z25+AA25 -> 8809.64 | AC25: =ROUND(IF(A25>=Assumptions!B144,(IF(A25>=25,Assumptions!B151,IF(A25>=16,Assumptions!B150,Assumptions!B149))/1000*Assumptions!B146)+IF(A25>=Assumptions!B145,(IF(A25>=25,Assumptions!B151,IF(A25>=16,Assumptions!B150,Assumptions!B149))*Assumptions!B152/1000*Assumptions!B147),0),0),0) -> 43 | AD25: =IF(Y25>=10000,Assumptions!B170,IF(Y25>=5000,Assumptions!B169,IF(Y25>=2000,Assumptions!B168,IF(Y25>=500,Assumptions!B167,0)))) -> 5
A26: 21 | B26: =B25*(1+Assumptions!B34) -> 9584.5568 | C26: =ROUND(AB26*Assumptions!B25,0) -> 197 | D26: =ROUND(AB26*Assumptions!B23,0) -> 25 | E26: =E25+D26-F26 -> 150 | F26: =ROUND(E25*Assumptions!B44,0) -> 8 | G26: =D26-F26 -> 17 | H26: =ROUND(E26*(Assumptions!B15*0.85+Assumptions!B11*0.15),0) -> 1721 | I26: =H26 -> 1721 | J26: =ROUND(E26*Assumptions!B68,0) -> 525 | K26: =ROUND(J26*Assumptions!B65,0) -> 42 | L26: =Assumptions!B70+IF(E26>Assumptions!B72,45,0) -> 31 | M26: =Assumptions!B76+Assumptions!B77 -> 35 | N26: =Assumptions!B81+Assumptions!B82+Assumptions!B87/12+Assumptions!B148 -> 116 | O26: =ROUND(I26*Assumptions!B85+E26*Assumptions!B86+W26*Assumptions!B85+ROUND(AB26*Assumptions!B137*Assumptions!B138*Assumptions!B139,0)*Assumptions!B86,0) -> 115 | P26: =K26+L26+M26+N26+O26+X26 -> 402 | Q26: =I26-P26 -> 1319 | R26: =ROUND(AB26*Assumptions!B51*Assumptions!B52,0) -> 3443 | S26: =I26+R26+W26+AC26+AD26 -> 5596 | T26: =IF(U26<P26*3,0,IF(U26<P26*6,ROUND((Q26+R26+W26+AC26+AD26)*0.75*Assumptions!B113,0),ROUND((Q26+R26+W26+AC26+AD26)*0.75*Assumptions!B114,0))) -> 1488 | U26: =U25+Q26+R26+W26+AC26+AD26 -> 34786 | V26: =IF(AB26>=Assumptions!B107,"Signal 6",IF(AB26>=Assumptions!B106,"Signal 5",IF(AB26>=Assumptions!B105,"Signal 4",IF(AB26>=Assumptions!B104,"Signal 3",IF(AB26>=Assumptions!B103,"Signal 2",IF(AB26>=Assumptions!B102,"Signal 1","Pre-Signal 1")))))) -> Pre-Signal 1 | W26: =ROUND(AB26*Assumptions!B137*Assumptions!B138*Assumptions!B139*Assumptions!B136,0) -> 384 | X26: =ROUND(AB26*Assumptions!B137*Assumptions!B65,0) -> 63 | Y26: =ROUND(Y25*(1+Assumptions!B165),0) -> 679 | Z26: =Assumptions!B157 -> 250 | AA26: =ROUND(Y26*Assumptions!B166,0) -> 2 | AB26: =B26+Z26+AA26 -> 9836.5568 | AC26: =ROUND(IF(A26>=Assumptions!B144,(IF(A26>=25,Assumptions!B151,IF(A26>=16,Assumptions!B150,Assumptions!B149))/1000*Assumptions!B146)+IF(A26>=Assumptions!B145,(IF(A26>=25,Assumptions!B151,IF(A26>=16,Assumptions!B150,Assumptions!B149))*Assumptions!B152/1000*Assumptions!B147),0),0),0) -> 43 | AD26: =IF(Y26>=10000,Assumptions!B170,IF(Y26>=5000,Assumptions!B169,IF(Y26>=2000,Assumptions!B168,IF(Y26>=500,Assumptions!B167,0)))) -> 5
A27: 22 | B27: =B26*(1+Assumptions!B34) -> 10734.704 | C27: =ROUND(AB27*Assumptions!B25,0) -> 220 | D27: =ROUND(AB27*Assumptions!B23,0) -> 27 | E27: =E26+D27-F27 -> 168 | F27: =ROUND(E26*Assumptions!B44,0) -> 9 | G27: =D27-F27 -> 18 | H27: =ROUND(E27*(Assumptions!B15*0.85+Assumptions!B11*0.15),0) -> 1928 | I27: =H27 -> 1928 | J27: =ROUND(E27*Assumptions!B68,0) -> 588 | K27: =ROUND(J27*Assumptions!B65,0) -> 47 | L27: =Assumptions!B70+IF(E27>Assumptions!B72,45,0) -> 31 | M27: =Assumptions!B76+Assumptions!B77 -> 35 | N27: =Assumptions!B81+Assumptions!B82+Assumptions!B87/12+Assumptions!B148 -> 116 | O27: =ROUND(I27*Assumptions!B85+E27*Assumptions!B86+W27*Assumptions!B85+ROUND(AB27*Assumptions!B137*Assumptions!B138*Assumptions!B139,0)*Assumptions!B86,0) -> 129 | P27: =K27+L27+M27+N27+O27+X27 -> 428 | Q27: =I27-P27 -> 1500 | R27: =ROUND(AB27*Assumptions!B51*Assumptions!B52,0) -> 3845 | S27: =I27+R27+W27+AC27+AD27 -> 6249 | T27: =IF(U27<P27*3,0,IF(U27<P27*6,ROUND((Q27+R27+W27+AC27+AD27)*0.75*Assumptions!B113,0),ROUND((Q27+R27+W27+AC27+AD27)*0.75*Assumptions!B114,0))) -> 1668 | U27: =U26+Q27+R27+W27+AC27+AD27 -> 40607 | V27: =IF(AB27>=Assumptions!B107,"Signal 6",IF(AB27>=Assumptions!B106,"Signal 5",IF(AB27>=Assumptions!B105,"Signal 4",IF(AB27>=Assumptions!B104,"Signal 3",IF(AB27>=Assumptions!B103,"Signal 2",IF(AB27>=Assumptions!B102,"Signal 1","Pre-Signal 1")))))) -> Signal 1 | W27: =ROUND(AB27*Assumptions!B137*Assumptions!B138*Assumptions!B139*Assumptions!B136,0) -> 428 | X27: =ROUND(AB27*Assumptions!B137*Assumptions!B65,0) -> 70 | Y27: =ROUND(Y26*(1+Assumptions!B165),0) -> 747 | Z27: =Assumptions!B157 -> 250 | AA27: =ROUND(Y27*Assumptions!B166,0) -> 2 | AB27: =B27+Z27+AA27 -> 10986.704 | AC27: =ROUND(IF(A27>=Assumptions!B144,(IF(A27>=25,Assumptions!B151,IF(A27>=16,Assumptions!B150,Assumptions!B149))/1000*Assumptions!B146)+IF(A27>=Assumptions!B145,(IF(A27>=25,Assumptions!B151,IF(A27>=16,Assumptions!B150,Assumptions!B149))*Assumptions!B152/1000*Assumptions!B147),0),0),0) -> 43 | AD27: =IF(Y27>=10000,Assumptions!B170,IF(Y27>=5000,Assumptions!B169,IF(Y27>=2000,Assumptions!B168,IF(Y27>=500,Assumptions!B167,0)))) -> 5
A28: 23 | B28: =B27*(1+Assumptions!B34) -> 12022.868 | C28: =ROUND(AB28*Assumptions!B25,0) -> 245 | D28: =ROUND(AB28*Assumptions!B23,0) -> 31 | E28: =E27+D28-F28 -> 189 | F28: =ROUND(E27*Assumptions!B44,0) -> 10 | G28: =D28-F28 -> 21 | H28: =ROUND(E28*(Assumptions!B15*0.85+Assumptions!B11*0.15),0) -> 2169 | I28: =H28 -> 2169 | J28: =ROUND(E28*Assumptions!B68,0) -> 662 | K28: =ROUND(J28*Assumptions!B65,0) -> 53 | L28: =Assumptions!B70+IF(E28>Assumptions!B72,45,0) -> 31 | M28: =Assumptions!B76+Assumptions!B77 -> 35 | N28: =Assumptions!B81+Assumptions!B82+Assumptions!B87/12+Assumptions!B148 -> 116 | O28: =ROUND(I28*Assumptions!B85+E28*Assumptions!B86+W28*Assumptions!B85+ROUND(AB28*Assumptions!B137*Assumptions!B138*Assumptions!B139,0)*Assumptions!B86,0) -> 145 | P28: =K28+L28+M28+N28+O28+X28 -> 459 | Q28: =I28-P28 -> 1710 | R28: =ROUND(AB28*Assumptions!B51*Assumptions!B52,0) -> 4296 | S28: =I28+R28+W28+AC28+AD28 -> 6992 | T28: =IF(U28<P28*3,0,IF(U28<P28*6,ROUND((Q28+R28+W28+AC28+AD28)*0.75*Assumptions!B113,0),ROUND((Q28+R28+W28+AC28+AD28)*0.75*Assumptions!B114,0))) -> 1872 | U28: =U27+Q28+R28+W28+AC28+AD28 -> 47140 | V28: =IF(AB28>=Assumptions!B107,"Signal 6",IF(AB28>=Assumptions!B106,"Signal 5",IF(AB28>=Assumptions!B105,"Signal 4",IF(AB28>=Assumptions!B104,"Signal 3",IF(AB28>=Assumptions!B103,"Signal 2",IF(AB28>=Assumptions!B102,"Signal 1","Pre-Signal 1")))))) -> Signal 1 | W28: =ROUND(AB28*Assumptions!B137*Assumptions!B138*Assumptions!B139*Assumptions!B136,0) -> 479 | X28: =ROUND(AB28*Assumptions!B137*Assumptions!B65,0) -> 79 | Y28: =ROUND(Y27*(1+Assumptions!B165),0) -> 822 | Z28: =Assumptions!B157 -> 250 | AA28: =ROUND(Y28*Assumptions!B166,0) -> 2 | AB28: =B28+Z28+AA28 -> 12274.868 | AC28: =ROUND(IF(A28>=Assumptions!B144,(IF(A28>=25,Assumptions!B151,IF(A28>=16,Assumptions!B150,Assumptions!B149))/1000*Assumptions!B146)+IF(A28>=Assumptions!B145,(IF(A28>=25,Assumptions!B151,IF(A28>=16,Assumptions!B150,Assumptions!B149))*Assumptions!B152/1000*Assumptions!B147),0),0),0) -> 43 | AD28: =IF(Y28>=10000,Assumptions!B170,IF(Y28>=5000,Assumptions!B169,IF(Y28>=2000,Assumptions!B168,IF(Y28>=500,Assumptions!B167,0)))) -> 5
A29: 24 | B29: =B28*(1+Assumptions!B34) -> 13465.612 | C29: =ROUND(AB29*Assumptions!B25,0) -> 274 | D29: =ROUND(AB29*Assumptions!B23,0) -> 34 | E29: =E28+D29-F29 -> 212 | F29: =ROUND(E28*Assumptions!B44,0) -> 11 | G29: =D29-F29 -> 23 | H29: =ROUND(E29*(Assumptions!B15*0.85+Assumptions!B11*0.15),0) -> 2433 | I29: =H29 -> 2433 | J29: =ROUND(E29*Assumptions!B68,0) -> 742 | K29: =ROUND(J29*Assumptions!B65,0) -> 59 | L29: =Assumptions!B70+IF(E29>Assumptions!B72,45,0) -> 31 | M29: =Assumptions!B76+Assumptions!B77 -> 35 | N29: =Assumptions!B81+Assumptions!B82+Assumptions!B87/12+Assumptions!B148 -> 116 | O29: =ROUND(I29*Assumptions!B85+E29*Assumptions!B86+W29*Assumptions!B85+ROUND(AB29*Assumptions!B137*Assumptions!B138*Assumptions!B139,0)*Assumptions!B86,0) -> 162 | P29: =K29+L29+M29+N29+O29+X29 -> 491 | Q29: =I29-P29 -> 1942 | R29: =ROUND(AB29*Assumptions!B51*Assumptions!B52,0) -> 4802 | S29: =I29+R29+W29+AC29+AD29 -> 7818 | T29: =IF(U29<P29*3,0,IF(U29<P29*6,ROUND((Q29+R29+W29+AC29+AD29)*0.75*Assumptions!B113,0),ROUND((Q29+R29+W29+AC29+AD29)*0.75*Assumptions!B114,0))) -> 2099 | U29: =U28+Q29+R29+W29+AC29+AD29 -> 54467 | V29: =IF(AB29>=Assumptions!B107,"Signal 6",IF(AB29>=Assumptions!B106,"Signal 5",IF(AB29>=Assumptions!B105,"Signal 4",IF(AB29>=Assumptions!B104,"Signal 3",IF(AB29>=Assumptions!B103,"Signal 2",IF(AB29>=Assumptions!B102,"Signal 1","Pre-Signal 1")))))) -> Signal 1 | W29: =ROUND(AB29*Assumptions!B137*Assumptions!B138*Assumptions!B139*Assumptions!B136,0) -> 535 | X29: =ROUND(AB29*Assumptions!B137*Assumptions!B65,0) -> 88 | Y29: =ROUND(Y28*(1+Assumptions!B165),0) -> 904 | Z29: =Assumptions!B157 -> 250 | AA29: =ROUND(Y29*Assumptions!B166,0) -> 3 | AB29: =B29+Z29+AA29 -> 13718.612 | AC29: =ROUND(IF(A29>=Assumptions!B144,(IF(A29>=25,Assumptions!B151,IF(A29>=16,Assumptions!B150,Assumptions!B149))/1000*Assumptions!B146)+IF(A29>=Assumptions!B145,(IF(A29>=25,Assumptions!B151,IF(A29>=16,Assumptions!B150,Assumptions!B149))*Assumptions!B152/1000*Assumptions!B147),0),0),0) -> 43 | AD29: =IF(Y29>=10000,Assumptions!B170,IF(Y29>=5000,Assumptions!B169,IF(Y29>=2000,Assumptions!B168,IF(Y29>=500,Assumptions!B167,0)))) -> 5
A30: 25 | B30: =B29*(1+Assumptions!B34) -> 15081.486 | C30: =ROUND(AB30*Assumptions!B25,0) -> 310 | D30: =ROUND(AB30*Assumptions!B23,0) -> 39 | E30: =E29+D30-F30 -> 238 | F30: =ROUND(E29*Assumptions!B44,0) -> 13 | G30: =D30-F30 -> 26 | H30: =ROUND(E30*(Assumptions!B15*0.85+Assumptions!B11*0.15),0) -> 2731 | I30: =H30 -> 2731 | J30: =ROUND(E30*Assumptions!B68,0) -> 833 | K30: =ROUND(J30*Assumptions!B65,0) -> 67 | L30: =Assumptions!B70+IF(E30>Assumptions!B72,45,0) -> 31 | M30: =Assumptions!B76+Assumptions!B77 -> 35 | N30: =Assumptions!B81+Assumptions!B82+Assumptions!B87/12+Assumptions!B148 -> 116 | O30: =ROUND(I30*Assumptions!B85+E30*Assumptions!B86+W30*Assumptions!B85+ROUND(AB30*Assumptions!B137*Assumptions!B138*Assumptions!B139,0)*Assumptions!B86,0) -> 182 | P30: =K30+L30+M30+N30+O30+X30 -> 530 | Q30: =I30-P30 -> 2201 | R30: =ROUND(AB30*Assumptions!B51*Assumptions!B52,0) -> 5420 | S30: =I30+R30+W30+AC30+AD30 -> 8836 | T30: =IF(U30<P30*3,0,IF(U30<P30*6,ROUND((Q30+R30+W30+AC30+AD30)*0.75*Assumptions!B113,0),ROUND((Q30+R30+W30+AC30+AD30)*0.75*Assumptions!B114,0))) -> 2380 | U30: =U29+Q30+R30+W30+AC30+AD30 -> 62773 | V30: =IF(AB30>=Assumptions!B107,"Signal 6",IF(AB30>=Assumptions!B106,"Signal 5",IF(AB30>=Assumptions!B105,"Signal 4",IF(AB30>=Assumptions!B104,"Signal 3",IF(AB30>=Assumptions!B103,"Signal 2",IF(AB30>=Assumptions!B102,"Signal 1","Pre-Signal 1")))))) -> Signal 1 | W30: =ROUND(AB30*Assumptions!B137*Assumptions!B138*Assumptions!B139*Assumptions!B136,0) -> 604 | X30: =ROUND(AB30*Assumptions!B137*Assumptions!B65,0) -> 99 | Y30: =ROUND(Y29*(1+Assumptions!B165),0) -> 994 | Z30: =Assumptions!B158 -> 400 | AA30: =ROUND(Y30*Assumptions!B166,0) -> 3 | AB30: =B30+Z30+AA30 -> 15484.486 | AC30: =ROUND(IF(A30>=Assumptions!B144,(IF(A30>=25,Assumptions!B151,IF(A30>=16,Assumptions!B150,Assumptions!B149))/1000*Assumptions!B146)+IF(A30>=Assumptions!B145,(IF(A30>=25,Assumptions!B151,IF(A30>=16,Assumptions!B150,Assumptions!B149))*Assumptions!B152/1000*Assumptions!B147),0),0),0) -> 76 | AD30: =IF(Y30>=10000,Assumptions!B170,IF(Y30>=5000,Assumptions!B169,IF(Y30>=2000,Assumptions!B168,IF(Y30>=500,Assumptions!B167,0)))) -> 5
A31: 26 | B31: =B30*(1+Assumptions!B34) -> 16891.264 | C31: =ROUND(AB31*Assumptions!B25,0) -> 346 | D31: =ROUND(AB31*Assumptions!B23,0) -> 43 | E31: =E30+D31-F31 -> 267 | F31: =ROUND(E30*Assumptions!B44,0) -> 14 | G31: =D31-F31 -> 29 | H31: =ROUND(E31*(Assumptions!B15*0.85+Assumptions!B11*0.15),0) -> 3064 | I31: =H31 -> 3064 | J31: =ROUND(E31*Assumptions!B68,0) -> 935 | K31: =ROUND(J31*Assumptions!B65,0) -> 75 | L31: =Assumptions!B70+IF(E31>Assumptions!B72,45,0) -> 31 | M31: =Assumptions!B76+Assumptions!B77 -> 35 | N31: =Assumptions!B81+Assumptions!B82+Assumptions!B87/12+Assumptions!B148 -> 116 | O31: =ROUND(I31*Assumptions!B85+E31*Assumptions!B86+W31*Assumptions!B85+ROUND(AB31*Assumptions!B137*Assumptions!B138*Assumptions!B139,0)*Assumptions!B86,0) -> 204 | P31: =K31+L31+M31+N31+O31+X31 -> 572 | Q31: =I31-P31 -> 2492 | R31: =ROUND(AB31*Assumptions!B51*Assumptions!B52,0) -> 6053 | S31: =I31+R31+W31+AC31+AD31 -> 9872 | T31: =IF(U31<P31*3,0,IF(U31<P31*6,ROUND((Q31+R31+W31+AC31+AD31)*0.75*Assumptions!B113,0),ROUND((Q31+R31+W31+AC31+AD31)*0.75*Assumptions!B114,0))) -> 2664 | U31: =U30+Q31+R31+W31+AC31+AD31 -> 72073 | V31: =IF(AB31>=Assumptions!B107,"Signal 6",IF(AB31>=Assumptions!B106,"Signal 5",IF(AB31>=Assumptions!B105,"Signal 4",IF(AB31>=Assumptions!B104,"Signal 3",IF(AB31>=Assumptions!B103,"Signal 2",IF(AB31>=Assumptions!B102,"Signal 1","Pre-Signal 1")))))) -> Signal 1 | W31: =ROUND(AB31*Assumptions!B137*Assumptions!B138*Assumptions!B139*Assumptions!B136,0) -> 674 | X31: =ROUND(AB31*Assumptions!B137*Assumptions!B65,0) -> 111 | Y31: =ROUND(Y30*(1+Assumptions!B165),0) -> 1093 | Z31: =Assumptions!B158 -> 400 | AA31: =ROUND(Y31*Assumptions!B166,0) -> 3 | AB31: =B31+Z31+AA31 -> 17294.264 | AC31: =ROUND(IF(A31>=Assumptions!B144,(IF(A31>=25,Assumptions!B151,IF(A31>=16,Assumptions!B150,Assumptions!B149))/1000*Assumptions!B146)+IF(A31>=Assumptions!B145,(IF(A31>=25,Assumptions!B151,IF(A31>=16,Assumptions!B150,Assumptions!B149))*Assumptions!B152/1000*Assumptions!B147),0),0),0) -> 76 | AD31: =IF(Y31>=10000,Assumptions!B170,IF(Y31>=5000,Assumptions!B169,IF(Y31>=2000,Assumptions!B168,IF(Y31>=500,Assumptions!B167,0)))) -> 5
A32: 27 | B32: =B31*(1+Assumptions!B34) -> 18918.216 | C32: =ROUND(AB32*Assumptions!B25,0) -> 386 | D32: =ROUND(AB32*Assumptions!B23,0) -> 48 | E32: =E31+D32-F32 -> 299 | F32: =ROUND(E31*Assumptions!B44,0) -> 16 | G32: =D32-F32 -> 32 | H32: =ROUND(E32*(Assumptions!B15*0.85+Assumptions!B11*0.15),0) -> 3431 | I32: =H32 -> 3431 | J32: =ROUND(E32*Assumptions!B68,0) -> 1047 | K32: =ROUND(J32*Assumptions!B65,0) -> 84 | L32: =Assumptions!B70+IF(E32>Assumptions!B72,45,0) -> 31 | M32: =Assumptions!B76+Assumptions!B77 -> 35 | N32: =Assumptions!B81+Assumptions!B82+Assumptions!B87/12+Assumptions!B148 -> 116 | O32: =ROUND(I32*Assumptions!B85+E32*Assumptions!B86+W32*Assumptions!B85+ROUND(AB32*Assumptions!B137*Assumptions!B138*Assumptions!B139,0)*Assumptions!B86,0) -> 228 | P32: =K32+L32+M32+N32+O32+X32 -> 618 | Q32: =I32-P32 -> 2813 | R32: =ROUND(AB32*Assumptions!B51*Assumptions!B52,0) -> 6763 | S32: =I32+R32+W32+AC32+AD32 -> 11029 | T32: =IF(U32<P32*3,0,IF(U32<P32*6,ROUND((Q32+R32+W32+AC32+AD32)*0.75*Assumptions!B113,0),ROUND((Q32+R32+W32+AC32+AD32)*0.75*Assumptions!B114,0))) -> 2983 | U32: =U31+Q32+R32+W32+AC32+AD32 -> 82484 | V32: =IF(AB32>=Assumptions!B107,"Signal 6",IF(AB32>=Assumptions!B106,"Signal 5",IF(AB32>=Assumptions!B105,"Signal 4",IF(AB32>=Assumptions!B104,"Signal 3",IF(AB32>=Assumptions!B103,"Signal 2",IF(AB32>=Assumptions!B102,"Signal 1","Pre-Signal 1")))))) -> Signal 1 | W32: =ROUND(AB32*Assumptions!B137*Assumptions!B138*Assumptions!B139*Assumptions!B136,0) -> 754 | X32: =ROUND(AB32*Assumptions!B137*Assumptions!B65,0) -> 124 | Y32: =ROUND(Y31*(1+Assumptions!B165),0) -> 1202 | Z32: =Assumptions!B158 -> 400 | AA32: =ROUND(Y32*Assumptions!B166,0) -> 4 | AB32: =B32+Z32+AA32 -> 19322.216 | AC32: =ROUND(IF(A32>=Assumptions!B144,(IF(A32>=25,Assumptions!B151,IF(A32>=16,Assumptions!B150,Assumptions!B149))/1000*Assumptions!B146)+IF(A32>=Assumptions!B145,(IF(A32>=25,Assumptions!B151,IF(A32>=16,Assumptions!B150,Assumptions!B149))*Assumptions!B152/1000*Assumptions!B147),0),0),0) -> 76 | AD32: =IF(Y32>=10000,Assumptions!B170,IF(Y32>=5000,Assumptions!B169,IF(Y32>=2000,Assumptions!B168,IF(Y32>=500,Assumptions!B167,0)))) -> 5
A33: 28 | B33: =B32*(1+Assumptions!B34) -> 21188.402 | C33: =ROUND(AB33*Assumptions!B25,0) -> 432 | D33: =ROUND(AB33*Assumptions!B23,0) -> 54 | E33: =E32+D33-F33 -> 335 | F33: =ROUND(E32*Assumptions!B44,0) -> 18 | G33: =D33-F33 -> 36 | H33: =ROUND(E33*(Assumptions!B15*0.85+Assumptions!B11*0.15),0) -> 3844 | I33: =H33 -> 3844 | J33: =ROUND(E33*Assumptions!B68,0) -> 1173 | K33: =ROUND(J33*Assumptions!B65,0) -> 94 | L33: =Assumptions!B70+IF(E33>Assumptions!B72,45,0) -> 31 | M33: =Assumptions!B76+Assumptions!B77 -> 35 | N33: =Assumptions!B81+Assumptions!B82+Assumptions!B87/12+Assumptions!B148 -> 116 | O33: =ROUND(I33*Assumptions!B85+E33*Assumptions!B86+W33*Assumptions!B85+ROUND(AB33*Assumptions!B137*Assumptions!B138*Assumptions!B139,0)*Assumptions!B86,0) -> 256 | P33: =K33+L33+M33+N33+O33+X33 -> 670 | Q33: =I33-P33 -> 3174 | R33: =ROUND(AB33*Assumptions!B51*Assumptions!B52,0) -> 7557 | S33: =I33+R33+W33+AC33+AD33 -> 12324 | T33: =IF(U33<P33*3,0,IF(U33<P33*6,ROUND((Q33+R33+W33+AC33+AD33)*0.75*Assumptions!B113,0),ROUND((Q33+R33+W33+AC33+AD33)*0.75*Assumptions!B114,0))) -> 3339 | U33: =U32+Q33+R33+W33+AC33+AD33 -> 94138 | V33: =IF(AB33>=Assumptions!B107,"Signal 6",IF(AB33>=Assumptions!B106,"Signal 5",IF(AB33>=Assumptions!B105,"Signal 4",IF(AB33>=Assumptions!B104,"Signal 3",IF(AB33>=Assumptions!B103,"Signal 2",IF(AB33>=Assumptions!B102,"Signal 1","Pre-Signal 1")))))) -> Signal 1 | W33: =ROUND(AB33*Assumptions!B137*Assumptions!B138*Assumptions!B139*Assumptions!B136,0) -> 842 | X33: =ROUND(AB33*Assumptions!B137*Assumptions!B65,0) -> 138 | Y33: =ROUND(Y32*(1+Assumptions!B165),0) -> 1322 | Z33: =Assumptions!B158 -> 400 | AA33: =ROUND(Y33*Assumptions!B166,0) -> 4 | AB33: =B33+Z33+AA33 -> 21592.402 | AC33: =ROUND(IF(A33>=Assumptions!B144,(IF(A33>=25,Assumptions!B151,IF(A33>=16,Assumptions!B150,Assumptions!B149))/1000*Assumptions!B146)+IF(A33>=Assumptions!B145,(IF(A33>=25,Assumptions!B151,IF(A33>=16,Assumptions!B150,Assumptions!B149))*Assumptions!B152/1000*Assumptions!B147),0),0),0) -> 76 | AD33: =IF(Y33>=10000,Assumptions!B170,IF(Y33>=5000,Assumptions!B169,IF(Y33>=2000,Assumptions!B168,IF(Y33>=500,Assumptions!B167,0)))) -> 5
A34: 29 | B34: =B33*(1+Assumptions!B34) -> 23731.01 | C34: =ROUND(AB34*Assumptions!B25,0) -> 483 | D34: =ROUND(AB34*Assumptions!B23,0) -> 60 | E34: =E33+D34-F34 -> 375 | F34: =ROUND(E33*Assumptions!B44,0) -> 20 | G34: =D34-F34 -> 40 | H34: =ROUND(E34*(Assumptions!B15*0.85+Assumptions!B11*0.15),0) -> 4303 | I34: =H34 -> 4303 | J34: =ROUND(E34*Assumptions!B68,0) -> 1313 | K34: =ROUND(J34*Assumptions!B65,0) -> 105 | L34: =Assumptions!B70+IF(E34>Assumptions!B72,45,0) -> 31 | M34: =Assumptions!B76+Assumptions!B77 -> 35 | N34: =Assumptions!B81+Assumptions!B82+Assumptions!B87/12+Assumptions!B148 -> 116 | O34: =ROUND(I34*Assumptions!B85+E34*Assumptions!B86+W34*Assumptions!B85+ROUND(AB34*Assumptions!B137*Assumptions!B138*Assumptions!B139,0)*Assumptions!B86,0) -> 286 | P34: =K34+L34+M34+N34+O34+X34 -> 727 | Q34: =I34-P34 -> 3576 | R34: =ROUND(AB34*Assumptions!B51*Assumptions!B52,0) -> 8447 | S34: =I34+R34+W34+AC34+AD34 -> 13772 | T34: =IF(U34<P34*3,0,IF(U34<P34*6,ROUND((Q34+R34+W34+AC34+AD34)*0.75*Assumptions!B113,0),ROUND((Q34+R34+W34+AC34+AD34)*0.75*Assumptions!B114,0))) -> 3737 | U34: =U33+Q34+R34+W34+AC34+AD34 -> 107183 | V34: =IF(AB34>=Assumptions!B107,"Signal 6",IF(AB34>=Assumptions!B106,"Signal 5",IF(AB34>=Assumptions!B105,"Signal 4",IF(AB34>=Assumptions!B104,"Signal 3",IF(AB34>=Assumptions!B103,"Signal 2",IF(AB34>=Assumptions!B102,"Signal 1","Pre-Signal 1")))))) -> Signal 1 | W34: =ROUND(AB34*Assumptions!B137*Assumptions!B138*Assumptions!B139*Assumptions!B136,0) -> 941 | X34: =ROUND(AB34*Assumptions!B137*Assumptions!B65,0) -> 154 | Y34: =ROUND(Y33*(1+Assumptions!B165),0) -> 1454 | Z34: =Assumptions!B158 -> 400 | AA34: =ROUND(Y34*Assumptions!B166,0) -> 4 | AB34: =B34+Z34+AA34 -> 24135.01 | AC34: =ROUND(IF(A34>=Assumptions!B144,(IF(A34>=25,Assumptions!B151,IF(A34>=16,Assumptions!B150,Assumptions!B149))/1000*Assumptions!B146)+IF(A34>=Assumptions!B145,(IF(A34>=25,Assumptions!B151,IF(A34>=16,Assumptions!B150,Assumptions!B149))*Assumptions!B152/1000*Assumptions!B147),0),0),0) -> 76 | AD34: =IF(Y34>=10000,Assumptions!B170,IF(Y34>=5000,Assumptions!B169,IF(Y34>=2000,Assumptions!B168,IF(Y34>=500,Assumptions!B167,0)))) -> 5
A35: 30 | B35: =B34*(1+Assumptions!B34) -> 26578.731 | C35: =ROUND(AB35*Assumptions!B25,0) -> 540 | D35: =ROUND(AB35*Assumptions!B23,0) -> 67 | E35: =E34+D35-F35 -> 419 | F35: =ROUND(E34*Assumptions!B44,0) -> 23 | G35: =D35-F35 -> 44 | H35: =ROUND(E35*(Assumptions!B15*0.85+Assumptions!B11*0.15),0) -> 4808 | I35: =H35 -> 4808 | J35: =ROUND(E35*Assumptions!B68,0) -> 1467 | K35: =ROUND(J35*Assumptions!B65,0) -> 117 | L35: =Assumptions!B70+IF(E35>Assumptions!B72,45,0) -> 31 | M35: =Assumptions!B76+Assumptions!B77 -> 35 | N35: =Assumptions!B81+Assumptions!B82+Assumptions!B87/12+Assumptions!B148 -> 116 | O35: =ROUND(I35*Assumptions!B85+E35*Assumptions!B86+W35*Assumptions!B85+ROUND(AB35*Assumptions!B137*Assumptions!B138*Assumptions!B139,0)*Assumptions!B86,0) -> 320 | P35: =K35+L35+M35+N35+O35+X35 -> 792 | Q35: =I35-P35 -> 4016 | R35: =ROUND(AB35*Assumptions!B51*Assumptions!B52,0) -> 9444 | S35: =I35+R35+W35+AC35+AD35 -> 15385 | T35: =IF(U35<P35*3,0,IF(U35<P35*6,ROUND((Q35+R35+W35+AC35+AD35)*0.75*Assumptions!B113,0),ROUND((Q35+R35+W35+AC35+AD35)*0.75*Assumptions!B114,0))) -> 4181 | U35: =U34+Q35+R35+W35+AC35+AD35 -> 121776 | V35: =IF(AB35>=Assumptions!B107,"Signal 6",IF(AB35>=Assumptions!B106,"Signal 5",IF(AB35>=Assumptions!B105,"Signal 4",IF(AB35>=Assumptions!B104,"Signal 3",IF(AB35>=Assumptions!B103,"Signal 2",IF(AB35>=Assumptions!B102,"Signal 1","Pre-Signal 1")))))) -> Signal 2 | W35: =ROUND(AB35*Assumptions!B137*Assumptions!B138*Assumptions!B139*Assumptions!B136,0) -> 1052 | X35: =ROUND(AB35*Assumptions!B137*Assumptions!B65,0) -> 173 | Y35: =ROUND(Y34*(1+Assumptions!B165),0) -> 1599 | Z35: =Assumptions!B158 -> 400 | AA35: =ROUND(Y35*Assumptions!B166,0) -> 5 | AB35: =B35+Z35+AA35 -> 26983.731 | AC35: =ROUND(IF(A35>=Assumptions!B144,(IF(A35>=25,Assumptions!B151,IF(A35>=16,Assumptions!B150,Assumptions!B149))/1000*Assumptions!B146)+IF(A35>=Assumptions!B145,(IF(A35>=25,Assumptions!B151,IF(A35>=16,Assumptions!B150,Assumptions!B149))*Assumptions!B152/1000*Assumptions!B147),0),0),0) -> 76 | AD35: =IF(Y35>=10000,Assumptions!B170,IF(Y35>=5000,Assumptions!B169,IF(Y35>=2000,Assumptions!B168,IF(Y35>=500,Assumptions!B167,0)))) -> 5
A36: 31 | B36: =B35*(1+Assumptions!B34) -> 29768.179 | C36: =ROUND(AB36*Assumptions!B25,0) -> 603 | D36: =ROUND(AB36*Assumptions!B23,0) -> 75 | E36: =E35+D36-F36 -> 469 | F36: =ROUND(E35*Assumptions!B44,0) -> 25 | G36: =D36-F36 -> 50 | H36: =ROUND(E36*(Assumptions!B15*0.85+Assumptions!B11*0.15),0) -> 5382 | I36: =H36 -> 5382 | J36: =ROUND(E36*Assumptions!B68,0) -> 1642 | K36: =ROUND(J36*Assumptions!B65,0) -> 131 | L36: =Assumptions!B70+IF(E36>Assumptions!B72,45,0) -> 31 | M36: =Assumptions!B76+Assumptions!B77 -> 35 | N36: =Assumptions!B81+Assumptions!B82+Assumptions!B87/12+Assumptions!B148 -> 116 | O36: =ROUND(I36*Assumptions!B85+E36*Assumptions!B86+W36*Assumptions!B85+ROUND(AB36*Assumptions!B137*Assumptions!B138*Assumptions!B139,0)*Assumptions!B86,0) -> 358 | P36: =K36+L36+M36+N36+O36+X36 -> 864 | Q36: =I36-P36 -> 4518 | R36: =ROUND(AB36*Assumptions!B51*Assumptions!B52,0) -> 10561 | S36: =I36+R36+W36+AC36+AD36 -> 17201 | T36: =IF(U36<P36*3,0,IF(U36<P36*6,ROUND((Q36+R36+W36+AC36+AD36)*0.75*Assumptions!B113,0),ROUND((Q36+R36+W36+AC36+AD36)*0.75*Assumptions!B114,0))) -> 4681 | U36: =U35+Q36+R36+W36+AC36+AD36 -> 138113 | V36: =IF(AB36>=Assumptions!B107,"Signal 6",IF(AB36>=Assumptions!B106,"Signal 5",IF(AB36>=Assumptions!B105,"Signal 4",IF(AB36>=Assumptions!B104,"Signal 3",IF(AB36>=Assumptions!B103,"Signal 2",IF(AB36>=Assumptions!B102,"Signal 1","Pre-Signal 1")))))) -> Signal 2 | W36: =ROUND(AB36*Assumptions!B137*Assumptions!B138*Assumptions!B139*Assumptions!B136,0) -> 1177 | X36: =ROUND(AB36*Assumptions!B137*Assumptions!B65,0) -> 193 | Y36: =ROUND(Y35*(1+Assumptions!B165),0) -> 1759 | Z36: =Assumptions!B158 -> 400 | AA36: =ROUND(Y36*Assumptions!B166,0) -> 5 | AB36: =B36+Z36+AA36 -> 30173.179 | AC36: =ROUND(IF(A36>=Assumptions!B144,(IF(A36>=25,Assumptions!B151,IF(A36>=16,Assumptions!B150,Assumptions!B149))/1000*Assumptions!B146)+IF(A36>=Assumptions!B145,(IF(A36>=25,Assumptions!B151,IF(A36>=16,Assumptions!B150,Assumptions!B149))*Assumptions!B152/1000*Assumptions!B147),0),0),0) -> 76 | AD36: =IF(Y36>=10000,Assumptions!B170,IF(Y36>=5000,Assumptions!B169,IF(Y36>=2000,Assumptions!B168,IF(Y36>=500,Assumptions!B167,0)))) -> 5
A37: 32 | B37: =B36*(1+Assumptions!B34) -> 33340.36 | C37: =ROUND(AB37*Assumptions!B25,0) -> 675 | D37: =ROUND(AB37*Assumptions!B23,0) -> 84 | E37: =E36+D37-F37 -> 525 | F37: =ROUND(E36*Assumptions!B44,0) -> 28 | G37: =D37-F37 -> 56 | H37: =ROUND(E37*(Assumptions!B15*0.85+Assumptions!B11*0.15),0) -> 6024 | I37: =H37 -> 6024 | J37: =ROUND(E37*Assumptions!B68,0) -> 1838 | K37: =ROUND(J37*Assumptions!B65,0) -> 147 | L37: =Assumptions!B70+IF(E37>Assumptions!B72,45,0) -> 76 | M37: =Assumptions!B76+Assumptions!B77 -> 35 | N37: =Assumptions!B81+Assumptions!B82+Assumptions!B87/12+Assumptions!B148 -> 116 | O37: =ROUND(I37*Assumptions!B85+E37*Assumptions!B86+W37*Assumptions!B85+ROUND(AB37*Assumptions!B137*Assumptions!B138*Assumptions!B139,0)*Assumptions!B86,0) -> 401 | P37: =K37+L37+M37+N37+O37+X37 -> 991 | Q37: =I37-P37 -> 5033 | R37: =ROUND(AB37*Assumptions!B51*Assumptions!B52,0) -> 11811 | S37: =I37+R37+W37+AC37+AD37 -> 19232 | T37: =IF(U37<P37*3,0,IF(U37<P37*6,ROUND((Q37+R37+W37+AC37+AD37)*0.75*Assumptions!B113,0),ROUND((Q37+R37+W37+AC37+AD37)*0.75*Assumptions!B114,0))) -> 5226 | U37: =U36+Q37+R37+W37+AC37+AD37 -> 156354 | V37: =IF(AB37>=Assumptions!B107,"Signal 6",IF(AB37>=Assumptions!B106,"Signal 5",IF(AB37>=Assumptions!B105,"Signal 4",IF(AB37>=Assumptions!B104,"Signal 3",IF(AB37>=Assumptions!B103,"Signal 2",IF(AB37>=Assumptions!B102,"Signal 1","Pre-Signal 1")))))) -> Signal 2 | W37: =ROUND(AB37*Assumptions!B137*Assumptions!B138*Assumptions!B139*Assumptions!B136,0) -> 1316 | X37: =ROUND(AB37*Assumptions!B137*Assumptions!B65,0) -> 216 | Y37: =ROUND(Y36*(1+Assumptions!B165),0) -> 1935 | Z37: =Assumptions!B158 -> 400 | AA37: =ROUND(Y37*Assumptions!B166,0) -> 6 | AB37: =B37+Z37+AA37 -> 33746.36 | AC37: =ROUND(IF(A37>=Assumptions!B144,(IF(A37>=25,Assumptions!B151,IF(A37>=16,Assumptions!B150,Assumptions!B149))/1000*Assumptions!B146)+IF(A37>=Assumptions!B145,(IF(A37>=25,Assumptions!B151,IF(A37>=16,Assumptions!B150,Assumptions!B149))*Assumptions!B152/1000*Assumptions!B147),0),0),0) -> 76 | AD37: =IF(Y37>=10000,Assumptions!B170,IF(Y37>=5000,Assumptions!B169,IF(Y37>=2000,Assumptions!B168,IF(Y37>=500,Assumptions!B167,0)))) -> 5
A38: 33 | B38: =B37*(1+Assumptions!B34) -> 37341.203 | C38: =ROUND(AB38*Assumptions!B25,0) -> 755 | D38: =ROUND(AB38*Assumptions!B23,0) -> 94 | E38: =E37+D38-F38 -> 587 | F38: =ROUND(E37*Assumptions!B44,0) -> 32 | G38: =D38-F38 -> 62 | H38: =ROUND(E38*(Assumptions!B15*0.85+Assumptions!B11*0.15),0) -> 6736 | I38: =H38 -> 6736 | J38: =ROUND(E38*Assumptions!B68,0) -> 2055 | K38: =ROUND(J38*Assumptions!B65,0) -> 164 | L38: =Assumptions!B70+IF(E38>Assumptions!B72,45,0) -> 76 | M38: =Assumptions!B76+Assumptions!B77 -> 35 | N38: =Assumptions!B81+Assumptions!B82+Assumptions!B87/12+Assumptions!B148 -> 116 | O38: =ROUND(I38*Assumptions!B85+E38*Assumptions!B86+W38*Assumptions!B85+ROUND(AB38*Assumptions!B137*Assumptions!B138*Assumptions!B139,0)*Assumptions!B86,0) -> 448 | P38: =K38+L38+M38+N38+O38+X38 -> 1081 | Q38: =I38-P38 -> 5655 | R38: =ROUND(AB38*Assumptions!B51*Assumptions!B52,0) -> 13212 | S38: =I38+R38+W38+AC38+AD38 -> 21516 | T38: =IF(U38<P38*3,0,IF(U38<P38*6,ROUND((Q38+R38+W38+AC38+AD38)*0.75*Assumptions!B113,0),ROUND((Q38+R38+W38+AC38+AD38)*0.75*Assumptions!B114,0))) -> 5855 | U38: =U37+Q38+R38+W38+AC38+AD38 -> 176789 | V38: =IF(AB38>=Assumptions!B107,"Signal 6",IF(AB38>=Assumptions!B106,"Signal 5",IF(AB38>=Assumptions!B105,"Signal 4",IF(AB38>=Assumptions!B104,"Signal 3",IF(AB38>=Assumptions!B103,"Signal 2",IF(AB38>=Assumptions!B102,"Signal 1","Pre-Signal 1")))))) -> Signal 2 | W38: =ROUND(AB38*Assumptions!B137*Assumptions!B138*Assumptions!B139*Assumptions!B136,0) -> 1472 | X38: =ROUND(AB38*Assumptions!B137*Assumptions!B65,0) -> 242 | Y38: =ROUND(Y37*(1+Assumptions!B165),0) -> 2129 | Z38: =Assumptions!B158 -> 400 | AA38: =ROUND(Y38*Assumptions!B166,0) -> 6 | AB38: =B38+Z38+AA38 -> 37747.203 | AC38: =ROUND(IF(A38>=Assumptions!B144,(IF(A38>=25,Assumptions!B151,IF(A38>=16,Assumptions!B150,Assumptions!B149))/1000*Assumptions!B146)+IF(A38>=Assumptions!B145,(IF(A38>=25,Assumptions!B151,IF(A38>=16,Assumptions!B150,Assumptions!B149))*Assumptions!B152/1000*Assumptions!B147),0),0),0) -> 76 | AD38: =IF(Y38>=10000,Assumptions!B170,IF(Y38>=5000,Assumptions!B169,IF(Y38>=2000,Assumptions!B168,IF(Y38>=500,Assumptions!B167,0)))) -> 20
A39: 34 | B39: =B38*(1+Assumptions!B34) -> 41822.148 | C39: =ROUND(AB39*Assumptions!B25,0) -> 845 | D39: =ROUND(AB39*Assumptions!B23,0) -> 106 | E39: =E38+D39-F39 -> 658 | F39: =ROUND(E38*Assumptions!B44,0) -> 35 | G39: =D39-F39 -> 71 | H39: =ROUND(E39*(Assumptions!B15*0.85+Assumptions!B11*0.15),0) -> 7551 | I39: =H39 -> 7551 | J39: =ROUND(E39*Assumptions!B68,0) -> 2303 | K39: =ROUND(J39*Assumptions!B65,0) -> 184 | L39: =Assumptions!B70+IF(E39>Assumptions!B72,45,0) -> 76 | M39: =Assumptions!B76+Assumptions!B77 -> 35 | N39: =Assumptions!B81+Assumptions!B82+Assumptions!B87/12+Assumptions!B148 -> 116 | O39: =ROUND(I39*Assumptions!B85+E39*Assumptions!B86+W39*Assumptions!B85+ROUND(AB39*Assumptions!B137*Assumptions!B138*Assumptions!B139,0)*Assumptions!B86,0) -> 502 | P39: =K39+L39+M39+N39+O39+X39 -> 1183 | Q39: =I39-P39 -> 6368 | R39: =ROUND(AB39*Assumptions!B51*Assumptions!B52,0) -> 14780 | S39: =I39+R39+W39+AC39+AD39 -> 24074 | T39: =IF(U39<P39*3,0,IF(U39<P39*6,ROUND((Q39+R39+W39+AC39+AD39)*0.75*Assumptions!B113,0),ROUND((Q39+R39+W39+AC39+AD39)*0.75*Assumptions!B114,0))) -> 6558 | U39: =U38+Q39+R39+W39+AC39+AD39 -> 199680 | V39: =IF(AB39>=Assumptions!B107,"Signal 6",IF(AB39>=Assumptions!B106,"Signal 5",IF(AB39>=Assumptions!B105,"Signal 4",IF(AB39>=Assumptions!B104,"Signal 3",IF(AB39>=Assumptions!B103,"Signal 2",IF(AB39>=Assumptions!B102,"Signal 1","Pre-Signal 1")))))) -> Signal 3 | W39: =ROUND(AB39*Assumptions!B137*Assumptions!B138*Assumptions!B139*Assumptions!B136,0) -> 1647 | X39: =ROUND(AB39*Assumptions!B137*Assumptions!B65,0) -> 270 | Y39: =ROUND(Y38*(1+Assumptions!B165),0) -> 2342 | Z39: =Assumptions!B158 -> 400 | AA39: =ROUND(Y39*Assumptions!B166,0) -> 7 | AB39: =B39+Z39+AA39 -> 42229.148 | AC39: =ROUND(IF(A39>=Assumptions!B144,(IF(A39>=25,Assumptions!B151,IF(A39>=16,Assumptions!B150,Assumptions!B149))/1000*Assumptions!B146)+IF(A39>=Assumptions!B145,(IF(A39>=25,Assumptions!B151,IF(A39>=16,Assumptions!B150,Assumptions!B149))*Assumptions!B152/1000*Assumptions!B147),0),0),0) -> 76 | AD39: =IF(Y39>=10000,Assumptions!B170,IF(Y39>=5000,Assumptions!B169,IF(Y39>=2000,Assumptions!B168,IF(Y39>=500,Assumptions!B167,0)))) -> 20
A40: 35 | B40: =B39*(1+Assumptions!B34) -> 46840.805 | C40: =ROUND(AB40*Assumptions!B25,0) -> 945 | D40: =ROUND(AB40*Assumptions!B23,0) -> 118 | E40: =E39+D40-F40 -> 737 | F40: =ROUND(E39*Assumptions!B44,0) -> 39 | G40: =D40-F40 -> 79 | H40: =ROUND(E40*(Assumptions!B15*0.85+Assumptions!B11*0.15),0) -> 8457 | I40: =H40 -> 8457 | J40: =ROUND(E40*Assumptions!B68,0) -> 2580 | K40: =ROUND(J40*Assumptions!B65,0) -> 206 | L40: =Assumptions!B70+IF(E40>Assumptions!B72,45,0) -> 76 | M40: =Assumptions!B76+Assumptions!B77 -> 35 | N40: =Assumptions!B81+Assumptions!B82+Assumptions!B87/12+Assumptions!B148 -> 116 | O40: =ROUND(I40*Assumptions!B85+E40*Assumptions!B86+W40*Assumptions!B85+ROUND(AB40*Assumptions!B137*Assumptions!B138*Assumptions!B139,0)*Assumptions!B86,0) -> 562 | P40: =K40+L40+M40+N40+O40+X40 -> 1297 | Q40: =I40-P40 -> 7160 | R40: =ROUND(AB40*Assumptions!B51*Assumptions!B52,0) -> 16537 | S40: =I40+R40+W40+AC40+AD40 -> 26933 | T40: =IF(U40<P40*3,0,IF(U40<P40*6,ROUND((Q40+R40+W40+AC40+AD40)*0.75*Assumptions!B113,0),ROUND((Q40+R40+W40+AC40+AD40)*0.75*Assumptions!B114,0))) -> 7345 | U40: =U39+Q40+R40+W40+AC40+AD40 -> 225316 | V40: =IF(AB40>=Assumptions!B107,"Signal 6",IF(AB40>=Assumptions!B106,"Signal 5",IF(AB40>=Assumptions!B105,"Signal 4",IF(AB40>=Assumptions!B104,"Signal 3",IF(AB40>=Assumptions!B103,"Signal 2",IF(AB40>=Assumptions!B102,"Signal 1","Pre-Signal 1")))))) -> Signal 3 | W40: =ROUND(AB40*Assumptions!B137*Assumptions!B138*Assumptions!B139*Assumptions!B136,0) -> 1843 | X40: =ROUND(AB40*Assumptions!B137*Assumptions!B65,0) -> 302 | Y40: =ROUND(Y39*(1+Assumptions!B165),0) -> 2576 | Z40: =Assumptions!B158 -> 400 | AA40: =ROUND(Y40*Assumptions!B166,0) -> 8 | AB40: =B40+Z40+AA40 -> 47248.805 | AC40: =ROUND(IF(A40>=Assumptions!B144,(IF(A40>=25,Assumptions!B151,IF(A40>=16,Assumptions!B150,Assumptions!B149))/1000*Assumptions!B146)+IF(A40>=Assumptions!B145,(IF(A40>=25,Assumptions!B151,IF(A40>=16,Assumptions!B150,Assumptions!B149))*Assumptions!B152/1000*Assumptions!B147),0),0),0) -> 76 | AD40: =IF(Y40>=10000,Assumptions!B170,IF(Y40>=5000,Assumptions!B169,IF(Y40>=2000,Assumptions!B168,IF(Y40>=500,Assumptions!B167,0)))) -> 20
A41: 36 | B41: =B40*(1+Assumptions!B34) -> 52461.702 | C41: =ROUND(AB41*Assumptions!B25,0) -> 1057 | D41: =ROUND(AB41*Assumptions!B23,0) -> 132 | E41: =E40+D41-F41 -> 825 | F41: =ROUND(E40*Assumptions!B44,0) -> 44 | G41: =D41-F41 -> 88 | H41: =ROUND(E41*(Assumptions!B15*0.85+Assumptions!B11*0.15),0) -> 9467 | I41: =H41 -> 9467 | J41: =ROUND(E41*Assumptions!B68,0) -> 2888 | K41: =ROUND(J41*Assumptions!B65,0) -> 231 | L41: =Assumptions!B70+IF(E41>Assumptions!B72,45,0) -> 76 | M41: =Assumptions!B76+Assumptions!B77 -> 35 | N41: =Assumptions!B81+Assumptions!B82+Assumptions!B87/12+Assumptions!B148 -> 116 | O41: =ROUND(I41*Assumptions!B85+E41*Assumptions!B86+W41*Assumptions!B85+ROUND(AB41*Assumptions!B137*Assumptions!B138*Assumptions!B139,0)*Assumptions!B86,0) -> 630 | P41: =K41+L41+M41+N41+O41+X41 -> 1426 | Q41: =I41-P41 -> 8041 | R41: =ROUND(AB41*Assumptions!B51*Assumptions!B52,0) -> 18505 | S41: =I41+R41+W41+AC41+AD41 -> 30130 | T41: =IF(U41<P41*3,0,IF(U41<P41*6,ROUND((Q41+R41+W41+AC41+AD41)*0.75*Assumptions!B113,0),ROUND((Q41+R41+W41+AC41+AD41)*0.75*Assumptions!B114,0))) -> 8224 | U41: =U40+Q41+R41+W41+AC41+AD41 -> 254020 | V41: =IF(AB41>=Assumptions!B107,"Signal 6",IF(AB41>=Assumptions!B106,"Signal 5",IF(AB41>=Assumptions!B105,"Signal 4",IF(AB41>=Assumptions!B104,"Signal 3",IF(AB41>=Assumptions!B103,"Signal 2",IF(AB41>=Assumptions!B102,"Signal 1","Pre-Signal 1")))))) -> Signal 3 | W41: =ROUND(AB41*Assumptions!B137*Assumptions!B138*Assumptions!B139*Assumptions!B136,0) -> 2062 | X41: =ROUND(AB41*Assumptions!B137*Assumptions!B65,0) -> 338 | Y41: =ROUND(Y40*(1+Assumptions!B165),0) -> 2834 | Z41: =Assumptions!B158 -> 400 | AA41: =ROUND(Y41*Assumptions!B166,0) -> 9 | AB41: =B41+Z41+AA41 -> 52870.702 | AC41: =ROUND(IF(A41>=Assumptions!B144,(IF(A41>=25,Assumptions!B151,IF(A41>=16,Assumptions!B150,Assumptions!B149))/1000*Assumptions!B146)+IF(A41>=Assumptions!B145,(IF(A41>=25,Assumptions!B151,IF(A41>=16,Assumptions!B150,Assumptions!B149))*Assumptions!B152/1000*Assumptions!B147),0),0),0) -> 76 | AD41: =IF(Y41>=10000,Assumptions!B170,IF(Y41>=5000,Assumptions!B169,IF(Y41>=2000,Assumptions!B168,IF(Y41>=500,Assumptions!B167,0)))) -> 20
A43: TOTALS | I43: =SUM(I6:I41) -> 84687 | P43: =SUM(P6:P41) -> 20268 | Q43: =SUM(Q6:Q41) -> 64419 | R43: =SUM(R6:R41) -> 169031 | S43: =SUM(S6:S41) -> 274288 | T43: =SUM(T6:T41) -> 72606 | W43: =SUM(W6:W41) -> 19052 | X43: =SUM(X6:X41) -> 3126 | AC43: =SUM(AC6:AC41) -> 1363 | AD43: =SUM(AD6:AD41) -> 155
A44: AVG MO | H44: =AVERAGE(H6:H41) -> 2352.4167 | Q44: =AVERAGE(Q6:Q41) -> 1789.4167
A45: M36 | B45: =AB41 -> 52870.702 | E45: =E41 -> 825 | H45: =H41 -> 9467 | S45: =S41 -> 30130 | T45: =T41 -> 8224 | U45: =U41 -> 254020 | V45: =V41 -> Signal 3 | AC45: =AC41 -> 76 | AD45: =AD41 -> 20

Sheet Optimistic
A1: OPTIMISTIC SCENARIO — Optimistic Growth
A2: 0.50% paid conversion | 15% MoM traffic growth | 4% monthly churn | Referral: 0.1% of total visitors x $350 blended
A3: Blue = hardcoded inputs | Black = calculated formulas | Green = Assumptions references | ▼ = NEW v16 columns (YT+IG integration)
A5: Month | B5: Organic Visitors | C5: Free Signups (Email 2%) | D5: New Paid Subs | E5: Total Paid Subs | F5: Churn This Month | G5: Net New Subs | H5: MRR ($) | I5: Monthly Revenue ($) | J5: Letter Gens | K5: API Costs ($) | L5: Infra ($) | M5: Content/ SEO ($) | N5: n8n+Tools ($) | O5: Stripe Fees ($) | P5: Total Costs ($) | Q5: Gross Profit ($) | R5: Referral Revenue ($) | S5: Total Revenue ($) | T5: Owner's Draw ($) | U5: Reserve Balance ($) | V5: Traffic Signal | W5: Per-Case Revenue ($) | X5: Free Tier API Cost ($) | Y5: IG Followers ▼ | Z5: YT Referral Visitors ▼ | AA5: IG Direct Visitors ▼ | AB5: TOTAL Visitors ▼ | AC5: YT AdSense Revenue ($) ▼ | AD5: IG Direct Revenue ($) ▼
A6: 1 | B6: =Assumptions!B32 -> 1200 | C6: =ROUND(AB6*Assumptions!B25,0) -> 24 | D6: =ROUND(AB6*Assumptions!B24,0) -> 6 | E6: =D6 -> 6 | F6: =0 -> 0 | G6: =D6-F6 -> 6 | H6: =ROUND(E6*Assumptions!B14,0) -> 48 | I6: =H6 -> 48 | J6: =ROUND(E6*Assumptions!B68,0) -> 21 | K6: =ROUND(J6*Assumptions!B65,0) -> 2 | L6: =Assumptions!B70+IF(E6>Assumptions!B72,45,0) -> 31 | M6: =Assumptions!B94+Assumptions!B95+Assumptions!B76+Assumptions!B77 -> 2785 | N6: =Assumptions!B81+Assumptions!B82+Assumptions!B87/12 -> 50 | O6: =ROUND(I6*Assumptions!B85+E6*Assumptions!B86+W6*Assumptions!B85+ROUND(AB6*Assumptions!B137*Assumptions!B138*Assumptions!B139,0)*Assumptions!B86,0) -> 6 | P6: =K6+L6+M6+N6+O6+X6 -> 2882 | Q6: =I6-P6 -> -2834 | R6: =0 -> 0 | S6: =I6+R6+W6+AC6+AD6 -> 95 | T6: =IF(U6<P6*3,0,IF(U6<P6*6,ROUND((Q6+R6+W6+AC6+AD6)*0.75*Assumptions!B113,0),ROUND((Q6+R6+W6+AC6+AD6)*0.75*Assumptions!B114,0))) -> 0 | U6: =Q6+R6+W6+AC6+AD6 -> -2787 | V6: =IF(AB6>=Assumptions!B107,"Signal 6",IF(AB6>=Assumptions!B106,"Signal 5",IF(AB6>=Assumptions!B105,"Signal 4",IF(AB6>=Assumptions!B104,"Signal 3",IF(AB6>=Assumptions!B103,"Signal 2",IF(AB6>=Assumptions!B102,"Signal 1","Pre-Signal 1")))))) -> Pre-Signal 1 | W6: =ROUND(AB6*Assumptions!B137*Assumptions!B138*Assumptions!B139*Assumptions!B136,0) -> 47 | X6: =ROUND(AB6*Assumptions!B137*Assumptions!B65,0) -> 8 | Y6: =Assumptions!B162 -> 50 | Z6: =Assumptions!B153 -> 0 | AA6: =ROUND(Y6*Assumptions!B166,0) -> 0 | AB6: =B6+Z6+AA6 -> 1200 | AC6: =ROUND(IF(A6>=Assumptions!B144,(IF(A6>=25,Assumptions!B151,IF(A6>=16,Assumptions!B150,Assumptions!B149))/1000*Assumptions!B146)+IF(A6>=Assumptions!B145,(IF(A6>=25,Assumptions!B151,IF(A6>=16,Assumptions!B150,Assumptions!B149))*Assumptions!B152/1000*Assumptions!B147),0),0),0) -> 0 | AD6: =IF(Y6>=10000,Assumptions!B170,IF(Y6>=5000,Assumptions!B169,IF(Y6>=2000,Assumptions!B168,IF(Y6>=500,Assumptions!B167,0)))) -> 0
A7: 2 | B7: =B6*(1+Assumptions!B35) -> 1380 | C7: =ROUND(AB7*Assumptions!B25,0) -> 28 | D7: =ROUND(AB7*Assumptions!B24,0) -> 7 | E7: =E6+D7-F7 -> 13 | F7: =ROUND(E6*Assumptions!B45,0) -> 0 | G7: =D7-F7 -> 7 | H7: =ROUND(E7*Assumptions!B14,0) -> 104 | I7: =H7 -> 104 | J7: =ROUND(E7*Assumptions!B68,0) -> 46 | K7: =ROUND(J7*Assumptions!B65,0) -> 4 | L7: =Assumptions!B70+IF(E7>Assumptions!B72,45,0) -> 31 | M7: =Assumptions!B76+Assumptions!B77 -> 35 | N7: =Assumptions!B81+Assumptions!B82+Assumptions!B87/12 -> 50 | O7: =ROUND(I7*Assumptions!B85+E7*Assumptions!B86+W7*Assumptions!B85+ROUND(AB7*Assumptions!B137*Assumptions!B138*Assumptions!B139,0)*Assumptions!B86,0) -> 10 | P7: =K7+L7+M7+N7+O7+X7 -> 139 | Q7: =I7-P7 -> -35 | R7: =0 -> 0 | S7: =I7+R7+W7+AC7+AD7 -> 158 | T7: =IF(U7<P7*3,0,IF(U7<P7*6,ROUND((Q7+R7+W7+AC7+AD7)*0.75*Assumptions!B113,0),ROUND((Q7+R7+W7+AC7+AD7)*0.75*Assumptions!B114,0))) -> 0 | U7: =U6+Q7+R7+W7+AC7+AD7 -> -2768 | V7: =IF(AB7>=Assumptions!B107,"Signal 6",IF(AB7>=Assumptions!B106,"Signal 5",IF(AB7>=Assumptions!B105,"Signal 4",IF(AB7>=Assumptions!B104,"Signal 3",IF(AB7>=Assumptions!B103,"Signal 2",IF(AB7>=Assumptions!B102,"Signal 1","Pre-Signal 1")))))) -> Pre-Signal 1 | W7: =ROUND(AB7*Assumptions!B137*Assumptions!B138*Assumptions!B139*Assumptions!B136,0) -> 54 | X7: =ROUND(AB7*Assumptions!B137*Assumptions!B65,0) -> 9 | Y7: =ROUND(Y6*(1+Assumptions!B163),0) -> 60 | Z7: =Assumptions!B153 -> 0 | AA7: =ROUND(Y7*Assumptions!B166,0) -> 0 | AB7: =B7+Z7+AA7 -> 1380 | AC7: =ROUND(IF(A7>=Assumptions!B144,(IF(A7>=25,Assumptions!B151,IF(A7>=16,Assumptions!B150,Assumptions!B149))/1000*Assumptions!B146)+IF(A7>=Assumptions!B145,(IF(A7>=25,Assumptions!B151,IF(A7>=16,Assumptions!B150,Assumptions!B149))*Assumptions!B152/1000*Assumptions!B147),0),0),0) -> 0 | AD7: =IF(Y7>=10000,Assumptions!B170,IF(Y7>=5000,Assumptions!B169,IF(Y7>=2000,Assumptions!B168,IF(Y7>=500,Assumptions!B167,0)))) -> 0
A8: 3 | B8: =B7*(1+Assumptions!B35)*Assumptions!B36 -> 1825.05 | C8: =ROUND(AB8*Assumptions!B25,0) -> 37 | D8: =ROUND(AB8*Assumptions!B24,0) -> 9 | E8: =E7+D8-F8 -> 21 | F8: =ROUND(E7*Assumptions!B45,0) -> 1 | G8: =D8-F8 -> 8 | H8: =ROUND(E8*Assumptions!B14,0) -> 168 | I8: =H8 -> 168 | J8: =ROUND(E8*Assumptions!B68,0) -> 74 | K8: =ROUND(J8*Assumptions!B65,0) -> 6 | L8: =Assumptions!B70+IF(E8>Assumptions!B72,45,0) -> 31 | M8: =Assumptions!B76+Assumptions!B77 -> 35 | N8: =Assumptions!B81+Assumptions!B82+Assumptions!B87/12+Assumptions!B148 -> 116 | O8: =ROUND(I8*Assumptions!B85+E8*Assumptions!B86+W8*Assumptions!B85+ROUND(AB8*Assumptions!B137*Assumptions!B138*Assumptions!B139,0)*Assumptions!B86,0) -> 15 | P8: =K8+L8+M8+N8+O8+X8 -> 215 | Q8: =I8-P8 -> -47 | R8: =0 -> 0 | S8: =I8+R8+W8+AC8+AD8 -> 239 | T8: =IF(U8<P8*3,0,IF(U8<P8*6,ROUND((Q8+R8+W8+AC8+AD8)*0.75*Assumptions!B113,0),ROUND((Q8+R8+W8+AC8+AD8)*0.75*Assumptions!B114,0))) -> 0 | U8: =U7+Q8+R8+W8+AC8+AD8 -> -2744 | V8: =IF(AB8>=Assumptions!B107,"Signal 6",IF(AB8>=Assumptions!B106,"Signal 5",IF(AB8>=Assumptions!B105,"Signal 4",IF(AB8>=Assumptions!B104,"Signal 3",IF(AB8>=Assumptions!B103,"Signal 2",IF(AB8>=Assumptions!B102,"Signal 1","Pre-Signal 1")))))) -> Pre-Signal 1 | W8: =ROUND(AB8*Assumptions!B137*Assumptions!B138*Assumptions!B139*Assumptions!B136,0) -> 71 | X8: =ROUND(AB8*Assumptions!B137*Assumptions!B65,0) -> 12 | Y8: =ROUND(Y7*(1+Assumptions!B163),0) -> 72 | Z8: =Assumptions!B153 -> 0 | AA8: =ROUND(Y8*Assumptions!B166,0) -> 0 | AB8: =B8+Z8+AA8 -> 1825.05 | AC8: =ROUND(IF(A8>=Assumptions!B144,(IF(A8>=25,Assumptions!B151,IF(A8>=16,Assumptions!B150,Assumptions!B149))/1000*Assumptions!B146)+IF(A8>=Assumptions!B145,(IF(A8>=25,Assumptions!B151,IF(A8>=16,Assumptions!B150,Assumptions!B149))*Assumptions!B152/1000*Assumptions!B147),0),0),0) -> 0 | AD8: =IF(Y8>=10000,Assumptions!B170,IF(Y8>=5000,Assumptions!B169,IF(Y8>=2000,Assumptions!B168,IF(Y8>=500,Assumptions!B167,0)))) -> 0
A9: 4 | B9: =B8*(1+Assumptions!B35) -> 2098.8075 | C9: =ROUND(AB9*Assumptions!B25,0) -> 42 | D9: =ROUND(AB9*Assumptions!B24,0) -> 10 | E9: =E8+D9-F9 -> 30 | F9: =ROUND(E8*Assumptions!B45,0) -> 1 | G9: =D9-F9 -> 9 | H9: =ROUND(E9*Assumptions!B14,0) -> 240 | I9: =H9 -> 240 | J9: =ROUND(E9*Assumptions!B68,0) -> 105 | K9: =ROUND(J9*Assumptions!B65,0) -> 8 | L9: =Assumptions!B70+IF(E9>Assumptions!B72,45,0) -> 31 | M9: =Assumptions!B76+Assumptions!B77 -> 35 | N9: =Assumptions!B81+Assumptions!B82+Assumptions!B87/12+Assumptions!B148 -> 116 | O9: =ROUND(I9*Assumptions!B85+E9*Assumptions!B86+W9*Assumptions!B85+ROUND(AB9*Assumptions!B137*Assumptions!B138*Assumptions!B139,0)*Assumptions!B86,0) -> 20 | P9: =K9+L9+M9+N9+O9+X9 -> 223 | Q9: =I9-P9 -> 17 | R9: =0 -> 0 | S9: =I9+R9+W9+AC9+AD9 -> 322 | T9: =IF(U9<P9*3,0,IF(U9<P9*6,ROUND((Q9+R9+W9+AC9+AD9)*0.75*Assumptions!B113,0),ROUND((Q9+R9+W9+AC9+AD9)*0.75*Assumptions!B114,0))) -> 0 | U9: =U8+Q9+R9+W9+AC9+AD9 -> -2645 | V9: =IF(AB9>=Assumptions!B107,"Signal 6",IF(AB9>=Assumptions!B106,"Signal 5",IF(AB9>=Assumptions!B105,"Signal 4",IF(AB9>=Assumptions!B104,"Signal 3",IF(AB9>=Assumptions!B103,"Signal 2",IF(AB9>=Assumptions!B102,"Signal 1","Pre-Signal 1")))))) -> Pre-Signal 1 | W9: =ROUND(AB9*Assumptions!B137*Assumptions!B138*Assumptions!B139*Assumptions!B136,0) -> 82 | X9: =ROUND(AB9*Assumptions!B137*Assumptions!B65,0) -> 13 | Y9: =ROUND(Y8*(1+Assumptions!B163),0) -> 86 | Z9: =Assumptions!B153 -> 0 | AA9: =ROUND(Y9*Assumptions!B166,0) -> 0 | AB9: =B9+Z9+AA9 -> 2098.8075 | AC9: =ROUND(IF(A9>=Assumptions!B144,(IF(A9>=25,Assumptions!B151,IF(A9>=16,Assumptions!B150,Assumptions!B149))/1000*Assumptions!B146)+IF(A9>=Assumptions!B145,(IF(A9>=25,Assumptions!B151,IF(A9>=16,Assumptions!B150,Assumptions!B149))*Assumptions!B152/1000*Assumptions!B147),0),0),0) -> 0 | AD9: =IF(Y9>=10000,Assumptions!B170,IF(Y9>=5000,Assumptions!B169,IF(Y9>=2000,Assumptions!B168,IF(Y9>=500,Assumptions!B167,0)))) -> 0
A10: 5 | B10: =B9*(1+Assumptions!B35) -> 2413.6286 | C10: =ROUND(AB10*Assumptions!B25,0) -> 48 | D10: =ROUND(AB10*Assumptions!B24,0) -> 12 | E10: =E9+D10-F10 -> 41 | F10: =ROUND(E9*Assumptions!B45,0) -> 1 | G10: =D10-F10 -> 11 | H10: =ROUND(E10*Assumptions!B14,0) -> 328 | I10: =H10 -> 328 | J10: =ROUND(E10*Assumptions!B68,0) -> 144 | K10: =ROUND(J10*Assumptions!B65,0) -> 12 | L10: =Assumptions!B70+IF(E10>Assumptions!B72,45,0) -> 31 | M10: =Assumptions!B76+Assumptions!B77 -> 35 | N10: =Assumptions!B81+Assumptions!B82+Assumptions!B87/12+Assumptions!B148 -> 116 | O10: =ROUND(I10*Assumptions!B85+E10*Assumptions!B86+W10*Assumptions!B85+ROUND(AB10*Assumptions!B137*Assumptions!B138*Assumptions!B139,0)*Assumptions!B86,0) -> 27 | P10: =K10+L10+M10+N10+O10+X10 -> 236 | Q10: =I10-P10 -> 92 | R10: =0 -> 0 | S10: =I10+R10+W10+AC10+AD10 -> 422 | T10: =IF(U10<P10*3,0,IF(U10<P10*6,ROUND((Q10+R10+W10+AC10+AD10)*0.75*Assumptions!B113,0),ROUND((Q10+R10+W10+AC10+AD10)*0.75*Assumptions!B114,0))) -> 0 | U10: =U9+Q10+R10+W10+AC10+AD10 -> -2459 | V10: =IF(AB10>=Assumptions!B107,"Signal 6",IF(AB10>=Assumptions!B106,"Signal 5",IF(AB10>=Assumptions!B105,"Signal 4",IF(AB10>=Assumptions!B104,"Signal 3",IF(AB10>=Assumptions!B103,"Signal 2",IF(AB10>=Assumptions!B102,"Signal 1","Pre-Signal 1")))))) -> Pre-Signal 1 | W10: =ROUND(AB10*Assumptions!B137*Assumptions!B138*Assumptions!B139*Assumptions!B136,0) -> 94 | X10: =ROUND(AB10*Assumptions!B137*Assumptions!B65,0) -> 15 | Y10: =ROUND(Y9*(1+Assumptions!B163),0) -> 103 | Z10: =Assumptions!B153 -> 0 | AA10: =ROUND(Y10*Assumptions!B166,0) -> 0 | AB10: =B10+Z10+AA10 -> 2413.6286 | AC10: =ROUND(IF(A10>=Assumptions!B144,(IF(A10>=25,Assumptions!B151,IF(A10>=16,Assumptions!B150,Assumptions!B149))/1000*Assumptions!B146)+IF(A10>=Assumptions!B145,(IF(A10>=25,Assumptions!B151,IF(A10>=16,Assumptions!B150,Assumptions!B149))*Assumptions!B152/1000*Assumptions!B147),0),0),0) -> 0 | AD10: =IF(Y10>=10000,Assumptions!B170,IF(Y10>=5000,Assumptions!B169,IF(Y10>=2000,Assumptions!B168,IF(Y10>=500,Assumptions!B167,0)))) -> 0
A11: 6 | B11: =B10*(1+Assumptions!B35)*Assumptions!B37 -> 2997.7268 | C11: =ROUND(AB11*Assumptions!B25,0) -> 60 | D11: =ROUND(AB11*Assumptions!B24,0) -> 15 | E11: =E10+D11-F11 -> 54 | F11: =ROUND(E10*Assumptions!B45,0) -> 2 | G11: =D11-F11 -> 13 | H11: =ROUND(E11*Assumptions!B14,0) -> 432 | I11: =H11 -> 432 | J11: =ROUND(E11*Assumptions!B68,0) -> 189 | K11: =ROUND(J11*Assumptions!B65,0) -> 15 | L11: =Assumptions!B70+IF(E11>Assumptions!B72,45,0) -> 31 | M11: =Assumptions!B76+Assumptions!B77 -> 35 | N11: =Assumptions!B81+Assumptions!B82+Assumptions!B87/12+Assumptions!B148 -> 116 | O11: =ROUND(I11*Assumptions!B85+E11*Assumptions!B86+W11*Assumptions!B85+ROUND(AB11*Assumptions!B137*Assumptions!B138*Assumptions!B139,0)*Assumptions!B86,0) -> 35 | P11: =K11+L11+M11+N11+O11+X11 -> 251 | Q11: =I11-P11 -> 181 | R11: =ROUND(AB11*Assumptions!B51*Assumptions!B52,0) -> 1058 | S11: =I11+R11+W11+AC11+AD11 -> 1608 | T11: =IF(U11<P11*3,0,IF(U11<P11*6,ROUND((Q11+R11+W11+AC11+AD11)*0.75*Assumptions!B113,0),ROUND((Q11+R11+W11+AC11+AD11)*0.75*Assumptions!B114,0))) -> 0 | U11: =U10+Q11+R11+W11+AC11+AD11 -> -1102 | V11: =IF(AB11>=Assumptions!B107,"Signal 6",IF(AB11>=Assumptions!B106,"Signal 5",IF(AB11>=Assumptions!B105,"Signal 4",IF(AB11>=Assumptions!B104,"Signal 3",IF(AB11>=Assumptions!B103,"Signal 2",IF(AB11>=Assumptions!B102,"Signal 1","Pre-Signal 1")))))) -> Pre-Signal 1 | W11: =ROUND(AB11*Assumptions!B137*Assumptions!B138*Assumptions!B139*Assumptions!B136,0) -> 118 | X11: =ROUND(AB11*Assumptions!B137*Assumptions!B65,0) -> 19 | Y11: =ROUND(Y10*(1+Assumptions!B163),0) -> 124 | Z11: =Assumptions!B154 -> 25 | AA11: =ROUND(Y11*Assumptions!B166,0) -> 0 | AB11: =B11+Z11+AA11 -> 3022.7268 | AC11: =ROUND(IF(A11>=Assumptions!B144,(IF(A11>=25,Assumptions!B151,IF(A11>=16,Assumptions!B150,Assumptions!B149))/1000*Assumptions!B146)+IF(A11>=Assumptions!B145,(IF(A11>=25,Assumptions!B151,IF(A11>=16,Assumptions!B150,Assumptions!B149))*Assumptions!B152/1000*Assumptions!B147),0),0),0) -> 0 | AD11: =IF(Y11>=10000,Assumptions!B170,IF(Y11>=5000,Assumptions!B169,IF(Y11>=2000,Assumptions!B168,IF(Y11>=500,Assumptions!B167,0)))) -> 0
A12: 7 | B12: =B11*(1+Assumptions!B35) -> 3447.3858 | C12: =ROUND(AB12*Assumptions!B25,0) -> 69 | D12: =ROUND(AB12*Assumptions!B24,0) -> 17 | E12: =E11+D12-F12 -> 69 | F12: =ROUND(E11*Assumptions!B45,0) -> 2 | G12: =D12-F12 -> 15 | H12: =ROUND(E12*Assumptions!B14,0) -> 552 | I12: =H12 -> 552 | J12: =ROUND(E12*Assumptions!B68,0) -> 242 | K12: =ROUND(J12*Assumptions!B65,0) -> 19 | L12: =Assumptions!B70+IF(E12>Assumptions!B72,45,0) -> 31 | M12: =Assumptions!B76+Assumptions!B77 -> 35 | N12: =Assumptions!B81+Assumptions!B82+Assumptions!B87/12+Assumptions!B148 -> 116 | O12: =ROUND(I12*Assumptions!B85+E12*Assumptions!B86+W12*Assumptions!B85+ROUND(AB12*Assumptions!B137*Assumptions!B138*Assumptions!B139,0)*Assumptions!B86,0) -> 44 | P12: =K12+L12+M12+N12+O12+X12 -> 267 | Q12: =I12-P12 -> 285 | R12: =ROUND(AB12*Assumptions!B51*Assumptions!B52,0) -> 1215 | S12: =I12+R12+W12+AC12+AD12 -> 1902 | T12: =IF(U12<P12*3,0,IF(U12<P12*6,ROUND((Q12+R12+W12+AC12+AD12)*0.75*Assumptions!B113,0),ROUND((Q12+R12+W12+AC12+AD12)*0.75*Assumptions!B114,0))) -> 0 | U12: =U11+Q12+R12+W12+AC12+AD12 -> 533 | V12: =IF(AB12>=Assumptions!B107,"Signal 6",IF(AB12>=Assumptions!B106,"Signal 5",IF(AB12>=Assumptions!B105,"Signal 4",IF(AB12>=Assumptions!B104,"Signal 3",IF(AB12>=Assumptions!B103,"Signal 2",IF(AB12>=Assumptions!B102,"Signal 1","Pre-Signal 1")))))) -> Pre-Signal 1 | W12: =ROUND(AB12*Assumptions!B137*Assumptions!B138*Assumptions!B139*Assumptions!B136,0) -> 135 | X12: =ROUND(AB12*Assumptions!B137*Assumptions!B65,0) -> 22 | Y12: =ROUND(Y11*(1+Assumptions!B164),0) -> 143 | Z12: =Assumptions!B154 -> 25 | AA12: =ROUND(Y12*Assumptions!B166,0) -> 0 | AB12: =B12+Z12+AA12 -> 3472.3858 | AC12: =ROUND(IF(A12>=Assumptions!B144,(IF(A12>=25,Assumptions!B151,IF(A12>=16,Assumptions!B150,Assumptions!B149))/1000*Assumptions!B146)+IF(A12>=Assumptions!B145,(IF(A12>=25,Assumptions!B151,IF(A12>=16,Assumptions!B150,Assumptions!B149))*Assumptions!B152/1000*Assumptions!B147),0),0),0) -> 0 | AD12: =IF(Y12>=10000,Assumptions!B170,IF(Y12>=5000,Assumptions!B169,IF(Y12>=2000,Assumptions!B168,IF(Y12>=500,Assumptions!B167,0)))) -> 0
A13: 8 | B13: =B12*(1+Assumptions!B35) -> 3964.4936 | C13: =ROUND(AB13*Assumptions!B25,0) -> 80 | D13: =ROUND(AB13*Assumptions!B24,0) -> 20 | E13: =E12+D13-F13 -> 86 | F13: =ROUND(E12*Assumptions!B45,0) -> 3 | G13: =D13-F13 -> 17 | H13: =ROUND(E13*Assumptions!B14,0) -> 688 | I13: =H13 -> 688 | J13: =ROUND(E13*Assumptions!B68,0) -> 301 | K13: =ROUND(J13*Assumptions!B65,0) -> 24 | L13: =Assumptions!B70+IF(E13>Assumptions!B72,45,0) -> 31 | M13: =Assumptions!B76+Assumptions!B77 -> 35 | N13: =Assumptions!B81+Assumptions!B82+Assumptions!B87/12+Assumptions!B148 -> 116 | O13: =ROUND(I13*Assumptions!B85+E13*Assumptions!B86+W13*Assumptions!B85+ROUND(AB13*Assumptions!B137*Assumptions!B138*Assumptions!B139,0)*Assumptions!B86,0) -> 54 | P13: =K13+L13+M13+N13+O13+X13 -> 286 | Q13: =I13-P13 -> 402 | R13: =ROUND(AB13*Assumptions!B51*Assumptions!B52,0) -> 1396 | S13: =I13+R13+W13+AC13+AD13 -> 2240 | T13: =IF(U13<P13*3,0,IF(U13<P13*6,ROUND((Q13+R13+W13+AC13+AD13)*0.75*Assumptions!B113,0),ROUND((Q13+R13+W13+AC13+AD13)*0.75*Assumptions!B114,0))) -> 560 | U13: =U12+Q13+R13+W13+AC13+AD13 -> 2487 | V13: =IF(AB13>=Assumptions!B107,"Signal 6",IF(AB13>=Assumptions!B106,"Signal 5",IF(AB13>=Assumptions!B105,"Signal 4",IF(AB13>=Assumptions!B104,"Signal 3",IF(AB13>=Assumptions!B103,"Signal 2",IF(AB13>=Assumptions!B102,"Signal 1","Pre-Signal 1")))))) -> Pre-Signal 1 | W13: =ROUND(AB13*Assumptions!B137*Assumptions!B138*Assumptions!B139*Assumptions!B136,0) -> 156 | X13: =ROUND(AB13*Assumptions!B137*Assumptions!B65,0) -> 26 | Y13: =ROUND(Y12*(1+Assumptions!B164),0) -> 164 | Z13: =Assumptions!B154 -> 25 | AA13: =ROUND(Y13*Assumptions!B166,0) -> 0 | AB13: =B13+Z13+AA13 -> 3989.4936 | AC13: =ROUND(IF(A13>=Assumptions!B144,(IF(A13>=25,Assumptions!B151,IF(A13>=16,Assumptions!B150,Assumptions!B149))/1000*Assumptions!B146)+IF(A13>=Assumptions!B145,(IF(A13>=25,Assumptions!B151,IF(A13>=16,Assumptions!B150,Assumptions!B149))*Assumptions!B152/1000*Assumptions!B147),0),0),0) -> 0 | AD13: =IF(Y13>=10000,Assumptions!B170,IF(Y13>=5000,Assumptions!B169,IF(Y13>=2000,Assumptions!B168,IF(Y13>=500,Assumptions!B167,0)))) -> 0
A14: 9 | B14: =B13*(1+Assumptions!B35) -> 4559.1677 | C14: =ROUND(AB14*Assumptions!B25,0) -> 92 | D14: =ROUND(AB14*Assumptions!B24,0) -> 23 | E14: =E13+D14-F14 -> 106 | F14: =ROUND(E13*Assumptions!B45,0) -> 3 | G14: =D14-F14 -> 20 | H14: =ROUND(E14*((Assumptions!B14+Assumptions!B15)/2),0) -> 1113 | I14: =H14 -> 1113 | J14: =ROUND(E14*Assumptions!B68,0) -> 371 | K14: =ROUND(J14*Assumptions!B65,0) -> 30 | L14: =Assumptions!B70+IF(E14>Assumptions!B72,45,0) -> 31 | M14: =Assumptions!B76+Assumptions!B77 -> 35 | N14: =Assumptions!B81+Assumptions!B82+Assumptions!B87/12+Assumptions!B148 -> 116 | O14: =ROUND(I14*Assumptions!B85+E14*Assumptions!B86+W14*Assumptions!B85+ROUND(AB14*Assumptions!B137*Assumptions!B138*Assumptions!B139,0)*Assumptions!B86,0) -> 73 | P14: =K14+L14+M14+N14+O14+X14 -> 315 | Q14: =I14-P14 -> 798 | R14: =ROUND(AB14*Assumptions!B51*Assumptions!B52,0) -> 1617 | S14: =I14+R14+W14+AC14+AD14 -> 2910 | T14: =IF(U14<P14*3,0,IF(U14<P14*6,ROUND((Q14+R14+W14+AC14+AD14)*0.75*Assumptions!B113,0),ROUND((Q14+R14+W14+AC14+AD14)*0.75*Assumptions!B114,0))) -> 743 | U14: =U13+Q14+R14+W14+AC14+AD14 -> 5082 | V14: =IF(AB14>=Assumptions!B107,"Signal 6",IF(AB14>=Assumptions!B106,"Signal 5",IF(AB14>=Assumptions!B105,"Signal 4",IF(AB14>=Assumptions!B104,"Signal 3",IF(AB14>=Assumptions!B103,"Signal 2",IF(AB14>=Assumptions!B102,"Signal 1","Pre-Signal 1")))))) -> Pre-Signal 1 | W14: =ROUND(AB14*Assumptions!B137*Assumptions!B138*Assumptions!B139*Assumptions!B136,0) -> 180 | X14: =ROUND(AB14*Assumptions!B137*Assumptions!B65,0) -> 30 | Y14: =ROUND(Y13*(1+Assumptions!B164),0) -> 189 | Z14: =Assumptions!B155 -> 60 | AA14: =ROUND(Y14*Assumptions!B166,0) -> 1 | AB14: =B14+Z14+AA14 -> 4620.1677 | AC14: =ROUND(IF(A14>=Assumptions!B144,(IF(A14>=25,Assumptions!B151,IF(A14>=16,Assumptions!B150,Assumptions!B149))/1000*Assumptions!B146)+IF(A14>=Assumptions!B145,(IF(A14>=25,Assumptions!B151,IF(A14>=16,Assumptions!B150,Assumptions!B149))*Assumptions!B152/1000*Assumptions!B147),0),0),0) -> 0 | AD14: =IF(Y14>=10000,Assumptions!B170,IF(Y14>=5000,Assumptions!B169,IF(Y14>=2000,Assumptions!B168,IF(Y14>=500,Assumptions!B167,0)))) -> 0
A15: 10 | B15: =B14*(1+Assumptions!B35) -> 5243.0428 | C15: =ROUND(AB15*Assumptions!B25,0) -> 106 | D15: =ROUND(AB15*Assumptions!B24,0) -> 27 | E15: =E14+D15-F15 -> 129 | F15: =ROUND(E14*Assumptions!B45,0) -> 4 | G15: =D15-F15 -> 23 | H15: =ROUND(E15*(Assumptions!B15*0.85+Assumptions!B11*0.15),0) -> 1480 | I15: =H15 -> 1480 | J15: =ROUND(E15*Assumptions!B68,0) -> 452 | K15: =ROUND(J15*Assumptions!B65,0) -> 36 | L15: =Assumptions!B70+IF(E15>Assumptions!B72,45,0) -> 31 | M15: =Assumptions!B76+Assumptions!B77 -> 35 | N15: =Assumptions!B81+Assumptions!B82+Assumptions!B87/12+Assumptions!B148 -> 116 | O15: =ROUND(I15*Assumptions!B85+E15*Assumptions!B86+W15*Assumptions!B85+ROUND(AB15*Assumptions!B137*Assumptions!B138*Assumptions!B139,0)*Assumptions!B86,0) -> 92 | P15: =K15+L15+M15+N15+O15+X15 -> 344 | Q15: =I15-P15 -> 1136 | R15: =ROUND(AB15*Assumptions!B51*Assumptions!B52,0) -> 1856 | S15: =I15+R15+W15+AC15+AD15 -> 3543 | T15: =IF(U15<P15*3,0,IF(U15<P15*6,ROUND((Q15+R15+W15+AC15+AD15)*0.75*Assumptions!B113,0),ROUND((Q15+R15+W15+AC15+AD15)*0.75*Assumptions!B114,0))) -> 917 | U15: =U14+Q15+R15+W15+AC15+AD15 -> 8281 | V15: =IF(AB15>=Assumptions!B107,"Signal 6",IF(AB15>=Assumptions!B106,"Signal 5",IF(AB15>=Assumptions!B105,"Signal 4",IF(AB15>=Assumptions!B104,"Signal 3",IF(AB15>=Assumptions!B103,"Signal 2",IF(AB15>=Assumptions!B102,"Signal 1","Pre-Signal 1")))))) -> Pre-Signal 1 | W15: =ROUND(AB15*Assumptions!B137*Assumptions!B138*Assumptions!B139*Assumptions!B136,0) -> 207 | X15: =ROUND(AB15*Assumptions!B137*Assumptions!B65,0) -> 34 | Y15: =ROUND(Y14*(1+Assumptions!B164),0) -> 217 | Z15: =Assumptions!B155 -> 60 | AA15: =ROUND(Y15*Assumptions!B166,0) -> 1 | AB15: =B15+Z15+AA15 -> 5304.0428 | AC15: =ROUND(IF(A15>=Assumptions!B144,(IF(A15>=25,Assumptions!B151,IF(A15>=16,Assumptions!B150,Assumptions!B149))/1000*Assumptions!B146)+IF(A15>=Assumptions!B145,(IF(A15>=25,Assumptions!B151,IF(A15>=16,Assumptions!B150,Assumptions!B149))*Assumptions!B152/1000*Assumptions!B147),0),0),0) -> 0 | AD15: =IF(Y15>=10000,Assumptions!B170,IF(Y15>=5000,Assumptions!B169,IF(Y15>=2000,Assumptions!B168,IF(Y15>=500,Assumptions!B167,0)))) -> 0
A16: 11 | B16: =B15*(1+Assumptions!B35) -> 6029.4992 | C16: =ROUND(AB16*Assumptions!B25,0) -> 122 | D16: =ROUND(AB16*Assumptions!B24,0) -> 30 | E16: =E15+D16-F16 -> 154 | F16: =ROUND(E15*Assumptions!B45,0) -> 5 | G16: =D16-F16 -> 25 | H16: =ROUND(E16*(Assumptions!B15*0.85+Assumptions!B11*0.15),0) -> 1767 | I16: =H16 -> 1767 | J16: =ROUND(E16*Assumptions!B68,0) -> 539 | K16: =ROUND(J16*Assumptions!B65,0) -> 43 | L16: =Assumptions!B70+IF(E16>Assumptions!B72,45,0) -> 31 | M16: =Assumptions!B76+Assumptions!B77 -> 35 | N16: =Assumptions!B81+Assumptions!B82+Assumptions!B87/12+Assumptions!B148 -> 116 | O16: =ROUND(I16*Assumptions!B85+E16*Assumptions!B86+W16*Assumptions!B85+ROUND(AB16*Assumptions!B137*Assumptions!B138*Assumptions!B139,0)*Assumptions!B86,0) -> 110 | P16: =K16+L16+M16+N16+O16+X16 -> 374 | Q16: =I16-P16 -> 1393 | R16: =ROUND(AB16*Assumptions!B51*Assumptions!B52,0) -> 2132 | S16: =I16+R16+W16+AC16+AD16 -> 4137 | T16: =IF(U16<P16*3,0,IF(U16<P16*6,ROUND((Q16+R16+W16+AC16+AD16)*0.75*Assumptions!B113,0),ROUND((Q16+R16+W16+AC16+AD16)*0.75*Assumptions!B114,0))) -> 1078 | U16: =U15+Q16+R16+W16+AC16+AD16 -> 12044 | V16: =IF(AB16>=Assumptions!B107,"Signal 6",IF(AB16>=Assumptions!B106,"Signal 5",IF(AB16>=Assumptions!B105,"Signal 4",IF(AB16>=Assumptions!B104,"Signal 3",IF(AB16>=Assumptions!B103,"Signal 2",IF(AB16>=Assumptions!B102,"Signal 1","Pre-Signal 1")))))) -> Pre-Signal 1 | W16: =ROUND(AB16*Assumptions!B137*Assumptions!B138*Assumptions!B139*Assumptions!B136,0) -> 238 | X16: =ROUND(AB16*Assumptions!B137*Assumptions!B65,0) -> 39 | Y16: =ROUND(Y15*(1+Assumptions!B164),0) -> 250 | Z16: =Assumptions!B155 -> 60 | AA16: =ROUND(Y16*Assumptions!B166,0) -> 1 | AB16: =B16+Z16+AA16 -> 6090.4992 | AC16: =ROUND(IF(A16>=Assumptions!B144,(IF(A16>=25,Assumptions!B151,IF(A16>=16,Assumptions!B150,Assumptions!B149))/1000*Assumptions!B146)+IF(A16>=Assumptions!B145,(IF(A16>=25,Assumptions!B151,IF(A16>=16,Assumptions!B150,Assumptions!B149))*Assumptions!B152/1000*Assumptions!B147),0),0),0) -> 0 | AD16: =IF(Y16>=10000,Assumptions!B170,IF(Y16>=5000,Assumptions!B169,IF(Y16>=2000,Assumptions!B168,IF(Y16>=500,Assumptions!B167,0)))) -> 0
A17: 12 | B17: =B16*(1+Assumptions!B35) -> 6933.9241 | C17: =ROUND(AB17*Assumptions!B25,0) -> 141 | D17: =ROUND(AB17*Assumptions!B24,0) -> 35 | E17: =E16+D17-F17 -> 183 | F17: =ROUND(E16*Assumptions!B45,0) -> 6 | G17: =D17-F17 -> 29 | H17: =ROUND(E17*(Assumptions!B15*0.85+Assumptions!B11*0.15),0) -> 2100 | I17: =H17 -> 2100 | J17: =ROUND(E17*Assumptions!B68,0) -> 641 | K17: =ROUND(J17*Assumptions!B65,0) -> 51 | L17: =Assumptions!B70+IF(E17>Assumptions!B72,45,0) -> 31 | M17: =Assumptions!B76+Assumptions!B77 -> 35 | N17: =Assumptions!B81+Assumptions!B82+Assumptions!B87/12+Assumptions!B148 -> 116 | O17: =ROUND(I17*Assumptions!B85+E17*Assumptions!B86+W17*Assumptions!B85+ROUND(AB17*Assumptions!B137*Assumptions!B138*Assumptions!B139,0)*Assumptions!B86,0) -> 130 | P17: =K17+L17+M17+N17+O17+X17 -> 408 | Q17: =I17-P17 -> 1692 | R17: =ROUND(AB17*Assumptions!B51*Assumptions!B52,0) -> 2471 | S17: =I17+R17+W17+AC17+AD17 -> 4862 | T17: =IF(U17<P17*3,0,IF(U17<P17*6,ROUND((Q17+R17+W17+AC17+AD17)*0.75*Assumptions!B113,0),ROUND((Q17+R17+W17+AC17+AD17)*0.75*Assumptions!B114,0))) -> 1276 | U17: =U16+Q17+R17+W17+AC17+AD17 -> 16498 | V17: =IF(AB17>=Assumptions!B107,"Signal 6",IF(AB17>=Assumptions!B106,"Signal 5",IF(AB17>=Assumptions!B105,"Signal 4",IF(AB17>=Assumptions!B104,"Signal 3",IF(AB17>=Assumptions!B103,"Signal 2",IF(AB17>=Assumptions!B102,"Signal 1","Pre-Signal 1")))))) -> Pre-Signal 1 | W17: =ROUND(AB17*Assumptions!B137*Assumptions!B138*Assumptions!B139*Assumptions!B136,0) -> 275 | X17: =ROUND(AB17*Assumptions!B137*Assumptions!B65,0) -> 45 | Y17: =ROUND(Y16*(1+Assumptions!B164),0) -> 288 | Z17: =Assumptions!B156 -> 125 | AA17: =ROUND(Y17*Assumptions!B166,0) -> 1 | AB17: =B17+Z17+AA17 -> 7059.9241 | AC17: =ROUND(IF(A17>=Assumptions!B144,(IF(A17>=25,Assumptions!B151,IF(A17>=16,Assumptions!B150,Assumptions!B149))/1000*Assumptions!B146)+IF(A17>=Assumptions!B145,(IF(A17>=25,Assumptions!B151,IF(A17>=16,Assumptions!B150,Assumptions!B149))*Assumptions!B152/1000*Assumptions!B147),0),0),0) -> 16 | AD17: =IF(Y17>=10000,Assumptions!B170,IF(Y17>=5000,Assumptions!B169,IF(Y17>=2000,Assumptions!B168,IF(Y17>=500,Assumptions!B167,0)))) -> 0
A18: 13 | B18: =B17*(1+Assumptions!B35) -> 7974.0128 | C18: =ROUND(AB18*Assumptions!B25,0) -> 162 | D18: =ROUND(AB18*Assumptions!B24,0) -> 41 | E18: =E17+D18-F18 -> 217 | F18: =ROUND(E17*Assumptions!B45,0) -> 7 | G18: =D18-F18 -> 34 | H18: =ROUND(E18*(Assumptions!B15*0.85+Assumptions!B11*0.15),0) -> 2490 | I18: =H18 -> 2490 | J18: =ROUND(E18*Assumptions!B68,0) -> 760 | K18: =ROUND(J18*Assumptions!B65,0) -> 61 | L18: =Assumptions!B70+IF(E18>Assumptions!B72,45,0) -> 31 | M18: =Assumptions!B76+Assumptions!B77 -> 35 | N18: =Assumptions!B81+Assumptions!B82+Assumptions!B87/12+Assumptions!B148 -> 116 | O18: =ROUND(I18*Assumptions!B85+E18*Assumptions!B86+W18*Assumptions!B85+ROUND(AB18*Assumptions!B137*Assumptions!B138*Assumptions!B139,0)*Assumptions!B86,0) -> 154 | P18: =K18+L18+M18+N18+O18+X18 -> 449 | Q18: =I18-P18 -> 2041 | R18: =ROUND(AB18*Assumptions!B51*Assumptions!B52,0) -> 2835 | S18: =I18+R18+W18+AC18+AD18 -> 5657 | T18: =IF(U18<P18*3,0,IF(U18<P18*6,ROUND((Q18+R18+W18+AC18+AD18)*0.75*Assumptions!B113,0),ROUND((Q18+R18+W18+AC18+AD18)*0.75*Assumptions!B114,0))) -> 1492 | U18: =U17+Q18+R18+W18+AC18+AD18 -> 21706 | V18: =IF(AB18>=Assumptions!B107,"Signal 6",IF(AB18>=Assumptions!B106,"Signal 5",IF(AB18>=Assumptions!B105,"Signal 4",IF(AB18>=Assumptions!B104,"Signal 3",IF(AB18>=Assumptions!B103,"Signal 2",IF(AB18>=Assumptions!B102,"Signal 1","Pre-Signal 1")))))) -> Pre-Signal 1 | W18: =ROUND(AB18*Assumptions!B137*Assumptions!B138*Assumptions!B139*Assumptions!B136,0) -> 316 | X18: =ROUND(AB18*Assumptions!B137*Assumptions!B65,0) -> 52 | Y18: =ROUND(Y17*(1+Assumptions!B165),0) -> 317 | Z18: =Assumptions!B156 -> 125 | AA18: =ROUND(Y18*Assumptions!B166,0) -> 1 | AB18: =B18+Z18+AA18 -> 8100.0128 | AC18: =ROUND(IF(A18>=Assumptions!B144,(IF(A18>=25,Assumptions!B151,IF(A18>=16,Assumptions!B150,Assumptions!B149))/1000*Assumptions!B146)+IF(A18>=Assumptions!B145,(IF(A18>=25,Assumptions!B151,IF(A18>=16,Assumptions!B150,Assumptions!B149))*Assumptions!B152/1000*Assumptions!B147),0),0),0) -> 16 | AD18: =IF(Y18>=10000,Assumptions!B170,IF(Y18>=5000,Assumptions!B169,IF(Y18>=2000,Assumptions!B168,IF(Y18>=500,Assumptions!B167,0)))) -> 0
A19: 14 | B19: =B18*(1+Assumptions!B35) -> 9170.1147 | C19: =ROUND(AB19*Assumptions!B25,0) -> 186 | D19: =ROUND(AB19*Assumptions!B24,0) -> 46 | E19: =E18+D19-F19 -> 254 | F19: =ROUND(E18*Assumptions!B45,0) -> 9 | G19: =D19-F19 -> 37 | H19: =ROUND(E19*(Assumptions!B15*0.85+Assumptions!B11*0.15),0) -> 2915 | I19: =H19 -> 2915 | J19: =ROUND(E19*Assumptions!B68,0) -> 889 | K19: =ROUND(J19*Assumptions!B65,0) -> 71 | L19: =Assumptions!B70+IF(E19>Assumptions!B72,45,0) -> 31 | M19: =Assumptions!B76+Assumptions!B77 -> 35 | N19: =Assumptions!B81+Assumptions!B82+Assumptions!B87/12+Assumptions!B148 -> 116 | O19: =ROUND(I19*Assumptions!B85+E19*Assumptions!B86+W19*Assumptions!B85+ROUND(AB19*Assumptions!B137*Assumptions!B138*Assumptions!B139,0)*Assumptions!B86,0) -> 180 | P19: =K19+L19+M19+N19+O19+X19 -> 492 | Q19: =I19-P19 -> 2423 | R19: =ROUND(AB19*Assumptions!B51*Assumptions!B52,0) -> 3254 | S19: =I19+R19+W19+AC19+AD19 -> 6548 | T19: =IF(U19<P19*3,0,IF(U19<P19*6,ROUND((Q19+R19+W19+AC19+AD19)*0.75*Assumptions!B113,0),ROUND((Q19+R19+W19+AC19+AD19)*0.75*Assumptions!B114,0))) -> 1735 | U19: =U18+Q19+R19+W19+AC19+AD19 -> 27762 | V19: =IF(AB19>=Assumptions!B107,"Signal 6",IF(AB19>=Assumptions!B106,"Signal 5",IF(AB19>=Assumptions!B105,"Signal 4",IF(AB19>=Assumptions!B104,"Signal 3",IF(AB19>=Assumptions!B103,"Signal 2",IF(AB19>=Assumptions!B102,"Signal 1","Pre-Signal 1")))))) -> Pre-Signal 1 | W19: =ROUND(AB19*Assumptions!B137*Assumptions!B138*Assumptions!B139*Assumptions!B136,0) -> 363 | X19: =ROUND(AB19*Assumptions!B137*Assumptions!B65,0) -> 59 | Y19: =ROUND(Y18*(1+Assumptions!B165),0) -> 349 | Z19: =Assumptions!B156 -> 125 | AA19: =ROUND(Y19*Assumptions!B166,0) -> 1 | AB19: =B19+Z19+AA19 -> 9296.1147 | AC19: =ROUND(IF(A19>=Assumptions!B144,(IF(A19>=25,Assumptions!B151,IF(A19>=16,Assumptions!B150,Assumptions!B149))/1000*Assumptions!B146)+IF(A19>=Assumptions!B145,(IF(A19>=25,Assumptions!B151,IF(A19>=16,Assumptions!B150,Assumptions!B149))*Assumptions!B152/1000*Assumptions!B147),0),0),0) -> 16 | AD19: =IF(Y19>=10000,Assumptions!B170,IF(Y19>=5000,Assumptions!B169,IF(Y19>=2000,Assumptions!B168,IF(Y19>=500,Assumptions!B167,0)))) -> 0
