Workbook

Sheet Dashboard
A1: MyAdvocate Projections v14 — Executive Dashboard
A2: Source: PMP v19 | Version: v14.0 — March 2026 | Scenarios: Conservative / Expected / Optimistic
A4: KEY METRICS — MONTH 36
B5: Conservative | C5: Expected | D5: Optimistic
A6: Monthly Visitors | B6: =Conservative!B41 -> 9181.6988 | C6: =Expected!B41 -> 52461.702 | D6: =Optimistic!B41 -> 198484.8
A7: Paid Subscribers | B7: =Conservative!E41 -> 92 | C7: =Expected!E41 -> 812 | D7: =Optimistic!E41 -> 5994
A8: MRR | B8: =Conservative!H41 -> 1056 | C8: =Expected!H41 -> 9318 | D8: =Optimistic!H41 -> 68781
A9: Monthly Referral Revenue | B9: =Conservative!R41 -> 3214 | C9: =Expected!R41 -> 18362 | D9: =Optimistic!R41 -> 69470
A10: Per-Case Revenue (M36) | B10: =Conservative!W41 -> 358 | C10: =Expected!W41 -> 2046 | D10: =Optimistic!W41 -> 7741
A11: Total Revenue (M36) | B11: =Conservative!S41 -> 4628 | C11: =Expected!S41 -> 29726 | D11: =Optimistic!S41 -> 145992
A12: Owner's Draw (M36) | B12: =Conservative!T41 -> 1234 | C12: =Expected!T41 -> 8119 | D12: =Optimistic!T41 -> 39722
A13: Reserve Balance | B13: =Conservative!U41 -> 46391 | C13: =Expected!U41 -> 249148 | D13: =Optimistic!U41 -> 1036002
A14: Traffic Signal | B14: =Conservative!V41 -> Pre-Signal 1 | C14: =Expected!V41 -> Signal 3 | D14: =Optimistic!V41 -> Signal 6
A15: 3-Yr Subscription Revenue | B15: =Conservative!I43 -> 12386 | C15: =Expected!I43 -> 82970 | D15: =Optimistic!I43 -> 513896
A16: 3-Yr Total Referral Revenue | B16: =Conservative!R43 -> 39390 | C16: =Expected!R43 -> 166268 | D16: =Optimistic!R43 -> 525609
A17: 3-Yr Per-Case Revenue | B17: =Conservative!W43 -> 4517 | C17: =Expected!W43 -> 18744 | D17: =Optimistic!W43 -> 58915
A18: 3-Yr Total Revenue | B18: =Conservative!S43 -> 56293 | C18: =Expected!S43 -> 267982 | D18: =Optimistic!S43 -> 1098420
A20: CONVERSION & GROWTH ASSUMPTIONS
B21: Conservative | C21: Expected | D21: Optimistic
A22: Paid Conversion Rate | B22: =Assumptions!B22 -> 0.0015 | C22: =Assumptions!B23 -> 0.0025 | D22: =Assumptions!B24 -> 0.005
A23: Monthly Traffic Growth | B23: =Assumptions!B33 -> 0.08 | C23: =Assumptions!B34 -> 0.12 | D23: =Assumptions!B35 -> 0.15
A24: Monthly Churn | B24: =Assumptions!B43 -> 0.08 | C24: =Assumptions!B44 -> 0.06 | D24: =Assumptions!B45 -> 0.04
A25: Per-Case Price | B25: =Assumptions!B136 -> 13 | C25: =Assumptions!B136 -> 13 | D25: =Assumptions!B136 -> 13
A26: Tool Engagement Rate | B26: =Assumptions!B137 -> 0.08 | C26: =Assumptions!B137 -> 0.08 | D26: =Assumptions!B137 -> 0.08

Sheet Assumptions
A1: MyAdvocate Financial Model v14 — Assumptions
A2: Source: PMP v19 | Blue = input (user-editable) | Black = calculated | Green = cross-sheet link
A3: Version: v14.0 — March 2026 | Scenarios: Conservative / Expected / Optimistic
A5: CORE BUSINESS ASSUMPTIONS
A6: Launch Month | B6: 1 | C6: Month 1 = Launch
A7: Planning Horizon (months) | B7: 36 | C7: 3-year projection
A9: PRICING STRUCTURE
A10: Founding Advocate Annual Price | B10: 34 | C10: $34/year — first 250 subs, locked forever
A11: Founding Advocate Monthly Equivalent | B11: =B10/12 -> 2.8333333 | C11: $34/12 — for MRR calculation purposes
A12: Founding Advocate Renewal Price (Year 2+) | B12: 55 | C12: $55/yr — permanent FA rate after Year 1 lock
A13: FA Cohort Cap | B13: 250 | C13: Maximum Founding Advocates — hard cap
A14: Basic Tier Monthly | B14: 8 | C14: Launch tier — all new subs Months 1–8
A15: Standard Tier Monthly (Month 9+) | B15: 13 | C15: Price increase Month 9 — new subs only
A16: Advocate Builder Quarterly | B16: 21 | C16: $21/quarter — alternative entry point
A17: Advocate Builder Monthly Equivalent | B17: =B16/3 -> 7 | C17: $21/3 — for MRR purposes
A18: Annual Standard Price | B18: 55 | C18: $55/yr for committed annual subscribers
A19: Premium Monthly (Phase 4+) | B19: 21 | C19: Native app tier — Phase 4 unlock
A21: CONVERSION RATES — HEALTHCARE COLD TRAFFIC
A22: Conservative Paid Conversion Rate | B22: 0.0015 | C22: 0.15% — cold traffic baseline. Source: PMP v19 §3
A23: Expected Paid Conversion Rate | B23: 0.0025 | C23: 0.25% — moderate, denial-code SEO boost
A24: Optimistic Paid Conversion Rate | B24: 0.005 | C24: 0.50% — high-intent denial code + SEO optimization
A25: Free Signup / Email Capture Rate | B25: 0.02 | C25: 2.0% of visitors — owned email list growth
A26: Denial Decoder Free-to-Paid Lift | B26: 1.15 | C26: 15% higher conversion from denial code page visitors
A27: Founding Advocate Conversion Rate (of early subs) | B27: 0.4 | C27: ~40% of first subs take the FA offer
A29: SEO TRAFFIC GROWTH MODEL
A30: Month 1 Traffic — Conservative | B30: 500 | C30: Minimal launch, no prior SEO momentum
A31: Month 1 Traffic — Expected | B31: 800 | C31: Early SEO content live at launch
A32: Month 1 Traffic — Optimistic | B32: 1200 | C32: Aggressive pre-launch content build
A33: Monthly Traffic Growth — Conservative | B33: 0.08 | C33: 8% MoM — slow organic compounding
A34: Monthly Traffic Growth — Expected | B34: 0.12 | C34: 12% MoM — consistent 2x/week publishing
A35: Monthly Traffic Growth — Optimistic | B35: 0.15 | C35: 15% MoM — aggressive SEO + denial codes indexing fast
A36: Denial Code Program Traffic Boost (Month 3+) | B36: 1.15 | C36: 15% additional traffic lift from 200+ denial code pages indexing
A37: Content Cluster Maturity Boost (Month 6+) | B37: 1.08 | C37: 8% additional lift as pillar/cluster architecture matures
A38: Publishing Cadence (articles/week) | B38: 2 | C38: 2x/week per PMP v19 §4C — sustained from Month 1
A39: Denial Code Pages (Month 3 launch) | B39: 200 | C39: 200 denial code pages built — one-time SEO asset
A40: Month 12 Cumulative Articles Target | B40: 60 | C40: ~2x/week × 26 weeks = ~52 articles + backlog
A42: CHURN & RETENTION
A43: Monthly Churn — Conservative | B43: 0.08 | C43: 8% monthly churn — challenging retention environment
A44: Monthly Churn — Expected | B44: 0.06 | C44: 6% monthly churn — decent product-market fit
A45: Monthly Churn — Optimistic | B45: 0.04 | C45: 4% monthly churn — strong engagement, content value
A46: Founding Advocate Churn Rate | B46: 0.02 | C46: 2% — locked pricing creates loyalty. Grandfathered rate.
A47: Annual Subscriber Churn Rate | B47: 0.04 | C47: 4% annual — commitment reduces churn significantly
A49: ATTORNEY REFERRAL ECONOMICS — TRAFFIC-BASED FLAT RATE
A50: Referral Program Start Month | B50: 6 | C50: Month 6 — Signal 1 gate. Source: PMP v19 §3
A51: Referral Conversion Rate (of monthly visitors) | B51: 0.001 | C51: 0.1% of monthly visitors → referred. Traffic-based. Living assumption.
A52: Blended Revenue per Referral ($) | B52: 350 | C52: $350 blended — midpoint of $300–$400 range. Update with actuals.
A64: COSTS — API & INFRASTRUCTURE
A65: Cost per Letter Generation (Claude API) | B65: 0.08 | C65: Per letter — Claude claude-sonnet-4-6. Source: PMP v19 §8C
A66: Cost per Denial Decoder Lookup | B66: 0.01 | C66: Minimal API — structured lookup, short prompt
A67: Cost per Document Parse | B67: 0.05 | C67: Bounded document parsing — Phase 1 feature
A68: Letters per Paid Sub per Month | B68: 3.5 | C68: Average usage — 2 tools × ~1.75 letters each
A69: Denial Decoder Lookups per User per Month (free) | B69: 5 | C69: Free tier usage — no signup required
A70: Base Infrastructure Monthly | B70: 31 | C70: Vercel free + Supabase free + DO Droplet $6 + domain ~$1/mo
A71: Anthropic API Hard Cap Monthly | B71: 200 | C71: Emergency shutoff cap — CTO Sentinel monitors
A72: Infrastructure Scale Threshold (subs) | B72: 500 | C72: Upgrade Vercel/Supabase to paid at ~500 subs ($25+$20/mo more)
A74: COSTS — CONTENT & SEO
A75: Content Production Cost per Article | B75: 0 | C75: Founder-written Phase 1 — $0 direct cost
A76: SEO Tool Stack Monthly (Ahrefs Lite) | B76: 29 | C76: Ahrefs Lite $29/mo. GSC free. Buffer $6/mo included below.
A77: Social Scheduling (Buffer) | B77: 6 | C77: $6/mo for cross-platform scheduling
A78: Denial Code Database Build Cost | B78: 0 | C78: Founder-built — data is public (CMS codes, CARC codes)
A80: COSTS — PLATFORM OPERATIONS
A81: n8n Pro Monthly | B81: 20 | C81: Board of Agents automation platform
A82: Claude Code Monthly (Founder Dev) | B82: 20 | C82: Anthropic Pro plan — development only, not user-facing
A83: Beehiiv Monthly (to 1k subs) | B83: 0 | C83: Free tier covers first 1,000 email subscribers
A84: Beehiiv Monthly (1k+ subs) | B84: 42 | C84: $42/mo Beehiiv Scale — activates at ~1k email subs (~Month 12)
A85: Stripe Transaction Fee % | B85: 0.029 | C85: 2.9% per transaction
A86: Stripe Fixed Fee per Transaction | B86: 0.3 | C86: $0.30 per transaction
A87: Google Workspace + Domain Annual | B87: 120 | C87: $10/mo equiv — sarsh@getmyadvocate.org + domain
A93: ONE-TIME LAUNCH COSTS
A94: Healthcare Compliance Attorney Review | B94: 2250 | C94: $1,500–$3,000 range — using midpoint. Source: PMP v19 §11
A95: Security Audit (External) | B95: 500 | C95: External audit — Month 1 launch blocker
A96: LLC Formation / DBA Registration | B96: 500 | C96: Already done — included for completeness
A97: Total One-Time Launch Costs | B97: =B94+B95+B96 -> 3250 | C97: Sum of one-time items
A101: TRAFFIC MILESTONE GATES — PMP v19 §3
A102: Signal 1 — Phase 2 Unlock | B102: 10000 | C102: 10,000 monthly visitors. Referral outreach + CMO/COO agents
A103: Signal 2 — Phase 3 Unlock | B103: 25000 | C103: 25,000 monthly visitors AND $5,000 MRR. CSO/CPO agents
A104: Signal 3 — Fractional Hire Consider | B104: 40000 | C104: 40,000 monthly visitors. Referral automation, fractional help
A105: Signal 4 — Phase 4 Scale | B105: 65000 | C105: 65,000 monthly visitors AND $15,000 MRR. Full agent stack
A106: Signal 5 — B2B + Native App | B106: 110000 | C106: 110,000 monthly visitors. B2B outreach, VA hire
A107: Signal 6 — First Full-Time Hire Assessment | B107: 175000 | C107: 175,000 monthly visitors. Full-time transition review
A108: Signal 2 MRR Gate | B108: 5000 | C108: $5,000 MRR required alongside Signal 2 traffic
A109: Signal 4 MRR Gate | B109: 15000 | C109: $15,000 MRR required alongside Signal 4 traffic
A111: FOUNDER COMPENSATION — PHASE-GATED WITHDRAWAL RATES
A112: Phase 1 Withdrawal Rate | B112: 0 | C112: 0% — all profit builds reserve. No exceptions.
A113: Phase 2 Withdrawal Rate (Baseline) | B113: 0.236 | C113: 23.6% of monthly profit — Phase 2 standard
A114: Phase 3 Withdrawal Rate (Baseline) | B114: 0.382 | C114: 38.2% of monthly profit — Phase 3 standard
A115: Phase 4 Withdrawal Rate (Baseline) | B115: 0.618 | C115: 61.8% of monthly profit — Phase 4 standard
A116: Native App Development Fund % | B116: 0.2 | C116: 20% of monthly profit → app development fund
A117: Phase 2 Reserve Floor (months of opex) | B117: 3 | C117: 3-month reserve required for Phase 2 withdrawal
A118: Phase 3 Reserve Floor (months of opex) | B118: 6 | C118: 6-month reserve required for Phase 3 withdrawal + PRW quarterly
A119: Phase 4 Reserve Floor (months of opex) | B119: 12 | C119: 12-month reserve for Phase 4 withdrawal
A121: PROFIT RELEASE WINDOWS — DISCRETIONARY DRAW CAPS
A122: Level 4-5 (Phase 2) Quarterly Reserve Bar | B122: 4 | C122: 4 months — standard quarterly PRW bar
A123: Level 4-5 (Phase 2) Monthly Trigger Reserve Bar | B123: 6 | C123: 6 months — higher bar for monthly trigger option
A124: Level 4-5 Discretionary Cap | B124: 0.35 | C124: 35% of monthly profit — max with health check
A125: Level 6-7 (Phase 3) Quarterly Reserve Bar | B125: 6 | C125: 6 months
A126: Level 6-7 (Phase 3) Monthly Trigger Reserve Bar | B126: 8 | C126: 8 months
A127: Level 6-7 Discretionary Cap | B127: 0.55 | C127: 55% of monthly profit
A128: Level 8 (Phase 4) Quarterly Reserve Bar | B128: 8 | C128: 8 months
A129: Level 8 Monthly Trigger Reserve Bar | B129: 10 | C129: 10 months
...

Sheet Conservative
A1: CONSERVATIVE SCENARIO — Conservative Growth
A2: 0.15% paid conversion | 8% MoM traffic growth | 8% monthly churn | Referral: 0.1% of visitors x $350 blended
A3: Blue = hardcoded inputs | Black = calculated formulas | Green = Assumptions references
A5: Month | B5: Monthly Visitors | C5: Free Signups (Email 2%) | D5: New Paid Subs | E5: Total Paid Subs | F5: Churn This Month | G5: Net New Subs | H5: MRR ($) | I5: Monthly Revenue ($) | J5: Letter Generations | K5: API Costs ($) | L5: Infrastructure ($) | M5: Content/SEO ($) | N5: n8n + Tools ($) | O5: Stripe Fees ($) | P5: Total Costs ($) | Q5: Gross Profit ($) | R5: Referral Revenue ($) | S5: Total Revenue ($) | T5: Owner's Draw ($) | U5: Reserve Balance ($) | V5: Traffic Signal | W5: Per-Case Revenue ($) | X5: Free Tier API Cost ($)
A6: 1 | B6: =Assumptions!B30 -> 500 | C6: =ROUND(B6*Assumptions!B25,0) -> 10 | D6: =ROUND(B6*Assumptions!B22,0) -> 1 | E6: =D6 -> 1 | F6: =0 -> 0 | G6: =D6-F6 -> 1 | H6: =ROUND(E6*Assumptions!B14,0) -> 8 | I6: =H6 -> 8 | J6: =ROUND(E6*Assumptions!B68,0) -> 4 | K6: =ROUND(J6*Assumptions!B65,0) -> 0 | L6: =Assumptions!B70+IF(E6>Assumptions!B72,45,0) -> 31 | M6: =Assumptions!B94+Assumptions!B95+Assumptions!B76+Assumptions!B77 -> 2785 | N6: =Assumptions!B81+Assumptions!B82+Assumptions!B87/12 -> 50 | O6: =ROUND(I6*Assumptions!B85+E6*Assumptions!B86+W6*Assumptions!B85+ROUND(B6*Assumptions!B137*Assumptions!B138*Assumptions!B139,0)*Assumptions!B86,0) -> 2 | P6: =K6+L6+M6+N6+O6+X6 -> 2871 | Q6: =I6-P6 -> -2863 | R6: =0 -> 0 | S6: =I6+R6+W6 -> 28 | T6: =IF(U6<P6*3,0,IF(U6<P6*6,ROUND((Q6+R6+W6)*0.75*Assumptions!B113,0),ROUND((Q6+R6+W6)*0.75*Assumptions!B114,0))) -> 0 | U6: =Q6+R6+W6 -> -2843 | V6: =IF(B6>=Assumptions!B107,"Signal 6",IF(B6>=Assumptions!B106,"Signal 5",IF(B6>=Assumptions!B105,"Signal 4",IF(B6>=Assumptions!B104,"Signal 3",IF(B6>=Assumptions!B103,"Signal 2",IF(B6>=Assumptions!B102,"Signal 1","Pre-Signal 1")))))) -> Pre-Signal 1 | W6: =ROUND(B6*Assumptions!B137*Assumptions!B138*Assumptions!B139*Assumptions!B136,0) -> 20 | X6: =ROUND(B6*Assumptions!B137*Assumptions!B65,0) -> 3
A7: 2 | B7: =B6*(1+Assumptions!B33) -> 540 | C7: =ROUND(B7*Assumptions!B25,0) -> 11 | D7: =ROUND(B7*Assumptions!B22,0) -> 1 | E7: =E6+D7-F7 -> 2 | F7: =ROUND(E6*Assumptions!B43,0) -> 0 | G7: =D7-F7 -> 1 | H7: =ROUND(E7*Assumptions!B14,0) -> 16 | I7: =H7 -> 16 | J7: =ROUND(E7*Assumptions!B68,0) -> 7 | K7: =ROUND(J7*Assumptions!B65,0) -> 1 | L7: =Assumptions!B70+IF(E7>Assumptions!B72,45,0) -> 31 | M7: =Assumptions!B76+Assumptions!B77 -> 35 | N7: =Assumptions!B81+Assumptions!B82+Assumptions!B87/12 -> 50 | O7: =ROUND(I7*Assumptions!B85+E7*Assumptions!B86+W7*Assumptions!B85+ROUND(B7*Assumptions!B137*Assumptions!B138*Assumptions!B139,0)*Assumptions!B86,0) -> 2 | P7: =K7+L7+M7+N7+O7+X7 -> 122 | Q7: =I7-P7 -> -106 | R7: =0 -> 0 | S7: =I7+R7+W7 -> 37 | T7: =IF(U7<P7*3,0,IF(U7<P7*6,ROUND((Q7+R7+W7)*0.75*Assumptions!B113,0),ROUND((Q7+R7+W7)*0.75*Assumptions!B114,0))) -> 0 | U7: =U6+Q7+R7+W7 -> -2928 | V7: =IF(B7>=Assumptions!B107,"Signal 6",IF(B7>=Assumptions!B106,"Signal 5",IF(B7>=Assumptions!B105,"Signal 4",IF(B7>=Assumptions!B104,"Signal 3",IF(B7>=Assumptions!B103,"Signal 2",IF(B7>=Assumptions!B102,"Signal 1","Pre-Signal 1")))))) -> Pre-Signal 1 | W7: =ROUND(B7*Assumptions!B137*Assumptions!B138*Assumptions!B139*Assumptions!B136,0) -> 21 | X7: =ROUND(B7*Assumptions!B137*Assumptions!B65,0) -> 3
A8: 3 | B8: =B7*(1+Assumptions!B33)*Assumptions!B36 -> 670.68 | C8: =ROUND(B8*Assumptions!B25,0) -> 13 | D8: =ROUND(B8*Assumptions!B22,0) -> 1 | E8: =E7+D8-F8 -> 3 | F8: =ROUND(E7*Assumptions!B43,0) -> 0 | G8: =D8-F8 -> 1 | H8: =ROUND(E8*Assumptions!B14,0) -> 24 | I8: =H8 -> 24 | J8: =ROUND(E8*Assumptions!B68,0) -> 11 | K8: =ROUND(J8*Assumptions!B65,0) -> 1 | L8: =Assumptions!B70+IF(E8>Assumptions!B72,45,0) -> 31 | M8: =Assumptions!B76+Assumptions!B77 -> 35 | N8: =Assumptions!B81+Assumptions!B82+Assumptions!B87/12 -> 50 | O8: =ROUND(I8*Assumptions!B85+E8*Assumptions!B86+W8*Assumptions!B85+ROUND(B8*Assumptions!B137*Assumptions!B138*Assumptions!B139,0)*Assumptions!B86,0) -> 3 | P8: =K8+L8+M8+N8+O8+X8 -> 124 | Q8: =I8-P8 -> -100 | R8: =0 -> 0 | S8: =I8+R8+W8 -> 50 | T8: =IF(U8<P8*3,0,IF(U8<P8*6,ROUND((Q8+R8+W8)*0.75*Assumptions!B113,0),ROUND((Q8+R8+W8)*0.75*Assumptions!B114,0))) -> 0 | U8: =U7+Q8+R8+W8 -> -3002 | V8: =IF(B8>=Assumptions!B107,"Signal 6",IF(B8>=Assumptions!B106,"Signal 5",IF(B8>=Assumptions!B105,"Signal 4",IF(B8>=Assumptions!B104,"Signal 3",IF(B8>=Assumptions!B103,"Signal 2",IF(B8>=Assumptions!B102,"Signal 1","Pre-Signal 1")))))) -> Pre-Signal 1 | W8: =ROUND(B8*Assumptions!B137*Assumptions!B138*Assumptions!B139*Assumptions!B136,0) -> 26 | X8: =ROUND(B8*Assumptions!B137*Assumptions!B65,0) -> 4
A9: 4 | B9: =B8*(1+Assumptions!B33) -> 724.3344 | C9: =ROUND(B9*Assumptions!B25,0) -> 14 | D9: =ROUND(B9*Assumptions!B22,0) -> 1 | E9: =E8+D9-F9 -> 4 | F9: =ROUND(E8*Assumptions!B43,0) -> 0 | G9: =D9-F9 -> 1 | H9: =ROUND(E9*Assumptions!B14,0) -> 32 | I9: =H9 -> 32 | J9: =ROUND(E9*Assumptions!B68,0) -> 14 | K9: =ROUND(J9*Assumptions!B65,0) -> 1 | L9: =Assumptions!B70+IF(E9>Assumptions!B72,45,0) -> 31 | M9: =Assumptions!B76+Assumptions!B77 -> 35 | N9: =Assumptions!B81+Assumptions!B82+Assumptions!B87/12 -> 50 | O9: =ROUND(I9*Assumptions!B85+E9*Assumptions!B86+W9*Assumptions!B85+ROUND(B9*Assumptions!B137*Assumptions!B138*Assumptions!B139,0)*Assumptions!B86,0) -> 4 | P9: =K9+L9+M9+N9+O9+X9 -> 126 | Q9: =I9-P9 -> -94 | R9: =0 -> 0 | S9: =I9+R9+W9 -> 60 | T9: =IF(U9<P9*3,0,IF(U9<P9*6,ROUND((Q9+R9+W9)*0.75*Assumptions!B113,0),ROUND((Q9+R9+W9)*0.75*Assumptions!B114,0))) -> 0 | U9: =U8+Q9+R9+W9 -> -3068 | V9: =IF(B9>=Assumptions!B107,"Signal 6",IF(B9>=Assumptions!B106,"Signal 5",IF(B9>=Assumptions!B105,"Signal 4",IF(B9>=Assumptions!B104,"Signal 3",IF(B9>=Assumptions!B103,"Signal 2",IF(B9>=Assumptions!B102,"Signal 1","Pre-Signal 1")))))) -> Pre-Signal 1 | W9: =ROUND(B9*Assumptions!B137*Assumptions!B138*Assumptions!B139*Assumptions!B136,0) -> 28 | X9: =ROUND(B9*Assumptions!B137*Assumptions!B65,0) -> 5
A10: 5 | B10: =B9*(1+Assumptions!B33) -> 782.28115 | C10: =ROUND(B10*Assumptions!B25,0) -> 16 | D10: =ROUND(B10*Assumptions!B22,0) -> 1 | E10: =E9+D10-F10 -> 5 | F10: =ROUND(E9*Assumptions!B43,0) -> 0 | G10: =D10-F10 -> 1 | H10: =ROUND(E10*Assumptions!B14,0) -> 40 | I10: =H10 -> 40 | J10: =ROUND(E10*Assumptions!B68,0) -> 18 | K10: =ROUND(J10*Assumptions!B65,0) -> 1 | L10: =Assumptions!B70+IF(E10>Assumptions!B72,45,0) -> 31 | M10: =Assumptions!B76+Assumptions!B77 -> 35 | N10: =Assumptions!B81+Assumptions!B82+Assumptions!B87/12 -> 50 | O10: =ROUND(I10*Assumptions!B85+E10*Assumptions!B86+W10*Assumptions!B85+ROUND(B10*Assumptions!B137*Assumptions!B138*Assumptions!B139,0)*Assumptions!B86,0) -> 4 | P10: =K10+L10+M10+N10+O10+X10 -> 126 | Q10: =I10-P10 -> -86 | R10: =0 -> 0 | S10: =I10+R10+W10 -> 71 | T10: =IF(U10<P10*3,0,IF(U10<P10*6,ROUND((Q10+R10+W10)*0.75*Assumptions!B113,0),ROUND((Q10+R10+W10)*0.75*Assumptions!B114,0))) -> 0 | U10: =U9+Q10+R10+W10 -> -3123 | V10: =IF(B10>=Assumptions!B107,"Signal 6",IF(B10>=Assumptions!B106,"Signal 5",IF(B10>=Assumptions!B105,"Signal 4",IF(B10>=Assumptions!B104,"Signal 3",IF(B10>=Assumptions!B103,"Signal 2",IF(B10>=Assumptions!B102,"Signal 1","Pre-Signal 1")))))) -> Pre-Signal 1 | W10: =ROUND(B10*Assumptions!B137*Assumptions!B138*Assumptions!B139*Assumptions!B136,0) -> 31 | X10: =ROUND(B10*Assumptions!B137*Assumptions!B65,0) -> 5
A11: 6 | B11: =B10*(1+Assumptions!B33)*Assumptions!B37 -> 912.45274 | C11: =ROUND(B11*Assumptions!B25,0) -> 18 | D11: =ROUND(B11*Assumptions!B22,0) -> 1 | E11: =E10+D11-F11 -> 6 | F11: =ROUND(E10*Assumptions!B43,0) -> 0 | G11: =D11-F11 -> 1 | H11: =ROUND(E11*Assumptions!B14,0) -> 48 | I11: =H11 -> 48 | J11: =ROUND(E11*Assumptions!B68,0) -> 21 | K11: =ROUND(J11*Assumptions!B65,0) -> 2 | L11: =Assumptions!B70+IF(E11>Assumptions!B72,45,0) -> 31 | M11: =Assumptions!B76+Assumptions!B77 -> 35 | N11: =Assumptions!B81+Assumptions!B82+Assumptions!B87/12 -> 50 | O11: =ROUND(I11*Assumptions!B85+E11*Assumptions!B86+W11*Assumptions!B85+ROUND(B11*Assumptions!B137*Assumptions!B138*Assumptions!B139,0)*Assumptions!B86,0) -> 5 | P11: =K11+L11+M11+N11+O11+X11 -> 129 | Q11: =I11-P11 -> -81 | R11: =ROUND(B11*Assumptions!B51*Assumptions!B52,0) -> 319 | S11: =I11+R11+W11 -> 403 | T11: =IF(U11<P11*3,0,IF(U11<P11*6,ROUND((Q11+R11+W11)*0.75*Assumptions!B113,0),ROUND((Q11+R11+W11)*0.75*Assumptions!B114,0))) -> 0 | U11: =U10+Q11+R11+W11 -> -2849 | V11: =IF(B11>=Assumptions!B107,"Signal 6",IF(B11>=Assumptions!B106,"Signal 5",IF(B11>=Assumptions!B105,"Signal 4",IF(B11>=Assumptions!B104,"Signal 3",IF(B11>=Assumptions!B103,"Signal 2",IF(B11>=Assumptions!B102,"Signal 1","Pre-Signal 1")))))) -> Pre-Signal 1 | W11: =ROUND(B11*Assumptions!B137*Assumptions!B138*Assumptions!B139*Assumptions!B136,0) -> 36 | X11: =ROUND(B11*Assumptions!B137*Assumptions!B65,0) -> 6
A12: 7 | B12: =B11*(1+Assumptions!B33) -> 985.44895 | C12: =ROUND(B12*Assumptions!B25,0) -> 20 | D12: =ROUND(B12*Assumptions!B22,0) -> 1 | E12: =E11+D12-F12 -> 7 | F12: =ROUND(E11*Assumptions!B43,0) -> 0 | G12: =D12-F12 -> 1 | H12: =ROUND(E12*Assumptions!B14,0) -> 56 | I12: =H12 -> 56 | J12: =ROUND(E12*Assumptions!B68,0) -> 25 | K12: =ROUND(J12*Assumptions!B65,0) -> 2 | L12: =Assumptions!B70+IF(E12>Assumptions!B72,45,0) -> 31 | M12: =Assumptions!B76+Assumptions!B77 -> 35 | N12: =Assumptions!B81+Assumptions!B82+Assumptions!B87/12 -> 50 | O12: =ROUND(I12*Assumptions!B85+E12*Assumptions!B86+W12*Assumptions!B85+ROUND(B12*Assumptions!B137*Assumptions!B138*Assumptions!B139,0)*Assumptions!B86,0) -> 6 | P12: =K12+L12+M12+N12+O12+X12 -> 130 | Q12: =I12-P12 -> -74 | R12: =ROUND(B12*Assumptions!B51*Assumptions!B52,0) -> 345 | S12: =I12+R12+W12 -> 439 | T12: =IF(U12<P12*3,0,IF(U12<P12*6,ROUND((Q12+R12+W12)*0.75*Assumptions!B113,0),ROUND((Q12+R12+W12)*0.75*Assumptions!B114,0))) -> 0 | U12: =U11+Q12+R12+W12 -> -2540 | V12: =IF(B12>=Assumptions!B107,"Signal 6",IF(B12>=Assumptions!B106,"Signal 5",IF(B12>=Assumptions!B105,"Signal 4",IF(B12>=Assumptions!B104,"Signal 3",IF(B12>=Assumptions!B103,"Signal 2",IF(B12>=Assumptions!B102,"Signal 1","Pre-Signal 1")))))) -> Pre-Signal 1 | W12: =ROUND(B12*Assumptions!B137*Assumptions!B138*Assumptions!B139*Assumptions!B136,0) -> 38 | X12: =ROUND(B12*Assumptions!B137*Assumptions!B65,0) -> 6
A13: 8 | B13: =B12*(1+Assumptions!B33) -> 1064.2849 | C13: =ROUND(B13*Assumptions!B25,0) -> 21 | D13: =ROUND(B13*Assumptions!B22,0) -> 2 | E13: =E12+D13-F13 -> 8 | F13: =ROUND(E12*Assumptions!B43,0) -> 1 | G13: =D13-F13 -> 1 | H13: =ROUND(E13*Assumptions!B14,0) -> 64 | I13: =H13 -> 64 | J13: =ROUND(E13*Assumptions!B68,0) -> 28 | K13: =ROUND(J13*Assumptions!B65,0) -> 2 | L13: =Assumptions!B70+IF(E13>Assumptions!B72,45,0) -> 31 | M13: =Assumptions!B76+Assumptions!B77 -> 35 | N13: =Assumptions!B81+Assumptions!B82+Assumptions!B87/12 -> 50 | O13: =ROUND(I13*Assumptions!B85+E13*Assumptions!B86+W13*Assumptions!B85+ROUND(B13*Assumptions!B137*Assumptions!B138*Assumptions!B139,0)*Assumptions!B86,0) -> 6 | P13: =K13+L13+M13+N13+O13+X13 -> 131 | Q13: =I13-P13 -> -67 | R13: =ROUND(B13*Assumptions!B51*Assumptions!B52,0) -> 372 | S13: =I13+R13+W13 -> 478 | T13: =IF(U13<P13*3,0,IF(U13<P13*6,ROUND((Q13+R13+W13)*0.75*Assumptions!B113,0),ROUND((Q13+R13+W13)*0.75*Assumptions!B114,0))) -> 0 | U13: =U12+Q13+R13+W13 -> -2193 | V13: =IF(B13>=Assumptions!B107,"Signal 6",IF(B13>=Assumptions!B106,"Signal 5",IF(B13>=Assumptions!B105,"Signal 4",IF(B13>=Assumptions!B104,"Signal 3",IF(B13>=Assumptions!B103,"Signal 2",IF(B13>=Assumptions!B102,"Signal 1","Pre-Signal 1")))))) -> Pre-Signal 1 | W13: =ROUND(B13*Assumptions!B137*Assumptions!B138*Assumptions!B139*Assumptions!B136,0) -> 42 | X13: =ROUND(B13*Assumptions!B137*Assumptions!B65,0) -> 7
A14: 9 | B14: =B13*(1+Assumptions!B33) -> 1149.4277 | C14: =ROUND(B14*Assumptions!B25,0) -> 23 | D14: =ROUND(B14*Assumptions!B22,0) -> 2 | E14: =E13+D14-F14 -> 9 | F14: =ROUND(E13*Assumptions!B43,0) -> 1 | G14: =D14-F14 -> 1 | H14: =ROUND(E14*((Assumptions!B14+Assumptions!B15)/2),0) -> 95 | I14: =H14 -> 95 | J14: =ROUND(E14*Assumptions!B68,0) -> 32 | K14: =ROUND(J14*Assumptions!B65,0) -> 3 | L14: =Assumptions!B70+IF(E14>Assumptions!B72,45,0) -> 31 | M14: =Assumptions!B76+Assumptions!B77 -> 35 | N14: =Assumptions!B81+Assumptions!B82+Assumptions!B87/12 -> 50 | O14: =ROUND(I14*Assumptions!B85+E14*Assumptions!B86+W14*Assumptions!B85+ROUND(B14*Assumptions!B137*Assumptions!B138*Assumptions!B139,0)*Assumptions!B86,0) -> 8 | P14: =K14+L14+M14+N14+O14+X14 -> 134 | Q14: =I14-P14 -> -39 | R14: =ROUND(B14*Assumptions!B51*Assumptions!B52,0) -> 402 | S14: =I14+R14+W14 -> 542 | T14: =IF(U14<P14*3,0,IF(U14<P14*6,ROUND((Q14+R14+W14)*0.75*Assumptions!B113,0),ROUND((Q14+R14+W14)*0.75*Assumptions!B114,0))) -> 0 | U14: =U13+Q14+R14+W14 -> -1785 | V14: =IF(B14>=Assumptions!B107,"Signal 6",IF(B14>=Assumptions!B106,"Signal 5",IF(B14>=Assumptions!B105,"Signal 4",IF(B14>=Assumptions!B104,"Signal 3",IF(B14>=Assumptions!B103,"Signal 2",IF(B14>=Assumptions!B102,"Signal 1","Pre-Signal 1")))))) -> Pre-Signal 1 | W14: =ROUND(B14*Assumptions!B137*Assumptions!B138*Assumptions!B139*Assumptions!B136,0) -> 45 | X14: =ROUND(B14*Assumptions!B137*Assumptions!B65,0) -> 7
A15: 10 | B15: =B14*(1+Assumptions!B33) -> 1241.3819 | C15: =ROUND(B15*Assumptions!B25,0) -> 25 | D15: =ROUND(B15*Assumptions!B22,0) -> 2 | E15: =E14+D15-F15 -> 10 | F15: =ROUND(E14*Assumptions!B43,0) -> 1 | G15: =D15-F15 -> 1 | H15: =ROUND(E15*(Assumptions!B15*0.85+Assumptions!B11*0.15),0) -> 115 | I15: =H15 -> 115 | J15: =ROUND(E15*Assumptions!B68,0) -> 35 | K15: =ROUND(J15*Assumptions!B65,0) -> 3 | L15: =Assumptions!B70+IF(E15>Assumptions!B72,45,0) -> 31 | M15: =Assumptions!B76+Assumptions!B77 -> 35 | N15: =Assumptions!B81+Assumptions!B82+Assumptions!B87/12 -> 50 | O15: =ROUND(I15*Assumptions!B85+E15*Assumptions!B86+W15*Assumptions!B85+ROUND(B15*Assumptions!B137*Assumptions!B138*Assumptions!B139,0)*Assumptions!B86,0) -> 9 | P15: =K15+L15+M15+N15+O15+X15 -> 136 | Q15: =I15-P15 -> -21 | R15: =ROUND(B15*Assumptions!B51*Assumptions!B52,0) -> 434 | S15: =I15+R15+W15 -> 597 | T15: =IF(U15<P15*3,0,IF(U15<P15*6,ROUND((Q15+R15+W15)*0.75*Assumptions!B113,0),ROUND((Q15+R15+W15)*0.75*Assumptions!B114,0))) -> 0 | U15: =U14+Q15+R15+W15 -> -1324 | V15: =IF(B15>=Assumptions!B107,"Signal 6",IF(B15>=Assumptions!B106,"Signal 5",IF(B15>=Assumptions!B105,"Signal 4",IF(B15>=Assumptions!B104,"Signal 3",IF(B15>=Assumptions!B103,"Signal 2",IF(B15>=Assumptions!B102,"Signal 1","Pre-Signal 1")))))) -> Pre-Signal 1 | W15: =ROUND(B15*Assumptions!B137*Assumptions!B138*Assumptions!B139*Assumptions!B136,0) -> 48 | X15: =ROUND(B15*Assumptions!B137*Assumptions!B65,0) -> 8
A16: 11 | B16: =B15*(1+Assumptions!B33) -> 1340.6924 | C16: =ROUND(B16*Assumptions!B25,0) -> 27 | D16: =ROUND(B16*Assumptions!B22,0) -> 2 | E16: =E15+D16-F16 -> 11 | F16: =ROUND(E15*Assumptions!B43,0) -> 1 | G16: =D16-F16 -> 1 | H16: =ROUND(E16*(Assumptions!B15*0.85+Assumptions!B11*0.15),0) -> 126 | I16: =H16 -> 126 | J16: =ROUND(E16*Assumptions!B68,0) -> 39 | K16: =ROUND(J16*Assumptions!B65,0) -> 3 | L16: =Assumptions!B70+IF(E16>Assumptions!B72,45,0) -> 31 | M16: =Assumptions!B76+Assumptions!B77 -> 35 | N16: =Assumptions!B81+Assumptions!B82+Assumptions!B87/12 -> 50 | O16: =ROUND(I16*Assumptions!B85+E16*Assumptions!B86+W16*Assumptions!B85+ROUND(B16*Assumptions!B137*Assumptions!B138*Assumptions!B139,0)*Assumptions!B86,0) -> 10 | P16: =K16+L16+M16+N16+O16+X16 -> 138 | Q16: =I16-P16 -> -12 | R16: =ROUND(B16*Assumptions!B51*Assumptions!B52,0) -> 469 | S16: =I16+R16+W16 -> 647 | T16: =IF(U16<P16*3,0,IF(U16<P16*6,ROUND((Q16+R16+W16)*0.75*Assumptions!B113,0),ROUND((Q16+R16+W16)*0.75*Assumptions!B114,0))) -> 0 | U16: =U15+Q16+R16+W16 -> -815 | V16: =IF(B16>=Assumptions!B107,"Signal 6",IF(B16>=Assumptions!B106,"Signal 5",IF(B16>=Assumptions!B105,"Signal 4",IF(B16>=Assumptions!B104,"Signal 3",IF(B16>=Assumptions!B103,"Signal 2",IF(B16>=Assumptions!B102,"Signal 1","Pre-Signal 1")))))) -> Pre-Signal 1 | W16: =ROUND(B16*Assumptions!B137*Assumptions!B138*Assumptions!B139*Assumptions!B136,0) -> 52 | X16: =ROUND(B16*Assumptions!B137*Assumptions!B65,0) -> 9
A17: 12 | B17: =B16*(1+Assumptions!B33) -> 1447.9478 | C17: =ROUND(B17*Assumptions!B25,0) -> 29 | D17: =ROUND(B17*Assumptions!B22,0) -> 2 | E17: =E16+D17-F17 -> 12 | F17: =ROUND(E16*Assumptions!B43,0) -> 1 | G17: =D17-F17 -> 1 | H17: =ROUND(E17*(Assumptions!B15*0.85+Assumptions!B11*0.15),0) -> 138 | I17: =H17 -> 138 | J17: =ROUND(E17*Assumptions!B68,0) -> 42 | K17: =ROUND(J17*Assumptions!B65,0) -> 3 | L17: =Assumptions!B70+IF(E17>Assumptions!B72,45,0) -> 31 | M17: =Assumptions!B76+Assumptions!B77 -> 35 | N17: =Assumptions!B81+Assumptions!B82+Assumptions!B87/12 -> 50 | O17: =ROUND(I17*Assumptions!B85+E17*Assumptions!B86+W17*Assumptions!B85+ROUND(B17*Assumptions!B137*Assumptions!B138*Assumptions!B139,0)*Assumptions!B86,0) -> 10 | P17: =K17+L17+M17+N17+O17+X17 -> 138 | Q17: =I17-P17 -> 0 | R17: =ROUND(B17*Assumptions!B51*Assumptions!B52,0) -> 507 | S17: =I17+R17+W17 -> 701 | T17: =IF(U17<P17*3,0,IF(U17<P17*6,ROUND((Q17+R17+W17)*0.75*Assumptions!B113,0),ROUND((Q17+R17+W17)*0.75*Assumptions!B114,0))) -> 0 | U17: =U16+Q17+R17+W17 -> -252 | V17: =IF(B17>=Assumptions!B107,"Signal 6",IF(B17>=Assumptions!B106,"Signal 5",IF(B17>=Assumptions!B105,"Signal 4",IF(B17>=Assumptions!B104,"Signal 3",IF(B17>=Assumptions!B103,"Signal 2",IF(B17>=Assumptions!B102,"Signal 1","Pre-Signal 1")))))) -> Pre-Signal 1 | W17: =ROUND(B17*Assumptions!B137*Assumptions!B138*Assumptions!B139*Assumptions!B136,0) -> 56 | X17: =ROUND(B17*Assumptions!B137*Assumptions!B65,0) -> 9
A18: 13 | B18: =B17*(1+Assumptions!B33) -> 1563.7836 | C18: =ROUND(B18*Assumptions!B25,0) -> 31 | D18: =ROUND(B18*Assumptions!B22,0) -> 2 | E18: =E17+D18-F18 -> 13 | F18: =ROUND(E17*Assumptions!B43,0) -> 1 | G18: =D18-F18 -> 1 | H18: =ROUND(E18*(Assumptions!B15*0.85+Assumptions!B11*0.15),0) -> 149 | I18: =H18 -> 149 | J18: =ROUND(E18*Assumptions!B68,0) -> 46 | K18: =ROUND(J18*Assumptions!B65,0) -> 4 | L18: =Assumptions!B70+IF(E18>Assumptions!B72,45,0) -> 31 | M18: =Assumptions!B76+Assumptions!B77 -> 35 | N18: =Assumptions!B81+Assumptions!B82+Assumptions!B87/12+Assumptions!B84 -> 92 | O18: =ROUND(I18*Assumptions!B85+E18*Assumptions!B86+W18*Assumptions!B85+ROUND(B18*Assumptions!B137*Assumptions!B138*Assumptions!B139,0)*Assumptions!B86,0) -> 11 | P18: =K18+L18+M18+N18+O18+X18 -> 183 | Q18: =I18-P18 -> -34 | R18: =ROUND(B18*Assumptions!B51*Assumptions!B52,0) -> 547 | S18: =I18+R18+W18 -> 757 | T18: =IF(U18<P18*3,0,IF(U18<P18*6,ROUND((Q18+R18+W18)*0.75*Assumptions!B113,0),ROUND((Q18+R18+W18)*0.75*Assumptions!B114,0))) -> 0 | U18: =U17+Q18+R18+W18 -> 322 | V18: =IF(B18>=Assumptions!B107,"Signal 6",IF(B18>=Assumptions!B106,"Signal 5",IF(B18>=Assumptions!B105,"Signal 4",IF(B18>=Assumptions!B104,"Signal 3",IF(B18>=Assumptions!B103,"Signal 2",IF(B18>=Assumptions!B102,"Signal 1","Pre-Signal 1")))))) -> Pre-Signal 1 | W18: =ROUND(B18*Assumptions!B137*Assumptions!B138*Assumptions!B139*Assumptions!B136,0) -> 61 | X18: =ROUND(B18*Assumptions!B137*Assumptions!B65,0) -> 10
A19: 14 | B19: =B18*(1+Assumptions!B33) -> 1688.8863 | C19: =ROUND(B19*Assumptions!B25,0) -> 34 | D19: =ROUND(B19*Assumptions!B22,0) -> 3 | E19: =E18+D19-F19 -> 15 | F19: =ROUND(E18*Assumptions!B43,0) -> 1 | G19: =D19-F19 -> 2 | H19: =ROUND(E19*(Assumptions!B15*0.85+Assumptions!B11*0.15),0) -> 172 | I19: =H19 -> 172 | J19: =ROUND(E19*Assumptions!B68,0) -> 53 | K19: =ROUND(J19*Assumptions!B65,0) -> 4 | L19: =Assumptions!B70+IF(E19>Assumptions!B72,45,0) -> 31 | M19: =Assumptions!B76+Assumptions!B77 -> 35 | N19: =Assumptions!B81+Assumptions!B82+Assumptions!B87/12+Assumptions!B84 -> 92 | O19: =ROUND(I19*Assumptions!B85+E19*Assumptions!B86+W19*Assumptions!B85+ROUND(B19*Assumptions!B137*Assumptions!B138*Assumptions!B139,0)*Assumptions!B86,0) -> 13 | P19: =K19+L19+M19+N19+O19+X19 -> 186 | Q19: =I19-P19 -> -14 | R19: =ROUND(B19*Assumptions!B51*Assumptions!B52,0) -> 591 | S19: =I19+R19+W19 -> 829 | T19: =IF(U19<P19*3,0,IF(U19<P19*6,ROUND((Q19+R19+W19)*0.75*Assumptions!B113,0),ROUND((Q19+R19+W19)*0.75*Assumptions!B114,0))) -> 114 | U19: =U18+Q19+R19+W19 -> 965 | V19: =IF(B19>=Assumptions!B107,"Signal 6",IF(B19>=Assumptions!B106,"Signal 5",IF(B19>=Assumptions!B105,"Signal 4",IF(B19>=Assumptions!B104,"Signal 3",IF(B19>=Assumptions!B103,"Signal 2",IF(B19>=Assumptions!B102,"Signal 1","Pre-Signal 1")))))) -> Pre-Signal 1 | W19: =ROUND(B19*Assumptions!B137*Assumptions!B138*Assumptions!B139*Assumptions!B136,0) -> 66 | X19: =ROUND(B19*Assumptions!B137*Assumptions!B65,0) -> 11
A20: 15 | B20: =B19*(1+Assumptions!B33) -> 1823.9972 | C20: =ROUND(B20*Assumptions!B25,0) -> 36 | D20: =ROUND(B20*Assumptions!B22,0) -> 3 | E20: =E19+D20-F20 -> 17 | F20: =ROUND(E19*Assumptions!B43,0) -> 1 | G20: =D20-F20 -> 2 | H20: =ROUND(E20*(Assumptions!B15*0.85+Assumptions!B11*0.15),0) -> 195 | I20: =H20 -> 195 | J20: =ROUND(E20*Assumptions!B68,0) -> 60 | K20: =ROUND(J20*Assumptions!B65,0) -> 5 | L20: =Assumptions!B70+IF(E20>Assumptions!B72,45,0) -> 31 | M20: =Assumptions!B76+Assumptions!B77 -> 35 | N20: =Assumptions!B81+Assumptions!B82+Assumptions!B87/12+Assumptions!B84 -> 92 | O20: =ROUND(I20*Assumptions!B85+E20*Assumptions!B86+W20*Assumptions!B85+ROUND(B20*Assumptions!B137*Assumptions!B138*Assumptions!B139,0)*Assumptions!B86,0) -> 14 | P20: =K20+L20+M20+N20+O20+X20 -> 189 | Q20: =I20-P20 -> 6 | R20: =ROUND(B20*Assumptions!B51*Assumptions!B52,0) -> 638 | S20: =I20+R20+W20 -> 904 | T20: =IF(U20<P20*3,0,IF(U20<P20*6,ROUND((Q20+R20+W20)*0.75*Assumptions!B113,0),ROUND((Q20+R20+W20)*0.75*Assumptions!B114,0))) -> 205 | U20: =U19+Q20+R20+W20 -> 1680 | V20: =IF(B20>=Assumptions!B107,"Signal 6",IF(B20>=Assumptions!B106,"Signal 5",IF(B20>=Assumptions!B105,"Signal 4",IF(B20>=Assumptions!B104,"Signal 3",IF(B20>=Assumptions!B103,"Signal 2",IF(B20>=Assumptions!B102,"Signal 1","Pre-Signal 1")))))) -> Pre-Signal 1 | W20: =ROUND(B20*Assumptions!B137*Assumptions!B138*Assumptions!B139*Assumptions!B136,0) -> 71 | X20: =ROUND(B20*Assumptions!B137*Assumptions!B65,0) -> 12
A21: 16 | B21: =B20*(1+Assumptions!B33) -> 1969.917 | C21: =ROUND(B21*Assumptions!B25,0) -> 39 | D21: =ROUND(B21*Assumptions!B22,0) -> 3 | E21: =E20+D21-F21 -> 19 | F21: =ROUND(E20*Assumptions!B43,0) -> 1 | G21: =D21-F21 -> 2 | H21: =ROUND(E21*(Assumptions!B15*0.85+Assumptions!B11*0.15),0) -> 218 | I21: =H21 -> 218 | J21: =ROUND(E21*Assumptions!B68,0) -> 67 | K21: =ROUND(J21*Assumptions!B65,0) -> 5 | L21: =Assumptions!B70+IF(E21>Assumptions!B72,45,0) -> 31 | M21: =Assumptions!B76+Assumptions!B77 -> 35 | N21: =Assumptions!B81+Assumptions!B82+Assumptions!B87/12+Assumptions!B84 -> 92 | O21: =ROUND(I21*Assumptions!B85+E21*Assumptions!B86+W21*Assumptions!B85+ROUND(B21*Assumptions!B137*Assumptions!B138*Assumptions!B139,0)*Assumptions!B86,0) -> 16 | P21: =K21+L21+M21+N21+O21+X21 -> 192 | Q21: =I21-P21 -> 26 | R21: =ROUND(B21*Assumptions!B51*Assumptions!B52,0) -> 689 | S21: =I21+R21+W21 -> 984 | T21: =IF(U21<P21*3,0,IF(U21<P21*6,ROUND((Q21+R21+W21)*0.75*Assumptions!B113,0),ROUND((Q21+R21+W21)*0.75*Assumptions!B114,0))) -> 227 | U21: =U20+Q21+R21+W21 -> 2472 | V21: =IF(B21>=Assumptions!B107,"Signal 6",IF(B21>=Assumptions!B106,"Signal 5",IF(B21>=Assumptions!B105,"Signal 4",IF(B21>=Assumptions!B104,"Signal 3",IF(B21>=Assumptions!B103,"Signal 2",IF(B21>=Assumptions!B102,"Signal 1","Pre-Signal 1")))))) -> Pre-Signal 1 | W21: =ROUND(B21*Assumptions!B137*Assumptions!B138*Assumptions!B139*Assumptions!B136,0) -> 77 | X21: =ROUND(B21*Assumptions!B137*Assumptions!B65,0) -> 13
A22: 17 | B22: =B21*(1+Assumptions!B33) -> 2127.5104 | C22: =ROUND(B22*Assumptions!B25,0) -> 43 | D22: =ROUND(B22*Assumptions!B22,0) -> 3 | E22: =E21+D22-F22 -> 20 | F22: =ROUND(E21*Assumptions!B43,0) -> 2 | G22: =D22-F22 -> 1 | H22: =ROUND(E22*(Assumptions!B15*0.85+Assumptions!B11*0.15),0) -> 230 | I22: =H22 -> 230 | J22: =ROUND(E22*Assumptions!B68,0) -> 70 | K22: =ROUND(J22*Assumptions!B65,0) -> 6 | L22: =Assumptions!B70+IF(E22>Assumptions!B72,45,0) -> 31 | M22: =Assumptions!B76+Assumptions!B77 -> 35 | N22: =Assumptions!B81+Assumptions!B82+Assumptions!B87/12+Assumptions!B84 -> 92 | O22: =ROUND(I22*Assumptions!B85+E22*Assumptions!B86+W22*Assumptions!B85+ROUND(B22*Assumptions!B137*Assumptions!B138*Assumptions!B139,0)*Assumptions!B86,0) -> 17 | P22: =K22+L22+M22+N22+O22+X22 -> 195 | Q22: =I22-P22 -> 35 | R22: =ROUND(B22*Assumptions!B51*Assumptions!B52,0) -> 745 | S22: =I22+R22+W22 -> 1058 | T22: =IF(U22<P22*3,0,IF(U22<P22*6,ROUND((Q22+R22+W22)*0.75*Assumptions!B113,0),ROUND((Q22+R22+W22)*0.75*Assumptions!B114,0))) -> 247 | U22: =U21+Q22+R22+W22 -> 3335 | V22: =IF(B22>=Assumptions!B107,"Signal 6",IF(B22>=Assumptions!B106,"Signal 5",IF(B22>=Assumptions!B105,"Signal 4",IF(B22>=Assumptions!B104,"Signal 3",IF(B22>=Assumptions!B103,"Signal 2",IF(B22>=Assumptions!B102,"Signal 1","Pre-Signal 1")))))) -> Pre-Signal 1 | W22: =ROUND(B22*Assumptions!B137*Assumptions!B138*Assumptions!B139*Assumptions!B136,0) -> 83 | X22: =ROUND(B22*Assumptions!B137*Assumptions!B65,0) -> 14
A23: 18 | B23: =B22*(1+Assumptions!B33) -> 2297.7112 | C23: =ROUND(B23*Assumptions!B25,0) -> 46 | D23: =ROUND(B23*Assumptions!B22,0) -> 3 | E23: =E22+D23-F23 -> 21 | F23: =ROUND(E22*Assumptions!B43,0) -> 2 | G23: =D23-F23 -> 1 | H23: =ROUND(E23*(Assumptions!B15*0.85+Assumptions!B11*0.15),0) -> 241 | I23: =H23 -> 241 | J23: =ROUND(E23*Assumptions!B68,0) -> 74 | K23: =ROUND(J23*Assumptions!B65,0) -> 6 | L23: =Assumptions!B70+IF(E23>Assumptions!B72,45,0) -> 31 | M23: =Assumptions!B76+Assumptions!B77 -> 35 | N23: =Assumptions!B81+Assumptions!B82+Assumptions!B87/12+Assumptions!B84 -> 92 | O23: =ROUND(I23*Assumptions!B85+E23*Assumptions!B86+W23*Assumptions!B85+ROUND(B23*Assumptions!B137*Assumptions!B138*Assumptions!B139,0)*Assumptions!B86,0) -> 18 | P23: =K23+L23+M23+N23+O23+X23 -> 197 | Q23: =I23-P23 -> 44 | R23: =ROUND(B23*Assumptions!B51*Assumptions!B52,0) -> 804 | S23: =I23+R23+W23 -> 1135 | T23: =IF(U23<P23*3,0,IF(U23<P23*6,ROUND((Q23+R23+W23)*0.75*Assumptions!B113,0),ROUND((Q23+R23+W23)*0.75*Assumptions!B114,0))) -> 269 | U23: =U22+Q23+R23+W23 -> 4273 | V23: =IF(B23>=Assumptions!B107,"Signal 6",IF(B23>=Assumptions!B106,"Signal 5",IF(B23>=Assumptions!B105,"Signal 4",IF(B23>=Assumptions!B104,"Signal 3",IF(B23>=Assumptions!B103,"Signal 2",IF(B23>=Assumptions!B102,"Signal 1","Pre-Signal 1")))))) -> Pre-Signal 1 | W23: =ROUND(B23*Assumptions!B137*Assumptions!B138*Assumptions!B139*Assumptions!B136,0) -> 90 | X23: =ROUND(B23*Assumptions!B137*Assumptions!B65,0) -> 15
A24: 19 | B24: =B23*(1+Assumptions!B33) -> 2481.5281 | C24: =ROUND(B24*Assumptions!B25,0) -> 50 | D24: =ROUND(B24*Assumptions!B22,0) -> 4 | E24: =E23+D24-F24 -> 23 | F24: =ROUND(E23*Assumptions!B43,0) -> 2 | G24: =D24-F24 -> 2 | H24: =ROUND(E24*(Assumptions!B15*0.85+Assumptions!B11*0.15),0) -> 264 | I24: =H24 -> 264 | J24: =ROUND(E24*Assumptions!B68,0) -> 81 | K24: =ROUND(J24*Assumptions!B65,0) -> 6 | L24: =Assumptions!B70+IF(E24>Assumptions!B72,45,0) -> 31 | M24: =Assumptions!B76+Assumptions!B77 -> 35 | N24: =Assumptions!B81+Assumptions!B82+Assumptions!B87/12+Assumptions!B84 -> 92 | O24: =ROUND(I24*Assumptions!B85+E24*Assumptions!B86+W24*Assumptions!B85+ROUND(B24*Assumptions!B137*Assumptions!B138*Assumptions!B139,0)*Assumptions!B86,0) -> 19 | P24: =K24+L24+M24+N24+O24+X24 -> 199 | Q24: =I24-P24 -> 65 | R24: =ROUND(B24*Assumptions!B51*Assumptions!B52,0) -> 869 | S24: =I24+R24+W24 -> 1230 | T24: =IF(U24<P24*3,0,IF(U24<P24*6,ROUND((Q24+R24+W24)*0.75*Assumptions!B113,0),ROUND((Q24+R24+W24)*0.75*Assumptions!B114,0))) -> 295 | U24: =U23+Q24+R24+W24 -> 5304 | V24: =IF(B24>=Assumptions!B107,"Signal 6",IF(B24>=Assumptions!B106,"Signal 5",IF(B24>=Assumptions!B105,"Signal 4",IF(B24>=Assumptions!B104,"Signal 3",IF(B24>=Assumptions!B103,"Signal 2",IF(B24>=Assumptions!B102,"Signal 1","Pre-Signal 1")))))) -> Pre-Signal 1 | W24: =ROUND(B24*Assumptions!B137*Assumptions!B138*Assumptions!B139*Assumptions!B136,0) -> 97 | X24: =ROUND(B24*Assumptions!B137*Assumptions!B65,0) -> 16
A25: 20 | B25: =B24*(1+Assumptions!B33) -> 2680.0504 | C25: =ROUND(B25*Assumptions!B25,0) -> 54 | D25: =ROUND(B25*Assumptions!B22,0) -> 4 | E25: =E24+D25-F25 -> 25 | F25: =ROUND(E24*Assumptions!B43,0) -> 2 | G25: =D25-F25 -> 2 | H25: =ROUND(E25*(Assumptions!B15*0.85+Assumptions!B11*0.15),0) -> 287 | I25: =H25 -> 287 | J25: =ROUND(E25*Assumptions!B68,0) -> 88 | K25: =ROUND(J25*Assumptions!B65,0) -> 7 | L25: =Assumptions!B70+IF(E25>Assumptions!B72,45,0) -> 31 | M25: =Assumptions!B76+Assumptions!B77 -> 35 | N25: =Assumptions!B81+Assumptions!B82+Assumptions!B87/12+Assumptions!B84 -> 92 | O25: =ROUND(I25*Assumptions!B85+E25*Assumptions!B86+W25*Assumptions!B85+ROUND(B25*Assumptions!B137*Assumptions!B138*Assumptions!B139,0)*Assumptions!B86,0) -> 21 | P25: =K25+L25+M25+N25+O25+X25 -> 203 | Q25: =I25-P25 -> 84 | R25: =ROUND(B25*Assumptions!B51*Assumptions!B52,0) -> 938 | S25: =I25+R25+W25 -> 1330 | T25: =IF(U25<P25*3,0,IF(U25<P25*6,ROUND((Q25+R25+W25)*0.75*Assumptions!B113,0),ROUND((Q25+R25+W25)*0.75*Assumptions!B114,0))) -> 323 | U25: =U24+Q25+R25+W25 -> 6431 | V25: =IF(B25>=Assumptions!B107,"Signal 6",IF(B25>=Assumptions!B106,"Signal 5",IF(B25>=Assumptions!B105,"Signal 4",IF(B25>=Assumptions!B104,"Signal 3",IF(B25>=Assumptions!B103,"Signal 2",IF(B25>=Assumptions!B102,"Signal 1","Pre-Signal 1")))))) -> Pre-Signal 1 | W25: =ROUND(B25*Assumptions!B137*Assumptions!B138*Assumptions!B139*Assumptions!B136,0) -> 105 | X25: =ROUND(B25*Assumptions!B137*Assumptions!B65,0) -> 17
A26: 21 | B26: =B25*(1+Assumptions!B33) -> 2894.4544 | C26: =ROUND(B26*Assumptions!B25,0) -> 58 | D26: =ROUND(B26*Assumptions!B22,0) -> 4 | E26: =E25+D26-F26 -> 27 | F26: =ROUND(E25*Assumptions!B43,0) -> 2 | G26: =D26-F26 -> 2 | H26: =ROUND(E26*(Assumptions!B15*0.85+Assumptions!B11*0.15),0) -> 310 | I26: =H26 -> 310 | J26: =ROUND(E26*Assumptions!B68,0) -> 95 | K26: =ROUND(J26*Assumptions!B65,0) -> 8 | L26: =Assumptions!B70+IF(E26>Assumptions!B72,45,0) -> 31 | M26: =Assumptions!B76+Assumptions!B77 -> 35 | N26: =Assumptions!B81+Assumptions!B82+Assumptions!B87/12+Assumptions!B84 -> 92 | O26: =ROUND(I26*Assumptions!B85+E26*Assumptions!B86+W26*Assumptions!B85+ROUND(B26*Assumptions!B137*Assumptions!B138*Assumptions!B139,0)*Assumptions!B86,0) -> 23 | P26: =K26+L26+M26+N26+O26+X26 -> 208 | Q26: =I26-P26 -> 102 | R26: =ROUND(B26*Assumptions!B51*Assumptions!B52,0) -> 1013 | S26: =I26+R26+W26 -> 1436 | T26: =IF(U26<P26*3,0,IF(U26<P26*6,ROUND((Q26+R26+W26)*0.75*Assumptions!B113,0),ROUND((Q26+R26+W26)*0.75*Assumptions!B114,0))) -> 352 | U26: =U25+Q26+R26+W26 -> 7659 | V26: =IF(B26>=Assumptions!B107,"Signal 6",IF(B26>=Assumptions!B106,"Signal 5",IF(B26>=Assumptions!B105,"Signal 4",IF(B26>=Assumptions!B104,"Signal 3",IF(B26>=Assumptions!B103,"Signal 2",IF(B26>=Assumptions!B102,"Signal 1","Pre-Signal 1")))))) -> Pre-Signal 1 | W26: =ROUND(B26*Assumptions!B137*Assumptions!B138*Assumptions!B139*Assumptions!B136,0) -> 113 | X26: =ROUND(B26*Assumptions!B137*Assumptions!B65,0) -> 19
A27: 22 | B27: =B26*(1+Assumptions!B33) -> 3126.0107 | C27: =ROUND(B27*Assumptions!B25,0) -> 63 | D27: =ROUND(B27*Assumptions!B22,0) -> 5 | E27: =E26+D27-F27 -> 30 | F27: =ROUND(E26*Assumptions!B43,0) -> 2 | G27: =D27-F27 -> 3 | H27: =ROUND(E27*(Assumptions!B15*0.85+Assumptions!B11*0.15),0) -> 344 | I27: =H27 -> 344 | J27: =ROUND(E27*Assumptions!B68,0) -> 105 | K27: =ROUND(J27*Assumptions!B65,0) -> 8 | L27: =Assumptions!B70+IF(E27>Assumptions!B72,45,0) -> 31 | M27: =Assumptions!B76+Assumptions!B77 -> 35 | N27: =Assumptions!B81+Assumptions!B82+Assumptions!B87/12+Assumptions!B84 -> 92 | O27: =ROUND(I27*Assumptions!B85+E27*Assumptions!B86+W27*Assumptions!B85+ROUND(B27*Assumptions!B137*Assumptions!B138*Assumptions!B139,0)*Assumptions!B86,0) -> 25 | P27: =K27+L27+M27+N27+O27+X27 -> 211 | Q27: =I27-P27 -> 133 | R27: =ROUND(B27*Assumptions!B51*Assumptions!B52,0) -> 1094 | S27: =I27+R27+W27 -> 1560 | T27: =IF(U27<P27*3,0,IF(U27<P27*6,ROUND((Q27+R27+W27)*0.75*Assumptions!B113,0),ROUND((Q27+R27+W27)*0.75*Assumptions!B114,0))) -> 386 | U27: =U26+Q27+R27+W27 -> 9008 | V27: =IF(B27>=Assumptions!B107,"Signal 6",IF(B27>=Assumptions!B106,"Signal 5",IF(B27>=Assumptions!B105,"Signal 4",IF(B27>=Assumptions!B104,"Signal 3",IF(B27>=Assumptions!B103,"Signal 2",IF(B27>=Assumptions!B102,"Signal 1","Pre-Signal 1")))))) -> Pre-Signal 1 | W27: =ROUND(B27*Assumptions!B137*Assumptions!B138*Assumptions!B139*Assumptions!B136,0) -> 122 | X27: =ROUND(B27*Assumptions!B137*Assumptions!B65,0) -> 20
A28: 23 | B28: =B27*(1+Assumptions!B33) -> 3376.0916 | C28: =ROUND(B28*Assumptions!B25,0) -> 68 | D28: =ROUND(B28*Assumptions!B22,0) -> 5 | E28: =E27+D28-F28 -> 33 | F28: =ROUND(E27*Assumptions!B43,0) -> 2 | G28: =D28-F28 -> 3 | H28: =ROUND(E28*(Assumptions!B15*0.85+Assumptions!B11*0.15),0) -> 379 | I28: =H28 -> 379 | J28: =ROUND(E28*Assumptions!B68,0) -> 116 | K28: =ROUND(J28*Assumptions!B65,0) -> 9 | L28: =Assumptions!B70+IF(E28>Assumptions!B72,45,0) -> 31 | M28: =Assumptions!B76+Assumptions!B77 -> 35 | N28: =Assumptions!B81+Assumptions!B82+Assumptions!B87/12+Assumptions!B84 -> 92 | O28: =ROUND(I28*Assumptions!B85+E28*Assumptions!B86+W28*Assumptions!B85+ROUND(B28*Assumptions!B137*Assumptions!B138*Assumptions!B139,0)*Assumptions!B86,0) -> 28 | P28: =K28+L28+M28+N28+O28+X28 -> 217 | Q28: =I28-P28 -> 162 | R28: =ROUND(B28*Assumptions!B51*Assumptions!B52,0) -> 1182 | S28: =I28+R28+W28 -> 1693 | T28: =IF(U28<P28*3,0,IF(U28<P28*6,ROUND((Q28+R28+W28)*0.75*Assumptions!B113,0),ROUND((Q28+R28+W28)*0.75*Assumptions!B114,0))) -> 423 | U28: =U27+Q28+R28+W28 -> 10484 | V28: =IF(B28>=Assumptions!B107,"Signal 6",IF(B28>=Assumptions!B106,"Signal 5",IF(B28>=Assumptions!B105,"Signal 4",IF(B28>=Assumptions!B104,"Signal 3",IF(B28>=Assumptions!B103,"Signal 2",IF(B28>=Assumptions!B102,"Signal 1","Pre-Signal 1")))))) -> Pre-Signal 1 | W28: =ROUND(B28*Assumptions!B137*Assumptions!B138*Assumptions!B139*Assumptions!B136,0) -> 132 | X28: =ROUND(B28*Assumptions!B137*Assumptions!B65,0) -> 22
A29: 24 | B29: =B28*(1+Assumptions!B33) -> 3646.1789 | C29: =ROUND(B29*Assumptions!B25,0) -> 73 | D29: =ROUND(B29*Assumptions!B22,0) -> 5 | E29: =E28+D29-F29 -> 35 | F29: =ROUND(E28*Assumptions!B43,0) -> 3 | G29: =D29-F29 -> 2 | H29: =ROUND(E29*(Assumptions!B15*0.85+Assumptions!B11*0.15),0) -> 402 | I29: =H29 -> 402 | J29: =ROUND(E29*Assumptions!B68,0) -> 123 | K29: =ROUND(J29*Assumptions!B65,0) -> 10 | L29: =Assumptions!B70+IF(E29>Assumptions!B72,45,0) -> 31 | M29: =Assumptions!B76+Assumptions!B77 -> 35 | N29: =Assumptions!B81+Assumptions!B82+Assumptions!B87/12+Assumptions!B84 -> 92 | O29: =ROUND(I29*Assumptions!B85+E29*Assumptions!B86+W29*Assumptions!B85+ROUND(B29*Assumptions!B137*Assumptions!B138*Assumptions!B139,0)*Assumptions!B86,0) -> 30 | P29: =K29+L29+M29+N29+O29+X29 -> 221 | Q29: =I29-P29 -> 181 | R29: =ROUND(B29*Assumptions!B51*Assumptions!B52,0) -> 1276 | S29: =I29+R29+W29 -> 1820 | T29: =IF(U29<P29*3,0,IF(U29<P29*6,ROUND((Q29+R29+W29)*0.75*Assumptions!B113,0),ROUND((Q29+R29+W29)*0.75*Assumptions!B114,0))) -> 458 | U29: =U28+Q29+R29+W29 -> 12083 | V29: =IF(B29>=Assumptions!B107,"Signal 6",IF(B29>=Assumptions!B106,"Signal 5",IF(B29>=Assumptions!B105,"Signal 4",IF(B29>=Assumptions!B104,"Signal 3",IF(B29>=Assumptions!B103,"Signal 2",IF(B29>=Assumptions!B102,"Signal 1","Pre-Signal 1")))))) -> Pre-Signal 1 | W29: =ROUND(B29*Assumptions!B137*Assumptions!B138*Assumptions!B139*Assumptions!B136,0) -> 142 | X29: =ROUND(B29*Assumptions!B137*Assumptions!B65,0) -> 23
A30: 25 | B30: =B29*(1+Assumptions!B33) -> 3937.8732 | C30: =ROUND(B30*Assumptions!B25,0) -> 79 | D30: =ROUND(B30*Assumptions!B22,0) -> 6 | E30: =E29+D30-F30 -> 38 | F30: =ROUND(E29*Assumptions!B43,0) -> 3 | G30: =D30-F30 -> 3 | H30: =ROUND(E30*(Assumptions!B15*0.85+Assumptions!B11*0.15),0) -> 436 | I30: =H30 -> 436 | J30: =ROUND(E30*Assumptions!B68,0) -> 133 | K30: =ROUND(J30*Assumptions!B65,0) -> 11 | L30: =Assumptions!B70+IF(E30>Assumptions!B72,45,0) -> 31 | M30: =Assumptions!B76+Assumptions!B77 -> 35 | N30: =Assumptions!B81+Assumptions!B82+Assumptions!B87/12+Assumptions!B84 -> 92 | O30: =ROUND(I30*Assumptions!B85+E30*Assumptions!B86+W30*Assumptions!B85+ROUND(B30*Assumptions!B137*Assumptions!B138*Assumptions!B139,0)*Assumptions!B86,0) -> 32 | P30: =K30+L30+M30+N30+O30+X30 -> 226 | Q30: =I30-P30 -> 210 | R30: =ROUND(B30*Assumptions!B51*Assumptions!B52,0) -> 1378 | S30: =I30+R30+W30 -> 1968 | T30: =IF(U30<P30*3,0,IF(U30<P30*6,ROUND((Q30+R30+W30)*0.75*Assumptions!B113,0),ROUND((Q30+R30+W30)*0.75*Assumptions!B114,0))) -> 499 | U30: =U29+Q30+R30+W30 -> 13825 | V30: =IF(B30>=Assumptions!B107,"Signal 6",IF(B30>=Assumptions!B106,"Signal 5",IF(B30>=Assumptions!B105,"Signal 4",IF(B30>=Assumptions!B104,"Signal 3",IF(B30>=Assumptions!B103,"Signal 2",IF(B30>=Assumptions!B102,"Signal 1","Pre-Signal 1")))))) -> Pre-Signal 1 | W30: =ROUND(B30*Assumptions!B137*Assumptions!B138*Assumptions!B139*Assumptions!B136,0) -> 154 | X30: =ROUND(B30*Assumptions!B137*Assumptions!B65,0) -> 25
A31: 26 | B31: =B30*(1+Assumptions!B33) -> 4252.9031 | C31: =ROUND(B31*Assumptions!B25,0) -> 85 | D31: =ROUND(B31*Assumptions!B22,0) -> 6 | E31: =E30+D31-F31 -> 41 | F31: =ROUND(E30*Assumptions!B43,0) -> 3 | G31: =D31-F31 -> 3 | H31: =ROUND(E31*(Assumptions!B15*0.85+Assumptions!B11*0.15),0) -> 470 | I31: =H31 -> 470 | J31: =ROUND(E31*Assumptions!B68,0) -> 144 | K31: =ROUND(J31*Assumptions!B65,0) -> 12 | L31: =Assumptions!B70+IF(E31>Assumptions!B72,45,0) -> 31 | M31: =Assumptions!B76+Assumptions!B77 -> 35 | N31: =Assumptions!B81+Assumptions!B82+Assumptions!B87/12+Assumptions!B84 -> 92 | O31: =ROUND(I31*Assumptions!B85+E31*Assumptions!B86+W31*Assumptions!B85+ROUND(B31*Assumptions!B137*Assumptions!B138*Assumptions!B139,0)*Assumptions!B86,0) -> 35 | P31: =K31+L31+M31+N31+O31+X31 -> 232 | Q31: =I31-P31 -> 238 | R31: =ROUND(B31*Assumptions!B51*Assumptions!B52,0) -> 1489 | S31: =I31+R31+W31 -> 2125 | T31: =IF(U31<P31*3,0,IF(U31<P31*6,ROUND((Q31+R31+W31)*0.75*Assumptions!B113,0),ROUND((Q31+R31+W31)*0.75*Assumptions!B114,0))) -> 542 | U31: =U30+Q31+R31+W31 -> 15718 | V31: =IF(B31>=Assumptions!B107,"Signal 6",IF(B31>=Assumptions!B106,"Signal 5",IF(B31>=Assumptions!B105,"Signal 4",IF(B31>=Assumptions!B104,"Signal 3",IF(B31>=Assumptions!B103,"Signal 2",IF(B31>=Assumptions!B102,"Signal 1","Pre-Signal 1")))))) -> Pre-Signal 1 | W31: =ROUND(B31*Assumptions!B137*Assumptions!B138*Assumptions!B139*Assumptions!B136,0) -> 166 | X31: =ROUND(B31*Assumptions!B137*Assumptions!B65,0) -> 27
A32: 27 | B32: =B31*(1+Assumptions!B33) -> 4593.1353 | C32: =ROUND(B32*Assumptions!B25,0) -> 92 | D32: =ROUND(B32*Assumptions!B22,0) -> 7 | E32: =E31+D32-F32 -> 45 | F32: =ROUND(E31*Assumptions!B43,0) -> 3 | G32: =D32-F32 -> 4 | H32: =ROUND(E32*(Assumptions!B15*0.85+Assumptions!B11*0.15),0) -> 516 | I32: =H32 -> 516 | J32: =ROUND(E32*Assumptions!B68,0) -> 158 | K32: =ROUND(J32*Assumptions!B65,0) -> 13 | L32: =Assumptions!B70+IF(E32>Assumptions!B72,45,0) -> 31 | M32: =Assumptions!B76+Assumptions!B77 -> 35 | N32: =Assumptions!B81+Assumptions!B82+Assumptions!B87/12+Assumptions!B84 -> 92 | O32: =ROUND(I32*Assumptions!B85+E32*Assumptions!B86+W32*Assumptions!B85+ROUND(B32*Assumptions!B137*Assumptions!B138*Assumptions!B139,0)*Assumptions!B86,0) -> 38 | P32: =K32+L32+M32+N32+O32+X32 -> 238 | Q32: =I32-P32 -> 278 | R32: =ROUND(B32*Assumptions!B51*Assumptions!B52,0) -> 1608 | S32: =I32+R32+W32 -> 2303 | T32: =IF(U32<P32*3,0,IF(U32<P32*6,ROUND((Q32+R32+W32)*0.75*Assumptions!B113,0),ROUND((Q32+R32+W32)*0.75*Assumptions!B114,0))) -> 592 | U32: =U31+Q32+R32+W32 -> 17783 | V32: =IF(B32>=Assumptions!B107,"Signal 6",IF(B32>=Assumptions!B106,"Signal 5",IF(B32>=Assumptions!B105,"Signal 4",IF(B32>=Assumptions!B104,"Signal 3",IF(B32>=Assumptions!B103,"Signal 2",IF(B32>=Assumptions!B102,"Signal 1","Pre-Signal 1")))))) -> Pre-Signal 1 | W32: =ROUND(B32*Assumptions!B137*Assumptions!B138*Assumptions!B139*Assumptions!B136,0) -> 179 | X32: =ROUND(B32*Assumptions!B137*Assumptions!B65,0) -> 29
A33: 28 | B33: =B32*(1+Assumptions!B33) -> 4960.5862 | C33: =ROUND(B33*Assumptions!B25,0) -> 99 | D33: =ROUND(B33*Assumptions!B22,0) -> 7 | E33: =E32+D33-F33 -> 48 | F33: =ROUND(E32*Assumptions!B43,0) -> 4 | G33: =D33-F33 -> 3 | H33: =ROUND(E33*(Assumptions!B15*0.85+Assumptions!B11*0.15),0) -> 551 | I33: =H33 -> 551 | J33: =ROUND(E33*Assumptions!B68,0) -> 168 | K33: =ROUND(J33*Assumptions!B65,0) -> 13 | L33: =Assumptions!B70+IF(E33>Assumptions!B72,45,0) -> 31 | M33: =Assumptions!B76+Assumptions!B77 -> 35 | N33: =Assumptions!B81+Assumptions!B82+Assumptions!B87/12+Assumptions!B84 -> 92 | O33: =ROUND(I33*Assumptions!B85+E33*Assumptions!B86+W33*Assumptions!B85+ROUND(B33*Assumptions!B137*Assumptions!B138*Assumptions!B139,0)*Assumptions!B86,0) -> 40 | P33: =K33+L33+M33+N33+O33+X33 -> 243 | Q33: =I33-P33 -> 308 | R33: =ROUND(B33*Assumptions!B51*Assumptions!B52,0) -> 1736 | S33: =I33+R33+W33 -> 2480 | T33: =IF(U33<P33*3,0,IF(U33<P33*6,ROUND((Q33+R33+W33)*0.75*Assumptions!B113,0),ROUND((Q33+R33+W33)*0.75*Assumptions!B114,0))) -> 641 | U33: =U32+Q33+R33+W33 -> 20020 | V33: =IF(B33>=Assumptions!B107,"Signal 6",IF(B33>=Assumptions!B106,"Signal 5",IF(B33>=Assumptions!B105,"Signal 4",IF(B33>=Assumptions!B104,"Signal 3",IF(B33>=Assumptions!B103,"Signal 2",IF(B33>=Assumptions!B102,"Signal 1","Pre-Signal 1")))))) -> Pre-Signal 1 | W33: =ROUND(B33*Assumptions!B137*Assumptions!B138*Assumptions!B139*Assumptions!B136,0) -> 193 | X33: =ROUND(B33*Assumptions!B137*Assumptions!B65,0) -> 32
A34: 29 | B34: =B33*(1+Assumptions!B33) -> 5357.4331 | C34: =ROUND(B34*Assumptions!B25,0) -> 107 | D34: =ROUND(B34*Assumptions!B22,0) -> 8 | E34: =E33+D34-F34 -> 52 | F34: =ROUND(E33*Assumptions!B43,0) -> 4 | G34: =D34-F34 -> 4 | H34: =ROUND(E34*(Assumptions!B15*0.85+Assumptions!B11*0.15),0) -> 597 | I34: =H34 -> 597 | J34: =ROUND(E34*Assumptions!B68,0) -> 182 | K34: =ROUND(J34*Assumptions!B65,0) -> 15 | L34: =Assumptions!B70+IF(E34>Assumptions!B72,45,0) -> 31 | M34: =Assumptions!B76+Assumptions!B77 -> 35 | N34: =Assumptions!B81+Assumptions!B82+Assumptions!B87/12+Assumptions!B84 -> 92 | O34: =ROUND(I34*Assumptions!B85+E34*Assumptions!B86+W34*Assumptions!B85+ROUND(B34*Assumptions!B137*Assumptions!B138*Assumptions!B139,0)*Assumptions!B86,0) -> 44 | P34: =K34+L34+M34+N34+O34+X34 -> 251 | Q34: =I34-P34 -> 346 | R34: =ROUND(B34*Assumptions!B51*Assumptions!B52,0) -> 1875 | S34: =I34+R34+W34 -> 2681 | T34: =IF(U34<P34*3,0,IF(U34<P34*6,ROUND((Q34+R34+W34)*0.75*Assumptions!B113,0),ROUND((Q34+R34+W34)*0.75*Assumptions!B114,0))) -> 696 | U34: =U33+Q34+R34+W34 -> 22450 | V34: =IF(B34>=Assumptions!B107,"Signal 6",IF(B34>=Assumptions!B106,"Signal 5",IF(B34>=Assumptions!B105,"Signal 4",IF(B34>=Assumptions!B104,"Signal 3",IF(B34>=Assumptions!B103,"Signal 2",IF(B34>=Assumptions!B102,"Signal 1","Pre-Signal 1")))))) -> Pre-Signal 1 | W34: =ROUND(B34*Assumptions!B137*Assumptions!B138*Assumptions!B139*Assumptions!B136,0) -> 209 | X34: =ROUND(B34*Assumptions!B137*Assumptions!B65,0) -> 34
A35: 30 | B35: =B34*(1+Assumptions!B33) -> 5786.0277 | C35: =ROUND(B35*Assumptions!B25,0) -> 116 | D35: =ROUND(B35*Assumptions!B22,0) -> 9 | E35: =E34+D35-F35 -> 57 | F35: =ROUND(E34*Assumptions!B43,0) -> 4 | G35: =D35-F35 -> 5 | H35: =ROUND(E35*(Assumptions!B15*0.85+Assumptions!B11*0.15),0) -> 654 | I35: =H35 -> 654 | J35: =ROUND(E35*Assumptions!B68,0) -> 200 | K35: =ROUND(J35*Assumptions!B65,0) -> 16 | L35: =Assumptions!B70+IF(E35>Assumptions!B72,45,0) -> 31 | M35: =Assumptions!B76+Assumptions!B77 -> 35 | N35: =Assumptions!B81+Assumptions!B82+Assumptions!B87/12+Assumptions!B84 -> 92 | O35: =ROUND(I35*Assumptions!B85+E35*Assumptions!B86+W35*Assumptions!B85+ROUND(B35*Assumptions!B137*Assumptions!B138*Assumptions!B139,0)*Assumptions!B86,0) -> 48 | P35: =K35+L35+M35+N35+O35+X35 -> 259 | Q35: =I35-P35 -> 395 | R35: =ROUND(B35*Assumptions!B51*Assumptions!B52,0) -> 2025 | S35: =I35+R35+W35 -> 2905 | T35: =IF(U35<P35*3,0,IF(U35<P35*6,ROUND((Q35+R35+W35)*0.75*Assumptions!B113,0),ROUND((Q35+R35+W35)*0.75*Assumptions!B114,0))) -> 758 | U35: =U34+Q35+R35+W35 -> 25096 | V35: =IF(B35>=Assumptions!B107,"Signal 6",IF(B35>=Assumptions!B106,"Signal 5",IF(B35>=Assumptions!B105,"Signal 4",IF(B35>=Assumptions!B104,"Signal 3",IF(B35>=Assumptions!B103,"Signal 2",IF(B35>=Assumptions!B102,"Signal 1","Pre-Signal 1")))))) -> Pre-Signal 1 | W35: =ROUND(B35*Assumptions!B137*Assumptions!B138*Assumptions!B139*Assumptions!B136,0) -> 226 | X35: =ROUND(B35*Assumptions!B137*Assumptions!B65,0) -> 37
A36: 31 | B36: =B35*(1+Assumptions!B33) -> 6248.9099 | C36: =ROUND(B36*Assumptions!B25,0) -> 125 | D36: =ROUND(B36*Assumptions!B22,0) -> 9 | E36: =E35+D36-F36 -> 61 | F36: =ROUND(E35*Assumptions!B43,0) -> 5 | G36: =D36-F36 -> 4 | H36: =ROUND(E36*(Assumptions!B15*0.85+Assumptions!B11*0.15),0) -> 700 | I36: =H36 -> 700 | J36: =ROUND(E36*Assumptions!B68,0) -> 214 | K36: =ROUND(J36*Assumptions!B65,0) -> 17 | L36: =Assumptions!B70+IF(E36>Assumptions!B72,45,0) -> 31 | M36: =Assumptions!B76+Assumptions!B77 -> 35 | N36: =Assumptions!B81+Assumptions!B82+Assumptions!B87/12+Assumptions!B84 -> 92 | O36: =ROUND(I36*Assumptions!B85+E36*Assumptions!B86+W36*Assumptions!B85+ROUND(B36*Assumptions!B137*Assumptions!B138*Assumptions!B139,0)*Assumptions!B86,0) -> 51 | P36: =K36+L36+M36+N36+O36+X36 -> 266 | Q36: =I36-P36 -> 434 | R36: =ROUND(B36*Assumptions!B51*Assumptions!B52,0) -> 2187 | S36: =I36+R36+W36 -> 3131 | T36: =IF(U36<P36*3,0,IF(U36<P36*6,ROUND((Q36+R36+W36)*0.75*Assumptions!B113,0),ROUND((Q36+R36+W36)*0.75*Assumptions!B114,0))) -> 821 | U36: =U35+Q36+R36+W36 -> 27961 | V36: =IF(B36>=Assumptions!B107,"Signal 6",IF(B36>=Assumptions!B106,"Signal 5",IF(B36>=Assumptions!B105,"Signal 4",IF(B36>=Assumptions!B104,"Signal 3",IF(B36>=Assumptions!B103,"Signal 2",IF(B36>=Assumptions!B102,"Signal 1","Pre-Signal 1")))))) -> Pre-Signal 1 | W36: =ROUND(B36*Assumptions!B137*Assumptions!B138*Assumptions!B139*Assumptions!B136,0) -> 244 | X36: =ROUND(B36*Assumptions!B137*Assumptions!B65,0) -> 40
A37: 32 | B37: =B36*(1+Assumptions!B33) -> 6748.8227 | C37: =ROUND(B37*Assumptions!B25,0) -> 135 | D37: =ROUND(B37*Assumptions!B22,0) -> 10 | E37: =E36+D37-F37 -> 66 | F37: =ROUND(E36*Assumptions!B43,0) -> 5 | G37: =D37-F37 -> 5 | H37: =ROUND(E37*(Assumptions!B15*0.85+Assumptions!B11*0.15),0) -> 757 | I37: =H37 -> 757 | J37: =ROUND(E37*Assumptions!B68,0) -> 231 | K37: =ROUND(J37*Assumptions!B65,0) -> 18 | L37: =Assumptions!B70+IF(E37>Assumptions!B72,45,0) -> 31 | M37: =Assumptions!B76+Assumptions!B77 -> 35 | N37: =Assumptions!B81+Assumptions!B82+Assumptions!B87/12+Assumptions!B84 -> 92 | O37: =ROUND(I37*Assumptions!B85+E37*Assumptions!B86+W37*Assumptions!B85+ROUND(B37*Assumptions!B137*Assumptions!B138*Assumptions!B139,0)*Assumptions!B86,0) -> 55 | P37: =K37+L37+M37+N37+O37+X37 -> 274 | Q37: =I37-P37 -> 483 | R37: =ROUND(B37*Assumptions!B51*Assumptions!B52,0) -> 2362 | S37: =I37+R37+W37 -> 3382 | T37: =IF(U37<P37*3,0,IF(U37<P37*6,ROUND((Q37+R37+W37)*0.75*Assumptions!B113,0),ROUND((Q37+R37+W37)*0.75*Assumptions!B114,0))) -> 890 | U37: =U36+Q37+R37+W37 -> 31069 | V37: =IF(B37>=Assumptions!B107,"Signal 6",IF(B37>=Assumptions!B106,"Signal 5",IF(B37>=Assumptions!B105,"Signal 4",IF(B37>=Assumptions!B104,"Signal 3",IF(B37>=Assumptions!B103,"Signal 2",IF(B37>=Assumptions!B102,"Signal 1","Pre-Signal 1")))))) -> Pre-Signal 1 | W37: =ROUND(B37*Assumptions!B137*Assumptions!B138*Assumptions!B139*Assumptions!B136,0) -> 263 | X37: =ROUND(B37*Assumptions!B137*Assumptions!B65,0) -> 43
A38: 33 | B38: =B37*(1+Assumptions!B33) -> 7288.7285 | C38: =ROUND(B38*Assumptions!B25,0) -> 146 | D38: =ROUND(B38*Assumptions!B22,0) -> 11 | E38: =E37+D38-F38 -> 72 | F38: =ROUND(E37*Assumptions!B43,0) -> 5 | G38: =D38-F38 -> 6 | H38: =ROUND(E38*(Assumptions!B15*0.85+Assumptions!B11*0.15),0) -> 826 | I38: =H38 -> 826 | J38: =ROUND(E38*Assumptions!B68,0) -> 252 | K38: =ROUND(J38*Assumptions!B65,0) -> 20 | L38: =Assumptions!B70+IF(E38>Assumptions!B72,45,0) -> 31 | M38: =Assumptions!B76+Assumptions!B77 -> 35 | N38: =Assumptions!B81+Assumptions!B82+Assumptions!B87/12+Assumptions!B84 -> 92 | O38: =ROUND(I38*Assumptions!B85+E38*Assumptions!B86+W38*Assumptions!B85+ROUND(B38*Assumptions!B137*Assumptions!B138*Assumptions!B139,0)*Assumptions!B86,0) -> 60 | P38: =K38+L38+M38+N38+O38+X38 -> 285 | Q38: =I38-P38 -> 541 | R38: =ROUND(B38*Assumptions!B51*Assumptions!B52,0) -> 2551 | S38: =I38+R38+W38 -> 3661 | T38: =IF(U38<P38*3,0,IF(U38<P38*6,ROUND((Q38+R38+W38)*0.75*Assumptions!B113,0),ROUND((Q38+R38+W38)*0.75*Assumptions!B114,0))) -> 967 | U38: =U37+Q38+R38+W38 -> 34445 | V38: =IF(B38>=Assumptions!B107,"Signal 6",IF(B38>=Assumptions!B106,"Signal 5",IF(B38>=Assumptions!B105,"Signal 4",IF(B38>=Assumptions!B104,"Signal 3",IF(B38>=Assumptions!B103,"Signal 2",IF(B38>=Assumptions!B102,"Signal 1","Pre-Signal 1")))))) -> Pre-Signal 1 | W38: =ROUND(B38*Assumptions!B137*Assumptions!B138*Assumptions!B139*Assumptions!B136,0) -> 284 | X38: =ROUND(B38*Assumptions!B137*Assumptions!B65,0) -> 47
A39: 34 | B39: =B38*(1+Assumptions!B33) -> 7871.8268 | C39: =ROUND(B39*Assumptions!B25,0) -> 157 | D39: =ROUND(B39*Assumptions!B22,0) -> 12 | E39: =E38+D39-F39 -> 78 | F39: =ROUND(E38*Assumptions!B43,0) -> 6 | G39: =D39-F39 -> 6 | H39: =ROUND(E39*(Assumptions!B15*0.85+Assumptions!B11*0.15),0) -> 895 | I39: =H39 -> 895 | J39: =ROUND(E39*Assumptions!B68,0) -> 273 | K39: =ROUND(J39*Assumptions!B65,0) -> 22 | L39: =Assumptions!B70+IF(E39>Assumptions!B72,45,0) -> 31 | M39: =Assumptions!B76+Assumptions!B77 -> 35 | N39: =Assumptions!B81+Assumptions!B82+Assumptions!B87/12+Assumptions!B84 -> 92 | O39: =ROUND(I39*Assumptions!B85+E39*Assumptions!B86+W39*Assumptions!B85+ROUND(B39*Assumptions!B137*Assumptions!B138*Assumptions!B139,0)*Assumptions!B86,0) -> 65 | P39: =K39+L39+M39+N39+O39+X39 -> 295 | Q39: =I39-P39 -> 600 | R39: =ROUND(B39*Assumptions!B51*Assumptions!B52,0) -> 2755 | S39: =I39+R39+W39 -> 3957 | T39: =IF(U39<P39*3,0,IF(U39<P39*6,ROUND((Q39+R39+W39)*0.75*Assumptions!B113,0),ROUND((Q39+R39+W39)*0.75*Assumptions!B114,0))) -> 1049 | U39: =U38+Q39+R39+W39 -> 38107 | V39: =IF(B39>=Assumptions!B107,"Signal 6",IF(B39>=Assumptions!B106,"Signal 5",IF(B39>=Assumptions!B105,"Signal 4",IF(B39>=Assumptions!B104,"Signal 3",IF(B39>=Assumptions!B103,"Signal 2",IF(B39>=Assumptions!B102,"Signal 1","Pre-Signal 1")))))) -> Pre-Signal 1 | W39: =ROUND(B39*Assumptions!B137*Assumptions!B138*Assumptions!B139*Assumptions!B136,0) -> 307 | X39: =ROUND(B39*Assumptions!B137*Assumptions!B65,0) -> 50
A40: 35 | B40: =B39*(1+Assumptions!B33) -> 8501.573 | C40: =ROUND(B40*Assumptions!B25,0) -> 170 | D40: =ROUND(B40*Assumptions!B22,0) -> 13 | E40: =E39+D40-F40 -> 85 | F40: =ROUND(E39*Assumptions!B43,0) -> 6 | G40: =D40-F40 -> 7 | H40: =ROUND(E40*(Assumptions!B15*0.85+Assumptions!B11*0.15),0) -> 975 | I40: =H40 -> 975 | J40: =ROUND(E40*Assumptions!B68,0) -> 298 | K40: =ROUND(J40*Assumptions!B65,0) -> 24 | L40: =Assumptions!B70+IF(E40>Assumptions!B72,45,0) -> 31 | M40: =Assumptions!B76+Assumptions!B77 -> 35 | N40: =Assumptions!B81+Assumptions!B82+Assumptions!B87/12+Assumptions!B84 -> 92 | O40: =ROUND(I40*Assumptions!B85+E40*Assumptions!B86+W40*Assumptions!B85+ROUND(B40*Assumptions!B137*Assumptions!B138*Assumptions!B139,0)*Assumptions!B86,0) -> 71 | P40: =K40+L40+M40+N40+O40+X40 -> 307 | Q40: =I40-P40 -> 668 | R40: =ROUND(B40*Assumptions!B51*Assumptions!B52,0) -> 2976 | S40: =I40+R40+W40 -> 4283 | T40: =IF(U40<P40*3,0,IF(U40<P40*6,ROUND((Q40+R40+W40)*0.75*Assumptions!B113,0),ROUND((Q40+R40+W40)*0.75*Assumptions!B114,0))) -> 1139 | U40: =U39+Q40+R40+W40 -> 42083 | V40: =IF(B40>=Assumptions!B107,"Signal 6",IF(B40>=Assumptions!B106,"Signal 5",IF(B40>=Assumptions!B105,"Signal 4",IF(B40>=Assumptions!B104,"Signal 3",IF(B40>=Assumptions!B103,"Signal 2",IF(B40>=Assumptions!B102,"Signal 1","Pre-Signal 1")))))) -> Pre-Signal 1 | W40: =ROUND(B40*Assumptions!B137*Assumptions!B138*Assumptions!B139*Assumptions!B136,0) -> 332 | X40: =ROUND(B40*Assumptions!B137*Assumptions!B65,0) -> 54
A41: 36 | B41: =B40*(1+Assumptions!B33) -> 9181.6988 | C41: =ROUND(B41*Assumptions!B25,0) -> 184 | D41: =ROUND(B41*Assumptions!B22,0) -> 14 | E41: =E40+D41-F41 -> 92 | F41: =ROUND(E40*Assumptions!B43,0) -> 7 | G41: =D41-F41 -> 7 | H41: =ROUND(E41*(Assumptions!B15*0.85+Assumptions!B11*0.15),0) -> 1056 | I41: =H41 -> 1056 | J41: =ROUND(E41*Assumptions!B68,0) -> 322 | K41: =ROUND(J41*Assumptions!B65,0) -> 26 | L41: =Assumptions!B70+IF(E41>Assumptions!B72,45,0) -> 31 | M41: =Assumptions!B76+Assumptions!B77 -> 35 | N41: =Assumptions!B81+Assumptions!B82+Assumptions!B87/12+Assumptions!B84 -> 92 | O41: =ROUND(I41*Assumptions!B85+E41*Assumptions!B86+W41*Assumptions!B85+ROUND(B41*Assumptions!B137*Assumptions!B138*Assumptions!B139,0)*Assumptions!B86,0) -> 77 | P41: =K41+L41+M41+N41+O41+X41 -> 320 | Q41: =I41-P41 -> 736 | R41: =ROUND(B41*Assumptions!B51*Assumptions!B52,0) -> 3214 | S41: =I41+R41+W41 -> 4628 | T41: =IF(U41<P41*3,0,IF(U41<P41*6,ROUND((Q41+R41+W41)*0.75*Assumptions!B113,0),ROUND((Q41+R41+W41)*0.75*Assumptions!B114,0))) -> 1234 | U41: =U40+Q41+R41+W41 -> 46391 | V41: =IF(B41>=Assumptions!B107,"Signal 6",IF(B41>=Assumptions!B106,"Signal 5",IF(B41>=Assumptions!B105,"Signal 4",IF(B41>=Assumptions!B104,"Signal 3",IF(B41>=Assumptions!B103,"Signal 2",IF(B41>=Assumptions!B102,"Signal 1","Pre-Signal 1")))))) -> Pre-Signal 1 | W41: =ROUND(B41*Assumptions!B137*Assumptions!B138*Assumptions!B139*Assumptions!B136,0) -> 358 | X41: =ROUND(B41*Assumptions!B137*Assumptions!B65,0) -> 59
A43: TOTALS | I43: =SUM(I6:I41) -> 12386 | P43: =SUM(P6:P41) -> 9902 | Q43: =SUM(Q6:Q41) -> 2484 | R43: =SUM(R6:R41) -> 39390 | S43: =SUM(S6:S41) -> 56293 | T43: =SUM(T6:T41) -> 13127 | W43: =SUM(W6:W41) -> 4517 | X43: =SUM(X6:X41) -> 741
A44: AVG MO | H44: =AVERAGE(H6:H41) -> 344.05556 | Q44: =AVERAGE(Q6:Q41) -> 69
A45: M36 | B45: =B41 -> 9181.6988 | E45: =E41 -> 92 | H45: =H41 -> 1056 | S45: =S41 -> 4628 | T45: =T41 -> 1234 | U45: =U41 -> 46391 | V45: =V41 -> Pre-Signal 1

Sheet Expected
A1: EXPECTED SCENARIO — Expected Growth
A2: 0.25% paid conversion | 12% MoM traffic growth | 6% monthly churn | Referral: 0.1% of visitors x $350 blended
A3: Blue = hardcoded inputs | Black = calculated formulas | Green = Assumptions references
A5: Month | B5: Monthly Visitors | C5: Free Signups (Email 2%) | D5: New Paid Subs | E5: Total Paid Subs | F5: Churn This Month | G5: Net New Subs | H5: MRR ($) | I5: Monthly Revenue ($) | J5: Letter Generations | K5: API Costs ($) | L5: Infrastructure ($) | M5: Content/SEO ($) | N5: n8n + Tools ($) | O5: Stripe Fees ($) | P5: Total Costs ($) | Q5: Gross Profit ($) | R5: Referral Revenue ($) | S5: Total Revenue ($) | T5: Owner's Draw ($) | U5: Reserve Balance ($) | V5: Traffic Signal | W5: Per-Case Revenue ($) | X5: Free Tier API Cost ($)
A6: 1 | B6: =Assumptions!B31 -> 800 | C6: =ROUND(B6*Assumptions!B25,0) -> 16 | D6: =ROUND(B6*Assumptions!B23,0) -> 2 | E6: =D6 -> 2 | F6: =0 -> 0 | G6: =D6-F6 -> 2 | H6: =ROUND(E6*Assumptions!B14,0) -> 16 | I6: =H6 -> 16 | J6: =ROUND(E6*Assumptions!B68,0) -> 7 | K6: =ROUND(J6*Assumptions!B65,0) -> 1 | L6: =Assumptions!B70+IF(E6>Assumptions!B72,45,0) -> 31 | M6: =Assumptions!B94+Assumptions!B95+Assumptions!B76+Assumptions!B77 -> 2785 | N6: =Assumptions!B81+Assumptions!B82+Assumptions!B87/12 -> 50 | O6: =ROUND(I6*Assumptions!B85+E6*Assumptions!B86+W6*Assumptions!B85+ROUND(B6*Assumptions!B137*Assumptions!B138*Assumptions!B139,0)*Assumptions!B86,0) -> 3 | P6: =K6+L6+M6+N6+O6+X6 -> 2875 | Q6: =I6-P6 -> -2859 | R6: =0 -> 0 | S6: =I6+R6+W6 -> 47 | T6: =IF(U6<P6*3,0,IF(U6<P6*6,ROUND((Q6+R6+W6)*0.75*Assumptions!B113,0),ROUND((Q6+R6+W6)*0.75*Assumptions!B114,0))) -> 0 | U6: =Q6+R6+W6 -> -2828 | V6: =IF(B6>=Assumptions!B107,"Signal 6",IF(B6>=Assumptions!B106,"Signal 5",IF(B6>=Assumptions!B105,"Signal 4",IF(B6>=Assumptions!B104,"Signal 3",IF(B6>=Assumptions!B103,"Signal 2",IF(B6>=Assumptions!B102,"Signal 1","Pre-Signal 1")))))) -> Pre-Signal 1 | W6: =ROUND(B6*Assumptions!B137*Assumptions!B138*Assumptions!B139*Assumptions!B136,0) -> 31 | X6: =ROUND(B6*Assumptions!B137*Assumptions!B65,0) -> 5
A7: 2 | B7: =B6*(1+Assumptions!B34) -> 896 | C7: =ROUND(B7*Assumptions!B25,0) -> 18 | D7: =ROUND(B7*Assumptions!B23,0) -> 2 | E7: =E6+D7-F7 -> 4 | F7: =ROUND(E6*Assumptions!B44,0) -> 0 | G7: =D7-F7 -> 2 | H7: =ROUND(E7*Assumptions!B14,0) -> 32 | I7: =H7 -> 32 | J7: =ROUND(E7*Assumptions!B68,0) -> 14 | K7: =ROUND(J7*Assumptions!B65,0) -> 1 | L7: =Assumptions!B70+IF(E7>Assumptions!B72,45,0) -> 31 | M7: =Assumptions!B76+Assumptions!B77 -> 35 | N7: =Assumptions!B81+Assumptions!B82+Assumptions!B87/12 -> 50 | O7: =ROUND(I7*Assumptions!B85+E7*Assumptions!B86+W7*Assumptions!B85+ROUND(B7*Assumptions!B137*Assumptions!B138*Assumptions!B139,0)*Assumptions!B86,0) -> 4 | P7: =K7+L7+M7+N7+O7+X7 -> 127 | Q7: =I7-P7 -> -95 | R7: =0 -> 0 | S7: =I7+R7+W7 -> 67 | T7: =IF(U7<P7*3,0,IF(U7<P7*6,ROUND((Q7+R7+W7)*0.75*Assumptions!B113,0),ROUND((Q7+R7+W7)*0.75*Assumptions!B114,0))) -> 0 | U7: =U6+Q7+R7+W7 -> -2888 | V7: =IF(B7>=Assumptions!B107,"Signal 6",IF(B7>=Assumptions!B106,"Signal 5",IF(B7>=Assumptions!B105,"Signal 4",IF(B7>=Assumptions!B104,"Signal 3",IF(B7>=Assumptions!B103,"Signal 2",IF(B7>=Assumptions!B102,"Signal 1","Pre-Signal 1")))))) -> Pre-Signal 1 | W7: =ROUND(B7*Assumptions!B137*Assumptions!B138*Assumptions!B139*Assumptions!B136,0) -> 35 | X7: =ROUND(B7*Assumptions!B137*Assumptions!B65,0) -> 6
A8: 3 | B8: =B7*(1+Assumptions!B34)*Assumptions!B36 -> 1154.048 | C8: =ROUND(B8*Assumptions!B25,0) -> 23 | D8: =ROUND(B8*Assumptions!B23,0) -> 3 | E8: =E7+D8-F8 -> 7 | F8: =ROUND(E7*Assumptions!B44,0) -> 0 | G8: =D8-F8 -> 3 | H8: =ROUND(E8*Assumptions!B14,0) -> 56 | I8: =H8 -> 56 | J8: =ROUND(E8*Assumptions!B68,0) -> 25 | K8: =ROUND(J8*Assumptions!B65,0) -> 2 | L8: =Assumptions!B70+IF(E8>Assumptions!B72,45,0) -> 31 | M8: =Assumptions!B76+Assumptions!B77 -> 35 | N8: =Assumptions!B81+Assumptions!B82+Assumptions!B87/12 -> 50 | O8: =ROUND(I8*Assumptions!B85+E8*Assumptions!B86+W8*Assumptions!B85+ROUND(B8*Assumptions!B137*Assumptions!B138*Assumptions!B139,0)*Assumptions!B86,0) -> 6 | P8: =K8+L8+M8+N8+O8+X8 -> 131 | Q8: =I8-P8 -> -75 | R8: =0 -> 0 | S8: =I8+R8+W8 -> 101 | T8: =IF(U8<P8*3,0,IF(U8<P8*6,ROUND((Q8+R8+W8)*0.75*Assumptions!B113,0),ROUND((Q8+R8+W8)*0.75*Assumptions!B114,0))) -> 0 | U8: =U7+Q8+R8+W8 -> -2918 | V8: =IF(B8>=Assumptions!B107,"Signal 6",IF(B8>=Assumptions!B106,"Signal 5",IF(B8>=Assumptions!B105,"Signal 4",IF(B8>=Assumptions!B104,"Signal 3",IF(B8>=Assumptions!B103,"Signal 2",IF(B8>=Assumptions!B102,"Signal 1","Pre-Signal 1")))))) -> Pre-Signal 1 | W8: =ROUND(B8*Assumptions!B137*Assumptions!B138*Assumptions!B139*Assumptions!B136,0) -> 45 | X8: =ROUND(B8*Assumptions!B137*Assumptions!B65,0) -> 7
A9: 4 | B9: =B8*(1+Assumptions!B34) -> 1292.5338 | C9: =ROUND(B9*Assumptions!B25,0) -> 26 | D9: =ROUND(B9*Assumptions!B23,0) -> 3 | E9: =E8+D9-F9 -> 10 | F9: =ROUND(E8*Assumptions!B44,0) -> 0 | G9: =D9-F9 -> 3 | H9: =ROUND(E9*Assumptions!B14,0) -> 80 | I9: =H9 -> 80 | J9: =ROUND(E9*Assumptions!B68,0) -> 35 | K9: =ROUND(J9*Assumptions!B65,0) -> 3 | L9: =Assumptions!B70+IF(E9>Assumptions!B72,45,0) -> 31 | M9: =Assumptions!B76+Assumptions!B77 -> 35 | N9: =Assumptions!B81+Assumptions!B82+Assumptions!B87/12 -> 50 | O9: =ROUND(I9*Assumptions!B85+E9*Assumptions!B86+W9*Assumptions!B85+ROUND(B9*Assumptions!B137*Assumptions!B138*Assumptions!B139,0)*Assumptions!B86,0) -> 8 | P9: =K9+L9+M9+N9+O9+X9 -> 135 | Q9: =I9-P9 -> -55 | R9: =0 -> 0 | S9: =I9+R9+W9 -> 130 | T9: =IF(U9<P9*3,0,IF(U9<P9*6,ROUND((Q9+R9+W9)*0.75*Assumptions!B113,0),ROUND((Q9+R9+W9)*0.75*Assumptions!B114,0))) -> 0 | U9: =U8+Q9+R9+W9 -> -2923 | V9: =IF(B9>=Assumptions!B107,"Signal 6",IF(B9>=Assumptions!B106,"Signal 5",IF(B9>=Assumptions!B105,"Signal 4",IF(B9>=Assumptions!B104,"Signal 3",IF(B9>=Assumptions!B103,"Signal 2",IF(B9>=Assumptions!B102,"Signal 1","Pre-Signal 1")))))) -> Pre-Signal 1 | W9: =ROUND(B9*Assumptions!B137*Assumptions!B138*Assumptions!B139*Assumptions!B136,0) -> 50 | X9: =ROUND(B9*Assumptions!B137*Assumptions!B65,0) -> 8
A10: 5 | B10: =B9*(1+Assumptions!B34) -> 1447.6378 | C10: =ROUND(B10*Assumptions!B25,0) -> 29 | D10: =ROUND(B10*Assumptions!B23,0) -> 4 | E10: =E9+D10-F10 -> 13 | F10: =ROUND(E9*Assumptions!B44,0) -> 1 | G10: =D10-F10 -> 3 | H10: =ROUND(E10*Assumptions!B14,0) -> 104 | I10: =H10 -> 104 | J10: =ROUND(E10*Assumptions!B68,0) -> 46 | K10: =ROUND(J10*Assumptions!B65,0) -> 4 | L10: =Assumptions!B70+IF(E10>Assumptions!B72,45,0) -> 31 | M10: =Assumptions!B76+Assumptions!B77 -> 35 | N10: =Assumptions!B81+Assumptions!B82+Assumptions!B87/12 -> 50 | O10: =ROUND(I10*Assumptions!B85+E10*Assumptions!B86+W10*Assumptions!B85+ROUND(B10*Assumptions!B137*Assumptions!B138*Assumptions!B139,0)*Assumptions!B86,0) -> 10 | P10: =K10+L10+M10+N10+O10+X10 -> 139 | Q10: =I10-P10 -> -35 | R10: =0 -> 0 | S10: =I10+R10+W10 -> 160 | T10: =IF(U10<P10*3,0,IF(U10<P10*6,ROUND((Q10+R10+W10)*0.75*Assumptions!B113,0),ROUND((Q10+R10+W10)*0.75*Assumptions!B114,0))) -> 0 | U10: =U9+Q10+R10+W10 -> -2902 | V10: =IF(B10>=Assumptions!B107,"Signal 6",IF(B10>=Assumptions!B106,"Signal 5",IF(B10>=Assumptions!B105,"Signal 4",IF(B10>=Assumptions!B104,"Signal 3",IF(B10>=Assumptions!B103,"Signal 2",IF(B10>=Assumptions!B102,"Signal 1","Pre-Signal 1")))))) -> Pre-Signal 1 | W10: =ROUND(B10*Assumptions!B137*Assumptions!B138*Assumptions!B139*Assumptions!B136,0) -> 56 | X10: =ROUND(B10*Assumptions!B137*Assumptions!B65,0) -> 9
A11: 6 | B11: =B10*(1+Assumptions!B34)*Assumptions!B37 -> 1751.0627 | C11: =ROUND(B11*Assumptions!B25,0) -> 35 | D11: =ROUND(B11*Assumptions!B23,0) -> 4 | E11: =E10+D11-F11 -> 16 | F11: =ROUND(E10*Assumptions!B44,0) -> 1 | G11: =D11-F11 -> 3 | H11: =ROUND(E11*Assumptions!B14,0) -> 128 | I11: =H11 -> 128 | J11: =ROUND(E11*Assumptions!B68,0) -> 56 | K11: =ROUND(J11*Assumptions!B65,0) -> 4 | L11: =Assumptions!B70+IF(E11>Assumptions!B72,45,0) -> 31 | M11: =Assumptions!B76+Assumptions!B77 -> 35 | N11: =Assumptions!B81+Assumptions!B82+Assumptions!B87/12 -> 50 | O11: =ROUND(I11*Assumptions!B85+E11*Assumptions!B86+W11*Assumptions!B85+ROUND(B11*Assumptions!B137*Assumptions!B138*Assumptions!B139,0)*Assumptions!B86,0) -> 12 | P11: =K11+L11+M11+N11+O11+X11 -> 143 | Q11: =I11-P11 -> -15 | R11: =ROUND(B11*Assumptions!B51*Assumptions!B52,0) -> 613 | S11: =I11+R11+W11 -> 809 | T11: =IF(U11<P11*3,0,IF(U11<P11*6,ROUND((Q11+R11+W11)*0.75*Assumptions!B113,0),ROUND((Q11+R11+W11)*0.75*Assumptions!B114,0))) -> 0 | U11: =U10+Q11+R11+W11 -> -2236 | V11: =IF(B11>=Assumptions!B107,"Signal 6",IF(B11>=Assumptions!B106,"Signal 5",IF(B11>=Assumptions!B105,"Signal 4",IF(B11>=Assumptions!B104,"Signal 3",IF(B11>=Assumptions!B103,"Signal 2",IF(B11>=Assumptions!B102,"Signal 1","Pre-Signal 1")))))) -> Pre-Signal 1 | W11: =ROUND(B11*Assumptions!B137*Assumptions!B138*Assumptions!B139*Assumptions!B136,0) -> 68 | X11: =ROUND(B11*Assumptions!B137*Assumptions!B65,0) -> 11
A12: 7 | B12: =B11*(1+Assumptions!B34) -> 1961.1902 | C12: =ROUND(B12*Assumptions!B25,0) -> 39 | D12: =ROUND(B12*Assumptions!B23,0) -> 5 | E12: =E11+D12-F12 -> 20 | F12: =ROUND(E11*Assumptions!B44,0) -> 1 | G12: =D12-F12 -> 4 | H12: =ROUND(E12*Assumptions!B14,0) -> 160 | I12: =H12 -> 160 | J12: =ROUND(E12*Assumptions!B68,0) -> 70 | K12: =ROUND(J12*Assumptions!B65,0) -> 6 | L12: =Assumptions!B70+IF(E12>Assumptions!B72,45,0) -> 31 | M12: =Assumptions!B76+Assumptions!B77 -> 35 | N12: =Assumptions!B81+Assumptions!B82+Assumptions!B87/12 -> 50 | O12: =ROUND(I12*Assumptions!B85+E12*Assumptions!B86+W12*Assumptions!B85+ROUND(B12*Assumptions!B137*Assumptions!B138*Assumptions!B139,0)*Assumptions!B86,0) -> 15 | P12: =K12+L12+M12+N12+O12+X12 -> 150 | Q12: =I12-P12 -> 10 | R12: =ROUND(B12*Assumptions!B51*Assumptions!B52,0) -> 686 | S12: =I12+R12+W12 -> 922 | T12: =IF(U12<P12*3,0,IF(U12<P12*6,ROUND((Q12+R12+W12)*0.75*Assumptions!B113,0),ROUND((Q12+R12+W12)*0.75*Assumptions!B114,0))) -> 0 | U12: =U11+Q12+R12+W12 -> -1464 | V12: =IF(B12>=Assumptions!B107,"Signal 6",IF(B12>=Assumptions!B106,"Signal 5",IF(B12>=Assumptions!B105,"Signal 4",IF(B12>=Assumptions!B104,"Signal 3",IF(B12>=Assumptions!B103,"Signal 2",IF(B12>=Assumptions!B102,"Signal 1","Pre-Signal 1")))))) -> Pre-Signal 1 | W12: =ROUND(B12*Assumptions!B137*Assumptions!B138*Assumptions!B139*Assumptions!B136,0) -> 76 | X12: =ROUND(B12*Assumptions!B137*Assumptions!B65,0) -> 13
A13: 8 | B13: =B12*(1+Assumptions!B34) -> 2196.533 | C13: =ROUND(B13*Assumptions!B25,0) -> 44 | D13: =ROUND(B13*Assumptions!B23,0) -> 5 | E13: =E12+D13-F13 -> 24 | F13: =ROUND(E12*Assumptions!B44,0) -> 1 | G13: =D13-F13 -> 4 | H13: =ROUND(E13*Assumptions!B14,0) -> 192 | I13: =H13 -> 192 | J13: =ROUND(E13*Assumptions!B68,0) -> 84 | K13: =ROUND(J13*Assumptions!B65,0) -> 7 | L13: =Assumptions!B70+IF(E13>Assumptions!B72,45,0) -> 31 | M13: =Assumptions!B76+Assumptions!B77 -> 35 | N13: =Assumptions!B81+Assumptions!B82+Assumptions!B87/12 -> 50 | O13: =ROUND(I13*Assumptions!B85+E13*Assumptions!B86+W13*Assumptions!B85+ROUND(B13*Assumptions!B137*Assumptions!B138*Assumptions!B139,0)*Assumptions!B86,0) -> 17 | P13: =K13+L13+M13+N13+O13+X13 -> 154 | Q13: =I13-P13 -> 38 | R13: =ROUND(B13*Assumptions!B51*Assumptions!B52,0) -> 769 | S13: =I13+R13+W13 -> 1047 | T13: =IF(U13<P13*3,0,IF(U13<P13*6,ROUND((Q13+R13+W13)*0.75*Assumptions!B113,0),ROUND((Q13+R13+W13)*0.75*Assumptions!B114,0))) -> 0 | U13: =U12+Q13+R13+W13 -> -571 | V13: =IF(B13>=Assumptions!B107,"Signal 6",IF(B13>=Assumptions!B106,"Signal 5",IF(B13>=Assumptions!B105,"Signal 4",IF(B13>=Assumptions!B104,"Signal 3",IF(B13>=Assumptions!B103,"Signal 2",IF(B13>=Assumptions!B102,"Signal 1","Pre-Signal 1")))))) -> Pre-Signal 1 | W13: =ROUND(B13*Assumptions!B137*Assumptions!B138*Assumptions!B139*Assumptions!B136,0) -> 86 | X13: =ROUND(B13*Assumptions!B137*Assumptions!B65,0) -> 14
A14: 9 | B14: =B13*(1+Assumptions!B34) -> 2460.117 | C14: =ROUND(B14*Assumptions!B25,0) -> 49 | D14: =ROUND(B14*Assumptions!B23,0) -> 6 | E14: =E13+D14-F14 -> 29 | F14: =ROUND(E13*Assumptions!B44,0) -> 1 | G14: =D14-F14 -> 5 | H14: =ROUND(E14*((Assumptions!B14+Assumptions!B15)/2),0) -> 305 | I14: =H14 -> 305 | J14: =ROUND(E14*Assumptions!B68,0) -> 102 | K14: =ROUND(J14*Assumptions!B65,0) -> 8 | L14: =Assumptions!B70+IF(E14>Assumptions!B72,45,0) -> 31 | M14: =Assumptions!B76+Assumptions!B77 -> 35 | N14: =Assumptions!B81+Assumptions!B82+Assumptions!B87/12 -> 50 | O14: =ROUND(I14*Assumptions!B85+E14*Assumptions!B86+W14*Assumptions!B85+ROUND(B14*Assumptions!B137*Assumptions!B138*Assumptions!B139,0)*Assumptions!B86,0) -> 22 | P14: =K14+L14+M14+N14+O14+X14 -> 162 | Q14: =I14-P14 -> 143 | R14: =ROUND(B14*Assumptions!B51*Assumptions!B52,0) -> 861 | S14: =I14+R14+W14 -> 1262 | T14: =IF(U14<P14*3,0,IF(U14<P14*6,ROUND((Q14+R14+W14)*0.75*Assumptions!B113,0),ROUND((Q14+R14+W14)*0.75*Assumptions!B114,0))) -> 195 | U14: =U13+Q14+R14+W14 -> 529 | V14: =IF(B14>=Assumptions!B107,"Signal 6",IF(B14>=Assumptions!B106,"Signal 5",IF(B14>=Assumptions!B105,"Signal 4",IF(B14>=Assumptions!B104,"Signal 3",IF(B14>=Assumptions!B103,"Signal 2",IF(B14>=Assumptions!B102,"Signal 1","Pre-Signal 1")))))) -> Pre-Signal 1 | W14: =ROUND(B14*Assumptions!B137*Assumptions!B138*Assumptions!B139*Assumptions!B136,0) -> 96 | X14: =ROUND(B14*Assumptions!B137*Assumptions!B65,0) -> 16
A15: 10 | B15: =B14*(1+Assumptions!B34) -> 2755.3311 | C15: =ROUND(B15*Assumptions!B25,0) -> 55 | D15: =ROUND(B15*Assumptions!B23,0) -> 7 | E15: =E14+D15-F15 -> 34 | F15: =ROUND(E14*Assumptions!B44,0) -> 2 | G15: =D15-F15 -> 5 | H15: =ROUND(E15*(Assumptions!B15*0.85+Assumptions!B11*0.15),0) -> 390 | I15: =H15 -> 390 | J15: =ROUND(E15*Assumptions!B68,0) -> 119 | K15: =ROUND(J15*Assumptions!B65,0) -> 10 | L15: =Assumptions!B70+IF(E15>Assumptions!B72,45,0) -> 31 | M15: =Assumptions!B76+Assumptions!B77 -> 35 | N15: =Assumptions!B81+Assumptions!B82+Assumptions!B87/12 -> 50 | O15: =ROUND(I15*Assumptions!B85+E15*Assumptions!B86+W15*Assumptions!B85+ROUND(B15*Assumptions!B137*Assumptions!B138*Assumptions!B139,0)*Assumptions!B86,0) -> 27 | P15: =K15+L15+M15+N15+O15+X15 -> 171 | Q15: =I15-P15 -> 219 | R15: =ROUND(B15*Assumptions!B51*Assumptions!B52,0) -> 964 | S15: =I15+R15+W15 -> 1461 | T15: =IF(U15<P15*3,0,IF(U15<P15*6,ROUND((Q15+R15+W15)*0.75*Assumptions!B113,0),ROUND((Q15+R15+W15)*0.75*Assumptions!B114,0))) -> 370 | U15: =U14+Q15+R15+W15 -> 1819 | V15: =IF(B15>=Assumptions!B107,"Signal 6",IF(B15>=Assumptions!B106,"Signal 5",IF(B15>=Assumptions!B105,"Signal 4",IF(B15>=Assumptions!B104,"Signal 3",IF(B15>=Assumptions!B103,"Signal 2",IF(B15>=Assumptions!B102,"Signal 1","Pre-Signal 1")))))) -> Pre-Signal 1 | W15: =ROUND(B15*Assumptions!B137*Assumptions!B138*Assumptions!B139*Assumptions!B136,0) -> 107 | X15: =ROUND(B15*Assumptions!B137*Assumptions!B65,0) -> 18
A16: 11 | B16: =B15*(1+Assumptions!B34) -> 3085.9708 | C16: =ROUND(B16*Assumptions!B25,0) -> 62 | D16: =ROUND(B16*Assumptions!B23,0) -> 8 | E16: =E15+D16-F16 -> 40 | F16: =ROUND(E15*Assumptions!B44,0) -> 2 | G16: =D16-F16 -> 6 | H16: =ROUND(E16*(Assumptions!B15*0.85+Assumptions!B11*0.15),0) -> 459 | I16: =H16 -> 459 | J16: =ROUND(E16*Assumptions!B68,0) -> 140 | K16: =ROUND(J16*Assumptions!B65,0) -> 11 | L16: =Assumptions!B70+IF(E16>Assumptions!B72,45,0) -> 31 | M16: =Assumptions!B76+Assumptions!B77 -> 35 | N16: =Assumptions!B81+Assumptions!B82+Assumptions!B87/12 -> 50 | O16: =ROUND(I16*Assumptions!B85+E16*Assumptions!B86+W16*Assumptions!B85+ROUND(B16*Assumptions!B137*Assumptions!B138*Assumptions!B139,0)*Assumptions!B86,0) -> 31 | P16: =K16+L16+M16+N16+O16+X16 -> 178 | Q16: =I16-P16 -> 281 | R16: =ROUND(B16*Assumptions!B51*Assumptions!B52,0) -> 1080 | S16: =I16+R16+W16 -> 1659 | T16: =IF(U16<P16*3,0,IF(U16<P16*6,ROUND((Q16+R16+W16)*0.75*Assumptions!B113,0),ROUND((Q16+R16+W16)*0.75*Assumptions!B114,0))) -> 424 | U16: =U15+Q16+R16+W16 -> 3300 | V16: =IF(B16>=Assumptions!B107,"Signal 6",IF(B16>=Assumptions!B106,"Signal 5",IF(B16>=Assumptions!B105,"Signal 4",IF(B16>=Assumptions!B104,"Signal 3",IF(B16>=Assumptions!B103,"Signal 2",IF(B16>=Assumptions!B102,"Signal 1","Pre-Signal 1")))))) -> Pre-Signal 1 | W16: =ROUND(B16*Assumptions!B137*Assumptions!B138*Assumptions!B139*Assumptions!B136,0) -> 120 | X16: =ROUND(B16*Assumptions!B137*Assumptions!B65,0) -> 20
A17: 12 | B17: =B16*(1+Assumptions!B34) -> 3456.2873 | C17: =ROUND(B17*Assumptions!B25,0) -> 69 | D17: =ROUND(B17*Assumptions!B23,0) -> 9 | E17: =E16+D17-F17 -> 47 | F17: =ROUND(E16*Assumptions!B44,0) -> 2 | G17: =D17-F17 -> 7 | H17: =ROUND(E17*(Assumptions!B15*0.85+Assumptions!B11*0.15),0) -> 539 | I17: =H17 -> 539 | J17: =ROUND(E17*Assumptions!B68,0) -> 165 | K17: =ROUND(J17*Assumptions!B65,0) -> 13 | L17: =Assumptions!B70+IF(E17>Assumptions!B72,45,0) -> 31 | M17: =Assumptions!B76+Assumptions!B77 -> 35 | N17: =Assumptions!B81+Assumptions!B82+Assumptions!B87/12 -> 50 | O17: =ROUND(I17*Assumptions!B85+E17*Assumptions!B86+W17*Assumptions!B85+ROUND(B17*Assumptions!B137*Assumptions!B138*Assumptions!B139,0)*Assumptions!B86,0) -> 37 | P17: =K17+L17+M17+N17+O17+X17 -> 188 | Q17: =I17-P17 -> 351 | R17: =ROUND(B17*Assumptions!B51*Assumptions!B52,0) -> 1210 | S17: =I17+R17+W17 -> 1884 | T17: =IF(U17<P17*3,0,IF(U17<P17*6,ROUND((Q17+R17+W17)*0.75*Assumptions!B113,0),ROUND((Q17+R17+W17)*0.75*Assumptions!B114,0))) -> 486 | U17: =U16+Q17+R17+W17 -> 4996 | V17: =IF(B17>=Assumptions!B107,"Signal 6",IF(B17>=Assumptions!B106,"Signal 5",IF(B17>=Assumptions!B105,"Signal 4",IF(B17>=Assumptions!B104,"Signal 3",IF(B17>=Assumptions!B103,"Signal 2",IF(B17>=Assumptions!B102,"Signal 1","Pre-Signal 1")))))) -> Pre-Signal 1 | W17: =ROUND(B17*Assumptions!B137*Assumptions!B138*Assumptions!B139*Assumptions!B136,0) -> 135 | X17: =ROUND(B17*Assumptions!B137*Assumptions!B65,0) -> 22
A18: 13 | B18: =B17*(1+Assumptions!B34) -> 3871.0417 | C18: =ROUND(B18*Assumptions!B25,0) -> 77 | D18: =ROUND(B18*Assumptions!B23,0) -> 10 | E18: =E17+D18-F18 -> 54 | F18: =ROUND(E17*Assumptions!B44,0) -> 3 | G18: =D18-F18 -> 7 | H18: =ROUND(E18*(Assumptions!B15*0.85+Assumptions!B11*0.15),0) -> 620 | I18: =H18 -> 620 | J18: =ROUND(E18*Assumptions!B68,0) -> 189 | K18: =ROUND(J18*Assumptions!B65,0) -> 15 | L18: =Assumptions!B70+IF(E18>Assumptions!B72,45,0) -> 31 | M18: =Assumptions!B76+Assumptions!B77 -> 35 | N18: =Assumptions!B81+Assumptions!B82+Assumptions!B87/12+Assumptions!B84 -> 92 | O18: =ROUND(I18*Assumptions!B85+E18*Assumptions!B86+W18*Assumptions!B85+ROUND(B18*Assumptions!B137*Assumptions!B138*Assumptions!B139,0)*Assumptions!B86,0) -> 42 | P18: =K18+L18+M18+N18+O18+X18 -> 240 | Q18: =I18-P18 -> 380 | R18: =ROUND(B18*Assumptions!B51*Assumptions!B52,0) -> 1355 | S18: =I18+R18+W18 -> 2126 | T18: =IF(U18<P18*3,0,IF(U18<P18*6,ROUND((Q18+R18+W18)*0.75*Assumptions!B113,0),ROUND((Q18+R18+W18)*0.75*Assumptions!B114,0))) -> 540 | U18: =U17+Q18+R18+W18 -> 6882 | V18: =IF(B18>=Assumptions!B107,"Signal 6",IF(B18>=Assumptions!B106,"Signal 5",IF(B18>=Assumptions!B105,"Signal 4",IF(B18>=Assumptions!B104,"Signal 3",IF(B18>=Assumptions!B103,"Signal 2",IF(B18>=Assumptions!B102,"Signal 1","Pre-Signal 1")))))) -> Pre-Signal 1 | W18: =ROUND(B18*Assumptions!B137*Assumptions!B138*Assumptions!B139*Assumptions!B136,0) -> 151 | X18: =ROUND(B18*Assumptions!B137*Assumptions!B65,0) -> 25
A19: 14 | B19: =B18*(1+Assumptions!B34) -> 4335.5668 | C19: =ROUND(B19*Assumptions!B25,0) -> 87 | D19: =ROUND(B19*Assumptions!B23,0) -> 11 | E19: =E18+D19-F19 -> 62 | F19: =ROUND(E18*Assumptions!B44,0) -> 3 | G19: =D19-F19 -> 8 | H19: =ROUND(E19*(Assumptions!B15*0.85+Assumptions!B11*0.15),0) -> 711 | I19: =H19 -> 711 | J19: =ROUND(E19*Assumptions!B68,0) -> 217 | K19: =ROUND(J19*Assumptions!B65,0) -> 17 | L19: =Assumptions!B70+IF(E19>Assumptions!B72,45,0) -> 31 | M19: =Assumptions!B76+Assumptions!B77 -> 35 | N19: =Assumptions!B81+Assumptions!B82+Assumptions!B87/12+Assumptions!B84 -> 92 | O19: =ROUND(I19*Assumptions!B85+E19*Assumptions!B86+W19*Assumptions!B85+ROUND(B19*Assumptions!B137*Assumptions!B138*Assumptions!B139,0)*Assumptions!B86,0) -> 48 | P19: =K19+L19+M19+N19+O19+X19 -> 251 | Q19: =I19-P19 -> 460 | R19: =ROUND(B19*Assumptions!B51*Assumptions!B52,0) -> 1517 | S19: =I19+R19+W19 -> 2397 | T19: =IF(U19<P19*3,0,IF(U19<P19*6,ROUND((Q19+R19+W19)*0.75*Assumptions!B113,0),ROUND((Q19+R19+W19)*0.75*Assumptions!B114,0))) -> 615 | U19: =U18+Q19+R19+W19 -> 9028 | V19: =IF(B19>=Assumptions!B107,"Signal 6",IF(B19>=Assumptions!B106,"Signal 5",IF(B19>=Assumptions!B105,"Signal 4",IF(B19>=Assumptions!B104,"Signal 3",IF(B19>=Assumptions!B103,"Signal 2",IF(B19>=Assumptions!B102,"Signal 1","Pre-Signal 1")))))) -> Pre-Signal 1 | W19: =ROUND(B19*Assumptions!B137*Assumptions!B138*Assumptions!B139*Assumptions!B136,0) -> 169 | X19: =ROUND(B19*Assumptions!B137*Assumptions!B65,0) -> 28
A20: 15 | B20: =B19*(1+Assumptions!B34) -> 4855.8348 | C20: =ROUND(B20*Assumptions!B25,0) -> 97 | D20: =ROUND(B20*Assumptions!B23,0) -> 12 | E20: =E19+D20-F20 -> 70 | F20: =ROUND(E19*Assumptions!B44,0) -> 4 | G20: =D20-F20 -> 8 | H20: =ROUND(E20*(Assumptions!B15*0.85+Assumptions!B11*0.15),0) -> 803 | I20: =H20 -> 803 | J20: =ROUND(E20*Assumptions!B68,0) -> 245 | K20: =ROUND(J20*Assumptions!B65,0) -> 20 | L20: =Assumptions!B70+IF(E20>Assumptions!B72,45,0) -> 31 | M20: =Assumptions!B76+Assumptions!B77 -> 35 | N20: =Assumptions!B81+Assumptions!B82+Assumptions!B87/12+Assumptions!B84 -> 92 | O20: =ROUND(I20*Assumptions!B85+E20*Assumptions!B86+W20*Assumptions!B85+ROUND(B20*Assumptions!B137*Assumptions!B138*Assumptions!B139,0)*Assumptions!B86,0) -> 54 | P20: =K20+L20+M20+N20+O20+X20 -> 263 | Q20: =I20-P20 -> 540 | R20: =ROUND(B20*Assumptions!B51*Assumptions!B52,0) -> 1700 | S20: =I20+R20+W20 -> 2692 | T20: =IF(U20<P20*3,0,IF(U20<P20*6,ROUND((Q20+R20+W20)*0.75*Assumptions!B113,0),ROUND((Q20+R20+W20)*0.75*Assumptions!B114,0))) -> 696 | U20: =U19+Q20+R20+W20 -> 11457 | V20: =IF(B20>=Assumptions!B107,"Signal 6",IF(B20>=Assumptions!B106,"Signal 5",IF(B20>=Assumptions!B105,"Signal 4",IF(B20>=Assumptions!B104,"Signal 3",IF(B20>=Assumptions!B103,"Signal 2",IF(B20>=Assumptions!B102,"Signal 1","Pre-Signal 1")))))) -> Pre-Signal 1 | W20: =ROUND(B20*Assumptions!B137*Assumptions!B138*Assumptions!B139*Assumptions!B136,0) -> 189 | X20: =ROUND(B20*Assumptions!B137*Assumptions!B65,0) -> 31
A21: 16 | B21: =B20*(1+Assumptions!B34) -> 5438.5349 | C21: =ROUND(B21*Assumptions!B25,0) -> 109 | D21: =ROUND(B21*Assumptions!B23,0) -> 14 | E21: =E20+D21-F21 -> 80 | F21: =ROUND(E20*Assumptions!B44,0) -> 4 | G21: =D21-F21 -> 10 | H21: =ROUND(E21*(Assumptions!B15*0.85+Assumptions!B11*0.15),0) -> 918 | I21: =H21 -> 918 | J21: =ROUND(E21*Assumptions!B68,0) -> 280 | K21: =ROUND(J21*Assumptions!B65,0) -> 22 | L21: =Assumptions!B70+IF(E21>Assumptions!B72,45,0) -> 31 | M21: =Assumptions!B76+Assumptions!B77 -> 35 | N21: =Assumptions!B81+Assumptions!B82+Assumptions!B87/12+Assumptions!B84 -> 92 | O21: =ROUND(I21*Assumptions!B85+E21*Assumptions!B86+W21*Assumptions!B85+ROUND(B21*Assumptions!B137*Assumptions!B138*Assumptions!B139,0)*Assumptions!B86,0) -> 62 | P21: =K21+L21+M21+N21+O21+X21 -> 277 | Q21: =I21-P21 -> 641 | R21: =ROUND(B21*Assumptions!B51*Assumptions!B52,0) -> 1903 | S21: =I21+R21+W21 -> 3033 | T21: =IF(U21<P21*3,0,IF(U21<P21*6,ROUND((Q21+R21+W21)*0.75*Assumptions!B113,0),ROUND((Q21+R21+W21)*0.75*Assumptions!B114,0))) -> 790 | U21: =U20+Q21+R21+W21 -> 14213 | V21: =IF(B21>=Assumptions!B107,"Signal 6",IF(B21>=Assumptions!B106,"Signal 5",IF(B21>=Assumptions!B105,"Signal 4",IF(B21>=Assumptions!B104,"Signal 3",IF(B21>=Assumptions!B103,"Signal 2",IF(B21>=Assumptions!B102,"Signal 1","Pre-Signal 1")))))) -> Pre-Signal 1 | W21: =ROUND(B21*Assumptions!B137*Assumptions!B138*Assumptions!B139*Assumptions!B136,0) -> 212 | X21: =ROUND(B21*Assumptions!B137*Assumptions!B65,0) -> 35
A22: 17 | B22: =B21*(1+Assumptions!B34) -> 6091.1591 | C22: =ROUND(B22*Assumptions!B25,0) -> 122 | D22: =ROUND(B22*Assumptions!B23,0) -> 15 | E22: =E21+D22-F22 -> 90 | F22: =ROUND(E21*Assumptions!B44,0) -> 5 | G22: =D22-F22 -> 10 | H22: =ROUND(E22*(Assumptions!B15*0.85+Assumptions!B11*0.15),0) -> 1033 | I22: =H22 -> 1033 | J22: =ROUND(E22*Assumptions!B68,0) -> 315 | K22: =ROUND(J22*Assumptions!B65,0) -> 25 | L22: =Assumptions!B70+IF(E22>Assumptions!B72,45,0) -> 31 | M22: =Assumptions!B76+Assumptions!B77 -> 35 | N22: =Assumptions!B81+Assumptions!B82+Assumptions!B87/12+Assumptions!B84 -> 92 | O22: =ROUND(I22*Assumptions!B85+E22*Assumptions!B86+W22*Assumptions!B85+ROUND(B22*Assumptions!B137*Assumptions!B138*Assumptions!B139,0)*Assumptions!B86,0) -> 69 | P22: =K22+L22+M22+N22+O22+X22 -> 291 | Q22: =I22-P22 -> 742 | R22: =ROUND(B22*Assumptions!B51*Assumptions!B52,0) -> 2132 | S22: =I22+R22+W22 -> 3403 | T22: =IF(U22<P22*3,0,IF(U22<P22*6,ROUND((Q22+R22+W22)*0.75*Assumptions!B113,0),ROUND((Q22+R22+W22)*0.75*Assumptions!B114,0))) -> 892 | U22: =U21+Q22+R22+W22 -> 17325 | V22: =IF(B22>=Assumptions!B107,"Signal 6",IF(B22>=Assumptions!B106,"Signal 5",IF(B22>=Assumptions!B105,"Signal 4",IF(B22>=Assumptions!B104,"Signal 3",IF(B22>=Assumptions!B103,"Signal 2",IF(B22>=Assumptions!B102,"Signal 1","Pre-Signal 1")))))) -> Pre-Signal 1 | W22: =ROUND(B22*Assumptions!B137*Assumptions!B138*Assumptions!B139*Assumptions!B136,0) -> 238 | X22: =ROUND(B22*Assumptions!B137*Assumptions!B65,0) -> 39
A23: 18 | B23: =B22*(1+Assumptions!B34) -> 6822.0982 | C23: =ROUND(B23*Assumptions!B25,0) -> 136 | D23: =ROUND(B23*Assumptions!B23,0) -> 17 | E23: =E22+D23-F23 -> 102 | F23: =ROUND(E22*Assumptions!B44,0) -> 5 | G23: =D23-F23 -> 12 | H23: =ROUND(E23*(Assumptions!B15*0.85+Assumptions!B11*0.15),0) -> 1170 | I23: =H23 -> 1170 | J23: =ROUND(E23*Assumptions!B68,0) -> 357 | K23: =ROUND(J23*Assumptions!B65,0) -> 29 | L23: =Assumptions!B70+IF(E23>Assumptions!B72,45,0) -> 31 | M23: =Assumptions!B76+Assumptions!B77 -> 35 | N23: =Assumptions!B81+Assumptions!B82+Assumptions!B87/12+Assumptions!B84 -> 92 | O23: =ROUND(I23*Assumptions!B85+E23*Assumptions!B86+W23*Assumptions!B85+ROUND(B23*Assumptions!B137*Assumptions!B138*Assumptions!B139,0)*Assumptions!B86,0) -> 78 | P23: =K23+L23+M23+N23+O23+X23 -> 309 | Q23: =I23-P23 -> 861 | R23: =ROUND(B23*Assumptions!B51*Assumptions!B52,0) -> 2388 | S23: =I23+R23+W23 -> 3824 | T23: =IF(U23<P23*3,0,IF(U23<P23*6,ROUND((Q23+R23+W23)*0.75*Assumptions!B113,0),ROUND((Q23+R23+W23)*0.75*Assumptions!B114,0))) -> 1007 | U23: =U22+Q23+R23+W23 -> 20840 | V23: =IF(B23>=Assumptions!B107,"Signal 6",IF(B23>=Assumptions!B106,"Signal 5",IF(B23>=Assumptions!B105,"Signal 4",IF(B23>=Assumptions!B104,"Signal 3",IF(B23>=Assumptions!B103,"Signal 2",IF(B23>=Assumptions!B102,"Signal 1","Pre-Signal 1")))))) -> Pre-Signal 1 | W23: =ROUND(B23*Assumptions!B137*Assumptions!B138*Assumptions!B139*Assumptions!B136,0) -> 266 | X23: =ROUND(B23*Assumptions!B137*Assumptions!B65,0) -> 44
A24: 19 | B24: =B23*(1+Assumptions!B34) -> 7640.75 | C24: =ROUND(B24*Assumptions!B25,0) -> 153 | D24: =ROUND(B24*Assumptions!B23,0) -> 19 | E24: =E23+D24-F24 -> 115 | F24: =ROUND(E23*Assumptions!B44,0) -> 6 | G24: =D24-F24 -> 13 | H24: =ROUND(E24*(Assumptions!B15*0.85+Assumptions!B11*0.15),0) -> 1320 | I24: =H24 -> 1320 | J24: =ROUND(E24*Assumptions!B68,0) -> 403 | K24: =ROUND(J24*Assumptions!B65,0) -> 32 | L24: =Assumptions!B70+IF(E24>Assumptions!B72,45,0) -> 31 | M24: =Assumptions!B76+Assumptions!B77 -> 35 | N24: =Assumptions!B81+Assumptions!B82+Assumptions!B87/12+Assumptions!B84 -> 92 | O24: =ROUND(I24*Assumptions!B85+E24*Assumptions!B86+W24*Assumptions!B85+ROUND(B24*Assumptions!B137*Assumptions!B138*Assumptions!B139,0)*Assumptions!B86,0) -> 88 | P24: =K24+L24+M24+N24+O24+X24 -> 327 | Q24: =I24-P24 -> 993 | R24: =ROUND(B24*Assumptions!B51*Assumptions!B52,0) -> 2674 | S24: =I24+R24+W24 -> 4292 | T24: =IF(U24<P24*3,0,IF(U24<P24*6,ROUND((Q24+R24+W24)*0.75*Assumptions!B113,0),ROUND((Q24+R24+W24)*0.75*Assumptions!B114,0))) -> 1136 | U24: =U23+Q24+R24+W24 -> 24805 | V24: =IF(B24>=Assumptions!B107,"Signal 6",IF(B24>=Assumptions!B106,"Signal 5",IF(B24>=Assumptions!B105,"Signal 4",IF(B24>=Assumptions!B104,"Signal 3",IF(B24>=Assumptions!B103,"Signal 2",IF(B24>=Assumptions!B102,"Signal 1","Pre-Signal 1")))))) -> Pre-Signal 1 | W24: =ROUND(B24*Assumptions!B137*Assumptions!B138*Assumptions!B139*Assumptions!B136,0) -> 298 | X24: =ROUND(B24*Assumptions!B137*Assumptions!B65,0) -> 49
A25: 20 | B25: =B24*(1+Assumptions!B34) -> 8557.64 | C25: =ROUND(B25*Assumptions!B25,0) -> 171 | D25: =ROUND(B25*Assumptions!B23,0) -> 21 | E25: =E24+D25-F25 -> 129 | F25: =ROUND(E24*Assumptions!B44,0) -> 7 | G25: =D25-F25 -> 14 | H25: =ROUND(E25*(Assumptions!B15*0.85+Assumptions!B11*0.15),0) -> 1480 | I25: =H25 -> 1480 | J25: =ROUND(E25*Assumptions!B68,0) -> 452 | K25: =ROUND(J25*Assumptions!B65,0) -> 36 | L25: =Assumptions!B70+IF(E25>Assumptions!B72,45,0) -> 31 | M25: =Assumptions!B76+Assumptions!B77 -> 35 | N25: =Assumptions!B81+Assumptions!B82+Assumptions!B87/12+Assumptions!B84 -> 92 | O25: =ROUND(I25*Assumptions!B85+E25*Assumptions!B86+W25*Assumptions!B85+ROUND(B25*Assumptions!B137*Assumptions!B138*Assumptions!B139,0)*Assumptions!B86,0) -> 99 | P25: =K25+L25+M25+N25+O25+X25 -> 348 | Q25: =I25-P25 -> 1132 | R25: =ROUND(B25*Assumptions!B51*Assumptions!B52,0) -> 2995 | S25: =I25+R25+W25 -> 4809 | T25: =IF(U25<P25*3,0,IF(U25<P25*6,ROUND((Q25+R25+W25)*0.75*Assumptions!B113,0),ROUND((Q25+R25+W25)*0.75*Assumptions!B114,0))) -> 1278 | U25: =U24+Q25+R25+W25 -> 29266 | V25: =IF(B25>=Assumptions!B107,"Signal 6",IF(B25>=Assumptions!B106,"Signal 5",IF(B25>=Assumptions!B105,"Signal 4",IF(B25>=Assumptions!B104,"Signal 3",IF(B25>=Assumptions!B103,"Signal 2",IF(B25>=Assumptions!B102,"Signal 1","Pre-Signal 1")))))) -> Pre-Signal 1 | W25: =ROUND(B25*Assumptions!B137*Assumptions!B138*Assumptions!B139*Assumptions!B136,0) -> 334 | X25: =ROUND(B25*Assumptions!B137*Assumptions!B65,0) -> 55
A26: 21 | B26: =B25*(1+Assumptions!B34) -> 9584.5568 | C26: =ROUND(B26*Assumptions!B25,0) -> 192 | D26: =ROUND(B26*Assumptions!B23,0) -> 24 | E26: =E25+D26-F26 -> 145 | F26: =ROUND(E25*Assumptions!B44,0) -> 8 | G26: =D26-F26 -> 16 | H26: =ROUND(E26*(Assumptions!B15*0.85+Assumptions!B11*0.15),0) -> 1664 | I26: =H26 -> 1664 | J26: =ROUND(E26*Assumptions!B68,0) -> 508 | K26: =ROUND(J26*Assumptions!B65,0) -> 41 | L26: =Assumptions!B70+IF(E26>Assumptions!B72,45,0) -> 31 | M26: =Assumptions!B76+Assumptions!B77 -> 35 | N26: =Assumptions!B81+Assumptions!B82+Assumptions!B87/12+Assumptions!B84 -> 92 | O26: =ROUND(I26*Assumptions!B85+E26*Assumptions!B86+W26*Assumptions!B85+ROUND(B26*Assumptions!B137*Assumptions!B138*Assumptions!B139,0)*Assumptions!B86,0) -> 111 | P26: =K26+L26+M26+N26+O26+X26 -> 371 | Q26: =I26-P26 -> 1293 | R26: =ROUND(B26*Assumptions!B51*Assumptions!B52,0) -> 3355 | S26: =I26+R26+W26 -> 5393 | T26: =IF(U26<P26*3,0,IF(U26<P26*6,ROUND((Q26+R26+W26)*0.75*Assumptions!B113,0),ROUND((Q26+R26+W26)*0.75*Assumptions!B114,0))) -> 1439 | U26: =U25+Q26+R26+W26 -> 34288 | V26: =IF(B26>=Assumptions!B107,"Signal 6",IF(B26>=Assumptions!B106,"Signal 5",IF(B26>=Assumptions!B105,"Signal 4",IF(B26>=Assumptions!B104,"Signal 3",IF(B26>=Assumptions!B103,"Signal 2",IF(B26>=Assumptions!B102,"Signal 1","Pre-Signal 1")))))) -> Pre-Signal 1 | W26: =ROUND(B26*Assumptions!B137*Assumptions!B138*Assumptions!B139*Assumptions!B136,0) -> 374 | X26: =ROUND(B26*Assumptions!B137*Assumptions!B65,0) -> 61
A27: 22 | B27: =B26*(1+Assumptions!B34) -> 10734.704 | C27: =ROUND(B27*Assumptions!B25,0) -> 215 | D27: =ROUND(B27*Assumptions!B23,0) -> 27 | E27: =E26+D27-F27 -> 163 | F27: =ROUND(E26*Assumptions!B44,0) -> 9 | G27: =D27-F27 -> 18 | H27: =ROUND(E27*(Assumptions!B15*0.85+Assumptions!B11*0.15),0) -> 1870 | I27: =H27 -> 1870 | J27: =ROUND(E27*Assumptions!B68,0) -> 571 | K27: =ROUND(J27*Assumptions!B65,0) -> 46 | L27: =Assumptions!B70+IF(E27>Assumptions!B72,45,0) -> 31 | M27: =Assumptions!B76+Assumptions!B77 -> 35 | N27: =Assumptions!B81+Assumptions!B82+Assumptions!B87/12+Assumptions!B84 -> 92 | O27: =ROUND(I27*Assumptions!B85+E27*Assumptions!B86+W27*Assumptions!B85+ROUND(B27*Assumptions!B137*Assumptions!B138*Assumptions!B139,0)*Assumptions!B86,0) -> 125 | P27: =K27+L27+M27+N27+O27+X27 -> 398 | Q27: =I27-P27 -> 1472 | R27: =ROUND(B27*Assumptions!B51*Assumptions!B52,0) -> 3757 | S27: =I27+R27+W27 -> 6046 | T27: =IF(U27<P27*3,0,IF(U27<P27*6,ROUND((Q27+R27+W27)*0.75*Assumptions!B113,0),ROUND((Q27+R27+W27)*0.75*Assumptions!B114,0))) -> 1618 | U27: =U26+Q27+R27+W27 -> 39936 | V27: =IF(B27>=Assumptions!B107,"Signal 6",IF(B27>=Assumptions!B106,"Signal 5",IF(B27>=Assumptions!B105,"Signal 4",IF(B27>=Assumptions!B104,"Signal 3",IF(B27>=Assumptions!B103,"Signal 2",IF(B27>=Assumptions!B102,"Signal 1","Pre-Signal 1")))))) -> Signal 1 | W27: =ROUND(B27*Assumptions!B137*Assumptions!B138*Assumptions!B139*Assumptions!B136,0) -> 419 | X27: =ROUND(B27*Assumptions!B137*Assumptions!B65,0) -> 69
A28: 23 | B28: =B27*(1+Assumptions!B34) -> 12022.868 | C28: =ROUND(B28*Assumptions!B25,0) -> 240 | D28: =ROUND(B28*Assumptions!B23,0) -> 30 | E28: =E27+D28-F28 -> 183 | F28: =ROUND(E27*Assumptions!B44,0) -> 10 | G28: =D28-F28 -> 20 | H28: =ROUND(E28*(Assumptions!B15*0.85+Assumptions!B11*0.15),0) -> 2100 | I28: =H28 -> 2100 | J28: =ROUND(E28*Assumptions!B68,0) -> 641 | K28: =ROUND(J28*Assumptions!B65,0) -> 51 | L28: =Assumptions!B70+IF(E28>Assumptions!B72,45,0) -> 31 | M28: =Assumptions!B76+Assumptions!B77 -> 35 | N28: =Assumptions!B81+Assumptions!B82+Assumptions!B87/12+Assumptions!B84 -> 92 | O28: =ROUND(I28*Assumptions!B85+E28*Assumptions!B86+W28*Assumptions!B85+ROUND(B28*Assumptions!B137*Assumptions!B138*Assumptions!B139,0)*Assumptions!B86,0) -> 140 | P28: =K28+L28+M28+N28+O28+X28 -> 426 | Q28: =I28-P28 -> 1674 | R28: =ROUND(B28*Assumptions!B51*Assumptions!B52,0) -> 4208 | S28: =I28+R28+W28 -> 6777 | T28: =IF(U28<P28*3,0,IF(U28<P28*6,ROUND((Q28+R28+W28)*0.75*Assumptions!B113,0),ROUND((Q28+R28+W28)*0.75*Assumptions!B114,0))) -> 1820 | U28: =U27+Q28+R28+W28 -> 46287 | V28: =IF(B28>=Assumptions!B107,"Signal 6",IF(B28>=Assumptions!B106,"Signal 5",IF(B28>=Assumptions!B105,"Signal 4",IF(B28>=Assumptions!B104,"Signal 3",IF(B28>=Assumptions!B103,"Signal 2",IF(B28>=Assumptions!B102,"Signal 1","Pre-Signal 1")))))) -> Signal 1 | W28: =ROUND(B28*Assumptions!B137*Assumptions!B138*Assumptions!B139*Assumptions!B136,0) -> 469 | X28: =ROUND(B28*Assumptions!B137*Assumptions!B65,0) -> 77
A29: 24 | B29: =B28*(1+Assumptions!B34) -> 13465.612 | C29: =ROUND(B29*Assumptions!B25,0) -> 269 | D29: =ROUND(B29*Assumptions!B23,0) -> 34 | E29: =E28+D29-F29 -> 206 | F29: =ROUND(E28*Assumptions!B44,0) -> 11 | G29: =D29-F29 -> 23 | H29: =ROUND(E29*(Assumptions!B15*0.85+Assumptions!B11*0.15),0) -> 2364 | I29: =H29 -> 2364 | J29: =ROUND(E29*Assumptions!B68,0) -> 721 | K29: =ROUND(J29*Assumptions!B65,0) -> 58 | L29: =Assumptions!B70+IF(E29>Assumptions!B72,45,0) -> 31 | M29: =Assumptions!B76+Assumptions!B77 -> 35 | N29: =Assumptions!B81+Assumptions!B82+Assumptions!B87/12+Assumptions!B84 -> 92 | O29: =ROUND(I29*Assumptions!B85+E29*Assumptions!B86+W29*Assumptions!B85+ROUND(B29*Assumptions!B137*Assumptions!B138*Assumptions!B139,0)*Assumptions!B86,0) -> 158 | P29: =K29+L29+M29+N29+O29+X29 -> 460 | Q29: =I29-P29 -> 1904 | R29: =ROUND(B29*Assumptions!B51*Assumptions!B52,0) -> 4713 | S29: =I29+R29+W29 -> 7602 | T29: =IF(U29<P29*3,0,IF(U29<P29*6,ROUND((Q29+R29+W29)*0.75*Assumptions!B113,0),ROUND((Q29+R29+W29)*0.75*Assumptions!B114,0))) -> 2046 | U29: =U28+Q29+R29+W29 -> 53429 | V29: =IF(B29>=Assumptions!B107,"Signal 6",IF(B29>=Assumptions!B106,"Signal 5",IF(B29>=Assumptions!B105,"Signal 4",IF(B29>=Assumptions!B104,"Signal 3",IF(B29>=Assumptions!B103,"Signal 2",IF(B29>=Assumptions!B102,"Signal 1","Pre-Signal 1")))))) -> Signal 1 | W29: =ROUND(B29*Assumptions!B137*Assumptions!B138*Assumptions!B139*Assumptions!B136,0) -> 525 | X29: =ROUND(B29*Assumptions!B137*Assumptions!B65,0) -> 86
A30: 25 | B30: =B29*(1+Assumptions!B34) -> 15081.486 | C30: =ROUND(B30*Assumptions!B25,0) -> 302 | D30: =ROUND(B30*Assumptions!B23,0) -> 38 | E30: =E29+D30-F30 -> 232 | F30: =ROUND(E29*Assumptions!B44,0) -> 12 | G30: =D30-F30 -> 26 | H30: =ROUND(E30*(Assumptions!B15*0.85+Assumptions!B11*0.15),0) -> 2662 | I30: =H30 -> 2662 | J30: =ROUND(E30*Assumptions!B68,0) -> 812 | K30: =ROUND(J30*Assumptions!B65,0) -> 65 | L30: =Assumptions!B70+IF(E30>Assumptions!B72,45,0) -> 31 | M30: =Assumptions!B76+Assumptions!B77 -> 35 | N30: =Assumptions!B81+Assumptions!B82+Assumptions!B87/12+Assumptions!B84 -> 92 | O30: =ROUND(I30*Assumptions!B85+E30*Assumptions!B86+W30*Assumptions!B85+ROUND(B30*Assumptions!B137*Assumptions!B138*Assumptions!B139,0)*Assumptions!B86,0) -> 177 | P30: =K30+L30+M30+N30+O30+X30 -> 497 | Q30: =I30-P30 -> 2165 | R30: =ROUND(B30*Assumptions!B51*Assumptions!B52,0) -> 5279 | S30: =I30+R30+W30 -> 8529 | T30: =IF(U30<P30*3,0,IF(U30<P30*6,ROUND((Q30+R30+W30)*0.75*Assumptions!B113,0),ROUND((Q30+R30+W30)*0.75*Assumptions!B114,0))) -> 2301 | U30: =U29+Q30+R30+W30 -> 61461 | V30: =IF(B30>=Assumptions!B107,"Signal 6",IF(B30>=Assumptions!B106,"Signal 5",IF(B30>=Assumptions!B105,"Signal 4",IF(B30>=Assumptions!B104,"Signal 3",IF(B30>=Assumptions!B103,"Signal 2",IF(B30>=Assumptions!B102,"Signal 1","Pre-Signal 1")))))) -> Signal 1 | W30: =ROUND(B30*Assumptions!B137*Assumptions!B138*Assumptions!B139*Assumptions!B136,0) -> 588 | X30: =ROUND(B30*Assumptions!B137*Assumptions!B65,0) -> 97
A31: 26 | B31: =B30*(1+Assumptions!B34) -> 16891.264 | C31: =ROUND(B31*Assumptions!B25,0) -> 338 | D31: =ROUND(B31*Assumptions!B23,0) -> 42 | E31: =E30+D31-F31 -> 260 | F31: =ROUND(E30*Assumptions!B44,0) -> 14 | G31: =D31-F31 -> 28 | H31: =ROUND(E31*(Assumptions!B15*0.85+Assumptions!B11*0.15),0) -> 2984 | I31: =H31 -> 2984 | J31: =ROUND(E31*Assumptions!B68,0) -> 910 | K31: =ROUND(J31*Assumptions!B65,0) -> 73 | L31: =Assumptions!B70+IF(E31>Assumptions!B72,45,0) -> 31 | M31: =Assumptions!B76+Assumptions!B77 -> 35 | N31: =Assumptions!B81+Assumptions!B82+Assumptions!B87/12+Assumptions!B84 -> 92 | O31: =ROUND(I31*Assumptions!B85+E31*Assumptions!B86+W31*Assumptions!B85+ROUND(B31*Assumptions!B137*Assumptions!B138*Assumptions!B139,0)*Assumptions!B86,0) -> 199 | P31: =K31+L31+M31+N31+O31+X31 -> 538 | Q31: =I31-P31 -> 2446 | R31: =ROUND(B31*Assumptions!B51*Assumptions!B52,0) -> 5912 | S31: =I31+R31+W31 -> 9555 | T31: =IF(U31<P31*3,0,IF(U31<P31*6,ROUND((Q31+R31+W31)*0.75*Assumptions!B113,0),ROUND((Q31+R31+W31)*0.75*Assumptions!B114,0))) -> 2583 | U31: =U30+Q31+R31+W31 -> 70478 | V31: =IF(B31>=Assumptions!B107,"Signal 6",IF(B31>=Assumptions!B106,"Signal 5",IF(B31>=Assumptions!B105,"Signal 4",IF(B31>=Assumptions!B104,"Signal 3",IF(B31>=Assumptions!B103,"Signal 2",IF(B31>=Assumptions!B102,"Signal 1","Pre-Signal 1")))))) -> Signal 1 | W31: =ROUND(B31*Assumptions!B137*Assumptions!B138*Assumptions!B139*Assumptions!B136,0) -> 659 | X31: =ROUND(B31*Assumptions!B137*Assumptions!B65,0) -> 108
A32: 27 | B32: =B31*(1+Assumptions!B34) -> 18918.216 | C32: =ROUND(B32*Assumptions!B25,0) -> 378 | D32: =ROUND(B32*Assumptions!B23,0) -> 47 | E32: =E31+D32-F32 -> 291 | F32: =ROUND(E31*Assumptions!B44,0) -> 16 | G32: =D32-F32 -> 31 | H32: =ROUND(E32*(Assumptions!B15*0.85+Assumptions!B11*0.15),0) -> 3339 | I32: =H32 -> 3339 | J32: =ROUND(E32*Assumptions!B68,0) -> 1019 | K32: =ROUND(J32*Assumptions!B65,0) -> 82 | L32: =Assumptions!B70+IF(E32>Assumptions!B72,45,0) -> 31 | M32: =Assumptions!B76+Assumptions!B77 -> 35 | N32: =Assumptions!B81+Assumptions!B82+Assumptions!B87/12+Assumptions!B84 -> 92 | O32: =ROUND(I32*Assumptions!B85+E32*Assumptions!B86+W32*Assumptions!B85+ROUND(B32*Assumptions!B137*Assumptions!B138*Assumptions!B139,0)*Assumptions!B86,0) -> 223 | P32: =K32+L32+M32+N32+O32+X32 -> 584 | Q32: =I32-P32 -> 2755 | R32: =ROUND(B32*Assumptions!B51*Assumptions!B52,0) -> 6621 | S32: =I32+R32+W32 -> 10698 | T32: =IF(U32<P32*3,0,IF(U32<P32*6,ROUND((Q32+R32+W32)*0.75*Assumptions!B113,0),ROUND((Q32+R32+W32)*0.75*Assumptions!B114,0))) -> 2898 | U32: =U31+Q32+R32+W32 -> 80592 | V32: =IF(B32>=Assumptions!B107,"Signal 6",IF(B32>=Assumptions!B106,"Signal 5",IF(B32>=Assumptions!B105,"Signal 4",IF(B32>=Assumptions!B104,"Signal 3",IF(B32>=Assumptions!B103,"Signal 2",IF(B32>=Assumptions!B102,"Signal 1","Pre-Signal 1")))))) -> Signal 1 | W32: =ROUND(B32*Assumptions!B137*Assumptions!B138*Assumptions!B139*Assumptions!B136,0) -> 738 | X32: =ROUND(B32*Assumptions!B137*Assumptions!B65,0) -> 121
A33: 28 | B33: =B32*(1+Assumptions!B34) -> 21188.402 | C33: =ROUND(B33*Assumptions!B25,0) -> 424 | D33: =ROUND(B33*Assumptions!B23,0) -> 53 | E33: =E32+D33-F33 -> 327 | F33: =ROUND(E32*Assumptions!B44,0) -> 17 | G33: =D33-F33 -> 36 | H33: =ROUND(E33*(Assumptions!B15*0.85+Assumptions!B11*0.15),0) -> 3752 | I33: =H33 -> 3752 | J33: =ROUND(E33*Assumptions!B68,0) -> 1145 | K33: =ROUND(J33*Assumptions!B65,0) -> 92 | L33: =Assumptions!B70+IF(E33>Assumptions!B72,45,0) -> 31 | M33: =Assumptions!B76+Assumptions!B77 -> 35 | N33: =Assumptions!B81+Assumptions!B82+Assumptions!B87/12+Assumptions!B84 -> 92 | O33: =ROUND(I33*Assumptions!B85+E33*Assumptions!B86+W33*Assumptions!B85+ROUND(B33*Assumptions!B137*Assumptions!B138*Assumptions!B139,0)*Assumptions!B86,0) -> 250 | P33: =K33+L33+M33+N33+O33+X33 -> 636 | Q33: =I33-P33 -> 3116 | R33: =ROUND(B33*Assumptions!B51*Assumptions!B52,0) -> 7416 | S33: =I33+R33+W33 -> 11994 | T33: =IF(U33<P33*3,0,IF(U33<P33*6,ROUND((Q33+R33+W33)*0.75*Assumptions!B113,0),ROUND((Q33+R33+W33)*0.75*Assumptions!B114,0))) -> 3254 | U33: =U32+Q33+R33+W33 -> 91950 | V33: =IF(B33>=Assumptions!B107,"Signal 6",IF(B33>=Assumptions!B106,"Signal 5",IF(B33>=Assumptions!B105,"Signal 4",IF(B33>=Assumptions!B104,"Signal 3",IF(B33>=Assumptions!B103,"Signal 2",IF(B33>=Assumptions!B102,"Signal 1","Pre-Signal 1")))))) -> Signal 1 | W33: =ROUND(B33*Assumptions!B137*Assumptions!B138*Assumptions!B139*Assumptions!B136,0) -> 826 | X33: =ROUND(B33*Assumptions!B137*Assumptions!B65,0) -> 136
A34: 29 | B34: =B33*(1+Assumptions!B34) -> 23731.01 | C34: =ROUND(B34*Assumptions!B25,0) -> 475 | D34: =ROUND(B34*Assumptions!B23,0) -> 59 | E34: =E33+D34-F34 -> 366 | F34: =ROUND(E33*Assumptions!B44,0) -> 20 | G34: =D34-F34 -> 39 | H34: =ROUND(E34*(Assumptions!B15*0.85+Assumptions!B11*0.15),0) -> 4200 | I34: =H34 -> 4200 | J34: =ROUND(E34*Assumptions!B68,0) -> 1281 | K34: =ROUND(J34*Assumptions!B65,0) -> 102 | L34: =Assumptions!B70+IF(E34>Assumptions!B72,45,0) -> 31 | M34: =Assumptions!B76+Assumptions!B77 -> 35 | N34: =Assumptions!B81+Assumptions!B82+Assumptions!B87/12+Assumptions!B84 -> 92 | O34: =ROUND(I34*Assumptions!B85+E34*Assumptions!B86+W34*Assumptions!B85+ROUND(B34*Assumptions!B137*Assumptions!B138*Assumptions!B139,0)*Assumptions!B86,0) -> 280 | P34: =K34+L34+M34+N34+O34+X34 -> 692 | Q34: =I34-P34 -> 3508 | R34: =ROUND(B34*Assumptions!B51*Assumptions!B52,0) -> 8306 | S34: =I34+R34+W34 -> 13432 | T34: =IF(U34<P34*3,0,IF(U34<P34*6,ROUND((Q34+R34+W34)*0.75*Assumptions!B113,0),ROUND((Q34+R34+W34)*0.75*Assumptions!B114,0))) -> 3650 | U34: =U33+Q34+R34+W34 -> 104690 | V34: =IF(B34>=Assumptions!B107,"Signal 6",IF(B34>=Assumptions!B106,"Signal 5",IF(B34>=Assumptions!B105,"Signal 4",IF(B34>=Assumptions!B104,"Signal 3",IF(B34>=Assumptions!B103,"Signal 2",IF(B34>=Assumptions!B102,"Signal 1","Pre-Signal 1")))))) -> Signal 1 | W34: =ROUND(B34*Assumptions!B137*Assumptions!B138*Assumptions!B139*Assumptions!B136,0) -> 926 | X34: =ROUND(B34*Assumptions!B137*Assumptions!B65,0) -> 152
A35: 30 | B35: =B34*(1+Assumptions!B34) -> 26578.731 | C35: =ROUND(B35*Assumptions!B25,0) -> 532 | D35: =ROUND(B35*Assumptions!B23,0) -> 66 | E35: =E34+D35-F35 -> 410 | F35: =ROUND(E34*Assumptions!B44,0) -> 22 | G35: =D35-F35 -> 44 | H35: =ROUND(E35*(Assumptions!B15*0.85+Assumptions!B11*0.15),0) -> 4705 | I35: =H35 -> 4705 | J35: =ROUND(E35*Assumptions!B68,0) -> 1435 | K35: =ROUND(J35*Assumptions!B65,0) -> 115 | L35: =Assumptions!B70+IF(E35>Assumptions!B72,45,0) -> 31 | M35: =Assumptions!B76+Assumptions!B77 -> 35 | N35: =Assumptions!B81+Assumptions!B82+Assumptions!B87/12+Assumptions!B84 -> 92 | O35: =ROUND(I35*Assumptions!B85+E35*Assumptions!B86+W35*Assumptions!B85+ROUND(B35*Assumptions!B137*Assumptions!B138*Assumptions!B139,0)*Assumptions!B86,0) -> 314 | P35: =K35+L35+M35+N35+O35+X35 -> 757 | Q35: =I35-P35 -> 3948 | R35: =ROUND(B35*Assumptions!B51*Assumptions!B52,0) -> 9303 | S35: =I35+R35+W35 -> 15045 | T35: =IF(U35<P35*3,0,IF(U35<P35*6,ROUND((Q35+R35+W35)*0.75*Assumptions!B113,0),ROUND((Q35+R35+W35)*0.75*Assumptions!B114,0))) -> 4094 | U35: =U34+Q35+R35+W35 -> 118978 | V35: =IF(B35>=Assumptions!B107,"Signal 6",IF(B35>=Assumptions!B106,"Signal 5",IF(B35>=Assumptions!B105,"Signal 4",IF(B35>=Assumptions!B104,"Signal 3",IF(B35>=Assumptions!B103,"Signal 2",IF(B35>=Assumptions!B102,"Signal 1","Pre-Signal 1")))))) -> Signal 2 | W35: =ROUND(B35*Assumptions!B137*Assumptions!B138*Assumptions!B139*Assumptions!B136,0) -> 1037 | X35: =ROUND(B35*Assumptions!B137*Assumptions!B65,0) -> 170
A36: 31 | B36: =B35*(1+Assumptions!B34) -> 29768.179 | C36: =ROUND(B36*Assumptions!B25,0) -> 595 | D36: =ROUND(B36*Assumptions!B23,0) -> 74 | E36: =E35+D36-F36 -> 459 | F36: =ROUND(E35*Assumptions!B44,0) -> 25 | G36: =D36-F36 -> 49 | H36: =ROUND(E36*(Assumptions!B15*0.85+Assumptions!B11*0.15),0) -> 5267 | I36: =H36 -> 5267 | J36: =ROUND(E36*Assumptions!B68,0) -> 1607 | K36: =ROUND(J36*Assumptions!B65,0) -> 129 | L36: =Assumptions!B70+IF(E36>Assumptions!B72,45,0) -> 31 | M36: =Assumptions!B76+Assumptions!B77 -> 35 | N36: =Assumptions!B81+Assumptions!B82+Assumptions!B87/12+Assumptions!B84 -> 92 | O36: =ROUND(I36*Assumptions!B85+E36*Assumptions!B86+W36*Assumptions!B85+ROUND(B36*Assumptions!B137*Assumptions!B138*Assumptions!B139,0)*Assumptions!B86,0) -> 351 | P36: =K36+L36+M36+N36+O36+X36 -> 829 | Q36: =I36-P36 -> 4438 | R36: =ROUND(B36*Assumptions!B51*Assumptions!B52,0) -> 10419 | S36: =I36+R36+W36 -> 16847 | T36: =IF(U36<P36*3,0,IF(U36<P36*6,ROUND((Q36+R36+W36)*0.75*Assumptions!B113,0),ROUND((Q36+R36+W36)*0.75*Assumptions!B114,0))) -> 4589 | U36: =U35+Q36+R36+W36 -> 134996 | V36: =IF(B36>=Assumptions!B107,"Signal 6",IF(B36>=Assumptions!B106,"Signal 5",IF(B36>=Assumptions!B105,"Signal 4",IF(B36>=Assumptions!B104,"Signal 3",IF(B36>=Assumptions!B103,"Signal 2",IF(B36>=Assumptions!B102,"Signal 1","Pre-Signal 1")))))) -> Signal 2 | W36: =ROUND(B36*Assumptions!B137*Assumptions!B138*Assumptions!B139*Assumptions!B136,0) -> 1161 | X36: =ROUND(B36*Assumptions!B137*Assumptions!B65,0) -> 191
A37: 32 | B37: =B36*(1+Assumptions!B34) -> 33340.36 | C37: =ROUND(B37*Assumptions!B25,0) -> 667 | D37: =ROUND(B37*Assumptions!B23,0) -> 83 | E37: =E36+D37-F37 -> 514 | F37: =ROUND(E36*Assumptions!B44,0) -> 28 | G37: =D37-F37 -> 55 | H37: =ROUND(E37*(Assumptions!B15*0.85+Assumptions!B11*0.15),0) -> 5898 | I37: =H37 -> 5898 | J37: =ROUND(E37*Assumptions!B68,0) -> 1799 | K37: =ROUND(J37*Assumptions!B65,0) -> 144 | L37: =Assumptions!B70+IF(E37>Assumptions!B72,45,0) -> 76 | M37: =Assumptions!B76+Assumptions!B77 -> 35 | N37: =Assumptions!B81+Assumptions!B82+Assumptions!B87/12+Assumptions!B84 -> 92 | O37: =ROUND(I37*Assumptions!B85+E37*Assumptions!B86+W37*Assumptions!B85+ROUND(B37*Assumptions!B137*Assumptions!B138*Assumptions!B139,0)*Assumptions!B86,0) -> 393 | P37: =K37+L37+M37+N37+O37+X37 -> 953 | Q37: =I37-P37 -> 4945 | R37: =ROUND(B37*Assumptions!B51*Assumptions!B52,0) -> 11669 | S37: =I37+R37+W37 -> 18867 | T37: =IF(U37<P37*3,0,IF(U37<P37*6,ROUND((Q37+R37+W37)*0.75*Assumptions!B113,0),ROUND((Q37+R37+W37)*0.75*Assumptions!B114,0))) -> 5132 | U37: =U36+Q37+R37+W37 -> 152910 | V37: =IF(B37>=Assumptions!B107,"Signal 6",IF(B37>=Assumptions!B106,"Signal 5",IF(B37>=Assumptions!B105,"Signal 4",IF(B37>=Assumptions!B104,"Signal 3",IF(B37>=Assumptions!B103,"Signal 2",IF(B37>=Assumptions!B102,"Signal 1","Pre-Signal 1")))))) -> Signal 2 | W37: =ROUND(B37*Assumptions!B137*Assumptions!B138*Assumptions!B139*Assumptions!B136,0) -> 1300 | X37: =ROUND(B37*Assumptions!B137*Assumptions!B65,0) -> 213
A38: 33 | B38: =B37*(1+Assumptions!B34) -> 37341.203 | C38: =ROUND(B38*Assumptions!B25,0) -> 747 | D38: =ROUND(B38*Assumptions!B23,0) -> 93 | E38: =E37+D38-F38 -> 576 | F38: =ROUND(E37*Assumptions!B44,0) -> 31 | G38: =D38-F38 -> 62 | H38: =ROUND(E38*(Assumptions!B15*0.85+Assumptions!B11*0.15),0) -> 6610 | I38: =H38 -> 6610 | J38: =ROUND(E38*Assumptions!B68,0) -> 2016 | K38: =ROUND(J38*Assumptions!B65,0) -> 161 | L38: =Assumptions!B70+IF(E38>Assumptions!B72,45,0) -> 76 | M38: =Assumptions!B76+Assumptions!B77 -> 35 | N38: =Assumptions!B81+Assumptions!B82+Assumptions!B87/12+Assumptions!B84 -> 92 | O38: =ROUND(I38*Assumptions!B85+E38*Assumptions!B86+W38*Assumptions!B85+ROUND(B38*Assumptions!B137*Assumptions!B138*Assumptions!B139,0)*Assumptions!B86,0) -> 440 | P38: =K38+L38+M38+N38+O38+X38 -> 1043 | Q38: =I38-P38 -> 5567 | R38: =ROUND(B38*Assumptions!B51*Assumptions!B52,0) -> 13069 | S38: =I38+R38+W38 -> 21135 | T38: =IF(U38<P38*3,0,IF(U38<P38*6,ROUND((Q38+R38+W38)*0.75*Assumptions!B113,0),ROUND((Q38+R38+W38)*0.75*Assumptions!B114,0))) -> 5756 | U38: =U37+Q38+R38+W38 -> 173002 | V38: =IF(B38>=Assumptions!B107,"Signal 6",IF(B38>=Assumptions!B106,"Signal 5",IF(B38>=Assumptions!B105,"Signal 4",IF(B38>=Assumptions!B104,"Signal 3",IF(B38>=Assumptions!B103,"Signal 2",IF(B38>=Assumptions!B102,"Signal 1","Pre-Signal 1")))))) -> Signal 2 | W38: =ROUND(B38*Assumptions!B137*Assumptions!B138*Assumptions!B139*Assumptions!B136,0) -> 1456 | X38: =ROUND(B38*Assumptions!B137*Assumptions!B65,0) -> 239
A39: 34 | B39: =B38*(1+Assumptions!B34) -> 41822.148 | C39: =ROUND(B39*Assumptions!B25,0) -> 836 | D39: =ROUND(B39*Assumptions!B23,0) -> 105 | E39: =E38+D39-F39 -> 646 | F39: =ROUND(E38*Assumptions!B44,0) -> 35 | G39: =D39-F39 -> 70 | H39: =ROUND(E39*(Assumptions!B15*0.85+Assumptions!B11*0.15),0) -> 7413 | I39: =H39 -> 7413 | J39: =ROUND(E39*Assumptions!B68,0) -> 2261 | K39: =ROUND(J39*Assumptions!B65,0) -> 181 | L39: =Assumptions!B70+IF(E39>Assumptions!B72,45,0) -> 76 | M39: =Assumptions!B76+Assumptions!B77 -> 35 | N39: =Assumptions!B81+Assumptions!B82+Assumptions!B87/12+Assumptions!B84 -> 92 | O39: =ROUND(I39*Assumptions!B85+E39*Assumptions!B86+W39*Assumptions!B85+ROUND(B39*Assumptions!B137*Assumptions!B138*Assumptions!B139,0)*Assumptions!B86,0) -> 494 | P39: =K39+L39+M39+N39+O39+X39 -> 1146 | Q39: =I39-P39 -> 6267 | R39: =ROUND(B39*Assumptions!B51*Assumptions!B52,0) -> 14638 | S39: =I39+R39+W39 -> 23682 | T39: =IF(U39<P39*3,0,IF(U39<P39*6,ROUND((Q39+R39+W39)*0.75*Assumptions!B113,0),ROUND((Q39+R39+W39)*0.75*Assumptions!B114,0))) -> 6457 | U39: =U38+Q39+R39+W39 -> 195538 | V39: =IF(B39>=Assumptions!B107,"Signal 6",IF(B39>=Assumptions!B106,"Signal 5",IF(B39>=Assumptions!B105,"Signal 4",IF(B39>=Assumptions!B104,"Signal 3",IF(B39>=Assumptions!B103,"Signal 2",IF(B39>=Assumptions!B102,"Signal 1","Pre-Signal 1")))))) -> Signal 3 | W39: =ROUND(B39*Assumptions!B137*Assumptions!B138*Assumptions!B139*Assumptions!B136,0) -> 1631 | X39: =ROUND(B39*Assumptions!B137*Assumptions!B65,0) -> 268
A40: 35 | B40: =B39*(1+Assumptions!B34) -> 46840.805 | C40: =ROUND(B40*Assumptions!B25,0) -> 937 | D40: =ROUND(B40*Assumptions!B23,0) -> 117 | E40: =E39+D40-F40 -> 724 | F40: =ROUND(E39*Assumptions!B44,0) -> 39 | G40: =D40-F40 -> 78 | H40: =ROUND(E40*(Assumptions!B15*0.85+Assumptions!B11*0.15),0) -> 8308 | I40: =H40 -> 8308 | J40: =ROUND(E40*Assumptions!B68,0) -> 2534 | K40: =ROUND(J40*Assumptions!B65,0) -> 203 | L40: =Assumptions!B70+IF(E40>Assumptions!B72,45,0) -> 76 | M40: =Assumptions!B76+Assumptions!B77 -> 35 | N40: =Assumptions!B81+Assumptions!B82+Assumptions!B87/12+Assumptions!B84 -> 92 | O40: =ROUND(I40*Assumptions!B85+E40*Assumptions!B86+W40*Assumptions!B85+ROUND(B40*Assumptions!B137*Assumptions!B138*Assumptions!B139,0)*Assumptions!B86,0) -> 553 | P40: =K40+L40+M40+N40+O40+X40 -> 1259 | Q40: =I40-P40 -> 7049 | R40: =ROUND(B40*Assumptions!B51*Assumptions!B52,0) -> 16394 | S40: =I40+R40+W40 -> 26529 | T40: =IF(U40<P40*3,0,IF(U40<P40*6,ROUND((Q40+R40+W40)*0.75*Assumptions!B113,0),ROUND((Q40+R40+W40)*0.75*Assumptions!B114,0))) -> 7240 | U40: =U39+Q40+R40+W40 -> 220808 | V40: =IF(B40>=Assumptions!B107,"Signal 6",IF(B40>=Assumptions!B106,"Signal 5",IF(B40>=Assumptions!B105,"Signal 4",IF(B40>=Assumptions!B104,"Signal 3",IF(B40>=Assumptions!B103,"Signal 2",IF(B40>=Assumptions!B102,"Signal 1","Pre-Signal 1")))))) -> Signal 3 | W40: =ROUND(B40*Assumptions!B137*Assumptions!B138*Assumptions!B139*Assumptions!B136,0) -> 1827 | X40: =ROUND(B40*Assumptions!B137*Assumptions!B65,0) -> 300
A41: 36 | B41: =B40*(1+Assumptions!B34) -> 52461.702 | C41: =ROUND(B41*Assumptions!B25,0) -> 1049 | D41: =ROUND(B41*Assumptions!B23,0) -> 131 | E41: =E40+D41-F41 -> 812 | F41: =ROUND(E40*Assumptions!B44,0) -> 43 | G41: =D41-F41 -> 88 | H41: =ROUND(E41*(Assumptions!B15*0.85+Assumptions!B11*0.15),0) -> 9318 | I41: =H41 -> 9318 | J41: =ROUND(E41*Assumptions!B68,0) -> 2842 | K41: =ROUND(J41*Assumptions!B65,0) -> 227 | L41: =Assumptions!B70+IF(E41>Assumptions!B72,45,0) -> 76 | M41: =Assumptions!B76+Assumptions!B77 -> 35 | N41: =Assumptions!B81+Assumptions!B82+Assumptions!B87/12+Assumptions!B84 -> 92 | O41: =ROUND(I41*Assumptions!B85+E41*Assumptions!B86+W41*Assumptions!B85+ROUND(B41*Assumptions!B137*Assumptions!B138*Assumptions!B139,0)*Assumptions!B86,0) -> 620 | P41: =K41+L41+M41+N41+O41+X41 -> 1386 | Q41: =I41-P41 -> 7932 | R41: =ROUND(B41*Assumptions!B51*Assumptions!B52,0) -> 18362 | S41: =I41+R41+W41 -> 29726 | T41: =IF(U41<P41*3,0,IF(U41<P41*6,ROUND((Q41+R41+W41)*0.75*Assumptions!B113,0),ROUND((Q41+R41+W41)*0.75*Assumptions!B114,0))) -> 8119 | U41: =U40+Q41+R41+W41 -> 249148 | V41: =IF(B41>=Assumptions!B107,"Signal 6",IF(B41>=Assumptions!B106,"Signal 5",IF(B41>=Assumptions!B105,"Signal 4",IF(B41>=Assumptions!B104,"Signal 3",IF(B41>=Assumptions!B103,"Signal 2",IF(B41>=Assumptions!B102,"Signal 1","Pre-Signal 1")))))) -> Signal 3 | W41: =ROUND(B41*Assumptions!B137*Assumptions!B138*Assumptions!B139*Assumptions!B136,0) -> 2046 | X41: =ROUND(B41*Assumptions!B137*Assumptions!B65,0) -> 336
A43: TOTALS | I43: =SUM(I6:I41) -> 82970 | P43: =SUM(P6:P41) -> 18834 | Q43: =SUM(Q6:Q41) -> 64136 | R43: =SUM(R6:R41) -> 166268 | S43: =SUM(S6:S41) -> 267982 | T43: =SUM(T6:T41) -> 71425 | W43: =SUM(W6:W41) -> 18744 | X43: =SUM(X6:X41) -> 3079
A44: AVG MO | H44: =AVERAGE(H6:H41) -> 2304.7222 | Q44: =AVERAGE(Q6:Q41) -> 1781.5556
A45: M36 | B45: =B41 -> 52461.702 | E45: =E41 -> 812 | H45: =H41 -> 9318 | S45: =S41 -> 29726 | T45: =T41 -> 8119 | U45: =U41 -> 249148 | V45: =V41 -> Signal 3

Sheet Optimistic
A1: OPTIMISTIC SCENARIO — Optimistic Growth
A2: 0.50% paid conversion | 15% MoM traffic growth | 4% monthly churn | Referral: 0.1% of visitors x $350 blended
A3: Blue = hardcoded inputs | Black = calculated formulas | Green = Assumptions references
A5: Month | B5: Monthly Visitors | C5: Free Signups (Email 2%) | D5: New Paid Subs | E5: Total Paid Subs | F5: Churn This Month | G5: Net New Subs | H5: MRR ($) | I5: Monthly Revenue ($) | J5: Letter Generations | K5: API Costs ($) | L5: Infrastructure ($) | M5: Content/SEO ($) | N5: n8n + Tools ($) | O5: Stripe Fees ($) | P5: Total Costs ($) | Q5: Gross Profit ($) | R5: Referral Revenue ($) | S5: Total Revenue ($) | T5: Owner's Draw ($) | U5: Reserve Balance ($) | V5: Traffic Signal | W5: Per-Case Revenue ($) | X5: Free Tier API Cost ($)
A6: 1 | B6: =Assumptions!B32 -> 1200 | C6: =ROUND(B6*Assumptions!B25,0) -> 24 | D6: =ROUND(B6*Assumptions!B24,0) -> 6 | E6: =D6 -> 6 | F6: =0 -> 0 | G6: =D6-F6 -> 6 | H6: =ROUND(E6*Assumptions!B14,0) -> 48 | I6: =H6 -> 48 | J6: =ROUND(E6*Assumptions!B68,0) -> 21 | K6: =ROUND(J6*Assumptions!B65,0) -> 2 | L6: =Assumptions!B70+IF(E6>Assumptions!B72,45,0) -> 31 | M6: =Assumptions!B94+Assumptions!B95+Assumptions!B76+Assumptions!B77 -> 2785 | N6: =Assumptions!B81+Assumptions!B82+Assumptions!B87/12 -> 50 | O6: =ROUND(I6*Assumptions!B85+E6*Assumptions!B86+W6*Assumptions!B85+ROUND(B6*Assumptions!B137*Assumptions!B138*Assumptions!B139,0)*Assumptions!B86,0) -> 6 | P6: =K6+L6+M6+N6+O6+X6 -> 2882 | Q6: =I6-P6 -> -2834 | R6: =0 -> 0 | S6: =I6+R6+W6 -> 95 | T6: =IF(U6<P6*3,0,IF(U6<P6*6,ROUND((Q6+R6+W6)*0.75*Assumptions!B113,0),ROUND((Q6+R6+W6)*0.75*Assumptions!B114,0))) -> 0 | U6: =Q6+R6+W6 -> -2787 | V6: =IF(B6>=Assumptions!B107,"Signal 6",IF(B6>=Assumptions!B106,"Signal 5",IF(B6>=Assumptions!B105,"Signal 4",IF(B6>=Assumptions!B104,"Signal 3",IF(B6>=Assumptions!B103,"Signal 2",IF(B6>=Assumptions!B102,"Signal 1","Pre-Signal 1")))))) -> Pre-Signal 1 | W6: =ROUND(B6*Assumptions!B137*Assumptions!B138*Assumptions!B139*Assumptions!B136,0) -> 47 | X6: =ROUND(B6*Assumptions!B137*Assumptions!B65,0) -> 8
A7: 2 | B7: =B6*(1+Assumptions!B35) -> 1380 | C7: =ROUND(B7*Assumptions!B25,0) -> 28 | D7: =ROUND(B7*Assumptions!B24,0) -> 7 | E7: =E6+D7-F7 -> 13 | F7: =ROUND(E6*Assumptions!B45,0) -> 0 | G7: =D7-F7 -> 7 | H7: =ROUND(E7*Assumptions!B14,0) -> 104 | I7: =H7 -> 104 | J7: =ROUND(E7*Assumptions!B68,0) -> 46 | K7: =ROUND(J7*Assumptions!B65,0) -> 4 | L7: =Assumptions!B70+IF(E7>Assumptions!B72,45,0) -> 31 | M7: =Assumptions!B76+Assumptions!B77 -> 35 | N7: =Assumptions!B81+Assumptions!B82+Assumptions!B87/12 -> 50 | O7: =ROUND(I7*Assumptions!B85+E7*Assumptions!B86+W7*Assumptions!B85+ROUND(B7*Assumptions!B137*Assumptions!B138*Assumptions!B139,0)*Assumptions!B86,0) -> 10 | P7: =K7+L7+M7+N7+O7+X7 -> 139 | Q7: =I7-P7 -> -35 | R7: =0 -> 0 | S7: =I7+R7+W7 -> 158 | T7: =IF(U7<P7*3,0,IF(U7<P7*6,ROUND((Q7+R7+W7)*0.75*Assumptions!B113,0),ROUND((Q7+R7+W7)*0.75*Assumptions!B114,0))) -> 0 | U7: =U6+Q7+R7+W7 -> -2768 | V7: =IF(B7>=Assumptions!B107,"Signal 6",IF(B7>=Assumptions!B106,"Signal 5",IF(B7>=Assumptions!B105,"Signal 4",IF(B7>=Assumptions!B104,"Signal 3",IF(B7>=Assumptions!B103,"Signal 2",IF(B7>=Assumptions!B102,"Signal 1","Pre-Signal 1")))))) -> Pre-Signal 1 | W7: =ROUND(B7*Assumptions!B137*Assumptions!B138*Assumptions!B139*Assumptions!B136,0) -> 54 | X7: =ROUND(B7*Assumptions!B137*Assumptions!B65,0) -> 9
A8: 3 | B8: =B7*(1+Assumptions!B35)*Assumptions!B36 -> 1825.05 | C8: =ROUND(B8*Assumptions!B25,0) -> 37 | D8: =ROUND(B8*Assumptions!B24,0) -> 9 | E8: =E7+D8-F8 -> 21 | F8: =ROUND(E7*Assumptions!B45,0) -> 1 | G8: =D8-F8 -> 8 | H8: =ROUND(E8*Assumptions!B14,0) -> 168 | I8: =H8 -> 168 | J8: =ROUND(E8*Assumptions!B68,0) -> 74 | K8: =ROUND(J8*Assumptions!B65,0) -> 6 | L8: =Assumptions!B70+IF(E8>Assumptions!B72,45,0) -> 31 | M8: =Assumptions!B76+Assumptions!B77 -> 35 | N8: =Assumptions!B81+Assumptions!B82+Assumptions!B87/12 -> 50 | O8: =ROUND(I8*Assumptions!B85+E8*Assumptions!B86+W8*Assumptions!B85+ROUND(B8*Assumptions!B137*Assumptions!B138*Assumptions!B139,0)*Assumptions!B86,0) -> 15 | P8: =K8+L8+M8+N8+O8+X8 -> 149 | Q8: =I8-P8 -> 19 | R8: =0 -> 0 | S8: =I8+R8+W8 -> 239 | T8: =IF(U8<P8*3,0,IF(U8<P8*6,ROUND((Q8+R8+W8)*0.75*Assumptions!B113,0),ROUND((Q8+R8+W8)*0.75*Assumptions!B114,0))) -> 0 | U8: =U7+Q8+R8+W8 -> -2678 | V8: =IF(B8>=Assumptions!B107,"Signal 6",IF(B8>=Assumptions!B106,"Signal 5",IF(B8>=Assumptions!B105,"Signal 4",IF(B8>=Assumptions!B104,"Signal 3",IF(B8>=Assumptions!B103,"Signal 2",IF(B8>=Assumptions!B102,"Signal 1","Pre-Signal 1")))))) -> Pre-Signal 1 | W8: =ROUND(B8*Assumptions!B137*Assumptions!B138*Assumptions!B139*Assumptions!B136,0) -> 71 | X8: =ROUND(B8*Assumptions!B137*Assumptions!B65,0) -> 12
A9: 4 | B9: =B8*(1+Assumptions!B35) -> 2098.8075 | C9: =ROUND(B9*Assumptions!B25,0) -> 42 | D9: =ROUND(B9*Assumptions!B24,0) -> 10 | E9: =E8+D9-F9 -> 30 | F9: =ROUND(E8*Assumptions!B45,0) -> 1 | G9: =D9-F9 -> 9 | H9: =ROUND(E9*Assumptions!B14,0) -> 240 | I9: =H9 -> 240 | J9: =ROUND(E9*Assumptions!B68,0) -> 105 | K9: =ROUND(J9*Assumptions!B65,0) -> 8 | L9: =Assumptions!B70+IF(E9>Assumptions!B72,45,0) -> 31 | M9: =Assumptions!B76+Assumptions!B77 -> 35 | N9: =Assumptions!B81+Assumptions!B82+Assumptions!B87/12 -> 50 | O9: =ROUND(I9*Assumptions!B85+E9*Assumptions!B86+W9*Assumptions!B85+ROUND(B9*Assumptions!B137*Assumptions!B138*Assumptions!B139,0)*Assumptions!B86,0) -> 20 | P9: =K9+L9+M9+N9+O9+X9 -> 157 | Q9: =I9-P9 -> 83 | R9: =0 -> 0 | S9: =I9+R9+W9 -> 322 | T9: =IF(U9<P9*3,0,IF(U9<P9*6,ROUND((Q9+R9+W9)*0.75*Assumptions!B113,0),ROUND((Q9+R9+W9)*0.75*Assumptions!B114,0))) -> 0 | U9: =U8+Q9+R9+W9 -> -2513 | V9: =IF(B9>=Assumptions!B107,"Signal 6",IF(B9>=Assumptions!B106,"Signal 5",IF(B9>=Assumptions!B105,"Signal 4",IF(B9>=Assumptions!B104,"Signal 3",IF(B9>=Assumptions!B103,"Signal 2",IF(B9>=Assumptions!B102,"Signal 1","Pre-Signal 1")))))) -> Pre-Signal 1 | W9: =ROUND(B9*Assumptions!B137*Assumptions!B138*Assumptions!B139*Assumptions!B136,0) -> 82 | X9: =ROUND(B9*Assumptions!B137*Assumptions!B65,0) -> 13
A10: 5 | B10: =B9*(1+Assumptions!B35) -> 2413.6286 | C10: =ROUND(B10*Assumptions!B25,0) -> 48 | D10: =ROUND(B10*Assumptions!B24,0) -> 12 | E10: =E9+D10-F10 -> 41 | F10: =ROUND(E9*Assumptions!B45,0) -> 1 | G10: =D10-F10 -> 11 | H10: =ROUND(E10*Assumptions!B14,0) -> 328 | I10: =H10 -> 328 | J10: =ROUND(E10*Assumptions!B68,0) -> 144 | K10: =ROUND(J10*Assumptions!B65,0) -> 12 | L10: =Assumptions!B70+IF(E10>Assumptions!B72,45,0) -> 31 | M10: =Assumptions!B76+Assumptions!B77 -> 35 | N10: =Assumptions!B81+Assumptions!B82+Assumptions!B87/12 -> 50 | O10: =ROUND(I10*Assumptions!B85+E10*Assumptions!B86+W10*Assumptions!B85+ROUND(B10*Assumptions!B137*Assumptions!B138*Assumptions!B139,0)*Assumptions!B86,0) -> 27 | P10: =K10+L10+M10+N10+O10+X10 -> 170 | Q10: =I10-P10 -> 158 | R10: =0 -> 0 | S10: =I10+R10+W10 -> 422 | T10: =IF(U10<P10*3,0,IF(U10<P10*6,ROUND((Q10+R10+W10)*0.75*Assumptions!B113,0),ROUND((Q10+R10+W10)*0.75*Assumptions!B114,0))) -> 0 | U10: =U9+Q10+R10+W10 -> -2261 | V10: =IF(B10>=Assumptions!B107,"Signal 6",IF(B10>=Assumptions!B106,"Signal 5",IF(B10>=Assumptions!B105,"Signal 4",IF(B10>=Assumptions!B104,"Signal 3",IF(B10>=Assumptions!B103,"Signal 2",IF(B10>=Assumptions!B102,"Signal 1","Pre-Signal 1")))))) -> Pre-Signal 1 | W10: =ROUND(B10*Assumptions!B137*Assumptions!B138*Assumptions!B139*Assumptions!B136,0) -> 94 | X10: =ROUND(B10*Assumptions!B137*Assumptions!B65,0) -> 15
A11: 6 | B11: =B10*(1+Assumptions!B35)*Assumptions!B37 -> 2997.7268 | C11: =ROUND(B11*Assumptions!B25,0) -> 60 | D11: =ROUND(B11*Assumptions!B24,0) -> 15 | E11: =E10+D11-F11 -> 54 | F11: =ROUND(E10*Assumptions!B45,0) -> 2 | G11: =D11-F11 -> 13 | H11: =ROUND(E11*Assumptions!B14,0) -> 432 | I11: =H11 -> 432 | J11: =ROUND(E11*Assumptions!B68,0) -> 189 | K11: =ROUND(J11*Assumptions!B65,0) -> 15 | L11: =Assumptions!B70+IF(E11>Assumptions!B72,45,0) -> 31 | M11: =Assumptions!B76+Assumptions!B77 -> 35 | N11: =Assumptions!B81+Assumptions!B82+Assumptions!B87/12 -> 50 | O11: =ROUND(I11*Assumptions!B85+E11*Assumptions!B86+W11*Assumptions!B85+ROUND(B11*Assumptions!B137*Assumptions!B138*Assumptions!B139,0)*Assumptions!B86,0) -> 35 | P11: =K11+L11+M11+N11+O11+X11 -> 185 | Q11: =I11-P11 -> 247 | R11: =ROUND(B11*Assumptions!B51*Assumptions!B52,0) -> 1049 | S11: =I11+R11+W11 -> 1598 | T11: =IF(U11<P11*3,0,IF(U11<P11*6,ROUND((Q11+R11+W11)*0.75*Assumptions!B113,0),ROUND((Q11+R11+W11)*0.75*Assumptions!B114,0))) -> 0 | U11: =U10+Q11+R11+W11 -> -848 | V11: =IF(B11>=Assumptions!B107,"Signal 6",IF(B11>=Assumptions!B106,"Signal 5",IF(B11>=Assumptions!B105,"Signal 4",IF(B11>=Assumptions!B104,"Signal 3",IF(B11>=Assumptions!B103,"Signal 2",IF(B11>=Assumptions!B102,"Signal 1","Pre-Signal 1")))))) -> Pre-Signal 1 | W11: =ROUND(B11*Assumptions!B137*Assumptions!B138*Assumptions!B139*Assumptions!B136,0) -> 117 | X11: =ROUND(B11*Assumptions!B137*Assumptions!B65,0) -> 19
A12: 7 | B12: =B11*(1+Assumptions!B35) -> 3447.3858 | C12: =ROUND(B12*Assumptions!B25,0) -> 69 | D12: =ROUND(B12*Assumptions!B24,0) -> 17 | E12: =E11+D12-F12 -> 69 | F12: =ROUND(E11*Assumptions!B45,0) -> 2 | G12: =D12-F12 -> 15 | H12: =ROUND(E12*Assumptions!B14,0) -> 552 | I12: =H12 -> 552 | J12: =ROUND(E12*Assumptions!B68,0) -> 242 | K12: =ROUND(J12*Assumptions!B65,0) -> 19 | L12: =Assumptions!B70+IF(E12>Assumptions!B72,45,0) -> 31 | M12: =Assumptions!B76+Assumptions!B77 -> 35 | N12: =Assumptions!B81+Assumptions!B82+Assumptions!B87/12 -> 50 | O12: =ROUND(I12*Assumptions!B85+E12*Assumptions!B86+W12*Assumptions!B85+ROUND(B12*Assumptions!B137*Assumptions!B138*Assumptions!B139,0)*Assumptions!B86,0) -> 44 | P12: =K12+L12+M12+N12+O12+X12 -> 201 | Q12: =I12-P12 -> 351 | R12: =ROUND(B12*Assumptions!B51*Assumptions!B52,0) -> 1207 | S12: =I12+R12+W12 -> 1893 | T12: =IF(U12<P12*3,0,IF(U12<P12*6,ROUND((Q12+R12+W12)*0.75*Assumptions!B113,0),ROUND((Q12+R12+W12)*0.75*Assumptions!B114,0))) -> 299 | U12: =U11+Q12+R12+W12 -> 844 | V12: =IF(B12>=Assumptions!B107,"Signal 6",IF(B12>=Assumptions!B106,"Signal 5",IF(B12>=Assumptions!B105,"Signal 4",IF(B12>=Assumptions!B104,"Signal 3",IF(B12>=Assumptions!B103,"Signal 2",IF(B12>=Assumptions!B102,"Signal 1","Pre-Signal 1")))))) -> Pre-Signal 1 | W12: =ROUND(B12*Assumptions!B137*Assumptions!B138*Assumptions!B139*Assumptions!B136,0) -> 134 | X12: =ROUND(B12*Assumptions!B137*Assumptions!B65,0) -> 22
A13: 8 | B13: =B12*(1+Assumptions!B35) -> 3964.4936 | C13: =ROUND(B13*Assumptions!B25,0) -> 79 | D13: =ROUND(B13*Assumptions!B24,0) -> 20 | E13: =E12+D13-F13 -> 86 | F13: =ROUND(E12*Assumptions!B45,0) -> 3 | G13: =D13-F13 -> 17 | H13: =ROUND(E13*Assumptions!B14,0) -> 688 | I13: =H13 -> 688 | J13: =ROUND(E13*Assumptions!B68,0) -> 301 | K13: =ROUND(J13*Assumptions!B65,0) -> 24 | L13: =Assumptions!B70+IF(E13>Assumptions!B72,45,0) -> 31 | M13: =Assumptions!B76+Assumptions!B77 -> 35 | N13: =Assumptions!B81+Assumptions!B82+Assumptions!B87/12 -> 50 | O13: =ROUND(I13*Assumptions!B85+E13*Assumptions!B86+W13*Assumptions!B85+ROUND(B13*Assumptions!B137*Assumptions!B138*Assumptions!B139,0)*Assumptions!B86,0) -> 54 | P13: =K13+L13+M13+N13+O13+X13 -> 219 | Q13: =I13-P13 -> 469 | R13: =ROUND(B13*Assumptions!B51*Assumptions!B52,0) -> 1388 | S13: =I13+R13+W13 -> 2231 | T13: =IF(U13<P13*3,0,IF(U13<P13*6,ROUND((Q13+R13+W13)*0.75*Assumptions!B113,0),ROUND((Q13+R13+W13)*0.75*Assumptions!B114,0))) -> 576 | U13: =U12+Q13+R13+W13 -> 2856 | V13: =IF(B13>=Assumptions!B107,"Signal 6",IF(B13>=Assumptions!B106,"Signal 5",IF(B13>=Assumptions!B105,"Signal 4",IF(B13>=Assumptions!B104,"Signal 3",IF(B13>=Assumptions!B103,"Signal 2",IF(B13>=Assumptions!B102,"Signal 1","Pre-Signal 1")))))) -> Pre-Signal 1 | W13: =ROUND(B13*Assumptions!B137*Assumptions!B138*Assumptions!B139*Assumptions!B136,0) -> 155 | X13: =ROUND(B13*Assumptions!B137*Assumptions!B65,0) -> 25
A14: 9 | B14: =B13*(1+Assumptions!B35) -> 4559.1677 | C14: =ROUND(B14*Assumptions!B25,0) -> 91 | D14: =ROUND(B14*Assumptions!B24,0) -> 23 | E14: =E13+D14-F14 -> 106 | F14: =ROUND(E13*Assumptions!B45,0) -> 3 | G14: =D14-F14 -> 20 | H14: =ROUND(E14*((Assumptions!B14+Assumptions!B15)/2),0) -> 1113 | I14: =H14 -> 1113 | J14: =ROUND(E14*Assumptions!B68,0) -> 371 | K14: =ROUND(J14*Assumptions!B65,0) -> 30 | L14: =Assumptions!B70+IF(E14>Assumptions!B72,45,0) -> 31 | M14: =Assumptions!B76+Assumptions!B77 -> 35 | N14: =Assumptions!B81+Assumptions!B82+Assumptions!B87/12 -> 50 | O14: =ROUND(I14*Assumptions!B85+E14*Assumptions!B86+W14*Assumptions!B85+ROUND(B14*Assumptions!B137*Assumptions!B138*Assumptions!B139,0)*Assumptions!B86,0) -> 73 | P14: =K14+L14+M14+N14+O14+X14 -> 248 | Q14: =I14-P14 -> 865 | R14: =ROUND(B14*Assumptions!B51*Assumptions!B52,0) -> 1596 | S14: =I14+R14+W14 -> 2887 | T14: =IF(U14<P14*3,0,IF(U14<P14*6,ROUND((Q14+R14+W14)*0.75*Assumptions!B113,0),ROUND((Q14+R14+W14)*0.75*Assumptions!B114,0))) -> 756 | U14: =U13+Q14+R14+W14 -> 5495 | V14: =IF(B14>=Assumptions!B107,"Signal 6",IF(B14>=Assumptions!B106,"Signal 5",IF(B14>=Assumptions!B105,"Signal 4",IF(B14>=Assumptions!B104,"Signal 3",IF(B14>=Assumptions!B103,"Signal 2",IF(B14>=Assumptions!B102,"Signal 1","Pre-Signal 1")))))) -> Pre-Signal 1 | W14: =ROUND(B14*Assumptions!B137*Assumptions!B138*Assumptions!B139*Assumptions!B136,0) -> 178 | X14: =ROUND(B14*Assumptions!B137*Assumptions!B65,0) -> 29
A15: 10 | B15: =B14*(1+Assumptions!B35) -> 5243.0428 | C15: =ROUND(B15*Assumptions!B25,0) -> 105 | D15: =ROUND(B15*Assumptions!B24,0) -> 26 | E15: =E14+D15-F15 -> 128 | F15: =ROUND(E14*Assumptions!B45,0) -> 4 | G15: =D15-F15 -> 22 | H15: =ROUND(E15*(Assumptions!B15*0.85+Assumptions!B11*0.15),0) -> 1469 | I15: =H15 -> 1469 | J15: =ROUND(E15*Assumptions!B68,0) -> 448 | K15: =ROUND(J15*Assumptions!B65,0) -> 36 | L15: =Assumptions!B70+IF(E15>Assumptions!B72,45,0) -> 31 | M15: =Assumptions!B76+Assumptions!B77 -> 35 | N15: =Assumptions!B81+Assumptions!B82+Assumptions!B87/12 -> 50 | O15: =ROUND(I15*Assumptions!B85+E15*Assumptions!B86+W15*Assumptions!B85+ROUND(B15*Assumptions!B137*Assumptions!B138*Assumptions!B139,0)*Assumptions!B86,0) -> 92 | P15: =K15+L15+M15+N15+O15+X15 -> 278 | Q15: =I15-P15 -> 1191 | R15: =ROUND(B15*Assumptions!B51*Assumptions!B52,0) -> 1835 | S15: =I15+R15+W15 -> 3508 | T15: =IF(U15<P15*3,0,IF(U15<P15*6,ROUND((Q15+R15+W15)*0.75*Assumptions!B113,0),ROUND((Q15+R15+W15)*0.75*Assumptions!B114,0))) -> 925 | U15: =U14+Q15+R15+W15 -> 8725 | V15: =IF(B15>=Assumptions!B107,"Signal 6",IF(B15>=Assumptions!B106,"Signal 5",IF(B15>=Assumptions!B105,"Signal 4",IF(B15>=Assumptions!B104,"Signal 3",IF(B15>=Assumptions!B103,"Signal 2",IF(B15>=Assumptions!B102,"Signal 1","Pre-Signal 1")))))) -> Pre-Signal 1 | W15: =ROUND(B15*Assumptions!B137*Assumptions!B138*Assumptions!B139*Assumptions!B136,0) -> 204 | X15: =ROUND(B15*Assumptions!B137*Assumptions!B65,0) -> 34
A16: 11 | B16: =B15*(1+Assumptions!B35) -> 6029.4992 | C16: =ROUND(B16*Assumptions!B25,0) -> 121 | D16: =ROUND(B16*Assumptions!B24,0) -> 30 | E16: =E15+D16-F16 -> 153 | F16: =ROUND(E15*Assumptions!B45,0) -> 5 | G16: =D16-F16 -> 25 | H16: =ROUND(E16*(Assumptions!B15*0.85+Assumptions!B11*0.15),0) -> 1756 | I16: =H16 -> 1756 | J16: =ROUND(E16*Assumptions!B68,0) -> 536 | K16: =ROUND(J16*Assumptions!B65,0) -> 43 | L16: =Assumptions!B70+IF(E16>Assumptions!B72,45,0) -> 31 | M16: =Assumptions!B76+Assumptions!B77 -> 35 | N16: =Assumptions!B81+Assumptions!B82+Assumptions!B87/12 -> 50 | O16: =ROUND(I16*Assumptions!B85+E16*Assumptions!B86+W16*Assumptions!B85+ROUND(B16*Assumptions!B137*Assumptions!B138*Assumptions!B139,0)*Assumptions!B86,0) -> 109 | P16: =K16+L16+M16+N16+O16+X16 -> 307 | Q16: =I16-P16 -> 1449 | R16: =ROUND(B16*Assumptions!B51*Assumptions!B52,0) -> 2110 | S16: =I16+R16+W16 -> 4101 | T16: =IF(U16<P16*3,0,IF(U16<P16*6,ROUND((Q16+R16+W16)*0.75*Assumptions!B113,0),ROUND((Q16+R16+W16)*0.75*Assumptions!B114,0))) -> 1087 | U16: =U15+Q16+R16+W16 -> 12519 | V16: =IF(B16>=Assumptions!B107,"Signal 6",IF(B16>=Assumptions!B106,"Signal 5",IF(B16>=Assumptions!B105,"Signal 4",IF(B16>=Assumptions!B104,"Signal 3",IF(B16>=Assumptions!B103,"Signal 2",IF(B16>=Assumptions!B102,"Signal 1","Pre-Signal 1")))))) -> Pre-Signal 1 | W16: =ROUND(B16*Assumptions!B137*Assumptions!B138*Assumptions!B139*Assumptions!B136,0) -> 235 | X16: =ROUND(B16*Assumptions!B137*Assumptions!B65,0) -> 39
A17: 12 | B17: =B16*(1+Assumptions!B35) -> 6933.9241 | C17: =ROUND(B17*Assumptions!B25,0) -> 139 | D17: =ROUND(B17*Assumptions!B24,0) -> 35 | E17: =E16+D17-F17 -> 182 | F17: =ROUND(E16*Assumptions!B45,0) -> 6 | G17: =D17-F17 -> 29 | H17: =ROUND(E17*(Assumptions!B15*0.85+Assumptions!B11*0.15),0) -> 2088 | I17: =H17 -> 2088 | J17: =ROUND(E17*Assumptions!B68,0) -> 637 | K17: =ROUND(J17*Assumptions!B65,0) -> 51 | L17: =Assumptions!B70+IF(E17>Assumptions!B72,45,0) -> 31 | M17: =Assumptions!B76+Assumptions!B77 -> 35 | N17: =Assumptions!B81+Assumptions!B82+Assumptions!B87/12 -> 50 | O17: =ROUND(I17*Assumptions!B85+E17*Assumptions!B86+W17*Assumptions!B85+ROUND(B17*Assumptions!B137*Assumptions!B138*Assumptions!B139,0)*Assumptions!B86,0) -> 129 | P17: =K17+L17+M17+N17+O17+X17 -> 340 | Q17: =I17-P17 -> 1748 | R17: =ROUND(B17*Assumptions!B51*Assumptions!B52,0) -> 2427 | S17: =I17+R17+W17 -> 4785 | T17: =IF(U17<P17*3,0,IF(U17<P17*6,ROUND((Q17+R17+W17)*0.75*Assumptions!B113,0),ROUND((Q17+R17+W17)*0.75*Assumptions!B114,0))) -> 1273 | U17: =U16+Q17+R17+W17 -> 16964 | V17: =IF(B17>=Assumptions!B107,"Signal 6",IF(B17>=Assumptions!B106,"Signal 5",IF(B17>=Assumptions!B105,"Signal 4",IF(B17>=Assumptions!B104,"Signal 3",IF(B17>=Assumptions!B103,"Signal 2",IF(B17>=Assumptions!B102,"Signal 1","Pre-Signal 1")))))) -> Pre-Signal 1 | W17: =ROUND(B17*Assumptions!B137*Assumptions!B138*Assumptions!B139*Assumptions!B136,0) -> 270 | X17: =ROUND(B17*Assumptions!B137*Assumptions!B65,0) -> 44
A18: 13 | B18: =B17*(1+Assumptions!B35) -> 7974.0128 | C18: =ROUND(B18*Assumptions!B25,0) -> 159 | D18: =ROUND(B18*Assumptions!B24,0) -> 40 | E18: =E17+D18-F18 -> 215 | F18: =ROUND(E17*Assumptions!B45,0) -> 7 | G18: =D18-F18 -> 33 | H18: =ROUND(E18*(Assumptions!B15*0.85+Assumptions!B11*0.15),0) -> 2467 | I18: =H18 -> 2467 | J18: =ROUND(E18*Assumptions!B68,0) -> 753 | K18: =ROUND(J18*Assumptions!B65,0) -> 60 | L18: =Assumptions!B70+IF(E18>Assumptions!B72,45,0) -> 31 | M18: =Assumptions!B76+Assumptions!B77 -> 35 | N18: =Assumptions!B81+Assumptions!B82+Assumptions!B87/12+Assumptions!B84 -> 92 | O18: =ROUND(I18*Assumptions!B85+E18*Assumptions!B86+W18*Assumptions!B85+ROUND(B18*Assumptions!B137*Assumptions!B138*Assumptions!B139,0)*Assumptions!B86,0) -> 152 | P18: =K18+L18+M18+N18+O18+X18 -> 421 | Q18: =I18-P18 -> 2046 | R18: =ROUND(B18*Assumptions!B51*Assumptions!B52,0) -> 2791 | S18: =I18+R18+W18 -> 5569 | T18: =IF(U18<P18*3,0,IF(U18<P18*6,ROUND((Q18+R18+W18)*0.75*Assumptions!B113,0),ROUND((Q18+R18+W18)*0.75*Assumptions!B114,0))) -> 1475 | U18: =U17+Q18+R18+W18 -> 22112 | V18: =IF(B18>=Assumptions!B107,"Signal 6",IF(B18>=Assumptions!B106,"Signal 5",IF(B18>=Assumptions!B105,"Signal 4",IF(B18>=Assumptions!B104,"Signal 3",IF(B18>=Assumptions!B103,"Signal 2",IF(B18>=Assumptions!B102,"Signal 1","Pre-Signal 1")))))) -> Pre-Signal 1 | W18: =ROUND(B18*Assumptions!B137*Assumptions!B138*Assumptions!B139*Assumptions!B136,0) -> 311 | X18: =ROUND(B18*Assumptions!B137*Assumptions!B65,0) -> 51
A19: 14 | B19: =B18*(1+Assumptions!B35) -> 9170.1147 | C19: =ROUND(B19*Assumptions!B25,0) -> 183 | D19: =ROUND(B19*Assumptions!B24,0) -> 46 | E19: =E18+D19-F19 -> 252 | F19: =ROUND(E18*Assumptions!B45,0) -> 9 | G19: =D19-F19 -> 37 | H19: =ROUND(E19*(Assumptions!B15*0.85+Assumptions!B11*0.15),0) -> 2892 | I19: =H19 -> 2892 | J19: =ROUND(E19*Assumptions!B68,0) -> 882 | K19: =ROUND(J19*Assumptions!B65,0) -> 71 | L19: =Assumptions!B70+IF(E19>Assumptions!B72,45,0) -> 31 | M19: =Assumptions!B76+Assumptions!B77 -> 35 | N19: =Assumptions!B81+Assumptions!B82+Assumptions!B87/12+Assumptions!B84 -> 92 | O19: =ROUND(I19*Assumptions!B85+E19*Assumptions!B86+W19*Assumptions!B85+ROUND(B19*Assumptions!B137*Assumptions!B138*Assumptions!B139,0)*Assumptions!B86,0) -> 178 | P19: =K19+L19+M19+N19+O19+X19 -> 466 | Q19: =I19-P19 -> 2426 | R19: =ROUND(B19*Assumptions!B51*Assumptions!B52,0) -> 3210 | S19: =I19+R19+W19 -> 6460 | T19: =IF(U19<P19*3,0,IF(U19<P19*6,ROUND((Q19+R19+W19)*0.75*Assumptions!B113,0),ROUND((Q19+R19+W19)*0.75*Assumptions!B114,0))) -> 1717 | U19: =U18+Q19+R19+W19 -> 28106 | V19: =IF(B19>=Assumptions!B107,"Signal 6",IF(B19>=Assumptions!B106,"Signal 5",IF(B19>=Assumptions!B105,"Signal 4",IF(B19>=Assumptions!B104,"Signal 3",IF(B19>=Assumptions!B103,"Signal 2",IF(B19>=Assumptions!B102,"Signal 1","Pre-Signal 1")))))) -> Pre-Signal 1 | W19: =ROUND(B19*Assumptions!B137*Assumptions!B138*Assumptions!B139*Assumptions!B136,0) -> 358 | X19: =ROUND(B19*Assumptions!B137*Assumptions!B65,0) -> 59
A20: 15 | B20: =B19*(1+Assumptions!B35) -> 10545.632 | C20: =ROUND(B20*Assumptions!B25,0) -> 211 | D20: =ROUND(B20*Assumptions!B24,0) -> 53 | E20: =E19+D20-F20 -> 295 | F20: =ROUND(E19*Assumptions!B45,0) -> 10 | G20: =D20-F20 -> 43 | H20: =ROUND(E20*(Assumptions!B15*0.85+Assumptions!B11*0.15),0) -> 3385 | I20: =H20 -> 3385 | J20: =ROUND(E20*Assumptions!B68,0) -> 1033 | K20: =ROUND(J20*Assumptions!B65,0) -> 83 | L20: =Assumptions!B70+IF(E20>Assumptions!B72,45,0) -> 31 | M20: =Assumptions!B76+Assumptions!B77 -> 35 | N20: =Assumptions!B81+Assumptions!B82+Assumptions!B87/12+Assumptions!B84 -> 92 | O20: =ROUND(I20*Assumptions!B85+E20*Assumptions!B86+W20*Assumptions!B85+ROUND(B20*Assumptions!B137*Assumptions!B138*Assumptions!B139,0)*Assumptions!B86,0) -> 208 | P20: =K20+L20+M20+N20+O20+X20 -> 516 | Q20: =I20-P20 -> 2869 | R20: =ROUND(B20*Assumptions!B51*Assumptions!B52,0) -> 3691 | S20: =I20+R20+W20 -> 7487 | T20: =IF(U20<P20*3,0,IF(U20<P20*6,ROUND((Q20+R20+W20)*0.75*Assumptions!B113,0),ROUND((Q20+R20+W20)*0.75*Assumptions!B114,0))) -> 1997 | U20: =U19+Q20+R20+W20 -> 35077 | V20: =IF(B20>=Assumptions!B107,"Signal 6",IF(B20>=Assumptions!B106,"Signal 5",IF(B20>=Assumptions!B105,"Signal 4",IF(B20>=Assumptions!B104,"Signal 3",IF(B20>=Assumptions!B103,"Signal 2",IF(B20>=Assumptions!B102,"Signal 1","Pre-Signal 1")))))) -> Signal 1 | W20: =ROUND(B20*Assumptions!B137*Assumptions!B138*Assumptions!B139*Assumptions!B136,0) -> 411 | X20: =ROUND(B20*Assumptions!B137*Assumptions!B65,0) -> 67
A21: 16 | B21: =B20*(1+Assumptions!B35) -> 12127.477 | C21: =ROUND(B21*Assumptions!B25,0) -> 243 | D21: =ROUND(B21*Assumptions!B24,0) -> 61 | E21: =E20+D21-F21 -> 344 | F21: =ROUND(E20*Assumptions!B45,0) -> 12 | G21: =D21-F21 -> 49 | H21: =ROUND(E21*(Assumptions!B15*0.85+Assumptions!B11*0.15),0) -> 3947 | I21: =H21 -> 3947 | J21: =ROUND(E21*Assumptions!B68,0) -> 1204 | K21: =ROUND(J21*Assumptions!B65,0) -> 96 | L21: =Assumptions!B70+IF(E21>Assumptions!B72,45,0) -> 31 | M21: =Assumptions!B76+Assumptions!B77 -> 35 | N21: =Assumptions!B81+Assumptions!B82+Assumptions!B87/12+Assumptions!B84 -> 92 | O21: =ROUND(I21*Assumptions!B85+E21*Assumptions!B86+W21*Assumptions!B85+ROUND(B21*Assumptions!B137*Assumptions!B138*Assumptions!B139,0)*Assumptions!B86,0) -> 242 | P21: =K21+L21+M21+N21+O21+X21 -> 574 | Q21: =I21-P21 -> 3373 | R21: =ROUND(B21*Assumptions!B51*Assumptions!B52,0) -> 4245 | S21: =I21+R21+W21 -> 8665 | T21: =IF(U21<P21*3,0,IF(U21<P21*6,ROUND((Q21+R21+W21)*0.75*Assumptions!B113,0),ROUND((Q21+R21+W21)*0.75*Assumptions!B114,0))) -> 2318 | U21: =U20+Q21+R21+W21 -> 43168 | V21: =IF(B21>=Assumptions!B107,"Signal 6",IF(B21>=Assumptions!B106,"Signal 5",IF(B21>=Assumptions!B105,"Signal 4",IF(B21>=Assumptions!B104,"Signal 3",IF(B21>=Assumptions!B103,"Signal 2",IF(B21>=Assumptions!B102,"Signal 1","Pre-Signal 1")))))) -> Signal 1 | W21: =ROUND(B21*Assumptions!B137*Assumptions!B138*Assumptions!B139*Assumptions!B136,0) -> 473 | X21: =ROUND(B21*Assumptions!B137*Assumptions!B65,0) -> 78
A22: 17 | B22: =B21*(1+Assumptions!B35) -> 13946.598 | C22: =ROUND(B22*Assumptions!B25,0) -> 279 | D22: =ROUND(B22*Assumptions!B24,0) -> 70 | E22: =E21+D22-F22 -> 400 | F22: =ROUND(E21*Assumptions!B45,0) -> 14 | G22: =D22-F22 -> 56 | H22: =ROUND(E22*(Assumptions!B15*0.85+Assumptions!B11*0.15),0) -> 4590 | I22: =H22 -> 4590 | J22: =ROUND(E22*Assumptions!B68,0) -> 1400 | K22: =ROUND(J22*Assumptions!B65,0) -> 112 | L22: =Assumptions!B70+IF(E22>Assumptions!B72,45,0) -> 31 | M22: =Assumptions!B76+Assumptions!B77 -> 35 | N22: =Assumptions!B81+Assumptions!B82+Assumptions!B87/12+Assumptions!B84 -> 92 | O22: =ROUND(I22*Assumptions!B85+E22*Assumptions!B86+W22*Assumptions!B85+ROUND(B22*Assumptions!B137*Assumptions!B138*Assumptions!B139,0)*Assumptions!B86,0) -> 281 | P22: =K22+L22+M22+N22+O22+X22 -> 640 | Q22: =I22-P22 -> 3950 | R22: =ROUND(B22*Assumptions!B51*Assumptions!B52,0) -> 4881 | S22: =I22+R22+W22 -> 10015 | T22: =IF(U22<P22*3,0,IF(U22<P22*6,ROUND((Q22+R22+W22)*0.75*Assumptions!B113,0),ROUND((Q22+R22+W22)*0.75*Assumptions!B114,0))) -> 2686 | U22: =U21+Q22+R22+W22 -> 52543 | V22: =IF(B22>=Assumptions!B107,"Signal 6",IF(B22>=Assumptions!B106,"Signal 5",IF(B22>=Assumptions!B105,"Signal 4",IF(B22>=Assumptions!B104,"Signal 3",IF(B22>=Assumptions!B103,"Signal 2",IF(B22>=Assumptions!B102,"Signal 1","Pre-Signal 1")))))) -> Signal 1 | W22: =ROUND(B22*Assumptions!B137*Assumptions!B138*Assumptions!B139*Assumptions!B136,0) -> 544 | X22: =ROUND(B22*Assumptions!B137*Assumptions!B65,0) -> 89
A23: 18 | B23: =B22*(1+Assumptions!B35) -> 16038.588 | C23: =ROUND(B23*Assumptions!B25,0) -> 321 | D23: =ROUND(B23*Assumptions!B24,0) -> 80 | E23: =E22+D23-F23 -> 464 | F23: =ROUND(E22*Assumptions!B45,0) -> 16 | G23: =D23-F23 -> 64 | H23: =ROUND(E23*(Assumptions!B15*0.85+Assumptions!B11*0.15),0) -> 5324 | I23: =H23 -> 5324 | J23: =ROUND(E23*Assumptions!B68,0) -> 1624 | K23: =ROUND(J23*Assumptions!B65,0) -> 130 | L23: =Assumptions!B70+IF(E23>Assumptions!B72,45,0) -> 31 | M23: =Assumptions!B76+Assumptions!B77 -> 35 | N23: =Assumptions!B81+Assumptions!B82+Assumptions!B87/12+Assumptions!B84 -> 92 | O23: =ROUND(I23*Assumptions!B85+E23*Assumptions!B86+W23*Assumptions!B85+ROUND(B23*Assumptions!B137*Assumptions!B138*Assumptions!B139,0)*Assumptions!B86,0) -> 326 | P23: =K23+L23+M23+N23+O23+X23 -> 717 | Q23: =I23-P23 -> 4607 | R23: =ROUND(B23*Assumptions!B51*Assumptions!B52,0) -> 5614 | S23: =I23+R23+W23 -> 11564 | T23: =IF(U23<P23*3,0,IF(U23<P23*6,ROUND((Q23+R23+W23)*0.75*Assumptions!B113,0),ROUND((Q23+R23+W23)*0.75*Assumptions!B114,0))) -> 3108 | U23: =U22+Q23+R23+W23 -> 63390 | V23: =IF(B23>=Assumptions!B107,"Signal 6",IF(B23>=Assumptions!B106,"Signal 5",IF(B23>=Assumptions!B105,"Signal 4",IF(B23>=Assumptions!B104,"Signal 3",IF(B23>=Assumptions!B103,"Signal 2",IF(B23>=Assumptions!B102,"Signal 1","Pre-Signal 1")))))) -> Signal 1 | W23: =ROUND(B23*Assumptions!B137*Assumptions!B138*Assumptions!B139*Assumptions!B136,0) -> 626 | X23: =ROUND(B23*Assumptions!B137*Assumptions!B65,0) -> 103
A24: 19 | B24: =B23*(1+Assumptions!B35) -> 18444.376 | C24: =ROUND(B24*Assumptions!B25,0) -> 369 | D24: =ROUND(B24*Assumptions!B24,0) -> 92 | E24: =E23+D24-F24 -> 537 | F24: =ROUND(E23*Assumptions!B45,0) -> 19 | G24: =D24-F24 -> 73 | H24: =ROUND(E24*(Assumptions!B15*0.85+Assumptions!B11*0.15),0) -> 6162 | I24: =H24 -> 6162 | J24: =ROUND(E24*Assumptions!B68,0) -> 1880 | K24: =ROUND(J24*Assumptions!B65,0) -> 150 | L24: =Assumptions!B70+IF(E24>Assumptions!B72,45,0) -> 76 | M24: =Assumptions!B76+Assumptions!B77 -> 35 | N24: =Assumptions!B81+Assumptions!B82+Assumptions!B87/12+Assumptions!B84 -> 92 | O24: =ROUND(I24*Assumptions!B85+E24*Assumptions!B86+W24*Assumptions!B85+ROUND(B24*Assumptions!B137*Assumptions!B138*Assumptions!B139,0)*Assumptions!B86,0) -> 377 | P24: =K24+L24+M24+N24+O24+X24 -> 848 | Q24: =I24-P24 -> 5314 | R24: =ROUND(B24*Assumptions!B51*Assumptions!B52,0) -> 6456 | S24: =I24+R24+W24 -> 13337 | T24: =IF(U24<P24*3,0,IF(U24<P24*6,ROUND((Q24+R24+W24)*0.75*Assumptions!B113,0),ROUND((Q24+R24+W24)*0.75*Assumptions!B114,0))) -> 3578 | U24: =U23+Q24+R24+W24 -> 75879 | V24: =IF(B24>=Assumptions!B107,"Signal 6",IF(B24>=Assumptions!B106,"Signal 5",IF(B24>=Assumptions!B105,"Signal 4",IF(B24>=Assumptions!B104,"Signal 3",IF(B24>=Assumptions!B103,"Signal 2",IF(B24>=Assumptions!B102,"Signal 1","Pre-Signal 1")))))) -> Signal 1 | W24: =ROUND(B24*Assumptions!B137*Assumptions!B138*Assumptions!B139*Assumptions!B136,0) -> 719 | X24: =ROUND(B24*Assumptions!B137*Assumptions!B65,0) -> 118
A25: 20 | B25: =B24*(1+Assumptions!B35) -> 21211.032 | C25: =ROUND(B25*Assumptions!B25,0) -> 424 | D25: =ROUND(B25*Assumptions!B24,0) -> 106 | E25: =E24+D25-F25 -> 622 | F25: =ROUND(E24*Assumptions!B45,0) -> 21 | G25: =D25-F25 -> 85 | H25: =ROUND(E25*(Assumptions!B15*0.85+Assumptions!B11*0.15),0) -> 7137 | I25: =H25 -> 7137 | J25: =ROUND(E25*Assumptions!B68,0) -> 2177 | K25: =ROUND(J25*Assumptions!B65,0) -> 174 | L25: =Assumptions!B70+IF(E25>Assumptions!B72,45,0) -> 76 | M25: =Assumptions!B76+Assumptions!B77 -> 35 | N25: =Assumptions!B81+Assumptions!B82+Assumptions!B87/12+Assumptions!B84 -> 92 | O25: =ROUND(I25*Assumptions!B85+E25*Assumptions!B86+W25*Assumptions!B85+ROUND(B25*Assumptions!B137*Assumptions!B138*Assumptions!B139,0)*Assumptions!B86,0) -> 437 | P25: =K25+L25+M25+N25+O25+X25 -> 950 | Q25: =I25-P25 -> 6187 | R25: =ROUND(B25*Assumptions!B51*Assumptions!B52,0) -> 7424 | S25: =I25+R25+W25 -> 15388 | T25: =IF(U25<P25*3,0,IF(U25<P25*6,ROUND((Q25+R25+W25)*0.75*Assumptions!B113,0),ROUND((Q25+R25+W25)*0.75*Assumptions!B114,0))) -> 4136 | U25: =U24+Q25+R25+W25 -> 90317 | V25: =IF(B25>=Assumptions!B107,"Signal 6",IF(B25>=Assumptions!B106,"Signal 5",IF(B25>=Assumptions!B105,"Signal 4",IF(B25>=Assumptions!B104,"Signal 3",IF(B25>=Assumptions!B103,"Signal 2",IF(B25>=Assumptions!B102,"Signal 1","Pre-Signal 1")))))) -> Signal 1 | W25: =ROUND(B25*Assumptions!B137*Assumptions!B138*Assumptions!B139*Assumptions!B136,0) -> 827 | X25: =ROUND(B25*Assumptions!B137*Assumptions!B65,0) -> 136
A26: 21 | B26: =B25*(1+Assumptions!B35) -> 24392.687 | C26: =ROUND(B26*Assumptions!B25,0) -> 488 | D26: =ROUND(B26*Assumptions!B24,0) -> 122 | E26: =E25+D26-F26 -> 719 | F26: =ROUND(E25*Assumptions!B45,0) -> 25 | G26: =D26-F26 -> 97 | H26: =ROUND(E26*(Assumptions!B15*0.85+Assumptions!B11*0.15),0) -> 8251 | I26: =H26 -> 8251 | J26: =ROUND(E26*Assumptions!B68,0) -> 2517 | K26: =ROUND(J26*Assumptions!B65,0) -> 201 | L26: =Assumptions!B70+IF(E26>Assumptions!B72,45,0) -> 76 | M26: =Assumptions!B76+Assumptions!B77 -> 35 | N26: =Assumptions!B81+Assumptions!B82+Assumptions!B87/12+Assumptions!B84 -> 92 | O26: =ROUND(I26*Assumptions!B85+E26*Assumptions!B86+W26*Assumptions!B85+ROUND(B26*Assumptions!B137*Assumptions!B138*Assumptions!B139,0)*Assumptions!B86,0) -> 504 | P26: =K26+L26+M26+N26+O26+X26 -> 1064 | Q26: =I26-P26 -> 7187 | R26: =ROUND(B26*Assumptions!B51*Assumptions!B52,0) -> 8537 | S26: =I26+R26+W26 -> 17739 | T26: =IF(U26<P26*3,0,IF(U26<P26*6,ROUND((Q26+R26+W26)*0.75*Assumptions!B113,0),ROUND((Q26+R26+W26)*0.75*Assumptions!B114,0))) -> 4777 | U26: =U25+Q26+R26+W26 -> 106992 | V26: =IF(B26>=Assumptions!B107,"Signal 6",IF(B26>=Assumptions!B106,"Signal 5",IF(B26>=Assumptions!B105,"Signal 4",IF(B26>=Assumptions!B104,"Signal 3",IF(B26>=Assumptions!B103,"Signal 2",IF(B26>=Assumptions!B102,"Signal 1","Pre-Signal 1")))))) -> Signal 1 | W26: =ROUND(B26*Assumptions!B137*Assumptions!B138*Assumptions!B139*Assumptions!B136,0) -> 951 | X26: =ROUND(B26*Assumptions!B137*Assumptions!B65,0) -> 156
A27: 22 | B27: =B26*(1+Assumptions!B35) -> 28051.59 | C27: =ROUND(B27*Assumptions!B25,0) -> 561 | D27: =ROUND(B27*Assumptions!B24,0) -> 140 | E27: =E26+D27-F27 -> 830 | F27: =ROUND(E26*Assumptions!B45,0) -> 29 | G27: =D27-F27 -> 111 | H27: =ROUND(E27*(Assumptions!B15*0.85+Assumptions!B11*0.15),0) -> 9524 | I27: =H27 -> 9524 | J27: =ROUND(E27*Assumptions!B68,0) -> 2905 | K27: =ROUND(J27*Assumptions!B65,0) -> 232 | L27: =Assumptions!B70+IF(E27>Assumptions!B72,45,0) -> 76 | M27: =Assumptions!B76+Assumptions!B77 -> 35 | N27: =Assumptions!B81+Assumptions!B82+Assumptions!B87/12+Assumptions!B84 -> 92 | O27: =ROUND(I27*Assumptions!B85+E27*Assumptions!B86+W27*Assumptions!B85+ROUND(B27*Assumptions!B137*Assumptions!B138*Assumptions!B139,0)*Assumptions!B86,0) -> 582 | P27: =K27+L27+M27+N27+O27+X27 -> 1197 | Q27: =I27-P27 -> 8327 | R27: =ROUND(B27*Assumptions!B51*Assumptions!B52,0) -> 9818 | S27: =I27+R27+W27 -> 20436 | T27: =IF(U27<P27*3,0,IF(U27<P27*6,ROUND((Q27+R27+W27)*0.75*Assumptions!B113,0),ROUND((Q27+R27+W27)*0.75*Assumptions!B114,0))) -> 5512 | U27: =U26+Q27+R27+W27 -> 126231 | V27: =IF(B27>=Assumptions!B107,"Signal 6",IF(B27>=Assumptions!B106,"Signal 5",IF(B27>=Assumptions!B105,"Signal 4",IF(B27>=Assumptions!B104,"Signal 3",IF(B27>=Assumptions!B103,"Signal 2",IF(B27>=Assumptions!B102,"Signal 1","Pre-Signal 1")))))) -> Signal 2 | W27: =ROUND(B27*Assumptions!B137*Assumptions!B138*Assumptions!B139*Assumptions!B136,0) -> 1094 | X27: =ROUND(B27*Assumptions!B137*Assumptions!B65,0) -> 180
A28: 23 | B28: =B27*(1+Assumptions!B35) -> 32259.329 | C28: =ROUND(B28*Assumptions!B25,0) -> 645 | D28: =ROUND(B28*Assumptions!B24,0) -> 161 | E28: =E27+D28-F28 -> 958 | F28: =ROUND(E27*Assumptions!B45,0) -> 33 | G28: =D28-F28 -> 128 | H28: =ROUND(E28*(Assumptions!B15*0.85+Assumptions!B11*0.15),0) -> 10993 | I28: =H28 -> 10993 | J28: =ROUND(E28*Assumptions!B68,0) -> 3353 | K28: =ROUND(J28*Assumptions!B65,0) -> 268 | L28: =Assumptions!B70+IF(E28>Assumptions!B72,45,0) -> 76 | M28: =Assumptions!B76+Assumptions!B77 -> 35 | N28: =Assumptions!B81+Assumptions!B82+Assumptions!B87/12+Assumptions!B84 -> 92 | O28: =ROUND(I28*Assumptions!B85+E28*Assumptions!B86+W28*Assumptions!B85+ROUND(B28*Assumptions!B137*Assumptions!B138*Assumptions!B139,0)*Assumptions!B86,0) -> 672 | P28: =K28+L28+M28+N28+O28+X28 -> 1349 | Q28: =I28-P28 -> 9644 | R28: =ROUND(B28*Assumptions!B51*Assumptions!B52,0) -> 11291 | S28: =I28+R28+W28 -> 23542 | T28: =IF(U28<P28*3,0,IF(U28<P28*6,ROUND((Q28+R28+W28)*0.75*Assumptions!B113,0),ROUND((Q28+R28+W28)*0.75*Assumptions!B114,0))) -> 6358 | U28: =U27+Q28+R28+W28 -> 148424 | V28: =IF(B28>=Assumptions!B107,"Signal 6",IF(B28>=Assumptions!B106,"Signal 5",IF(B28>=Assumptions!B105,"Signal 4",IF(B28>=Assumptions!B104,"Signal 3",IF(B28>=Assumptions!B103,"Signal 2",IF(B28>=Assumptions!B102,"Signal 1","Pre-Signal 1")))))) -> Signal 2 | W28: =ROUND(B28*Assumptions!B137*Assumptions!B138*Assumptions!B139*Assumptions!B136,0) -> 1258 | X28: =ROUND(B28*Assumptions!B137*Assumptions!B65,0) -> 206
A29: 24 | B29: =B28*(1+Assumptions!B35) -> 37098.228 | C29: =ROUND(B29*Assumptions!B25,0) -> 742 | D29: =ROUND(B29*Assumptions!B24,0) -> 185 | E29: =E28+D29-F29 -> 1105 | F29: =ROUND(E28*Assumptions!B45,0) -> 38 | G29: =D29-F29 -> 147 | H29: =ROUND(E29*(Assumptions!B15*0.85+Assumptions!B11*0.15),0) -> 12680 | I29: =H29 -> 12680 | J29: =ROUND(E29*Assumptions!B68,0) -> 3868 | K29: =ROUND(J29*Assumptions!B65,0) -> 309 | L29: =Assumptions!B70+IF(E29>Assumptions!B72,45,0) -> 76 | M29: =Assumptions!B76+Assumptions!B77 -> 35 | N29: =Assumptions!B81+Assumptions!B82+Assumptions!B87/12+Assumptions!B84 -> 92 | O29: =ROUND(I29*Assumptions!B85+E29*Assumptions!B86+W29*Assumptions!B85+ROUND(B29*Assumptions!B137*Assumptions!B138*Assumptions!B139,0)*Assumptions!B86,0) -> 774 | P29: =K29+L29+M29+N29+O29+X29 -> 1523 | Q29: =I29-P29 -> 11157 | R29: =ROUND(B29*Assumptions!B51*Assumptions!B52,0) -> 12984 | S29: =I29+R29+W29 -> 27111 | T29: =IF(U29<P29*3,0,IF(U29<P29*6,ROUND((Q29+R29+W29)*0.75*Assumptions!B113,0),ROUND((Q29+R29+W29)*0.75*Assumptions!B114,0))) -> 7331 | U29: =U28+Q29+R29+W29 -> 174012 | V29: =IF(B29>=Assumptions!B107,"Signal 6",IF(B29>=Assumptions!B106,"Signal 5",IF(B29>=Assumptions!B105,"Signal 4",IF(B29>=Assumptions!B104,"Signal 3",IF(B29>=Assumptions!B103,"Signal 2",IF(B29>=Assumptions!B102,"Signal 1","Pre-Signal 1")))))) -> Signal 2 | W29: =ROUND(B29*Assumptions!B137*Assumptions!B138*Assumptions!B139*Assumptions!B136,0) -> 1447 | X29: =ROUND(B29*Assumptions!B137*Assumptions!B65,0) -> 237
A30: 25 | B30: =B29*(1+Assumptions!B35) -> 42662.963 | C30: =ROUND(B30*Assumptions!B25,0) -> 853 | D30: =ROUND(B30*Assumptions!B24,0) -> 213 | E30: =E29+D30-F30 -> 1274 | F30: =ROUND(E29*Assumptions!B45,0) -> 44 | G30: =D30-F30 -> 169 | H30: =ROUND(E30*(Assumptions!B15*0.85+Assumptions!B11*0.15),0) -> 14619 | I30: =H30 -> 14619 | J30: =ROUND(E30*Assumptions!B68,0) -> 4459 | K30: =ROUND(J30*Assumptions!B65,0) -> 357 | L30: =Assumptions!B70+IF(E30>Assumptions!B72,45,0) -> 76 | M30: =Assumptions!B76+Assumptions!B77 -> 35 | N30: =Assumptions!B81+Assumptions!B82+Assumptions!B87/12+Assumptions!B84 -> 92 | O30: =ROUND(I30*Assumptions!B85+E30*Assumptions!B86+W30*Assumptions!B85+ROUND(B30*Assumptions!B137*Assumptions!B138*Assumptions!B139,0)*Assumptions!B86,0) -> 893 | P30: =K30+L30+M30+N30+O30+X30 -> 1726 | Q30: =I30-P30 -> 12893 | R30: =ROUND(B30*Assumptions!B51*Assumptions!B52,0) -> 14932 | S30: =I30+R30+W30 -> 31215 | T30: =IF(U30<P30*3,0,IF(U30<P30*6,ROUND((Q30+R30+W30)*0.75*Assumptions!B113,0),ROUND((Q30+R30+W30)*0.75*Assumptions!B114,0))) -> 8449 | U30: =U29+Q30+R30+W30 -> 203501 | V30: =IF(B30>=Assumptions!B107,"Signal 6",IF(B30>=Assumptions!B106,"Signal 5",IF(B30>=Assumptions!B105,"Signal 4",IF(B30>=Assumptions!B104,"Signal 3",IF(B30>=Assumptions!B103,"Signal 2",IF(B30>=Assumptions!B102,"Signal 1","Pre-Signal 1")))))) -> Signal 3 | W30: =ROUND(B30*Assumptions!B137*Assumptions!B138*Assumptions!B139*Assumptions!B136,0) -> 1664 | X30: =ROUND(B30*Assumptions!B137*Assumptions!B65,0) -> 273
A31: 26 | B31: =B30*(1+Assumptions!B35) -> 49062.407 | C31: =ROUND(B31*Assumptions!B25,0) -> 981 | D31: =ROUND(B31*Assumptions!B24,0) -> 245 | E31: =E30+D31-F31 -> 1468 | F31: =ROUND(E30*Assumptions!B45,0) -> 51 | G31: =D31-F31 -> 194 | H31: =ROUND(E31*(Assumptions!B15*0.85+Assumptions!B11*0.15),0) -> 16845 | I31: =H31 -> 16845 | J31: =ROUND(E31*Assumptions!B68,0) -> 5138 | K31: =ROUND(J31*Assumptions!B65,0) -> 411 | L31: =Assumptions!B70+IF(E31>Assumptions!B72,45,0) -> 76 | M31: =Assumptions!B76+Assumptions!B77 -> 35 | N31: =Assumptions!B81+Assumptions!B82+Assumptions!B87/12+Assumptions!B84 -> 92 | O31: =ROUND(I31*Assumptions!B85+E31*Assumptions!B86+W31*Assumptions!B85+ROUND(B31*Assumptions!B137*Assumptions!B138*Assumptions!B139,0)*Assumptions!B86,0) -> 1028 | P31: =K31+L31+M31+N31+O31+X31 -> 1956 | Q31: =I31-P31 -> 14889 | R31: =ROUND(B31*Assumptions!B51*Assumptions!B52,0) -> 17172 | S31: =I31+R31+W31 -> 35930 | T31: =IF(U31<P31*3,0,IF(U31<P31*6,ROUND((Q31+R31+W31)*0.75*Assumptions!B113,0),ROUND((Q31+R31+W31)*0.75*Assumptions!B114,0))) -> 9734 | U31: =U30+Q31+R31+W31 -> 237475 | V31: =IF(B31>=Assumptions!B107,"Signal 6",IF(B31>=Assumptions!B106,"Signal 5",IF(B31>=Assumptions!B105,"Signal 4",IF(B31>=Assumptions!B104,"Signal 3",IF(B31>=Assumptions!B103,"Signal 2",IF(B31>=Assumptions!B102,"Signal 1","Pre-Signal 1")))))) -> Signal 3 | W31: =ROUND(B31*Assumptions!B137*Assumptions!B138*Assumptions!B139*Assumptions!B136,0) -> 1913 | X31: =ROUND(B31*Assumptions!B137*Assumptions!B65,0) -> 314
A32: 27 | B32: =B31*(1+Assumptions!B35) -> 56421.768 | C32: =ROUND(B32*Assumptions!B25,0) -> 1128 | D32: =ROUND(B32*Assumptions!B24,0) -> 282 | E32: =E31+D32-F32 -> 1691 | F32: =ROUND(E31*Assumptions!B45,0) -> 59 | G32: =D32-F32 -> 223 | H32: =ROUND(E32*(Assumptions!B15*0.85+Assumptions!B11*0.15),0) -> 19404 | I32: =H32 -> 19404 | J32: =ROUND(E32*Assumptions!B68,0) -> 5919 | K32: =ROUND(J32*Assumptions!B65,0) -> 474 | L32: =Assumptions!B70+IF(E32>Assumptions!B72,45,0) -> 76 | M32: =Assumptions!B76+Assumptions!B77 -> 35 | N32: =Assumptions!B81+Assumptions!B82+Assumptions!B87/12+Assumptions!B84 -> 92 | O32: =ROUND(I32*Assumptions!B85+E32*Assumptions!B86+W32*Assumptions!B85+ROUND(B32*Assumptions!B137*Assumptions!B138*Assumptions!B139,0)*Assumptions!B86,0) -> 1185 | P32: =K32+L32+M32+N32+O32+X32 -> 2223 | Q32: =I32-P32 -> 17181 | R32: =ROUND(B32*Assumptions!B51*Assumptions!B52,0) -> 19748 | S32: =I32+R32+W32 -> 41352 | T32: =IF(U32<P32*3,0,IF(U32<P32*6,ROUND((Q32+R32+W32)*0.75*Assumptions!B113,0),ROUND((Q32+R32+W32)*0.75*Assumptions!B114,0))) -> 11210 | U32: =U31+Q32+R32+W32 -> 276604 | V32: =IF(B32>=Assumptions!B107,"Signal 6",IF(B32>=Assumptions!B106,"Signal 5",IF(B32>=Assumptions!B105,"Signal 4",IF(B32>=Assumptions!B104,"Signal 3",IF(B32>=Assumptions!B103,"Signal 2",IF(B32>=Assumptions!B102,"Signal 1","Pre-Signal 1")))))) -> Signal 3 | W32: =ROUND(B32*Assumptions!B137*Assumptions!B138*Assumptions!B139*Assumptions!B136,0) -> 2200 | X32: =ROUND(B32*Assumptions!B137*Assumptions!B65,0) -> 361
A33: 28 | B33: =B32*(1+Assumptions!B35) -> 64885.033 | C33: =ROUND(B33*Assumptions!B25,0) -> 1298 | D33: =ROUND(B33*Assumptions!B24,0) -> 324 | E33: =E32+D33-F33 -> 1947 | F33: =ROUND(E32*Assumptions!B45,0) -> 68 | G33: =D33-F33 -> 256 | H33: =ROUND(E33*(Assumptions!B15*0.85+Assumptions!B11*0.15),0) -> 22342 | I33: =H33 -> 22342 | J33: =ROUND(E33*Assumptions!B68,0) -> 6815 | K33: =ROUND(J33*Assumptions!B65,0) -> 545 | L33: =Assumptions!B70+IF(E33>Assumptions!B72,45,0) -> 76 | M33: =Assumptions!B76+Assumptions!B77 -> 35 | N33: =Assumptions!B81+Assumptions!B82+Assumptions!B87/12+Assumptions!B84 -> 92 | O33: =ROUND(I33*Assumptions!B85+E33*Assumptions!B86+W33*Assumptions!B85+ROUND(B33*Assumptions!B137*Assumptions!B138*Assumptions!B139,0)*Assumptions!B86,0) -> 1364 | P33: =K33+L33+M33+N33+O33+X33 -> 2527 | Q33: =I33-P33 -> 19815 | R33: =ROUND(B33*Assumptions!B51*Assumptions!B52,0) -> 22710 | S33: =I33+R33+W33 -> 47583 | T33: =IF(U33<P33*3,0,IF(U33<P33*6,ROUND((Q33+R33+W33)*0.75*Assumptions!B113,0),ROUND((Q33+R33+W33)*0.75*Assumptions!B114,0))) -> 12909 | U33: =U32+Q33+R33+W33 -> 321660 | V33: =IF(B33>=Assumptions!B107,"Signal 6",IF(B33>=Assumptions!B106,"Signal 5",IF(B33>=Assumptions!B105,"Signal 4",IF(B33>=Assumptions!B104,"Signal 3",IF(B33>=Assumptions!B103,"Signal 2",IF(B33>=Assumptions!B102,"Signal 1","Pre-Signal 1")))))) -> Signal 3 | W33: =ROUND(B33*Assumptions!B137*Assumptions!B138*Assumptions!B139*Assumptions!B136,0) -> 2531 | X33: =ROUND(B33*Assumptions!B137*Assumptions!B65,0) -> 415
A34: 29 | B34: =B33*(1+Assumptions!B35) -> 74617.788 | C34: =ROUND(B34*Assumptions!B25,0) -> 1492 | D34: =ROUND(B34*Assumptions!B24,0) -> 373 | E34: =E33+D34-F34 -> 2242 | F34: =ROUND(E33*Assumptions!B45,0) -> 78 | G34: =D34-F34 -> 295 | H34: =ROUND(E34*(Assumptions!B15*0.85+Assumptions!B11*0.15),0) -> 25727 | I34: =H34 -> 25727 | J34: =ROUND(E34*Assumptions!B68,0) -> 7847 | K34: =ROUND(J34*Assumptions!B65,0) -> 628 | L34: =Assumptions!B70+IF(E34>Assumptions!B72,45,0) -> 76 | M34: =Assumptions!B76+Assumptions!B77 -> 35 | N34: =Assumptions!B81+Assumptions!B82+Assumptions!B87/12+Assumptions!B84 -> 92 | O34: =ROUND(I34*Assumptions!B85+E34*Assumptions!B86+W34*Assumptions!B85+ROUND(B34*Assumptions!B137*Assumptions!B138*Assumptions!B139,0)*Assumptions!B86,0) -> 1570 | P34: =K34+L34+M34+N34+O34+X34 -> 2879 | Q34: =I34-P34 -> 22848 | R34: =ROUND(B34*Assumptions!B51*Assumptions!B52,0) -> 26116 | S34: =I34+R34+W34 -> 54753 | T34: =IF(U34<P34*3,0,IF(U34<P34*6,ROUND((Q34+R34+W34)*0.75*Assumptions!B113,0),ROUND((Q34+R34+W34)*0.75*Assumptions!B114,0))) -> 14862 | U34: =U33+Q34+R34+W34 -> 373534 | V34: =IF(B34>=Assumptions!B107,"Signal 6",IF(B34>=Assumptions!B106,"Signal 5",IF(B34>=Assumptions!B105,"Signal 4",IF(B34>=Assumptions!B104,"Signal 3",IF(B34>=Assumptions!B103,"Signal 2",IF(B34>=Assumptions!B102,"Signal 1","Pre-Signal 1")))))) -> Signal 4 | W34: =ROUND(B34*Assumptions!B137*Assumptions!B138*Assumptions!B139*Assumptions!B136,0) -> 2910 | X34: =ROUND(B34*Assumptions!B137*Assumptions!B65,0) -> 478
A35: 30 | B35: =B34*(1+Assumptions!B35) -> 85810.456 | C35: =ROUND(B35*Assumptions!B25,0) -> 1716 | D35: =ROUND(B35*Assumptions!B24,0) -> 429 | E35: =E34+D35-F35 -> 2581 | F35: =ROUND(E34*Assumptions!B45,0) -> 90 | G35: =D35-F35 -> 339 | H35: =ROUND(E35*(Assumptions!B15*0.85+Assumptions!B11*0.15),0) -> 29617 | I35: =H35 -> 29617 | J35: =ROUND(E35*Assumptions!B68,0) -> 9034 | K35: =ROUND(J35*Assumptions!B65,0) -> 723 | L35: =Assumptions!B70+IF(E35>Assumptions!B72,45,0) -> 76 | M35: =Assumptions!B76+Assumptions!B77 -> 35 | N35: =Assumptions!B81+Assumptions!B82+Assumptions!B87/12+Assumptions!B84 -> 92 | O35: =ROUND(I35*Assumptions!B85+E35*Assumptions!B86+W35*Assumptions!B85+ROUND(B35*Assumptions!B137*Assumptions!B138*Assumptions!B139,0)*Assumptions!B86,0) -> 1807 | P35: =K35+L35+M35+N35+O35+X35 -> 3282 | Q35: =I35-P35 -> 26335 | R35: =ROUND(B35*Assumptions!B51*Assumptions!B52,0) -> 30034 | S35: =I35+R35+W35 -> 62998 | T35: =IF(U35<P35*3,0,IF(U35<P35*6,ROUND((Q35+R35+W35)*0.75*Assumptions!B113,0),ROUND((Q35+R35+W35)*0.75*Assumptions!B114,0))) -> 17109 | U35: =U34+Q35+R35+W35 -> 433250 | V35: =IF(B35>=Assumptions!B107,"Signal 6",IF(B35>=Assumptions!B106,"Signal 5",IF(B35>=Assumptions!B105,"Signal 4",IF(B35>=Assumptions!B104,"Signal 3",IF(B35>=Assumptions!B103,"Signal 2",IF(B35>=Assumptions!B102,"Signal 1","Pre-Signal 1")))))) -> Signal 4 | W35: =ROUND(B35*Assumptions!B137*Assumptions!B138*Assumptions!B139*Assumptions!B136,0) -> 3347 | X35: =ROUND(B35*Assumptions!B137*Assumptions!B65,0) -> 549
A36: 31 | B36: =B35*(1+Assumptions!B35) -> 98682.025 | C36: =ROUND(B36*Assumptions!B25,0) -> 1974 | D36: =ROUND(B36*Assumptions!B24,0) -> 493 | E36: =E35+D36-F36 -> 2971 | F36: =ROUND(E35*Assumptions!B45,0) -> 103 | G36: =D36-F36 -> 390 | H36: =ROUND(E36*(Assumptions!B15*0.85+Assumptions!B11*0.15),0) -> 34092 | I36: =H36 -> 34092 | J36: =ROUND(E36*Assumptions!B68,0) -> 10399 | K36: =ROUND(J36*Assumptions!B65,0) -> 832 | L36: =Assumptions!B70+IF(E36>Assumptions!B72,45,0) -> 76 | M36: =Assumptions!B76+Assumptions!B77 -> 35 | N36: =Assumptions!B81+Assumptions!B82+Assumptions!B87/12+Assumptions!B84 -> 92 | O36: =ROUND(I36*Assumptions!B85+E36*Assumptions!B86+W36*Assumptions!B85+ROUND(B36*Assumptions!B137*Assumptions!B138*Assumptions!B139,0)*Assumptions!B86,0) -> 2080 | P36: =K36+L36+M36+N36+O36+X36 -> 3747 | Q36: =I36-P36 -> 30345 | R36: =ROUND(B36*Assumptions!B51*Assumptions!B52,0) -> 34539 | S36: =I36+R36+W36 -> 72480 | T36: =IF(U36<P36*3,0,IF(U36<P36*6,ROUND((Q36+R36+W36)*0.75*Assumptions!B113,0),ROUND((Q36+R36+W36)*0.75*Assumptions!B114,0))) -> 19692 | U36: =U35+Q36+R36+W36 -> 501983 | V36: =IF(B36>=Assumptions!B107,"Signal 6",IF(B36>=Assumptions!B106,"Signal 5",IF(B36>=Assumptions!B105,"Signal 4",IF(B36>=Assumptions!B104,"Signal 3",IF(B36>=Assumptions!B103,"Signal 2",IF(B36>=Assumptions!B102,"Signal 1","Pre-Signal 1")))))) -> Signal 4 | W36: =ROUND(B36*Assumptions!B137*Assumptions!B138*Assumptions!B139*Assumptions!B136,0) -> 3849 | X36: =ROUND(B36*Assumptions!B137*Assumptions!B65,0) -> 632
A37: 32 | B37: =B36*(1+Assumptions!B35) -> 113484.33 | C37: =ROUND(B37*Assumptions!B25,0) -> 2270 | D37: =ROUND(B37*Assumptions!B24,0) -> 567 | E37: =E36+D37-F37 -> 3419 | F37: =ROUND(E36*Assumptions!B45,0) -> 119 | G37: =D37-F37 -> 448 | H37: =ROUND(E37*(Assumptions!B15*0.85+Assumptions!B11*0.15),0) -> 39233 | I37: =H37 -> 39233 | J37: =ROUND(E37*Assumptions!B68,0) -> 11967 | K37: =ROUND(J37*Assumptions!B65,0) -> 957 | L37: =Assumptions!B70+IF(E37>Assumptions!B72,45,0) -> 76 | M37: =Assumptions!B76+Assumptions!B77 -> 35 | N37: =Assumptions!B81+Assumptions!B82+Assumptions!B87/12+Assumptions!B84 -> 92 | O37: =ROUND(I37*Assumptions!B85+E37*Assumptions!B86+W37*Assumptions!B85+ROUND(B37*Assumptions!B137*Assumptions!B138*Assumptions!B139,0)*Assumptions!B86,0) -> 2394 | P37: =K37+L37+M37+N37+O37+X37 -> 4280 | Q37: =I37-P37 -> 34953 | R37: =ROUND(B37*Assumptions!B51*Assumptions!B52,0) -> 39720 | S37: =I37+R37+W37 -> 83379 | T37: =IF(U37<P37*3,0,IF(U37<P37*6,ROUND((Q37+R37+W37)*0.75*Assumptions!B113,0),ROUND((Q37+R37+W37)*0.75*Assumptions!B114,0))) -> 22662 | U37: =U36+Q37+R37+W37 -> 581082 | V37: =IF(B37>=Assumptions!B107,"Signal 6",IF(B37>=Assumptions!B106,"Signal 5",IF(B37>=Assumptions!B105,"Signal 4",IF(B37>=Assumptions!B104,"Signal 3",IF(B37>=Assumptions!B103,"Signal 2",IF(B37>=Assumptions!B102,"Signal 1","Pre-Signal 1")))))) -> Signal 5 | W37: =ROUND(B37*Assumptions!B137*Assumptions!B138*Assumptions!B139*Assumptions!B136,0) -> 4426 | X37: =ROUND(B37*Assumptions!B137*Assumptions!B65,0) -> 726
A38: 33 | B38: =B37*(1+Assumptions!B35) -> 130506.98 | C38: =ROUND(B38*Assumptions!B25,0) -> 2610 | D38: =ROUND(B38*Assumptions!B24,0) -> 653 | E38: =E37+D38-F38 -> 3935 | F38: =ROUND(E37*Assumptions!B45,0) -> 137 | G38: =D38-F38 -> 516 | H38: =ROUND(E38*(Assumptions!B15*0.85+Assumptions!B11*0.15),0) -> 45154 | I38: =H38 -> 45154 | J38: =ROUND(E38*Assumptions!B68,0) -> 13773 | K38: =ROUND(J38*Assumptions!B65,0) -> 1102 | L38: =Assumptions!B70+IF(E38>Assumptions!B72,45,0) -> 76 | M38: =Assumptions!B76+Assumptions!B77 -> 35 | N38: =Assumptions!B81+Assumptions!B82+Assumptions!B87/12+Assumptions!B84 -> 92 | O38: =ROUND(I38*Assumptions!B85+E38*Assumptions!B86+W38*Assumptions!B85+ROUND(B38*Assumptions!B137*Assumptions!B138*Assumptions!B139,0)*Assumptions!B86,0) -> 2755 | P38: =K38+L38+M38+N38+O38+X38 -> 4895 | Q38: =I38-P38 -> 40259 | R38: =ROUND(B38*Assumptions!B51*Assumptions!B52,0) -> 45677 | S38: =I38+R38+W38 -> 95921 | T38: =IF(U38<P38*3,0,IF(U38<P38*6,ROUND((Q38+R38+W38)*0.75*Assumptions!B113,0),ROUND((Q38+R38+W38)*0.75*Assumptions!B114,0))) -> 26079 | U38: =U37+Q38+R38+W38 -> 672108 | V38: =IF(B38>=Assumptions!B107,"Signal 6",IF(B38>=Assumptions!B106,"Signal 5",IF(B38>=Assumptions!B105,"Signal 4",IF(B38>=Assumptions!B104,"Signal 3",IF(B38>=Assumptions!B103,"Signal 2",IF(B38>=Assumptions!B102,"Signal 1","Pre-Signal 1")))))) -> Signal 5 | W38: =ROUND(B38*Assumptions!B137*Assumptions!B138*Assumptions!B139*Assumptions!B136,0) -> 5090 | X38: =ROUND(B38*Assumptions!B137*Assumptions!B65,0) -> 835
A39: 34 | B39: =B38*(1+Assumptions!B35) -> 150083.02 | C39: =ROUND(B39*Assumptions!B25,0) -> 3002 | D39: =ROUND(B39*Assumptions!B24,0) -> 750 | E39: =E38+D39-F39 -> 4528 | F39: =ROUND(E38*Assumptions!B45,0) -> 157 | G39: =D39-F39 -> 593 | H39: =ROUND(E39*(Assumptions!B15*0.85+Assumptions!B11*0.15),0) -> 51959 | I39: =H39 -> 51959 | J39: =ROUND(E39*Assumptions!B68,0) -> 15848 | K39: =ROUND(J39*Assumptions!B65,0) -> 1268 | L39: =Assumptions!B70+IF(E39>Assumptions!B72,45,0) -> 76 | M39: =Assumptions!B76+Assumptions!B77 -> 35 | N39: =Assumptions!B81+Assumptions!B82+Assumptions!B87/12+Assumptions!B84 -> 92 | O39: =ROUND(I39*Assumptions!B85+E39*Assumptions!B86+W39*Assumptions!B85+ROUND(B39*Assumptions!B137*Assumptions!B138*Assumptions!B139,0)*Assumptions!B86,0) -> 3170 | P39: =K39+L39+M39+N39+O39+X39 -> 5602 | Q39: =I39-P39 -> 46357 | R39: =ROUND(B39*Assumptions!B51*Assumptions!B52,0) -> 52529 | S39: =I39+R39+W39 -> 110341 | T39: =IF(U39<P39*3,0,IF(U39<P39*6,ROUND((Q39+R39+W39)*0.75*Assumptions!B113,0),ROUND((Q39+R39+W39)*0.75*Assumptions!B114,0))) -> 30008 | U39: =U38+Q39+R39+W39 -> 776847 | V39: =IF(B39>=Assumptions!B107,"Signal 6",IF(B39>=Assumptions!B106,"Signal 5",IF(B39>=Assumptions!B105,"Signal 4",IF(B39>=Assumptions!B104,"Signal 3",IF(B39>=Assumptions!B103,"Signal 2",IF(B39>=Assumptions!B102,"Signal 1","Pre-Signal 1")))))) -> Signal 5 | W39: =ROUND(B39*Assumptions!B137*Assumptions!B138*Assumptions!B139*Assumptions!B136,0) -> 5853 | X39: =ROUND(B39*Assumptions!B137*Assumptions!B65,0) -> 961
A40: 35 | B40: =B39*(1+Assumptions!B35) -> 172595.48 | C40: =ROUND(B40*Assumptions!B25,0) -> 3452 | D40: =ROUND(B40*Assumptions!B24,0) -> 863 | E40: =E39+D40-F40 -> 5210 | F40: =ROUND(E39*Assumptions!B45,0) -> 181 | G40: =D40-F40 -> 682 | H40: =ROUND(E40*(Assumptions!B15*0.85+Assumptions!B11*0.15),0) -> 59785 | I40: =H40 -> 59785 | J40: =ROUND(E40*Assumptions!B68,0) -> 18235 | K40: =ROUND(J40*Assumptions!B65,0) -> 1459 | L40: =Assumptions!B70+IF(E40>Assumptions!B72,45,0) -> 76 | M40: =Assumptions!B76+Assumptions!B77 -> 35 | N40: =Assumptions!B81+Assumptions!B82+Assumptions!B87/12+Assumptions!B84 -> 92 | O40: =ROUND(I40*Assumptions!B85+E40*Assumptions!B86+W40*Assumptions!B85+ROUND(B40*Assumptions!B137*Assumptions!B138*Assumptions!B139,0)*Assumptions!B86,0) -> 3647 | P40: =K40+L40+M40+N40+O40+X40 -> 6414 | Q40: =I40-P40 -> 53371 | R40: =ROUND(B40*Assumptions!B51*Assumptions!B52,0) -> 60408 | S40: =I40+R40+W40 -> 126924 | T40: =IF(U40<P40*3,0,IF(U40<P40*6,ROUND((Q40+R40+W40)*0.75*Assumptions!B113,0),ROUND((Q40+R40+W40)*0.75*Assumptions!B114,0))) -> 34526 | U40: =U39+Q40+R40+W40 -> 897357 | V40: =IF(B40>=Assumptions!B107,"Signal 6",IF(B40>=Assumptions!B106,"Signal 5",IF(B40>=Assumptions!B105,"Signal 4",IF(B40>=Assumptions!B104,"Signal 3",IF(B40>=Assumptions!B103,"Signal 2",IF(B40>=Assumptions!B102,"Signal 1","Pre-Signal 1")))))) -> Signal 5 | W40: =ROUND(B40*Assumptions!B137*Assumptions!B138*Assumptions!B139*Assumptions!B136,0) -> 6731 | X40: =ROUND(B40*Assumptions!B137*Assumptions!B65,0) -> 1105
A41: 36 | B41: =B40*(1+Assumptions!B35) -> 198484.8 | C41: =ROUND(B41*Assumptions!B25,0) -> 3970 | D41: =ROUND(B41*Assumptions!B24,0) -> 992 | E41: =E40+D41-F41 -> 5994 | F41: =ROUND(E40*Assumptions!B45,0) -> 208 | G41: =D41-F41 -> 784 | H41: =ROUND(E41*(Assumptions!B15*0.85+Assumptions!B11*0.15),0) -> 68781 | I41: =H41 -> 68781 | J41: =ROUND(E41*Assumptions!B68,0) -> 20979 | K41: =ROUND(J41*Assumptions!B65,0) -> 1678 | L41: =Assumptions!B70+IF(E41>Assumptions!B72,45,0) -> 76 | M41: =Assumptions!B76+Assumptions!B77 -> 35 | N41: =Assumptions!B81+Assumptions!B82+Assumptions!B87/12+Assumptions!B84 -> 92 | O41: =ROUND(I41*Assumptions!B85+E41*Assumptions!B86+W41*Assumptions!B85+ROUND(B41*Assumptions!B137*Assumptions!B138*Assumptions!B139,0)*Assumptions!B86,0) -> 4196 | P41: =K41+L41+M41+N41+O41+X41 -> 7347 | Q41: =I41-P41 -> 61434 | R41: =ROUND(B41*Assumptions!B51*Assumptions!B52,0) -> 69470 | S41: =I41+R41+W41 -> 145992 | T41: =IF(U41<P41*3,0,IF(U41<P41*6,ROUND((Q41+R41+W41)*0.75*Assumptions!B113,0),ROUND((Q41+R41+W41)*0.75*Assumptions!B114,0))) -> 39722 | U41: =U40+Q41+R41+W41 -> 1036002 | V41: =IF(B41>=Assumptions!B107,"Signal 6",IF(B41>=Assumptions!B106,"Signal 5",IF(B41>=Assumptions!B105,"Signal 4",IF(B41>=Assumptions!B104,"Signal 3",IF(B41>=Assumptions!B103,"Signal 2",IF(B41>=Assumptions!B102,"Signal 1","Pre-Signal 1")))))) -> Signal 6 | W41: =ROUND(B41*Assumptions!B137*Assumptions!B138*Assumptions!B139*Assumptions!B136,0) -> 7741 | X41: =ROUND(B41*Assumptions!B137*Assumptions!B65,0) -> 1270
A43: TOTALS | I43: =SUM(I6:I41) -> 513896 | P43: =SUM(P6:P41) -> 62418 | Q43: =SUM(Q6:Q41) -> 451478 | R43: =SUM(R6:R41) -> 525609 | S43: =SUM(S6:S41) -> 1098420 | T43: =SUM(T6:T41) -> 296871 | W43: =SUM(W6:W41) -> 58915 | X43: =SUM(X6:X41) -> 9668
A44: AVG MO | H44: =AVERAGE(H6:H41) -> 14274.889 | Q44: =AVERAGE(Q6:Q41) -> 12541.056
A45: M36 | B45: =B41 -> 198484.8 | E45: =E41 -> 5994 | H45: =H41 -> 68781 | S45: =S41 -> 145992 | T45: =T41 -> 39722 | U45: =U41 -> 1036002 | V45: =V41 -> Signal 6

Sheet VALIDATION
A1: VALIDATION CHECKS — ALL MUST SHOW PASS BEFORE RELEASE
A2: Run this sheet after every model update. Any FAIL blocks release.
A4: Check | B4: Expected | C4: Actual / Formula | D4: Status | E4: Notes
A5: Conservative conversion rate correct (B22) | B5: 0.15% | C5: =Assumptions!B22 -> 0.0015 | D5: =IF(Assumptions!B22=0.0015,"PASS","FAIL — should be 0.0015") -> PASS | E5: Core formula check. B22 = Conservative paid conv. NOT B25 (free signup).
A6: Expected conversion rate correct (B23) | B6: 0.25% | C6: =Assumptions!B23 -> 0.0025 | D6: =IF(Assumptions!B23=0.0025,"PASS","FAIL — should be 0.0025") -> PASS | E6: Core formula check.
A7: Optimistic conversion rate correct (B24) | B7: 0.50% | C7: =Assumptions!B24 -> 0.005 | D7: =IF(Assumptions!B24=0.005,"PASS","FAIL — should be 0.005") -> PASS | E7: Core formula check.
A8: Free signup rate > all paid conv rates | B8: B25 (2%) > B22, B23, B24 | C8: =Assumptions!B25 -> 0.02 | D8: =IF(AND(Assumptions!B25>Assumptions!B22,Assumptions!B25>Assumptions!B23,Assumptions!B25>Assumptions!B24),"PASS","FAIL — free rate should exceed paid conversion") -> PASS | E8: Sanity check: email capture always > paid conversion.
A9: Conservative traffic growth = 8% | B9: 8% | C9: =Assumptions!B33 -> 0.08 | D9: =IF(Assumptions!B33=0.08,"PASS","FAIL — should be 0.08") -> PASS | E9: Traffic model check.
A10: Expected traffic growth = 12% | B10: 12% | C10: =Assumptions!B34 -> 0.12 | D10: =IF(Assumptions!B34=0.12,"PASS","FAIL — should be 0.12") -> PASS | E10: Traffic model check.
A11: Optimistic traffic growth = 15% | B11: 15% | C11: =Assumptions!B35 -> 0.15 | D11: =IF(Assumptions!B35=0.15,"PASS","FAIL — should be 0.15 (15% MoM — realistic ceiling for 36-month solo SEO)") -> PASS | E11: Changed from 18% to 15%: 18% for 36 months = 490k visitors, not defensible for solo healthcare SEO.
A12: Conservative churn = 8% | B12: 8% | C12: =Assumptions!B43 -> 0.08 | D12: =IF(Assumptions!B43=0.08,"PASS","FAIL — should be 0.08") -> PASS | E12: Churn model check.
A13: Expected churn = 6% | B13: 6% | C13: =Assumptions!B44 -> 0.06 | D13: =IF(Assumptions!B44=0.06,"PASS","FAIL — should be 0.06") -> PASS | E13: Churn model check.
A14: Optimistic churn = 4% | B14: 4% | C14: =Assumptions!B45 -> 0.04 | D14: =IF(Assumptions!B45=0.04,"PASS","FAIL — should be 0.04") -> PASS | E14: Churn model check.
A15: Referral program starts Month 6 | B15: Month 6 | C15: =Assumptions!B50 -> 6 | D15: =IF(Assumptions!B50=6,"PASS","FAIL — should be 6") -> PASS | E15: Source: PMP v19 §3 — Signal 1 gate.
A16: Signal 1 gate = 10,000 visitors | B16: 10,000 | C16: =Assumptions!B102 -> 10000 | D16: =IF(Assumptions!B102=10000,"PASS","FAIL — should be 10000") -> PASS | E16: PMP v19 §3 clean gate number.
A17: Signal 2 gate = 25,000 visitors | B17: 25,000 | C17: =Assumptions!B103 -> 25000 | D17: =IF(Assumptions!B103=25000,"PASS","FAIL — should be 25000") -> PASS | E17: PMP v19 §3 clean gate number.
A18: Signal 3 gate = 40,000 visitors | B18: 40,000 | C18: =Assumptions!B104 -> 40000 | D18: =IF(Assumptions!B104=40000,"PASS","FAIL — should be 40000") -> PASS | E18: PMP v19 §3 clean gate number.
A19: Signal 4 gate = 65,000 visitors | B19: 65,000 | C19: =Assumptions!B105 -> 65000 | D19: =IF(Assumptions!B105=65000,"PASS","FAIL — should be 65000") -> PASS | E19: PMP v19 §3 clean gate number.
A20: Signal 5 gate = 110,000 visitors | B20: 110,000 | C20: =Assumptions!B106 -> 110000 | D20: =IF(Assumptions!B106=110000,"PASS","FAIL — should be 110000") -> PASS | E20: PMP v19 §3 clean gate number.
A21: Phase 1 withdrawal = 0% | B21: 0% | C21: =Assumptions!B112 -> 0 | D21: =IF(Assumptions!B112=0,"PASS","FAIL — Phase 1 must be 0%") -> PASS | E21: Non-negotiable. No Phase 1 withdrawals under any condition.
A22: Level 9 monthly PRW bar = 12 months | B22: 12 | C22: =Assumptions!B132 -> 12 | D22: =IF(Assumptions!B132=12,"PASS","FAIL — should be 12 per PMP v19 §9C") -> PASS | E22: PMP v19 §9C: Level 9 monthly trigger requires 12-month reserve.
A23: Conservative M36 reserve positive | B23: >$0 | C23: =Conservative!U41 -> 46391 | D23: =IF(Conservative!U41>0,"PASS","FAIL — Conservative scenario ends negative") -> PASS | E23: Business must be self-sustaining by M36 in Conservative scenario.
A24: Expected M36 reserve positive | B24: >$0 | C24: =Expected!U41 -> 249148 | D24: =IF(Expected!U41>0,"PASS","FAIL — Expected scenario ends negative") -> PASS | E24: Expected scenario reserve check.
A25: Conservative M36 subscribers > 0 | B25: >0 | C25: =Conservative!E41 -> 92 | D25: =IF(Conservative!E41>0,"PASS","FAIL — no subscribers in Conservative M36") -> PASS | E25: Basic growth sanity check.
A26: No Fibonacci gate numbers remain | B26: No 16180/26171/42325/68502 in gates | C26: Manual check | D26: =IF(AND(Assumptions!B103<>16180,Assumptions!B104<>26171,Assumptions!B105<>42325,Assumptions!B106<>68502),"PASS","FAIL — Fibonacci gates still present") -> PASS | E26: v12 used Fibonacci numbers. v13+ uses clean business milestones.
A27: Conservative M36 monthly cash-flow positive | B27: Gross Profit M36 > $0 | C27: =Conservative!Q41 -> 736 | D27: =IF(Conservative!Q41>0,"PASS","FAIL — Conservative not cash-flow positive by M36") -> PASS | E27: Monthly profit must be positive by M36. Conservative reserve may never fully recover.
A28: Denial Decoder API cost = $0 (static DB) | B28: Static lookup — no LLM | C28: Static lookup — no LLM | D28: =IF(Assumptions!B66=0.01,"PASS — note: B66 not used in API formula","PASS — static lookup confirmed") -> PASS — note: B66 not used in API formula | E28: Denial code lookups use static JSON/CSV. No Claude API call. Only letters hit the API.
A29: Optimistic M36 MRR > Conservative M36 MRR | B29: Optimistic > Conservative | C29: =Optimistic!H41&" vs "&Conservative!H41 -> 68781 vs 1056 | D29: =IF(Optimistic!H41>Conservative!H41,"PASS","FAIL — Optimistic should exceed Conservative") -> PASS | E29: Scenario ordering sanity check.
A30: Per-case price = $13 (B136) | B30: $13 | C30: =Assumptions!B136 -> 13 | D30: =IF(Assumptions!B136=13,"PASS","FAIL — per-case price should be 13") -> PASS | E30: v14 addition. Per-case price matches Standard tier — convergence architecture.
A31: Letter tool engagement rate = 8% (B137) | B31: 8% | C31: =Assumptions!B137 -> 0.08 | D31: =IF(Assumptions!B137=0.08,"PASS","FAIL — should be 0.08 per Pricing Strategy v2") -> PASS | E31: v14 addition. Free letter tool engagement. Does NOT include Denial Decoder.
A32: Per-case revenue positive in Expected M12 | B32: >$0 | C32: =Expected!W17 -> 135 | D32: =IF(Expected!W17>0,"PASS","FAIL — Expected M12 per-case should be positive") -> PASS | E32: v14 addition. Sanity check: per-case formula is generating revenue by Month 12.
A33: Total revenue > subscription revenue in Expected M36 | B33: S41 > I41 | C33: =Expected!S41&" vs "&Expected!I41 -> 29726 vs 9318 | D33: =IF(Expected!S41>Expected!I41,"PASS","FAIL — Total revenue should exceed sub revenue (referral + per-case add-ons)") -> PASS | E33: v14 addition. Confirms per-case + referral are additive to subscriptions.
A35: TOTAL CHECKS | B35: 29 checks | D35: =COUNTIF(D5:D34,"PASS")&" of 29 PASS" -> 28 of 29 PASS

Sheet SEO Model
A1: SEO Model — See PMP v19 for full specification
A2: This sheet carried forward from v13 — no changes in v14.

Sheet Agent Deployment
A1: Agent Deployment — See PMP v19 for full specification
A2: This sheet carried forward from v13 — no changes in v14.

Sheet Security Costs
A1: Security Costs — See PMP v19 for full specification
A2: This sheet carried forward from v13 — no changes in v14.
